Workbook

Sheet Escaneo Diario
A1: GRUPO QUINCE 22 | CONTROL DE INVENTARIOS Y CONTEO CÍCLICO DIARIO
A2: 📅 FECHA ACTUAL | C2: 📦 TOTAL ESCANEOS | E2: 🏷️ PRODUCTOS ÚNICOS | H2: 📊 TOTAL DE PIEZAS | J2: 🚀 ACCIÓN OPERATIVA
A3: =TODAY() | C3: =COUNTIF(C7:C1000, "<>") | E3: =IFERROR(__xludf.DUMMYFUNCTION("IFERROR(ROWS(UNIQUE(FILTER(D7:D1000, D7:D1000<>""""))), 0)"),0.0) | H3: =COUNTIF(C7:C1000, "<>") | J3: FINALIZAR ESCANEO
A4: Jornada en curso | C4: Registros capturados | E4: SKUs distintos | H4: Unidades contadas | J4: Asignar Folios y Archivar
A6: Fecha/Hora | B6: Ubicación/Rack | C6: UPC CODE | D6: SKU | E6: Marca | F6: Descripción | G6: División | H6: Categoría | I6: Talla / Size | J6: Alertas y Duplicados
D7: {=IF($C7="","",IFNA(_xlfn.XLOOKUP($C7,Productos!$A:$A,Productos!$E:$E,IFNA(_xlfn.XLOOKUP(TEXT($C7,"0"),Productos!$A:$A,Productos!$E:$E,IFNA(_xlfn.XLOOKUP(IFERROR(VALUE($C7),""),Productos!$A:$A,Productos!$E:$E,_xlfn.XLOOKUP($C7,Productos!$E:$E,Productos!$E:$E,"NO ENCONTRADO")),"NO ENCONTRADO")),"NO ENCONTRADO")),"NO ENCONTRADO"))} | E7: {=IF(OR($D7="",$D7="NO ENCONTRADO"),"",_xlfn.XLOOKUP($D7,Productos!$E:$E,Productos!$H:$H,""))} | F7: {=IF(OR($D7="",$D7="NO ENCONTRADO"),"",_xlfn.XLOOKUP($D7,Productos!$E:$E,Productos!$I:$I,""))} | G7: {=IF(OR($D7="",$D7="NO ENCONTRADO"),"",_xlfn.XLOOKUP($D7,Productos!$E:$E,Productos!$J:$J,""))} | H7: {=IF(OR($D7="",$D7="NO ENCONTRADO"),"",_xlfn.XLOOKUP($D7,Productos!$E:$E,Productos!$K:$K,""))} | I7: {=IF(OR($D7="",$D7="NO ENCONTRADO"),"",_xlfn.XLOOKUP($D7,Productos!$E:$E,Productos!$F:$F,""))} | J7: =IF($C7="","",IF($D7="NO ENCONTRADO",IF(COUNTIF($C$7:$C$1000,$C7)>1,"⚠️ No encontrado | Duplicado","⚠️ No encontrado"),IF(COUNTIF($C$7:$C$1000,$C7)>1,"⚠️ Duplicado","Verificado")))
D8: {=IF($C8="","",IFNA(_xlfn.XLOOKUP($C8,Productos!$A:$A,Productos!$E:$E,IFNA(_xlfn.XLOOKUP(TEXT($C8,"0"),Productos!$A:$A,Productos!$E:$E,IFNA(_xlfn.XLOOKUP(IFERROR(VALUE($C8),""),Productos!$A:$A,Productos!$E:$E,_xlfn.XLOOKUP($C8,Productos!$E:$E,Productos!$E:$E,"NO ENCONTRADO")),"NO ENCONTRADO")),"NO ENCONTRADO")),"NO ENCONTRADO"))} | E8: {=IF(OR($D8="",$D8="NO ENCONTRADO"),"",_xlfn.XLOOKUP($D8,Productos!$E:$E,Productos!$H:$H,""))} | F8: {=IF(OR($D8="",$D8="NO ENCONTRADO"),"",_xlfn.XLOOKUP($D8,Productos!$E:$E,Productos!$I:$I,""))} | G8: {=IF(OR($D8="",$D8="NO ENCONTRADO"),"",_xlfn.XLOOKUP($D8,Productos!$E:$E,Productos!$J:$J,""))} | H8: {=IF(OR($D8="",$D8="NO ENCONTRADO"),"",_xlfn.XLOOKUP($D8,Productos!$E:$E,Productos!$K:$K,""))} | I8: {=IF(OR($D8="",$D8="NO ENCONTRADO"),"",_xlfn.XLOOKUP($D8,Productos!$E:$E,Productos!$F:$F,""))} | J8: =IF($C8="","",IF($D8="NO ENCONTRADO",IF(COUNTIF($C$7:$C$1000,$C8)>1,"⚠️ No encontrado | Duplicado","⚠️ No encontrado"),IF(COUNTIF($C$7:$C$1000,$C8)>1,"⚠️ Duplicado","Verificado")))
D9: {=IF($C9="","",IFNA(_xlfn.XLOOKUP($C9,Productos!$A:$A,Productos!$E:$E,IFNA(_xlfn.XLOOKUP(TEXT($C9,"0"),Productos!$A:$A,Productos!$E:$E,IFNA(_xlfn.XLOOKUP(IFERROR(VALUE($C9),""),Productos!$A:$A,Productos!$E:$E,_xlfn.XLOOKUP($C9,Productos!$E:$E,Productos!$E:$E,"NO ENCONTRADO")),"NO ENCONTRADO")),"NO ENCONTRADO")),"NO ENCONTRADO"))} | E9: {=IF(OR($D9="",$D9="NO ENCONTRADO"),"",_xlfn.XLOOKUP($D9,Productos!$E:$E,Productos!$H:$H,""))} | F9: {=IF(OR($D9="",$D9="NO ENCONTRADO"),"",_xlfn.XLOOKUP($D9,Productos!$E:$E,Productos!$I:$I,""))} | G9: {=IF(OR($D9="",$D9="NO ENCONTRADO"),"",_xlfn.XLOOKUP($D9,Productos!$E:$E,Productos!$J:$J,""))} | H9: {=IF(OR($D9="",$D9="NO ENCONTRADO"),"",_xlfn.XLOOKUP($D9,Productos!$E:$E,Productos!$K:$K,""))} | I9: {=IF(OR($D9="",$D9="NO ENCONTRADO"),"",_xlfn.XLOOKUP($D9,Productos!$E:$E,Productos!$F:$F,""))} | J9: =IF($C9="","",IF($D9="NO ENCONTRADO",IF(COUNTIF($C$7:$C$1000,$C9)>1,"⚠️ No encontrado | Duplicado","⚠️ No encontrado"),IF(COUNTIF($C$7:$C$1000,$C9)>1,"⚠️ Duplicado","Verificado")))
D10: {=IF($C10="","",IFNA(_xlfn.XLOOKUP($C10,Productos!$A:$A,Productos!$E:$E,IFNA(_xlfn.XLOOKUP(TEXT($C10,"0"),Productos!$A:$A,Productos!$E:$E,IFNA(_xlfn.XLOOKUP(IFERROR(VALUE($C10),""),Productos!$A:$A,Productos!$E:$E,_xlfn.XLOOKUP($C10,Productos!$E:$E,Productos!$E:$E,"NO ENCONTRADO")),"NO ENCONTRADO")),"NO ENCONTRADO")),"NO ENCONTRADO"))} | E10: {=IF(OR($D10="",$D10="NO ENCONTRADO"),"",_xlfn.XLOOKUP($D10,Productos!$E:$E,Productos!$H:$H,""))} | F10: {=IF(OR($D10="",$D10="NO ENCONTRADO"),"",_xlfn.XLOOKUP($D10,Productos!$E:$E,Productos!$I:$I,""))} | G10: {=IF(OR($D10="",$D10="NO ENCONTRADO"),"",_xlfn.XLOOKUP($D10,Productos!$E:$E,Productos!$J:$J,""))} | H10: {=IF(OR($D10="",$D10="NO ENCONTRADO"),"",_xlfn.XLOOKUP($D10,Productos!$E:$E,Productos!$K:$K,""))} | I10: {=IF(OR($D10="",$D10="NO ENCONTRADO"),"",_xlfn.XLOOKUP($D10,Productos!$E:$E,Productos!$F:$F,""))} | J10: =IF($C10="","",IF($D10="NO ENCONTRADO",IF(COUNTIF($C$7:$C$1000,$C10)>1,"⚠️ No encontrado | Duplicado","⚠️ No encontrado"),IF(COUNTIF($C$7:$C$1000,$C10)>1,"⚠️ Duplicado","Verificado")))
D11: {=IF($C11="","",IFNA(_xlfn.XLOOKUP($C11,Productos!$A:$A,Productos!$E:$E,IFNA(_xlfn.XLOOKUP(TEXT($C11,"0"),Productos!$A:$A,Productos!$E:$E,IFNA(_xlfn.XLOOKUP(IFERROR(VALUE($C11),""),Productos!$A:$A,Productos!$E:$E,_xlfn.XLOOKUP($C11,Productos!$E:$E,Productos!$E:$E,"NO ENCONTRADO")),"NO ENCONTRADO")),"NO ENCONTRADO")),"NO ENCONTRADO"))} | E11: {=IF(OR($D11="",$D11="NO ENCONTRADO"),"",_xlfn.XLOOKUP($D11,Productos!$E:$E,Productos!$H:$H,""))} | F11: {=IF(OR($D11="",$D11="NO ENCONTRADO"),"",_xlfn.XLOOKUP($D11,Productos!$E:$E,Productos!$I:$I,""))} | G11: {=IF(OR($D11="",$D11="NO ENCONTRADO"),"",_xlfn.XLOOKUP($D11,Productos!$E:$E,Productos!$J:$J,""))} | H11: {=IF(OR($D11="",$D11="NO ENCONTRADO"),"",_xlfn.XLOOKUP($D11,Productos!$E:$E,Productos!$K:$K,""))} | I11: {=IF(OR($D11="",$D11="NO ENCONTRADO"),"",_xlfn.XLOOKUP($D11,Productos!$E:$E,Productos!$F:$F,""))} | J11: =IF($C11="","",IF($D11="NO ENCONTRADO",IF(COUNTIF($C$7:$C$1000,$C11)>1,"⚠️ No encontrado | Duplicado","⚠️ No encontrado"),IF(COUNTIF($C$7:$C$1000,$C11)>1,"⚠️ Duplicado","Verificado")))
D12: {=IF($C12="","",IFNA(_xlfn.XLOOKUP($C12,Productos!$A:$A,Productos!$E:$E,IFNA(_xlfn.XLOOKUP(TEXT($C12,"0"),Productos!$A:$A,Productos!$E:$E,IFNA(_xlfn.XLOOKUP(IFERROR(VALUE($C12),""),Productos!$A:$A,Productos!$E:$E,_xlfn.XLOOKUP($C12,Productos!$E:$E,Productos!$E:$E,"NO ENCONTRADO")),"NO ENCONTRADO")),"NO ENCONTRADO")),"NO ENCONTRADO"))} | E12: {=IF(OR($D12="",$D12="NO ENCONTRADO"),"",_xlfn.XLOOKUP($D12,Productos!$E:$E,Productos!$H:$H,""))} | F12: {=IF(OR($D12="",$D12="NO ENCONTRADO"),"",_xlfn.XLOOKUP($D12,Productos!$E:$E,Productos!$I:$I,""))} | G12: {=IF(OR($D12="",$D12="NO ENCONTRADO"),"",_xlfn.XLOOKUP($D12,Productos!$E:$E,Productos!$J:$J,""))} | H12: {=IF(OR($D12="",$D12="NO ENCONTRADO"),"",_xlfn.XLOOKUP($D12,Productos!$E:$E,Productos!$K:$K,""))} | I12: {=IF(OR($D12="",$D12="NO ENCONTRADO"),"",_xlfn.XLOOKUP($D12,Productos!$E:$E,Productos!$F:$F,""))} | J12: =IF($C12="","",IF($D12="NO ENCONTRADO",IF(COUNTIF($C$7:$C$1000,$C12)>1,"⚠️ No encontrado | Duplicado","⚠️ No encontrado"),IF(COUNTIF($C$7:$C$1000,$C12)>1,"⚠️ Duplicado","Verificado")))
D13: {=IF($C13="","",IFNA(_xlfn.XLOOKUP($C13,Productos!$A:$A,Productos!$E:$E,IFNA(_xlfn.XLOOKUP(TEXT($C13,"0"),Productos!$A:$A,Productos!$E:$E,IFNA(_xlfn.XLOOKUP(IFERROR(VALUE($C13),""),Productos!$A:$A,Productos!$E:$E,_xlfn.XLOOKUP($C13,Productos!$E:$E,Productos!$E:$E,"NO ENCONTRADO")),"NO ENCONTRADO")),"NO ENCONTRADO")),"NO ENCONTRADO"))} | E13: {=IF(OR($D13="",$D13="NO ENCONTRADO"),"",_xlfn.XLOOKUP($D13,Productos!$E:$E,Productos!$H:$H,""))} | F13: {=IF(OR($D13="",$D13="NO ENCONTRADO"),"",_xlfn.XLOOKUP($D13,Productos!$E:$E,Productos!$I:$I,""))} | G13: {=IF(OR($D13="",$D13="NO ENCONTRADO"),"",_xlfn.XLOOKUP($D13,Productos!$E:$E,Productos!$J:$J,""))} | H13: {=IF(OR($D13="",$D13="NO ENCONTRADO"),"",_xlfn.XLOOKUP($D13,Productos!$E:$E,Productos!$K:$K,""))} | I13: {=IF(OR($D13="",$D13="NO ENCONTRADO"),"",_xlfn.XLOOKUP($D13,Productos!$E:$E,Productos!$F:$F,""))} | J13: =IF($C13="","",IF($D13="NO ENCONTRADO",IF(COUNTIF($C$7:$C$1000,$C13)>1,"⚠️ No encontrado | Duplicado","⚠️ No encontrado"),IF(COUNTIF($C$7:$C$1000,$C13)>1,"⚠️ Duplicado","Verificado")))
D14: {=IF($C14="","",IFNA(_xlfn.XLOOKUP($C14,Productos!$A:$A,Productos!$E:$E,IFNA(_xlfn.XLOOKUP(TEXT($C14,"0"),Productos!$A:$A,Productos!$E:$E,IFNA(_xlfn.XLOOKUP(IFERROR(VALUE($C14),""),Productos!$A:$A,Productos!$E:$E,_xlfn.XLOOKUP($C14,Productos!$E:$E,Productos!$E:$E,"NO ENCONTRADO")),"NO ENCONTRADO")),"NO ENCONTRADO")),"NO ENCONTRADO"))} | E14: {=IF(OR($D14="",$D14="NO ENCONTRADO"),"",_xlfn.XLOOKUP($D14,Productos!$E:$E,Productos!$H:$H,""))} | F14: {=IF(OR($D14="",$D14="NO ENCONTRADO"),"",_xlfn.XLOOKUP($D14,Productos!$E:$E,Productos!$I:$I,""))} | G14: {=IF(OR($D14="",$D14="NO ENCONTRADO"),"",_xlfn.XLOOKUP($D14,Productos!$E:$E,Productos!$J:$J,""))} | H14: {=IF(OR($D14="",$D14="NO ENCONTRADO"),"",_xlfn.XLOOKUP($D14,Productos!$E:$E,Productos!$K:$K,""))} | I14: {=IF(OR($D14="",$D14="NO ENCONTRADO"),"",_xlfn.XLOOKUP($D14,Productos!$E:$E,Productos!$F:$F,""))} | J14: =IF($C14="","",IF($D14="NO ENCONTRADO",IF(COUNTIF($C$7:$C$1000,$C14)>1,"⚠️ No encontrado | Duplicado","⚠️ No encontrado"),IF(COUNTIF($C$7:$C$1000,$C14)>1,"⚠️ Duplicado","Verificado")))
D15: {=IF($C15="","",IFNA(_xlfn.XLOOKUP($C15,Productos!$A:$A,Productos!$E:$E,IFNA(_xlfn.XLOOKUP(TEXT($C15,"0"),Productos!$A:$A,Productos!$E:$E,IFNA(_xlfn.XLOOKUP(IFERROR(VALUE($C15),""),Productos!$A:$A,Productos!$E:$E,_xlfn.XLOOKUP($C15,Productos!$E:$E,Productos!$E:$E,"NO ENCONTRADO")),"NO ENCONTRADO")),"NO ENCONTRADO")),"NO ENCONTRADO"))} | E15: {=IF(OR($D15="",$D15="NO ENCONTRADO"),"",_xlfn.XLOOKUP($D15,Productos!$E:$E,Productos!$H:$H,""))} | F15: {=IF(OR($D15="",$D15="NO ENCONTRADO"),"",_xlfn.XLOOKUP($D15,Productos!$E:$E,Productos!$I:$I,""))} | G15: {=IF(OR($D15="",$D15="NO ENCONTRADO"),"",_xlfn.XLOOKUP($D15,Productos!$E:$E,Productos!$J:$J,""))} | H15: {=IF(OR($D15="",$D15="NO ENCONTRADO"),"",_xlfn.XLOOKUP($D15,Productos!$E:$E,Productos!$K:$K,""))} | I15: {=IF(OR($D15="",$D15="NO ENCONTRADO"),"",_xlfn.XLOOKUP($D15,Productos!$E:$E,Productos!$F:$F,""))} | J15: =IF($C15="","",IF($D15="NO ENCONTRADO",IF(COUNTIF($C$7:$C$1000,$C15)>1,"⚠️ No encontrado | Duplicado","⚠️ No encontrado"),IF(COUNTIF($C$7:$C$1000,$C15)>1,"⚠️ Duplicado","Verificado")))
D16: {=IF($C16="","",IFNA(_xlfn.XLOOKUP($C16,Productos!$A:$A,Productos!$E:$E,IFNA(_xlfn.XLOOKUP(TEXT($C16,"0"),Productos!$A:$A,Productos!$E:$E,IFNA(_xlfn.XLOOKUP(IFERROR(VALUE($C16),""),Productos!$A:$A,Productos!$E:$E,_xlfn.XLOOKUP($C16,Productos!$E:$E,Productos!$E:$E,"NO ENCONTRADO")),"NO ENCONTRADO")),"NO ENCONTRADO")),"NO ENCONTRADO"))} | E16: {=IF(OR($D16="",$D16="NO ENCONTRADO"),"",_xlfn.XLOOKUP($D16,Productos!$E:$E,Productos!$H:$H,""))} | F16: {=IF(OR($D16="",$D16="NO ENCONTRADO"),"",_xlfn.XLOOKUP($D16,Productos!$E:$E,Productos!$I:$I,""))} | G16: {=IF(OR($D16="",$D16="NO ENCONTRADO"),"",_xlfn.XLOOKUP($D16,Productos!$E:$E,Productos!$J:$J,""))} | H16: {=IF(OR($D16="",$D16="NO ENCONTRADO"),"",_xlfn.XLOOKUP($D16,Productos!$E:$E,Productos!$K:$K,""))} | I16: {=IF(OR($D16="",$D16="NO ENCONTRADO"),"",_xlfn.XLOOKUP($D16,Productos!$E:$E,Productos!$F:$F,""))} | J16: =IF($C16="","",IF($D16="NO ENCONTRADO",IF(COUNTIF($C$7:$C$1000,$C16)>1,"⚠️ No encontrado | Duplicado","⚠️ No encontrado"),IF(COUNTIF($C$7:$C$1000,$C16)>1,"⚠️ Duplicado","Verificado")))
D17: {=IF($C17="","",IFNA(_xlfn.XLOOKUP($C17,Productos!$A:$A,Productos!$E:$E,IFNA(_xlfn.XLOOKUP(TEXT($C17,"0"),Productos!$A:$A,Productos!$E:$E,IFNA(_xlfn.XLOOKUP(IFERROR(VALUE($C17),""),Productos!$A:$A,Productos!$E:$E,_xlfn.XLOOKUP($C17,Productos!$E:$E,Productos!$E:$E,"NO ENCONTRADO")),"NO ENCONTRADO")),"NO ENCONTRADO")),"NO ENCONTRADO"))} | E17: {=IF(OR($D17="",$D17="NO ENCONTRADO"),"",_xlfn.XLOOKUP($D17,Productos!$E:$E,Productos!$H:$H,""))} | F17: {=IF(OR($D17="",$D17="NO ENCONTRADO"),"",_xlfn.XLOOKUP($D17,Productos!$E:$E,Productos!$I:$I,""))} | G17: {=IF(OR($D17="",$D17="NO ENCONTRADO"),"",_xlfn.XLOOKUP($D17,Productos!$E:$E,Productos!$J:$J,""))} | H17: {=IF(OR($D17="",$D17="NO ENCONTRADO"),"",_xlfn.XLOOKUP($D17,Productos!$E:$E,Productos!$K:$K,""))} | I17: {=IF(OR($D17="",$D17="NO ENCONTRADO"),"",_xlfn.XLOOKUP($D17,Productos!$E:$E,Productos!$F:$F,""))} | J17: =IF($C17="","",IF($D17="NO ENCONTRADO",IF(COUNTIF($C$7:$C$1000,$C17)>1,"⚠️ No encontrado | Duplicado","⚠️ No encontrado"),IF(COUNTIF($C$7:$C$1000,$C17)>1,"⚠️ Duplicado","Verificado")))
D18: {=IF($C18="","",IFNA(_xlfn.XLOOKUP($C18,Productos!$A:$A,Productos!$E:$E,IFNA(_xlfn.XLOOKUP(TEXT($C18,"0"),Productos!$A:$A,Productos!$E:$E,IFNA(_xlfn.XLOOKUP(IFERROR(VALUE($C18),""),Productos!$A:$A,Productos!$E:$E,_xlfn.XLOOKUP($C18,Productos!$E:$E,Productos!$E:$E,"NO ENCONTRADO")),"NO ENCONTRADO")),"NO ENCONTRADO")),"NO ENCONTRADO"))} | E18: {=IF(OR($D18="",$D18="NO ENCONTRADO"),"",_xlfn.XLOOKUP($D18,Productos!$E:$E,Productos!$H:$H,""))} | F18: {=IF(OR($D18="",$D18="NO ENCONTRADO"),"",_xlfn.XLOOKUP($D18,Productos!$E:$E,Productos!$I:$I,""))} | G18: {=IF(OR($D18="",$D18="NO ENCONTRADO"),"",_xlfn.XLOOKUP($D18,Productos!$E:$E,Productos!$J:$J,""))} | H18: {=IF(OR($D18="",$D18="NO ENCONTRADO"),"",_xlfn.XLOOKUP($D18,Productos!$E:$E,Productos!$K:$K,""))} | I18: {=IF(OR($D18="",$D18="NO ENCONTRADO"),"",_xlfn.XLOOKUP($D18,Productos!$E:$E,Productos!$F:$F,""))} | J18: =IF($C18="","",IF($D18="NO ENCONTRADO",IF(COUNTIF($C$7:$C$1000,$C18)>1,"⚠️ No encontrado | Duplicado","⚠️ No encontrado"),IF(COUNTIF($C$7:$C$1000,$C18)>1,"⚠️ Duplicado","Verificado")))
... D1000: {=IF($C1000="","",IFNA(_xlfn.XLOOKUP($C1000,Productos!$A:$A,Productos!$E:$E,IFNA(_xlfn.XLOOKUP(TEXT($C1000,"0"),Productos!$A:$A,Productos!$E:$E,IFNA(_xlfn.XLOOKUP(IFERROR(VALUE($C1000),""),Productos!$A:$A,Productos!$E:$E,_xlfn.XLOOKUP($C1000,Productos!$E:$E,Productos!$E:$E,"NO ENCONTRADO")),"NO ENCONTRADO")),"NO ENCONTRADO")),"NO ENCONTRADO"))} | E1000: {=IF(OR($D1000="",$D1000="NO ENCONTRADO"),"",_xlfn.XLOOKUP($D1000,Productos!$E:$E,Productos!$H:$H,""))} | F1000: {=IF(OR($D1000="",$D1000="NO ENCONTRADO"),"",_xlfn.XLOOKUP($D1000,Productos!$E:$E,Productos!$I:$I,""))} | G1000: {=IF(OR($D1000="",$D1000="NO ENCONTRADO"),"",_xlfn.XLOOKUP($D1000,Productos!$E:$E,Productos!$J:$J,""))} | H1000: {=IF(OR($D1000="",$D1000="NO ENCONTRADO"),"",_xlfn.XLOOKUP($D1000,Productos!$E:$E,Productos!$K:$K,""))} | I1000: {=IF(OR($D1000="",$D1000="NO ENCONTRADO"),"",_xlfn.XLOOKUP($D1000,Productos!$E:$E,Productos!$F:$F,""))} | J1000: =IF($C1000="","",IF($D1000="NO ENCONTRADO",IF(COUNTIF($C$7:$C$1000,$C1000)>1,"⚠️ No encontrado | Duplicado","⚠️ No encontrado"),IF(COUNTIF($C$7:$C$1000,$C1000)>1,"⚠️ Duplicado","Verificado")))

Sheet Historial de Escaneos
A1: HISTORIAL Y BITÁCORA CONSOLIDADA DE CONTEOS CÍCLICOS - GRUPO QUINCE 22
A2: Registro histórico de auditorías, folios automáticos por ubicación y trazabilidad consolidada de marcas e inventario físico
A3: Fecha de Conteo | B3: Hora Registro | C3: Folio de Escaneo | D3: Ubicación / Rack | E3: Marcas Escaneadas (Todas) | F3: Total Piezas | G3: Auditor / Responsable | H3: Dictamen de Auditoría | I3: Alertas de Modificación / Incidencias
A4: 46274 | B4: 0.44097222 | C4: ESC-20260909-J1-L1-01 | D4: J1-L1-01 | E4: =IFERROR(__xludf.DUMMYFUNCTION("IFERROR(TEXTJOIN("", "", TRUE, UNIQUE(FILTER(Table_2[Marca], Table_2[Folio de Escaneo]=C4))), """")"),"Stetson") | F4: =SUMIFS(Table_2[Piezas Contadas],Table_2[Folio de Escaneo],C4) | H4: Revisión Requerida | I4: 2 pzs con UPC inexistente en Productos

Sheet Escaneos
A1: Folio de Escaneo | B1: Fecha / Hora | C1: Ubicación / Rack | D1: UPC CODE | E1: SKU | F1: Marca | G1: Descripción | H1: Categoría | I1: Talla / Size | J1: Piezas Contadas | K1: Auditor / Responsable | L1: Estado de Conteo | M1: Detalle de Modificaciones / Alertas
A2: ESC-20260909-J1-L1-01 | B2: 2026-09-09 10:45:00 | C2: J1-L1-01 | D2: 7506499570848 | F2: Stetson | G2: Camisa Stetson Vintage Range Sable Crest | H2: Camisas | I2: 2XL | J2: 2 | L2: Revisión Requerida | M2: UPC no existe en Productos

Sheet Configuración
A1: CONFIGURACIÓN DEL SISTEMA Y CATÁLOGOS MAESTROS - GRUPO QUINCE 22
A2: Catálogos oficiales para validación de datos y listas desplegables del conteo cíclico diario
A3: Ubicaciones / Racks | B3: Marcas | C3: Categorías | D3: Tallas / Sizes | E3: Auditores / Operadores | F3: Estado de Conteo | H3: Ubicaciones NetSuite (Hoja a Revisar) | I3: SKUs con stock | J3: Piezas en sistema
A4: Pasillo A - Racks Principales | B4: 1522 Original | C4: Playeras | D4: XS | E4: Jesús Fregoso | F4: Verificado | H4: Almacenes G1522 | I4: {=_xlfn.XLOOKUP($H4,Criterios!$G$6:$G$200,Criterios!I$6:I$200,"")} | J4: {=_xlfn.XLOOKUP($H4,Criterios!$G$6:$G$200,Criterios!J$6:J$200,"")}
A5: Pasillo B - Estantería Media | B5: Urban Trend | C5: Pantalones | D5: S | E5: Carlos Morales | F5: Con Discrepancia | H5: AMAZON | I5: {=_xlfn.XLOOKUP($H5,Criterios!$G$6:$G$200,Criterios!I$6:I$200,"")} | J5: {=_xlfn.XLOOKUP($H5,Criterios!$G$6:$G$200,Criterios!J$6:J$200,"")}
A6: Pasillo C - Calzado y Confección | B6: Denim Co. | C6: Sudaderas | D6: M | E6: Andrea Valenzuela | F6: Pendiente | H6: ARIAT CHIHUAHUA | I6: {=_xlfn.XLOOKUP($H6,Criterios!$G$6:$G$200,Criterios!I$6:I$200,"")} | J6: {=_xlfn.XLOOKUP($H6,Criterios!$G$6:$G$200,Criterios!J$6:J$200,"")}
A7: Pasillo D - Accesorios | B7: Active Wear | C7: Chamarras | D7: L | E7: Luis Fernández | F7: Revisión Requerida | H7: ARIAT OUTLET GDL | I7: {=_xlfn.XLOOKUP($H7,Criterios!$G$6:$G$200,Criterios!I$6:I$200,"")} | J7: {=_xlfn.XLOOKUP($H7,Criterios!$G$6:$G$200,Criterios!J$6:J$200,"")}
A8: Pasillo E - Devoluciones | B8: Casual Basics | C8: Gorras | D8: XL | E8: Mariana Garza | H8: ARIAT PLAZA SAN LUIS | I8: {=_xlfn.XLOOKUP($H8,Criterios!$G$6:$G$200,Criterios!I$6:I$200,"")} | J8: {=_xlfn.XLOOKUP($H8,Criterios!$G$6:$G$200,Criterios!J$6:J$200,"")}
A9: Bodega Central - Tarimas | B9: Signature 1522 | C9: Camisas | D9: XXL | E9: Roberto Méndez | H9: ARIAT SAN NICOLAS NL | I9: {=_xlfn.XLOOKUP($H9,Criterios!$G$6:$G$200,Criterios!I$6:I$200,"")} | J9: {=_xlfn.XLOOKUP($H9,Criterios!$G$6:$G$200,Criterios!J$6:J$200,"")}
A10: Zona de Picking 1 | B10: Premium Line | C10: Calzado | D10: 28x32 | E10: Sofía Castro | H10: B25 CEDIS | I10: {=_xlfn.XLOOKUP($H10,Criterios!$G$6:$G$200,Criterios!I$6:I$200,"")} | J10: {=_xlfn.XLOOKUP($H10,Criterios!$G$6:$G$200,Criterios!J$6:J$200,"")}
A11: Zona de Recepción | B11: Vintage Republic | C11: Accesorios | D11: 30x32 | E11: Miguel Ángel Ruiz | H11: B25 STETSON.MX | I11: {=_xlfn.XLOOKUP($H11,Criterios!$G$6:$G$200,Criterios!I$6:I$200,"")} | J11: {=_xlfn.XLOOKUP($H11,Criterios!$G$6:$G$200,Criterios!J$6:J$200,"")}
A12: Almacén General - Cuarentena | B12: Essentials | C12: Ropa Deportiva | D12: 32x32 | E12: Diana Navarro | H12: B25 WB MERCADO LIBRE | I12: {=_xlfn.XLOOKUP($H12,Criterios!$G$6:$G$200,Criterios!I$6:I$200,"")} | J12: {=_xlfn.XLOOKUP($H12,Criterios!$G$6:$G$200,Criterios!J$6:J$200,"")}
A13: Mesa de Empaque | B13: Colección Especial | C13: Ropa Interior | D13: 34x32 | E13: Pedro Gómez | H13: B25 WESTERN BROTHERS.MX | I13: {=_xlfn.XLOOKUP($H13,Criterios!$G$6:$G$200,Criterios!I$6:I$200,"")} | J13: {=_xlfn.XLOOKUP($H13,Criterios!$G$6:$G$200,Criterios!J$6:J$200,"")}
A14: Área de Devoluciones | B14: Edición Limitada | C14: Calcetería | D14: UNITALLA | E14: Laura Sánchez | H14: CAPSLAB Warehouse | I14: {=_xlfn.XLOOKUP($H14,Criterios!$G$6:$G$200,Criterios!I$6:I$200,"")} | J14: {=_xlfn.XLOOKUP($H14,Criterios!$G$6:$G$200,Criterios!J$6:J$200,"")}
A15: J1-L1-01 | B15: Stetson | C15: Jeans | D15: 29 x 32 | H15: CL Muestras | I15: {=_xlfn.XLOOKUP($H15,Criterios!$G$6:$G$200,Criterios!I$6:I$200,"")} | J15: {=_xlfn.XLOOKUP($H15,Criterios!$G$6:$G$200,Criterios!J$6:J$200,"")}
A16: Almacenes G1522 | B16: Ariat | C16: Denim | D16: 30 x 32 | H16: CL POS | I16: {=_xlfn.XLOOKUP($H16,Criterios!$G$6:$G$200,Criterios!I$6:I$200,"")} | J16: {=_xlfn.XLOOKUP($H16,Criterios!$G$6:$G$200,Criterios!J$6:J$200,"")}
A17: AMAZON | B17: CAPSLAB | C17: Ropa | D17: 31 x 32 | H17: CONSIGNA REFLO | I17: {=_xlfn.XLOOKUP($H17,Criterios!$G$6:$G$200,Criterios!I$6:I$200,"")} | J17: {=_xlfn.XLOOKUP($H17,Criterios!$G$6:$G$200,Criterios!J$6:J$200,"")}
A18: ARIAT CHIHUAHUA | B18: Denver | D18: 32 x 34 | H18: CONSIGNAS | I18: {=_xlfn.XLOOKUP($H18,Criterios!$G$6:$G$200,Criterios!I$6:I$200,"")} | J18: {=_xlfn.XLOOKUP($H18,Criterios!$G$6:$G$200,Criterios!J$6:J$200,"")}
A19: ARIAT OUTLET GDL | B19: Generico | D19: 33 x 32 | H19: DEPARTAMENTAL | I19: {=_xlfn.XLOOKUP($H19,Criterios!$G$6:$G$200,Criterios!I$6:I$200,"")} | J19: {=_xlfn.XLOOKUP($H19,Criterios!$G$6:$G$200,Criterios!J$6:J$200,"")}
A20: ARIAT PLAZA SAN LUIS | B20: Happy Socks | D20: 34 x 34 | H20: ECOMMERCE | I20: {=_xlfn.XLOOKUP($H20,Criterios!$G$6:$G$200,Criterios!I$6:I$200,"")} | J20: {=_xlfn.XLOOKUP($H20,Criterios!$G$6:$G$200,Criterios!J$6:J$200,"")}
A21: ARIAT SAN NICOLAS NL | B21: Montana West | D21: 34 x 36 | H21: ENGLISH REP | I21: {=_xlfn.XLOOKUP($H21,Criterios!$G$6:$G$200,Criterios!I$6:I$200,"")} | J21: {=_xlfn.XLOOKUP($H21,Criterios!$G$6:$G$200,Criterios!J$6:J$200,"")}
A22: B25 CEDIS | B22: REFLO | D22: 36 x 32 | H22: EVENTOS (CONSIGNA) | I22: {=_xlfn.XLOOKUP($H22,Criterios!$G$6:$G$200,Criterios!I$6:I$200,"")} | J22: {=_xlfn.XLOOKUP($H22,Criterios!$G$6:$G$200,Criterios!J$6:J$200,"")}
A23: B25 STETSON.MX | B23: Ranch & Corral | D23: 36 x 34 | H23: Fixtures & MKT | I23: {=_xlfn.XLOOKUP($H23,Criterios!$G$6:$G$200,Criterios!I$6:I$200,"")} | J23: {=_xlfn.XLOOKUP($H23,Criterios!$G$6:$G$200,Criterios!J$6:J$200,"")}
A24: B25 WB MERCADO LIBRE | B24: Tru Western | D24: 38 x 32 | H24: FULL MELI | I24: {=_xlfn.XLOOKUP($H24,Criterios!$G$6:$G$200,Criterios!I$6:I$200,"")} | J24: {=_xlfn.XLOOKUP($H24,Criterios!$G$6:$G$200,Criterios!J$6:J$200,"")}
A25: B25 WESTERN BROTHERS.MX | B25: Willow Lane | D25: 32 x 32 | H25: G1522 Defectos | I25: {=_xlfn.XLOOKUP($H25,Criterios!$G$6:$G$200,Criterios!I$6:I$200,"")} | J25: {=_xlfn.XLOOKUP($H25,Criterios!$G$6:$G$200,Criterios!J$6:J$200,"")}
A26: CAPSLAB Warehouse | B26: Wrangler | D26: 34 x 32 | H26: G1522 Lost | I26: {=_xlfn.XLOOKUP($H26,Criterios!$G$6:$G$200,Criterios!I$6:I$200,"")} | J26: {=_xlfn.XLOOKUP($H26,Criterios!$G$6:$G$200,Criterios!J$6:J$200,"")}
A27: CL Muestras | H27: G1522 QA Hold | I27: {=_xlfn.XLOOKUP($H27,Criterios!$G$6:$G$200,Criterios!I$6:I$200,"")} | J27: {=_xlfn.XLOOKUP($H27,Criterios!$G$6:$G$200,Criterios!J$6:J$200,"")}
A28: CL POS | H28: GENERAL | I28: {=_xlfn.XLOOKUP($H28,Criterios!$G$6:$G$200,Criterios!I$6:I$200,"")} | J28: {=_xlfn.XLOOKUP($H28,Criterios!$G$6:$G$200,Criterios!J$6:J$200,"")}
A29: CONSIGNA REFLO | H29: HAPPY SOCKS | I29: {=_xlfn.XLOOKUP($H29,Criterios!$G$6:$G$200,Criterios!I$6:I$200,"")} | J29: {=_xlfn.XLOOKUP($H29,Criterios!$G$6:$G$200,Criterios!J$6:J$200,"")}
A30: CONSIGNAS | H30: HS MERCADO LIBRE | I30: {=_xlfn.XLOOKUP($H30,Criterios!$G$6:$G$200,Criterios!I$6:I$200,"")} | J30: {=_xlfn.XLOOKUP($H30,Criterios!$G$6:$G$200,Criterios!J$6:J$200,"")}
A31: DEPARTAMENTAL | H31: KEY ACCOUNTS | I31: {=_xlfn.XLOOKUP($H31,Criterios!$G$6:$G$200,Criterios!I$6:I$200,"")} | J31: {=_xlfn.XLOOKUP($H31,Criterios!$G$6:$G$200,Criterios!J$6:J$200,"")}
A32: ECOMMERCE | H32: LIVERPOOL MKP | I32: {=_xlfn.XLOOKUP($H32,Criterios!$G$6:$G$200,Criterios!I$6:I$200,"")} | J32: {=_xlfn.XLOOKUP($H32,Criterios!$G$6:$G$200,Criterios!J$6:J$200,"")}
A33: ENGLISH REP | H33: Mercado libre | I33: {=_xlfn.XLOOKUP($H33,Criterios!$G$6:$G$200,Criterios!I$6:I$200,"")} | J33: {=_xlfn.XLOOKUP($H33,Criterios!$G$6:$G$200,Criterios!J$6:J$200,"")}
A34: EVENTOS (CONSIGNA) | H34: MUESTRAS & EXPO | I34: {=_xlfn.XLOOKUP($H34,Criterios!$G$6:$G$200,Criterios!I$6:I$200,"")} | J34: {=_xlfn.XLOOKUP($H34,Criterios!$G$6:$G$200,Criterios!J$6:J$200,"")}
A35: Fixtures & MKT | H35: MUESTRAS REFLO | I35: {=_xlfn.XLOOKUP($H35,Criterios!$G$6:$G$200,Criterios!I$6:I$200,"")} | J35: {=_xlfn.XLOOKUP($H35,Criterios!$G$6:$G$200,Criterios!J$6:J$200,"")}
A36: FULL MELI | H36: Nogales Store | I36: {=_xlfn.XLOOKUP($H36,Criterios!$G$6:$G$200,Criterios!I$6:I$200,"")} | J36: {=_xlfn.XLOOKUP($H36,Criterios!$G$6:$G$200,Criterios!J$6:J$200,"")}
A37: G1522 Defectos | H37: Plaza del Sol Store | I37: {=_xlfn.XLOOKUP($H37,Criterios!$G$6:$G$200,Criterios!I$6:I$200,"")} | J37: {=_xlfn.XLOOKUP($H37,Criterios!$G$6:$G$200,Criterios!J$6:J$200,"")}
A38: G1522 Lost | H38: POTRILLOS | I38: {=_xlfn.XLOOKUP($H38,Criterios!$G$6:$G$200,Criterios!I$6:I$200,"")} | J38: {=_xlfn.XLOOKUP($H38,Criterios!$G$6:$G$200,Criterios!J$6:J$200,"")}
... A52: PUNTO DE VENTA | H52: ZONA SUR | I52: {=_xlfn.XLOOKUP($H52,Criterios!$G$6:$G$200,Criterios!I$6:I$200,"")} | J52: {=_xlfn.XLOOKUP($H52,Criterios!$G$6:$G$200,Criterios!J$6:J$200,"")}
A53: Punto de venta HS
A54: REFLO ALMACEN
A55: STETSON AMERICAS
A56: The Hat Club
A57: VENTAS CAMPAÑA
A58: WB FORUM TLAQUEPAQUE
A59: WB OUTLET LERMA
A60: Web
A61: WEB
A62: ZONA NORTE
A63: ZONA POS
A64: ZONA SUR

Sheet Productos
A1: Código de barras | B1: Identificador interno | C1: Marca principal | D1: WB N.º de estilo | E1: WB SKU | F1: WB Talla | G1: WB Talla de EE. UU. | H1: WB Marca | I1: WB Descripcion | J1: WB División | K1: WB Categoría | L1: WB Género | M1: WB Licencia | N1: WB Temporada | O1: WB Ciclo de vida | P1: WB Color | Q1: WB Fit | R1: WB Silueta | S1: WB Composición | T1: WB Descripción larga | U1: WB País de origen | V1: Unidad | W1: SAT Clave de producto | X1: Enlace de imagen | Y1: Precio de compra | Z1: Precio de venta | AA1: Estatus de Validación | AB1: Detalle de Discrepancias | AC1: 🔍 Panel de Duplicados | AD1: Stock Sistema NetSuite | AE1: Ubicaciones con stock (NetSuite) | AF1: Disponible NetSuite | AG1: Origen del registro | AH1: Notas de enriquecimiento / revisión | AI1: ¿Alguna ubicación en negativo? | AJ1: Ubicaciones con existencia negativa | AK1: Fuentes de consulta | AL1: Precio compra vigente | AM1: Precio venta vigente | AN1: 📍 Ubicación en plataformas (Plataforma + Marca) | AO1: Stock Shopify Stetson México | AP1: Stock Shopify Western Brothers | AQ1: Stock Odoo Universal Unique Brands | AR1: Ubicaciones con stock (plataformas)
A2: 7506499570833 | B2: 108359 | C2: Multimarca | D2: 01-TDAG012-0010 | E2: 01-TDAG012-0010-M | F2: M | G2: M | H2: Denver | I2: Playera Denver caballero blanco | J2: Ropa | K2: Playeras | L2: Hombre | M2: Denver | N2: SS26 | O2: Seasonal | P2: Blanco | Q2: Regular | S2: 100% Algodón | T2: Playera Denver caballero blanco Regular | U2: México | V2: PZS | W2: 53101602 | Y2: 329 | Z2: 559.48276 | AA2: =IF(AND(A2="", B2="", E2=""), "", IF(AB2="", "Válido", IF((LEN(AB2)-LEN(SUBSTITUTE(AB2,"; ","")))/2+1>(LEN(AB2)-LEN(SUBSTITUTE(AB2,"[Aviso]","")))/7, "Con Incidencias", "Válido"))) | AB2: =IF(AND(A2="", B2="", E2=""), "", TEXTJOIN("; ", TRUE, IF(OR(TRIM(A2&"")="", ISNUMBER(SEARCH("FALTA", A2))), "UPC faltante/inválido", ""), IF(AND(A2<>"", IFERROR(_xlfn.XMATCH(A2,$A$2:$A$204,0,1)<>_xlfn.XMATCH(A2,$A$2:$A$204,0,-1),FALSE)), "Código de barras duplicado", ""), IF(AND(E2<>"", COUNTIF($E$2:$E$204, E2)>1), "SKU duplicado", ""), IF(OR(J2="", J2=""), "[Aviso] División no capturada ()", IF(ISNA(MATCH(J2, Criterios!$A$123:$A$126, 0)), "División no válida", "")), IF(OR(K2="", K2=""), "[Aviso] Categoría no capturada ()", IF(ISNA(MATCH(K2, Criterios!$A$81:$A$120, 0)), "Categoría no válida", IF(AND(J2<>"", J2<>"", J2<>VLOOKUP(K2, Criterios!$A$81:$B$120, 2, FALSE)), "División no coincide con Categoría", ""))), IF(OR(L2="", L2=""), "[Aviso] Género no capturado ()", IF(ISNA(MATCH(L2, Criterios!$B$123:$B$127, 0)), "Género no válido", "")), IF(OR(N2="", N2=""), "[Aviso] Temporada no capturada ()", IF(ISNA(MATCH(N2, Criterios!$C$123:$C$128, 0)), "Temporada no válida", "")), IF(OR(O2="", O2=""), "[Aviso] Ciclo de vida no capturado ()", IF(ISNA(MATCH(O2, Criterios!$D$123:$D$124, 0)), "Ciclo de vida no válido", "")))) | AD2: 0 | AF2: 0 | AG2: Nuevo – NetSuite sin existencia | AH2: Revisión 29/09/2026: Campos sin respaldo: X; Auditoría NetSuite 30/09/2026: llenado desde NetSuite [P,V,Y,T] | 01/10/2026: complementado desde Shopify Western Brothers (match por código de barras): WB Silueta | Homologación G1522 06/10/2026: Validación G1522: Dígito de control del código de barras inválido | AI2: No | AK2: ProductosCatalogoEstandar907.xlsx: fila 6236 [N,O,Q,S,U,Y]; G1522_Extraccion_Articulos_NetSuite_2026-09-30.xlsx: fila 56518 [P,V,Y,T] | Shopify WB: producto 8569955352761 / variante 47621314445497 | AL2: 329 | AM2: 649 | AN2: Shopify Western Brothers | AP2: 0
A3: 7506499570834 | B3: 108360 | C3: Multimarca | D3: 01-TDAG012-0010 | E3: 01-TDAG012-0010-L | F3: L | G3: L | H3: Denver | I3: Playera Denver caballero blanco | J3: Ropa | K3: Playeras | L3: Hombre | M3: Denver | N3: SS26 | O3: Seasonal | P3: Blanco | Q3: Regular | S3: 100% Algodón | T3: Playera Denver caballero blanco Regular | U3: México | V3: PZS | W3: 53101602 | Y3: 329 | Z3: 559.48276 | AA3: =IF(AND(A3="", B3="", E3=""), "", IF(AB3="", "Válido", IF((LEN(AB3)-LEN(SUBSTITUTE(AB3,"; ","")))/2+1>(LEN(AB3)-LEN(SUBSTITUTE(AB3,"[Aviso]","")))/7, "Con Incidencias", "Válido"))) | AB3: =IF(AND(A3="", B3="", E3=""), "", TEXTJOIN("; ", TRUE, IF(OR(TRIM(A3&"")="", ISNUMBER(SEARCH("FALTA", A3))), "UPC faltante/inválido", ""), IF(AND(A3<>"", IFERROR(_xlfn.XMATCH(A3,$A$2:$A$204,0,1)<>_xlfn.XMATCH(A3,$A$2:$A$204,0,-1),FALSE)), "Código de barras duplicado", ""), IF(AND(E3<>"", COUNTIF($E$2:$E$204, E3)>1), "SKU duplicado", ""), IF(OR(J3="", J3=""), "[Aviso] División no capturada ()", IF(ISNA(MATCH(J3, Criterios!$A$123:$A$126, 0)), "División no válida", "")), IF(OR(K3="", K3=""), "[Aviso] Categoría no capturada ()", IF(ISNA(MATCH(K3, Criterios!$A$81:$A$120, 0)), "Categoría no válida", IF(AND(J3<>"", J3<>"", J3<>VLOOKUP(K3, Criterios!$A$81:$B$120, 2, FALSE)), "División no coincide con Categoría", ""))), IF(OR(L3="", L3=""), "[Aviso] Género no capturado ()", IF(ISNA(MATCH(L3, Criterios!$B$123:$B$127, 0)), "Género no válido", "")), IF(OR(N3="", N3=""), "[Aviso] Temporada no capturada ()", IF(ISNA(MATCH(N3, Criterios!$C$123:$C$128, 0)), "Temporada no válida", "")), IF(OR(O3="", O3=""), "[Aviso] Ciclo de vida no capturado ()", IF(ISNA(MATCH(O3, Criterios!$D$123:$D$124, 0)), "Ciclo de vida no válido", "")))) | AD3: 3 | AE3: WB OUTLET LERMA: 3 | AF3: 3 | AG3: Nuevo – NetSuite con existencia | AH3: Revisión 29/09/2026: Campos sin respaldo: X; Auditoría NetSuite 30/09/2026: llenado desde NetSuite [P,V,Y,T] | 01/10/2026: complementado desde Shopify Western Brothers (match por código de barras): WB Silueta | Homologación G1522 06/10/2026: Validación G1522: Dígito de control del código de barras inválido | AI3: No | AK3: ProductosCatalogoEstandar907.xlsx: fila 6237 [N,O,Q,S,U,Y]; G1522_Extraccion_Articulos_NetSuite_2026-09-30.xlsx: fila 56519 [P,V,Y,T] | Shopify WB: producto 8569955352761 / variante 47621314478265 | AL3: 329 | AM3: 649 | AN3: Shopify Western Brothers | AP3: 3 | AR3: Shopify Western Brothers › Western Brothers Outlet Lerma: 3
A4: 7506499570835 | B4: 108361 | C4: Multimarca | D4: 01-TDAG012-0010 | E4: 01-TDAG012-0010-XL | F4: XL | G4: XL | H4: Denver | I4: Playera Denver caballero blanco | J4: Ropa | K4: Playeras | L4: Hombre | M4: Denver | N4: SS26 | O4: Seasonal | P4: Blanco | Q4: Regular | S4: 100% Algodón | T4: Playera Denver caballero blanco Regular | U4: México | V4: PZS | W4: 53101602 | Y4: 329 | Z4: 559.48276 | AA4: =IF(AND(A4="", B4="", E4=""), "", IF(AB4="", "Válido", IF((LEN(AB4)-LEN(SUBSTITUTE(AB4,"; ","")))/2+1>(LEN(AB4)-LEN(SUBSTITUTE(AB4,"[Aviso]","")))/7, "Con Incidencias", "Válido"))) | AB4: =IF(AND(A4="", B4="", E4=""), "", TEXTJOIN("; ", TRUE, IF(OR(TRIM(A4&"")="", ISNUMBER(SEARCH("FALTA", A4))), "UPC faltante/inválido", ""), IF(AND(A4<>"", IFERROR(_xlfn.XMATCH(A4,$A$2:$A$204,0,1)<>_xlfn.XMATCH(A4,$A$2:$A$204,0,-1),FALSE)), "Código de barras duplicado", ""), IF(AND(E4<>"", COUNTIF($E$2:$E$204, E4)>1), "SKU duplicado", ""), IF(OR(J4="", J4=""), "[Aviso] División no capturada ()", IF(ISNA(MATCH(J4, Criterios!$A$123:$A$126, 0)), "División no válida", "")), IF(OR(K4="", K4=""), "[Aviso] Categoría no capturada ()", IF(ISNA(MATCH(K4, Criterios!$A$81:$A$120, 0)), "Categoría no válida", IF(AND(J4<>"", J4<>"", J4<>VLOOKUP(K4, Criterios!$A$81:$B$120, 2, FALSE)), "División no coincide con Categoría", ""))), IF(OR(L4="", L4=""), "[Aviso] Género no capturado ()", IF(ISNA(MATCH(L4, Criterios!$B$123:$B$127, 0)), "Género no válido", "")), IF(OR(N4="", N4=""), "[Aviso] Temporada no capturada ()", IF(ISNA(MATCH(N4, Criterios!$C$123:$C$128, 0)), "Temporada no válida", "")), IF(OR(O4="", O4=""), "[Aviso] Ciclo de vida no capturado ()", IF(ISNA(MATCH(O4, Criterios!$D$123:$D$124, 0)), "Ciclo de vida no válido", "")))) | AD4: 3 | AE4: WB OUTLET LERMA: 3 | AF4: 3 | AG4: Nuevo – NetSuite con existencia | AH4: Revisión 29/09/2026: Campos sin respaldo: X; Auditoría NetSuite 30/09/2026: llenado desde NetSuite [P,V,Y,T] | 01/10/2026: complementado desde Shopify Western Brothers (match por código de barras): WB Silueta | Homologación G1522 06/10/2026: Validación G1522: Dígito de control del código de barras inválido | AI4: No | AK4: ProductosCatalogoEstandar907.xlsx: fila 6238 [N,O,Q,S,U,Y]; G1522_Extraccion_Articulos_NetSuite_2026-09-30.xlsx: fila 56520 [P,V,Y,T] | Shopify WB: producto 8569955352761 / variante 47621314511033 | AL4: 329 | AM4: 649 | AN4: Shopify Western Brothers | AP4: 3 | AR4: Shopify Western Brothers › Western Brothers Outlet Lerma: 3
A5: 7506499570836 | B5: 108362 | C5: Multimarca | D5: 01-TDAG012-0011 | E5: 01-TDAG012-0011-S | F5: S | G5: S | H5: Denver | I5: Playera Denver caballero negro calavera con guitarra | J5: Ropa | K5: Playeras | L5: Hombre | M5: Denver | N5: SS26 | O5: Seasonal | P5: Negro | Q5: Regular | S5: 100% Algodón | T5: Playera Denver caballero negro calavera con guitarra Regular | U5: México | V5: PZS | W5: 53101602 | Y5: 329 | Z5: 559.48276 | AA5: =IF(AND(A5="", B5="", E5=""), "", IF(AB5="", "Válido", IF((LEN(AB5)-LEN(SUBSTITUTE(AB5,"; ","")))/2+1>(LEN(AB5)-LEN(SUBSTITUTE(AB5,"[Aviso]","")))/7, "Con Incidencias", "Válido"))) | AB5: =IF(AND(A5="", B5="", E5=""), "", TEXTJOIN("; ", TRUE, IF(OR(TRIM(A5&"")="", ISNUMBER(SEARCH("FALTA", A5))), "UPC faltante/inválido", ""), IF(AND(A5<>"", IFERROR(_xlfn.XMATCH(A5,$A$2:$A$204,0,1)<>_xlfn.XMATCH(A5,$A$2:$A$204,0,-1),FALSE)), "Código de barras duplicado", ""), IF(AND(E5<>"", COUNTIF($E$2:$E$204, E5)>1), "SKU duplicado", ""), IF(OR(J5="", J5=""), "[Aviso] División no capturada ()", IF(ISNA(MATCH(J5, Criterios!$A$123:$A$126, 0)), "División no válida", "")), IF(OR(K5="", K5=""), "[Aviso] Categoría no capturada ()", IF(ISNA(MATCH(K5, Criterios!$A$81:$A$120, 0)), "Categoría no válida", IF(AND(J5<>"", J5<>"", J5<>VLOOKUP(K5, Criterios!$A$81:$B$120, 2, FALSE)), "División no coincide con Categoría", ""))), IF(OR(L5="", L5=""), "[Aviso] Género no capturado ()", IF(ISNA(MATCH(L5, Criterios!$B$123:$B$127, 0)), "Género no válido", "")), IF(OR(N5="", N5=""), "[Aviso] Temporada no capturada ()", IF(ISNA(MATCH(N5, Criterios!$C$123:$C$128, 0)), "Temporada no válida", "")), IF(OR(O5="", O5=""), "[Aviso] Ciclo de vida no capturado ()", IF(ISNA(MATCH(O5, Criterios!$D$123:$D$124, 0)), "Ciclo de vida no válido", "")))) | AD5: 2 | AE5: WB OUTLET LERMA: 2 | AF5: 2 | AG5: Nuevo – NetSuite con existencia | AH5: Revisión 29/09/2026: Campos sin respaldo: X; Auditoría NetSuite 30/09/2026: llenado desde NetSuite [P,V,Y,T] | 01/10/2026: complementado desde Shopify Western Brothers (match por código de barras): WB Silueta | Homologación G1522 06/10/2026: Validación G1522: Dígito de control del código de barras inválido | AI5: No | AK5: ProductosCatalogoEstandar907.xlsx: fila 6239 [N,O,Q,S,U,Y]; G1522_Extraccion_Articulos_NetSuite_2026-09-30.xlsx: fila 56521 [P,V,Y,T] | Shopify WB: producto 8569955680441 / variante 47621314773177 | AL5: 329 | AM5: 649 | AN5: Shopify Western Brothers | AP5: 2 | AR5: Shopify Western Brothers › Western Brothers Outlet Lerma: 2
A6: 7506499570837 | B6: 108363 | C6: Multimarca | D6: 01-TDAG012-0011 | E6: 01-TDAG012-0011-M | F6: M | G6: M | H6: Denver | I6: Playera Denver caballero negro calavera con guitarra | J6: Ropa | K6: Playeras | L6: Hombre | M6: Denver | N6: SS26 | O6: Seasonal | P6: Negro | Q6: Regular | S6: 100% Algodón | T6: Playera Denver caballero negro calavera con guitarra Regular | U6: México | V6: PZS | W6: 53101602 | Y6: 329 | Z6: 559.48276 | AA6: =IF(AND(A6="", B6="", E6=""), "", IF(AB6="", "Válido", IF((LEN(AB6)-LEN(SUBSTITUTE(AB6,"; ","")))/2+1>(LEN(AB6)-LEN(SUBSTITUTE(AB6,"[Aviso]","")))/7, "Con Incidencias", "Válido"))) | AB6: =IF(AND(A6="", B6="", E6=""), "", TEXTJOIN("; ", TRUE, IF(OR(TRIM(A6&"")="", ISNUMBER(SEARCH("FALTA", A6))), "UPC faltante/inválido", ""), IF(AND(A6<>"", IFERROR(_xlfn.XMATCH(A6,$A$2:$A$204,0,1)<>_xlfn.XMATCH(A6,$A$2:$A$204,0,-1),FALSE)), "Código de barras duplicado", ""), IF(AND(E6<>"", COUNTIF($E$2:$E$204, E6)>1), "SKU duplicado", ""), IF(OR(J6="", J6=""), "[Aviso] División no capturada ()", IF(ISNA(MATCH(J6, Criterios!$A$123:$A$126, 0)), "División no válida", "")), IF(OR(K6="", K6=""), "[Aviso] Categoría no capturada ()", IF(ISNA(MATCH(K6, Criterios!$A$81:$A$120, 0)), "Categoría no válida", IF(AND(J6<>"", J6<>"", J6<>VLOOKUP(K6, Criterios!$A$81:$B$120, 2, FALSE)), "División no coincide con Categoría", ""))), IF(OR(L6="", L6=""), "[Aviso] Género no capturado ()", IF(ISNA(MATCH(L6, Criterios!$B$123:$B$127, 0)), "Género no válido", "")), IF(OR(N6="", N6=""), "[Aviso] Temporada no capturada ()", IF(ISNA(MATCH(N6, Criterios!$C$123:$C$128, 0)), "Temporada no válida", "")), IF(OR(O6="", O6=""), "[Aviso] Ciclo de vida no capturado ()", IF(ISNA(MATCH(O6, Criterios!$D$123:$D$124, 0)), "Ciclo de vida no válido", "")))) | AD6: 1 | AE6: WB OUTLET LERMA: 1 | AF6: 1 | AG6: Nuevo – NetSuite con existencia | AH6: Revisión 29/09/2026: Campos sin respaldo: X; Auditoría NetSuite 30/09/2026: llenado desde NetSuite [P,V,Y,T] | 01/10/2026: complementado desde Shopify Western Brothers (match por código de barras): WB Silueta | Homologación G1522 06/10/2026: Validación G1522: Dígito de control del código de barras inválido | AI6: No | AK6: ProductosCatalogoEstandar907.xlsx: fila 6240 [N,O,Q,S,U,Y]; G1522_Extraccion_Articulos_NetSuite_2026-09-30.xlsx: fila 56522 [P,V,Y,T] | Shopify WB: producto 8569955680441 / variante 47621314805945 | AL6: 329 | AM6: 649 | AN6: Shopify Western Brothers | AP6: 1 | AR6: Shopify Western Brothers › Western Brothers Outlet Lerma: 1
A7: 7506499570838 | B7: 108364 | C7: Multimarca | D7: 01-TDAG012-0011 | E7: 01-TDAG012-0011-L | F7: L | G7: L | H7: Denver | I7: Playera Denver caballero negro calavera con guitarra | J7: Ropa | K7: Playeras | L7: Hombre | M7: Denver | N7: SS26 | O7: Seasonal | P7: Negro | Q7: Regular | S7: 100% Algodón | T7: Playera Denver caballero negro calavera con guitarra Regular | U7: México | V7: PZS | W7: 53101602 | Y7: 329 | Z7: 559.48276 | AA7: =IF(AND(A7="", B7="", E7=""), "", IF(AB7="", "Válido", IF((LEN(AB7)-LEN(SUBSTITUTE(AB7,"; ","")))/2+1>(LEN(AB7)-LEN(SUBSTITUTE(AB7,"[Aviso]","")))/7, "Con Incidencias", "Válido"))) | AB7: =IF(AND(A7="", B7="", E7=""), "", TEXTJOIN("; ", TRUE, IF(OR(TRIM(A7&"")="", ISNUMBER(SEARCH("FALTA", A7))), "UPC faltante/inválido", ""), IF(AND(A7<>"", IFERROR(_xlfn.XMATCH(A7,$A$2:$A$204,0,1)<>_xlfn.XMATCH(A7,$A$2:$A$204,0,-1),FALSE)), "Código de barras duplicado", ""), IF(AND(E7<>"", COUNTIF($E$2:$E$204, E7)>1), "SKU duplicado", ""), IF(OR(J7="", J7=""), "[Aviso] División no capturada ()", IF(ISNA(MATCH(J7, Criterios!$A$123:$A$126, 0)), "División no válida", "")), IF(OR(K7="", K7=""), "[Aviso] Categoría no capturada ()", IF(ISNA(MATCH(K7, Criterios!$A$81:$A$120, 0)), "Categoría no válida", IF(AND(J7<>"", J7<>"", J7<>VLOOKUP(K7, Criterios!$A$81:$B$120, 2, FALSE)), "División no coincide con Categoría", ""))), IF(OR(L7="", L7=""), "[Aviso] Género no capturado ()", IF(ISNA(MATCH(L7, Criterios!$B$123:$B$127, 0)), "Género no válido", "")), IF(OR(N7="", N7=""), "[Aviso] Temporada no capturada ()", IF(ISNA(MATCH(N7, Criterios!$C$123:$C$128, 0)), "Temporada no válida", "")), IF(OR(O7="", O7=""), "[Aviso] Ciclo de vida no capturado ()", IF(ISNA(MATCH(O7, Criterios!$D$123:$D$124, 0)), "Ciclo de vida no válido", "")))) | AD7: 1 | AE7: WB OUTLET LERMA: 1 | AF7: 1 | AG7: Nuevo – NetSuite con existencia | AH7: Revisión 29/09/2026: Campos sin respaldo: X; Auditoría NetSuite 30/09/2026: llenado desde NetSuite [P,V,Y,T] | 01/10/2026: complementado desde Shopify Western Brothers (match por código de barras): WB Silueta | Homologación G1522 06/10/2026: Validación G1522: Dígito de control del código de barras inválido | AI7: No | AK7: ProductosCatalogoEstandar907.xlsx: fila 6241 [N,O,Q,S,U,Y]; G1522_Extraccion_Articulos_NetSuite_2026-09-30.xlsx: fila 56523 [P,V,Y,T] | Shopify WB: producto 8569955680441 / variante 47621314838713 | AL7: 329 | AM7: 649 | AN7: Shopify Western Brothers | AP7: 1 | AR7: Shopify Western Brothers › Western Brothers Outlet Lerma: 1
A8: 7506499570839 | B8: 108365 | C8: Multimarca | D8: 01-TDAG012-0011 | E8: 01-TDAG012-0011-XL | F8: XL | G8: XL | H8: Denver | I8: Playera Denver caballero negro calavera con guitarra | J8: Ropa | K8: Playeras | L8: Hombre | M8: Denver | N8: SS26 | O8: Seasonal | P8: Negro | Q8: Regular | S8: 100% Algodón | T8: Playera Denver caballero negro calavera con guitarra Regular | U8: México | V8: PZS | W8: 53101602 | Y8: 329 | Z8: 559.48276 | AA8: =IF(AND(A8="", B8="", E8=""), "", IF(AB8="", "Válido", IF((LEN(AB8)-LEN(SUBSTITUTE(AB8,"; ","")))/2+1>(LEN(AB8)-LEN(SUBSTITUTE(AB8,"[Aviso]","")))/7, "Con Incidencias", "Válido"))) | AB8: =IF(AND(A8="", B8="", E8=""), "", TEXTJOIN("; ", TRUE, IF(OR(TRIM(A8&"")="", ISNUMBER(SEARCH("FALTA", A8))), "UPC faltante/inválido", ""), IF(AND(A8<>"", IFERROR(_xlfn.XMATCH(A8,$A$2:$A$204,0,1)<>_xlfn.XMATCH(A8,$A$2:$A$204,0,-1),FALSE)), "Código de barras duplicado", ""), IF(AND(E8<>"", COUNTIF($E$2:$E$204, E8)>1), "SKU duplicado", ""), IF(OR(J8="", J8=""), "[Aviso] División no capturada ()", IF(ISNA(MATCH(J8, Criterios!$A$123:$A$126, 0)), "División no válida", "")), IF(OR(K8="", K8=""), "[Aviso] Categoría no capturada ()", IF(ISNA(MATCH(K8, Criterios!$A$81:$A$120, 0)), "Categoría no válida", IF(AND(J8<>"", J8<>"", J8<>VLOOKUP(K8, Criterios!$A$81:$B$120, 2, FALSE)), "División no coincide con Categoría", ""))), IF(OR(L8="", L8=""), "[Aviso] Género no capturado ()", IF(ISNA(MATCH(L8, Criterios!$B$123:$B$127, 0)), "Género no válido", "")), IF(OR(N8="", N8=""), "[Aviso] Temporada no capturada ()", IF(ISNA(MATCH(N8, Criterios!$C$123:$C$128, 0)), "Temporada no válida", "")), IF(OR(O8="", O8=""), "[Aviso] Ciclo de vida no capturado ()", IF(ISNA(MATCH(O8, Criterios!$D$123:$D$124, 0)), "Ciclo de vida no válido", "")))) | AD8: 3 | AE8: WB OUTLET LERMA: 3 | AF8: 3 | AG8: Nuevo – NetSuite con existencia | AH8: Revisión 29/09/2026: Campos sin respaldo: X; Auditoría NetSuite 30/09/2026: llenado desde NetSuite [P,V,Y,T] | 01/10/2026: complementado desde Shopify Western Brothers (match por código de barras): WB Silueta | Homologación G1522 06/10/2026: Validación G1522: Dígito de control del código de barras inválido | AI8: No | AK8: ProductosCatalogoEstandar907.xlsx: fila 6242 [N,O,Q,S,U,Y]; G1522_Extraccion_Articulos_NetSuite_2026-09-30.xlsx: fila 56524 [P,V,Y,T] | Shopify WB: producto 8569955680441 / variante 47621314871481 | AL8: 329 | AM8: 649 | AN8: Shopify Western Brothers | AP8: 3 | AR8: Shopify Western Brothers › Western Brothers Outlet Lerma: 3
A9: 7506499570840 | B9: 108366 | C9: Multimarca | D9: 01-TDAG012-0015 | E9: 01-TDAG012-0015-S | F9: S | G9: S | H9: Denver | I9: Playera Denver caballero blanco cocodrilo | J9: Ropa | K9: Playeras | L9: Hombre | M9: Denver | N9: SS26 | O9: Seasonal | P9: Blanco | Q9: Regular | S9: 100% Algodón | T9: Playera Denver caballero blanco cocodrilo Regular | U9: México | V9: PZS | W9: 53101602 | Y9: 329 | Z9: 559.48276 | AA9: =IF(AND(A9="", B9="", E9=""), "", IF(AB9="", "Válido", IF((LEN(AB9)-LEN(SUBSTITUTE(AB9,"; ","")))/2+1>(LEN(AB9)-LEN(SUBSTITUTE(AB9,"[Aviso]","")))/7, "Con Incidencias", "Válido"))) | AB9: =IF(AND(A9="", B9="", E9=""), "", TEXTJOIN("; ", TRUE, IF(OR(TRIM(A9&"")="", ISNUMBER(SEARCH("FALTA", A9))), "UPC faltante/inválido", ""), IF(AND(A9<>"", IFERROR(_xlfn.XMATCH(A9,$A$2:$A$204,0,1)<>_xlfn.XMATCH(A9,$A$2:$A$204,0,-1),FALSE)), "Código de barras duplicado", ""), IF(AND(E9<>"", COUNTIF($E$2:$E$204, E9)>1), "SKU duplicado", ""), IF(OR(J9="", J9=""), "[Aviso] División no capturada ()", IF(ISNA(MATCH(J9, Criterios!$A$123:$A$126, 0)), "División no válida", "")), IF(OR(K9="", K9=""), "[Aviso] Categoría no capturada ()", IF(ISNA(MATCH(K9, Criterios!$A$81:$A$120, 0)), "Categoría no válida", IF(AND(J9<>"", J9<>"", J9<>VLOOKUP(K9, Criterios!$A$81:$B$120, 2, FALSE)), "División no coincide con Categoría", ""))), IF(OR(L9="", L9=""), "[Aviso] Género no capturado ()", IF(ISNA(MATCH(L9, Criterios!$B$123:$B$127, 0)), "Género no válido", "")), IF(OR(N9="", N9=""), "[Aviso] Temporada no capturada ()", IF(ISNA(MATCH(N9, Criterios!$C$123:$C$128, 0)), "Temporada no válida", "")), IF(OR(O9="", O9=""), "[Aviso] Ciclo de vida no capturado ()", IF(ISNA(MATCH(O9, Criterios!$D$123:$D$124, 0)), "Ciclo de vida no válido", "")))) | AD9: 1 | AE9: WB OUTLET LERMA: 1 | AF9: 1 | AG9: Nuevo – NetSuite con existencia | AH9: Revisión 29/09/2026: Campos sin respaldo: X; Auditoría NetSuite 30/09/2026: llenado desde NetSuite [P,V,Y,T] | 01/10/2026: complementado desde Shopify Western Brothers (match por código de barras): WB Silueta | Homologación G1522 06/10/2026: Validación G1522: Dígito de control del código de barras inválido | AI9: No | AK9: ProductosCatalogoEstandar907.xlsx: fila 6243 [N,O,Q,S,U,Y]; G1522_Extraccion_Articulos_NetSuite_2026-09-30.xlsx: fila 56525 [P,V,Y,T] | Shopify WB: producto 8569955811513 / variante 47621315166393 | AL9: 329 | AM9: 649 | AN9: Shopify Western Brothers | AP9: 2 | AR9: Shopify Western Brothers › Western Brothers Outlet Lerma: 2
A10: 7506499570841 | B10: 108367 | C10: Multimarca | D10: 01-TDAG012-0015 | E10: 01-TDAG012-0015-M | F10: M | G10: M | H10: Denver | I10: Playera Denver caballero blanco cocodrilo | J10: Ropa | K10: Playeras | L10: Hombre | M10: Denver | N10: SS26 | O10: Seasonal | P10: Blanco | Q10: Regular | S10: 100% Algodón | T10: Playera Denver caballero blanco cocodrilo Regular | U10: México | V10: PZS | W10: 53101602 | Y10: 329 | Z10: 559.48276 | AA10: =IF(AND(A10="", B10="", E10=""), "", IF(AB10="", "Válido", IF((LEN(AB10)-LEN(SUBSTITUTE(AB10,"; ","")))/2+1>(LEN(AB10)-LEN(SUBSTITUTE(AB10,"[Aviso]","")))/7, "Con Incidencias", "Válido"))) | AB10: =IF(AND(A10="", B10="", E10=""), "", TEXTJOIN("; ", TRUE, IF(OR(TRIM(A10&"")="", ISNUMBER(SEARCH("FALTA", A10))), "UPC faltante/inválido", ""), IF(AND(A10<>"", IFERROR(_xlfn.XMATCH(A10,$A$2:$A$204,0,1)<>_xlfn.XMATCH(A10,$A$2:$A$204,0,-1),FALSE)), "Código de barras duplicado", ""), IF(AND(E10<>"", COUNTIF($E$2:$E$204, E10)>1), "SKU duplicado", ""), IF(OR(J10="", J10=""), "[Aviso] División no capturada ()", IF(ISNA(MATCH(J10, Criterios!$A$123:$A$126, 0)), "División no válida", "")), IF(OR(K10="", K10=""), "[Aviso] Categoría no capturada ()", IF(ISNA(MATCH(K10, Criterios!$A$81:$A$120, 0)), "Categoría no válida", IF(AND(J10<>"", J10<>"", J10<>VLOOKUP(K10, Criterios!$A$81:$B$120, 2, FALSE)), "División no coincide con Categoría", ""))), IF(OR(L10="", L10=""), "[Aviso] Género no capturado ()", IF(ISNA(MATCH(L10, Criterios!$B$123:$B$127, 0)), "Género no válido", "")), IF(OR(N10="", N10=""), "[Aviso] Temporada no capturada ()", IF(ISNA(MATCH(N10, Criterios!$C$123:$C$128, 0)), "Temporada no válida", "")), IF(OR(O10="", O10=""), "[Aviso] Ciclo de vida no capturado ()", IF(ISNA(MATCH(O10, Criterios!$D$123:$D$124, 0)), "Ciclo de vida no válido", "")))) | AD10: 2 | AE10: WB OUTLET LERMA: 2 | AF10: 2 | AG10: Nuevo – NetSuite con existencia | AH10: Revisión 29/09/2026: Campos sin respaldo: X; Auditoría NetSuite 30/09/2026: llenado desde NetSuite [P,V,Y,T] | 01/10/2026: complementado desde Shopify Western Brothers (match por código de barras): WB Silueta | Homologación G1522 06/10/2026: Validación G1522: Dígito de control del código de barras inválido | AI10: No | AK10: ProductosCatalogoEstandar907.xlsx: fila 6244 [N,O,Q,S,U,Y]; G1522_Extraccion_Articulos_NetSuite_2026-09-30.xlsx: fila 56526 [P,V,Y,T] | Shopify WB: producto 8569955811513 / variante 47621315199161 | AL10: 329 | AM10: 649 | AN10: Shopify Western Brothers | AP10: 2 | AR10: Shopify Western Brothers › Western Brothers Outlet Lerma: 2
A11: 7506499570842 | B11: 108368 | C11: Multimarca | D11: 01-TDAG012-0015 | E11: 01-TDAG012-0015-L | F11: L | G11: L | H11: Denver | I11: Playera Denver caballero blanco cocodrilo | J11: Ropa | K11: Playeras | L11: Hombre | M11: Denver | N11: SS26 | O11: Seasonal | P11: Blanco | Q11: Regular | S11: 100% Algodón | T11: Playera Denver caballero blanco cocodrilo Regular | U11: México | V11: PZS | W11: 53101602 | Y11: 329 | Z11: 559.48276 | AA11: =IF(AND(A11="", B11="", E11=""), "", IF(AB11="", "Válido", IF((LEN(AB11)-LEN(SUBSTITUTE(AB11,"; ","")))/2+1>(LEN(AB11)-LEN(SUBSTITUTE(AB11,"[Aviso]","")))/7, "Con Incidencias", "Válido"))) | AB11: =IF(AND(A11="", B11="", E11=""), "", TEXTJOIN("; ", TRUE, IF(OR(TRIM(A11&"")="", ISNUMBER(SEARCH("FALTA", A11))), "UPC faltante/inválido", ""), IF(AND(A11<>"", IFERROR(_xlfn.XMATCH(A11,$A$2:$A$204,0,1)<>_xlfn.XMATCH(A11,$A$2:$A$204,0,-1),FALSE)), "Código de barras duplicado", ""), IF(AND(E11<>"", COUNTIF($E$2:$E$204, E11)>1), "SKU duplicado", ""), IF(OR(J11="", J11=""), "[Aviso] División no capturada ()", IF(ISNA(MATCH(J11, Criterios!$A$123:$A$126, 0)), "División no válida", "")), IF(OR(K11="", K11=""), "[Aviso] Categoría no capturada ()", IF(ISNA(MATCH(K11, Criterios!$A$81:$A$120, 0)), "Categoría no válida", IF(AND(J11<>"", J11<>"", J11<>VLOOKUP(K11, Criterios!$A$81:$B$120, 2, FALSE)), "División no coincide con Categoría", ""))), IF(OR(L11="", L11=""), "[Aviso] Género no capturado ()", IF(ISNA(MATCH(L11, Criterios!$B$123:$B$127, 0)), "Género no válido", "")), IF(OR(N11="", N11=""), "[Aviso] Temporada no capturada ()", IF(ISNA(MATCH(N11, Criterios!$C$123:$C$128, 0)), "Temporada no válida", "")), IF(OR(O11="", O11=""), "[Aviso] Ciclo de vida no capturado ()", IF(ISNA(MATCH(O11, Criterios!$D$123:$D$124, 0)), "Ciclo de vida no válido", "")))) | AD11: 0 | AF11: 0 | AG11: Nuevo – NetSuite sin existencia | AH11: Revisión 29/09/2026: Campos sin respaldo: X; Auditoría NetSuite 30/09/2026: llenado desde NetSuite [P,V,Y,T] | 01/10/2026: complementado desde Shopify Western Brothers (match por código de barras): WB Silueta | Homologación G1522 06/10/2026: Validación G1522: Dígito de control del código de barras inválido | AI11: No | AK11: ProductosCatalogoEstandar907.xlsx: fila 6245 [N,O,Q,S,U,Y]; G1522_Extraccion_Articulos_NetSuite_2026-09-30.xlsx: fila 56527 [P,V,Y,T] | Shopify WB: producto 8569955811513 / variante 47621315231929 | AL11: 329 | AM11: 649 | AN11: Shopify Western Brothers | AP11: 0
A12: 7506499570843 | B12: 108369 | C12: Multimarca | D12: 01-TDAG012-0015 | E12: 01-TDAG012-0015-XL | F12: XL | G12: XL | H12: Denver | I12: Playera Denver caballero blanco cocodrilo | J12: Ropa | K12: Playeras | L12: Hombre | M12: Denver | N12: SS26 | O12: Seasonal | P12: Blanco | Q12: Regular | S12: 100% Algodón | T12: Playera Denver caballero blanco cocodrilo Regular | U12: México | V12: PZS | W12: 53101602 | Y12: 329 | Z12: 559.48276 | AA12: =IF(AND(A12="", B12="", E12=""), "", IF(AB12="", "Válido", IF((LEN(AB12)-LEN(SUBSTITUTE(AB12,"; ","")))/2+1>(LEN(AB12)-LEN(SUBSTITUTE(AB12,"[Aviso]","")))/7, "Con Incidencias", "Válido"))) | AB12: =IF(AND(A12="", B12="", E12=""), "", TEXTJOIN("; ", TRUE, IF(OR(TRIM(A12&"")="", ISNUMBER(SEARCH("FALTA", A12))), "UPC faltante/inválido", ""), IF(AND(A12<>"", IFERROR(_xlfn.XMATCH(A12,$A$2:$A$204,0,1)<>_xlfn.XMATCH(A12,$A$2:$A$204,0,-1),FALSE)), "Código de barras duplicado", ""), IF(AND(E12<>"", COUNTIF($E$2:$E$204, E12)>1), "SKU duplicado", ""), IF(OR(J12="", J12=""), "[Aviso] División no capturada ()", IF(ISNA(MATCH(J12, Criterios!$A$123:$A$126, 0)), "División no válida", "")), IF(OR(K12="", K12=""), "[Aviso] Categoría no capturada ()", IF(ISNA(MATCH(K12, Criterios!$A$81:$A$120, 0)), "Categoría no válida", IF(AND(J12<>"", J12<>"", J12<>VLOOKUP(K12, Criterios!$A$81:$B$120, 2, FALSE)), "División no coincide con Categoría", ""))), IF(OR(L12="", L12=""), "[Aviso] Género no capturado ()", IF(ISNA(MATCH(L12, Criterios!$B$123:$B$127, 0)), "Género no válido", "")), IF(OR(N12="", N12=""), "[Aviso] Temporada no capturada ()", IF(ISNA(MATCH(N12, Criterios!$C$123:$C$128, 0)), "Temporada no válida", "")), IF(OR(O12="", O12=""), "[Aviso] Ciclo de vida no capturado ()", IF(ISNA(MATCH(O12, Criterios!$D$123:$D$124, 0)), "Ciclo de vida no válido", "")))) | AD12: 0 | AF12: 0 | AG12: Nuevo – NetSuite con existencia | AH12: Revisión 29/09/2026: Campos sin respaldo: X; Auditoría NetSuite 30/09/2026: llenado desde NetSuite [P,V,Y,T] | 01/10/2026: complementado desde Shopify Western Brothers (match por código de barras): WB Silueta | Homologación G1522 06/10/2026: Validación G1522: Dígito de control del código de barras inválido | AI12: No | AK12: ProductosCatalogoEstandar907.xlsx: fila 6246 [N,O,Q,S,U,Y]; G1522_Extraccion_Articulos_NetSuite_2026-09-30.xlsx: fila 56528 [P,V,Y,T] | Shopify WB: producto 8569955811513 / variante 47621315264697 | AL12: 329 | AM12: 649 | AN12: Shopify Western Brothers | AP12: 1 | AR12: Shopify Western Brothers › Western Brothers Outlet Lerma: 1
A13: 7506499570844 | B13: 108370 | C13: Multimarca | D13: 01-TDAG012-0017 | E13: 01-TDAG012-0017-S | F13: S | G13: S | H13: Denver | I13: Playera Denver caballero azul toro enojado | J13: Ropa | K13: Playeras | L13: Hombre | M13: Denver | N13: SS26 | O13: Seasonal | P13: Azul | Q13: Regular | S13: 100% Algodón | T13: Playera Denver caballero azul toro enojado Regular | U13: México | V13: PZS | W13: 53101602 | Y13: 329 | Z13: 559.48276 | AA13: =IF(AND(A13="", B13="", E13=""), "", IF(AB13="", "Válido", IF((LEN(AB13)-LEN(SUBSTITUTE(AB13,"; ","")))/2+1>(LEN(AB13)-LEN(SUBSTITUTE(AB13,"[Aviso]","")))/7, "Con Incidencias", "Válido"))) | AB13: =IF(AND(A13="", B13="", E13=""), "", TEXTJOIN("; ", TRUE, IF(OR(TRIM(A13&"")="", ISNUMBER(SEARCH("FALTA", A13))), "UPC faltante/inválido", ""), IF(AND(A13<>"", IFERROR(_xlfn.XMATCH(A13,$A$2:$A$204,0,1)<>_xlfn.XMATCH(A13,$A$2:$A$204,0,-1),FALSE)), "Código de barras duplicado", ""), IF(AND(E13<>"", COUNTIF($E$2:$E$204, E13)>1), "SKU duplicado", ""), IF(OR(J13="", J13=""), "[Aviso] División no capturada ()", IF(ISNA(MATCH(J13, Criterios!$A$123:$A$126, 0)), "División no válida", "")), IF(OR(K13="", K13=""), "[Aviso] Categoría no capturada ()", IF(ISNA(MATCH(K13, Criterios!$A$81:$A$120, 0)), "Categoría no válida", IF(AND(J13<>"", J13<>"", J13<>VLOOKUP(K13, Criterios!$A$81:$B$120, 2, FALSE)), "División no coincide con Categoría", ""))), IF(OR(L13="", L13=""), "[Aviso] Género no capturado ()", IF(ISNA(MATCH(L13, Criterios!$B$123:$B$127, 0)), "Género no válido", "")), IF(OR(N13="", N13=""), "[Aviso] Temporada no capturada ()", IF(ISNA(MATCH(N13, Criterios!$C$123:$C$128, 0)), "Temporada no válida", "")), IF(OR(O13="", O13=""), "[Aviso] Ciclo de vida no capturado ()", IF(ISNA(MATCH(O13, Criterios!$D$123:$D$124, 0)), "Ciclo de vida no válido", "")))) | AD13: 4 | AE13: WB OUTLET LERMA: 4 | AF13: 4 | AG13: Nuevo – NetSuite con existencia | AH13: Revisión 29/09/2026: Campos sin respaldo: X; Auditoría NetSuite 30/09/2026: llenado desde NetSuite [P,V,Y,T] | 01/10/2026: complementado desde Shopify Western Brothers (match por código de barras): WB Silueta | Homologación G1522 06/10/2026: Validación G1522: Dígito de control del código de barras inválido | AI13: No | AK13: ProductosCatalogoEstandar907.xlsx: fila 6247 [N,O,Q,S,U,Y]; G1522_Extraccion_Articulos_NetSuite_2026-09-30.xlsx: fila 56529 [P,V,Y,T] | Shopify WB: producto 8569955975353 / variante 47621315428537 | AL13: 329 | AM13: 649 | AN13: Shopify Western Brothers | AP13: 4 | AR13: Shopify Western Brothers › Western Brothers Outlet Lerma: 4
A14: 7506499570845 | B14: 108371 | C14: Multimarca | D14: 01-TDAG012-0017 | E14: 01-TDAG012-0017-M | F14: M | G14: M | H14: Denver | I14: Playera Denver caballero azul toro enojado | J14: Ropa | K14: Playeras | L14: Hombre | M14: Denver | N14: SS26 | O14: Seasonal | P14: Azul | Q14: Regular | S14: 100% Algodón | T14: Playera Denver caballero azul toro enojado Regular | U14: México | V14: PZS | W14: 53101602 | Y14: 329 | Z14: 559.48276 | AA14: =IF(AND(A14="", B14="", E14=""), "", IF(AB14="", "Válido", IF((LEN(AB14)-LEN(SUBSTITUTE(AB14,"; ","")))/2+1>(LEN(AB14)-LEN(SUBSTITUTE(AB14,"[Aviso]","")))/7, "Con Incidencias", "Válido"))) | AB14: =IF(AND(A14="", B14="", E14=""), "", TEXTJOIN("; ", TRUE, IF(OR(TRIM(A14&"")="", ISNUMBER(SEARCH("FALTA", A14))), "UPC faltante/inválido", ""), IF(AND(A14<>"", IFERROR(_xlfn.XMATCH(A14,$A$2:$A$204,0,1)<>_xlfn.XMATCH(A14,$A$2:$A$204,0,-1),FALSE)), "Código de barras duplicado", ""), IF(AND(E14<>"", COUNTIF($E$2:$E$204, E14)>1), "SKU duplicado", ""), IF(OR(J14="", J14=""), "[Aviso] División no capturada ()", IF(ISNA(MATCH(J14, Criterios!$A$123:$A$126, 0)), "División no válida", "")), IF(OR(K14="", K14=""), "[Aviso] Categoría no capturada ()", IF(ISNA(MATCH(K14, Criterios!$A$81:$A$120, 0)), "Categoría no válida", IF(AND(J14<>"", J14<>"", J14<>VLOOKUP(K14, Criterios!$A$81:$B$120, 2, FALSE)), "División no coincide con Categoría", ""))), IF(OR(L14="", L14=""), "[Aviso] Género no capturado ()", IF(ISNA(MATCH(L14, Criterios!$B$123:$B$127, 0)), "Género no válido", "")), IF(OR(N14="", N14=""), "[Aviso] Temporada no capturada ()", IF(ISNA(MATCH(N14, Criterios!$C$123:$C$128, 0)), "Temporada no válida", "")), IF(OR(O14="", O14=""), "[Aviso] Ciclo de vida no capturado ()", IF(ISNA(MATCH(O14, Criterios!$D$123:$D$124, 0)), "Ciclo de vida no válido", "")))) | AD14: 3 | AE14: WB OUTLET LERMA: 3 | AF14: 3 | AG14: Nuevo – NetSuite con existencia | AH14: Revisión 29/09/2026: Campos sin respaldo: X; Auditoría NetSuite 30/09/2026: llenado desde NetSuite [P,V,Y,T] | 01/10/2026: complementado desde Shopify Western Brothers (match por código de barras): WB Silueta | Homologación G1522 06/10/2026: Validación G1522: Dígito de control del código de barras inválido | AI14: No | AK14: ProductosCatalogoEstandar907.xlsx: fila 6248 [N,O,Q,S,U,Y]; G1522_Extraccion_Articulos_NetSuite_2026-09-30.xlsx: fila 56530 [P,V,Y,T] | Shopify WB: producto 8569955975353 / variante 47621315461305 | AL14: 329 | AM14: 649 | AN14: Shopify Western Brothers | AP14: 3 | AR14: Shopify Western Brothers › Western Brothers Outlet Lerma: 3
A15: 7506499570846 | B15: 108372 | C15: Multimarca | D15: 01-TDAG012-0017 | E15: 01-TDAG012-0017-L | F15: L | G15: L | H15: Denver | I15: Playera Denver caballero azul toro enojado | J15: Ropa | K15: Playeras | L15: Hombre | M15: Denver | N15: SS26 | O15: Seasonal | P15: Azul | Q15: Regular | S15: 100% Algodón | T15: Playera Denver caballero azul toro enojado Regular | U15: México | V15: PZS | W15: 53101602 | Y15: 329 | Z15: 559.48276 | AA15: =IF(AND(A15="", B15="", E15=""), "", IF(AB15="", "Válido", IF((LEN(AB15)-LEN(SUBSTITUTE(AB15,"; ","")))/2+1>(LEN(AB15)-LEN(SUBSTITUTE(AB15,"[Aviso]","")))/7, "Con Incidencias", "Válido"))) | AB15: =IF(AND(A15="", B15="", E15=""), "", TEXTJOIN("; ", TRUE, IF(OR(TRIM(A15&"")="", ISNUMBER(SEARCH("FALTA", A15))), "UPC faltante/inválido", ""), IF(AND(A15<>"", IFERROR(_xlfn.XMATCH(A15,$A$2:$A$204,0,1)<>_xlfn.XMATCH(A15,$A$2:$A$204,0,-1),FALSE)), "Código de barras duplicado", ""), IF(AND(E15<>"", COUNTIF($E$2:$E$204, E15)>1), "SKU duplicado", ""), IF(OR(J15="", J15=""), "[Aviso] División no capturada ()", IF(ISNA(MATCH(J15, Criterios!$A$123:$A$126, 0)), "División no válida", "")), IF(OR(K15="", K15=""), "[Aviso] Categoría no capturada ()", IF(ISNA(MATCH(K15, Criterios!$A$81:$A$120, 0)), "Categoría no válida", IF(AND(J15<>"", J15<>"", J15<>VLOOKUP(K15, Criterios!$A$81:$B$120, 2, FALSE)), "División no coincide con Categoría", ""))), IF(OR(L15="", L15=""), "[Aviso] Género no capturado ()", IF(ISNA(MATCH(L15, Criterios!$B$123:$B$127, 0)), "Género no válido", "")), IF(OR(N15="", N15=""), "[Aviso] Temporada no capturada ()", IF(ISNA(MATCH(N15, Criterios!$C$123:$C$128, 0)), "Temporada no válida", "")), IF(OR(O15="", O15=""), "[Aviso] Ciclo de vida no capturado ()", IF(ISNA(MATCH(O15, Criterios!$D$123:$D$124, 0)), "Ciclo de vida no válido", "")))) | AD15: 4 | AE15: WB OUTLET LERMA: 4 | AF15: 4 | AG15: Nuevo – NetSuite con existencia | AH15: Revisión 29/09/2026: Campos sin respaldo: X; Auditoría NetSuite 30/09/2026: llenado desde NetSuite [P,V,Y,T] | 01/10/2026: complementado desde Shopify Western Brothers (match por código de barras): WB Silueta | Homologación G1522 06/10/2026: Validación G1522: Dígito de control del código de barras inválido | AI15: No | AK15: ProductosCatalogoEstandar907.xlsx: fila 6249 [N,O,Q,S,U,Y]; G1522_Extraccion_Articulos_NetSuite_2026-09-30.xlsx: fila 56531 [P,V,Y,T] | Shopify WB: producto 8569955975353 / variante 47621315494073 | AL15: 329 | AM15: 649 | AN15: Shopify Western Brothers | AP15: 4 | AR15: Shopify Western Brothers › Western Brothers Outlet Lerma: 4
A16: 7506499570847 | B16: 108373 | C16: Multimarca | D16: 01-TDAG012-0017 | E16: 01-TDAG012-0017-XL | F16: XL | G16: XL | H16: Denver | I16: Playera Denver caballero azul toro enojado | J16: Ropa | K16: Playeras | L16: Hombre | M16: Denver | N16: SS26 | O16: Seasonal | P16: Azul | Q16: Regular | S16: 100% Algodón | T16: Playera Denver caballero azul toro enojado Regular | U16: México | V16: PZS | W16: 53101602 | Y16: 329 | Z16: 559.48276 | AA16: =IF(AND(A16="", B16="", E16=""), "", IF(AB16="", "Válido", IF((LEN(AB16)-LEN(SUBSTITUTE(AB16,"; ","")))/2+1>(LEN(AB16)-LEN(SUBSTITUTE(AB16,"[Aviso]","")))/7, "Con Incidencias", "Válido"))) | AB16: =IF(AND(A16="", B16="", E16=""), "", TEXTJOIN("; ", TRUE, IF(OR(TRIM(A16&"")="", ISNUMBER(SEARCH("FALTA", A16))), "UPC faltante/inválido", ""), IF(AND(A16<>"", IFERROR(_xlfn.XMATCH(A16,$A$2:$A$204,0,1)<>_xlfn.XMATCH(A16,$A$2:$A$204,0,-1),FALSE)), "Código de barras duplicado", ""), IF(AND(E16<>"", COUNTIF($E$2:$E$204, E16)>1), "SKU duplicado", ""), IF(OR(J16="", J16=""), "[Aviso] División no capturada ()", IF(ISNA(MATCH(J16, Criterios!$A$123:$A$126, 0)), "División no válida", "")), IF(OR(K16="", K16=""), "[Aviso] Categoría no capturada ()", IF(ISNA(MATCH(K16, Criterios!$A$81:$A$120, 0)), "Categoría no válida", IF(AND(J16<>"", J16<>"", J16<>VLOOKUP(K16, Criterios!$A$81:$B$120, 2, FALSE)), "División no coincide con Categoría", ""))), IF(OR(L16="", L16=""), "[Aviso] Género no capturado ()", IF(ISNA(MATCH(L16, Criterios!$B$123:$B$127, 0)), "Género no válido", "")), IF(OR(N16="", N16=""), "[Aviso] Temporada no capturada ()", IF(ISNA(MATCH(N16, Criterios!$C$123:$C$128, 0)), "Temporada no válida", "")), IF(OR(O16="", O16=""), "[Aviso] Ciclo de vida no capturado ()", IF(ISNA(MATCH(O16, Criterios!$D$123:$D$124, 0)), "Ciclo de vida no válido", "")))) | AD16: 3 | AE16: WB OUTLET LERMA: 3 | AF16: 3 | AG16: Nuevo – NetSuite con existencia | AH16: Revisión 29/09/2026: Campos sin respaldo: X; Auditoría NetSuite 30/09/2026: llenado desde NetSuite [P,V,Y,T] | 01/10/2026: complementado desde Shopify Western Brothers (match por código de barras): WB Silueta | Homologación G1522 06/10/2026: Validación G1522: Dígito de control del código de barras inválido | AI16: No | AK16: ProductosCatalogoEstandar907.xlsx: fila 6250 [N,O,Q,S,U,Y]; G1522_Extraccion_Articulos_NetSuite_2026-09-30.xlsx: fila 56532 [P,V,Y,T] | Shopify WB: producto 8569955975353 / variante 47621315526841 | AL16: 329 | AM16: 649 | AN16: Shopify Western Brothers | AP16: 3 | AR16: Shopify Western Brothers › Western Brothers Outlet Lerma: 3
A17: 7506499570849 | B17: 108375 | C17: Multimarca | D17: 02-TDAG012-0007 | E17: 02-TDAG012-0007-M | F17: M | G17: M | H17: Denver | I17: Playera Denver dama negro corazon toros | J17: Ropa | K17: Playeras | L17: Mujer | M17: Denver | N17: SS26 | O17: Seasonal | P17: Negro | Q17: Regular | S17: 100% Algodón | T17: Playera Denver dama negro corazon toros Regular | U17: México | V17: PZS | W17: 53101604 | Y17: 319 | Z17: 559.48276 | AA17: =IF(AND(A17="", B17="", E17=""), "", IF(AB17="", "Válido", IF((LEN(AB17)-LEN(SUBSTITUTE(AB17,"; ","")))/2+1>(LEN(AB17)-LEN(SUBSTITUTE(AB17,"[Aviso]","")))/7, "Con Incidencias", "Válido"))) | AB17: =IF(AND(A17="", B17="", E17=""), "", TEXTJOIN("; ", TRUE, IF(OR(TRIM(A17&"")="", ISNUMBER(SEARCH("FALTA", A17))), "UPC faltante/inválido", ""), IF(AND(A17<>"", IFERROR(_xlfn.XMATCH(A17,$A$2:$A$204,0,1)<>_xlfn.XMATCH(A17,$A$2:$A$204,0,-1),FALSE)), "Código de barras duplicado", ""), IF(AND(E17<>"", COUNTIF($E$2:$E$204, E17)>1), "SKU duplicado", ""), IF(OR(J17="", J17=""), "[Aviso] División no capturada ()", IF(ISNA(MATCH(J17, Criterios!$A$123:$A$126, 0)), "División no válida", "")), IF(OR(K17="", K17=""), "[Aviso] Categoría no capturada ()", IF(ISNA(MATCH(K17, Criterios!$A$81:$A$120, 0)), "Categoría no válida", IF(AND(J17<>"", J17<>"", J17<>VLOOKUP(K17, Criterios!$A$81:$B$120, 2, FALSE)), "División no coincide con Categoría", ""))), IF(OR(L17="", L17=""), "[Aviso] Género no capturado ()", IF(ISNA(MATCH(L17, Criterios!$B$123:$B$127, 0)), "Género no válido", "")), IF(OR(N17="", N17=""), "[Aviso] Temporada no capturada ()", IF(ISNA(MATCH(N17, Criterios!$C$123:$C$128, 0)), "Temporada no válida", "")), IF(OR(O17="", O17=""), "[Aviso] Ciclo de vida no capturado ()", IF(ISNA(MATCH(O17, Criterios!$D$123:$D$124, 0)), "Ciclo de vida no válido", "")))) | AD17: 4 | AE17: WB OUTLET LERMA: 4 | AF17: 4 | AG17: Nuevo – NetSuite con existencia | AH17: Revisión 29/09/2026: Campos sin respaldo: X; Auditoría NetSuite 30/09/2026: llenado desde NetSuite [P,V,Y,T] | 01/10/2026: complementado desde Shopify Western Brothers (match por código de barras): WB Silueta | Homologación G1522 06/10/2026: Validación G1522: Dígito de control del código de barras inválido | AI17: No | AK17: ProductosCatalogoEstandar907.xlsx: fila 6252 [N,O,Q,S,U,Y]; G1522_Extraccion_Articulos_NetSuite_2026-09-30.xlsx: fila 56534 [P,V,Y,T] | Shopify WB: producto 8569956139193 / variante 47621315821753 | AL17: 319 | AM17: 649 | AN17: Shopify Western Brothers | AP17: 4 | AR17: Shopify Western Brothers › Western Brothers Outlet Lerma: 4
A18: 7506499570850 | B18: 108376 | C18: Multimarca | D18: 02-TDAG012-0007 | E18: 02-TDAG012-0007-L | F18: L | G18: L | H18: Denver | I18: Playera Denver dama negro corazon toros | J18: Ropa | K18: Playeras | L18: Mujer | M18: Denver | N18: SS26 | O18: Seasonal | P18: Negro | Q18: Regular | S18: 100% Algodón | T18: Playera Denver dama negro corazon toros Regular | U18: México | V18: PZS | W18: 53101604 | Y18: 319 | Z18: 559.48276 | AA18: =IF(AND(A18="", B18="", E18=""), "", IF(AB18="", "Válido", IF((LEN(AB18)-LEN(SUBSTITUTE(AB18,"; ","")))/2+1>(LEN(AB18)-LEN(SUBSTITUTE(AB18,"[Aviso]","")))/7, "Con Incidencias", "Válido"))) | AB18: =IF(AND(A18="", B18="", E18=""), "", TEXTJOIN("; ", TRUE, IF(OR(TRIM(A18&"")="", ISNUMBER(SEARCH("FALTA", A18))), "UPC faltante/inválido", ""), IF(AND(A18<>"", IFERROR(_xlfn.XMATCH(A18,$A$2:$A$204,0,1)<>_xlfn.XMATCH(A18,$A$2:$A$204,0,-1),FALSE)), "Código de barras duplicado", ""), IF(AND(E18<>"", COUNTIF($E$2:$E$204, E18)>1), "SKU duplicado", ""), IF(OR(J18="", J18=""), "[Aviso] División no capturada ()", IF(ISNA(MATCH(J18, Criterios!$A$123:$A$126, 0)), "División no válida", "")), IF(OR(K18="", K18=""), "[Aviso] Categoría no capturada ()", IF(ISNA(MATCH(K18, Criterios!$A$81:$A$120, 0)), "Categoría no válida", IF(AND(J18<>"", J18<>"", J18<>VLOOKUP(K18, Criterios!$A$81:$B$120, 2, FALSE)), "División no coincide con Categoría", ""))), IF(OR(L18="", L18=""), "[Aviso] Género no capturado ()", IF(ISNA(MATCH(L18, Criterios!$B$123:$B$127, 0)), "Género no válido", "")), IF(OR(N18="", N18=""), "[Aviso] Temporada no capturada ()", IF(ISNA(MATCH(N18, Criterios!$C$123:$C$128, 0)), "Temporada no válida", "")), IF(OR(O18="", O18=""), "[Aviso] Ciclo de vida no capturado ()", IF(ISNA(MATCH(O18, Criterios!$D$123:$D$124, 0)), "Ciclo de vida no válido", "")))) | AD18: 4 | AE18: WB OUTLET LERMA: 4 | AF18: 4 | AG18: Nuevo – NetSuite con existencia | AH18: Revisión 29/09/2026: Campos sin respaldo: X; Auditoría NetSuite 30/09/2026: llenado desde NetSuite [P,V,Y,T] | 01/10/2026: complementado desde Shopify Western Brothers (match por código de barras): WB Silueta | Homologación G1522 06/10/2026: Validación G1522: Dígito de control del código de barras inválido | AI18: No | AK18: ProductosCatalogoEstandar907.xlsx: fila 6253 [N,O,Q,S,U,Y]; G1522_Extraccion_Articulos_NetSuite_2026-09-30.xlsx: fila 56535 [P,V,Y,T] | Shopify WB: producto 8569956139193 / variante 47621315854521 | AL18: 319 | AM18: 649 | AN18: Shopify Western Brothers | AP18: 4 | AR18: Shopify Western Brothers › Western Brothers Outlet Lerma: 4
A19: 7506499570851 | B19: 108377 | C19: Multimarca | D19: 02-TDAG012-0007 | E19: 02-TDAG012-0007-XL | F19: XL | G19: XL | H19: Denver | I19: Playera Denver dama negro corazon toros | J19: Ropa | K19: Playeras | L19: Mujer | M19: Denver | N19: SS26 | O19: Seasonal | P19: Negro | Q19: Regular | S19: 100% Algodón | T19: Playera Denver dama negro corazon toros Regular | U19: México | V19: PZS | W19: 53101604 | Y19: 319 | Z19: 559.48276 | AA19: =IF(AND(A19="", B19="", E19=""), "", IF(AB19="", "Válido", IF((LEN(AB19)-LEN(SUBSTITUTE(AB19,"; ","")))/2+1>(LEN(AB19)-LEN(SUBSTITUTE(AB19,"[Aviso]","")))/7, "Con Incidencias", "Válido"))) | AB19: =IF(AND(A19="", B19="", E19=""), "", TEXTJOIN("; ", TRUE, IF(OR(TRIM(A19&"")="", ISNUMBER(SEARCH("FALTA", A19))), "UPC faltante/inválido", ""), IF(AND(A19<>"", IFERROR(_xlfn.XMATCH(A19,$A$2:$A$204,0,1)<>_xlfn.XMATCH(A19,$A$2:$A$204,0,-1),FALSE)), "Código de barras duplicado", ""), IF(AND(E19<>"", COUNTIF($E$2:$E$204, E19)>1), "SKU duplicado", ""), IF(OR(J19="", J19=""), "[Aviso] División no capturada ()", IF(ISNA(MATCH(J19, Criterios!$A$123:$A$126, 0)), "División no válida", "")), IF(OR(K19="", K19=""), "[Aviso] Categoría no capturada ()", IF(ISNA(MATCH(K19, Criterios!$A$81:$A$120, 0)), "Categoría no válida", IF(AND(J19<>"", J19<>"", J19<>VLOOKUP(K19, Criterios!$A$81:$B$120, 2, FALSE)), "División no coincide con Categoría", ""))), IF(OR(L19="", L19=""), "[Aviso] Género no capturado ()", IF(ISNA(MATCH(L19, Criterios!$B$123:$B$127, 0)), "Género no válido", "")), IF(OR(N19="", N19=""), "[Aviso] Temporada no capturada ()", IF(ISNA(MATCH(N19, Criterios!$C$123:$C$128, 0)), "Temporada no válida", "")), IF(OR(O19="", O19=""), "[Aviso] Ciclo de vida no capturado ()", IF(ISNA(MATCH(O19, Criterios!$D$123:$D$124, 0)), "Ciclo de vida no válido", "")))) | AD19: 4 | AE19: WB OUTLET LERMA: 4 | AF19: 4 | AG19: Nuevo – NetSuite con existencia | AH19: Revisión 29/09/2026: Campos sin respaldo: X; Auditoría NetSuite 30/09/2026: llenado desde NetSuite [P,V,Y,T] | 01/10/2026: complementado desde Shopify Western Brothers (match por código de barras): WB Silueta | Homologación G1522 06/10/2026: Validación G1522: Dígito de control del código de barras inválido | AI19: No | AK19: ProductosCatalogoEstandar907.xlsx: fila 6254 [N,O,Q,S,U,Y]; G1522_Extraccion_Articulos_NetSuite_2026-09-30.xlsx: fila 56536 [P,V,Y,T] | Shopify WB: producto 8569956139193 / variante 47621315887289 | AL19: 319 | AM19: 649 | AN19: Shopify Western Brothers | AP19: 4 | AR19: Shopify Western Brothers › Western Brothers Outlet Lerma: 4
A20: 7506499570852 | B20: 108378 | C20: Multimarca | D20: 02-TDAG012-0010 | E20: 02-TDAG012-0010-S | F20: S | G20: S | H20: Denver | I20: Playera Denver dama beige botas | J20: Ropa | K20: Playeras | L20: Mujer | M20: Denver | N20: SS26 | O20: Seasonal | P20: Beige | Q20: Regular | S20: 100% Algodón | T20: Playera Denver dama beige botas Regular | U20: México | V20: PZS | W20: 53101604 | Y20: 319 | Z20: 559.48276 | AA20: =IF(AND(A20="", B20="", E20=""), "", IF(AB20="", "Válido", IF((LEN(AB20)-LEN(SUBSTITUTE(AB20,"; ","")))/2+1>(LEN(AB20)-LEN(SUBSTITUTE(AB20,"[Aviso]","")))/7, "Con Incidencias", "Válido"))) | AB20: =IF(AND(A20="", B20="", E20=""), "", TEXTJOIN("; ", TRUE, IF(OR(TRIM(A20&"")="", ISNUMBER(SEARCH("FALTA", A20))), "UPC faltante/inválido", ""), IF(AND(A20<>"", IFERROR(_xlfn.XMATCH(A20,$A$2:$A$204,0,1)<>_xlfn.XMATCH(A20,$A$2:$A$204,0,-1),FALSE)), "Código de barras duplicado", ""), IF(AND(E20<>"", COUNTIF($E$2:$E$204, E20)>1), "SKU duplicado", ""), IF(OR(J20="", J20=""), "[Aviso] División no capturada ()", IF(ISNA(MATCH(J20, Criterios!$A$123:$A$126, 0)), "División no válida", "")), IF(OR(K20="", K20=""), "[Aviso] Categoría no capturada ()", IF(ISNA(MATCH(K20, Criterios!$A$81:$A$120, 0)), "Categoría no válida", IF(AND(J20<>"", J20<>"", J20<>VLOOKUP(K20, Criterios!$A$81:$B$120, 2, FALSE)), "División no coincide con Categoría", ""))), IF(OR(L20="", L20=""), "[Aviso] Género no capturado ()", IF(ISNA(MATCH(L20, Criterios!$B$123:$B$127, 0)), "Género no válido", "")), IF(OR(N20="", N20=""), "[Aviso] Temporada no capturada ()", IF(ISNA(MATCH(N20, Criterios!$C$123:$C$128, 0)), "Temporada no válida", "")), IF(OR(O20="", O20=""), "[Aviso] Ciclo de vida no capturado ()", IF(ISNA(MATCH(O20, Criterios!$D$123:$D$124, 0)), "Ciclo de vida no válido", "")))) | AD20: 2 | AE20: WB OUTLET LERMA: 2 | AF20: 2 | AG20: Nuevo – NetSuite con existencia | AH20: Revisión 29/09/2026: Campos sin respaldo: X; Auditoría NetSuite 30/09/2026: llenado desde NetSuite [P,V,Y,T] | 01/10/2026: complementado desde Shopify Western Brothers (match por código de barras): WB Silueta | Homologación G1522 06/10/2026: Validación G1522: Dígito de control del código de barras inválido | AI20: No | AK20: ProductosCatalogoEstandar907.xlsx: fila 6255 [N,O,Q,S,U,Y]; G1522_Extraccion_Articulos_NetSuite_2026-09-30.xlsx: fila 56537 [P,V,Y,T] | Shopify WB: producto 8569956270265 / variante 47621316018361 | AL20: 319 | AM20: 649 | AN20: Shopify Western Brothers | AP20: 3 | AR20: Shopify Western Brothers › Western Brothers Outlet Lerma: 3
A21: 7506499570853 | B21: 108379 | C21: Multimarca | D21: 02-TDAG012-0010 | E21: 02-TDAG012-0010-M | F21: M | G21: M | H21: Denver | I21: Playera Denver dama beige botas | J21: Ropa | K21: Playeras | L21: Mujer | M21: Denver | N21: SS26 | O21: Seasonal | P21: Beige | Q21: Regular | S21: 100% Algodón | T21: Playera Denver dama beige botas Regular | U21: México | V21: PZS | W21: 53101604 | Y21: 319 | Z21: 559.48276 | AA21: =IF(AND(A21="", B21="", E21=""), "", IF(AB21="", "Válido", IF((LEN(AB21)-LEN(SUBSTITUTE(AB21,"; ","")))/2+1>(LEN(AB21)-LEN(SUBSTITUTE(AB21,"[Aviso]","")))/7, "Con Incidencias", "Válido"))) | AB21: =IF(AND(A21="", B21="", E21=""), "", TEXTJOIN("; ", TRUE, IF(OR(TRIM(A21&"")="", ISNUMBER(SEARCH("FALTA", A21))), "UPC faltante/inválido", ""), IF(AND(A21<>"", IFERROR(_xlfn.XMATCH(A21,$A$2:$A$204,0,1)<>_xlfn.XMATCH(A21,$A$2:$A$204,0,-1),FALSE)), "Código de barras duplicado", ""), IF(AND(E21<>"", COUNTIF($E$2:$E$204, E21)>1), "SKU duplicado", ""), IF(OR(J21="", J21=""), "[Aviso] División no capturada ()", IF(ISNA(MATCH(J21, Criterios!$A$123:$A$126, 0)), "División no válida", "")), IF(OR(K21="", K21=""), "[Aviso] Categoría no capturada ()", IF(ISNA(MATCH(K21, Criterios!$A$81:$A$120, 0)), "Categoría no válida", IF(AND(J21<>"", J21<>"", J21<>VLOOKUP(K21, Criterios!$A$81:$B$120, 2, FALSE)), "División no coincide con Categoría", ""))), IF(OR(L21="", L21=""), "[Aviso] Género no capturado ()", IF(ISNA(MATCH(L21, Criterios!$B$123:$B$127, 0)), "Género no válido", "")), IF(OR(N21="", N21=""), "[Aviso] Temporada no capturada ()", IF(ISNA(MATCH(N21, Criterios!$C$123:$C$128, 0)), "Temporada no válida", "")), IF(OR(O21="", O21=""), "[Aviso] Ciclo de vida no capturado ()", IF(ISNA(MATCH(O21, Criterios!$D$123:$D$124, 0)), "Ciclo de vida no válido", "")))) | AD21: 3 | AE21: WB OUTLET LERMA: 3 | AF21: 3 | AG21: Nuevo – NetSuite con existencia | AH21: Revisión 29/09/2026: Campos sin respaldo: X; Auditoría NetSuite 30/09/2026: llenado desde NetSuite [P,V,Y,T] | 01/10/2026: complementado desde Shopify Western Brothers (match por código de barras): WB Silueta | Homologación G1522 06/10/2026: Validación G1522: Dígito de control del código de barras inválido | AI21: No | AK21: ProductosCatalogoEstandar907.xlsx: fila 6256 [N,O,Q,S,U,Y]; G1522_Extraccion_Articulos_NetSuite_2026-09-30.xlsx: fila 56538 [P,V,Y,T] | Shopify WB: producto 8569956270265 / variante 47621316051129 | AL21: 319 | AM21: 649 | AN21: Shopify Western Brothers | AP21: 3 | AR21: Shopify Western Brothers › Western Brothers Outlet Lerma: 3
A22: 7506499570854 | B22: 108380 | C22: Multimarca | D22: 02-TDAG012-0010 | E22: 02-TDAG012-0010-L | F22: L | G22: L | H22: Denver | I22: Playera Denver dama beige botas | J22: Ropa | K22: Playeras | L22: Mujer | M22: Denver | N22: SS26 | O22: Seasonal | P22: Beige | Q22: Regular | S22: 100% Algodón | T22: Playera Denver dama beige botas Regular | U22: México | V22: PZS | W22: 53101604 | Y22: 319 | Z22: 559.48276 | AA22: =IF(AND(A22="", B22="", E22=""), "", IF(AB22="", "Válido", IF((LEN(AB22)-LEN(SUBSTITUTE(AB22,"; ","")))/2+1>(LEN(AB22)-LEN(SUBSTITUTE(AB22,"[Aviso]","")))/7, "Con Incidencias", "Válido"))) | AB22: =IF(AND(A22="", B22="", E22=""), "", TEXTJOIN("; ", TRUE, IF(OR(TRIM(A22&"")="", ISNUMBER(SEARCH("FALTA", A22))), "UPC faltante/inválido", ""), IF(AND(A22<>"", IFERROR(_xlfn.XMATCH(A22,$A$2:$A$204,0,1)<>_xlfn.XMATCH(A22,$A$2:$A$204,0,-1),FALSE)), "Código de barras duplicado", ""), IF(AND(E22<>"", COUNTIF($E$2:$E$204, E22)>1), "SKU duplicado", ""), IF(OR(J22="", J22=""), "[Aviso] División no capturada ()", IF(ISNA(MATCH(J22, Criterios!$A$123:$A$126, 0)), "División no válida", "")), IF(OR(K22="", K22=""), "[Aviso] Categoría no capturada ()", IF(ISNA(MATCH(K22, Criterios!$A$81:$A$120, 0)), "Categoría no válida", IF(AND(J22<>"", J22<>"", J22<>VLOOKUP(K22, Criterios!$A$81:$B$120, 2, FALSE)), "División no coincide con Categoría", ""))), IF(OR(L22="", L22=""), "[Aviso] Género no capturado ()", IF(ISNA(MATCH(L22, Criterios!$B$123:$B$127, 0)), "Género no válido", "")), IF(OR(N22="", N22=""), "[Aviso] Temporada no capturada ()", IF(ISNA(MATCH(N22, Criterios!$C$123:$C$128, 0)), "Temporada no válida", "")), IF(OR(O22="", O22=""), "[Aviso] Ciclo de vida no capturado ()", IF(ISNA(MATCH(O22, Criterios!$D$123:$D$124, 0)), "Ciclo de vida no válido", "")))) | AD22: 2 | AE22: WB OUTLET LERMA: 2 | AF22: 2 | AG22: Nuevo – NetSuite con existencia | AH22: Revisión 29/09/2026: Campos sin respaldo: X; Auditoría NetSuite 30/09/2026: llenado desde NetSuite [P,V,Y,T] | 01/10/2026: complementado desde Shopify Western Brothers (match por código de barras): WB Silueta | Homologación G1522 06/10/2026: Validación G1522: Dígito de control del código de barras inválido | AI22: No | AK22: ProductosCatalogoEstandar907.xlsx: fila 6257 [N,O,Q,S,U,Y]; G1522_Extraccion_Articulos_NetSuite_2026-09-30.xlsx: fila 56539 [P,V,Y,T] | Shopify WB: producto 8569956270265 / variante 47621316083897 | AL22: 319 | AM22: 649 | AN22: Shopify Western Brothers | AP22: 3 | AR22: Shopify Western Brothers › Western Brothers Outlet Lerma: 3
A23: 7506499570855 | B23: 108381 | C23: Multimarca | D23: 02-TDAG012-0010 | E23: 02-TDAG012-0010-XL | F23: XL | G23: XL | H23: Denver | I23: Playera Denver dama beige botas | J23: Ropa | K23: Playeras | L23: Mujer | M23: Denver | N23: SS26 | O23: Seasonal | P23: Beige | Q23: Regular | S23: 100% Algodón | T23: Playera Denver dama beige botas Regular | U23: México | V23: PZS | W23: 53101604 | Y23: 319 | Z23: 559.48276 | AA23: =IF(AND(A23="", B23="", E23=""), "", IF(AB23="", "Válido", IF((LEN(AB23)-LEN(SUBSTITUTE(AB23,"; ","")))/2+1>(LEN(AB23)-LEN(SUBSTITUTE(AB23,"[Aviso]","")))/7, "Con Incidencias", "Válido"))) | AB23: =IF(AND(A23="", B23="", E23=""), "", TEXTJOIN("; ", TRUE, IF(OR(TRIM(A23&"")="", ISNUMBER(SEARCH("FALTA", A23))), "UPC faltante/inválido", ""), IF(AND(A23<>"", IFERROR(_xlfn.XMATCH(A23,$A$2:$A$204,0,1)<>_xlfn.XMATCH(A23,$A$2:$A$204,0,-1),FALSE)), "Código de barras duplicado", ""), IF(AND(E23<>"", COUNTIF($E$2:$E$204, E23)>1), "SKU duplicado", ""), IF(OR(J23="", J23=""), "[Aviso] División no capturada ()", IF(ISNA(MATCH(J23, Criterios!$A$123:$A$126, 0)), "División no válida", "")), IF(OR(K23="", K23=""), "[Aviso] Categoría no capturada ()", IF(ISNA(MATCH(K23, Criterios!$A$81:$A$120, 0)), "Categoría no válida", IF(AND(J23<>"", J23<>"", J23<>VLOOKUP(K23, Criterios!$A$81:$B$120, 2, FALSE)), "División no coincide con Categoría", ""))), IF(OR(L23="", L23=""), "[Aviso] Género no capturado ()", IF(ISNA(MATCH(L23, Criterios!$B$123:$B$127, 0)), "Género no válido", "")), IF(OR(N23="", N23=""), "[Aviso] Temporada no capturada ()", IF(ISNA(MATCH(N23, Criterios!$C$123:$C$128, 0)), "Temporada no válida", "")), IF(OR(O23="", O23=""), "[Aviso] Ciclo de vida no capturado ()", IF(ISNA(MATCH(O23, Criterios!$D$123:$D$124, 0)), "Ciclo de vida no válido", "")))) | AD23: 3 | AE23: WB OUTLET LERMA: 3 | AF23: 3 | AG23: Nuevo – NetSuite con existencia | AH23: Revisión 29/09/2026: Campos sin respaldo: X; Auditoría NetSuite 30/09/2026: llenado desde NetSuite [P,V,Y,T] | 01/10/2026: complementado desde Shopify Western Brothers (match por código de barras): WB Silueta | AI23: No | AK23: ProductosCatalogoEstandar907.xlsx: fila 6258 [N,O,Q,S,U,Y]; G1522_Extraccion_Articulos_NetSuite_2026-09-30.xlsx: fila 56540 [P,V,Y,T] | Shopify WB: producto 8569956270265 / variante 47621316116665 | AL23: 319 | AM23: 649 | AN23: Shopify Western Brothers | AP23: 3 | AR23: Shopify Western Brothers › Western Brothers Outlet Lerma: 3
A24: 7506499570856 | B24: 108382 | C24: Multimarca | D24: 02-TDAG012-0012 | E24: 02-TDAG012-0012-S | F24: S | G24: S | H24: Denver | I24: Playera Denver dama beige placa denversito | J24: Ropa | K24: Playeras | L24: Mujer | M24: Denver | N24: SS26 | O24: Seasonal | P24: Beige | Q24: Regular | S24: 100% Algodón | T24: Playera Denver dama beige placa denversito Regular | U24: México | V24: PZS | W24: 53101604 | Y24: 319 | Z24: 559.48276 | AA24: =IF(AND(A24="", B24="", E24=""), "", IF(AB24="", "Válido", IF((LEN(AB24)-LEN(SUBSTITUTE(AB24,"; ","")))/2+1>(LEN(AB24)-LEN(SUBSTITUTE(AB24,"[Aviso]","")))/7, "Con Incidencias", "Válido"))) | AB24: =IF(AND(A24="", B24="", E24=""), "", TEXTJOIN("; ", TRUE, IF(OR(TRIM(A24&"")="", ISNUMBER(SEARCH("FALTA", A24))), "UPC faltante/inválido", ""), IF(AND(A24<>"", IFERROR(_xlfn.XMATCH(A24,$A$2:$A$204,0,1)<>_xlfn.XMATCH(A24,$A$2:$A$204,0,-1),FALSE)), "Código de barras duplicado", ""), IF(AND(E24<>"", COUNTIF($E$2:$E$204, E24)>1), "SKU duplicado", ""), IF(OR(J24="", J24=""), "[Aviso] División no capturada ()", IF(ISNA(MATCH(J24, Criterios!$A$123:$A$126, 0)), "División no válida", "")), IF(OR(K24="", K24=""), "[Aviso] Categoría no capturada ()", IF(ISNA(MATCH(K24, Criterios!$A$81:$A$120, 0)), "Categoría no válida", IF(AND(J24<>"", J24<>"", J24<>VLOOKUP(K24, Criterios!$A$81:$B$120, 2, FALSE)), "División no coincide con Categoría", ""))), IF(OR(L24="", L24=""), "[Aviso] Género no capturado ()", IF(ISNA(MATCH(L24, Criterios!$B$123:$B$127, 0)), "Género no válido", "")), IF(OR(N24="", N24=""), "[Aviso] Temporada no capturada ()", IF(ISNA(MATCH(N24, Criterios!$C$123:$C$128, 0)), "Temporada no válida", "")), IF(OR(O24="", O24=""), "[Aviso] Ciclo de vida no capturado ()", IF(ISNA(MATCH(O24, Criterios!$D$123:$D$124, 0)), "Ciclo de vida no válido", "")))) | AD24: 0 | AF24: 0 | AG24: Nuevo – NetSuite sin existencia | AH24: Revisión 29/09/2026: Campos sin respaldo: X; Auditoría NetSuite 30/09/2026: llenado desde NetSuite [P,V,Y,T] | 01/10/2026: complementado desde Shopify Western Brothers (match por código de barras): WB Silueta | Homologación G1522 06/10/2026: Validación G1522: Dígito de control del código de barras inválido | AI24: No | AK24: ProductosCatalogoEstandar907.xlsx: fila 6259 [N,O,Q,S,U,Y]; G1522_Extraccion_Articulos_NetSuite_2026-09-30.xlsx: fila 56541 [P,V,Y,T] | Shopify WB: producto 8569956499641 / variante 47621316346041 | AL24: 319 | AM24: 649 | AN24: Shopify Western Brothers | AP24: 0
A25: 7506499570857 | B25: 108383 | C25: Multimarca | D25: 02-TDAG012-0012 | E25: 02-TDAG012-0012-M | F25: M | G25: M | H25: Denver | I25: Playera Denver dama beige placa denversito | J25: Ropa | K25: Playeras | L25: Mujer | M25: Denver | N25: SS26 | O25: Seasonal | P25: Beige | Q25: Regular | S25: 100% Algodón | T25: Playera Denver dama beige placa denversito Regular | U25: México | V25: PZS | W25: 53101604 | Y25: 319 | Z25: 559.48276 | AA25: =IF(AND(A25="", B25="", E25=""), "", IF(AB25="", "Válido", IF((LEN(AB25)-LEN(SUBSTITUTE(AB25,"; ","")))/2+1>(LEN(AB25)-LEN(SUBSTITUTE(AB25,"[Aviso]","")))/7, "Con Incidencias", "Válido"))) | AB25: =IF(AND(A25="", B25="", E25=""), "", TEXTJOIN("; ", TRUE, IF(OR(TRIM(A25&"")="", ISNUMBER(SEARCH("FALTA", A25))), "UPC faltante/inválido", ""), IF(AND(A25<>"", IFERROR(_xlfn.XMATCH(A25,$A$2:$A$204,0,1)<>_xlfn.XMATCH(A25,$A$2:$A$204,0,-1),FALSE)), "Código de barras duplicado", ""), IF(AND(E25<>"", COUNTIF($E$2:$E$204, E25)>1), "SKU duplicado", ""), IF(OR(J25="", J25=""), "[Aviso] División no capturada ()", IF(ISNA(MATCH(J25, Criterios!$A$123:$A$126, 0)), "División no válida", "")), IF(OR(K25="", K25=""), "[Aviso] Categoría no capturada ()", IF(ISNA(MATCH(K25, Criterios!$A$81:$A$120, 0)), "Categoría no válida", IF(AND(J25<>"", J25<>"", J25<>VLOOKUP(K25, Criterios!$A$81:$B$120, 2, FALSE)), "División no coincide con Categoría", ""))), IF(OR(L25="", L25=""), "[Aviso] Género no capturado ()", IF(ISNA(MATCH(L25, Criterios!$B$123:$B$127, 0)), "Género no válido", "")), IF(OR(N25="", N25=""), "[Aviso] Temporada no capturada ()", IF(ISNA(MATCH(N25, Criterios!$C$123:$C$128, 0)), "Temporada no válida", "")), IF(OR(O25="", O25=""), "[Aviso] Ciclo de vida no capturado ()", IF(ISNA(MATCH(O25, Criterios!$D$123:$D$124, 0)), "Ciclo de vida no válido", "")))) | AD25: 0 | AF25: 0 | AG25: Nuevo – NetSuite sin existencia | AH25: Revisión 29/09/2026: Campos sin respaldo: X; Auditoría NetSuite 30/09/2026: llenado desde NetSuite [P,V,Y,T] | 01/10/2026: complementado desde Shopify Western Brothers (match por código de barras): WB Silueta | Homologación G1522 06/10/2026: Validación G1522: Dígito de control del código de barras inválido | AI25: No | AK25: ProductosCatalogoEstandar907.xlsx: fila 6260 [N,O,Q,S,U,Y]; G1522_Extraccion_Articulos_NetSuite_2026-09-30.xlsx: fila 56542 [P,V,Y,T] | Shopify WB: producto 8569956499641 / variante 47621316378809 | AL25: 319 | AM25: 649 | AN25: Shopify Western Brothers | AP25: 0
A26: 7506499570858 | B26: 108384 | C26: Multimarca | D26: 02-TDAG012-0012 | E26: 02-TDAG012-0012-L | F26: L | G26: L | H26: Denver | I26: Playera Denver dama beige placa denversito | J26: Ropa | K26: Playeras | L26: Mujer | M26: Denver | N26: SS26 | O26: Seasonal | P26: Beige | Q26: Regular | S26: 100% Algodón | T26: Playera Denver dama beige placa denversito Regular | U26: México | V26: PZS | W26: 53101604 | Y26: 319 | Z26: 559.48276 | AA26: =IF(AND(A26="", B26="", E26=""), "", IF(AB26="", "Válido", IF((LEN(AB26)-LEN(SUBSTITUTE(AB26,"; ","")))/2+1>(LEN(AB26)-LEN(SUBSTITUTE(AB26,"[Aviso]","")))/7, "Con Incidencias", "Válido"))) | AB26: =IF(AND(A26="", B26="", E26=""), "", TEXTJOIN("; ", TRUE, IF(OR(TRIM(A26&"")="", ISNUMBER(SEARCH("FALTA", A26))), "UPC faltante/inválido", ""), IF(AND(A26<>"", IFERROR(_xlfn.XMATCH(A26,$A$2:$A$204,0,1)<>_xlfn.XMATCH(A26,$A$2:$A$204,0,-1),FALSE)), "Código de barras duplicado", ""), IF(AND(E26<>"", COUNTIF($E$2:$E$204, E26)>1), "SKU duplicado", ""), IF(OR(J26="", J26=""), "[Aviso] División no capturada ()", IF(ISNA(MATCH(J26, Criterios!$A$123:$A$126, 0)), "División no válida", "")), IF(OR(K26="", K26=""), "[Aviso] Categoría no capturada ()", IF(ISNA(MATCH(K26, Criterios!$A$81:$A$120, 0)), "Categoría no válida", IF(AND(J26<>"", J26<>"", J26<>VLOOKUP(K26, Criterios!$A$81:$B$120, 2, FALSE)), "División no coincide con Categoría", ""))), IF(OR(L26="", L26=""), "[Aviso] Género no capturado ()", IF(ISNA(MATCH(L26, Criterios!$B$123:$B$127, 0)), "Género no válido", "")), IF(OR(N26="", N26=""), "[Aviso] Temporada no capturada ()", IF(ISNA(MATCH(N26, Criterios!$C$123:$C$128, 0)), "Temporada no válida", "")), IF(OR(O26="", O26=""), "[Aviso] Ciclo de vida no capturado ()", IF(ISNA(MATCH(O26, Criterios!$D$123:$D$124, 0)), "Ciclo de vida no válido", "")))) | AD26: -1 | AF26: 0 | AG26: Nuevo – NetSuite sin existencia | AH26: Revisión 29/09/2026: Campos sin respaldo: X; Auditoría NetSuite 30/09/2026: llenado desde NetSuite [P,V,Y,T] | 01/10/2026: complementado desde Shopify Western Brothers (match por código de barras): WB Silueta | Homologación G1522 06/10/2026: Validación G1522: Dígito de control del código de barras inválido | AI26: Sí | AJ26: WB OUTLET LERMA: -1 | AK26: ProductosCatalogoEstandar907.xlsx: fila 6261 [N,O,Q,S,U,Y]; G1522_Extraccion_Articulos_NetSuite_2026-09-30.xlsx: fila 56543 [P,V,Y,T] | Shopify WB: producto 8569956499641 / variante 47621316411577 | AL26: 319 | AM26: 649 | AN26: Shopify Western Brothers | AP26: -1
A27: 7506499570859 | B27: 108385 | C27: Multimarca | D27: 02-TDAG012-0012 | E27: 02-TDAG012-0012-XL | F27: XL | G27: XL | H27: Denver | I27: Playera Denver dama beige placa denversito | J27: Ropa | K27: Playeras | L27: Mujer | M27: Denver | N27: SS26 | O27: Seasonal | P27: Beige | Q27: Regular | S27: 100% Algodón | T27: Playera Denver dama beige placa denversito Regular | U27: México | V27: PZS | W27: 53101604 | Y27: 319 | Z27: 559.48276 | AA27: =IF(AND(A27="", B27="", E27=""), "", IF(AB27="", "Válido", IF((LEN(AB27)-LEN(SUBSTITUTE(AB27,"; ","")))/2+1>(LEN(AB27)-LEN(SUBSTITUTE(AB27,"[Aviso]","")))/7, "Con Incidencias", "Válido"))) | AB27: =IF(AND(A27="", B27="", E27=""), "", TEXTJOIN("; ", TRUE, IF(OR(TRIM(A27&"")="", ISNUMBER(SEARCH("FALTA", A27))), "UPC faltante/inválido", ""), IF(AND(A27<>"", IFERROR(_xlfn.XMATCH(A27,$A$2:$A$204,0,1)<>_xlfn.XMATCH(A27,$A$2:$A$204,0,-1),FALSE)), "Código de barras duplicado", ""), IF(AND(E27<>"", COUNTIF($E$2:$E$204, E27)>1), "SKU duplicado", ""), IF(OR(J27="", J27=""), "[Aviso] División no capturada ()", IF(ISNA(MATCH(J27, Criterios!$A$123:$A$126, 0)), "División no válida", "")), IF(OR(K27="", K27=""), "[Aviso] Categoría no capturada ()", IF(ISNA(MATCH(K27, Criterios!$A$81:$A$120, 0)), "Categoría no válida", IF(AND(J27<>"", J27<>"", J27<>VLOOKUP(K27, Criterios!$A$81:$B$120, 2, FALSE)), "División no coincide con Categoría", ""))), IF(OR(L27="", L27=""), "[Aviso] Género no capturado ()", IF(ISNA(MATCH(L27, Criterios!$B$123:$B$127, 0)), "Género no válido", "")), IF(OR(N27="", N27=""), "[Aviso] Temporada no capturada ()", IF(ISNA(MATCH(N27, Criterios!$C$123:$C$128, 0)), "Temporada no válida", "")), IF(OR(O27="", O27=""), "[Aviso] Ciclo de vida no capturado ()", IF(ISNA(MATCH(O27, Criterios!$D$123:$D$124, 0)), "Ciclo de vida no válido", "")))) | AD27: 1 | AE27: WB OUTLET LERMA: 1 | AF27: 1 | AG27: Nuevo – NetSuite con existencia | AH27: Revisión 29/09/2026: Campos sin respaldo: X; Auditoría NetSuite 30/09/2026: llenado desde NetSuite [P,V,Y,T] | 01/10/2026: complementado desde Shopify Western Brothers (match por código de barras): WB Silueta | Homologación G1522 06/10/2026: Validación G1522: Dígito de control del código de barras inválido | AI27: No | AK27: ProductosCatalogoEstandar907.xlsx: fila 6262 [N,O,Q,S,U,Y]; G1522_Extraccion_Articulos_NetSuite_2026-09-30.xlsx: fila 56544 [P,V,Y,T] | Shopify WB: producto 8569956499641 / variante 47621316444345 | AL27: 319 | AM27: 649 | AN27: Shopify Western Brothers | AP27: 1 | AR27: Shopify Western Brothers › Western Brothers Outlet Lerma: 1
A28: 7506499530439 | B28: 108386 | C28: Multimarca | D28: A-CHH180 | E28: A-CHH180-S | F28: S | G28: S | H28: Denver | I28: Camisa Denver caballero estampado biznaga negra | J28: Ropa | K28: Camisas | L28: Hombre | M28: Denver | N28: SS26 | O28: Core | P28: Negro | Q28: Regular | S28: 100% Algodón | T28: Camisa Denver caballero estampado biznaga negra Regular | U28: México | V28: PZS | W28: 53101602 | Y28: 419 | Z28: 947.41379 | AA28: =IF(AND(A28="", B28="", E28=""), "", IF(AB28="", "Válido", IF((LEN(AB28)-LEN(SUBSTITUTE(AB28,"; ","")))/2+1>(LEN(AB28)-LEN(SUBSTITUTE(AB28,"[Aviso]","")))/7, "Con Incidencias", "Válido"))) | AB28: =IF(AND(A28="", B28="", E28=""), "", TEXTJOIN("; ", TRUE, IF(OR(TRIM(A28&"")="", ISNUMBER(SEARCH("FALTA", A28))), "UPC faltante/inválido", ""), IF(AND(A28<>"", IFERROR(_xlfn.XMATCH(A28,$A$2:$A$204,0,1)<>_xlfn.XMATCH(A28,$A$2:$A$204,0,-1),FALSE)), "Código de barras duplicado", ""), IF(AND(E28<>"", COUNTIF($E$2:$E$204, E28)>1), "SKU duplicado", ""), IF(OR(J28="", J28=""), "[Aviso] División no capturada ()", IF(ISNA(MATCH(J28, Criterios!$A$123:$A$126, 0)), "División no válida", "")), IF(OR(K28="", K28=""), "[Aviso] Categoría no capturada ()", IF(ISNA(MATCH(K28, Criterios!$A$81:$A$120, 0)), "Categoría no válida", IF(AND(J28<>"", J28<>"", J28<>VLOOKUP(K28, Criterios!$A$81:$B$120, 2, FALSE)), "División no coincide con Categoría", ""))), IF(OR(L28="", L28=""), "[Aviso] Género no capturado ()", IF(ISNA(MATCH(L28, Criterios!$B$123:$B$127, 0)), "Género no válido", "")), IF(OR(N28="", N28=""), "[Aviso] Temporada no capturada ()", IF(ISNA(MATCH(N28, Criterios!$C$123:$C$128, 0)), "Temporada no válida", "")), IF(OR(O28="", O28=""), "[Aviso] Ciclo de vida no capturado ()", IF(ISNA(MATCH(O28, Criterios!$D$123:$D$124, 0)), "Ciclo de vida no válido", "")))) | AD28: 3 | AE28: WB OUTLET LERMA: 3 | AF28: 3 | AG28: Nuevo – NetSuite con existencia | AH28: Revisión 29/09/2026: Campos sin respaldo: X; Auditoría NetSuite 30/09/2026: llenado desde NetSuite [P,V,Y,T] | 01/10/2026: complementado desde Shopify Western Brothers (match por código de barras): WB Silueta | AI28: No | AK28: ProductosCatalogoEstandar907.xlsx: fila 8 [N,O,Q,S,U,Y]; G1522_Extraccion_Articulos_NetSuite_2026-09-30.xlsx: fila 56545 [P,V,Y,T] | Shopify WB: producto 8569956663481 / variante 47621316673721 | AL28: 419 | AM28: 1099 | AN28: Shopify Western Brothers | AP28: 3 | AR28: Shopify Western Brothers › Western Brothers Outlet Lerma: 3
A29: 7506499531047 | B29: 108387 | C29: Multimarca | D29: A-CHH180 | E29: A-CHH180-M | F29: M | G29: M | H29: Denver | I29: Camisa Denver caballero estampado biznaga negra | J29: Ropa | K29: Camisas | L29: Hombre | M29: Denver | N29: SS26 | O29: Core | P29: Negro | Q29: Regular | S29: 100% Algodón | T29: Camisa Denver caballero estampado biznaga negra Regular | U29: México | V29: PZS | W29: 53101602 | Y29: 419 | Z29: 947.41379 | AA29: =IF(AND(A29="", B29="", E29=""), "", IF(AB29="", "Válido", IF((LEN(AB29)-LEN(SUBSTITUTE(AB29,"; ","")))/2+1>(LEN(AB29)-LEN(SUBSTITUTE(AB29,"[Aviso]","")))/7, "Con Incidencias", "Válido"))) | AB29: =IF(AND(A29="", B29="", E29=""), "", TEXTJOIN("; ", TRUE, IF(OR(TRIM(A29&"")="", ISNUMBER(SEARCH("FALTA", A29))), "UPC faltante/inválido", ""), IF(AND(A29<>"", IFERROR(_xlfn.XMATCH(A29,$A$2:$A$204,0,1)<>_xlfn.XMATCH(A29,$A$2:$A$204,0,-1),FALSE)), "Código de barras duplicado", ""), IF(AND(E29<>"", COUNTIF($E$2:$E$204, E29)>1), "SKU duplicado", ""), IF(OR(J29="", J29=""), "[Aviso] División no capturada ()", IF(ISNA(MATCH(J29, Criterios!$A$123:$A$126, 0)), "División no válida", "")), IF(OR(K29="", K29=""), "[Aviso] Categoría no capturada ()", IF(ISNA(MATCH(K29, Criterios!$A$81:$A$120, 0)), "Categoría no válida", IF(AND(J29<>"", J29<>"", J29<>VLOOKUP(K29, Criterios!$A$81:$B$120, 2, FALSE)), "División no coincide con Categoría", ""))), IF(OR(L29="", L29=""), "[Aviso] Género no capturado ()", IF(ISNA(MATCH(L29, Criterios!$B$123:$B$127, 0)), "Género no válido", "")), IF(OR(N29="", N29=""), "[Aviso] Temporada no capturada ()", IF(ISNA(MATCH(N29, Criterios!$C$123:$C$128, 0)), "Temporada no válida", "")), IF(OR(O29="", O29=""), "[Aviso] Ciclo de vida no capturado ()", IF(ISNA(MATCH(O29, Criterios!$D$123:$D$124, 0)), "Ciclo de vida no válido", "")))) | AD29: 3 | AE29: WB OUTLET LERMA: 3 | AF29: 3 | AG29: Nuevo – NetSuite con existencia | AH29: Revisión 29/09/2026: Campos sin respaldo: X; Auditoría NetSuite 30/09/2026: llenado desde NetSuite [P,V,Y,T] | 01/10/2026: complementado desde Shopify Western Brothers (match por código de barras): WB Silueta | AI29: No | AK29: ProductosCatalogoEstandar907.xlsx: fila 11 [N,O,Q,S,U,Y]; G1522_Extraccion_Articulos_NetSuite_2026-09-30.xlsx: fila 56546 [P,V,Y,T] | Shopify WB: producto 8569956663481 / variante 47621316772025 | AL29: 419 | AM29: 1099 | AN29: Shopify Western Brothers | AP29: 3 | AR29: Shopify Western Brothers › Western Brothers Outlet Lerma: 3
A30: 7506499530453 | B30: 108388 | C30: Multimarca | D30: A-CHH180 | E30: A-CHH180-L | F30: L | G30: L | H30: Denver | I30: Camisa Denver caballero estampado biznaga negra | J30: Ropa | K30: Camisas | L30: Hombre | M30: Denver | N30: SS26 | O30: Core | P30: Negro | Q30: Regular | S30: 100% Algodón | T30: Camisa Denver caballero estampado biznaga negra Regular | U30: México | V30: PZS | W30: 53101602 | Y30: 419 | Z30: 947.41379 | AA30: =IF(AND(A30="", B30="", E30=""), "", IF(AB30="", "Válido", IF((LEN(AB30)-LEN(SUBSTITUTE(AB30,"; ","")))/2+1>(LEN(AB30)-LEN(SUBSTITUTE(AB30,"[Aviso]","")))/7, "Con Incidencias", "Válido"))) | AB30: =IF(AND(A30="", B30="", E30=""), "", TEXTJOIN("; ", TRUE, IF(OR(TRIM(A30&"")="", ISNUMBER(SEARCH("FALTA", A30))), "UPC faltante/inválido", ""), IF(AND(A30<>"", IFERROR(_xlfn.XMATCH(A30,$A$2:$A$204,0,1)<>_xlfn.XMATCH(A30,$A$2:$A$204,0,-1),FALSE)), "Código de barras duplicado", ""), IF(AND(E30<>"", COUNTIF($E$2:$E$204, E30)>1), "SKU duplicado", ""), IF(OR(J30="", J30=""), "[Aviso] División no capturada ()", IF(ISNA(MATCH(J30, Criterios!$A$123:$A$126, 0)), "División no válida", "")), IF(OR(K30="", K30=""), "[Aviso] Categoría no capturada ()", IF(ISNA(MATCH(K30, Criterios!$A$81:$A$120, 0)), "Categoría no válida", IF(AND(J30<>"", J30<>"", J30<>VLOOKUP(K30, Criterios!$A$81:$B$120, 2, FALSE)), "División no coincide con Categoría", ""))), IF(OR(L30="", L30=""), "[Aviso] Género no capturado ()", IF(ISNA(MATCH(L30, Criterios!$B$123:$B$127, 0)), "Género no válido", "")), IF(OR(N30="", N30=""), "[Aviso] Temporada no capturada ()", IF(ISNA(MATCH(N30, Criterios!$C$123:$C$128, 0)), "Temporada no válida", "")), IF(OR(O30="", O30=""), "[Aviso] Ciclo de vida no capturado ()", IF(ISNA(MATCH(O30, Criterios!$D$123:$D$124, 0)), "Ciclo de vida no válido", "")))) | AD30: 0 | AF30: 0 | AG30: Nuevo – NetSuite sin existencia | AH30: Revisión 29/09/2026: Campos sin respaldo: X; Auditoría NetSuite 30/09/2026: llenado desde NetSuite [P,V,Y,T] | 01/10/2026: complementado desde Shopify Western Brothers (match por código de barras): WB Silueta | AI30: No | AK30: ProductosCatalogoEstandar907.xlsx: fila 9 [N,O,Q,S,U,Y]; G1522_Extraccion_Articulos_NetSuite_2026-09-30.xlsx: fila 56547 [P,V,Y,T] | Shopify WB: producto 8569956663481 / variante 47621316706489 | AL30: 419 | AM30: 1099 | AN30: Shopify Western Brothers | AP30: 0
A31: 7506499530460 | B31: 108389 | C31: Multimarca | D31: A-CHH180 | E31: A-CHH180-XL | F31: XL | G31: XL | H31: Denver | I31: Camisa Denver caballero estampado biznaga negra | J31: Ropa | K31: Camisas | L31: Hombre | M31: Denver | N31: SS26 | O31: Core | P31: Negro | Q31: Regular | S31: 100% Algodón | T31: Camisa Denver caballero estampado biznaga negra Regular | U31: México | V31: PZS | W31: 53101602 | Y31: 419 | Z31: 947.41379 | AA31: =IF(AND(A31="", B31="", E31=""), "", IF(AB31="", "Válido", IF((LEN(AB31)-LEN(SUBSTITUTE(AB31,"; ","")))/2+1>(LEN(AB31)-LEN(SUBSTITUTE(AB31,"[Aviso]","")))/7, "Con Incidencias", "Válido"))) | AB31: =IF(AND(A31="", B31="", E31=""), "", TEXTJOIN("; ", TRUE, IF(OR(TRIM(A31&"")="", ISNUMBER(SEARCH("FALTA", A31))), "UPC faltante/inválido", ""), IF(AND(A31<>"", IFERROR(_xlfn.XMATCH(A31,$A$2:$A$204,0,1)<>_xlfn.XMATCH(A31,$A$2:$A$204,0,-1),FALSE)), "Código de barras duplicado", ""), IF(AND(E31<>"", COUNTIF($E$2:$E$204, E31)>1), "SKU duplicado", ""), IF(OR(J31="", J31=""), "[Aviso] División no capturada ()", IF(ISNA(MATCH(J31, Criterios!$A$123:$A$126, 0)), "División no válida", "")), IF(OR(K31="", K31=""), "[Aviso] Categoría no capturada ()", IF(ISNA(MATCH(K31, Criterios!$A$81:$A$120, 0)), "Categoría no válida", IF(AND(J31<>"", J31<>"", J31<>VLOOKUP(K31, Criterios!$A$81:$B$120, 2, FALSE)), "División no coincide con Categoría", ""))), IF(OR(L31="", L31=""), "[Aviso] Género no capturado ()", IF(ISNA(MATCH(L31, Criterios!$B$123:$B$127, 0)), "Género no válido", "")), IF(OR(N31="", N31=""), "[Aviso] Temporada no capturada ()", IF(ISNA(MATCH(N31, Criterios!$C$123:$C$128, 0)), "Temporada no válida", "")), IF(OR(O31="", O31=""), "[Aviso] Ciclo de vida no capturado ()", IF(ISNA(MATCH(O31, Criterios!$D$123:$D$124, 0)), "Ciclo de vida no válido", "")))) | AD31: 0 | AF31: 0 | AG31: Nuevo – NetSuite sin existencia | AH31: Revisión 29/09/2026: Campos sin respaldo: X; Auditoría NetSuite 30/09/2026: llenado desde NetSuite [P,V,Y,T] | 01/10/2026: complementado desde Shopify Western Brothers (match por código de barras): WB Silueta | AI31: No | AK31: ProductosCatalogoEstandar907.xlsx: fila 10 [N,O,Q,S,U,Y]; G1522_Extraccion_Articulos_NetSuite_2026-09-30.xlsx: fila 56548 [P,V,Y,T] | Shopify WB: producto 8569956663481 / variante 47621316739257 | AL31: 419 | AM31: 1099 | AN31: Shopify Western Brothers | AP31: 0
A32: 7506499531184 | B32: 108390 | C32: Multimarca | D32: A-CHH185 | E32: A-CHH185-S | F32: S | G32: S | H32: Denver | I32: Camisa Denver caballero estampado nopal en verde | J32: Ropa | K32: Camisas | L32: Hombre | M32: Denver | N32: SS26 | O32: Seasonal | P32: Verde | Q32: Regular | S32: 100% Algodón | T32: Camisa Denver caballero estampado nopal en verde Regular | U32: México | V32: PZS | W32: 53101602 | Y32: 419 | Z32: 947.41379 | AA32: =IF(AND(A32="", B32="", E32=""), "", IF(AB32="", "Válido", IF((LEN(AB32)-LEN(SUBSTITUTE(AB32,"; ","")))/2+1>(LEN(AB32)-LEN(SUBSTITUTE(AB32,"[Aviso]","")))/7, "Con Incidencias", "Válido"))) | AB32: =IF(AND(A32="", B32="", E32=""), "", TEXTJOIN("; ", TRUE, IF(OR(TRIM(A32&"")="", ISNUMBER(SEARCH("FALTA", A32))), "UPC faltante/inválido", ""), IF(AND(A32<>"", IFERROR(_xlfn.XMATCH(A32,$A$2:$A$204,0,1)<>_xlfn.XMATCH(A32,$A$2:$A$204,0,-1),FALSE)), "Código de barras duplicado", ""), IF(AND(E32<>"", COUNTIF($E$2:$E$204, E32)>1), "SKU duplicado", ""), IF(OR(J32="", J32=""), "[Aviso] División no capturada ()", IF(ISNA(MATCH(J32, Criterios!$A$123:$A$126, 0)), "División no válida", "")), IF(OR(K32="", K32=""), "[Aviso] Categoría no capturada ()", IF(ISNA(MATCH(K32, Criterios!$A$81:$A$120, 0)), "Categoría no válida", IF(AND(J32<>"", J32<>"", J32<>VLOOKUP(K32, Criterios!$A$81:$B$120, 2, FALSE)), "División no coincide con Categoría", ""))), IF(OR(L32="", L32=""), "[Aviso] Género no capturado ()", IF(ISNA(MATCH(L32, Criterios!$B$123:$B$127, 0)), "Género no válido", "")), IF(OR(N32="", N32=""), "[Aviso] Temporada no capturada ()", IF(ISNA(MATCH(N32, Criterios!$C$123:$C$128, 0)), "Temporada no válida", "")), IF(OR(O32="", O32=""), "[Aviso] Ciclo de vida no capturado ()", IF(ISNA(MATCH(O32, Criterios!$D$123:$D$124, 0)), "Ciclo de vida no válido", "")))) | AD32: 3 | AE32: WB OUTLET LERMA: 3 | AF32: 3 | AG32: Nuevo – NetSuite con existencia | AH32: Revisión 29/09/2026: Campos sin respaldo: X; Auditoría NetSuite 30/09/2026: llenado desde NetSuite [P,V,Y,T] | 01/10/2026: complementado desde Shopify Western Brothers (match por código de barras): WB Silueta | AI32: No | AK32: ProductosCatalogoEstandar907.xlsx: fila 13 [N,O,Q,S,U,Y]; G1522_Extraccion_Articulos_NetSuite_2026-09-30.xlsx: fila 56549 [P,V,Y,T] | Shopify WB: producto 8569956827321 / variante 47621316968633 | AL32: 419 | AM32: 1099 | AN32: Shopify Western Brothers | AP32: 3 | AR32: Shopify Western Brothers › Western Brothers Outlet Lerma: 3
A33: 7506499530699 | B33: 108391 | C33: Multimarca | D33: A-CHH185 | E33: A-CHH185-M | F33: M | G33: M | H33: Denver | I33: Camisa Denver caballero estampado nopal en verde | J33: Ropa | K33: Camisas | L33: Hombre | M33: Denver | N33: SS26 | O33: Seasonal | P33: Verde | Q33: Regular | S33: 100% Algodón | T33: Camisa Denver caballero estampado nopal en verde Regular | U33: México | V33: PZS | W33: 53101602 | Y33: 419 | Z33: 947.41379 | AA33: =IF(AND(A33="", B33="", E33=""), "", IF(AB33="", "Válido", IF((LEN(AB33)-LEN(SUBSTITUTE(AB33,"; ","")))/2+1>(LEN(AB33)-LEN(SUBSTITUTE(AB33,"[Aviso]","")))/7, "Con Incidencias", "Válido"))) | AB33: =IF(AND(A33="", B33="", E33=""), "", TEXTJOIN("; ", TRUE, IF(OR(TRIM(A33&"")="", ISNUMBER(SEARCH("FALTA", A33))), "UPC faltante/inválido", ""), IF(AND(A33<>"", IFERROR(_xlfn.XMATCH(A33,$A$2:$A$204,0,1)<>_xlfn.XMATCH(A33,$A$2:$A$204,0,-1),FALSE)), "Código de barras duplicado", ""), IF(AND(E33<>"", COUNTIF($E$2:$E$204, E33)>1), "SKU duplicado", ""), IF(OR(J33="", J33=""), "[Aviso] División no capturada ()", IF(ISNA(MATCH(J33, Criterios!$A$123:$A$126, 0)), "División no válida", "")), IF(OR(K33="", K33=""), "[Aviso] Categoría no capturada ()", IF(ISNA(MATCH(K33, Criterios!$A$81:$A$120, 0)), "Categoría no válida", IF(AND(J33<>"", J33<>"", J33<>VLOOKUP(K33, Criterios!$A$81:$B$120, 2, FALSE)), "División no coincide con Categoría", ""))), IF(OR(L33="", L33=""), "[Aviso] Género no capturado ()", IF(ISNA(MATCH(L33, Criterios!$B$123:$B$127, 0)), "Género no válido", "")), IF(OR(N33="", N33=""), "[Aviso] Temporada no capturada ()", IF(ISNA(MATCH(N33, Criterios!$C$123:$C$128, 0)), "Temporada no válida", "")), IF(OR(O33="", O33=""), "[Aviso] Ciclo de vida no capturado ()", IF(ISNA(MATCH(O33, Criterios!$D$123:$D$124, 0)), "Ciclo de vida no válido", "")))) | AD33: 0 | AF33: 0 | AG33: Nuevo – NetSuite sin existencia | AH33: Revisión 29/09/2026: Campos sin respaldo: X; Auditoría NetSuite 30/09/2026: llenado desde NetSuite [P,V,Y,T] | 01/10/2026: complementado desde Shopify Western Brothers (match por código de barras): WB Silueta | AI33: No | AK33: ProductosCatalogoEstandar907.xlsx: fila 12 [N,O,Q,S,U,Y]; G1522_Extraccion_Articulos_NetSuite_2026-09-30.xlsx: fila 56550 [P,V,Y,T] | Shopify WB: producto 8569956827321 / variante 47621316935865 | AL33: 419 | AM33: 1099 | AN33: Shopify Western Brothers | AP33: 0
A34: 7506499531214 | B34: 108392 | C34: Multimarca | D34: A-CHH185 | E34: A-CHH185-XL | F34: XL | G34: XL | H34: Denver | I34: Camisa Denver caballero estampado nopal en verde | J34: Ropa | K34: Camisas | L34: Hombre | M34: Denver | N34: SS26 | O34: Seasonal | P34: Verde | Q34: Regular | S34: 100% Algodón | T34: Camisa Denver caballero estampado nopal en verde Regular | U34: México | V34: PZS | W34: 53101602 | Y34: 419 | Z34: 947.41379 | AA34: =IF(AND(A34="", B34="", E34=""), "", IF(AB34="", "Válido", IF((LEN(AB34)-LEN(SUBSTITUTE(AB34,"; ","")))/2+1>(LEN(AB34)-LEN(SUBSTITUTE(AB34,"[Aviso]","")))/7, "Con Incidencias", "Válido"))) | AB34: =IF(AND(A34="", B34="", E34=""), "", TEXTJOIN("; ", TRUE, IF(OR(TRIM(A34&"")="", ISNUMBER(SEARCH("FALTA", A34))), "UPC faltante/inválido", ""), IF(AND(A34<>"", IFERROR(_xlfn.XMATCH(A34,$A$2:$A$204,0,1)<>_xlfn.XMATCH(A34,$A$2:$A$204,0,-1),FALSE)), "Código de barras duplicado", ""), IF(AND(E34<>"", COUNTIF($E$2:$E$204, E34)>1), "SKU duplicado", ""), IF(OR(J34="", J34=""), "[Aviso] División no capturada ()", IF(ISNA(MATCH(J34, Criterios!$A$123:$A$126, 0)), "División no válida", "")), IF(OR(K34="", K34=""), "[Aviso] Categoría no capturada ()", IF(ISNA(MATCH(K34, Criterios!$A$81:$A$120, 0)), "Categoría no válida", IF(AND(J34<>"", J34<>"", J34<>VLOOKUP(K34, Criterios!$A$81:$B$120, 2, FALSE)), "División no coincide con Categoría", ""))), IF(OR(L34="", L34=""), "[Aviso] Género no capturado ()", IF(ISNA(MATCH(L34, Criterios!$B$123:$B$127, 0)), "Género no válido", "")), IF(OR(N34="", N34=""), "[Aviso] Temporada no capturada ()", IF(ISNA(MATCH(N34, Criterios!$C$123:$C$128, 0)), "Temporada no válida", "")), IF(OR(O34="", O34=""), "[Aviso] Ciclo de vida no capturado ()", IF(ISNA(MATCH(O34, Criterios!$D$123:$D$124, 0)), "Ciclo de vida no válido", "")))) | AD34: 0 | AF34: 0 | AG34: Nuevo – NetSuite sin existencia | AH34: Revisión 29/09/2026: Campos sin respaldo: X; Auditoría NetSuite 30/09/2026: llenado desde NetSuite [P,V,Y,T] | 01/10/2026: complementado desde Shopify Western Brothers (match por código de barras): WB Silueta | AI34: No | AK34: ProductosCatalogoEstandar907.xlsx: fila 14 [N,O,Q,S,U,Y]; G1522_Extraccion_Articulos_NetSuite_2026-09-30.xlsx: fila 56551 [P,V,Y,T] | Shopify WB: producto 8569956827321 / variante 47621317001401 | AL34: 419 | AM34: 1099 | AN34: Shopify Western Brothers | AP34: 0
A35: 7506499550376 | B35: 108393 | C35: Multimarca | D35: A-CHH206 | E35: A-CHH206-S | F35: S | G35: S | H35: Denver | I35: Camisa Denver caballero mosaico estrella en azul | J35: Ropa | K35: Camisas | L35: Hombre | M35: Denver | N35: SS26 | O35: Seasonal | P35: Azul | Q35: Regular | S35: 100% Algodón | T35: Camisa Denver caballero mosaico estrella en azul Regular | U35: México | V35: PZS | W35: 53101602 | Y35: 419 | Z35: 947.41379 | AA35: =IF(AND(A35="", B35="", E35=""), "", IF(AB35="", "Válido", IF((LEN(AB35)-LEN(SUBSTITUTE(AB35,"; ","")))/2+1>(LEN(AB35)-LEN(SUBSTITUTE(AB35,"[Aviso]","")))/7, "Con Incidencias", "Válido"))) | AB35: =IF(AND(A35="", B35="", E35=""), "", TEXTJOIN("; ", TRUE, IF(OR(TRIM(A35&"")="", ISNUMBER(SEARCH("FALTA", A35))), "UPC faltante/inválido", ""), IF(AND(A35<>"", IFERROR(_xlfn.XMATCH(A35,$A$2:$A$204,0,1)<>_xlfn.XMATCH(A35,$A$2:$A$204,0,-1),FALSE)), "Código de barras duplicado", ""), IF(AND(E35<>"", COUNTIF($E$2:$E$204, E35)>1), "SKU duplicado", ""), IF(OR(J35="", J35=""), "[Aviso] División no capturada ()", IF(ISNA(MATCH(J35, Criterios!$A$123:$A$126, 0)), "División no válida", "")), IF(OR(K35="", K35=""), "[Aviso] Categoría no capturada ()", IF(ISNA(MATCH(K35, Criterios!$A$81:$A$120, 0)), "Categoría no válida", IF(AND(J35<>"", J35<>"", J35<>VLOOKUP(K35, Criterios!$A$81:$B$120, 2, FALSE)), "División no coincide con Categoría", ""))), IF(OR(L35="", L35=""), "[Aviso] Género no capturado ()", IF(ISNA(MATCH(L35, Criterios!$B$123:$B$127, 0)), "Género no válido", "")), IF(OR(N35="", N35=""), "[Aviso] Temporada no capturada ()", IF(ISNA(MATCH(N35, Criterios!$C$123:$C$128, 0)), "Temporada no válida", "")), IF(OR(O35="", O35=""), "[Aviso] Ciclo de vida no capturado ()", IF(ISNA(MATCH(O35, Criterios!$D$123:$D$124, 0)), "Ciclo de vida no válido", "")))) | AD35: 4 | AE35: WB OUTLET LERMA: 4 | AF35: 4 | AG35: Nuevo – NetSuite con existencia | AH35: Revisión 29/09/2026: Campos sin respaldo: X; Auditoría NetSuite 30/09/2026: llenado desde NetSuite [P,V,Y,T] | 01/10/2026: complementado desde Shopify Western Brothers (match por código de barras): WB Silueta | AI35: No | AK35: ProductosCatalogoEstandar907.xlsx: fila 15 [N,O,Q,S,U,Y]; G1522_Extraccion_Articulos_NetSuite_2026-09-30.xlsx: fila 56552 [P,V,Y,T] | Shopify WB: producto 8569956991161 / variante 47621317165241 | AL35: 419 | AM35: 1099 | AN35: Shopify Western Brothers | AP35: 4 | AR35: Shopify Western Brothers › Western Brothers Outlet Lerma: 4
A36: 7506499550383 | B36: 108394 | C36: Multimarca | D36: A-CHH206 | E36: A-CHH206-M | F36: M | G36: M | H36: Denver | I36: Camisa Denver caballero mosaico estrella en azul | J36: Ropa | K36: Camisas | L36: Hombre | M36: Denver | N36: SS26 | O36: Seasonal | P36: Azul | Q36: Regular | S36: 100% Algodón | T36: Camisa Denver caballero mosaico estrella en azul Regular | U36: México | V36: PZS | W36: 53101602 | Y36: 419 | Z36: 947.41379 | AA36: =IF(AND(A36="", B36="", E36=""), "", IF(AB36="", "Válido", IF((LEN(AB36)-LEN(SUBSTITUTE(AB36,"; ","")))/2+1>(LEN(AB36)-LEN(SUBSTITUTE(AB36,"[Aviso]","")))/7, "Con Incidencias", "Válido"))) | AB36: =IF(AND(A36="", B36="", E36=""), "", TEXTJOIN("; ", TRUE, IF(OR(TRIM(A36&"")="", ISNUMBER(SEARCH("FALTA", A36))), "UPC faltante/inválido", ""), IF(AND(A36<>"", IFERROR(_xlfn.XMATCH(A36,$A$2:$A$204,0,1)<>_xlfn.XMATCH(A36,$A$2:$A$204,0,-1),FALSE)), "Código de barras duplicado", ""), IF(AND(E36<>"", COUNTIF($E$2:$E$204, E36)>1), "SKU duplicado", ""), IF(OR(J36="", J36=""), "[Aviso] División no capturada ()", IF(ISNA(MATCH(J36, Criterios!$A$123:$A$126, 0)), "División no válida", "")), IF(OR(K36="", K36=""), "[Aviso] Categoría no capturada ()", IF(ISNA(MATCH(K36, Criterios!$A$81:$A$120, 0)), "Categoría no válida", IF(AND(J36<>"", J36<>"", J36<>VLOOKUP(K36, Criterios!$A$81:$B$120, 2, FALSE)), "División no coincide con Categoría", ""))), IF(OR(L36="", L36=""), "[Aviso] Género no capturado ()", IF(ISNA(MATCH(L36, Criterios!$B$123:$B$127, 0)), "Género no válido", "")), IF(OR(N36="", N36=""), "[Aviso] Temporada no capturada ()", IF(ISNA(MATCH(N36, Criterios!$C$123:$C$128, 0)), "Temporada no válida", "")), IF(OR(O36="", O36=""), "[Aviso] Ciclo de vida no capturado ()", IF(ISNA(MATCH(O36, Criterios!$D$123:$D$124, 0)), "Ciclo de vida no válido", "")))) | AD36: 4 | AE36: WB OUTLET LERMA: 4 | AF36: 4 | AG36: Nuevo – NetSuite con existencia | AH36: Revisión 29/09/2026: Campos sin respaldo: X; Auditoría NetSuite 30/09/2026: llenado desde NetSuite [P,V,Y,T] | 01/10/2026: complementado desde Shopify Western Brothers (match por código de barras): WB Silueta | AI36: No | AK36: ProductosCatalogoEstandar907.xlsx: fila 16 [N,O,Q,S,U,Y]; G1522_Extraccion_Articulos_NetSuite_2026-09-30.xlsx: fila 56553 [P,V,Y,T] | Shopify WB: producto 8569956991161 / variante 47621317198009 | AL36: 419 | AM36: 1099 | AN36: Shopify Western Brothers | AP36: 4 | AR36: Shopify Western Brothers › Western Brothers Outlet Lerma: 4
A37: 7506499550390 | B37: 108395 | C37: Multimarca | D37: A-CHH206 | E37: A-CHH206-L | F37: L | G37: L | H37: Denver | I37: Camisa Denver caballero mosaico estrella en azul | J37: Ropa | K37: Camisas | L37: Hombre | M37: Denver | N37: SS26 | O37: Seasonal | P37: Azul | Q37: Regular | S37: 100% Algodón | T37: Camisa Denver caballero mosaico estrella en azul Regular | U37: México | V37: PZS | W37: 53101602 | Y37: 419 | Z37: 947.41379 | AA37: =IF(AND(A37="", B37="", E37=""), "", IF(AB37="", "Válido", IF((LEN(AB37)-LEN(SUBSTITUTE(AB37,"; ","")))/2+1>(LEN(AB37)-LEN(SUBSTITUTE(AB37,"[Aviso]","")))/7, "Con Incidencias", "Válido"))) | AB37: =IF(AND(A37="", B37="", E37=""), "", TEXTJOIN("; ", TRUE, IF(OR(TRIM(A37&"")="", ISNUMBER(SEARCH("FALTA", A37))), "UPC faltante/inválido", ""), IF(AND(A37<>"", IFERROR(_xlfn.XMATCH(A37,$A$2:$A$204,0,1)<>_xlfn.XMATCH(A37,$A$2:$A$204,0,-1),FALSE)), "Código de barras duplicado", ""), IF(AND(E37<>"", COUNTIF($E$2:$E$204, E37)>1), "SKU duplicado", ""), IF(OR(J37="", J37=""), "[Aviso] División no capturada ()", IF(ISNA(MATCH(J37, Criterios!$A$123:$A$126, 0)), "División no válida", "")), IF(OR(K37="", K37=""), "[Aviso] Categoría no capturada ()", IF(ISNA(MATCH(K37, Criterios!$A$81:$A$120, 0)), "Categoría no válida", IF(AND(J37<>"", J37<>"", J37<>VLOOKUP(K37, Criterios!$A$81:$B$120, 2, FALSE)), "División no coincide con Categoría", ""))), IF(OR(L37="", L37=""), "[Aviso] Género no capturado ()", IF(ISNA(MATCH(L37, Criterios!$B$123:$B$127, 0)), "Género no válido", "")), IF(OR(N37="", N37=""), "[Aviso] Temporada no capturada ()", IF(ISNA(MATCH(N37, Criterios!$C$123:$C$128, 0)), "Temporada no válida", "")), IF(OR(O37="", O37=""), "[Aviso] Ciclo de vida no capturado ()", IF(ISNA(MATCH(O37, Criterios!$D$123:$D$124, 0)), "Ciclo de vida no válido", "")))) | AD37: 2 | AE37: WB OUTLET LERMA: 2 | AF37: 2 | AG37: Nuevo – NetSuite con existencia | AH37: Revisión 29/09/2026: Campos sin respaldo: X; Auditoría NetSuite 30/09/2026: llenado desde NetSuite [P,V,Y,T] | 01/10/2026: complementado desde Shopify Western Brothers (match por código de barras): WB Silueta | AI37: No | AK37: ProductosCatalogoEstandar907.xlsx: fila 17 [N,O,Q,S,U,Y]; G1522_Extraccion_Articulos_NetSuite_2026-09-30.xlsx: fila 56554 [P,V,Y,T] | Shopify WB: producto 8569956991161 / variante 47621317230777 | AL37: 419 | AM37: 1099 | AN37: Shopify Western Brothers | AP37: 3 | AR37: Shopify Western Brothers › Western Brothers Outlet Lerma: 3
A38: 7506499550406 | B38: 108396 | C38: Multimarca | D38: A-CHH206 | E38: A-CHH206-XL | F38: XL | G38: XL | H38: Denver | I38: Camisa Denver caballero mosaico estrella en azul | J38: Ropa | K38: Camisas | L38: Hombre | M38: Denver | N38: SS26 | O38: Seasonal | P38: Azul | Q38: Regular | S38: 100% Algodón | T38: Camisa Denver caballero mosaico estrella en azul Regular | U38: México | V38: PZS | W38: 53101602 | Y38: 419 | Z38: 947.41379 | AA38: =IF(AND(A38="", B38="", E38=""), "", IF(AB38="", "Válido", IF((LEN(AB38)-LEN(SUBSTITUTE(AB38,"; ","")))/2+1>(LEN(AB38)-LEN(SUBSTITUTE(AB38,"[Aviso]","")))/7, "Con Incidencias", "Válido"))) | AB38: =IF(AND(A38="", B38="", E38=""), "", TEXTJOIN("; ", TRUE, IF(OR(TRIM(A38&"")="", ISNUMBER(SEARCH("FALTA", A38))), "UPC faltante/inválido", ""), IF(AND(A38<>"", IFERROR(_xlfn.XMATCH(A38,$A$2:$A$204,0,1)<>_xlfn.XMATCH(A38,$A$2:$A$204,0,-1),FALSE)), "Código de barras duplicado", ""), IF(AND(E38<>"", COUNTIF($E$2:$E$204, E38)>1), "SKU duplicado", ""), IF(OR(J38="", J38=""), "[Aviso] División no capturada ()", IF(ISNA(MATCH(J38, Criterios!$A$123:$A$126, 0)), "División no válida", "")), IF(OR(K38="", K38=""), "[Aviso] Categoría no capturada ()", IF(ISNA(MATCH(K38, Criterios!$A$81:$A$120, 0)), "Categoría no válida", IF(AND(J38<>"", J38<>"", J38<>VLOOKUP(K38, Criterios!$A$81:$B$120, 2, FALSE)), "División no coincide con Categoría", ""))), IF(OR(L38="", L38=""), "[Aviso] Género no capturado ()", IF(ISNA(MATCH(L38, Criterios!$B$123:$B$127, 0)), "Género no válido", "")), IF(OR(N38="", N38=""), "[Aviso] Temporada no capturada ()", IF(ISNA(MATCH(N38, Criterios!$C$123:$C$128, 0)), "Temporada no válida", "")), IF(OR(O38="", O38=""), "[Aviso] Ciclo de vida no capturado ()", IF(ISNA(MATCH(O38, Criterios!$D$123:$D$124, 0)), "Ciclo de vida no válido", "")))) | AD38: 2 | AE38: WB OUTLET LERMA: 2 | AF38: 2 | AG38: Nuevo – NetSuite con existencia | AH38: Revisión 29/09/2026: Campos sin respaldo: X; Auditoría NetSuite 30/09/2026: llenado desde NetSuite [P,V,Y,T] | 01/10/2026: complementado desde Shopify Western Brothers (match por código de barras): WB Silueta | AI38: No | AK38: ProductosCatalogoEstandar907.xlsx: fila 18 [N,O,Q,S,U,Y]; G1522_Extraccion_Articulos_NetSuite_2026-09-30.xlsx: fila 56555 [P,V,Y,T] | Shopify WB: producto 8569956991161 / variante 47621317263545 | AL38: 419 | AM38: 1099 | AN38: Shopify Western Brothers | AP38: 2 | AR38: Shopify Western Brothers › Western Brothers Outlet Lerma: 2
A39: 7506499526456 | B39: 108397 | C39: Multimarca | D39: A-CM126 | E39: A-CM126-XS | F39: XS | G39: XS | H39: Denver | I39: Camisa Denver dama flores amarillo | J39: Ropa | K39: Camisas | L39: Mujer | M39: Denver | N39: SS26 | O39: Seasonal | P39: Amarillo | Q39: Regular | S39: 100% Rayón | T39: Camisa Denver dama flores amarillo Regular | U39: México | V39: PZS | W39: 53101604 | Y39: 336 | Z39: 775 | AA39: =IF(AND(A39="", B39="", E39=""), "", IF(AB39="", "Válido", IF((LEN(AB39)-LEN(SUBSTITUTE(AB39,"; ","")))/2+1>(LEN(AB39)-LEN(SUBSTITUTE(AB39,"[Aviso]","")))/7, "Con Incidencias", "Válido"))) | AB39: =IF(AND(A39="", B39="", E39=""), "", TEXTJOIN("; ", TRUE, IF(OR(TRIM(A39&"")="", ISNUMBER(SEARCH("FALTA", A39))), "UPC faltante/inválido", ""), IF(AND(A39<>"", IFERROR(_xlfn.XMATCH(A39,$A$2:$A$204,0,1)<>_xlfn.XMATCH(A39,$A$2:$A$204,0,-1),FALSE)), "Código de barras duplicado", ""), IF(AND(E39<>"", COUNTIF($E$2:$E$204, E39)>1), "SKU duplicado", ""), IF(OR(J39="", J39=""), "[Aviso] División no capturada ()", IF(ISNA(MATCH(J39, Criterios!$A$123:$A$126, 0)), "División no válida", "")), IF(OR(K39="", K39=""), "[Aviso] Categoría no capturada ()", IF(ISNA(MATCH(K39, Criterios!$A$81:$A$120, 0)), "Categoría no válida", IF(AND(J39<>"", J39<>"", J39<>VLOOKUP(K39, Criterios!$A$81:$B$120, 2, FALSE)), "División no coincide con Categoría", ""))), IF(OR(L39="", L39=""), "[Aviso] Género no capturado ()", IF(ISNA(MATCH(L39, Criterios!$B$123:$B$127, 0)), "Género no válido", "")), IF(OR(N39="", N39=""), "[Aviso] Temporada no capturada ()", IF(ISNA(MATCH(N39, Criterios!$C$123:$C$128, 0)), "Temporada no válida", "")), IF(OR(O39="", O39=""), "[Aviso] Ciclo de vida no capturado ()", IF(ISNA(MATCH(O39, Criterios!$D$123:$D$124, 0)), "Ciclo de vida no válido", "")))) | AD39: 4 | AE39: WB OUTLET LERMA: 4 | AF39: 4 | AG39: Nuevo – NetSuite con existencia | AH39: Revisión 29/09/2026: Campos sin respaldo: X; Auditoría NetSuite 30/09/2026: llenado desde NetSuite [P,V,Y,T] | 01/10/2026: complementado desde Shopify Western Brothers (match por código de barras): WB Silueta | AI39: No | AK39: ProductosCatalogoEstandar907.xlsx: fila 19 [N,O,Q,S,U,Y]; G1522_Extraccion_Articulos_NetSuite_2026-09-30.xlsx: fila 56556 [P,V,Y,T] | Shopify WB: producto 8569957286073 / variante 47621317623993 | AL39: 336 | AM39: 899 | AN39: Shopify Western Brothers | AP39: 4 | AR39: Shopify Western Brothers › Western Brothers Outlet Lerma: 4
A40: 7506499526463 | B40: 108398 | C40: Multimarca | D40: A-CM126 | E40: A-CM126-S | F40: S | G40: S | H40: Denver | I40: Camisa Denver dama flores amarillo | J40: Ropa | K40: Camisas | L40: Mujer | M40: Denver | N40: SS26 | O40: Seasonal | P40: Amarillo | Q40: Regular | S40: 100% Rayón | T40: Camisa Denver dama flores amarillo Regular | U40: México | V40: PZS | W40: 53101604 | Y40: 336 | Z40: 775 | AA40: =IF(AND(A40="", B40="", E40=""), "", IF(AB40="", "Válido", IF((LEN(AB40)-LEN(SUBSTITUTE(AB40,"; ","")))/2+1>(LEN(AB40)-LEN(SUBSTITUTE(AB40,"[Aviso]","")))/7, "Con Incidencias", "Válido"))) | AB40: =IF(AND(A40="", B40="", E40=""), "", TEXTJOIN("; ", TRUE, IF(OR(TRIM(A40&"")="", ISNUMBER(SEARCH("FALTA", A40))), "UPC faltante/inválido", ""), IF(AND(A40<>"", IFERROR(_xlfn.XMATCH(A40,$A$2:$A$204,0,1)<>_xlfn.XMATCH(A40,$A$2:$A$204,0,-1),FALSE)), "Código de barras duplicado", ""), IF(AND(E40<>"", COUNTIF($E$2:$E$204, E40)>1), "SKU duplicado", ""), IF(OR(J40="", J40=""), "[Aviso] División no capturada ()", IF(ISNA(MATCH(J40, Criterios!$A$123:$A$126, 0)), "División no válida", "")), IF(OR(K40="", K40=""), "[Aviso] Categoría no capturada ()", IF(ISNA(MATCH(K40, Criterios!$A$81:$A$120, 0)), "Categoría no válida", IF(AND(J40<>"", J40<>"", J40<>VLOOKUP(K40, Criterios!$A$81:$B$120, 2, FALSE)), "División no coincide con Categoría", ""))), IF(OR(L40="", L40=""), "[Aviso] Género no capturado ()", IF(ISNA(MATCH(L40, Criterios!$B$123:$B$127, 0)), "Género no válido", "")), IF(OR(N40="", N40=""), "[Aviso] Temporada no capturada ()", IF(ISNA(MATCH(N40, Criterios!$C$123:$C$128, 0)), "Temporada no válida", "")), IF(OR(O40="", O40=""), "[Aviso] Ciclo de vida no capturado ()", IF(ISNA(MATCH(O40, Criterios!$D$123:$D$124, 0)), "Ciclo de vida no válido", "")))) | AD40: 3 | AE40: WB OUTLET LERMA: 3 | AF40: 3 | AG40: Nuevo – NetSuite con existencia | AH40: Revisión 29/09/2026: Campos sin respaldo: X; Auditoría NetSuite 30/09/2026: llenado desde NetSuite [P,V,Y,T] | 01/10/2026: complementado desde Shopify Western Brothers (match por código de barras): WB Silueta | AI40: No | AK40: ProductosCatalogoEstandar907.xlsx: fila 20 [N,O,Q,S,U,Y]; G1522_Extraccion_Articulos_NetSuite_2026-09-30.xlsx: fila 56557 [P,V,Y,T] | Shopify WB: producto 8569957286073 / variante 47621317656761 | AL40: 336 | AM40: 899 | AN40: Shopify Western Brothers | AP40: 3 | AR40: Shopify Western Brothers › Western Brothers Outlet Lerma: 3
A41: 7506499526470 | B41: 108399 | C41: Multimarca | D41: A-CM126 | E41: A-CM126-M | F41: M | G41: M | H41: Denver | I41: Camisa Denver dama flores amarillo | J41: Ropa | K41: Camisas | L41: Mujer | M41: Denver | N41: SS26 | O41: Seasonal | P41: Amarillo | Q41: Regular | S41: 100% Rayón | T41: Camisa Denver dama flores amarillo Regular | U41: México | V41: PZS | W41: 53101604 | Y41: 336 | Z41: 775 | AA41: =IF(AND(A41="", B41="", E41=""), "", IF(AB41="", "Válido", IF((LEN(AB41)-LEN(SUBSTITUTE(AB41,"; ","")))/2+1>(LEN(AB41)-LEN(SUBSTITUTE(AB41,"[Aviso]","")))/7, "Con Incidencias", "Válido"))) | AB41: =IF(AND(A41="", B41="", E41=""), "", TEXTJOIN("; ", TRUE, IF(OR(TRIM(A41&"")="", ISNUMBER(SEARCH("FALTA", A41))), "UPC faltante/inválido", ""), IF(AND(A41<>"", IFERROR(_xlfn.XMATCH(A41,$A$2:$A$204,0,1)<>_xlfn.XMATCH(A41,$A$2:$A$204,0,-1),FALSE)), "Código de barras duplicado", ""), IF(AND(E41<>"", COUNTIF($E$2:$E$204, E41)>1), "SKU duplicado", ""), IF(OR(J41="", J41=""), "[Aviso] División no capturada ()", IF(ISNA(MATCH(J41, Criterios!$A$123:$A$126, 0)), "División no válida", "")), IF(OR(K41="", K41=""), "[Aviso] Categoría no capturada ()", IF(ISNA(MATCH(K41, Criterios!$A$81:$A$120, 0)), "Categoría no válida", IF(AND(J41<>"", J41<>"", J41<>VLOOKUP(K41, Criterios!$A$81:$B$120, 2, FALSE)), "División no coincide con Categoría", ""))), IF(OR(L41="", L41=""), "[Aviso] Género no capturado ()", IF(ISNA(MATCH(L41, Criterios!$B$123:$B$127, 0)), "Género no válido", "")), IF(OR(N41="", N41=""), "[Aviso] Temporada no capturada ()", IF(ISNA(MATCH(N41, Criterios!$C$123:$C$128, 0)), "Temporada no válida", "")), IF(OR(O41="", O41=""), "[Aviso] Ciclo de vida no capturado ()", IF(ISNA(MATCH(O41, Criterios!$D$123:$D$124, 0)), "Ciclo de vida no válido", "")))) | AD41: 1 | AE41: WB OUTLET LERMA: 1 | AF41: 1 | AG41: Nuevo – NetSuite con existencia | AH41: Revisión 29/09/2026: Campos sin respaldo: X; Auditoría NetSuite 30/09/2026: llenado desde NetSuite [P,V,Y,T] | 01/10/2026: complementado desde Shopify Western Brothers (match por código de barras): WB Silueta | AI41: No | AK41: ProductosCatalogoEstandar907.xlsx: fila 21 [N,O,Q,S,U,Y]; G1522_Extraccion_Articulos_NetSuite_2026-09-30.xlsx: fila 56558 [P,V,Y,T] | Shopify WB: producto 8569957286073 / variante 47621317689529 | AL41: 336 | AM41: 899 | AN41: Shopify Western Brothers | AP41: 1 | AR41: Shopify Western Brothers › Western Brothers Outlet Lerma: 1
A42: 7506499526487 | B42: 108400 | C42: Multimarca | D42: A-CM126 | E42: A-CM126-L | F42: L | G42: L | H42: Denver | I42: Camisa Denver dama flores amarillo | J42: Ropa | K42: Camisas | L42: Mujer | M42: Denver | N42: SS26 | O42: Seasonal | P42: Amarillo | Q42: Regular | S42: 100% Rayón | T42: Camisa Denver dama flores amarillo Regular | U42: México | V42: PZS | W42: 53101604 | Y42: 336 | Z42: 775 | AA42: =IF(AND(A42="", B42="", E42=""), "", IF(AB42="", "Válido", IF((LEN(AB42)-LEN(SUBSTITUTE(AB42,"; ","")))/2+1>(LEN(AB42)-LEN(SUBSTITUTE(AB42,"[Aviso]","")))/7, "Con Incidencias", "Válido"))) | AB42: =IF(AND(A42="", B42="", E42=""), "", TEXTJOIN("; ", TRUE, IF(OR(TRIM(A42&"")="", ISNUMBER(SEARCH("FALTA", A42))), "UPC faltante/inválido", ""), IF(AND(A42<>"", IFERROR(_xlfn.XMATCH(A42,$A$2:$A$204,0,1)<>_xlfn.XMATCH(A42,$A$2:$A$204,0,-1),FALSE)), "Código de barras duplicado", ""), IF(AND(E42<>"", COUNTIF($E$2:$E$204, E42)>1), "SKU duplicado", ""), IF(OR(J42="", J42=""), "[Aviso] División no capturada ()", IF(ISNA(MATCH(J42, Criterios!$A$123:$A$126, 0)), "División no válida", "")), IF(OR(K42="", K42=""), "[Aviso] Categoría no capturada ()", IF(ISNA(MATCH(K42, Criterios!$A$81:$A$120, 0)), "Categoría no válida", IF(AND(J42<>"", J42<>"", J42<>VLOOKUP(K42, Criterios!$A$81:$B$120, 2, FALSE)), "División no coincide con Categoría", ""))), IF(OR(L42="", L42=""), "[Aviso] Género no capturado ()", IF(ISNA(MATCH(L42, Criterios!$B$123:$B$127, 0)), "Género no válido", "")), IF(OR(N42="", N42=""), "[Aviso] Temporada no capturada ()", IF(ISNA(MATCH(N42, Criterios!$C$123:$C$128, 0)), "Temporada no válida", "")), IF(OR(O42="", O42=""), "[Aviso] Ciclo de vida no capturado ()", IF(ISNA(MATCH(O42, Criterios!$D$123:$D$124, 0)), "Ciclo de vida no válido", "")))) | AD42: 2 | AE42: WB OUTLET LERMA: 2 | AF42: 2 | AG42: Nuevo – NetSuite con existencia | AH42: Revisión 29/09/2026: Campos sin respaldo: X; Auditoría NetSuite 30/09/2026: llenado desde NetSuite [P,V,Y,T] | 01/10/2026: complementado desde Shopify Western Brothers (match por código de barras): WB Silueta | AI42: No | AK42: ProductosCatalogoEstandar907.xlsx: fila 22 [N,O,Q,S,U,Y]; G1522_Extraccion_Articulos_NetSuite_2026-09-30.xlsx: fila 56559 [P,V,Y,T] | Shopify WB: producto 8569957286073 / variante 47621317722297 | AL42: 336 | AM42: 899 | AN42: Shopify Western Brothers | AP42: 2 | AR42: Shopify Western Brothers › Western Brothers Outlet Lerma: 2
A43: 7506499526494 | B43: 108401 | C43: Multimarca | D43: A-CM126 | E43: A-CM126-XL | F43: XL | G43: XL | H43: Denver | I43: Camisa Denver dama flores amarillo | J43: Ropa | K43: Camisas | L43: Mujer | M43: Denver | N43: SS26 | O43: Seasonal | P43: Amarillo | Q43: Regular | S43: 100% Rayón | T43: Camisa Denver dama flores amarillo Regular | U43: México | V43: PZS | W43: 53101604 | Y43: 336 | Z43: 775 | AA43: =IF(AND(A43="", B43="", E43=""), "", IF(AB43="", "Válido", IF((LEN(AB43)-LEN(SUBSTITUTE(AB43,"; ","")))/2+1>(LEN(AB43)-LEN(SUBSTITUTE(AB43,"[Aviso]","")))/7, "Con Incidencias", "Válido"))) | AB43: =IF(AND(A43="", B43="", E43=""), "", TEXTJOIN("; ", TRUE, IF(OR(TRIM(A43&"")="", ISNUMBER(SEARCH("FALTA", A43))), "UPC faltante/inválido", ""), IF(AND(A43<>"", IFERROR(_xlfn.XMATCH(A43,$A$2:$A$204,0,1)<>_xlfn.XMATCH(A43,$A$2:$A$204,0,-1),FALSE)), "Código de barras duplicado", ""), IF(AND(E43<>"", COUNTIF($E$2:$E$204, E43)>1), "SKU duplicado", ""), IF(OR(J43="", J43=""), "[Aviso] División no capturada ()", IF(ISNA(MATCH(J43, Criterios!$A$123:$A$126, 0)), "División no válida", "")), IF(OR(K43="", K43=""), "[Aviso] Categoría no capturada ()", IF(ISNA(MATCH(K43, Criterios!$A$81:$A$120, 0)), "Categoría no válida", IF(AND(J43<>"", J43<>"", J43<>VLOOKUP(K43, Criterios!$A$81:$B$120, 2, FALSE)), "División no coincide con Categoría", ""))), IF(OR(L43="", L43=""), "[Aviso] Género no capturado ()", IF(ISNA(MATCH(L43, Criterios!$B$123:$B$127, 0)), "Género no válido", "")), IF(OR(N43="", N43=""), "[Aviso] Temporada no capturada ()", IF(ISNA(MATCH(N43, Criterios!$C$123:$C$128, 0)), "Temporada no válida", "")), IF(OR(O43="", O43=""), "[Aviso] Ciclo de vida no capturado ()", IF(ISNA(MATCH(O43, Criterios!$D$123:$D$124, 0)), "Ciclo de vida no válido", "")))) | AD43: 3 | AE43: WB OUTLET LERMA: 3 | AF43: 3 | AG43: Nuevo – NetSuite con existencia | AH43: Revisión 29/09/2026: Campos sin respaldo: X; Auditoría NetSuite 30/09/2026: llenado desde NetSuite [P,V,Y,T] | 01/10/2026: complementado desde Shopify Western Brothers (match por código de barras): WB Silueta | AI43: No | AK43: ProductosCatalogoEstandar907.xlsx: fila 23 [N,O,Q,S,U,Y]; G1522_Extraccion_Articulos_NetSuite_2026-09-30.xlsx: fila 56560 [P,V,Y,T] | Shopify WB: producto 8569957286073 / variante 47621317755065 | AL43: 336 | AM43: 899 | AN43: Shopify Western Brothers | AP43: 3 | AR43: Shopify Western Brothers › Western Brothers Outlet Lerma: 3
A44: 7506499529587 | B44: 108402 | C44: Multimarca | D44: A-CM128 | E44: A-CM128-XS | F44: XS | G44: XS | H44: Denver | I44: Camisa Denver de dama verde | J44: Ropa | K44: Camisas | L44: Mujer | M44: Denver | N44: SS26 | O44: Seasonal | P44: Verde | Q44: Regular | S44: 100% Rayón | T44: Camisa Denver de dama verde Regular | U44: México | V44: PZS | W44: 53101604 | Y44: 336 | Z44: 775 | AA44: =IF(AND(A44="", B44="", E44=""), "", IF(AB44="", "Válido", IF((LEN(AB44)-LEN(SUBSTITUTE(AB44,"; ","")))/2+1>(LEN(AB44)-LEN(SUBSTITUTE(AB44,"[Aviso]","")))/7, "Con Incidencias", "Válido"))) | AB44: =IF(AND(A44="", B44="", E44=""), "", TEXTJOIN("; ", TRUE, IF(OR(TRIM(A44&"")="", ISNUMBER(SEARCH("FALTA", A44))), "UPC faltante/inválido", ""), IF(AND(A44<>"", IFERROR(_xlfn.XMATCH(A44,$A$2:$A$204,0,1)<>_xlfn.XMATCH(A44,$A$2:$A$204,0,-1),FALSE)), "Código de barras duplicado", ""), IF(AND(E44<>"", COUNTIF($E$2:$E$204, E44)>1), "SKU duplicado", ""), IF(OR(J44="", J44=""), "[Aviso] División no capturada ()", IF(ISNA(MATCH(J44, Criterios!$A$123:$A$126, 0)), "División no válida", "")), IF(OR(K44="", K44=""), "[Aviso] Categoría no capturada ()", IF(ISNA(MATCH(K44, Criterios!$A$81:$A$120, 0)), "Categoría no válida", IF(AND(J44<>"", J44<>"", J44<>VLOOKUP(K44, Criterios!$A$81:$B$120, 2, FALSE)), "División no coincide con Categoría", ""))), IF(OR(L44="", L44=""), "[Aviso] Género no capturado ()", IF(ISNA(MATCH(L44, Criterios!$B$123:$B$127, 0)), "Género no válido", "")), IF(OR(N44="", N44=""), "[Aviso] Temporada no capturada ()", IF(ISNA(MATCH(N44, Criterios!$C$123:$C$128, 0)), "Temporada no válida", "")), IF(OR(O44="", O44=""), "[Aviso] Ciclo de vida no capturado ()", IF(ISNA(MATCH(O44, Criterios!$D$123:$D$124, 0)), "Ciclo de vida no válido", "")))) | AD44: 0 | AF44: 0 | AG44: Nuevo – NetSuite sin existencia | AH44: Revisión 29/09/2026: Campos sin respaldo: X; Auditoría NetSuite 30/09/2026: llenado desde NetSuite [P,V,Y,T] | 01/10/2026: complementado desde Shopify Western Brothers (match por código de barras): WB Silueta | AI44: No | AK44: ProductosCatalogoEstandar907.xlsx: fila 24 [N,O,Q,S,U,Y]; G1522_Extraccion_Articulos_NetSuite_2026-09-30.xlsx: fila 56561 [P,V,Y,T] | Shopify WB: producto 8569957417145 / variante 47621317984441 | AL44: 336 | AM44: 899 | AN44: Shopify Western Brothers | AP44: 0
A45: 7506499529594 | B45: 108403 | C45: Multimarca | D45: A-CM128 | E45: A-CM128-S | F45: S | G45: S | H45: Denver | I45: Camisa Denver de dama verde | J45: Ropa | K45: Camisas | L45: Mujer | M45: Denver | N45: SS26 | O45: Seasonal | P45: Verde | Q45: Regular | S45: 100% Rayón | T45: Camisa Denver de dama verde Regular | U45: México | V45: PZS | W45: 53101604 | Y45: 336 | Z45: 775 | AA45: =IF(AND(A45="", B45="", E45=""), "", IF(AB45="", "Válido", IF((LEN(AB45)-LEN(SUBSTITUTE(AB45,"; ","")))/2+1>(LEN(AB45)-LEN(SUBSTITUTE(AB45,"[Aviso]","")))/7, "Con Incidencias", "Válido"))) | AB45: =IF(AND(A45="", B45="", E45=""), "", TEXTJOIN("; ", TRUE, IF(OR(TRIM(A45&"")="", ISNUMBER(SEARCH("FALTA", A45))), "UPC faltante/inválido", ""), IF(AND(A45<>"", IFERROR(_xlfn.XMATCH(A45,$A$2:$A$204,0,1)<>_xlfn.XMATCH(A45,$A$2:$A$204,0,-1),FALSE)), "Código de barras duplicado", ""), IF(AND(E45<>"", COUNTIF($E$2:$E$204, E45)>1), "SKU duplicado", ""), IF(OR(J45="", J45=""), "[Aviso] División no capturada ()", IF(ISNA(MATCH(J45, Criterios!$A$123:$A$126, 0)), "División no válida", "")), IF(OR(K45="", K45=""), "[Aviso] Categoría no capturada ()", IF(ISNA(MATCH(K45, Criterios!$A$81:$A$120, 0)), "Categoría no válida", IF(AND(J45<>"", J45<>"", J45<>VLOOKUP(K45, Criterios!$A$81:$B$120, 2, FALSE)), "División no coincide con Categoría", ""))), IF(OR(L45="", L45=""), "[Aviso] Género no capturado ()", IF(ISNA(MATCH(L45, Criterios!$B$123:$B$127, 0)), "Género no válido", "")), IF(OR(N45="", N45=""), "[Aviso] Temporada no capturada ()", IF(ISNA(MATCH(N45, Criterios!$C$123:$C$128, 0)), "Temporada no válida", "")), IF(OR(O45="", O45=""), "[Aviso] Ciclo de vida no capturado ()", IF(ISNA(MATCH(O45, Criterios!$D$123:$D$124, 0)), "Ciclo de vida no válido", "")))) | AD45: 0 | AF45: 0 | AG45: Nuevo – NetSuite sin existencia | AH45: Revisión 29/09/2026: Campos sin respaldo: X; Auditoría NetSuite 30/09/2026: llenado desde NetSuite [P,V,Y,T] | 01/10/2026: complementado desde Shopify Western Brothers (match por código de barras): WB Silueta | AI45: No | AK45: ProductosCatalogoEstandar907.xlsx: fila 25 [N,O,Q,S,U,Y]; G1522_Extraccion_Articulos_NetSuite_2026-09-30.xlsx: fila 56562 [P,V,Y,T] | Shopify WB: producto 8569957417145 / variante 47621318017209 | AL45: 336 | AM45: 899 | AN45: Shopify Western Brothers | AP45: 0
A46: 7506499529617 | B46: 108404 | C46: Multimarca | D46: A-CM128 | E46: A-CM128-L | F46: L | G46: L | H46: Denver | I46: Camisa Denver de dama verde | J46: Ropa | K46: Camisas | L46: Mujer | M46: Denver | N46: SS26 | O46: Seasonal | P46: Verde | Q46: Regular | S46: 100% Rayón | T46: Camisa Denver de dama verde Regular | U46: México | V46: PZS | W46: 53101604 | Y46: 336 | Z46: 775 | AA46: =IF(AND(A46="", B46="", E46=""), "", IF(AB46="", "Válido", IF((LEN(AB46)-LEN(SUBSTITUTE(AB46,"; ","")))/2+1>(LEN(AB46)-LEN(SUBSTITUTE(AB46,"[Aviso]","")))/7, "Con Incidencias", "Válido"))) | AB46: =IF(AND(A46="", B46="", E46=""), "", TEXTJOIN("; ", TRUE, IF(OR(TRIM(A46&"")="", ISNUMBER(SEARCH("FALTA", A46))), "UPC faltante/inválido", ""), IF(AND(A46<>"", IFERROR(_xlfn.XMATCH(A46,$A$2:$A$204,0,1)<>_xlfn.XMATCH(A46,$A$2:$A$204,0,-1),FALSE)), "Código de barras duplicado", ""), IF(AND(E46<>"", COUNTIF($E$2:$E$204, E46)>1), "SKU duplicado", ""), IF(OR(J46="", J46=""), "[Aviso] División no capturada ()", IF(ISNA(MATCH(J46, Criterios!$A$123:$A$126, 0)), "División no válida", "")), IF(OR(K46="", K46=""), "[Aviso] Categoría no capturada ()", IF(ISNA(MATCH(K46, Criterios!$A$81:$A$120, 0)), "Categoría no válida", IF(AND(J46<>"", J46<>"", J46<>VLOOKUP(K46, Criterios!$A$81:$B$120, 2, FALSE)), "División no coincide con Categoría", ""))), IF(OR(L46="", L46=""), "[Aviso] Género no capturado ()", IF(ISNA(MATCH(L46, Criterios!$B$123:$B$127, 0)), "Género no válido", "")), IF(OR(N46="", N46=""), "[Aviso] Temporada no capturada ()", IF(ISNA(MATCH(N46, Criterios!$C$123:$C$128, 0)), "Temporada no válida", "")), IF(OR(O46="", O46=""), "[Aviso] Ciclo de vida no capturado ()", IF(ISNA(MATCH(O46, Criterios!$D$123:$D$124, 0)), "Ciclo de vida no válido", "")))) | AD46: 4 | AE46: WB OUTLET LERMA: 4 | AF46: 4 | AG46: Nuevo – NetSuite con existencia | AH46: Revisión 29/09/2026: Campos sin respaldo: X; Auditoría NetSuite 30/09/2026: llenado desde NetSuite [P,V,Y,T] | 01/10/2026: complementado desde Shopify Western Brothers (match por código de barras): WB Silueta | AI46: No | AK46: ProductosCatalogoEstandar907.xlsx: fila 26 [N,O,Q,S,U,Y]; G1522_Extraccion_Articulos_NetSuite_2026-09-30.xlsx: fila 56563 [P,V,Y,T] | Shopify WB: producto 8569957417145 / variante 47621318049977 | AL46: 336 | AM46: 899 | AN46: Shopify Western Brothers | AP46: 4 | AR46: Shopify Western Brothers › Western Brothers Outlet Lerma: 4
A47: 7506499529785 | B47: 108405 | C47: Multimarca | D47: A-CM132 | E47: A-CM132-XS | F47: XS | G47: XS | H47: Denver | I47: Camisa Denver dama estampado bisnaga naranja | J47: Ropa | K47: Camisas | L47: Mujer | M47: Denver | N47: SS26 | O47: Seasonal | P47: Naranja | Q47: Regular | S47: 100% Rayón | T47: Camisa Denver dama estampado bisnaga naranja Regular | U47: México | V47: PZS | W47: 53101604 | Y47: 336 | Z47: 775 | AA47: =IF(AND(A47="", B47="", E47=""), "", IF(AB47="", "Válido", IF((LEN(AB47)-LEN(SUBSTITUTE(AB47,"; ","")))/2+1>(LEN(AB47)-LEN(SUBSTITUTE(AB47,"[Aviso]","")))/7, "Con Incidencias", "Válido"))) | AB47: =IF(AND(A47="", B47="", E47=""), "", TEXTJOIN("; ", TRUE, IF(OR(TRIM(A47&"")="", ISNUMBER(SEARCH("FALTA", A47))), "UPC faltante/inválido", ""), IF(AND(A47<>"", IFERROR(_xlfn.XMATCH(A47,$A$2:$A$204,0,1)<>_xlfn.XMATCH(A47,$A$2:$A$204,0,-1),FALSE)), "Código de barras duplicado", ""), IF(AND(E47<>"", COUNTIF($E$2:$E$204, E47)>1), "SKU duplicado", ""), IF(OR(J47="", J47=""), "[Aviso] División no capturada ()", IF(ISNA(MATCH(J47, Criterios!$A$123:$A$126, 0)), "División no válida", "")), IF(OR(K47="", K47=""), "[Aviso] Categoría no capturada ()", IF(ISNA(MATCH(K47, Criterios!$A$81:$A$120, 0)), "Categoría no válida", IF(AND(J47<>"", J47<>"", J47<>VLOOKUP(K47, Criterios!$A$81:$B$120, 2, FALSE)), "División no coincide con Categoría", ""))), IF(OR(L47="", L47=""), "[Aviso] Género no capturado ()", IF(ISNA(MATCH(L47, Criterios!$B$123:$B$127, 0)), "Género no válido", "")), IF(OR(N47="", N47=""), "[Aviso] Temporada no capturada ()", IF(ISNA(MATCH(N47, Criterios!$C$123:$C$128, 0)), "Temporada no válida", "")), IF(OR(O47="", O47=""), "[Aviso] Ciclo de vida no capturado ()", IF(ISNA(MATCH(O47, Criterios!$D$123:$D$124, 0)), "Ciclo de vida no válido", "")))) | AD47: 3 | AE47: WB OUTLET LERMA: 3 | AF47: 3 | AG47: Nuevo – NetSuite con existencia | AH47: Revisión 29/09/2026: Campos sin respaldo: X; Auditoría NetSuite 30/09/2026: llenado desde NetSuite [P,V,Y,T] | 01/10/2026: complementado desde Shopify Western Brothers (match por código de barras): WB Silueta | AI47: No | AK47: ProductosCatalogoEstandar907.xlsx: fila 27 [N,O,Q,S,U,Y]; G1522_Extraccion_Articulos_NetSuite_2026-09-30.xlsx: fila 56564 [P,V,Y,T] | Shopify WB: producto 8569957580985 / variante 47621318279353 | AL47: 336 | AM47: 899 | AN47: Shopify Western Brothers | AP47: 3 | AR47: Shopify Western Brothers › Western Brothers Outlet Lerma: 3
A48: 7506499529792 | B48: 108406 | C48: Multimarca | D48: A-CM132 | E48: A-CM132-S | F48: S | G48: S | H48: Denver | I48: Camisa Denver dama estampado bisnaga naranja | J48: Ropa | K48: Camisas | L48: Mujer | M48: Denver | N48: SS26 | O48: Seasonal | P48: Naranja | Q48: Regular | S48: 100% Rayón | T48: Camisa Denver dama estampado bisnaga naranja Regular | U48: México | V48: PZS | W48: 53101604 | Y48: 336 | Z48: 775 | AA48: =IF(AND(A48="", B48="", E48=""), "", IF(AB48="", "Válido", IF((LEN(AB48)-LEN(SUBSTITUTE(AB48,"; ","")))/2+1>(LEN(AB48)-LEN(SUBSTITUTE(AB48,"[Aviso]","")))/7, "Con Incidencias", "Válido"))) | AB48: =IF(AND(A48="", B48="", E48=""), "", TEXTJOIN("; ", TRUE, IF(OR(TRIM(A48&"")="", ISNUMBER(SEARCH("FALTA", A48))), "UPC faltante/inválido", ""), IF(AND(A48<>"", IFERROR(_xlfn.XMATCH(A48,$A$2:$A$204,0,1)<>_xlfn.XMATCH(A48,$A$2:$A$204,0,-1),FALSE)), "Código de barras duplicado", ""), IF(AND(E48<>"", COUNTIF($E$2:$E$204, E48)>1), "SKU duplicado", ""), IF(OR(J48="", J48=""), "[Aviso] División no capturada ()", IF(ISNA(MATCH(J48, Criterios!$A$123:$A$126, 0)), "División no válida", "")), IF(OR(K48="", K48=""), "[Aviso] Categoría no capturada ()", IF(ISNA(MATCH(K48, Criterios!$A$81:$A$120, 0)), "Categoría no válida", IF(AND(J48<>"", J48<>"", J48<>VLOOKUP(K48, Criterios!$A$81:$B$120, 2, FALSE)), "División no coincide con Categoría", ""))), IF(OR(L48="", L48=""), "[Aviso] Género no capturado ()", IF(ISNA(MATCH(L48, Criterios!$B$123:$B$127, 0)), "Género no válido", "")), IF(OR(N48="", N48=""), "[Aviso] Temporada no capturada ()", IF(ISNA(MATCH(N48, Criterios!$C$123:$C$128, 0)), "Temporada no válida", "")), IF(OR(O48="", O48=""), "[Aviso] Ciclo de vida no capturado ()", IF(ISNA(MATCH(O48, Criterios!$D$123:$D$124, 0)), "Ciclo de vida no válido", "")))) | AD48: 0 | AF48: 0 | AG48: Nuevo – NetSuite sin existencia | AH48: Revisión 29/09/2026: Campos sin respaldo: X; Auditoría NetSuite 30/09/2026: llenado desde NetSuite [P,V,Y,T] | 01/10/2026: complementado desde Shopify Western Brothers (match por código de barras): WB Silueta | AI48: No | AK48: ProductosCatalogoEstandar907.xlsx: fila 28 [N,O,Q,S,U,Y]; G1522_Extraccion_Articulos_NetSuite_2026-09-30.xlsx: fila 56565 [P,V,Y,T] | Shopify WB: producto 8569957580985 / variante 47621318312121 | AL48: 336 | AM48: 899 | AN48: Shopify Western Brothers | AP48: 0
A49: 7506499529808 | B49: 108407 | C49: Multimarca | D49: A-CM132 | E49: A-CM132-L | F49: L | G49: L | H49: Denver | I49: Camisa Denver dama estampado bisnaga naranja | J49: Ropa | K49: Camisas | L49: Mujer | M49: Denver | N49: SS26 | O49: Seasonal | P49: Naranja | Q49: Regular | S49: 100% Rayón | T49: Camisa Denver dama estampado bisnaga naranja Regular | U49: México | V49: PZS | W49: 53101604 | Y49: 336 | Z49: 775 | AA49: =IF(AND(A49="", B49="", E49=""), "", IF(AB49="", "Válido", IF((LEN(AB49)-LEN(SUBSTITUTE(AB49,"; ","")))/2+1>(LEN(AB49)-LEN(SUBSTITUTE(AB49,"[Aviso]","")))/7, "Con Incidencias", "Válido"))) | AB49: =IF(AND(A49="", B49="", E49=""), "", TEXTJOIN("; ", TRUE, IF(OR(TRIM(A49&"")="", ISNUMBER(SEARCH("FALTA", A49))), "UPC faltante/inválido", ""), IF(AND(A49<>"", IFERROR(_xlfn.XMATCH(A49,$A$2:$A$204,0,1)<>_xlfn.XMATCH(A49,$A$2:$A$204,0,-1),FALSE)), "Código de barras duplicado", ""), IF(AND(E49<>"", COUNTIF($E$2:$E$204, E49)>1), "SKU duplicado", ""), IF(OR(J49="", J49=""), "[Aviso] División no capturada ()", IF(ISNA(MATCH(J49, Criterios!$A$123:$A$126, 0)), "División no válida", "")), IF(OR(K49="", K49=""), "[Aviso] Categoría no capturada ()", IF(ISNA(MATCH(K49, Criterios!$A$81:$A$120, 0)), "Categoría no válida", IF(AND(J49<>"", J49<>"", J49<>VLOOKUP(K49, Criterios!$A$81:$B$120, 2, FALSE)), "División no coincide con Categoría", ""))), IF(OR(L49="", L49=""), "[Aviso] Género no capturado ()", IF(ISNA(MATCH(L49, Criterios!$B$123:$B$127, 0)), "Género no válido", "")), IF(OR(N49="", N49=""), "[Aviso] Temporada no capturada ()", IF(ISNA(MATCH(N49, Criterios!$C$123:$C$128, 0)), "Temporada no válida", "")), IF(OR(O49="", O49=""), "[Aviso] Ciclo de vida no capturado ()", IF(ISNA(MATCH(O49, Criterios!$D$123:$D$124, 0)), "Ciclo de vida no válido", "")))) | AD49: 0 | AF49: 0 | AG49: Nuevo – NetSuite sin existencia | AH49: Revisión 29/09/2026: Campos sin respaldo: X; Auditoría NetSuite 30/09/2026: llenado desde NetSuite [P,V,Y,T] | 01/10/2026: complementado desde Shopify Western Brothers (match por código de barras): WB Silueta | AI49: No | AK49: ProductosCatalogoEstandar907.xlsx: fila 29 [N,O,Q,S,U,Y]; G1522_Extraccion_Articulos_NetSuite_2026-09-30.xlsx: fila 56566 [P,V,Y,T] | Shopify WB: producto 8569957580985 / variante 47621318344889 | AL49: 336 | AM49: 899 | AN49: Shopify Western Brothers | AP49: 0
A50: 7506499529884 | B50: 108408 | C50: Multimarca | D50: A-CM134 | E50: A-CM134-XS | F50: XS | G50: XS | H50: Denver | I50: Camisa Denver dama estampado dalia durazno | J50: Ropa | K50: Camisas | L50: Mujer | M50: Denver | N50: SS26 | O50: Seasonal | P50: Naranja | Q50: Regular | S50: 100% Rayón | T50: Camisa Denver dama estampado dalia durazno Regular | U50: México | V50: PZS | W50: 53101604 | Y50: 336 | Z50: 775 | AA50: =IF(AND(A50="", B50="", E50=""), "", IF(AB50="", "Válido", IF((LEN(AB50)-LEN(SUBSTITUTE(AB50,"; ","")))/2+1>(LEN(AB50)-LEN(SUBSTITUTE(AB50,"[Aviso]","")))/7, "Con Incidencias", "Válido"))) | AB50: =IF(AND(A50="", B50="", E50=""), "", TEXTJOIN("; ", TRUE, IF(OR(TRIM(A50&"")="", ISNUMBER(SEARCH("FALTA", A50))), "UPC faltante/inválido", ""), IF(AND(A50<>"", IFERROR(_xlfn.XMATCH(A50,$A$2:$A$204,0,1)<>_xlfn.XMATCH(A50,$A$2:$A$204,0,-1),FALSE)), "Código de barras duplicado", ""), IF(AND(E50<>"", COUNTIF($E$2:$E$204, E50)>1), "SKU duplicado", ""), IF(OR(J50="", J50=""), "[Aviso] División no capturada ()", IF(ISNA(MATCH(J50, Criterios!$A$123:$A$126, 0)), "División no válida", "")), IF(OR(K50="", K50=""), "[Aviso] Categoría no capturada ()", IF(ISNA(MATCH(K50, Criterios!$A$81:$A$120, 0)), "Categoría no válida", IF(AND(J50<>"", J50<>"", J50<>VLOOKUP(K50, Criterios!$A$81:$B$120, 2, FALSE)), "División no coincide con Categoría", ""))), IF(OR(L50="", L50=""), "[Aviso] Género no capturado ()", IF(ISNA(MATCH(L50, Criterios!$B$123:$B$127, 0)), "Género no válido", "")), IF(OR(N50="", N50=""), "[Aviso] Temporada no capturada ()", IF(ISNA(MATCH(N50, Criterios!$C$123:$C$128, 0)), "Temporada no válida", "")), IF(OR(O50="", O50=""), "[Aviso] Ciclo de vida no capturado ()", IF(ISNA(MATCH(O50, Criterios!$D$123:$D$124, 0)), "Ciclo de vida no válido", "")))) | AD50: 0 | AF50: 0 | AG50: Nuevo – NetSuite sin existencia | AH50: Revisión 29/09/2026: Campos sin respaldo: X; Auditoría NetSuite 30/09/2026: llenado desde NetSuite [P,V,Y,T] | 01/10/2026: complementado desde Shopify Western Brothers (match por código de barras): WB Silueta | AI50: No | AK50: ProductosCatalogoEstandar907.xlsx: fila 30 [N,O,Q,S,U,Y]; G1522_Extraccion_Articulos_NetSuite_2026-09-30.xlsx: fila 56567 [P,V,Y,T] | Shopify WB: producto 8569957712057 / variante 47621318541497 | AL50: 336 | AM50: 899 | AN50: Shopify Western Brothers | AP50: 0
A51: 7506499529891 | B51: 108409 | C51: Multimarca | D51: A-CM134 | E51: A-CM134-S | F51: S | G51: S | H51: Denver | I51: Camisa Denver dama estampado dalia durazno | J51: Ropa | K51: Camisas | L51: Mujer | M51: Denver | N51: SS26 | O51: Seasonal | P51: Naranja | Q51: Regular | S51: 100% Rayón | T51: Camisa Denver dama estampado dalia durazno Regular | U51: México | V51: PZS | W51: 53101604 | Y51: 336 | Z51: 775 | AA51: =IF(AND(A51="", B51="", E51=""), "", IF(AB51="", "Válido", IF((LEN(AB51)-LEN(SUBSTITUTE(AB51,"; ","")))/2+1>(LEN(AB51)-LEN(SUBSTITUTE(AB51,"[Aviso]","")))/7, "Con Incidencias", "Válido"))) | AB51: =IF(AND(A51="", B51="", E51=""), "", TEXTJOIN("; ", TRUE, IF(OR(TRIM(A51&"")="", ISNUMBER(SEARCH("FALTA", A51))), "UPC faltante/inválido", ""), IF(AND(A51<>"", IFERROR(_xlfn.XMATCH(A51,$A$2:$A$204,0,1)<>_xlfn.XMATCH(A51,$A$2:$A$204,0,-1),FALSE)), "Código de barras duplicado", ""), IF(AND(E51<>"", COUNTIF($E$2:$E$204, E51)>1), "SKU duplicado", ""), IF(OR(J51="", J51=""), "[Aviso] División no capturada ()", IF(ISNA(MATCH(J51, Criterios!$A$123:$A$126, 0)), "División no válida", "")), IF(OR(K51="", K51=""), "[Aviso] Categoría no capturada ()", IF(ISNA(MATCH(K51, Criterios!$A$81:$A$120, 0)), "Categoría no válida", IF(AND(J51<>"", J51<>"", J51<>VLOOKUP(K51, Criterios!$A$81:$B$120, 2, FALSE)), "División no coincide con Categoría", ""))), IF(OR(L51="", L51=""), "[Aviso] Género no capturado ()", IF(ISNA(MATCH(L51, Criterios!$B$123:$B$127, 0)), "Género no válido", "")), IF(OR(N51="", N51=""), "[Aviso] Temporada no capturada ()", IF(ISNA(MATCH(N51, Criterios!$C$123:$C$128, 0)), "Temporada no válida", "")), IF(OR(O51="", O51=""), "[Aviso] Ciclo de vida no capturado ()", IF(ISNA(MATCH(O51, Criterios!$D$123:$D$124, 0)), "Ciclo de vida no válido", "")))) | AD51: 4 | AE51: WB OUTLET LERMA: 4 | AF51: 4 | AG51: Nuevo – NetSuite con existencia | AH51: Revisión 29/09/2026: Campos sin respaldo: X; Auditoría NetSuite 30/09/2026: llenado desde NetSuite [P,V,Y,T] | 01/10/2026: complementado desde Shopify Western Brothers (match por código de barras): WB Silueta | AI51: No | AK51: ProductosCatalogoEstandar907.xlsx: fila 31 [N,O,Q,S,U,Y]; G1522_Extraccion_Articulos_NetSuite_2026-09-30.xlsx: fila 56568 [P,V,Y,T] | Shopify WB: producto 8569957712057 / variante 47621318574265 | AL51: 336 | AM51: 899 | AN51: Shopify Western Brothers | AP51: 4 | AR51: Shopify Western Brothers › Western Brothers Outlet Lerma: 4
A52: 7506499529914 | B52: 108410 | C52: Multimarca | D52: A-CM134 | E52: A-CM134-L | F52: L | G52: L | H52: Denver | I52: Camisa Denver dama estampado dalia durazno | J52: Ropa | K52: Camisas | L52: Mujer | M52: Denver | N52: SS26 | O52: Seasonal | P52: Naranja | Q52: Regular | S52: 100% Rayón | T52: Camisa Denver dama estampado dalia durazno Regular | U52: México | V52: PZS | W52: 53101604 | Y52: 336 | Z52: 775 | AA52: =IF(AND(A52="", B52="", E52=""), "", IF(AB52="", "Válido", IF((LEN(AB52)-LEN(SUBSTITUTE(AB52,"; ","")))/2+1>(LEN(AB52)-LEN(SUBSTITUTE(AB52,"[Aviso]","")))/7, "Con Incidencias", "Válido"))) | AB52: =IF(AND(A52="", B52="", E52=""), "", TEXTJOIN("; ", TRUE, IF(OR(TRIM(A52&"")="", ISNUMBER(SEARCH("FALTA", A52))), "UPC faltante/inválido", ""), IF(AND(A52<>"", IFERROR(_xlfn.XMATCH(A52,$A$2:$A$204,0,1)<>_xlfn.XMATCH(A52,$A$2:$A$204,0,-1),FALSE)), "Código de barras duplicado", ""), IF(AND(E52<>"", COUNTIF($E$2:$E$204, E52)>1), "SKU duplicado", ""), IF(OR(J52="", J52=""), "[Aviso] División no capturada ()", IF(ISNA(MATCH(J52, Criterios!$A$123:$A$126, 0)), "División no válida", "")), IF(OR(K52="", K52=""), "[Aviso] Categoría no capturada ()", IF(ISNA(MATCH(K52, Criterios!$A$81:$A$120, 0)), "Categoría no válida", IF(AND(J52<>"", J52<>"", J52<>VLOOKUP(K52, Criterios!$A$81:$B$120, 2, FALSE)), "División no coincide con Categoría", ""))), IF(OR(L52="", L52=""), "[Aviso] Género no capturado ()", IF(ISNA(MATCH(L52, Criterios!$B$123:$B$127, 0)), "Género no válido", "")), IF(OR(N52="", N52=""), "[Aviso] Temporada no capturada ()", IF(ISNA(MATCH(N52, Criterios!$C$123:$C$128, 0)), "Temporada no válida", "")), IF(OR(O52="", O52=""), "[Aviso] Ciclo de vida no capturado ()", IF(ISNA(MATCH(O52, Criterios!$D$123:$D$124, 0)), "Ciclo de vida no válido", "")))) | AD52: 1 | AE52: WB OUTLET LERMA: 1 | AF52: 1 | AG52: Nuevo – NetSuite con existencia | AH52: Revisión 29/09/2026: Campos sin respaldo: X; Auditoría NetSuite 30/09/2026: llenado desde NetSuite [P,V,Y,T] | 01/10/2026: complementado desde Shopify Western Brothers (match por código de barras): WB Silueta | AI52: No | AK52: ProductosCatalogoEstandar907.xlsx: fila 32 [N,O,Q,S,U,Y]; G1522_Extraccion_Articulos_NetSuite_2026-09-30.xlsx: fila 56569 [P,V,Y,T] | Shopify WB: producto 8569957712057 / variante 47621318607033 | AL52: 336 | AM52: 899 | AN52: Shopify Western Brothers | AP52: 1 | AR52: Shopify Western Brothers › Western Brothers Outlet Lerma: 1
A53: 7506499551069 | B53: 108411 | C53: Multimarca | D53: A-CM152 | E53: A-CM152-M | F53: M | G53: M | H53: Denver | I53: Camisa Denver vaqueras | J53: Ropa | K53: Camisas | L53: Mujer | M53: Denver | N53: SS26 | O53: Seasonal | P53: Naranja | Q53: Regular | S53: 100% Rayón | T53: Camisa Denver vaqueras Regular | U53: México | V53: PZS | W53: 53101600 | Y53: 336 | Z53: 775 | AA53: =IF(AND(A53="", B53="", E53=""), "", IF(AB53="", "Válido", IF((LEN(AB53)-LEN(SUBSTITUTE(AB53,"; ","")))/2+1>(LEN(AB53)-LEN(SUBSTITUTE(AB53,"[Aviso]","")))/7, "Con Incidencias", "Válido"))) | AB53: =IF(AND(A53="", B53="", E53=""), "", TEXTJOIN("; ", TRUE, IF(OR(TRIM(A53&"")="", ISNUMBER(SEARCH("FALTA", A53))), "UPC faltante/inválido", ""), IF(AND(A53<>"", IFERROR(_xlfn.XMATCH(A53,$A$2:$A$204,0,1)<>_xlfn.XMATCH(A53,$A$2:$A$204,0,-1),FALSE)), "Código de barras duplicado", ""), IF(AND(E53<>"", COUNTIF($E$2:$E$204, E53)>1), "SKU duplicado", ""), IF(OR(J53="", J53=""), "[Aviso] División no capturada ()", IF(ISNA(MATCH(J53, Criterios!$A$123:$A$126, 0)), "División no válida", "")), IF(OR(K53="", K53=""), "[Aviso] Categoría no capturada ()", IF(ISNA(MATCH(K53, Criterios!$A$81:$A$120, 0)), "Categoría no válida", IF(AND(J53<>"", J53<>"", J53<>VLOOKUP(K53, Criterios!$A$81:$B$120, 2, FALSE)), "División no coincide con Categoría", ""))), IF(OR(L53="", L53=""), "[Aviso] Género no capturado ()", IF(ISNA(MATCH(L53, Criterios!$B$123:$B$127, 0)), "Género no válido", "")), IF(OR(N53="", N53=""), "[Aviso] Temporada no capturada ()", IF(ISNA(MATCH(N53, Criterios!$C$123:$C$128, 0)), "Temporada no válida", "")), IF(OR(O53="", O53=""), "[Aviso] Ciclo de vida no capturado ()", IF(ISNA(MATCH(O53, Criterios!$D$123:$D$124, 0)), "Ciclo de vida no válido", "")))) | AD53: 3 | AE53: WB OUTLET LERMA: 3 | AF53: 3 | AG53: Nuevo – NetSuite con existencia | AH53: Color por validar; Género por validar | Revisión 29/09/2026: Campos sin respaldo: X; Auditoría NetSuite 30/09/2026: llenado desde NetSuite [M,V,Y,T] | 01/10/2026: complementado desde Shopify Western Brothers (match por código de barras): WB Silueta | AI53: No | AK53: ProductosCatalogoEstandar907.xlsx: fila 33 [L,N,O,P,Q,S,U,Y]; G1522_Extraccion_Articulos_NetSuite_2026-09-30.xlsx: fila 56570 [M,V,Y,T] | Shopify WB: producto 8569957843129 / variante 47621318770873 | AL53: 336 | AM53: 899 | AN53: Shopify Western Brothers | AP53: 3 | AR53: Shopify Western Brothers › Western Brothers Outlet Lerma: 3
A54: 7506499551076 | B54: 108412 | C54: Multimarca | D54: A-CM152 | E54: A-CM152-L | F54: L | G54: L | H54: Denver | I54: Camisa Denver vaqueras | J54: Ropa | K54: Camisas | L54: Mujer | M54: Denver | N54: SS26 | O54: Seasonal | P54: Naranja | Q54: Regular | S54: 100% Rayón | T54: Camisa Denver vaqueras Regular | U54: México | V54: PZS | W54: 53101600 | Y54: 336 | Z54: 775 | AA54: =IF(AND(A54="", B54="", E54=""), "", IF(AB54="", "Válido", IF((LEN(AB54)-LEN(SUBSTITUTE(AB54,"; ","")))/2+1>(LEN(AB54)-LEN(SUBSTITUTE(AB54,"[Aviso]","")))/7, "Con Incidencias", "Válido"))) | AB54: =IF(AND(A54="", B54="", E54=""), "", TEXTJOIN("; ", TRUE, IF(OR(TRIM(A54&"")="", ISNUMBER(SEARCH("FALTA", A54))), "UPC faltante/inválido", ""), IF(AND(A54<>"", IFERROR(_xlfn.XMATCH(A54,$A$2:$A$204,0,1)<>_xlfn.XMATCH(A54,$A$2:$A$204,0,-1),FALSE)), "Código de barras duplicado", ""), IF(AND(E54<>"", COUNTIF($E$2:$E$204, E54)>1), "SKU duplicado", ""), IF(OR(J54="", J54=""), "[Aviso] División no capturada ()", IF(ISNA(MATCH(J54, Criterios!$A$123:$A$126, 0)), "División no válida", "")), IF(OR(K54="", K54=""), "[Aviso] Categoría no capturada ()", IF(ISNA(MATCH(K54, Criterios!$A$81:$A$120, 0)), "Categoría no válida", IF(AND(J54<>"", J54<>"", J54<>VLOOKUP(K54, Criterios!$A$81:$B$120, 2, FALSE)), "División no coincide con Categoría", ""))), IF(OR(L54="", L54=""), "[Aviso] Género no capturado ()", IF(ISNA(MATCH(L54, Criterios!$B$123:$B$127, 0)), "Género no válido", "")), IF(OR(N54="", N54=""), "[Aviso] Temporada no capturada ()", IF(ISNA(MATCH(N54, Criterios!$C$123:$C$128, 0)), "Temporada no válida", "")), IF(OR(O54="", O54=""), "[Aviso] Ciclo de vida no capturado ()", IF(ISNA(MATCH(O54, Criterios!$D$123:$D$124, 0)), "Ciclo de vida no válido", "")))) | AD54: 1 | AE54: WB OUTLET LERMA: 1 | AF54: 1 | AG54: Nuevo – NetSuite con existencia | AH54: Color por validar; Género por validar | Revisión 29/09/2026: Campos sin respaldo: X; Auditoría NetSuite 30/09/2026: llenado desde NetSuite [M,V,Y,T] | 01/10/2026: complementado desde Shopify Western Brothers (match por código de barras): WB Silueta | AI54: No | AK54: ProductosCatalogoEstandar907.xlsx: fila 34 [L,N,O,P,Q,S,U,Y]; G1522_Extraccion_Articulos_NetSuite_2026-09-30.xlsx: fila 56571 [M,V,Y,T] | Shopify WB: producto 8569957843129 / variante 47621318803641 | AL54: 336 | AM54: 899 | AN54: Shopify Western Brothers | AP54: 1 | AR54: Shopify Western Brothers › Western Brothers Outlet Lerma: 1
A55: 7506499551090 | B55: 108413 | C55: Multimarca | D55: A-CM152 | E55: A-CM152-XXL | F55: XXL | G55: XXL | H55: Denver | I55: Camisa Denver vaqueras | J55: Ropa | K55: Camisas | L55: Mujer | M55: Denver | N55: SS26 | O55: Seasonal | P55: Naranja | Q55: Regular | S55: 100% Rayón | T55: Camisa Denver vaqueras Regular | U55: México | V55: PZS | W55: 53101600 | Y55: 336 | Z55: 775 | AA55: =IF(AND(A55="", B55="", E55=""), "", IF(AB55="", "Válido", IF((LEN(AB55)-LEN(SUBSTITUTE(AB55,"; ","")))/2+1>(LEN(AB55)-LEN(SUBSTITUTE(AB55,"[Aviso]","")))/7, "Con Incidencias", "Válido"))) | AB55: =IF(AND(A55="", B55="", E55=""), "", TEXTJOIN("; ", TRUE, IF(OR(TRIM(A55&"")="", ISNUMBER(SEARCH("FALTA", A55))), "UPC faltante/inválido", ""), IF(AND(A55<>"", IFERROR(_xlfn.XMATCH(A55,$A$2:$A$204,0,1)<>_xlfn.XMATCH(A55,$A$2:$A$204,0,-1),FALSE)), "Código de barras duplicado", ""), IF(AND(E55<>"", COUNTIF($E$2:$E$204, E55)>1), "SKU duplicado", ""), IF(OR(J55="", J55=""), "[Aviso] División no capturada ()", IF(ISNA(MATCH(J55, Criterios!$A$123:$A$126, 0)), "División no válida", "")), IF(OR(K55="", K55=""), "[Aviso] Categoría no capturada ()", IF(ISNA(MATCH(K55, Criterios!$A$81:$A$120, 0)), "Categoría no válida", IF(AND(J55<>"", J55<>"", J55<>VLOOKUP(K55, Criterios!$A$81:$B$120, 2, FALSE)), "División no coincide con Categoría", ""))), IF(OR(L55="", L55=""), "[Aviso] Género no capturado ()", IF(ISNA(MATCH(L55, Criterios!$B$123:$B$127, 0)), "Género no válido", "")), IF(OR(N55="", N55=""), "[Aviso] Temporada no capturada ()", IF(ISNA(MATCH(N55, Criterios!$C$123:$C$128, 0)), "Temporada no válida", "")), IF(OR(O55="", O55=""), "[Aviso] Ciclo de vida no capturado ()", IF(ISNA(MATCH(O55, Criterios!$D$123:$D$124, 0)), "Ciclo de vida no válido", "")))) | AD55: 3 | AE55: WB OUTLET LERMA: 3 | AF55: 3 | AG55: Nuevo – NetSuite con existencia | AH55: Color por validar; Género por validar | Revisión 29/09/2026: Campos sin respaldo: X; Auditoría NetSuite 30/09/2026: llenado desde NetSuite [M,V,Y,T] | 01/10/2026: complementado desde Shopify Western Brothers (match por código de barras): WB Silueta | AI55: No | AK55: ProductosCatalogoEstandar907.xlsx: fila 35 [L,N,O,P,Q,S,U,Y]; G1522_Extraccion_Articulos_NetSuite_2026-09-30.xlsx: fila 56572 [M,V,Y,T] | Shopify WB: producto 8569957843129 / variante 47621318836409 | AL55: 336 | AM55: 899 | AN55: Shopify Western Brothers | AP55: 3 | AR55: Shopify Western Brothers › Western Brothers Outlet Lerma: 3
A56: 7506499530088 | B56: 108414 | C56: Multimarca | D56: C-CM128 | E56: C-CM128-XS | F56: XS | G56: XS | H56: Denver | I56: Camisa Denver dama estampado flor de yuca verde | J56: Ropa | K56: Camisas | L56: Mujer | M56: Denver | N56: SS26 | O56: Seasonal | P56: Verde | Q56: Regular | S56: 100% Rayón | T56: Camisa Denver dama estampado flor de yuca verde Regular | U56: México | V56: PZS | W56: 53101604 | Y56: 336 | Z56: 775 | AA56: =IF(AND(A56="", B56="", E56=""), "", IF(AB56="", "Válido", IF((LEN(AB56)-LEN(SUBSTITUTE(AB56,"; ","")))/2+1>(LEN(AB56)-LEN(SUBSTITUTE(AB56,"[Aviso]","")))/7, "Con Incidencias", "Válido"))) | AB56: =IF(AND(A56="", B56="", E56=""), "", TEXTJOIN("; ", TRUE, IF(OR(TRIM(A56&"")="", ISNUMBER(SEARCH("FALTA", A56))), "UPC faltante/inválido", ""), IF(AND(A56<>"", IFERROR(_xlfn.XMATCH(A56,$A$2:$A$204,0,1)<>_xlfn.XMATCH(A56,$A$2:$A$204,0,-1),FALSE)), "Código de barras duplicado", ""), IF(AND(E56<>"", COUNTIF($E$2:$E$204, E56)>1), "SKU duplicado", ""), IF(OR(J56="", J56=""), "[Aviso] División no capturada ()", IF(ISNA(MATCH(J56, Criterios!$A$123:$A$126, 0)), "División no válida", "")), IF(OR(K56="", K56=""), "[Aviso] Categoría no capturada ()", IF(ISNA(MATCH(K56, Criterios!$A$81:$A$120, 0)), "Categoría no válida", IF(AND(J56<>"", J56<>"", J56<>VLOOKUP(K56, Criterios!$A$81:$B$120, 2, FALSE)), "División no coincide con Categoría", ""))), IF(OR(L56="", L56=""), "[Aviso] Género no capturado ()", IF(ISNA(MATCH(L56, Criterios!$B$123:$B$127, 0)), "Género no válido", "")), IF(OR(N56="", N56=""), "[Aviso] Temporada no capturada ()", IF(ISNA(MATCH(N56, Criterios!$C$123:$C$128, 0)), "Temporada no válida", "")), IF(OR(O56="", O56=""), "[Aviso] Ciclo de vida no capturado ()", IF(ISNA(MATCH(O56, Criterios!$D$123:$D$124, 0)), "Ciclo de vida no válido", "")))) | AD56: 4 | AE56: WB OUTLET LERMA: 4 | AF56: 4 | AG56: Nuevo – NetSuite con existencia | AH56: Revisión 29/09/2026: Campos sin respaldo: X; Auditoría NetSuite 30/09/2026: llenado desde NetSuite [P,V,Y,T] | 01/10/2026: complementado desde Shopify Western Brothers (match por código de barras): WB Silueta | AI56: No | AK56: ProductosCatalogoEstandar907.xlsx: fila 5105 [N,O,Q,S,U,Y]; G1522_Extraccion_Articulos_NetSuite_2026-09-30.xlsx: fila 56573 [P,V,Y,T] | Shopify WB: producto 8569958039737 / variante 47621319033017 | AL56: 336 | AM56: 899 | AN56: Shopify Western Brothers | AP56: 4 | AR56: Shopify Western Brothers › Western Brothers Outlet Lerma: 4
A57: 7506499530095 | B57: 108415 | C57: Multimarca | D57: C-CM128 | E57: C-CM128-S | F57: S | G57: S | H57: Denver | I57: Camisa Denver dama estampado flor de yuca verde | J57: Ropa | K57: Camisas | L57: Mujer | M57: Denver | N57: SS26 | O57: Seasonal | P57: Verde | Q57: Regular | S57: 100% Rayón | T57: Camisa Denver dama estampado flor de yuca verde Regular | U57: México | V57: PZS | W57: 53101604 | Y57: 336 | Z57: 775 | AA57: =IF(AND(A57="", B57="", E57=""), "", IF(AB57="", "Válido", IF((LEN(AB57)-LEN(SUBSTITUTE(AB57,"; ","")))/2+1>(LEN(AB57)-LEN(SUBSTITUTE(AB57,"[Aviso]","")))/7, "Con Incidencias", "Válido"))) | AB57: =IF(AND(A57="", B57="", E57=""), "", TEXTJOIN("; ", TRUE, IF(OR(TRIM(A57&"")="", ISNUMBER(SEARCH("FALTA", A57))), "UPC faltante/inválido", ""), IF(AND(A57<>"", IFERROR(_xlfn.XMATCH(A57,$A$2:$A$204,0,1)<>_xlfn.XMATCH(A57,$A$2:$A$204,0,-1),FALSE)), "Código de barras duplicado", ""), IF(AND(E57<>"", COUNTIF($E$2:$E$204, E57)>1), "SKU duplicado", ""), IF(OR(J57="", J57=""), "[Aviso] División no capturada ()", IF(ISNA(MATCH(J57, Criterios!$A$123:$A$126, 0)), "División no válida", "")), IF(OR(K57="", K57=""), "[Aviso] Categoría no capturada ()", IF(ISNA(MATCH(K57, Criterios!$A$81:$A$120, 0)), "Categoría no válida", IF(AND(J57<>"", J57<>"", J57<>VLOOKUP(K57, Criterios!$A$81:$B$120, 2, FALSE)), "División no coincide con Categoría", ""))), IF(OR(L57="", L57=""), "[Aviso] Género no capturado ()", IF(ISNA(MATCH(L57, Criterios!$B$123:$B$127, 0)), "Género no válido", "")), IF(OR(N57="", N57=""), "[Aviso] Temporada no capturada ()", IF(ISNA(MATCH(N57, Criterios!$C$123:$C$128, 0)), "Temporada no válida", "")), IF(OR(O57="", O57=""), "[Aviso] Ciclo de vida no capturado ()", IF(ISNA(MATCH(O57, Criterios!$D$123:$D$124, 0)), "Ciclo de vida no válido", "")))) | AD57: 4 | AE57: WB OUTLET LERMA: 4 | AF57: 4 | AG57: Nuevo – NetSuite con existencia | AH57: Revisión 29/09/2026: Campos sin respaldo: X; Auditoría NetSuite 30/09/2026: llenado desde NetSuite [P,V,Y,T] | 01/10/2026: complementado desde Shopify Western Brothers (match por código de barras): WB Silueta | AI57: No | AK57: ProductosCatalogoEstandar907.xlsx: fila 5106 [N,O,Q,S,U,Y]; G1522_Extraccion_Articulos_NetSuite_2026-09-30.xlsx: fila 56574 [P,V,Y,T] | Shopify WB: producto 8569958039737 / variante 47621319065785 | AL57: 336 | AM57: 899 | AN57: Shopify Western Brothers | AP57: 4 | AR57: Shopify Western Brothers › Western Brothers Outlet Lerma: 4
A58: 7506499530101 | B58: 108416 | C58: Multimarca | D58: C-CM128 | E58: C-CM128-M | F58: M | G58: M | H58: Denver | I58: Camisa Denver dama estampado flor de yuca verde | J58: Ropa | K58: Camisas | L58: Mujer | M58: Denver | N58: SS26 | O58: Seasonal | P58: Verde | Q58: Regular | S58: 100% Rayón | T58: Camisa Denver dama estampado flor de yuca verde Regular | U58: México | V58: PZS | W58: 53101604 | Y58: 336 | Z58: 775 | AA58: =IF(AND(A58="", B58="", E58=""), "", IF(AB58="", "Válido", IF((LEN(AB58)-LEN(SUBSTITUTE(AB58,"; ","")))/2+1>(LEN(AB58)-LEN(SUBSTITUTE(AB58,"[Aviso]","")))/7, "Con Incidencias", "Válido"))) | AB58: =IF(AND(A58="", B58="", E58=""), "", TEXTJOIN("; ", TRUE, IF(OR(TRIM(A58&"")="", ISNUMBER(SEARCH("FALTA", A58))), "UPC faltante/inválido", ""), IF(AND(A58<>"", IFERROR(_xlfn.XMATCH(A58,$A$2:$A$204,0,1)<>_xlfn.XMATCH(A58,$A$2:$A$204,0,-1),FALSE)), "Código de barras duplicado", ""), IF(AND(E58<>"", COUNTIF($E$2:$E$204, E58)>1), "SKU duplicado", ""), IF(OR(J58="", J58=""), "[Aviso] División no capturada ()", IF(ISNA(MATCH(J58, Criterios!$A$123:$A$126, 0)), "División no válida", "")), IF(OR(K58="", K58=""), "[Aviso] Categoría no capturada ()", IF(ISNA(MATCH(K58, Criterios!$A$81:$A$120, 0)), "Categoría no válida", IF(AND(J58<>"", J58<>"", J58<>VLOOKUP(K58, Criterios!$A$81:$B$120, 2, FALSE)), "División no coincide con Categoría", ""))), IF(OR(L58="", L58=""), "[Aviso] Género no capturado ()", IF(ISNA(MATCH(L58, Criterios!$B$123:$B$127, 0)), "Género no válido", "")), IF(OR(N58="", N58=""), "[Aviso] Temporada no capturada ()", IF(ISNA(MATCH(N58, Criterios!$C$123:$C$128, 0)), "Temporada no válida", "")), IF(OR(O58="", O58=""), "[Aviso] Ciclo de vida no capturado ()", IF(ISNA(MATCH(O58, Criterios!$D$123:$D$124, 0)), "Ciclo de vida no válido", "")))) | AD58: 2 | AE58: WB OUTLET LERMA: 2 | AF58: 2 | AG58: Nuevo – NetSuite con existencia | AH58: Revisión 29/09/2026: Campos sin respaldo: X; Auditoría NetSuite 30/09/2026: llenado desde NetSuite [P,V,Y,T] | 01/10/2026: complementado desde Shopify Western Brothers (match por código de barras): WB Silueta | AI58: No | AK58: ProductosCatalogoEstandar907.xlsx: fila 5107 [N,O,Q,S,U,Y]; G1522_Extraccion_Articulos_NetSuite_2026-09-30.xlsx: fila 56575 [P,V,Y,T] | Shopify WB: producto 8569958039737 / variante 47621319098553 | AL58: 336 | AM58: 899 | AN58: Shopify Western Brothers | AP58: 2 | AR58: Shopify Western Brothers › Western Brothers Outlet Lerma: 2
A59: 7506499530118 | B59: 108417 | C59: Multimarca | D59: C-CM128 | E59: C-CM128-L | F59: L | G59: L | H59: Denver | I59: Camisa Denver dama estampado flor de yuca verde | J59: Ropa | K59: Camisas | L59: Mujer | M59: Denver | N59: SS26 | O59: Seasonal | P59: Verde | Q59: Regular | S59: 100% Rayón | T59: Camisa Denver dama estampado flor de yuca verde Regular | U59: México | V59: PZS | W59: 53101604 | Y59: 336 | Z59: 775 | AA59: =IF(AND(A59="", B59="", E59=""), "", IF(AB59="", "Válido", IF((LEN(AB59)-LEN(SUBSTITUTE(AB59,"; ","")))/2+1>(LEN(AB59)-LEN(SUBSTITUTE(AB59,"[Aviso]","")))/7, "Con Incidencias", "Válido"))) | AB59: =IF(AND(A59="", B59="", E59=""), "", TEXTJOIN("; ", TRUE, IF(OR(TRIM(A59&"")="", ISNUMBER(SEARCH("FALTA", A59))), "UPC faltante/inválido", ""), IF(AND(A59<>"", IFERROR(_xlfn.XMATCH(A59,$A$2:$A$204,0,1)<>_xlfn.XMATCH(A59,$A$2:$A$204,0,-1),FALSE)), "Código de barras duplicado", ""), IF(AND(E59<>"", COUNTIF($E$2:$E$204, E59)>1), "SKU duplicado", ""), IF(OR(J59="", J59=""), "[Aviso] División no capturada ()", IF(ISNA(MATCH(J59, Criterios!$A$123:$A$126, 0)), "División no válida", "")), IF(OR(K59="", K59=""), "[Aviso] Categoría no capturada ()", IF(ISNA(MATCH(K59, Criterios!$A$81:$A$120, 0)), "Categoría no válida", IF(AND(J59<>"", J59<>"", J59<>VLOOKUP(K59, Criterios!$A$81:$B$120, 2, FALSE)), "División no coincide con Categoría", ""))), IF(OR(L59="", L59=""), "[Aviso] Género no capturado ()", IF(ISNA(MATCH(L59, Criterios!$B$123:$B$127, 0)), "Género no válido", "")), IF(OR(N59="", N59=""), "[Aviso] Temporada no capturada ()", IF(ISNA(MATCH(N59, Criterios!$C$123:$C$128, 0)), "Temporada no válida", "")), IF(OR(O59="", O59=""), "[Aviso] Ciclo de vida no capturado ()", IF(ISNA(MATCH(O59, Criterios!$D$123:$D$124, 0)), "Ciclo de vida no válido", "")))) | AD59: 4 | AE59: WB OUTLET LERMA: 4 | AF59: 4 | AG59: Nuevo – NetSuite con existencia | AH59: Revisión 29/09/2026: Campos sin respaldo: X; Auditoría NetSuite 30/09/2026: llenado desde NetSuite [P,V,Y,T] | 01/10/2026: complementado desde Shopify Western Brothers (match por código de barras): WB Silueta | AI59: No | AK59: ProductosCatalogoEstandar907.xlsx: fila 5108 [N,O,Q,S,U,Y]; G1522_Extraccion_Articulos_NetSuite_2026-09-30.xlsx: fila 56576 [P,V,Y,T] | Shopify WB: producto 8569958039737 / variante 47621319131321 | AL59: 336 | AM59: 899 | AN59: Shopify Western Brothers | AP59: 4 | AR59: Shopify Western Brothers › Western Brothers Outlet Lerma: 4
A60: 7506499530125 | B60: 108418 | C60: Multimarca | D60: C-CM128 | E60: C-CM128-XL | F60: XL | G60: XL | H60: Denver | I60: Camisa Denver dama estampado flor de yuca verde | J60: Ropa | K60: Camisas | L60: Mujer | M60: Denver | N60: SS26 | O60: Seasonal | P60: Verde | Q60: Regular | S60: 100% Rayón | T60: Camisa Denver dama estampado flor de yuca verde Regular | U60: México | V60: PZS | W60: 53101604 | Y60: 336 | Z60: 775 | AA60: =IF(AND(A60="", B60="", E60=""), "", IF(AB60="", "Válido", IF((LEN(AB60)-LEN(SUBSTITUTE(AB60,"; ","")))/2+1>(LEN(AB60)-LEN(SUBSTITUTE(AB60,"[Aviso]","")))/7, "Con Incidencias", "Válido"))) | AB60: =IF(AND(A60="", B60="", E60=""), "", TEXTJOIN("; ", TRUE, IF(OR(TRIM(A60&"")="", ISNUMBER(SEARCH("FALTA", A60))), "UPC faltante/inválido", ""), IF(AND(A60<>"", IFERROR(_xlfn.XMATCH(A60,$A$2:$A$204,0,1)<>_xlfn.XMATCH(A60,$A$2:$A$204,0,-1),FALSE)), "Código de barras duplicado", ""), IF(AND(E60<>"", COUNTIF($E$2:$E$204, E60)>1), "SKU duplicado", ""), IF(OR(J60="", J60=""), "[Aviso] División no capturada ()", IF(ISNA(MATCH(J60, Criterios!$A$123:$A$126, 0)), "División no válida", "")), IF(OR(K60="", K60=""), "[Aviso] Categoría no capturada ()", IF(ISNA(MATCH(K60, Criterios!$A$81:$A$120, 0)), "Categoría no válida", IF(AND(J60<>"", J60<>"", J60<>VLOOKUP(K60, Criterios!$A$81:$B$120, 2, FALSE)), "División no coincide con Categoría", ""))), IF(OR(L60="", L60=""), "[Aviso] Género no capturado ()", IF(ISNA(MATCH(L60, Criterios!$B$123:$B$127, 0)), "Género no válido", "")), IF(OR(N60="", N60=""), "[Aviso] Temporada no capturada ()", IF(ISNA(MATCH(N60, Criterios!$C$123:$C$128, 0)), "Temporada no válida", "")), IF(OR(O60="", O60=""), "[Aviso] Ciclo de vida no capturado ()", IF(ISNA(MATCH(O60, Criterios!$D$123:$D$124, 0)), "Ciclo de vida no válido", "")))) | AD60: 1 | AE60: WB OUTLET LERMA: 1 | AF60: 1 | AG60: Nuevo – NetSuite con existencia | AH60: Revisión 29/09/2026: Campos sin respaldo: X; Auditoría NetSuite 30/09/2026: llenado desde NetSuite [P,V,Y,T] | 01/10/2026: complementado desde Shopify Western Brothers (match por código de barras): WB Silueta | AI60: No | AK60: ProductosCatalogoEstandar907.xlsx: fila 5109 [N,O,Q,S,U,Y]; G1522_Extraccion_Articulos_NetSuite_2026-09-30.xlsx: fila 56577 [P,V,Y,T] | Shopify WB: producto 8569958039737 / variante 47621319164089 | AL60: 336 | AM60: 899 | AN60: Shopify Western Brothers | AP60: 1 | AR60: Shopify Western Brothers › Western Brothers Outlet Lerma: 1
A61: 7506499530132 | B61: 108576 | C61: Multimarca | D61: C-CM130 | E61: C-CM130-XS | F61: XS | G61: XS | H61: Denver | I61: Camisa Denver dama estampado establo | J61: Ropa | K61: Camisas | L61: Mujer | M61: Denver | N61: SS26 | O61: Seasonal | P61: Cafe | Q61: Regular | S61: 100% Rayón | T61: Camisa Denver dama estampado establo Regular | U61: México | V61: PZS | W61: 53101604 | Y61: 336 | Z61: 775 | AA61: =IF(AND(A61="", B61="", E61=""), "", IF(AB61="", "Válido", IF((LEN(AB61)-LEN(SUBSTITUTE(AB61,"; ","")))/2+1>(LEN(AB61)-LEN(SUBSTITUTE(AB61,"[Aviso]","")))/7, "Con Incidencias", "Válido"))) | AB61: =IF(AND(A61="", B61="", E61=""), "", TEXTJOIN("; ", TRUE, IF(OR(TRIM(A61&"")="", ISNUMBER(SEARCH("FALTA", A61))), "UPC faltante/inválido", ""), IF(AND(A61<>"", IFERROR(_xlfn.XMATCH(A61,$A$2:$A$204,0,1)<>_xlfn.XMATCH(A61,$A$2:$A$204,0,-1),FALSE)), "Código de barras duplicado", ""), IF(AND(E61<>"", COUNTIF($E$2:$E$204, E61)>1), "SKU duplicado", ""), IF(OR(J61="", J61=""), "[Aviso] División no capturada ()", IF(ISNA(MATCH(J61, Criterios!$A$123:$A$126, 0)), "División no válida", "")), IF(OR(K61="", K61=""), "[Aviso] Categoría no capturada ()", IF(ISNA(MATCH(K61, Criterios!$A$81:$A$120, 0)), "Categoría no válida", IF(AND(J61<>"", J61<>"", J61<>VLOOKUP(K61, Criterios!$A$81:$B$120, 2, FALSE)), "División no coincide con Categoría", ""))), IF(OR(L61="", L61=""), "[Aviso] Género no capturado ()", IF(ISNA(MATCH(L61, Criterios!$B$123:$B$127, 0)), "Género no válido", "")), IF(OR(N61="", N61=""), "[Aviso] Temporada no capturada ()", IF(ISNA(MATCH(N61, Criterios!$C$123:$C$128, 0)), "Temporada no válida", "")), IF(OR(O61="", O61=""), "[Aviso] Ciclo de vida no capturado ()", IF(ISNA(MATCH(O61, Criterios!$D$123:$D$124, 0)), "Ciclo de vida no válido", "")))) | AD61: 0 | AF61: 0 | AG61: Nuevo – NetSuite con existencia | AH61: Revisión 29/09/2026: Campos sin respaldo: X; Auditoría NetSuite 30/09/2026: llenado desde NetSuite [P,V,Y,T] | 01/10/2026: complementado desde Shopify Western Brothers (match por código de barras): WB Silueta | AI61: No | AK61: ProductosCatalogoEstandar907.xlsx: fila 5111 [N,O,Q,S,U,Y]; G1522_Extraccion_Articulos_NetSuite_2026-09-30.xlsx: fila 56735 [P,V,Y,T] | Shopify WB: producto 8569958203577 / variante 47621319491769 | AL61: 336 | AM61: 899 | AN61: Shopify Western Brothers | AP61: 0
A62: 7506499530149 | B62: 108577 | C62: Multimarca | D62: C-CM130 | E62: C-CM130-S | F62: S | G62: S | H62: Denver | I62: Camisa Denver dama estampado establo | J62: Ropa | K62: Camisas | L62: Mujer | M62: Denver | N62: SS26 | O62: Seasonal | P62: Cafe | Q62: Regular | S62: 100% Rayón | T62: Camisa Denver dama estampado establo Regular | U62: México | V62: PZS | W62: 53101604 | Y62: 336 | Z62: 775 | AA62: =IF(AND(A62="", B62="", E62=""), "", IF(AB62="", "Válido", IF((LEN(AB62)-LEN(SUBSTITUTE(AB62,"; ","")))/2+1>(LEN(AB62)-LEN(SUBSTITUTE(AB62,"[Aviso]","")))/7, "Con Incidencias", "Válido"))) | AB62: =IF(AND(A62="", B62="", E62=""), "", TEXTJOIN("; ", TRUE, IF(OR(TRIM(A62&"")="", ISNUMBER(SEARCH("FALTA", A62))), "UPC faltante/inválido", ""), IF(AND(A62<>"", IFERROR(_xlfn.XMATCH(A62,$A$2:$A$204,0,1)<>_xlfn.XMATCH(A62,$A$2:$A$204,0,-1),FALSE)), "Código de barras duplicado", ""), IF(AND(E62<>"", COUNTIF($E$2:$E$204, E62)>1), "SKU duplicado", ""), IF(OR(J62="", J62=""), "[Aviso] División no capturada ()", IF(ISNA(MATCH(J62, Criterios!$A$123:$A$126, 0)), "División no válida", "")), IF(OR(K62="", K62=""), "[Aviso] Categoría no capturada ()", IF(ISNA(MATCH(K62, Criterios!$A$81:$A$120, 0)), "Categoría no válida", IF(AND(J62<>"", J62<>"", J62<>VLOOKUP(K62, Criterios!$A$81:$B$120, 2, FALSE)), "División no coincide con Categoría", ""))), IF(OR(L62="", L62=""), "[Aviso] Género no capturado ()", IF(ISNA(MATCH(L62, Criterios!$B$123:$B$127, 0)), "Género no válido", "")), IF(OR(N62="", N62=""), "[Aviso] Temporada no capturada ()", IF(ISNA(MATCH(N62, Criterios!$C$123:$C$128, 0)), "Temporada no válida", "")), IF(OR(O62="", O62=""), "[Aviso] Ciclo de vida no capturado ()", IF(ISNA(MATCH(O62, Criterios!$D$123:$D$124, 0)), "Ciclo de vida no válido", "")))) | AD62: 0 | AF62: 0 | AG62: Nuevo – NetSuite con existencia | AH62: Revisión 29/09/2026: Campos sin respaldo: X; Auditoría NetSuite 30/09/2026: llenado desde NetSuite [P,V,Y,T] | 01/10/2026: complementado desde Shopify Western Brothers (match por código de barras): WB Silueta | AI62: No | AK62: ProductosCatalogoEstandar907.xlsx: fila 5112 [N,O,Q,S,U,Y]; G1522_Extraccion_Articulos_NetSuite_2026-09-30.xlsx: fila 56736 [P,V,Y,T] | Shopify WB: producto 8569958203577 / variante 47621319524537 | AL62: 336 | AM62: 899 | AN62: Shopify Western Brothers | AP62: 1 | AR62: Shopify Western Brothers › Western Brothers Outlet Lerma: 1
A63: 7506499529709 | B63: 108578 | C63: Multimarca | D63: C-CM130 | E63: C-CM130-M | F63: M | G63: M | H63: Denver | I63: Camisa Denver dama estampado establo | J63: Ropa | K63: Camisas | L63: Mujer | M63: Denver | N63: SS26 | O63: Seasonal | P63: Cafe | Q63: Regular | S63: 100% Rayón | T63: Camisa Denver dama estampado establo Regular | U63: México | V63: PZS | W63: 53101604 | Y63: 336 | Z63: 775 | AA63: =IF(AND(A63="", B63="", E63=""), "", IF(AB63="", "Válido", IF((LEN(AB63)-LEN(SUBSTITUTE(AB63,"; ","")))/2+1>(LEN(AB63)-LEN(SUBSTITUTE(AB63,"[Aviso]","")))/7, "Con Incidencias", "Válido"))) | AB63: =IF(AND(A63="", B63="", E63=""), "", TEXTJOIN("; ", TRUE, IF(OR(TRIM(A63&"")="", ISNUMBER(SEARCH("FALTA", A63))), "UPC faltante/inválido", ""), IF(AND(A63<>"", IFERROR(_xlfn.XMATCH(A63,$A$2:$A$204,0,1)<>_xlfn.XMATCH(A63,$A$2:$A$204,0,-1),FALSE)), "Código de barras duplicado", ""), IF(AND(E63<>"", COUNTIF($E$2:$E$204, E63)>1), "SKU duplicado", ""), IF(OR(J63="", J63=""), "[Aviso] División no capturada ()", IF(ISNA(MATCH(J63, Criterios!$A$123:$A$126, 0)), "División no válida", "")), IF(OR(K63="", K63=""), "[Aviso] Categoría no capturada ()", IF(ISNA(MATCH(K63, Criterios!$A$81:$A$120, 0)), "Categoría no válida", IF(AND(J63<>"", J63<>"", J63<>VLOOKUP(K63, Criterios!$A$81:$B$120, 2, FALSE)), "División no coincide con Categoría", ""))), IF(OR(L63="", L63=""), "[Aviso] Género no capturado ()", IF(ISNA(MATCH(L63, Criterios!$B$123:$B$127, 0)), "Género no válido", "")), IF(OR(N63="", N63=""), "[Aviso] Temporada no capturada ()", IF(ISNA(MATCH(N63, Criterios!$C$123:$C$128, 0)), "Temporada no válida", "")), IF(OR(O63="", O63=""), "[Aviso] Ciclo de vida no capturado ()", IF(ISNA(MATCH(O63, Criterios!$D$123:$D$124, 0)), "Ciclo de vida no válido", "")))) | AD63: 0 | AF63: 0 | AG63: Nuevo – NetSuite sin existencia | AH63: Revisión 29/09/2026: Campos sin respaldo: X; Auditoría NetSuite 30/09/2026: llenado desde NetSuite [P,V,Y,T] | 01/10/2026: complementado desde Shopify Western Brothers (match por código de barras): WB Silueta | AI63: No | AK63: ProductosCatalogoEstandar907.xlsx: fila 5110 [N,O,Q,S,U,Y]; G1522_Extraccion_Articulos_NetSuite_2026-09-30.xlsx: fila 56737 [P,V,Y,T] | Shopify WB: producto 8569958203577 / variante 47621319459001 | AL63: 336 | AM63: 899 | AN63: Shopify Western Brothers | AP63: 0
A64: 7506499530163 | B64: 108579 | C64: Multimarca | D64: C-CM130 | E64: C-CM130-L | F64: L | G64: L | H64: Denver | I64: Camisa Denver dama estampado establo | J64: Ropa | K64: Camisas | L64: Mujer | M64: Denver | N64: SS26 | O64: Seasonal | P64: Cafe | Q64: Regular | S64: 100% Rayón | T64: Camisa Denver dama estampado establo Regular | U64: México | V64: PZS | W64: 53101604 | Y64: 336 | Z64: 775 | AA64: =IF(AND(A64="", B64="", E64=""), "", IF(AB64="", "Válido", IF((LEN(AB64)-LEN(SUBSTITUTE(AB64,"; ","")))/2+1>(LEN(AB64)-LEN(SUBSTITUTE(AB64,"[Aviso]","")))/7, "Con Incidencias", "Válido"))) | AB64: =IF(AND(A64="", B64="", E64=""), "", TEXTJOIN("; ", TRUE, IF(OR(TRIM(A64&"")="", ISNUMBER(SEARCH("FALTA", A64))), "UPC faltante/inválido", ""), IF(AND(A64<>"", IFERROR(_xlfn.XMATCH(A64,$A$2:$A$204,0,1)<>_xlfn.XMATCH(A64,$A$2:$A$204,0,-1),FALSE)), "Código de barras duplicado", ""), IF(AND(E64<>"", COUNTIF($E$2:$E$204, E64)>1), "SKU duplicado", ""), IF(OR(J64="", J64=""), "[Aviso] División no capturada ()", IF(ISNA(MATCH(J64, Criterios!$A$123:$A$126, 0)), "División no válida", "")), IF(OR(K64="", K64=""), "[Aviso] Categoría no capturada ()", IF(ISNA(MATCH(K64, Criterios!$A$81:$A$120, 0)), "Categoría no válida", IF(AND(J64<>"", J64<>"", J64<>VLOOKUP(K64, Criterios!$A$81:$B$120, 2, FALSE)), "División no coincide con Categoría", ""))), IF(OR(L64="", L64=""), "[Aviso] Género no capturado ()", IF(ISNA(MATCH(L64, Criterios!$B$123:$B$127, 0)), "Género no válido", "")), IF(OR(N64="", N64=""), "[Aviso] Temporada no capturada ()", IF(ISNA(MATCH(N64, Criterios!$C$123:$C$128, 0)), "Temporada no válida", "")), IF(OR(O64="", O64=""), "[Aviso] Ciclo de vida no capturado ()", IF(ISNA(MATCH(O64, Criterios!$D$123:$D$124, 0)), "Ciclo de vida no válido", "")))) | AD64: 3 | AE64: WB OUTLET LERMA: 3 | AF64: 3 | AG64: Nuevo – NetSuite con existencia | AH64: Revisión 29/09/2026: Campos sin respaldo: X; Auditoría NetSuite 30/09/2026: llenado desde NetSuite [P,V,Y,T] | 01/10/2026: complementado desde Shopify Western Brothers (match por código de barras): WB Silueta | AI64: No | AK64: ProductosCatalogoEstandar907.xlsx: fila 5113 [N,O,Q,S,U,Y]; G1522_Extraccion_Articulos_NetSuite_2026-09-30.xlsx: fila 56738 [P,V,Y,T] | Shopify WB: producto 8569958203577 / variante 47621319557305 | AL64: 336 | AM64: 899 | AN64: Shopify Western Brothers | AP64: 3 | AR64: Shopify Western Brothers › Western Brothers Outlet Lerma: 3
A65: 7506499570860 | B65: 108419 | C65: Multimarca | D65: CHH062 | E65: CHH062-S | F65: S | G65: S | H65: Denver | I65: Camisa Denver hombre vaquera morada/lineas rojas | J65: Ropa | K65: Camisas | L65: Hombre | M65: Denver | N65: SS26 | O65: Seasonal | P65: Morado | Q65: Regular | S65: 100% Algodón | T65: Camisa Denver hombre vaquera morada/lineas rojas Regular | U65: México | V65: PZS | W65: 53101602 | Y65: 419 | Z65: 947.41379 | AA65: =IF(AND(A65="", B65="", E65=""), "", IF(AB65="", "Válido", IF((LEN(AB65)-LEN(SUBSTITUTE(AB65,"; ","")))/2+1>(LEN(AB65)-LEN(SUBSTITUTE(AB65,"[Aviso]","")))/7, "Con Incidencias", "Válido"))) | AB65: =IF(AND(A65="", B65="", E65=""), "", TEXTJOIN("; ", TRUE, IF(OR(TRIM(A65&"")="", ISNUMBER(SEARCH("FALTA", A65))), "UPC faltante/inválido", ""), IF(AND(A65<>"", IFERROR(_xlfn.XMATCH(A65,$A$2:$A$204,0,1)<>_xlfn.XMATCH(A65,$A$2:$A$204,0,-1),FALSE)), "Código de barras duplicado", ""), IF(AND(E65<>"", COUNTIF($E$2:$E$204, E65)>1), "SKU duplicado", ""), IF(OR(J65="", J65=""), "[Aviso] División no capturada ()", IF(ISNA(MATCH(J65, Criterios!$A$123:$A$126, 0)), "División no válida", "")), IF(OR(K65="", K65=""), "[Aviso] Categoría no capturada ()", IF(ISNA(MATCH(K65, Criterios!$A$81:$A$120, 0)), "Categoría no válida", IF(AND(J65<>"", J65<>"", J65<>VLOOKUP(K65, Criterios!$A$81:$B$120, 2, FALSE)), "División no coincide con Categoría", ""))), IF(OR(L65="", L65=""), "[Aviso] Género no capturado ()", IF(ISNA(MATCH(L65, Criterios!$B$123:$B$127, 0)), "Género no válido", "")), IF(OR(N65="", N65=""), "[Aviso] Temporada no capturada ()", IF(ISNA(MATCH(N65, Criterios!$C$123:$C$128, 0)), "Temporada no válida", "")), IF(OR(O65="", O65=""), "[Aviso] Ciclo de vida no capturado ()", IF(ISNA(MATCH(O65, Criterios!$D$123:$D$124, 0)), "Ciclo de vida no válido", "")))) | AD65: 4 | AE65: WB OUTLET LERMA: 4 | AF65: 4 | AG65: Nuevo – NetSuite con existencia | AH65: Revisión 29/09/2026: Campos sin respaldo: X; Auditoría NetSuite 30/09/2026: llenado desde NetSuite [P,V,Y,T] | 01/10/2026: complementado desde Shopify Western Brothers (match por código de barras): WB Silueta | Homologación G1522 06/10/2026: Validación G1522: Dígito de control del código de barras inválido | AI65: No | AK65: ProductosCatalogoEstandar907.xlsx: fila 5114 [N,O,Q,S,U,Y]; G1522_Extraccion_Articulos_NetSuite_2026-09-30.xlsx: fila 56578 [P,V,Y,T] | Shopify WB: producto 8569958367417 / variante 47621319753913 | AL65: 419 | AM65: 1099 | AN65: Shopify Western Brothers | AP65: 4 | AR65: Shopify Western Brothers › Western Brothers Outlet Lerma: 4
A66: 7506499570861 | B66: 108420 | C66: Multimarca | D66: CHH062 | E66: CHH062-M | F66: M | G66: M | H66: Denver | I66: Camisa Denver hombre vaquera morada/lineas rojas | J66: Ropa | K66: Camisas | L66: Hombre | M66: Denver | N66: SS26 | O66: Seasonal | P66: Morado | Q66: Regular | S66: 100% Algodón | T66: Camisa Denver hombre vaquera morada/lineas rojas Regular | U66: México | V66: PZS | W66: 53101602 | Y66: 419 | Z66: 947.41379 | AA66: =IF(AND(A66="", B66="", E66=""), "", IF(AB66="", "Válido", IF((LEN(AB66)-LEN(SUBSTITUTE(AB66,"; ","")))/2+1>(LEN(AB66)-LEN(SUBSTITUTE(AB66,"[Aviso]","")))/7, "Con Incidencias", "Válido"))) | AB66: =IF(AND(A66="", B66="", E66=""), "", TEXTJOIN("; ", TRUE, IF(OR(TRIM(A66&"")="", ISNUMBER(SEARCH("FALTA", A66))), "UPC faltante/inválido", ""), IF(AND(A66<>"", IFERROR(_xlfn.XMATCH(A66,$A$2:$A$204,0,1)<>_xlfn.XMATCH(A66,$A$2:$A$204,0,-1),FALSE)), "Código de barras duplicado", ""), IF(AND(E66<>"", COUNTIF($E$2:$E$204, E66)>1), "SKU duplicado", ""), IF(OR(J66="", J66=""), "[Aviso] División no capturada ()", IF(ISNA(MATCH(J66, Criterios!$A$123:$A$126, 0)), "División no válida", "")), IF(OR(K66="", K66=""), "[Aviso] Categoría no capturada ()", IF(ISNA(MATCH(K66, Criterios!$A$81:$A$120, 0)), "Categoría no válida", IF(AND(J66<>"", J66<>"", J66<>VLOOKUP(K66, Criterios!$A$81:$B$120, 2, FALSE)), "División no coincide con Categoría", ""))), IF(OR(L66="", L66=""), "[Aviso] Género no capturado ()", IF(ISNA(MATCH(L66, Criterios!$B$123:$B$127, 0)), "Género no válido", "")), IF(OR(N66="", N66=""), "[Aviso] Temporada no capturada ()", IF(ISNA(MATCH(N66, Criterios!$C$123:$C$128, 0)), "Temporada no válida", "")), IF(OR(O66="", O66=""), "[Aviso] Ciclo de vida no capturado ()", IF(ISNA(MATCH(O66, Criterios!$D$123:$D$124, 0)), "Ciclo de vida no válido", "")))) | AD66: 0 | AF66: 0 | AG66: Nuevo – NetSuite sin existencia | AH66: Revisión 29/09/2026: Campos sin respaldo: X; Auditoría NetSuite 30/09/2026: llenado desde NetSuite [P,V,Y,T] | 01/10/2026: complementado desde Shopify Western Brothers (match por código de barras): WB Silueta | Homologación G1522 06/10/2026: Validación G1522: Dígito de control del código de barras inválido | AI66: No | AK66: ProductosCatalogoEstandar907.xlsx: fila 5115 [N,O,Q,S,U,Y]; G1522_Extraccion_Articulos_NetSuite_2026-09-30.xlsx: fila 56579 [P,V,Y,T] | Shopify WB: producto 8569958367417 / variante 47621319786681 | AL66: 419 | AM66: 1099 | AN66: Shopify Western Brothers | AP66: 0
A67: 7506499570862 | B67: 108421 | C67: Multimarca | D67: CHH062 | E67: CHH062-L | F67: L | G67: L | H67: Denver | I67: Camisa Denver hombre vaquera morada/lineas rojas | J67: Ropa | K67: Camisas | L67: Hombre | M67: Denver | N67: SS26 | O67: Seasonal | P67: Morado | Q67: Regular | S67: 100% Algodón | T67: Camisa Denver hombre vaquera morada/lineas rojas Regular | U67: México | V67: PZS | W67: 53101602 | Y67: 419 | Z67: 947.41379 | AA67: =IF(AND(A67="", B67="", E67=""), "", IF(AB67="", "Válido", IF((LEN(AB67)-LEN(SUBSTITUTE(AB67,"; ","")))/2+1>(LEN(AB67)-LEN(SUBSTITUTE(AB67,"[Aviso]","")))/7, "Con Incidencias", "Válido"))) | AB67: =IF(AND(A67="", B67="", E67=""), "", TEXTJOIN("; ", TRUE, IF(OR(TRIM(A67&"")="", ISNUMBER(SEARCH("FALTA", A67))), "UPC faltante/inválido", ""), IF(AND(A67<>"", IFERROR(_xlfn.XMATCH(A67,$A$2:$A$204,0,1)<>_xlfn.XMATCH(A67,$A$2:$A$204,0,-1),FALSE)), "Código de barras duplicado", ""), IF(AND(E67<>"", COUNTIF($E$2:$E$204, E67)>1), "SKU duplicado", ""), IF(OR(J67="", J67=""), "[Aviso] División no capturada ()", IF(ISNA(MATCH(J67, Criterios!$A$123:$A$126, 0)), "División no válida", "")), IF(OR(K67="", K67=""), "[Aviso] Categoría no capturada ()", IF(ISNA(MATCH(K67, Criterios!$A$81:$A$120, 0)), "Categoría no válida", IF(AND(J67<>"", J67<>"", J67<>VLOOKUP(K67, Criterios!$A$81:$B$120, 2, FALSE)), "División no coincide con Categoría", ""))), IF(OR(L67="", L67=""), "[Aviso] Género no capturado ()", IF(ISNA(MATCH(L67, Criterios!$B$123:$B$127, 0)), "Género no válido", "")), IF(OR(N67="", N67=""), "[Aviso] Temporada no capturada ()", IF(ISNA(MATCH(N67, Criterios!$C$123:$C$128, 0)), "Temporada no válida", "")), IF(OR(O67="", O67=""), "[Aviso] Ciclo de vida no capturado ()", IF(ISNA(MATCH(O67, Criterios!$D$123:$D$124, 0)), "Ciclo de vida no válido", "")))) | AD67: 2 | AE67: WB OUTLET LERMA: 2 | AF67: 2 | AG67: Nuevo – NetSuite con existencia | AH67: Revisión 29/09/2026: Campos sin respaldo: X; Auditoría NetSuite 30/09/2026: llenado desde NetSuite [P,V,Y,T] | 01/10/2026: complementado desde Shopify Western Brothers (match por código de barras): WB Silueta | AI67: No | AK67: ProductosCatalogoEstandar907.xlsx: fila 5116 [N,O,Q,S,U,Y]; G1522_Extraccion_Articulos_NetSuite_2026-09-30.xlsx: fila 56580 [P,V,Y,T] | Shopify WB: producto 8569958367417 / variante 47621319819449 | AL67: 419 | AM67: 1099 | AN67: Shopify Western Brothers | AP67: 2 | AR67: Shopify Western Brothers › Western Brothers Outlet Lerma: 2
A68: 7506499570863 | B68: 108422 | C68: Multimarca | D68: CHH062 | E68: CHH062-XL | F68: XL | G68: XL | H68: Denver | I68: Camisa Denver hombre vaquera morada/lineas rojas | J68: Ropa | K68: Camisas | L68: Hombre | M68: Denver | N68: SS26 | O68: Seasonal | P68: Morado | Q68: Regular | S68: 100% Algodón | T68: Camisa Denver hombre vaquera morada/lineas rojas Regular | U68: México | V68: PZS | W68: 53101602 | Y68: 419 | Z68: 947.41379 | AA68: =IF(AND(A68="", B68="", E68=""), "", IF(AB68="", "Válido", IF((LEN(AB68)-LEN(SUBSTITUTE(AB68,"; ","")))/2+1>(LEN(AB68)-LEN(SUBSTITUTE(AB68,"[Aviso]","")))/7, "Con Incidencias", "Válido"))) | AB68: =IF(AND(A68="", B68="", E68=""), "", TEXTJOIN("; ", TRUE, IF(OR(TRIM(A68&"")="", ISNUMBER(SEARCH("FALTA", A68))), "UPC faltante/inválido", ""), IF(AND(A68<>"", IFERROR(_xlfn.XMATCH(A68,$A$2:$A$204,0,1)<>_xlfn.XMATCH(A68,$A$2:$A$204,0,-1),FALSE)), "Código de barras duplicado", ""), IF(AND(E68<>"", COUNTIF($E$2:$E$204, E68)>1), "SKU duplicado", ""), IF(OR(J68="", J68=""), "[Aviso] División no capturada ()", IF(ISNA(MATCH(J68, Criterios!$A$123:$A$126, 0)), "División no válida", "")), IF(OR(K68="", K68=""), "[Aviso] Categoría no capturada ()", IF(ISNA(MATCH(K68, Criterios!$A$81:$A$120, 0)), "Categoría no válida", IF(AND(J68<>"", J68<>"", J68<>VLOOKUP(K68, Criterios!$A$81:$B$120, 2, FALSE)), "División no coincide con Categoría", ""))), IF(OR(L68="", L68=""), "[Aviso] Género no capturado ()", IF(ISNA(MATCH(L68, Criterios!$B$123:$B$127, 0)), "Género no válido", "")), IF(OR(N68="", N68=""), "[Aviso] Temporada no capturada ()", IF(ISNA(MATCH(N68, Criterios!$C$123:$C$128, 0)), "Temporada no válida", "")), IF(OR(O68="", O68=""), "[Aviso] Ciclo de vida no capturado ()", IF(ISNA(MATCH(O68, Criterios!$D$123:$D$124, 0)), "Ciclo de vida no válido", "")))) | AD68: 1 | AE68: WB OUTLET LERMA: 1 | AF68: 1 | AG68: Nuevo – NetSuite con existencia | AH68: Revisión 29/09/2026: Campos sin respaldo: X; Auditoría NetSuite 30/09/2026: llenado desde NetSuite [P,V,Y,T] | 01/10/2026: complementado desde Shopify Western Brothers (match por código de barras): WB Silueta | Homologación G1522 06/10/2026: Validación G1522: Dígito de control del código de barras inválido | AI68: No | AK68: ProductosCatalogoEstandar907.xlsx: fila 5117 [N,O,Q,S,U,Y]; G1522_Extraccion_Articulos_NetSuite_2026-09-30.xlsx: fila 56581 [P,V,Y,T] | Shopify WB: producto 8569958367417 / variante 47621319852217 | AL68: 419 | AM68: 1099 | AN68: Shopify Western Brothers | AP68: 1 | AR68: Shopify Western Brothers › Western Brothers Outlet Lerma: 1
A69: 7506499514958 | B69: 108423 | C69: Multimarca | D69: CM085 | E69: CM085-S | F69: S | G69: S | H69: Denver | I69: Camisa Denver dama print blanco franjas verde | J69: Ropa | K69: Camisas | L69: Mujer | M69: Denver | N69: SS26 | O69: Seasonal | P69: Azul | Q69: Regular | S69: 100% Rayón | T69: Camisa Denver dama print blanco franjas verde Regular | U69: México | V69: PZS | W69: 53101604 | Y69: 336 | Z69: 775 | AA69: =IF(AND(A69="", B69="", E69=""), "", IF(AB69="", "Válido", IF((LEN(AB69)-LEN(SUBSTITUTE(AB69,"; ","")))/2+1>(LEN(AB69)-LEN(SUBSTITUTE(AB69,"[Aviso]","")))/7, "Con Incidencias", "Válido"))) | AB69: =IF(AND(A69="", B69="", E69=""), "", TEXTJOIN("; ", TRUE, IF(OR(TRIM(A69&"")="", ISNUMBER(SEARCH("FALTA", A69))), "UPC faltante/inválido", ""), IF(AND(A69<>"", IFERROR(_xlfn.XMATCH(A69,$A$2:$A$204,0,1)<>_xlfn.XMATCH(A69,$A$2:$A$204,0,-1),FALSE)), "Código de barras duplicado", ""), IF(AND(E69<>"", COUNTIF($E$2:$E$204, E69)>1), "SKU duplicado", ""), IF(OR(J69="", J69=""), "[Aviso] División no capturada ()", IF(ISNA(MATCH(J69, Criterios!$A$123:$A$126, 0)), "División no válida", "")), IF(OR(K69="", K69=""), "[Aviso] Categoría no capturada ()", IF(ISNA(MATCH(K69, Criterios!$A$81:$A$120, 0)), "Categoría no válida", IF(AND(J69<>"", J69<>"", J69<>VLOOKUP(K69, Criterios!$A$81:$B$120, 2, FALSE)), "División no coincide con Categoría", ""))), IF(OR(L69="", L69=""), "[Aviso] Género no capturado ()", IF(ISNA(MATCH(L69, Criterios!$B$123:$B$127, 0)), "Género no válido", "")), IF(OR(N69="", N69=""), "[Aviso] Temporada no capturada ()", IF(ISNA(MATCH(N69, Criterios!$C$123:$C$128, 0)), "Temporada no válida", "")), IF(OR(O69="", O69=""), "[Aviso] Ciclo de vida no capturado ()", IF(ISNA(MATCH(O69, Criterios!$D$123:$D$124, 0)), "Ciclo de vida no válido", "")))) | AD69: 4 | AE69: WB OUTLET LERMA: 4 | AF69: 4 | AG69: Nuevo – NetSuite con existencia | AH69: Revisión 29/09/2026: Campos sin respaldo: X; Auditoría NetSuite 30/09/2026: llenado desde NetSuite [P,V,Y,T] | 01/10/2026: complementado desde Shopify Western Brothers (match por código de barras): WB Silueta | 01/10/2026: Shopify Western Brothers trae Color «Blanco» — se conservó el valor de Productos | AI69: No | AK69: ProductosCatalogoEstandar907.xlsx: fila 5118 [N,O,Q,S,U,Y]; G1522_Extraccion_Articulos_NetSuite_2026-09-30.xlsx: fila 56582 [P,V,Y,T] | Shopify WB: producto 8569958498489 / variante 47621319983289 | AL69: 336 | AM69: 899 | AN69: Shopify Western Brothers | AP69: 4 | AR69: Shopify Western Brothers › Western Brothers Outlet Lerma: 4
A70: 7506499514965 | B70: 108424 | C70: Multimarca | D70: CM085 | E70: CM085-M | F70: M | G70: M | H70: Denver | I70: Camisa Denver dama print blanco franjas verde | J70: Ropa | K70: Camisas | L70: Mujer | M70: Denver | N70: SS26 | O70: Seasonal | P70: Azul | Q70: Regular | S70: 100% Rayón | T70: Camisa Denver dama print blanco franjas verde Regular | U70: México | V70: PZS | W70: 53101604 | Y70: 336 | Z70: 775 | AA70: =IF(AND(A70="", B70="", E70=""), "", IF(AB70="", "Válido", IF((LEN(AB70)-LEN(SUBSTITUTE(AB70,"; ","")))/2+1>(LEN(AB70)-LEN(SUBSTITUTE(AB70,"[Aviso]","")))/7, "Con Incidencias", "Válido"))) | AB70: =IF(AND(A70="", B70="", E70=""), "", TEXTJOIN("; ", TRUE, IF(OR(TRIM(A70&"")="", ISNUMBER(SEARCH("FALTA", A70))), "UPC faltante/inválido", ""), IF(AND(A70<>"", IFERROR(_xlfn.XMATCH(A70,$A$2:$A$204,0,1)<>_xlfn.XMATCH(A70,$A$2:$A$204,0,-1),FALSE)), "Código de barras duplicado", ""), IF(AND(E70<>"", COUNTIF($E$2:$E$204, E70)>1), "SKU duplicado", ""), IF(OR(J70="", J70=""), "[Aviso] División no capturada ()", IF(ISNA(MATCH(J70, Criterios!$A$123:$A$126, 0)), "División no válida", "")), IF(OR(K70="", K70=""), "[Aviso] Categoría no capturada ()", IF(ISNA(MATCH(K70, Criterios!$A$81:$A$120, 0)), "Categoría no válida", IF(AND(J70<>"", J70<>"", J70<>VLOOKUP(K70, Criterios!$A$81:$B$120, 2, FALSE)), "División no coincide con Categoría", ""))), IF(OR(L70="", L70=""), "[Aviso] Género no capturado ()", IF(ISNA(MATCH(L70, Criterios!$B$123:$B$127, 0)), "Género no válido", "")), IF(OR(N70="", N70=""), "[Aviso] Temporada no capturada ()", IF(ISNA(MATCH(N70, Criterios!$C$123:$C$128, 0)), "Temporada no válida", "")), IF(OR(O70="", O70=""), "[Aviso] Ciclo de vida no capturado ()", IF(ISNA(MATCH(O70, Criterios!$D$123:$D$124, 0)), "Ciclo de vida no válido", "")))) | AD70: 2 | AE70: WB OUTLET LERMA: 2 | AF70: 2 | AG70: Nuevo – NetSuite con existencia | AH70: Revisión 29/09/2026: Campos sin respaldo: X; Auditoría NetSuite 30/09/2026: llenado desde NetSuite [P,V,Y,T] | 01/10/2026: complementado desde Shopify Western Brothers (match por código de barras): WB Silueta | 01/10/2026: Shopify Western Brothers trae Color «Blanco» — se conservó el valor de Productos | AI70: No | AK70: ProductosCatalogoEstandar907.xlsx: fila 5119 [N,O,Q,S,U,Y]; G1522_Extraccion_Articulos_NetSuite_2026-09-30.xlsx: fila 56583 [P,V,Y,T] | Shopify WB: producto 8569958498489 / variante 47621320016057 | AL70: 336 | AM70: 899 | AN70: Shopify Western Brothers | AP70: 2 | AR70: Shopify Western Brothers › Western Brothers Outlet Lerma: 2
A71: 7506499514972 | B71: 108425 | C71: Multimarca | D71: CM085 | E71: CM085-L | F71: L | G71: L | H71: Denver | I71: Camisa Denver dama print blanco franjas verde | J71: Ropa | K71: Camisas | L71: Mujer | M71: Denver | N71: SS26 | O71: Seasonal | P71: Azul | Q71: Regular | S71: 100% Rayón | T71: Camisa Denver dama print blanco franjas verde Regular | U71: México | V71: PZS | W71: 53101604 | Y71: 336 | Z71: 775 | AA71: =IF(AND(A71="", B71="", E71=""), "", IF(AB71="", "Válido", IF((LEN(AB71)-LEN(SUBSTITUTE(AB71,"; ","")))/2+1>(LEN(AB71)-LEN(SUBSTITUTE(AB71,"[Aviso]","")))/7, "Con Incidencias", "Válido"))) | AB71: =IF(AND(A71="", B71="", E71=""), "", TEXTJOIN("; ", TRUE, IF(OR(TRIM(A71&"")="", ISNUMBER(SEARCH("FALTA", A71))), "UPC faltante/inválido", ""), IF(AND(A71<>"", IFERROR(_xlfn.XMATCH(A71,$A$2:$A$204,0,1)<>_xlfn.XMATCH(A71,$A$2:$A$204,0,-1),FALSE)), "Código de barras duplicado", ""), IF(AND(E71<>"", COUNTIF($E$2:$E$204, E71)>1), "SKU duplicado", ""), IF(OR(J71="", J71=""), "[Aviso] División no capturada ()", IF(ISNA(MATCH(J71, Criterios!$A$123:$A$126, 0)), "División no válida", "")), IF(OR(K71="", K71=""), "[Aviso] Categoría no capturada ()", IF(ISNA(MATCH(K71, Criterios!$A$81:$A$120, 0)), "Categoría no válida", IF(AND(J71<>"", J71<>"", J71<>VLOOKUP(K71, Criterios!$A$81:$B$120, 2, FALSE)), "División no coincide con Categoría", ""))), IF(OR(L71="", L71=""), "[Aviso] Género no capturado ()", IF(ISNA(MATCH(L71, Criterios!$B$123:$B$127, 0)), "Género no válido", "")), IF(OR(N71="", N71=""), "[Aviso] Temporada no capturada ()", IF(ISNA(MATCH(N71, Criterios!$C$123:$C$128, 0)), "Temporada no válida", "")), IF(OR(O71="", O71=""), "[Aviso] Ciclo de vida no capturado ()", IF(ISNA(MATCH(O71, Criterios!$D$123:$D$124, 0)), "Ciclo de vida no válido", "")))) | AD71: 1 | AE71: WB OUTLET LERMA: 1 | AF71: 1 | AG71: Nuevo – NetSuite con existencia | AH71: Revisión 29/09/2026: Campos sin respaldo: X; Auditoría NetSuite 30/09/2026: llenado desde NetSuite [P,V,Y,T] | 01/10/2026: complementado desde Shopify Western Brothers (match por código de barras): WB Silueta | 01/10/2026: Shopify Western Brothers trae Color «Blanco» — se conservó el valor de Productos | AI71: No | AK71: ProductosCatalogoEstandar907.xlsx: fila 5120 [N,O,Q,S,U,Y]; G1522_Extraccion_Articulos_NetSuite_2026-09-30.xlsx: fila 56584 [P,V,Y,T] | Shopify WB: producto 8569958498489 / variante 47621320048825 | AL71: 336 | AM71: 899 | AN71: Shopify Western Brothers | AP71: 1 | AR71: Shopify Western Brothers › Western Brothers Outlet Lerma: 1
