Workbook

Sheet Escaneo Diario
A1: GRUPO QUINCE 22 | CONTROL DE INVENTARIOS Y CONTEO CÍCLICO DIARIO
A2: 📅 FECHA ACTUAL | C2: 📦 TOTAL ESCANEOS | E2: 🏷️ PRODUCTOS ÚNICOS | H2: 📊 TOTAL DE PIEZAS | J2: 🚀 ACCIÓN OPERATIVA
A3: =TODAY() | C3: =COUNTIF(C7:C1000, "<>") | E3: =IFERROR(__xludf.DUMMYFUNCTION("IFERROR(ROWS(UNIQUE(FILTER(D7:D1000, D7:D1000<>""""))), 0)"),0.0) | H3: =COUNTIF(C7:C1000, "<>") | J3: FINALIZAR ESCANEO
A4: Jornada en curso | C4: Registros capturados | E4: SKUs distintos | H4: Unidades contadas | J4: Asignar Folios y Archivar
A6: Fecha/Hora | B6: Ubicación/Rack | C6: UPC CODE | D6: SKU | E6: Marca | F6: Descripción | G6: División | H6: Categoría | I6: Talla / Size | J6: Alertas y Duplicados
D7: {=IF($C7="","",IFNA(_xlfn.XLOOKUP($C7,Productos!$A:$A,Productos!$E:$E,IFNA(_xlfn.XLOOKUP(TEXT($C7,"0"),Productos!$A:$A,Productos!$E:$E,IFNA(_xlfn.XLOOKUP(IFERROR(VALUE($C7),""),Productos!$A:$A,Productos!$E:$E,_xlfn.XLOOKUP($C7,Productos!$E:$E,Productos!$E:$E,"NO ENCONTRADO")),"NO ENCONTRADO")),"NO ENCONTRADO")),"NO ENCONTRADO"))} | E7: {=IF(OR($D7="",$D7="NO ENCONTRADO"),"",_xlfn.XLOOKUP($D7,Productos!$E:$E,Productos!$H:$H,""))} | F7: {=IF(OR($D7="",$D7="NO ENCONTRADO"),"",_xlfn.XLOOKUP($D7,Productos!$E:$E,Productos!$I:$I,""))} | G7: {=IF(OR($D7="",$D7="NO ENCONTRADO"),"",_xlfn.XLOOKUP($D7,Productos!$E:$E,Productos!$J:$J,""))} | H7: {=IF(OR($D7="",$D7="NO ENCONTRADO"),"",_xlfn.XLOOKUP($D7,Productos!$E:$E,Productos!$K:$K,""))} | I7: {=IF(OR($D7="",$D7="NO ENCONTRADO"),"",_xlfn.XLOOKUP($D7,Productos!$E:$E,Productos!$F:$F,""))} | J7: =IF($C7="","",IF($D7="NO ENCONTRADO",IF(COUNTIF($C$7:$C$1000,$C7)>1,"⚠️ No encontrado | Duplicado","⚠️ No encontrado"),IF(COUNTIF($C$7:$C$1000,$C7)>1,"⚠️ Duplicado","Verificado")))
D8: {=IF($C8="","",IFNA(_xlfn.XLOOKUP($C8,Productos!$A:$A,Productos!$E:$E,IFNA(_xlfn.XLOOKUP(TEXT($C8,"0"),Productos!$A:$A,Productos!$E:$E,IFNA(_xlfn.XLOOKUP(IFERROR(VALUE($C8),""),Productos!$A:$A,Productos!$E:$E,_xlfn.XLOOKUP($C8,Productos!$E:$E,Productos!$E:$E,"NO ENCONTRADO")),"NO ENCONTRADO")),"NO ENCONTRADO")),"NO ENCONTRADO"))} | E8: {=IF(OR($D8="",$D8="NO ENCONTRADO"),"",_xlfn.XLOOKUP($D8,Productos!$E:$E,Productos!$H:$H,""))} | F8: {=IF(OR($D8="",$D8="NO ENCONTRADO"),"",_xlfn.XLOOKUP($D8,Productos!$E:$E,Productos!$I:$I,""))} | G8: {=IF(OR($D8="",$D8="NO ENCONTRADO"),"",_xlfn.XLOOKUP($D8,Productos!$E:$E,Productos!$J:$J,""))} | H8: {=IF(OR($D8="",$D8="NO ENCONTRADO"),"",_xlfn.XLOOKUP($D8,Productos!$E:$E,Productos!$K:$K,""))} | I8: {=IF(OR($D8="",$D8="NO ENCONTRADO"),"",_xlfn.XLOOKUP($D8,Productos!$E:$E,Productos!$F:$F,""))} | J8: =IF($C8="","",IF($D8="NO ENCONTRADO",IF(COUNTIF($C$7:$C$1000,$C8)>1,"⚠️ No encontrado | Duplicado","⚠️ No encontrado"),IF(COUNTIF($C$7:$C$1000,$C8)>1,"⚠️ Duplicado","Verificado")))
D9: {=IF($C9="","",IFNA(_xlfn.XLOOKUP($C9,Productos!$A:$A,Productos!$E:$E,IFNA(_xlfn.XLOOKUP(TEXT($C9,"0"),Productos!$A:$A,Productos!$E:$E,IFNA(_xlfn.XLOOKUP(IFERROR(VALUE($C9),""),Productos!$A:$A,Productos!$E:$E,_xlfn.XLOOKUP($C9,Productos!$E:$E,Productos!$E:$E,"NO ENCONTRADO")),"NO ENCONTRADO")),"NO ENCONTRADO")),"NO ENCONTRADO"))} | E9: {=IF(OR($D9="",$D9="NO ENCONTRADO"),"",_xlfn.XLOOKUP($D9,Productos!$E:$E,Productos!$H:$H,""))} | F9: {=IF(OR($D9="",$D9="NO ENCONTRADO"),"",_xlfn.XLOOKUP($D9,Productos!$E:$E,Productos!$I:$I,""))} | G9: {=IF(OR($D9="",$D9="NO ENCONTRADO"),"",_xlfn.XLOOKUP($D9,Productos!$E:$E,Productos!$J:$J,""))} | H9: {=IF(OR($D9="",$D9="NO ENCONTRADO"),"",_xlfn.XLOOKUP($D9,Productos!$E:$E,Productos!$K:$K,""))} | I9: {=IF(OR($D9="",$D9="NO ENCONTRADO"),"",_xlfn.XLOOKUP($D9,Productos!$E:$E,Productos!$F:$F,""))} | J9: =IF($C9="","",IF($D9="NO ENCONTRADO",IF(COUNTIF($C$7:$C$1000,$C9)>1,"⚠️ No encontrado | Duplicado","⚠️ No encontrado"),IF(COUNTIF($C$7:$C$1000,$C9)>1,"⚠️ Duplicado","Verificado")))
D10: {=IF($C10="","",IFNA(_xlfn.XLOOKUP($C10,Productos!$A:$A,Productos!$E:$E,IFNA(_xlfn.XLOOKUP(TEXT($C10,"0"),Productos!$A:$A,Productos!$E:$E,IFNA(_xlfn.XLOOKUP(IFERROR(VALUE($C10),""),Productos!$A:$A,Productos!$E:$E,_xlfn.XLOOKUP($C10,Productos!$E:$E,Productos!$E:$E,"NO ENCONTRADO")),"NO ENCONTRADO")),"NO ENCONTRADO")),"NO ENCONTRADO"))} | E10: {=IF(OR($D10="",$D10="NO ENCONTRADO"),"",_xlfn.XLOOKUP($D10,Productos!$E:$E,Productos!$H:$H,""))} | F10: {=IF(OR($D10="",$D10="NO ENCONTRADO"),"",_xlfn.XLOOKUP($D10,Productos!$E:$E,Productos!$I:$I,""))} | G10: {=IF(OR($D10="",$D10="NO ENCONTRADO"),"",_xlfn.XLOOKUP($D10,Productos!$E:$E,Productos!$J:$J,""))} | H10: {=IF(OR($D10="",$D10="NO ENCONTRADO"),"",_xlfn.XLOOKUP($D10,Productos!$E:$E,Productos!$K:$K,""))} | I10: {=IF(OR($D10="",$D10="NO ENCONTRADO"),"",_xlfn.XLOOKUP($D10,Productos!$E:$E,Productos!$F:$F,""))} | J10: =IF($C10="","",IF($D10="NO ENCONTRADO",IF(COUNTIF($C$7:$C$1000,$C10)>1,"⚠️ No encontrado | Duplicado","⚠️ No encontrado"),IF(COUNTIF($C$7:$C$1000,$C10)>1,"⚠️ Duplicado","Verificado")))
D11: {=IF($C11="","",IFNA(_xlfn.XLOOKUP($C11,Productos!$A:$A,Productos!$E:$E,IFNA(_xlfn.XLOOKUP(TEXT($C11,"0"),Productos!$A:$A,Productos!$E:$E,IFNA(_xlfn.XLOOKUP(IFERROR(VALUE($C11),""),Productos!$A:$A,Productos!$E:$E,_xlfn.XLOOKUP($C11,Productos!$E:$E,Productos!$E:$E,"NO ENCONTRADO")),"NO ENCONTRADO")),"NO ENCONTRADO")),"NO ENCONTRADO"))} | E11: {=IF(OR($D11="",$D11="NO ENCONTRADO"),"",_xlfn.XLOOKUP($D11,Productos!$E:$E,Productos!$H:$H,""))} | F11: {=IF(OR($D11="",$D11="NO ENCONTRADO"),"",_xlfn.XLOOKUP($D11,Productos!$E:$E,Productos!$I:$I,""))} | G11: {=IF(OR($D11="",$D11="NO ENCONTRADO"),"",_xlfn.XLOOKUP($D11,Productos!$E:$E,Productos!$J:$J,""))} | H11: {=IF(OR($D11="",$D11="NO ENCONTRADO"),"",_xlfn.XLOOKUP($D11,Productos!$E:$E,Productos!$K:$K,""))} | I11: {=IF(OR($D11="",$D11="NO ENCONTRADO"),"",_xlfn.XLOOKUP($D11,Productos!$E:$E,Productos!$F:$F,""))} | J11: =IF($C11="","",IF($D11="NO ENCONTRADO",IF(COUNTIF($C$7:$C$1000,$C11)>1,"⚠️ No encontrado | Duplicado","⚠️ No encontrado"),IF(COUNTIF($C$7:$C$1000,$C11)>1,"⚠️ Duplicado","Verificado")))
D12: {=IF($C12="","",IFNA(_xlfn.XLOOKUP($C12,Productos!$A:$A,Productos!$E:$E,IFNA(_xlfn.XLOOKUP(TEXT($C12,"0"),Productos!$A:$A,Productos!$E:$E,IFNA(_xlfn.XLOOKUP(IFERROR(VALUE($C12),""),Productos!$A:$A,Productos!$E:$E,_xlfn.XLOOKUP($C12,Productos!$E:$E,Productos!$E:$E,"NO ENCONTRADO")),"NO ENCONTRADO")),"NO ENCONTRADO")),"NO ENCONTRADO"))} | E12: {=IF(OR($D12="",$D12="NO ENCONTRADO"),"",_xlfn.XLOOKUP($D12,Productos!$E:$E,Productos!$H:$H,""))} | F12: {=IF(OR($D12="",$D12="NO ENCONTRADO"),"",_xlfn.XLOOKUP($D12,Productos!$E:$E,Productos!$I:$I,""))} | G12: {=IF(OR($D12="",$D12="NO ENCONTRADO"),"",_xlfn.XLOOKUP($D12,Productos!$E:$E,Productos!$J:$J,""))} | H12: {=IF(OR($D12="",$D12="NO ENCONTRADO"),"",_xlfn.XLOOKUP($D12,Productos!$E:$E,Productos!$K:$K,""))} | I12: {=IF(OR($D12="",$D12="NO ENCONTRADO"),"",_xlfn.XLOOKUP($D12,Productos!$E:$E,Productos!$F:$F,""))} | J12: =IF($C12="","",IF($D12="NO ENCONTRADO",IF(COUNTIF($C$7:$C$1000,$C12)>1,"⚠️ No encontrado | Duplicado","⚠️ No encontrado"),IF(COUNTIF($C$7:$C$1000,$C12)>1,"⚠️ Duplicado","Verificado")))
D13: {=IF($C13="","",IFNA(_xlfn.XLOOKUP($C13,Productos!$A:$A,Productos!$E:$E,IFNA(_xlfn.XLOOKUP(TEXT($C13,"0"),Productos!$A:$A,Productos!$E:$E,IFNA(_xlfn.XLOOKUP(IFERROR(VALUE($C13),""),Productos!$A:$A,Productos!$E:$E,_xlfn.XLOOKUP($C13,Productos!$E:$E,Productos!$E:$E,"NO ENCONTRADO")),"NO ENCONTRADO")),"NO ENCONTRADO")),"NO ENCONTRADO"))} | E13: {=IF(OR($D13="",$D13="NO ENCONTRADO"),"",_xlfn.XLOOKUP($D13,Productos!$E:$E,Productos!$H:$H,""))} | F13: {=IF(OR($D13="",$D13="NO ENCONTRADO"),"",_xlfn.XLOOKUP($D13,Productos!$E:$E,Productos!$I:$I,""))} | G13: {=IF(OR($D13="",$D13="NO ENCONTRADO"),"",_xlfn.XLOOKUP($D13,Productos!$E:$E,Productos!$J:$J,""))} | H13: {=IF(OR($D13="",$D13="NO ENCONTRADO"),"",_xlfn.XLOOKUP($D13,Productos!$E:$E,Productos!$K:$K,""))} | I13: {=IF(OR($D13="",$D13="NO ENCONTRADO"),"",_xlfn.XLOOKUP($D13,Productos!$E:$E,Productos!$F:$F,""))} | J13: =IF($C13="","",IF($D13="NO ENCONTRADO",IF(COUNTIF($C$7:$C$1000,$C13)>1,"⚠️ No encontrado | Duplicado","⚠️ No encontrado"),IF(COUNTIF($C$7:$C$1000,$C13)>1,"⚠️ Duplicado","Verificado")))
D14: {=IF($C14="","",IFNA(_xlfn.XLOOKUP($C14,Productos!$A:$A,Productos!$E:$E,IFNA(_xlfn.XLOOKUP(TEXT($C14,"0"),Productos!$A:$A,Productos!$E:$E,IFNA(_xlfn.XLOOKUP(IFERROR(VALUE($C14),""),Productos!$A:$A,Productos!$E:$E,_xlfn.XLOOKUP($C14,Productos!$E:$E,Productos!$E:$E,"NO ENCONTRADO")),"NO ENCONTRADO")),"NO ENCONTRADO")),"NO ENCONTRADO"))} | E14: {=IF(OR($D14="",$D14="NO ENCONTRADO"),"",_xlfn.XLOOKUP($D14,Productos!$E:$E,Productos!$H:$H,""))} | F14: {=IF(OR($D14="",$D14="NO ENCONTRADO"),"",_xlfn.XLOOKUP($D14,Productos!$E:$E,Productos!$I:$I,""))} | G14: {=IF(OR($D14="",$D14="NO ENCONTRADO"),"",_xlfn.XLOOKUP($D14,Productos!$E:$E,Productos!$J:$J,""))} | H14: {=IF(OR($D14="",$D14="NO ENCONTRADO"),"",_xlfn.XLOOKUP($D14,Productos!$E:$E,Productos!$K:$K,""))} | I14: {=IF(OR($D14="",$D14="NO ENCONTRADO"),"",_xlfn.XLOOKUP($D14,Productos!$E:$E,Productos!$F:$F,""))} | J14: =IF($C14="","",IF($D14="NO ENCONTRADO",IF(COUNTIF($C$7:$C$1000,$C14)>1,"⚠️ No encontrado | Duplicado","⚠️ No encontrado"),IF(COUNTIF($C$7:$C$1000,$C14)>1,"⚠️ Duplicado","Verificado")))
D15: {=IF($C15="","",IFNA(_xlfn.XLOOKUP($C15,Productos!$A:$A,Productos!$E:$E,IFNA(_xlfn.XLOOKUP(TEXT($C15,"0"),Productos!$A:$A,Productos!$E:$E,IFNA(_xlfn.XLOOKUP(IFERROR(VALUE($C15),""),Productos!$A:$A,Productos!$E:$E,_xlfn.XLOOKUP($C15,Productos!$E:$E,Productos!$E:$E,"NO ENCONTRADO")),"NO ENCONTRADO")),"NO ENCONTRADO")),"NO ENCONTRADO"))} | E15: {=IF(OR($D15="",$D15="NO ENCONTRADO"),"",_xlfn.XLOOKUP($D15,Productos!$E:$E,Productos!$H:$H,""))} | F15: {=IF(OR($D15="",$D15="NO ENCONTRADO"),"",_xlfn.XLOOKUP($D15,Productos!$E:$E,Productos!$I:$I,""))} | G15: {=IF(OR($D15="",$D15="NO ENCONTRADO"),"",_xlfn.XLOOKUP($D15,Productos!$E:$E,Productos!$J:$J,""))} | H15: {=IF(OR($D15="",$D15="NO ENCONTRADO"),"",_xlfn.XLOOKUP($D15,Productos!$E:$E,Productos!$K:$K,""))} | I15: {=IF(OR($D15="",$D15="NO ENCONTRADO"),"",_xlfn.XLOOKUP($D15,Productos!$E:$E,Productos!$F:$F,""))} | J15: =IF($C15="","",IF($D15="NO ENCONTRADO",IF(COUNTIF($C$7:$C$1000,$C15)>1,"⚠️ No encontrado | Duplicado","⚠️ No encontrado"),IF(COUNTIF($C$7:$C$1000,$C15)>1,"⚠️ Duplicado","Verificado")))
D16: {=IF($C16="","",IFNA(_xlfn.XLOOKUP($C16,Productos!$A:$A,Productos!$E:$E,IFNA(_xlfn.XLOOKUP(TEXT($C16,"0"),Productos!$A:$A,Productos!$E:$E,IFNA(_xlfn.XLOOKUP(IFERROR(VALUE($C16),""),Productos!$A:$A,Productos!$E:$E,_xlfn.XLOOKUP($C16,Productos!$E:$E,Productos!$E:$E,"NO ENCONTRADO")),"NO ENCONTRADO")),"NO ENCONTRADO")),"NO ENCONTRADO"))} | E16: {=IF(OR($D16="",$D16="NO ENCONTRADO"),"",_xlfn.XLOOKUP($D16,Productos!$E:$E,Productos!$H:$H,""))} | F16: {=IF(OR($D16="",$D16="NO ENCONTRADO"),"",_xlfn.XLOOKUP($D16,Productos!$E:$E,Productos!$I:$I,""))} | G16: {=IF(OR($D16="",$D16="NO ENCONTRADO"),"",_xlfn.XLOOKUP($D16,Productos!$E:$E,Productos!$J:$J,""))} | H16: {=IF(OR($D16="",$D16="NO ENCONTRADO"),"",_xlfn.XLOOKUP($D16,Productos!$E:$E,Productos!$K:$K,""))} | I16: {=IF(OR($D16="",$D16="NO ENCONTRADO"),"",_xlfn.XLOOKUP($D16,Productos!$E:$E,Productos!$F:$F,""))} | J16: =IF($C16="","",IF($D16="NO ENCONTRADO",IF(COUNTIF($C$7:$C$1000,$C16)>1,"⚠️ No encontrado | Duplicado","⚠️ No encontrado"),IF(COUNTIF($C$7:$C$1000,$C16)>1,"⚠️ Duplicado","Verificado")))
D17: {=IF($C17="","",IFNA(_xlfn.XLOOKUP($C17,Productos!$A:$A,Productos!$E:$E,IFNA(_xlfn.XLOOKUP(TEXT($C17,"0"),Productos!$A:$A,Productos!$E:$E,IFNA(_xlfn.XLOOKUP(IFERROR(VALUE($C17),""),Productos!$A:$A,Productos!$E:$E,_xlfn.XLOOKUP($C17,Productos!$E:$E,Productos!$E:$E,"NO ENCONTRADO")),"NO ENCONTRADO")),"NO ENCONTRADO")),"NO ENCONTRADO"))} | E17: {=IF(OR($D17="",$D17="NO ENCONTRADO"),"",_xlfn.XLOOKUP($D17,Productos!$E:$E,Productos!$H:$H,""))} | F17: {=IF(OR($D17="",$D17="NO ENCONTRADO"),"",_xlfn.XLOOKUP($D17,Productos!$E:$E,Productos!$I:$I,""))} | G17: {=IF(OR($D17="",$D17="NO ENCONTRADO"),"",_xlfn.XLOOKUP($D17,Productos!$E:$E,Productos!$J:$J,""))} | H17: {=IF(OR($D17="",$D17="NO ENCONTRADO"),"",_xlfn.XLOOKUP($D17,Productos!$E:$E,Productos!$K:$K,""))} | I17: {=IF(OR($D17="",$D17="NO ENCONTRADO"),"",_xlfn.XLOOKUP($D17,Productos!$E:$E,Productos!$F:$F,""))} | J17: =IF($C17="","",IF($D17="NO ENCONTRADO",IF(COUNTIF($C$7:$C$1000,$C17)>1,"⚠️ No encontrado | Duplicado","⚠️ No encontrado"),IF(COUNTIF($C$7:$C$1000,$C17)>1,"⚠️ Duplicado","Verificado")))
D18: {=IF($C18="","",IFNA(_xlfn.XLOOKUP($C18,Productos!$A:$A,Productos!$E:$E,IFNA(_xlfn.XLOOKUP(TEXT($C18,"0"),Productos!$A:$A,Productos!$E:$E,IFNA(_xlfn.XLOOKUP(IFERROR(VALUE($C18),""),Productos!$A:$A,Productos!$E:$E,_xlfn.XLOOKUP($C18,Productos!$E:$E,Productos!$E:$E,"NO ENCONTRADO")),"NO ENCONTRADO")),"NO ENCONTRADO")),"NO ENCONTRADO"))} | E18: {=IF(OR($D18="",$D18="NO ENCONTRADO"),"",_xlfn.XLOOKUP($D18,Productos!$E:$E,Productos!$H:$H,""))} | F18: {=IF(OR($D18="",$D18="NO ENCONTRADO"),"",_xlfn.XLOOKUP($D18,Productos!$E:$E,Productos!$I:$I,""))} | G18: {=IF(OR($D18="",$D18="NO ENCONTRADO"),"",_xlfn.XLOOKUP($D18,Productos!$E:$E,Productos!$J:$J,""))} | H18: {=IF(OR($D18="",$D18="NO ENCONTRADO"),"",_xlfn.XLOOKUP($D18,Productos!$E:$E,Productos!$K:$K,""))} | I18: {=IF(OR($D18="",$D18="NO ENCONTRADO"),"",_xlfn.XLOOKUP($D18,Productos!$E:$E,Productos!$F:$F,""))} | J18: =IF($C18="","",IF($D18="NO ENCONTRADO",IF(COUNTIF($C$7:$C$1000,$C18)>1,"⚠️ No encontrado | Duplicado","⚠️ No encontrado"),IF(COUNTIF($C$7:$C$1000,$C18)>1,"⚠️ Duplicado","Verificado")))
... D1000: {=IF($C1000="","",IFNA(_xlfn.XLOOKUP($C1000,Productos!$A:$A,Productos!$E:$E,IFNA(_xlfn.XLOOKUP(TEXT($C1000,"0"),Productos!$A:$A,Productos!$E:$E,IFNA(_xlfn.XLOOKUP(IFERROR(VALUE($C1000),""),Productos!$A:$A,Productos!$E:$E,_xlfn.XLOOKUP($C1000,Productos!$E:$E,Productos!$E:$E,"NO ENCONTRADO")),"NO ENCONTRADO")),"NO ENCONTRADO")),"NO ENCONTRADO"))} | E1000: {=IF(OR($D1000="",$D1000="NO ENCONTRADO"),"",_xlfn.XLOOKUP($D1000,Productos!$E:$E,Productos!$H:$H,""))} | F1000: {=IF(OR($D1000="",$D1000="NO ENCONTRADO"),"",_xlfn.XLOOKUP($D1000,Productos!$E:$E,Productos!$I:$I,""))} | G1000: {=IF(OR($D1000="",$D1000="NO ENCONTRADO"),"",_xlfn.XLOOKUP($D1000,Productos!$E:$E,Productos!$J:$J,""))} | H1000: {=IF(OR($D1000="",$D1000="NO ENCONTRADO"),"",_xlfn.XLOOKUP($D1000,Productos!$E:$E,Productos!$K:$K,""))} | I1000: {=IF(OR($D1000="",$D1000="NO ENCONTRADO"),"",_xlfn.XLOOKUP($D1000,Productos!$E:$E,Productos!$F:$F,""))} | J1000: =IF($C1000="","",IF($D1000="NO ENCONTRADO",IF(COUNTIF($C$7:$C$1000,$C1000)>1,"⚠️ No encontrado | Duplicado","⚠️ No encontrado"),IF(COUNTIF($C$7:$C$1000,$C1000)>1,"⚠️ Duplicado","Verificado")))

Sheet Historial de Escaneos
A1: HISTORIAL Y BITÁCORA CONSOLIDADA DE CONTEOS CÍCLICOS - GRUPO QUINCE 22
A2: Registro histórico de auditorías, folios automáticos por ubicación y trazabilidad consolidada de marcas e inventario físico
A3: Fecha de Conteo | B3: Hora Registro | C3: Folio de Escaneo | D3: Ubicación / Rack | E3: Marcas Escaneadas (Todas) | F3: Total Piezas | G3: Auditor / Responsable | H3: Dictamen de Auditoría | I3: Alertas de Modificación / Incidencias

Sheet Escaneos
A1: Folio de Escaneo | B1: Fecha / Hora | C1: Ubicación / Rack | D1: UPC CODE | E1: SKU | F1: Marca | G1: Descripción | H1: Categoría | I1: Talla / Size | J1: Piezas Contadas | K1: Auditor / Responsable | L1: Estado de Conteo | M1: Detalle de Modificaciones / Alertas

Sheet Configuración
A1: CONFIGURACIÓN DEL SISTEMA Y CATÁLOGOS MAESTROS - GRUPO QUINCE 22
A2: Catálogos oficiales para validación de datos y listas desplegables del conteo cíclico diario
A3: Ubicaciones / Racks | B3: Marcas | C3: Categorías | D3: Tallas / Sizes | E3: Auditores / Operadores | F3: Estado de Conteo | H3: Ubicaciones NetSuite (Hoja a Revisar) | I3: SKUs con stock | J3: Piezas en sistema
A4: Pasillo A - Racks Principales | B4: 1522 Original | C4: Playeras | D4: XS | E4: Jesús Fregoso | F4: Verificado | H4: Almacenes G1522 | I4: {=_xlfn.XLOOKUP($H4,Criterios!$G$6:$G$200,Criterios!I$6:I$200,"")} | J4: {=_xlfn.XLOOKUP($H4,Criterios!$G$6:$G$200,Criterios!J$6:J$200,"")}
A5: Pasillo B - Estantería Media | B5: Urban Trend | C5: Pantalones | D5: S | E5: Carlos Morales | F5: Con Discrepancia | H5: AMAZON | I5: {=_xlfn.XLOOKUP($H5,Criterios!$G$6:$G$200,Criterios!I$6:I$200,"")} | J5: {=_xlfn.XLOOKUP($H5,Criterios!$G$6:$G$200,Criterios!J$6:J$200,"")}
A6: Pasillo C - Calzado y Confección | B6: Denim Co. | C6: Sudaderas | D6: M | E6: Andrea Valenzuela | F6: Pendiente | H6: ARIAT CHIHUAHUA | I6: {=_xlfn.XLOOKUP($H6,Criterios!$G$6:$G$200,Criterios!I$6:I$200,"")} | J6: {=_xlfn.XLOOKUP($H6,Criterios!$G$6:$G$200,Criterios!J$6:J$200,"")}
A7: Pasillo D - Accesorios | B7: Active Wear | C7: Chamarras | D7: L | E7: Luis Fernández | F7: Revisión Requerida | H7: ARIAT OUTLET GDL | I7: {=_xlfn.XLOOKUP($H7,Criterios!$G$6:$G$200,Criterios!I$6:I$200,"")} | J7: {=_xlfn.XLOOKUP($H7,Criterios!$G$6:$G$200,Criterios!J$6:J$200,"")}
A8: Pasillo E - Devoluciones | B8: Casual Basics | C8: Gorras | D8: XL | E8: Mariana Garza | H8: ARIAT PLAZA SAN LUIS | I8: {=_xlfn.XLOOKUP($H8,Criterios!$G$6:$G$200,Criterios!I$6:I$200,"")} | J8: {=_xlfn.XLOOKUP($H8,Criterios!$G$6:$G$200,Criterios!J$6:J$200,"")}
A9: Bodega Central - Tarimas | B9: Signature 1522 | C9: Camisas | D9: XXL | E9: Roberto Méndez | H9: ARIAT SAN NICOLAS NL | I9: {=_xlfn.XLOOKUP($H9,Criterios!$G$6:$G$200,Criterios!I$6:I$200,"")} | J9: {=_xlfn.XLOOKUP($H9,Criterios!$G$6:$G$200,Criterios!J$6:J$200,"")}
A10: Zona de Picking 1 | B10: Premium Line | C10: Calzado | D10: 28x32 | E10: Sofía Castro | H10: B25 CEDIS | I10: {=_xlfn.XLOOKUP($H10,Criterios!$G$6:$G$200,Criterios!I$6:I$200,"")} | J10: {=_xlfn.XLOOKUP($H10,Criterios!$G$6:$G$200,Criterios!J$6:J$200,"")}
A11: Zona de Recepción | B11: Vintage Republic | C11: Accesorios | D11: 30x32 | E11: Miguel Ángel Ruiz | H11: B25 STETSON.MX | I11: {=_xlfn.XLOOKUP($H11,Criterios!$G$6:$G$200,Criterios!I$6:I$200,"")} | J11: {=_xlfn.XLOOKUP($H11,Criterios!$G$6:$G$200,Criterios!J$6:J$200,"")}
A12: Almacén General - Cuarentena | B12: Essentials | C12: Ropa Deportiva | D12: 32x32 | E12: Diana Navarro | H12: B25 WB MERCADO LIBRE | I12: {=_xlfn.XLOOKUP($H12,Criterios!$G$6:$G$200,Criterios!I$6:I$200,"")} | J12: {=_xlfn.XLOOKUP($H12,Criterios!$G$6:$G$200,Criterios!J$6:J$200,"")}
A13: Mesa de Empaque | B13: Colección Especial | C13: Ropa Interior | D13: 34x32 | E13: Pedro Gómez | H13: B25 WESTERN BROTHERS.MX | I13: {=_xlfn.XLOOKUP($H13,Criterios!$G$6:$G$200,Criterios!I$6:I$200,"")} | J13: {=_xlfn.XLOOKUP($H13,Criterios!$G$6:$G$200,Criterios!J$6:J$200,"")}
A14: Área de Devoluciones | B14: Edición Limitada | C14: Calcetería | D14: UNITALLA | E14: Laura Sánchez | H14: CAPSLAB Warehouse | I14: {=_xlfn.XLOOKUP($H14,Criterios!$G$6:$G$200,Criterios!I$6:I$200,"")} | J14: {=_xlfn.XLOOKUP($H14,Criterios!$G$6:$G$200,Criterios!J$6:J$200,"")}
A15: J1-L1-01 | B15: Stetson | C15: Jeans | D15: 29 x 32 | H15: CL Muestras | I15: {=_xlfn.XLOOKUP($H15,Criterios!$G$6:$G$200,Criterios!I$6:I$200,"")} | J15: {=_xlfn.XLOOKUP($H15,Criterios!$G$6:$G$200,Criterios!J$6:J$200,"")}
A16: Almacenes G1522 | B16: Ariat | C16: Denim | D16: 30 x 32 | H16: CL POS | I16: {=_xlfn.XLOOKUP($H16,Criterios!$G$6:$G$200,Criterios!I$6:I$200,"")} | J16: {=_xlfn.XLOOKUP($H16,Criterios!$G$6:$G$200,Criterios!J$6:J$200,"")}
A17: AMAZON | B17: CAPSLAB | C17: Ropa | D17: 31 x 32 | H17: CONSIGNA REFLO | I17: {=_xlfn.XLOOKUP($H17,Criterios!$G$6:$G$200,Criterios!I$6:I$200,"")} | J17: {=_xlfn.XLOOKUP($H17,Criterios!$G$6:$G$200,Criterios!J$6:J$200,"")}
A18: ARIAT CHIHUAHUA | B18: Denver | D18: 32 x 34 | H18: CONSIGNAS | I18: {=_xlfn.XLOOKUP($H18,Criterios!$G$6:$G$200,Criterios!I$6:I$200,"")} | J18: {=_xlfn.XLOOKUP($H18,Criterios!$G$6:$G$200,Criterios!J$6:J$200,"")}
A19: ARIAT OUTLET GDL | B19: Generico | D19: 33 x 32 | H19: DEPARTAMENTAL | I19: {=_xlfn.XLOOKUP($H19,Criterios!$G$6:$G$200,Criterios!I$6:I$200,"")} | J19: {=_xlfn.XLOOKUP($H19,Criterios!$G$6:$G$200,Criterios!J$6:J$200,"")}
A20: ARIAT PLAZA SAN LUIS | B20: Happy Socks | D20: 34 x 34 | H20: ECOMMERCE | I20: {=_xlfn.XLOOKUP($H20,Criterios!$G$6:$G$200,Criterios!I$6:I$200,"")} | J20: {=_xlfn.XLOOKUP($H20,Criterios!$G$6:$G$200,Criterios!J$6:J$200,"")}
A21: ARIAT SAN NICOLAS NL | B21: Montana West | D21: 34 x 36 | H21: ENGLISH REP | I21: {=_xlfn.XLOOKUP($H21,Criterios!$G$6:$G$200,Criterios!I$6:I$200,"")} | J21: {=_xlfn.XLOOKUP($H21,Criterios!$G$6:$G$200,Criterios!J$6:J$200,"")}
A22: B25 CEDIS | B22: REFLO | D22: 36 x 32 | H22: EVENTOS (CONSIGNA) | I22: {=_xlfn.XLOOKUP($H22,Criterios!$G$6:$G$200,Criterios!I$6:I$200,"")} | J22: {=_xlfn.XLOOKUP($H22,Criterios!$G$6:$G$200,Criterios!J$6:J$200,"")}
A23: B25 STETSON.MX | B23: Ranch & Corral | D23: 36 x 34 | H23: Fixtures & MKT | I23: {=_xlfn.XLOOKUP($H23,Criterios!$G$6:$G$200,Criterios!I$6:I$200,"")} | J23: {=_xlfn.XLOOKUP($H23,Criterios!$G$6:$G$200,Criterios!J$6:J$200,"")}
A24: B25 WB MERCADO LIBRE | B24: Tru Western | D24: 38 x 32 | H24: FULL MELI | I24: {=_xlfn.XLOOKUP($H24,Criterios!$G$6:$G$200,Criterios!I$6:I$200,"")} | J24: {=_xlfn.XLOOKUP($H24,Criterios!$G$6:$G$200,Criterios!J$6:J$200,"")}
A25: B25 WESTERN BROTHERS.MX | B25: Willow Lane | D25: 32 x 32 | H25: G1522 Defectos | I25: {=_xlfn.XLOOKUP($H25,Criterios!$G$6:$G$200,Criterios!I$6:I$200,"")} | J25: {=_xlfn.XLOOKUP($H25,Criterios!$G$6:$G$200,Criterios!J$6:J$200,"")}
A26: CAPSLAB Warehouse | B26: Wrangler | D26: 34 x 32 | H26: G1522 Lost | I26: {=_xlfn.XLOOKUP($H26,Criterios!$G$6:$G$200,Criterios!I$6:I$200,"")} | J26: {=_xlfn.XLOOKUP($H26,Criterios!$G$6:$G$200,Criterios!J$6:J$200,"")}
A27: CL Muestras | H27: G1522 QA Hold | I27: {=_xlfn.XLOOKUP($H27,Criterios!$G$6:$G$200,Criterios!I$6:I$200,"")} | J27: {=_xlfn.XLOOKUP($H27,Criterios!$G$6:$G$200,Criterios!J$6:J$200,"")}
A28: CL POS | H28: GENERAL | I28: {=_xlfn.XLOOKUP($H28,Criterios!$G$6:$G$200,Criterios!I$6:I$200,"")} | J28: {=_xlfn.XLOOKUP($H28,Criterios!$G$6:$G$200,Criterios!J$6:J$200,"")}
A29: CONSIGNA REFLO | H29: HAPPY SOCKS | I29: {=_xlfn.XLOOKUP($H29,Criterios!$G$6:$G$200,Criterios!I$6:I$200,"")} | J29: {=_xlfn.XLOOKUP($H29,Criterios!$G$6:$G$200,Criterios!J$6:J$200,"")}
A30: CONSIGNAS | H30: HS MERCADO LIBRE | I30: {=_xlfn.XLOOKUP($H30,Criterios!$G$6:$G$200,Criterios!I$6:I$200,"")} | J30: {=_xlfn.XLOOKUP($H30,Criterios!$G$6:$G$200,Criterios!J$6:J$200,"")}
A31: DEPARTAMENTAL | H31: KEY ACCOUNTS | I31: {=_xlfn.XLOOKUP($H31,Criterios!$G$6:$G$200,Criterios!I$6:I$200,"")} | J31: {=_xlfn.XLOOKUP($H31,Criterios!$G$6:$G$200,Criterios!J$6:J$200,"")}
A32: ECOMMERCE | H32: LIVERPOOL MKP | I32: {=_xlfn.XLOOKUP($H32,Criterios!$G$6:$G$200,Criterios!I$6:I$200,"")} | J32: {=_xlfn.XLOOKUP($H32,Criterios!$G$6:$G$200,Criterios!J$6:J$200,"")}
A33: ENGLISH REP | H33: Mercado libre | I33: {=_xlfn.XLOOKUP($H33,Criterios!$G$6:$G$200,Criterios!I$6:I$200,"")} | J33: {=_xlfn.XLOOKUP($H33,Criterios!$G$6:$G$200,Criterios!J$6:J$200,"")}
A34: EVENTOS (CONSIGNA) | H34: MUESTRAS & EXPO | I34: {=_xlfn.XLOOKUP($H34,Criterios!$G$6:$G$200,Criterios!I$6:I$200,"")} | J34: {=_xlfn.XLOOKUP($H34,Criterios!$G$6:$G$200,Criterios!J$6:J$200,"")}
A35: Fixtures & MKT | H35: MUESTRAS REFLO | I35: {=_xlfn.XLOOKUP($H35,Criterios!$G$6:$G$200,Criterios!I$6:I$200,"")} | J35: {=_xlfn.XLOOKUP($H35,Criterios!$G$6:$G$200,Criterios!J$6:J$200,"")}
A36: FULL MELI | H36: Nogales Store | I36: {=_xlfn.XLOOKUP($H36,Criterios!$G$6:$G$200,Criterios!I$6:I$200,"")} | J36: {=_xlfn.XLOOKUP($H36,Criterios!$G$6:$G$200,Criterios!J$6:J$200,"")}
A37: G1522 Defectos | H37: Plaza del Sol Store | I37: {=_xlfn.XLOOKUP($H37,Criterios!$G$6:$G$200,Criterios!I$6:I$200,"")} | J37: {=_xlfn.XLOOKUP($H37,Criterios!$G$6:$G$200,Criterios!J$6:J$200,"")}
A38: G1522 Lost | H38: POTRILLOS | I38: {=_xlfn.XLOOKUP($H38,Criterios!$G$6:$G$200,Criterios!I$6:I$200,"")} | J38: {=_xlfn.XLOOKUP($H38,Criterios!$G$6:$G$200,Criterios!J$6:J$200,"")}
... A52: PUNTO DE VENTA | H52: ZONA SUR | I52: {=_xlfn.XLOOKUP($H52,Criterios!$G$6:$G$200,Criterios!I$6:I$200,"")} | J52: {=_xlfn.XLOOKUP($H52,Criterios!$G$6:$G$200,Criterios!J$6:J$200,"")}
A53: Punto de venta HS
A54: REFLO ALMACEN
A55: STETSON AMERICAS
A56: The Hat Club
A57: VENTAS CAMPAÑA
A58: WB FORUM TLAQUEPAQUE
A59: WB OUTLET LERMA
A60: Web
A61: WEB
A62: ZONA NORTE
A63: ZONA POS
A64: ZONA SUR

Sheet Productos
A1: Código de barras | B1: Identificador interno | C1: Marca principal | D1: WB N.º de estilo | E1: WB SKU | F1: WB Talla | G1: WB Talla de EE. UU. | H1: WB Marca | I1: WB Descripcion | J1: WB División | K1: WB Categoría | L1: WB Género | M1: WB Licencia | N1: WB Temporada | O1: WB Ciclo de vida | P1: WB Color | Q1: WB Fit | R1: WB Silueta | S1: WB Composición | T1: WB Descripción larga | U1: WB País de origen | V1: Unidad | W1: SAT Clave de producto | X1: Enlace de imagen | Y1: Precio de compra | Z1: Precio de venta | AA1: Estatus de Validación | AB1: Detalle de Discrepancias | AC1: 🔍 Panel de Duplicados | AD1: Stock Sistema NetSuite | AE1: Ubicaciones con stock (NetSuite) | AF1: Disponible NetSuite | AG1: Origen del registro | AH1: Notas de enriquecimiento / revisión | AI1: ¿Alguna ubicación en negativo? | AJ1: Ubicaciones con existencia negativa | AK1: Fuentes de consulta | AL1: Precio compra vigente | AM1: Precio venta vigente | AN1: 📍 Ubicación en plataformas (Plataforma + Marca) | AO1: Stock Shopify Stetson México | AP1: Stock Shopify Western Brothers | AQ1: Stock Odoo Universal Unique Brands | AR1: Ubicaciones con stock (plataformas)
A2: 087327013586 | C2: Yellowstone | E2: 95597 | F2: 100 ml | G2: 3.4 fl oz | H2: Yellowstone | I2: TESTER YELLOWSTONE 3.4 OZ COLOGNE SPRAY | J2: Accesorios | K2: Fragancias | L2: Unisex | V2: PZS | W2: 53131620 | X2: https://m-universal-unique-brands.odoo.com/web/image/product.product/27709/image_1920 | Z2: 679 | AA2: =IF(AND(A2="", B2="", E2=""), "", IF(AB2="", "Válido", IF((LEN(AB2)-LEN(SUBSTITUTE(AB2,"; ","")))/2+1>(LEN(AB2)-LEN(SUBSTITUTE(AB2,"[Aviso]","")))/7, "Con Incidencias", "Válido"))) | AB2: =IF(AND(A2="", B2="", E2=""), "", TEXTJOIN("; ", TRUE, IF(OR(TRIM(A2&"")="", ISNUMBER(SEARCH("FALTA", A2))), "UPC faltante/inválido", ""), IF(AND(A2<>"", IFERROR(_xlfn.XMATCH(A2,$A$2:$A$12,0,1)<>_xlfn.XMATCH(A2,$A$2:$A$12,0,-1),FALSE)), "Código de barras duplicado", ""), IF(AND(E2<>"", COUNTIF($E$2:$E$12, E2)>1), "SKU duplicado", ""), IF(OR(J2="", J2=""), "[Aviso] División no capturada ()", IF(ISNA(MATCH(J2, Criterios!$A$123:$A$126, 0)), "División no válida", "")), IF(OR(K2="", K2=""), "[Aviso] Categoría no capturada ()", IF(ISNA(MATCH(K2, Criterios!$A$81:$A$120, 0)), "Categoría no válida", IF(AND(J2<>"", J2<>"", J2<>VLOOKUP(K2, Criterios!$A$81:$B$120, 2, FALSE)), "División no coincide con Categoría", ""))), IF(OR(L2="", L2=""), "[Aviso] Género no capturado ()", IF(ISNA(MATCH(L2, Criterios!$B$123:$B$127, 0)), "Género no válido", "")), IF(OR(N2="", N2=""), "[Aviso] Temporada no capturada ()", IF(ISNA(MATCH(N2, Criterios!$C$123:$C$128, 0)), "Temporada no válida", "")), IF(OR(O2="", O2=""), "[Aviso] Ciclo de vida no capturado ()", IF(ISNA(MATCH(O2, Criterios!$D$123:$D$124, 0)), "Ciclo de vida no válido", "")))) | AG2: Nuevo – Odoo Universal Unique Brands 01/10/2026 | AH2: 01/10/2026: alta desde Odoo Universal Unique Brands (no existía en Productos por código de barras ni SKU) | Marca detectada en el nombre; Categoría: Sinónimo "Cologne" en nombre (fuera de tabla D); Género: regla accesorios sin género; Contenido convertido de oz a ml | Homologación G1522 06/10/2026: Validación G1522: Falta estilo · Validador NetSuite / Odoo: V6: falta estilo · Validador Shopify: V6: falta estilo; WB: precio con IVA no termina en 9 | AK2: Odoo: producto 27709 / plantilla 34445 | AN2: Odoo Universal Unique Brands | AQ2: 2 | AR2: Odoo Universal Unique Brands › Bodega 25 › Bodega 25/Output: 2
C3: Yellowstone | E3: 96234 | F3: 100 ml | G3: 3.4 fl oz | H3: Yellowstone | I3: TESTER YELLOWSTONE RIDE 3.4 OZ COLOGNE SPRAY | J3: Accesorios | K3: Fragancias | L3: Unisex | V3: PZS | W3: 53131620 | X3: https://m-universal-unique-brands.odoo.com/web/image/product.product/27708/image_1920 | Z3: 679 | AA3: =IF(AND(A3="", B3="", E3=""), "", IF(AB3="", "Válido", IF((LEN(AB3)-LEN(SUBSTITUTE(AB3,"; ","")))/2+1>(LEN(AB3)-LEN(SUBSTITUTE(AB3,"[Aviso]","")))/7, "Con Incidencias", "Válido"))) | AB3: =IF(AND(A3="", B3="", E3=""), "", TEXTJOIN("; ", TRUE, IF(OR(TRIM(A3&"")="", ISNUMBER(SEARCH("FALTA", A3))), "UPC faltante/inválido", ""), IF(AND(A3<>"", IFERROR(_xlfn.XMATCH(A3,$A$2:$A$12,0,1)<>_xlfn.XMATCH(A3,$A$2:$A$12,0,-1),FALSE)), "Código de barras duplicado", ""), IF(AND(E3<>"", COUNTIF($E$2:$E$12, E3)>1), "SKU duplicado", ""), IF(OR(J3="", J3=""), "[Aviso] División no capturada ()", IF(ISNA(MATCH(J3, Criterios!$A$123:$A$126, 0)), "División no válida", "")), IF(OR(K3="", K3=""), "[Aviso] Categoría no capturada ()", IF(ISNA(MATCH(K3, Criterios!$A$81:$A$120, 0)), "Categoría no válida", IF(AND(J3<>"", J3<>"", J3<>VLOOKUP(K3, Criterios!$A$81:$B$120, 2, FALSE)), "División no coincide con Categoría", ""))), IF(OR(L3="", L3=""), "[Aviso] Género no capturado ()", IF(ISNA(MATCH(L3, Criterios!$B$123:$B$127, 0)), "Género no válido", "")), IF(OR(N3="", N3=""), "[Aviso] Temporada no capturada ()", IF(ISNA(MATCH(N3, Criterios!$C$123:$C$128, 0)), "Temporada no válida", "")), IF(OR(O3="", O3=""), "[Aviso] Ciclo de vida no capturado ()", IF(ISNA(MATCH(O3, Criterios!$D$123:$D$124, 0)), "Ciclo de vida no válido", "")))) | AG3: Nuevo – Odoo Universal Unique Brands 01/10/2026 | AH3: 01/10/2026: alta desde Odoo Universal Unique Brands (no existía en Productos por código de barras ni SKU) | Marca detectada en el nombre; Categoría: Sinónimo "Cologne" en nombre (fuera de tabla D); Género: regla accesorios sin género; Contenido convertido de oz a ml | Homologación G1522 06/10/2026: Validación G1522: Código de barras faltante · Validador NetSuite / Odoo: V1: falta código de barras · Validador Shopify: V1: falta código de barras; WB: precio con IVA no termina en 9 | AK3: Odoo: producto 27708 / plantilla 34444 | AN3: Odoo Universal Unique Brands | AQ3: 3 | AR3: Odoo Universal Unique Brands › Bodega 25 › Bodega 25/General: 1 | Odoo Universal Unique Brands › Bodega 25 › Bodega 25/Output: 2
A4: 087327025572 | C4: Yellowstone | E4: 96235 | F4: 50 ml | G4: 1.7 fl oz | H4: Yellowstone | I4: TESTER Yellowstone - 1.7oz EDP - Tornado | J4: Accesorios | K4: Fragancias | L4: Unisex | V4: PZS | W4: 53131620 | X4: https://m-universal-unique-brands.odoo.com/web/image/product.product/27711/image_1920 | Z4: 639 | AA4: =IF(AND(A4="", B4="", E4=""), "", IF(AB4="", "Válido", IF((LEN(AB4)-LEN(SUBSTITUTE(AB4,"; ","")))/2+1>(LEN(AB4)-LEN(SUBSTITUTE(AB4,"[Aviso]","")))/7, "Con Incidencias", "Válido"))) | AB4: =IF(AND(A4="", B4="", E4=""), "", TEXTJOIN("; ", TRUE, IF(OR(TRIM(A4&"")="", ISNUMBER(SEARCH("FALTA", A4))), "UPC faltante/inválido", ""), IF(AND(A4<>"", IFERROR(_xlfn.XMATCH(A4,$A$2:$A$12,0,1)<>_xlfn.XMATCH(A4,$A$2:$A$12,0,-1),FALSE)), "Código de barras duplicado", ""), IF(AND(E4<>"", COUNTIF($E$2:$E$12, E4)>1), "SKU duplicado", ""), IF(OR(J4="", J4=""), "[Aviso] División no capturada ()", IF(ISNA(MATCH(J4, Criterios!$A$123:$A$126, 0)), "División no válida", "")), IF(OR(K4="", K4=""), "[Aviso] Categoría no capturada ()", IF(ISNA(MATCH(K4, Criterios!$A$81:$A$120, 0)), "Categoría no válida", IF(AND(J4<>"", J4<>"", J4<>VLOOKUP(K4, Criterios!$A$81:$B$120, 2, FALSE)), "División no coincide con Categoría", ""))), IF(OR(L4="", L4=""), "[Aviso] Género no capturado ()", IF(ISNA(MATCH(L4, Criterios!$B$123:$B$127, 0)), "Género no válido", "")), IF(OR(N4="", N4=""), "[Aviso] Temporada no capturada ()", IF(ISNA(MATCH(N4, Criterios!$C$123:$C$128, 0)), "Temporada no válida", "")), IF(OR(O4="", O4=""), "[Aviso] Ciclo de vida no capturado ()", IF(ISNA(MATCH(O4, Criterios!$D$123:$D$124, 0)), "Ciclo de vida no válido", "")))) | AG4: Nuevo – Odoo Universal Unique Brands 01/10/2026 | AH4: 01/10/2026: alta desde Odoo Universal Unique Brands (no existía en Productos por código de barras ni SKU) | Marca detectada en el nombre; Categoría: Sinónimo "Perfume" en tipo/categoría (Accesorios / Perfume); Género: regla accesorios sin género; Contenido convertido de oz a ml | Homologación G1522 06/10/2026: Validación G1522: Falta estilo · Validador NetSuite / Odoo: V6: falta estilo · Validador Shopify: V6: falta estilo; WB: precio con IVA no termina en 9 | AK4: Odoo: producto 27711 / plantilla 34447 | AN4: Odoo Universal Unique Brands | AQ4: 3 | AR4: Odoo Universal Unique Brands › Bodega 25 › Bodega 25/General: 1 | Odoo Universal Unique Brands › Bodega 25 › Bodega 25/Output: 2
A5: 087327030415 | C5: Yellowstone | E5: 96645 | F5: 100 ml | G5: 3.4 fl oz | H5: Yellowstone | I5: TESTER Yellowstone - Ride Reserve 3.4oz EDC | J5: Accesorios | K5: Fragancias | L5: Unisex | V5: PZS | W5: 53131620 | X5: https://m-universal-unique-brands.odoo.com/web/image/product.product/27710/image_1920 | Z5: 759 | AA5: =IF(AND(A5="", B5="", E5=""), "", IF(AB5="", "Válido", IF((LEN(AB5)-LEN(SUBSTITUTE(AB5,"; ","")))/2+1>(LEN(AB5)-LEN(SUBSTITUTE(AB5,"[Aviso]","")))/7, "Con Incidencias", "Válido"))) | AB5: =IF(AND(A5="", B5="", E5=""), "", TEXTJOIN("; ", TRUE, IF(OR(TRIM(A5&"")="", ISNUMBER(SEARCH("FALTA", A5))), "UPC faltante/inválido", ""), IF(AND(A5<>"", IFERROR(_xlfn.XMATCH(A5,$A$2:$A$12,0,1)<>_xlfn.XMATCH(A5,$A$2:$A$12,0,-1),FALSE)), "Código de barras duplicado", ""), IF(AND(E5<>"", COUNTIF($E$2:$E$12, E5)>1), "SKU duplicado", ""), IF(OR(J5="", J5=""), "[Aviso] División no capturada ()", IF(ISNA(MATCH(J5, Criterios!$A$123:$A$126, 0)), "División no válida", "")), IF(OR(K5="", K5=""), "[Aviso] Categoría no capturada ()", IF(ISNA(MATCH(K5, Criterios!$A$81:$A$120, 0)), "Categoría no válida", IF(AND(J5<>"", J5<>"", J5<>VLOOKUP(K5, Criterios!$A$81:$B$120, 2, FALSE)), "División no coincide con Categoría", ""))), IF(OR(L5="", L5=""), "[Aviso] Género no capturado ()", IF(ISNA(MATCH(L5, Criterios!$B$123:$B$127, 0)), "Género no válido", "")), IF(OR(N5="", N5=""), "[Aviso] Temporada no capturada ()", IF(ISNA(MATCH(N5, Criterios!$C$123:$C$128, 0)), "Temporada no válida", "")), IF(OR(O5="", O5=""), "[Aviso] Ciclo de vida no capturado ()", IF(ISNA(MATCH(O5, Criterios!$D$123:$D$124, 0)), "Ciclo de vida no válido", "")))) | AG5: Nuevo – Odoo Universal Unique Brands 01/10/2026 | AH5: 01/10/2026: alta desde Odoo Universal Unique Brands (no existía en Productos por código de barras ni SKU) | Marca detectada en el nombre; Categoría: Sinónimo "Perfume" en tipo/categoría (Accesorios / Perfume); Género: regla accesorios sin género; Contenido convertido de oz a ml | Homologación G1522 06/10/2026: Validación G1522: Falta estilo · Validador NetSuite / Odoo: V6: falta estilo · Validador Shopify: V6: falta estilo; WB: precio con IVA no termina en 9 | AK5: Odoo: producto 27710 / plantilla 34446 | AN5: Odoo Universal Unique Brands | AQ5: 2 | AR5: Odoo Universal Unique Brands › Bodega 25 › Bodega 25/General: 1 | Odoo Universal Unique Brands › Bodega 25 › Bodega 25/Output: 1
A6: 7506552406541 | B6: 118246 | C6: Multimarca | D6: YW11 | E6: YW11 | F6: Talla única | G6: One Size | H6: Yellowstone | I6: Gorra Yellowstone 11 | J6: Accesorios | K6: Gorras | L6: Hombre | M6: Yellowstone | N6: FW26 | O6: Seasonal | P6: Negro | S6: 50% Poliéster 25% Algodón 14% Viscosa 11% Poliuretano | T6: Gorra Yellowstone 11 5 paneles | U6: China | V6: PZS | W6: 53102516 | Y6: 307.31 | Z6: 645.68966 | AA6: =IF(AND(A6="", B6="", E6=""), "", IF(AB6="", "Válido", IF((LEN(AB6)-LEN(SUBSTITUTE(AB6,"; ","")))/2+1>(LEN(AB6)-LEN(SUBSTITUTE(AB6,"[Aviso]","")))/7, "Con Incidencias", "Válido"))) | AB6: =IF(AND(A6="", B6="", E6=""), "", TEXTJOIN("; ", TRUE, IF(OR(TRIM(A6&"")="", ISNUMBER(SEARCH("FALTA", A6))), "UPC faltante/inválido", ""), IF(AND(A6<>"", IFERROR(_xlfn.XMATCH(A6,$A$2:$A$12,0,1)<>_xlfn.XMATCH(A6,$A$2:$A$12,0,-1),FALSE)), "Código de barras duplicado", ""), IF(AND(E6<>"", COUNTIF($E$2:$E$12, E6)>1), "SKU duplicado", ""), IF(OR(J6="", J6=""), "[Aviso] División no capturada ()", IF(ISNA(MATCH(J6, Criterios!$A$123:$A$126, 0)), "División no válida", "")), IF(OR(K6="", K6=""), "[Aviso] Categoría no capturada ()", IF(ISNA(MATCH(K6, Criterios!$A$81:$A$120, 0)), "Categoría no válida", IF(AND(J6<>"", J6<>"", J6<>VLOOKUP(K6, Criterios!$A$81:$B$120, 2, FALSE)), "División no coincide con Categoría", ""))), IF(OR(L6="", L6=""), "[Aviso] Género no capturado ()", IF(ISNA(MATCH(L6, Criterios!$B$123:$B$127, 0)), "Género no válido", "")), IF(OR(N6="", N6=""), "[Aviso] Temporada no capturada ()", IF(ISNA(MATCH(N6, Criterios!$C$123:$C$128, 0)), "Temporada no válida", "")), IF(OR(O6="", O6=""), "[Aviso] Ciclo de vida no capturado ()", IF(ISNA(MATCH(O6, Criterios!$D$123:$D$124, 0)), "Ciclo de vida no válido", "")))) | AD6: 25 | AE6: B25 CEDIS: 19 | WB OUTLET LERMA: 6 | AF6: 6 | AG6: Nuevo – NetSuite 06/10/2026 | AH6: Comprometido: 19 | En pedido: 19 | Homologación G1522 06/10/2026: WB Silueta: «» → «5 paneles» (Completado desde NetSuite) · WB Silueta: «5 paneles» → «» (Corrección aplicada) | AI6: No | AK6: NetSuite SuiteQL: item · inventoryitemlocations · itemprice (Base Price y RETAIL, moneda base) | AL6: 307.31 | AM6: 749
A7: 7506552411002 | B7: 118230 | C7: Multimarca | D7: YW32 | E7: YW32 | F7: Talla única | G7: One Size | H7: Yellowstone | I7: Gorra Yellowstone 32 | J7: Accesorios | K7: Gorras | L7: Hombre | M7: Yellowstone | N7: FW26 | O7: Seasonal | P7: Blanco | S7: 100% Poliéster | T7: Gorra Yellowstone 32 5 paneles | U7: China | V7: PZS | W7: 53102516 | Y7: 307.31 | Z7: 645.68966 | AA7: =IF(AND(A7="", B7="", E7=""), "", IF(AB7="", "Válido", IF((LEN(AB7)-LEN(SUBSTITUTE(AB7,"; ","")))/2+1>(LEN(AB7)-LEN(SUBSTITUTE(AB7,"[Aviso]","")))/7, "Con Incidencias", "Válido"))) | AB7: =IF(AND(A7="", B7="", E7=""), "", TEXTJOIN("; ", TRUE, IF(OR(TRIM(A7&"")="", ISNUMBER(SEARCH("FALTA", A7))), "UPC faltante/inválido", ""), IF(AND(A7<>"", IFERROR(_xlfn.XMATCH(A7,$A$2:$A$12,0,1)<>_xlfn.XMATCH(A7,$A$2:$A$12,0,-1),FALSE)), "Código de barras duplicado", ""), IF(AND(E7<>"", COUNTIF($E$2:$E$12, E7)>1), "SKU duplicado", ""), IF(OR(J7="", J7=""), "[Aviso] División no capturada ()", IF(ISNA(MATCH(J7, Criterios!$A$123:$A$126, 0)), "División no válida", "")), IF(OR(K7="", K7=""), "[Aviso] Categoría no capturada ()", IF(ISNA(MATCH(K7, Criterios!$A$81:$A$120, 0)), "Categoría no válida", IF(AND(J7<>"", J7<>"", J7<>VLOOKUP(K7, Criterios!$A$81:$B$120, 2, FALSE)), "División no coincide con Categoría", ""))), IF(OR(L7="", L7=""), "[Aviso] Género no capturado ()", IF(ISNA(MATCH(L7, Criterios!$B$123:$B$127, 0)), "Género no válido", "")), IF(OR(N7="", N7=""), "[Aviso] Temporada no capturada ()", IF(ISNA(MATCH(N7, Criterios!$C$123:$C$128, 0)), "Temporada no válida", "")), IF(OR(O7="", O7=""), "[Aviso] Ciclo de vida no capturado ()", IF(ISNA(MATCH(O7, Criterios!$D$123:$D$124, 0)), "Ciclo de vida no válido", "")))) | AD7: 41 | AE7: B25 CEDIS: 33 | WB OUTLET LERMA: 8 | AF7: 8 | AG7: Nuevo – NetSuite 06/10/2026 | AH7: Comprometido: 33 | En pedido: 33 | Homologación G1522 06/10/2026: WB Silueta: «» → «5 paneles» (Completado desde NetSuite) · WB Silueta: «5 paneles» → «» (Corrección aplicada) | AI7: No | AK7: NetSuite SuiteQL: item · inventoryitemlocations · itemprice (Base Price y RETAIL, moneda base) | AL7: 307.31 | AM7: 749
A8: 7506552411057 | B8: 118247 | C8: Multimarca | D8: YW37 | E8: YW37 | F8: Talla única | G8: One Size | H8: Yellowstone | I8: Gorra Yellowstone 37 | J8: Accesorios | K8: Gorras | L8: Hombre | M8: Yellowstone | N8: FW26 | O8: Seasonal | P8: Negro | S8: 50% Poliéster 25% Algodón 14% Viscosa 11% Poliuretano | T8: Gorra Yellowstone 37 5 paneles | U8: China | V8: PZS | W8: 53102516 | Y8: 307.31 | Z8: 645.68966 | AA8: =IF(AND(A8="", B8="", E8=""), "", IF(AB8="", "Válido", IF((LEN(AB8)-LEN(SUBSTITUTE(AB8,"; ","")))/2+1>(LEN(AB8)-LEN(SUBSTITUTE(AB8,"[Aviso]","")))/7, "Con Incidencias", "Válido"))) | AB8: =IF(AND(A8="", B8="", E8=""), "", TEXTJOIN("; ", TRUE, IF(OR(TRIM(A8&"")="", ISNUMBER(SEARCH("FALTA", A8))), "UPC faltante/inválido", ""), IF(AND(A8<>"", IFERROR(_xlfn.XMATCH(A8,$A$2:$A$12,0,1)<>_xlfn.XMATCH(A8,$A$2:$A$12,0,-1),FALSE)), "Código de barras duplicado", ""), IF(AND(E8<>"", COUNTIF($E$2:$E$12, E8)>1), "SKU duplicado", ""), IF(OR(J8="", J8=""), "[Aviso] División no capturada ()", IF(ISNA(MATCH(J8, Criterios!$A$123:$A$126, 0)), "División no válida", "")), IF(OR(K8="", K8=""), "[Aviso] Categoría no capturada ()", IF(ISNA(MATCH(K8, Criterios!$A$81:$A$120, 0)), "Categoría no válida", IF(AND(J8<>"", J8<>"", J8<>VLOOKUP(K8, Criterios!$A$81:$B$120, 2, FALSE)), "División no coincide con Categoría", ""))), IF(OR(L8="", L8=""), "[Aviso] Género no capturado ()", IF(ISNA(MATCH(L8, Criterios!$B$123:$B$127, 0)), "Género no válido", "")), IF(OR(N8="", N8=""), "[Aviso] Temporada no capturada ()", IF(ISNA(MATCH(N8, Criterios!$C$123:$C$128, 0)), "Temporada no válida", "")), IF(OR(O8="", O8=""), "[Aviso] Ciclo de vida no capturado ()", IF(ISNA(MATCH(O8, Criterios!$D$123:$D$124, 0)), "Ciclo de vida no válido", "")))) | AD8: 25 | AE8: B25 CEDIS: 19 | WB OUTLET LERMA: 6 | AF8: 6 | AG8: Nuevo – NetSuite 06/10/2026 | AH8: Comprometido: 19 | En pedido: 19 | Homologación G1522 06/10/2026: WB Silueta: «» → «5 paneles» (Completado desde NetSuite) · WB Silueta: «5 paneles» → «» (Corrección aplicada) | AI8: No | AK8: NetSuite SuiteQL: item · inventoryitemlocations · itemprice (Base Price y RETAIL, moneda base) | AL8: 307.31 | AM8: 749
A9: 7506552414997 | B9: 118231 | C9: Multimarca | D9: YW44 | E9: YW44 | F9: Talla única | G9: One Size | H9: Yellowstone | I9: Gorra Yellowstone 44 | J9: Accesorios | K9: Gorras | L9: Hombre | M9: Yellowstone | N9: FW26 | O9: Seasonal | P9: Cafe | S9: 50% Algodón 50% Poliéster | T9: Gorra Yellowstone 44 5 paneles | U9: China | V9: PZS | W9: 53102516 | Y9: 307.31 | Z9: 645.68966 | AA9: =IF(AND(A9="", B9="", E9=""), "", IF(AB9="", "Válido", IF((LEN(AB9)-LEN(SUBSTITUTE(AB9,"; ","")))/2+1>(LEN(AB9)-LEN(SUBSTITUTE(AB9,"[Aviso]","")))/7, "Con Incidencias", "Válido"))) | AB9: =IF(AND(A9="", B9="", E9=""), "", TEXTJOIN("; ", TRUE, IF(OR(TRIM(A9&"")="", ISNUMBER(SEARCH("FALTA", A9))), "UPC faltante/inválido", ""), IF(AND(A9<>"", IFERROR(_xlfn.XMATCH(A9,$A$2:$A$12,0,1)<>_xlfn.XMATCH(A9,$A$2:$A$12,0,-1),FALSE)), "Código de barras duplicado", ""), IF(AND(E9<>"", COUNTIF($E$2:$E$12, E9)>1), "SKU duplicado", ""), IF(OR(J9="", J9=""), "[Aviso] División no capturada ()", IF(ISNA(MATCH(J9, Criterios!$A$123:$A$126, 0)), "División no válida", "")), IF(OR(K9="", K9=""), "[Aviso] Categoría no capturada ()", IF(ISNA(MATCH(K9, Criterios!$A$81:$A$120, 0)), "Categoría no válida", IF(AND(J9<>"", J9<>"", J9<>VLOOKUP(K9, Criterios!$A$81:$B$120, 2, FALSE)), "División no coincide con Categoría", ""))), IF(OR(L9="", L9=""), "[Aviso] Género no capturado ()", IF(ISNA(MATCH(L9, Criterios!$B$123:$B$127, 0)), "Género no válido", "")), IF(OR(N9="", N9=""), "[Aviso] Temporada no capturada ()", IF(ISNA(MATCH(N9, Criterios!$C$123:$C$128, 0)), "Temporada no válida", "")), IF(OR(O9="", O9=""), "[Aviso] Ciclo de vida no capturado ()", IF(ISNA(MATCH(O9, Criterios!$D$123:$D$124, 0)), "Ciclo de vida no válido", "")))) | AD9: 39 | AE9: B25 CEDIS: 31 | WB OUTLET LERMA: 8 | AF9: 8 | AG9: Nuevo – NetSuite 06/10/2026 | AH9: Comprometido: 31 | En pedido: 31 | Homologación G1522 06/10/2026: WB Silueta: «» → «5 paneles» (Completado desde NetSuite) · WB Silueta: «5 paneles» → «» (Corrección aplicada) | AI9: No | AK9: NetSuite SuiteQL: item · inventoryitemlocations · itemprice (Base Price y RETAIL, moneda base) | AL9: 307.31 | AM9: 749
A10: 7506552415000 | B10: 118232 | C10: Multimarca | D10: YW45 | E10: YW45 | F10: Talla única | G10: One Size | H10: Yellowstone | I10: Gorra Yellowstone 45 | J10: Accesorios | K10: Gorras | L10: Hombre | M10: Yellowstone | N10: FW26 | O10: Seasonal | P10: Cafe | S10: 50% Algodón 50% Poliéster | T10: Gorra Yellowstone 45 5 paneles | U10: China | V10: PZS | W10: 53102516 | Y10: 307.31 | Z10: 645.68966 | AA10: =IF(AND(A10="", B10="", E10=""), "", IF(AB10="", "Válido", IF((LEN(AB10)-LEN(SUBSTITUTE(AB10,"; ","")))/2+1>(LEN(AB10)-LEN(SUBSTITUTE(AB10,"[Aviso]","")))/7, "Con Incidencias", "Válido"))) | AB10: =IF(AND(A10="", B10="", E10=""), "", TEXTJOIN("; ", TRUE, IF(OR(TRIM(A10&"")="", ISNUMBER(SEARCH("FALTA", A10))), "UPC faltante/inválido", ""), IF(AND(A10<>"", IFERROR(_xlfn.XMATCH(A10,$A$2:$A$12,0,1)<>_xlfn.XMATCH(A10,$A$2:$A$12,0,-1),FALSE)), "Código de barras duplicado", ""), IF(AND(E10<>"", COUNTIF($E$2:$E$12, E10)>1), "SKU duplicado", ""), IF(OR(J10="", J10=""), "[Aviso] División no capturada ()", IF(ISNA(MATCH(J10, Criterios!$A$123:$A$126, 0)), "División no válida", "")), IF(OR(K10="", K10=""), "[Aviso] Categoría no capturada ()", IF(ISNA(MATCH(K10, Criterios!$A$81:$A$120, 0)), "Categoría no válida", IF(AND(J10<>"", J10<>"", J10<>VLOOKUP(K10, Criterios!$A$81:$B$120, 2, FALSE)), "División no coincide con Categoría", ""))), IF(OR(L10="", L10=""), "[Aviso] Género no capturado ()", IF(ISNA(MATCH(L10, Criterios!$B$123:$B$127, 0)), "Género no válido", "")), IF(OR(N10="", N10=""), "[Aviso] Temporada no capturada ()", IF(ISNA(MATCH(N10, Criterios!$C$123:$C$128, 0)), "Temporada no válida", "")), IF(OR(O10="", O10=""), "[Aviso] Ciclo de vida no capturado ()", IF(ISNA(MATCH(O10, Criterios!$D$123:$D$124, 0)), "Ciclo de vida no válido", "")))) | AD10: 38 | AE10: B25 CEDIS: 30 | WB OUTLET LERMA: 8 | AF10: 8 | AG10: Nuevo – NetSuite 06/10/2026 | AH10: Comprometido: 30 | En pedido: 30 | Homologación G1522 06/10/2026: WB Silueta: «» → «5 paneles» (Completado desde NetSuite) · WB Silueta: «5 paneles» → «» (Corrección aplicada) | AI10: No | AK10: NetSuite SuiteQL: item · inventoryitemlocations · itemprice (Base Price y RETAIL, moneda base) | AL10: 307.31 | AM10: 749
A11: 7506552415017 | B11: 118248 | C11: Multimarca | D11: YW46 | E11: YW46 | F11: Talla única | G11: One Size | H11: Yellowstone | I11: Gorra Yellowstone 46 | J11: Accesorios | K11: Gorras | L11: Hombre | M11: Yellowstone | N11: FW26 | O11: Seasonal | P11: Cafe | S11: 50% Algodón 50% Poliéster | T11: Gorra Yellowstone 46 5 paneles | U11: China | V11: PZS | W11: 53102516 | Y11: 307.31 | Z11: 645.68966 | AA11: =IF(AND(A11="", B11="", E11=""), "", IF(AB11="", "Válido", IF((LEN(AB11)-LEN(SUBSTITUTE(AB11,"; ","")))/2+1>(LEN(AB11)-LEN(SUBSTITUTE(AB11,"[Aviso]","")))/7, "Con Incidencias", "Válido"))) | AB11: =IF(AND(A11="", B11="", E11=""), "", TEXTJOIN("; ", TRUE, IF(OR(TRIM(A11&"")="", ISNUMBER(SEARCH("FALTA", A11))), "UPC faltante/inválido", ""), IF(AND(A11<>"", IFERROR(_xlfn.XMATCH(A11,$A$2:$A$12,0,1)<>_xlfn.XMATCH(A11,$A$2:$A$12,0,-1),FALSE)), "Código de barras duplicado", ""), IF(AND(E11<>"", COUNTIF($E$2:$E$12, E11)>1), "SKU duplicado", ""), IF(OR(J11="", J11=""), "[Aviso] División no capturada ()", IF(ISNA(MATCH(J11, Criterios!$A$123:$A$126, 0)), "División no válida", "")), IF(OR(K11="", K11=""), "[Aviso] Categoría no capturada ()", IF(ISNA(MATCH(K11, Criterios!$A$81:$A$120, 0)), "Categoría no válida", IF(AND(J11<>"", J11<>"", J11<>VLOOKUP(K11, Criterios!$A$81:$B$120, 2, FALSE)), "División no coincide con Categoría", ""))), IF(OR(L11="", L11=""), "[Aviso] Género no capturado ()", IF(ISNA(MATCH(L11, Criterios!$B$123:$B$127, 0)), "Género no válido", "")), IF(OR(N11="", N11=""), "[Aviso] Temporada no capturada ()", IF(ISNA(MATCH(N11, Criterios!$C$123:$C$128, 0)), "Temporada no válida", "")), IF(OR(O11="", O11=""), "[Aviso] Ciclo de vida no capturado ()", IF(ISNA(MATCH(O11, Criterios!$D$123:$D$124, 0)), "Ciclo de vida no válido", "")))) | AD11: 7 | AE11: B25 CEDIS: 4 | WB OUTLET LERMA: 3 | AF11: 3 | AG11: Nuevo – NetSuite 06/10/2026 | AH11: Comprometido: 4 | En pedido: 4 | Homologación G1522 06/10/2026: WB Silueta: «» → «5 paneles» (Completado desde NetSuite) · WB Silueta: «5 paneles» → «» (Corrección aplicada) | AI11: No | AK11: NetSuite SuiteQL: item · inventoryitemlocations · itemprice (Base Price y RETAIL, moneda base) | AL11: 307.31 | AM11: 749
A12: 7506552415024 | B12: 118249 | C12: Multimarca | D12: YW47 | E12: YW47 | F12: Talla única | G12: One Size | H12: Yellowstone | I12: Gorra Yellowstone 47 | J12: Accesorios | K12: Gorras | L12: Hombre | M12: Yellowstone | N12: FW26 | O12: Seasonal | P12: Negro | S12: 50% Algodón 50% Poliéster | T12: Gorra Yellowstone 47 5 paneles | U12: China | V12: PZS | W12: 53102516 | Y12: 307.31 | Z12: 645.68966 | AA12: =IF(AND(A12="", B12="", E12=""), "", IF(AB12="", "Válido", IF((LEN(AB12)-LEN(SUBSTITUTE(AB12,"; ","")))/2+1>(LEN(AB12)-LEN(SUBSTITUTE(AB12,"[Aviso]","")))/7, "Con Incidencias", "Válido"))) | AB12: =IF(AND(A12="", B12="", E12=""), "", TEXTJOIN("; ", TRUE, IF(OR(TRIM(A12&"")="", ISNUMBER(SEARCH("FALTA", A12))), "UPC faltante/inválido", ""), IF(AND(A12<>"", IFERROR(_xlfn.XMATCH(A12,$A$2:$A$12,0,1)<>_xlfn.XMATCH(A12,$A$2:$A$12,0,-1),FALSE)), "Código de barras duplicado", ""), IF(AND(E12<>"", COUNTIF($E$2:$E$12, E12)>1), "SKU duplicado", ""), IF(OR(J12="", J12=""), "[Aviso] División no capturada ()", IF(ISNA(MATCH(J12, Criterios!$A$123:$A$126, 0)), "División no válida", "")), IF(OR(K12="", K12=""), "[Aviso] Categoría no capturada ()", IF(ISNA(MATCH(K12, Criterios!$A$81:$A$120, 0)), "Categoría no válida", IF(AND(J12<>"", J12<>"", J12<>VLOOKUP(K12, Criterios!$A$81:$B$120, 2, FALSE)), "División no coincide con Categoría", ""))), IF(OR(L12="", L12=""), "[Aviso] Género no capturado ()", IF(ISNA(MATCH(L12, Criterios!$B$123:$B$127, 0)), "Género no válido", "")), IF(OR(N12="", N12=""), "[Aviso] Temporada no capturada ()", IF(ISNA(MATCH(N12, Criterios!$C$123:$C$128, 0)), "Temporada no válida", "")), IF(OR(O12="", O12=""), "[Aviso] Ciclo de vida no capturado ()", IF(ISNA(MATCH(O12, Criterios!$D$123:$D$124, 0)), "Ciclo de vida no válido", "")))) | AD12: 7 | AE12: B25 CEDIS: 4 | WB OUTLET LERMA: 3 | AF12: 3 | AG12: Nuevo – NetSuite 06/10/2026 | AH12: Comprometido: 4 | En pedido: 4 | Homologación G1522 06/10/2026: WB Silueta: «» → «5 paneles» (Completado desde NetSuite) · WB Silueta: «5 paneles» → «» (Corrección aplicada) | AI12: No | AK12: NetSuite SuiteQL: item · inventoryitemlocations · itemprice (Base Price y RETAIL, moneda base) | AL12: 307.31 | AM12: 749

Sheet Productos_Resumen
A1: UPC | B1: SKU | C1: Id_Interno | D1: Descripcion | E1: Talla_MX | F1: Talla_USA | G1: Precio_Compra | H1: Precio_Venta | I1: Stock_NetSuite | J1: Disponible_NetSuite | K1: Ubicaciones_NetSuite | L1: Stock_Shopify_Stetson | M1: Stock_Shopify_WB | N1: Stock_Odoo | O1: Stock_Plataformas_Total | P1: Ubicaciones_Plataformas | Q1: Piezas_Escaneadas | R1: Ubicacion_Escaneo
A2: =IFERROR(__xludf.DUMMYFUNCTION("ARRAY_CONSTRAIN(ARRAYFORMULA(LET(_xlpm.d,Productos!$A$2:$AR12,_xlpm.f,((INDEX(_xlpm.d,0,1)<>"""")+(INDEX(_xlpm.d,0,2)<>"""")+(INDEX(_xlpm.d,0,5)<>"""")+(INDEX(_xlpm.d,0,9)<>""""))>0,_xlpm.z,LAMBDA(_xlpm.c,IF(INDEX(_xlpm.d,0,_xlpm.c)="""",0,INDEX(_xlpm."&"d,0,_xlpm.c))),_xlpm.num,LAMBDA(_xlpm.v,IF(_xlpm.v="""","""",IF(ISTEXT(_xlpm.v),IFERROR(NUMBERVALUE(SUBSTITUTE(_xlpm.v,"","","".""),""."","",""),_xlpm.v),_xlpm.v))),_xlpm.pr,LAMBDA(_xlpm.a,_xlpm.b,_xlpm.num(IF(INDEX(_xlpm.d,0,_xlpm.a)<>"""",INDEX(_xlpm.d,"&"0,_xlpm.a),IF(INDEX(_xlpm.d,0,_xlpm.b)<>"""",INDEX(_xlpm.d,0,_xlpm.b),"""")))),_xlpm.pc,_xlpm.pr(38,25),_xlpm.pv,_xlpm.pr(39,26),_xlpm.tot,_xlpm.z(41)+_xlpm.z(42)+_xlpm.z(43),_xlpm.x,FILTER(HSTACK(CHOOSECOLS(_xlpm.d,1,5,2,9,6,7),_xlpm.pc,_xlpm.pv,CHOOSECO"&"LS(_xlpm.d,30,32,31,41,42,43),_xlpm.tot,INDEX(_xlpm.d,0,44)),_xlpm.f),IF(_xlpm.x="""","""",_xlpm.x))), 11, 16)"),"052356088867") | Q2: =IFERROR(__xludf.DUMMYFUNCTION("MAP(FILTER(A2:A12, (B2:B12<>"""")+(D2:D12<>"""")), FILTER(B2:B12, (B2:B12<>"""")+(D2:D12<>"""")), LAMBDA(upc, sku, LET(s_alt, IF(ISNUMBER(SEARCH(""-XXL"", sku)), SUBSTITUTE(sku, ""-XXL"", ""-2XL""), IF(ISNUMBER(SEARCH(""-2XL"", sku)), SU"&"BSTITUTE(sku, ""-2XL"", ""-XXL""), IF(ISNUMBER(SEARCH(""-XXXL"", sku)), SUBSTITUTE(sku, ""-XXXL"", ""-3XL""), IF(ISNUMBER(SEARCH(""-3XL"", sku)), SUBSTITUTE(sku, ""-3XL"", ""-XXXL""), sku)))), pz_exact, IF(sku<>"""", SUMIFS(Table_2[Piezas Contadas], Table"&"_2[SKU], sku), 0), pz_alt, IF(s_alt<>sku, SUMIFS(Table_2[Piezas Contadas], Table_2[SKU], s_alt), 0), pz_upc_blank, IF(upc<>"""", SUMIFS(Table_2[Piezas Contadas], Table_2[UPC CODE], upc, Table_2[SKU], """"), 0), pz_exact + pz_alt + pz_upc_blank)))"),0.0) | R2: =IFERROR(__xludf.DUMMYFUNCTION("MAP(FILTER(A2:A12, (B2:B12<>"""")+(D2:D12<>"""")), FILTER(B2:B12, (B2:B12<>"""")+(D2:D12<>"""")), FILTER(Q2:Q12, (B2:B12<>"""")+(D2:D12<>"""")), LAMBDA(upc, sku, pz, IF(OR(pz=0, pz=""""), """", LET(s_alt, IF(ISNUMBER(SEARCH(""-X"&"XL"", sku)), SUBSTITUTE(sku, ""-XXL"", ""-2XL""), IF(ISNUMBER(SEARCH(""-2XL"", sku)), SUBSTITUTE(sku, ""-2XL"", ""-XXL""), IF(ISNUMBER(SEARCH(""-XXXL"", sku)), SUBSTITUTE(sku, ""-XXXL"", ""-3XL""), IF(ISNUMBER(SEARCH(""-3XL"", sku)), SUBSTITUTE(sku, ""-3X"&"L"", ""-XXXL""), sku)))), rk_sku, IFERROR(FILTER(Table_2[Ubicación / Rack], Table_2[SKU]=sku, Table_2[Ubicación / Rack]<>""""), """"), rk_alt, IF(s_alt<>sku, IFERROR(FILTER(Table_2[Ubicación / Rack], Table_2[SKU]=s_alt, Table_2[Ubicación / Rack]<>""""), "&"""""), """"), rk_upc, IF(upc<>"""", IFERROR(FILTER(Table_2[Ubicación / Rack], Table_2[UPC CODE]=upc, Table_2[SKU]="""", Table_2[Ubicación / Rack]<>""""), """"), """"), all_r, VSTACK(rk_sku, rk_alt, rk_upc), r_uniq, UNIQUE(IFERROR(FILTER(all_r, all_r<>"""""&"), """")), IF(INDEX(r_uniq, 1, 1)="""", """", TEXTJOIN("", "", TRUE, MAP(r_uniq, LAMBDA(rk, LET(cnt_sku, IF(sku<>"""", SUMIFS(Table_2[Piezas Contadas], Table_2[SKU], sku, Table_2[Ubicación / Rack], rk), 0), cnt_alt, IF(s_alt<>sku, SUMIFS(Table_2[Piezas Co"&"ntadas], Table_2[SKU], s_alt, Table_2[Ubicación / Rack], rk), 0), cnt_upc, IF(upc<>"""", SUMIFS(Table_2[Piezas Contadas], Table_2[UPC CODE], upc, Table_2[SKU], """", Table_2[Ubicación / Rack], rk), 0), rk & "" ("" & (cnt_sku + cnt_alt + cnt_upc) & "")""))"&")))))))"),"")

Sheet Criterios
A1: Criterios del Catálogo Estándar
A2: Guía de llenado y listas de valores válidos. Usa el índice para saltar a cada sección; sigue la Ruta de llenado en orden.
G3: Agrega ubicaciones nuevas al final de la lista; el desplegable de Escaneo las toma solas. Los escaneos solo suman al total y a la bodega asignada en la columna K; no se validan contra el stock de NetSuite. | L3: Captura el correo de cada auditor; los scripts lo usan para poner su nombre automáticamente. | P3: Valores que usa el Dictamen del Historial de Escaneos. | S3: Listas que alimentan los desplegables de Productos. Las columnas en negro se actualizan solas desde las tablas de Criterios; Fit y Silueta (azul) se editan aquí.
A4: ÍNDICE (clic en una sección para ir a ella) | G4: 9. UBICACIONES / RACKS | L4: 10. AUDITORES (correo → nombre) | P4: 11. ESTADOS DE CONTEO / DICTAMEN | S4: 12. LISTAS AUTOMÁTICAS PARA DESPLEGABLES (no editar; solo Fit y Silueta son editables)
A5: 1 | B5: Ruta de llenado — los 10 pasos para capturar un producto | G5: Ubicación | H5: Tipo | I5: SKUs con stock (NetSuite, corte 28/09/2026) | J5: Piezas en sistema (NetSuite, corte 28/09/2026) | K5: Bodega (25 / 43) | L5: Correo del usuario (Google / Microsoft) | M5: Nombre del auditor | N5: Usuario de Excel (Archivo › Cuenta) | P5: Estado | Q5: Cuándo se asigna | S5: Marca principal | T5: WB Marca | U5: División | V5: Género | W5: Temporada | X5: Ciclo de vida | Y5: Unidad | Z5: Color | AA5: Fit | AB5: Silueta | AC5: WB Talla | AD5: WB Talla de EE. UU.
A6: 2 | B6: Palabra clave → Categoría — qué categoría asignar según el nombre | G6: J1-L1-01 | H6: Rack físico | I6: =IF(OR($G6="",$H6="Rack físico"),"",COUNTIFS('Stock por Ubicación'!$A:$A,IF($H6="NetSuite",$G6,$G6&" ›*"),'Stock por Ubicación'!$G:$G,"<>0")) | J6: =IF(OR($G6="",$H6="Rack físico"),"",SUMIFS('Stock por Ubicación'!$G:$G,'Stock por Ubicación'!$A:$A,IF($H6="NetSuite",$G6,$G6&" ›*"))) | K6: Bodega 25 | M6: Jesús Fregoso | P6: Verificado | Q6: Todas las piezas de la ubicación cuadran con Productos (documento maestro); sin alertas. | S6: =IFERROR(__xludf.DUMMYFUNCTION("VSTACK(""Multimarca"", FILTER($A$133:$A$149, $A$133:$A$149<>""""), ""No Aplica"")"),"Multimarca") | T6: =IFERROR(__xludf.DUMMYFUNCTION("VSTACK(FILTER($A$133:$A$149, $A$133:$A$149<>""""), ""No Aplica"")"),"Roper") | U6: =IFERROR(__xludf.DUMMYFUNCTION("VSTACK(FILTER($A$123:$A$128, $A$123:$A$128<>""""), ""No Aplica"")"),"Accesorios") | V6: =IFERROR(__xludf.DUMMYFUNCTION("VSTACK(FILTER($B$123:$B$128, $B$123:$B$128<>""""), ""No Aplica"")"),"Hombre") | W6: =IFERROR(__xludf.DUMMYFUNCTION("VSTACK(FILTER($C$123:$C$128, $C$123:$C$128<>""""), ""No Aplica"")"),"SS26") | X6: =IFERROR(__xludf.DUMMYFUNCTION("VSTACK(FILTER($D$123:$D$128, $D$123:$D$128<>""""), ""No Aplica"")"),"Seasonal") | Y6: =IFERROR(__xludf.DUMMYFUNCTION("VSTACK(FILTER($E$123:$E$128, $E$123:$E$128<>""""), ""No Aplica"")"),"PZS") | Z6: =IFERROR(__xludf.DUMMYFUNCTION("VSTACK(FILTER($A$153:$A$169, $A$153:$A$169<>""""), ""No Aplica"")"),"Rojo") | AA6: Regular | AB6: Recto | AC6: =IFERROR(__xludf.DUMMYFUNCTION("VSTACK(UNIQUE(FILTER($B$184:$B$721, $B$184:$B$721<>"""", $B$184:$B$721<>""S / M / L / XL"")), ""No Aplica"")"),"Talla única") | AD6: =IFERROR(__xludf.DUMMYFUNCTION("VSTACK(UNIQUE(FILTER($C$184:$C$721, $C$184:$C$721<>"""", $C$184:$C$721<>""Igual"")), ""No Aplica"")"),"One Size")
A7: 3 | B7: Categorías — división y familia de talla de cada categoría | G7: Almacenes G1522 | H7: NetSuite | I7: =IF(OR($G7="",$H7="Rack físico"),"",COUNTIFS('Stock por Ubicación'!$A:$A,IF($H7="NetSuite",$G7,$G7&" ›*"),'Stock por Ubicación'!$G:$G,"<>0")) | J7: =IF(OR($G7="",$H7="Rack físico"),"",SUMIFS('Stock por Ubicación'!$G:$G,'Stock por Ubicación'!$A:$A,IF($H7="NetSuite",$G7,$G7&" ›*"))) | K7: Bodega 43 | P7: Con Discrepancia | Q7: Algún código escaneado tiene estatus no válido en Productos (documento maestro). | S7: =IFERROR(__xludf.DUMMYFUNCTION("""COMPUTED_VALUE"""),"Roper") | T7: =IFERROR(__xludf.DUMMYFUNCTION("""COMPUTED_VALUE"""),"Denver") | U7: =IFERROR(__xludf.DUMMYFUNCTION("""COMPUTED_VALUE"""),"Ropa") | V7: =IFERROR(__xludf.DUMMYFUNCTION("""COMPUTED_VALUE"""),"Mujer") | W7: =IFERROR(__xludf.DUMMYFUNCTION("""COMPUTED_VALUE"""),"FW26") | X7: =IFERROR(__xludf.DUMMYFUNCTION("""COMPUTED_VALUE"""),"Core") | Y7: =IFERROR(__xludf.DUMMYFUNCTION("""COMPUTED_VALUE"""),"PRS") | Z7: =IFERROR(__xludf.DUMMYFUNCTION("""COMPUTED_VALUE"""),"Azul") | AA7: Relajado | AB7: Bootcut | AC7: =IFERROR(__xludf.DUMMYFUNCTION("""COMPUTED_VALUE"""),"XXS") | AD7: =IFERROR(__xludf.DUMMYFUNCTION("""COMPUTED_VALUE"""),"XXS")
A8: 4 | B8: Listas básicas — División, Género, Temporada, Ciclo de vida, Unidad | G8: AMAZON | H8: NetSuite | I8: =IF(OR($G8="",$H8="Rack físico"),"",COUNTIFS('Stock por Ubicación'!$A:$A,IF($H8="NetSuite",$G8,$G8&" ›*"),'Stock por Ubicación'!$G:$G,"<>0")) | J8: =IF(OR($G8="",$H8="Rack físico"),"",SUMIFS('Stock por Ubicación'!$G:$G,'Stock por Ubicación'!$A:$A,IF($H8="NetSuite",$G8,$G8&" ›*"))) | P8: Revisión Requerida | Q8: Se escaneó al menos un código que no existe en Productos. | S8: =IFERROR(__xludf.DUMMYFUNCTION("""COMPUTED_VALUE"""),"Denver") | T8: =IFERROR(__xludf.DUMMYFUNCTION("""COMPUTED_VALUE"""),"Ariat") | U8: =IFERROR(__xludf.DUMMYFUNCTION("""COMPUTED_VALUE"""),"Denim") | V8: =IFERROR(__xludf.DUMMYFUNCTION("""COMPUTED_VALUE"""),"Niño") | W8: =IFERROR(__xludf.DUMMYFUNCTION("""COMPUTED_VALUE"""),"SS27") | X8: =IFERROR(__xludf.DUMMYFUNCTION("""COMPUTED_VALUE"""),"No Aplica") | Y8: =IFERROR(__xludf.DUMMYFUNCTION("""COMPUTED_VALUE"""),"No Aplica") | Z8: =IFERROR(__xludf.DUMMYFUNCTION("""COMPUTED_VALUE"""),"Amarillo") | AA8: Slim | AB8: Skinny | AC8: =IFERROR(__xludf.DUMMYFUNCTION("""COMPUTED_VALUE"""),"XS") | AD8: =IFERROR(__xludf.DUMMYFUNCTION("""COMPUTED_VALUE"""),"XS")
A9: 5 | B9: Marcas | G9: ARIAT CHIHUAHUA | H9: NetSuite | I9: =IF(OR($G9="",$H9="Rack físico"),"",COUNTIFS('Stock por Ubicación'!$A:$A,IF($H9="NetSuite",$G9,$G9&" ›*"),'Stock por Ubicación'!$G:$G,"<>0")) | J9: =IF(OR($G9="",$H9="Rack físico"),"",SUMIFS('Stock por Ubicación'!$G:$G,'Stock por Ubicación'!$A:$A,IF($H9="NetSuite",$G9,$G9&" ›*"))) | P9: Pendiente | Q9: Ubicación aún no contada o conteo sin finalizar. | S9: =IFERROR(__xludf.DUMMYFUNCTION("""COMPUTED_VALUE"""),"Ariat") | T9: =IFERROR(__xludf.DUMMYFUNCTION("""COMPUTED_VALUE"""),"Wrangler") | U9: =IFERROR(__xludf.DUMMYFUNCTION("""COMPUTED_VALUE"""),"Calzado") | V9: =IFERROR(__xludf.DUMMYFUNCTION("""COMPUTED_VALUE"""),"Niña") | W9: =IFERROR(__xludf.DUMMYFUNCTION("""COMPUTED_VALUE"""),"FW27") | Z9: =IFERROR(__xludf.DUMMYFUNCTION("""COMPUTED_VALUE"""),"Verde") | AA9: Clásico | AB9: Tapered | AC9: =IFERROR(__xludf.DUMMYFUNCTION("""COMPUTED_VALUE"""),"S") | AD9: =IFERROR(__xludf.DUMMYFUNCTION("""COMPUTED_VALUE"""),"S")
A10: 6 | B10: Colores y sinónimos — color base y cómo traducir nombres comerciales | G10: ARIAT OUTLET GDL | H10: NetSuite | I10: =IF(OR($G10="",$H10="Rack físico"),"",COUNTIFS('Stock por Ubicación'!$A:$A,IF($H10="NetSuite",$G10,$G10&" ›*"),'Stock por Ubicación'!$G:$G,"<>0")) | J10: =IF(OR($G10="",$H10="Rack físico"),"",SUMIFS('Stock por Ubicación'!$G:$G,'Stock por Ubicación'!$A:$A,IF($H10="NetSuite",$G10,$G10&" ›*"))) | S10: =IFERROR(__xludf.DUMMYFUNCTION("""COMPUTED_VALUE"""),"Wrangler") | T10: =IFERROR(__xludf.DUMMYFUNCTION("""COMPUTED_VALUE"""),"Stetson") | U10: =IFERROR(__xludf.DUMMYFUNCTION("""COMPUTED_VALUE"""),"No Aplica") | V10: =IFERROR(__xludf.DUMMYFUNCTION("""COMPUTED_VALUE"""),"Unisex") | W10: =IFERROR(__xludf.DUMMYFUNCTION("""COMPUTED_VALUE"""),"SS28") | Z10: =IFERROR(__xludf.DUMMYFUNCTION("""COMPUTED_VALUE"""),"Naranja") | AA10: Moderno | AB10: Trouser | AC10: =IFERROR(__xludf.DUMMYFUNCTION("""COMPUTED_VALUE"""),"M") | AD10: =IFERROR(__xludf.DUMMYFUNCTION("""COMPUTED_VALUE"""),"M")
A11: 7 | B11: Fit y Silueta — valores por tipo de prenda | G11: ARIAT PLAZA SAN LUIS | H11: NetSuite | I11: =IF(OR($G11="",$H11="Rack físico"),"",COUNTIFS('Stock por Ubicación'!$A:$A,IF($H11="NetSuite",$G11,$G11&" ›*"),'Stock por Ubicación'!$G:$G,"<>0")) | J11: =IF(OR($G11="",$H11="Rack físico"),"",SUMIFS('Stock por Ubicación'!$G:$G,'Stock por Ubicación'!$A:$A,IF($H11="NetSuite",$G11,$G11&" ›*"))) | S11: =IFERROR(__xludf.DUMMYFUNCTION("""COMPUTED_VALUE"""),"Stetson") | T11: =IFERROR(__xludf.DUMMYFUNCTION("""COMPUTED_VALUE"""),"Montana West") | V11: =IFERROR(__xludf.DUMMYFUNCTION("""COMPUTED_VALUE"""),"No Aplica") | W11: =IFERROR(__xludf.DUMMYFUNCTION("""COMPUTED_VALUE"""),"FW28") | Z11: =IFERROR(__xludf.DUMMYFUNCTION("""COMPUTED_VALUE"""),"Morado") | AA11: Recto | AB11: Punta Redonda Ancha | AC11: =IFERROR(__xludf.DUMMYFUNCTION("""COMPUTED_VALUE"""),"L") | AD11: =IFERROR(__xludf.DUMMYFUNCTION("""COMPUTED_VALUE"""),"L")
A12: 8 | B12: Catálogo de tallas — WB Talla → Talla de EE. UU. (con filtro por familia) | G12: ARIAT SAN NICOLAS NL | H12: NetSuite | I12: =IF(OR($G12="",$H12="Rack físico"),"",COUNTIFS('Stock por Ubicación'!$A:$A,IF($H12="NetSuite",$G12,$G12&" ›*"),'Stock por Ubicación'!$G:$G,"<>0")) | J12: =IF(OR($G12="",$H12="Rack físico"),"",SUMIFS('Stock por Ubicación'!$G:$G,'Stock por Ubicación'!$A:$A,IF($H12="NetSuite",$G12,$G12&" ›*"))) | S12: =IFERROR(__xludf.DUMMYFUNCTION("""COMPUTED_VALUE"""),"Montana West") | T12: =IFERROR(__xludf.DUMMYFUNCTION("""COMPUTED_VALUE"""),"Tru Western") | W12: =IFERROR(__xludf.DUMMYFUNCTION("""COMPUTED_VALUE"""),"No Aplica") | Z12: =IFERROR(__xludf.DUMMYFUNCTION("""COMPUTED_VALUE"""),"Rosa") | AA12: Bootcut | AB12: Punta Cuadrada Ancha | AC12: =IFERROR(__xludf.DUMMYFUNCTION("""COMPUTED_VALUE"""),"XL") | AD12: =IFERROR(__xludf.DUMMYFUNCTION("""COMPUTED_VALUE"""),"XL")
A13: 9 | B13: Ubicaciones / Racks (columna G) | G13: B25 CEDIS | H13: NetSuite | I13: =IF(OR($G13="",$H13="Rack físico"),"",COUNTIFS('Stock por Ubicación'!$A:$A,IF($H13="NetSuite",$G13,$G13&" ›*"),'Stock por Ubicación'!$G:$G,"<>0")) | J13: =IF(OR($G13="",$H13="Rack físico"),"",SUMIFS('Stock por Ubicación'!$G:$G,'Stock por Ubicación'!$A:$A,IF($H13="NetSuite",$G13,$G13&" ›*"))) | K13: Bodega 25 | S13: =IFERROR(__xludf.DUMMYFUNCTION("""COMPUTED_VALUE"""),"Tru Western") | T13: =IFERROR(__xludf.DUMMYFUNCTION("""COMPUTED_VALUE"""),"Ranch & Corral") | Z13: =IFERROR(__xludf.DUMMYFUNCTION("""COMPUTED_VALUE"""),"Negro") | AA13: No Aplica | AB13: Punta Redonda | AC13: =IFERROR(__xludf.DUMMYFUNCTION("""COMPUTED_VALUE"""),"XXL") | AD13: =IFERROR(__xludf.DUMMYFUNCTION("""COMPUTED_VALUE"""),"XXL")
A14: 10 | B14: Auditores (columna L) | G14: B25 STETSON.MX | H14: NetSuite | I14: =IF(OR($G14="",$H14="Rack físico"),"",COUNTIFS('Stock por Ubicación'!$A:$A,IF($H14="NetSuite",$G14,$G14&" ›*"),'Stock por Ubicación'!$G:$G,"<>0")) | J14: =IF(OR($G14="",$H14="Rack físico"),"",SUMIFS('Stock por Ubicación'!$G:$G,'Stock por Ubicación'!$A:$A,IF($H14="NetSuite",$G14,$G14&" ›*"))) | K14: Bodega 25 | S14: =IFERROR(__xludf.DUMMYFUNCTION("""COMPUTED_VALUE"""),"Ranch & Corral") | T14: =IFERROR(__xludf.DUMMYFUNCTION("""COMPUTED_VALUE"""),"Jony Lama") | Z14: =IFERROR(__xludf.DUMMYFUNCTION("""COMPUTED_VALUE"""),"Blanco") | AB14: Punta Cuadrada | AC14: =IFERROR(__xludf.DUMMYFUNCTION("""COMPUTED_VALUE"""),"XXXL") | AD14: =IFERROR(__xludf.DUMMYFUNCTION("""COMPUTED_VALUE"""),"XXXL")
A15: 11 | B15: Estados de conteo / Dictamen (columna P) | G15: B25 WB MERCADO LIBRE | H15: NetSuite | I15: =IF(OR($G15="",$H15="Rack físico"),"",COUNTIFS('Stock por Ubicación'!$A:$A,IF($H15="NetSuite",$G15,$G15&" ›*"),'Stock por Ubicación'!$G:$G,"<>0")) | J15: =IF(OR($G15="",$H15="Rack físico"),"",SUMIFS('Stock por Ubicación'!$G:$G,'Stock por Ubicación'!$A:$A,IF($H15="NetSuite",$G15,$G15&" ›*"))) | K15: Bodega 25 | S15: =IFERROR(__xludf.DUMMYFUNCTION("""COMPUTED_VALUE"""),"Jony Lama") | T15: =IFERROR(__xludf.DUMMYFUNCTION("""COMPUTED_VALUE"""),"Justin boots") | Z15: =IFERROR(__xludf.DUMMYFUNCTION("""COMPUTED_VALUE"""),"Gris") | AB15: Punta Ovalada | AC15: =IFERROR(__xludf.DUMMYFUNCTION("""COMPUTED_VALUE"""),"4XL") | AD15: =IFERROR(__xludf.DUMMYFUNCTION("""COMPUTED_VALUE"""),"4XL")
A16: 12 | B16: Listas automáticas para desplegables (columna S, no editar) | G16: B25 WESTERN BROTHERS.MX | H16: NetSuite | I16: =IF(OR($G16="",$H16="Rack físico"),"",COUNTIFS('Stock por Ubicación'!$A:$A,IF($H16="NetSuite",$G16,$G16&" ›*"),'Stock por Ubicación'!$G:$G,"<>0")) | J16: =IF(OR($G16="",$H16="Rack físico"),"",SUMIFS('Stock por Ubicación'!$G:$G,'Stock por Ubicación'!$A:$A,IF($H16="NetSuite",$G16,$G16&" ›*"))) | K16: Bodega 25 | S16: =IFERROR(__xludf.DUMMYFUNCTION("""COMPUTED_VALUE"""),"Justin boots") | T16: =IFERROR(__xludf.DUMMYFUNCTION("""COMPUTED_VALUE"""),"Yellowstone") | Z16: =IFERROR(__xludf.DUMMYFUNCTION("""COMPUTED_VALUE"""),"Beige") | AB16: Punta Snip | AC16: =IFERROR(__xludf.DUMMYFUNCTION("""COMPUTED_VALUE"""),0.0) | AD16: =IFERROR(__xludf.DUMMYFUNCTION("""COMPUTED_VALUE"""),0.0)
G17: CAPSLAB Warehouse | H17: NetSuite | I17: =IF(OR($G17="",$H17="Rack físico"),"",COUNTIFS('Stock por Ubicación'!$A:$A,IF($H17="NetSuite",$G17,$G17&" ›*"),'Stock por Ubicación'!$G:$G,"<>0")) | J17: =IF(OR($G17="",$H17="Rack físico"),"",SUMIFS('Stock por Ubicación'!$G:$G,'Stock por Ubicación'!$A:$A,IF($H17="NetSuite",$G17,$G17&" ›*"))) | S17: =IFERROR(__xludf.DUMMYFUNCTION("""COMPUTED_VALUE"""),"Yellowstone") | T17: =IFERROR(__xludf.DUMMYFUNCTION("""COMPUTED_VALUE"""),"Generico") | Z17: =IFERROR(__xludf.DUMMYFUNCTION("""COMPUTED_VALUE"""),"Cafe") | AB17: Horma Alexia | AC17: =IFERROR(__xludf.DUMMYFUNCTION("""COMPUTED_VALUE"""),2.0) | AD17: =IFERROR(__xludf.DUMMYFUNCTION("""COMPUTED_VALUE"""),2.0)
A18: 1. RUTA DE LLENADO (sigue estos pasos en orden) | E18: ↑ Volver al índice | G18: CL Muestras | H18: NetSuite | I18: =IF(OR($G18="",$H18="Rack físico"),"",COUNTIFS('Stock por Ubicación'!$A:$A,IF($H18="NetSuite",$G18,$G18&" ›*"),'Stock por Ubicación'!$G:$G,"<>0")) | J18: =IF(OR($G18="",$H18="Rack físico"),"",SUMIFS('Stock por Ubicación'!$G:$G,'Stock por Ubicación'!$A:$A,IF($H18="NetSuite",$G18,$G18&" ›*"))) | S18: =IFERROR(__xludf.DUMMYFUNCTION("""COMPUTED_VALUE"""),"Generico") | T18: =IFERROR(__xludf.DUMMYFUNCTION("""COMPUTED_VALUE"""),"CAPSLAB") | Z18: =IFERROR(__xludf.DUMMYFUNCTION("""COMPUTED_VALUE"""),"Varios") | AB18: Horma Agatha | AC18: =IFERROR(__xludf.DUMMYFUNCTION("""COMPUTED_VALUE"""),4.0) | AD18: =IFERROR(__xludf.DUMMYFUNCTION("""COMPUTED_VALUE"""),4.0)
A19: Paso | B19: Campo | C19: Qué hacer | G19: CL POS | H19: NetSuite | I19: =IF(OR($G19="",$H19="Rack físico"),"",COUNTIFS('Stock por Ubicación'!$A:$A,IF($H19="NetSuite",$G19,$G19&" ›*"),'Stock por Ubicación'!$G:$G,"<>0")) | J19: =IF(OR($G19="",$H19="Rack físico"),"",SUMIFS('Stock por Ubicación'!$G:$G,'Stock por Ubicación'!$A:$A,IF($H19="NetSuite",$G19,$G19&" ›*"))) | S19: =IFERROR(__xludf.DUMMYFUNCTION("""COMPUTED_VALUE"""),"CAPSLAB") | T19: =IFERROR(__xludf.DUMMYFUNCTION("""COMPUTED_VALUE"""),"Happy Socks") | Z19: =IFERROR(__xludf.DUMMYFUNCTION("""COMPUTED_VALUE"""),"No Aplica") | AB19: Copa Cattleman | AC19: =IFERROR(__xludf.DUMMYFUNCTION("""COMPUTED_VALUE"""),6.0) | AD19: =IFERROR(__xludf.DUMMYFUNCTION("""COMPUTED_VALUE"""),6.0)
A20: 1 | B20: Categoría y División | C20: Busca en el nombre del producto una palabra de la tabla «2. Palabra clave → Categoría». Esa fila te da la Categoría y la División. Si no hay palabra clave, usa la lista «3. Categorías»; si no existe, no la inventes: anótala en Revisión. | G20: CONSIGNA REFLO | H20: NetSuite | I20: =IF(OR($G20="",$H20="Rack físico"),"",COUNTIFS('Stock por Ubicación'!$A:$A,IF($H20="NetSuite",$G20,$G20&" ›*"),'Stock por Ubicación'!$G:$G,"<>0")) | J20: =IF(OR($G20="",$H20="Rack físico"),"",SUMIFS('Stock por Ubicación'!$G:$G,'Stock por Ubicación'!$A:$A,IF($H20="NetSuite",$G20,$G20&" ›*"))) | S20: =IFERROR(__xludf.DUMMYFUNCTION("""COMPUTED_VALUE"""),"Happy Socks") | T20: =IFERROR(__xludf.DUMMYFUNCTION("""COMPUTED_VALUE"""),"REFLO") | AB20: Copa Rancher | AC20: =IFERROR(__xludf.DUMMYFUNCTION("""COMPUTED_VALUE"""),8.0) | AD20: =IFERROR(__xludf.DUMMYFUNCTION("""COMPUTED_VALUE"""),8.0)
A21: 2 | B21: Género | C21: Dama / Mujer → Mujer · Caballero / Hombre → Hombre · Niño / Niña según corresponda · Sombreros y accesorios sin género → Unisex. Usa solo los valores de «4. Listas básicas». | G21: CONSIGNAS | H21: NetSuite | I21: =IF(OR($G21="",$H21="Rack físico"),"",COUNTIFS('Stock por Ubicación'!$A:$A,IF($H21="NetSuite",$G21,$G21&" ›*"),'Stock por Ubicación'!$G:$G,"<>0")) | J21: =IF(OR($G21="",$H21="Rack físico"),"",SUMIFS('Stock por Ubicación'!$G:$G,'Stock por Ubicación'!$A:$A,IF($H21="NetSuite",$G21,$G21&" ›*"))) | S21: =IFERROR(__xludf.DUMMYFUNCTION("""COMPUTED_VALUE"""),"REFLO") | T21: =IFERROR(__xludf.DUMMYFUNCTION("""COMPUTED_VALUE"""),"Willow Lane") | AB21: Copa Pinch Front | AC21: =IFERROR(__xludf.DUMMYFUNCTION("""COMPUTED_VALUE"""),10.0) | AD21: =IFERROR(__xludf.DUMMYFUNCTION("""COMPUTED_VALUE"""),10.0)
A22: 3 | B22: Familia de talla | C22: Con Categoría + Género ubica la familia en «3. Categorías» (columna Familia de talla). La familia define qué valores de talla son válidos. | G22: DEPARTAMENTAL | H22: NetSuite | I22: =IF(OR($G22="",$H22="Rack físico"),"",COUNTIFS('Stock por Ubicación'!$A:$A,IF($H22="NetSuite",$G22,$G22&" ›*"),'Stock por Ubicación'!$G:$G,"<>0")) | J22: =IF(OR($G22="",$H22="Rack físico"),"",SUMIFS('Stock por Ubicación'!$G:$G,'Stock por Ubicación'!$A:$A,IF($H22="NetSuite",$G22,$G22&" ›*"))) | S22: =IFERROR(__xludf.DUMMYFUNCTION("""COMPUTED_VALUE"""),"Willow Lane") | T22: =IFERROR(__xludf.DUMMYFUNCTION("""COMPUTED_VALUE"""),"No Aplica") | AB22: Copa Gus | AC22: =IFERROR(__xludf.DUMMYFUNCTION("""COMPUTED_VALUE"""),12.0) | AD22: =IFERROR(__xludf.DUMMYFUNCTION("""COMPUTED_VALUE"""),12.0)
A23: 4 | B23: WB Talla | C23: Captura el valor EXACTO de la columna «WB Talla» del «8. Catálogo de tallas» para esa familia (mismo texto, espacios y mayúsculas). Equivalencias de captura: CH→S, MED→M, GDE→L, 2XL→XXL, UNI→Talla única. Regla general: WB Talla = cómo se vende en México; Talla de EE. UU. = etiqueta americana. Nunca escribas equivalencias entre paréntesis dentro de la celda. | G23: ECOMMERCE | H23: NetSuite | I23: =IF(OR($G23="",$H23="Rack físico"),"",COUNTIFS('Stock por Ubicación'!$A:$A,IF($H23="NetSuite",$G23,$G23&" ›*"),'Stock por Ubicación'!$G:$G,"<>0")) | J23: =IF(OR($G23="",$H23="Rack físico"),"",SUMIFS('Stock por Ubicación'!$G:$G,'Stock por Ubicación'!$A:$A,IF($H23="NetSuite",$G23,$G23&" ›*"))) | S23: =IFERROR(__xludf.DUMMYFUNCTION("""COMPUTED_VALUE"""),"No Aplica") | AB23: Copa Teardrop | AC23: =IFERROR(__xludf.DUMMYFUNCTION("""COMPUTED_VALUE"""),14.0) | AD23: =IFERROR(__xludf.DUMMYFUNCTION("""COMPUTED_VALUE"""),14.0)
A24: 5 | B24: WB Talla de EE. UU. | C24: Toma el valor de la misma fila del catálogo (columna «Talla de EE. UU.»). Si la regla dice «Igual», copia la WB Talla. | G24: ENGLISH REP | H24: NetSuite | I24: =IF(OR($G24="",$H24="Rack físico"),"",COUNTIFS('Stock por Ubicación'!$A:$A,IF($H24="NetSuite",$G24,$G24&" ›*"),'Stock por Ubicación'!$G:$G,"<>0")) | J24: =IF(OR($G24="",$H24="Rack físico"),"",SUMIFS('Stock por Ubicación'!$G:$G,'Stock por Ubicación'!$A:$A,IF($H24="NetSuite",$G24,$G24&" ›*"))) | AB24: Copa Open Road | AC24: =IFERROR(__xludf.DUMMYFUNCTION("""COMPUTED_VALUE"""),16.0) | AD24: =IFERROR(__xludf.DUMMYFUNCTION("""COMPUTED_VALUE"""),16.0)
A25: 6 | B25: Color | C25: Elige el color base de «6. Colores». Nombres comerciales se traducen con la columna Sinónimos de la misma sección (ej. Cognac → Cafe). Si el nombre trae dos colores, usa el dominante. | G25: EVENTOS (CONSIGNA) | H25: NetSuite | I25: =IF(OR($G25="",$H25="Rack físico"),"",COUNTIFS('Stock por Ubicación'!$A:$A,IF($H25="NetSuite",$G25,$G25&" ›*"),'Stock por Ubicación'!$G:$G,"<>0")) | J25: =IF(OR($G25="",$H25="Rack físico"),"",SUMIFS('Stock por Ubicación'!$G:$G,'Stock por Ubicación'!$A:$A,IF($H25="NetSuite",$G25,$G25&" ›*"))) | AB25: Copa Brick | AC25: =IFERROR(__xludf.DUMMYFUNCTION("""COMPUTED_VALUE"""),"33 x 28") | AD25: =IFERROR(__xludf.DUMMYFUNCTION("""COMPUTED_VALUE"""),"33W / 28L")
A26: 7 | B26: Temporada, Ciclo de vida, Unidad | C26: Temporada y Ciclo de vida de «4. Listas básicas». Unidad: PRS para calzado (Botas, Zapatos, Tenis, Pantuflas); PZS para todo lo demás. | G26: Fixtures & MKT | H26: NetSuite | I26: =IF(OR($G26="",$H26="Rack físico"),"",COUNTIFS('Stock por Ubicación'!$A:$A,IF($H26="NetSuite",$G26,$G26&" ›*"),'Stock por Ubicación'!$G:$G,"<>0")) | J26: =IF(OR($G26="",$H26="Rack físico"),"",SUMIFS('Stock por Ubicación'!$G:$G,'Stock por Ubicación'!$A:$A,IF($H26="NetSuite",$G26,$G26&" ›*"))) | AB26: Cierre perimetral | AC26: =IFERROR(__xludf.DUMMYFUNCTION("""COMPUTED_VALUE"""),"34 x 28") | AD26: =IFERROR(__xludf.DUMMYFUNCTION("""COMPUTED_VALUE"""),"34W / 28L")
A27: 8 | B27: Fit | C27: Determina el fit usando la descripción larga y la tabla «7. Fit y Silueta». Aplica solo para Ropa y Denim. Usa "No Aplica" en calzado, sombreros y accesorios. | G27: FULL MELI | H27: NetSuite | I27: =IF(OR($G27="",$H27="Rack físico"),"",COUNTIFS('Stock por Ubicación'!$A:$A,IF($H27="NetSuite",$G27,$G27&" ›*"),'Stock por Ubicación'!$G:$G,"<>0")) | J27: =IF(OR($G27="",$H27="Rack físico"),"",SUMIFS('Stock por Ubicación'!$G:$G,'Stock por Ubicación'!$A:$A,IF($H27="NetSuite",$G27,$G27&" ›*"))) | AB27: No Aplica | AC27: =IFERROR(__xludf.DUMMYFUNCTION("""COMPUTED_VALUE"""),"36 x 28") | AD27: =IFERROR(__xludf.DUMMYFUNCTION("""COMPUTED_VALUE"""),"36W / 28L")
A28: 9 | B28: Silueta | C28: Determina la silueta usando la descripción y la tabla «7. Fit y Silueta». Aplica solo para Sombreros, Calzado y Jeans. Usa "No Aplica" en el resto. | G28: G1522 Defectos | H28: NetSuite | I28: =IF(OR($G28="",$H28="Rack físico"),"",COUNTIFS('Stock por Ubicación'!$A:$A,IF($H28="NetSuite",$G28,$G28&" ›*"),'Stock por Ubicación'!$G:$G,"<>0")) | J28: =IF(OR($G28="",$H28="Rack físico"),"",SUMIFS('Stock por Ubicación'!$G:$G,'Stock por Ubicación'!$A:$A,IF($H28="NetSuite",$G28,$G28&" ›*"))) | K28: Bodega 43 | AC28: =IFERROR(__xludf.DUMMYFUNCTION("""COMPUTED_VALUE"""),"28 x 30") | AD28: =IFERROR(__xludf.DUMMYFUNCTION("""COMPUTED_VALUE"""),"28W / 30L")
A29: 10 | B29: Si algo no cuadra | C29: No inventes valores: deja el campo vacío y registra el caso en la hoja Revisión para validarlo. | G29: G1522 Lost | H29: NetSuite | I29: =IF(OR($G29="",$H29="Rack físico"),"",COUNTIFS('Stock por Ubicación'!$A:$A,IF($H29="NetSuite",$G29,$G29&" ›*"),'Stock por Ubicación'!$G:$G,"<>0")) | J29: =IF(OR($G29="",$H29="Rack físico"),"",SUMIFS('Stock por Ubicación'!$G:$G,'Stock por Ubicación'!$A:$A,IF($H29="NetSuite",$G29,$G29&" ›*"))) | K29: Bodega 43 | AC29: =IFERROR(__xludf.DUMMYFUNCTION("""COMPUTED_VALUE"""),"29 x 30") | AD29: =IFERROR(__xludf.DUMMYFUNCTION("""COMPUTED_VALUE"""),"29W / 30L")
G30: G1522 QA Hold | H30: NetSuite | I30: =IF(OR($G30="",$H30="Rack físico"),"",COUNTIFS('Stock por Ubicación'!$A:$A,IF($H30="NetSuite",$G30,$G30&" ›*"),'Stock por Ubicación'!$G:$G,"<>0")) | J30: =IF(OR($G30="",$H30="Rack físico"),"",SUMIFS('Stock por Ubicación'!$G:$G,'Stock por Ubicación'!$A:$A,IF($H30="NetSuite",$G30,$G30&" ›*"))) | K30: Bodega 43 | AC30: =IFERROR(__xludf.DUMMYFUNCTION("""COMPUTED_VALUE"""),"30 x 30") | AD30: =IFERROR(__xludf.DUMMYFUNCTION("""COMPUTED_VALUE"""),"30W / 30L")
A31: 2. PALABRA CLAVE → CATEGORÍA | E31: ↑ Volver al índice | G31: GENERAL | H31: NetSuite | I31: =IF(OR($G31="",$H31="Rack físico"),"",COUNTIFS('Stock por Ubicación'!$A:$A,IF($H31="NetSuite",$G31,$G31&" ›*"),'Stock por Ubicación'!$G:$G,"<>0")) | J31: =IF(OR($G31="",$H31="Rack físico"),"",SUMIFS('Stock por Ubicación'!$G:$G,'Stock por Ubicación'!$A:$A,IF($H31="NetSuite",$G31,$G31&" ›*"))) | AC31: =IFERROR(__xludf.DUMMYFUNCTION("""COMPUTED_VALUE"""),"31 x 30") | AD31: =IFERROR(__xludf.DUMMYFUNCTION("""COMPUTED_VALUE"""),"31W / 30L")
A32: Busca la palabra en el nombre del producto; manda la PRIMERA que coincida (por eso las frases largas van arriba). | G32: HAPPY SOCKS | H32: NetSuite | I32: =IF(OR($G32="",$H32="Rack físico"),"",COUNTIFS('Stock por Ubicación'!$A:$A,IF($H32="NetSuite",$G32,$G32&" ›*"),'Stock por Ubicación'!$G:$G,"<>0")) | J32: =IF(OR($G32="",$H32="Rack físico"),"",SUMIFS('Stock por Ubicación'!$G:$G,'Stock por Ubicación'!$A:$A,IF($H32="NetSuite",$G32,$G32&" ›*"))) | AC32: =IFERROR(__xludf.DUMMYFUNCTION("""COMPUTED_VALUE"""),"32 x 30") | AD32: =IFERROR(__xludf.DUMMYFUNCTION("""COMPUTED_VALUE"""),"32W / 30L")
A33: Palabra clave | B33: Categoría | C33: División | G33: HS MERCADO LIBRE | H33: NetSuite | I33: =IF(OR($G33="",$H33="Rack físico"),"",COUNTIFS('Stock por Ubicación'!$A:$A,IF($H33="NetSuite",$G33,$G33&" ›*"),'Stock por Ubicación'!$G:$G,"<>0")) | J33: =IF(OR($G33="",$H33="Rack físico"),"",SUMIFS('Stock por Ubicación'!$G:$G,'Stock por Ubicación'!$A:$A,IF($H33="NetSuite",$G33,$G33&" ›*"))) | AC33: =IFERROR(__xludf.DUMMYFUNCTION("""COMPUTED_VALUE"""),"33 x 30") | AD33: =IFERROR(__xludf.DUMMYFUNCTION("""COMPUTED_VALUE"""),"33W / 30L")
A34: Cuidado de Botas | B34: Cuidado de Botas | C34: Accesorios | G34: KEY ACCOUNTS | H34: NetSuite | I34: =IF(OR($G34="",$H34="Rack físico"),"",COUNTIFS('Stock por Ubicación'!$A:$A,IF($H34="NetSuite",$G34,$G34&" ›*"),'Stock por Ubicación'!$G:$G,"<>0")) | J34: =IF(OR($G34="",$H34="Rack físico"),"",SUMIFS('Stock por Ubicación'!$G:$G,'Stock por Ubicación'!$A:$A,IF($H34="NetSuite",$G34,$G34&" ›*"))) | AC34: =IFERROR(__xludf.DUMMYFUNCTION("""COMPUTED_VALUE"""),"34 x 30") | AD34: =IFERROR(__xludf.DUMMYFUNCTION("""COMPUTED_VALUE"""),"34W / 30L")
A35: Cuidado de Sombreros | B35: Cuidado de Sombreros | C35: Accesorios | G35: LIVERPOOL MKP | H35: NetSuite | I35: =IF(OR($G35="",$H35="Rack físico"),"",COUNTIFS('Stock por Ubicación'!$A:$A,IF($H35="NetSuite",$G35,$G35&" ›*"),'Stock por Ubicación'!$G:$G,"<>0")) | J35: =IF(OR($G35="",$H35="Rack físico"),"",SUMIFS('Stock por Ubicación'!$G:$G,'Stock por Ubicación'!$A:$A,IF($H35="NetSuite",$G35,$G35&" ›*"))) | AC35: =IFERROR(__xludf.DUMMYFUNCTION("""COMPUTED_VALUE"""),"35 x 30") | AD35: =IFERROR(__xludf.DUMMYFUNCTION("""COMPUTED_VALUE"""),"35W / 30L")
A36: Plumas para sombrero | B36: Plumas para sombrero | C36: Accesorios | G36: Mercado libre | H36: NetSuite | I36: =IF(OR($G36="",$H36="Rack físico"),"",COUNTIFS('Stock por Ubicación'!$A:$A,IF($H36="NetSuite",$G36,$G36&" ›*"),'Stock por Ubicación'!$G:$G,"<>0")) | J36: =IF(OR($G36="",$H36="Rack físico"),"",SUMIFS('Stock por Ubicación'!$G:$G,'Stock por Ubicación'!$A:$A,IF($H36="NetSuite",$G36,$G36&" ›*"))) | AC36: =IFERROR(__xludf.DUMMYFUNCTION("""COMPUTED_VALUE"""),"36 x 30") | AD36: =IFERROR(__xludf.DUMMYFUNCTION("""COMPUTED_VALUE"""),"36W / 30L")
A37: Gorra | B37: Gorras | C37: Accesorios | G37: MUESTRAS & EXPO | H37: NetSuite | I37: =IF(OR($G37="",$H37="Rack físico"),"",COUNTIFS('Stock por Ubicación'!$A:$A,IF($H37="NetSuite",$G37,$G37&" ›*"),'Stock por Ubicación'!$G:$G,"<>0")) | J37: =IF(OR($G37="",$H37="Rack físico"),"",SUMIFS('Stock por Ubicación'!$G:$G,'Stock por Ubicación'!$A:$A,IF($H37="NetSuite",$G37,$G37&" ›*"))) | AC37: =IFERROR(__xludf.DUMMYFUNCTION("""COMPUTED_VALUE"""),"38 x 30") | AD37: =IFERROR(__xludf.DUMMYFUNCTION("""COMPUTED_VALUE"""),"38W / 30L")
A38: Sombrero | B38: Sombreros | C38: Accesorios | G38: MUESTRAS REFLO | H38: NetSuite | I38: =IF(OR($G38="",$H38="Rack físico"),"",COUNTIFS('Stock por Ubicación'!$A:$A,IF($H38="NetSuite",$G38,$G38&" ›*"),'Stock por Ubicación'!$G:$G,"<>0")) | J38: =IF(OR($G38="",$H38="Rack físico"),"",SUMIFS('Stock por Ubicación'!$G:$G,'Stock por Ubicación'!$A:$A,IF($H38="NetSuite",$G38,$G38&" ›*"))) | AC38: =IFERROR(__xludf.DUMMYFUNCTION("""COMPUTED_VALUE"""),"40 x 30") | AD38: =IFERROR(__xludf.DUMMYFUNCTION("""COMPUTED_VALUE"""),"40W / 30L")
A39: Texana | B39: Sombreros | C39: Accesorios | G39: Nogales Store | H39: NetSuite | I39: =IF(OR($G39="",$H39="Rack físico"),"",COUNTIFS('Stock por Ubicación'!$A:$A,IF($H39="NetSuite",$G39,$G39&" ›*"),'Stock por Ubicación'!$G:$G,"<>0")) | J39: =IF(OR($G39="",$H39="Rack físico"),"",SUMIFS('Stock por Ubicación'!$G:$G,'Stock por Ubicación'!$A:$A,IF($H39="NetSuite",$G39,$G39&" ›*"))) | AC39: =IFERROR(__xludf.DUMMYFUNCTION("""COMPUTED_VALUE"""),"42 x 30") | AD39: =IFERROR(__xludf.DUMMYFUNCTION("""COMPUTED_VALUE"""),"42W / 30L")
A40: Bandana | B40: Bandanas | C40: Accesorios | G40: Plaza del Sol Store | H40: NetSuite | I40: =IF(OR($G40="",$H40="Rack físico"),"",COUNTIFS('Stock por Ubicación'!$A:$A,IF($H40="NetSuite",$G40,$G40&" ›*"),'Stock por Ubicación'!$G:$G,"<>0")) | J40: =IF(OR($G40="",$H40="Rack físico"),"",SUMIFS('Stock por Ubicación'!$G:$G,'Stock por Ubicación'!$A:$A,IF($H40="NetSuite",$G40,$G40&" ›*"))) | AC40: =IFERROR(__xludf.DUMMYFUNCTION("""COMPUTED_VALUE"""),"44 x 30") | AD40: =IFERROR(__xludf.DUMMYFUNCTION("""COMPUTED_VALUE"""),"44W / 30L")
A41: Bolso | B41: Bolsos | C41: Accesorios | G41: POTRILLOS | H41: NetSuite | I41: =IF(OR($G41="",$H41="Rack físico"),"",COUNTIFS('Stock por Ubicación'!$A:$A,IF($H41="NetSuite",$G41,$G41&" ›*"),'Stock por Ubicación'!$G:$G,"<>0")) | J41: =IF(OR($G41="",$H41="Rack físico"),"",SUMIFS('Stock por Ubicación'!$G:$G,'Stock por Ubicación'!$A:$A,IF($H41="NetSuite",$G41,$G41&" ›*"))) | AC41: =IFERROR(__xludf.DUMMYFUNCTION("""COMPUTED_VALUE"""),"46 x 30") | AD41: =IFERROR(__xludf.DUMMYFUNCTION("""COMPUTED_VALUE"""),"46W / 30L")
A42: Bufanda | B42: Bufandas | C42: Accesorios | G42: PRIVALIA | H42: NetSuite | I42: =IF(OR($G42="",$H42="Rack físico"),"",COUNTIFS('Stock por Ubicación'!$A:$A,IF($H42="NetSuite",$G42,$G42&" ›*"),'Stock por Ubicación'!$G:$G,"<>0")) | J42: =IF(OR($G42="",$H42="Rack físico"),"",SUMIFS('Stock por Ubicación'!$G:$G,'Stock por Ubicación'!$A:$A,IF($H42="NetSuite",$G42,$G42&" ›*"))) | AC42: =IFERROR(__xludf.DUMMYFUNCTION("""COMPUTED_VALUE"""),"48 x 30") | AD42: =IFERROR(__xludf.DUMMYFUNCTION("""COMPUTED_VALUE"""),"48W / 30L")
A43: Cartera | B43: Carteras | C43: Accesorios | G43: PUNTO DE VENTA | H43: NetSuite | I43: =IF(OR($G43="",$H43="Rack físico"),"",COUNTIFS('Stock por Ubicación'!$A:$A,IF($H43="NetSuite",$G43,$G43&" ›*"),'Stock por Ubicación'!$G:$G,"<>0")) | J43: =IF(OR($G43="",$H43="Rack físico"),"",SUMIFS('Stock por Ubicación'!$G:$G,'Stock por Ubicación'!$A:$A,IF($H43="NetSuite",$G43,$G43&" ›*"))) | AC43: =IFERROR(__xludf.DUMMYFUNCTION("""COMPUTED_VALUE"""),"50 x 30") | AD43: =IFERROR(__xludf.DUMMYFUNCTION("""COMPUTED_VALUE"""),"50W / 30L")
A44: Clip para billetes | B44: Carteras | C44: Accesorios | G44: Punto de venta HS | H44: NetSuite | I44: =IF(OR($G44="",$H44="Rack físico"),"",COUNTIFS('Stock por Ubicación'!$A:$A,IF($H44="NetSuite",$G44,$G44&" ›*"),'Stock por Ubicación'!$G:$G,"<>0")) | J44: =IF(OR($G44="",$H44="Rack físico"),"",SUMIFS('Stock por Ubicación'!$G:$G,'Stock por Ubicación'!$A:$A,IF($H44="NetSuite",$G44,$G44&" ›*"))) | AC44: =IFERROR(__xludf.DUMMYFUNCTION("""COMPUTED_VALUE"""),"28 x 32") | AD44: =IFERROR(__xludf.DUMMYFUNCTION("""COMPUTED_VALUE"""),"28W / 32L")
A45: Cinturón | B45: Cinturones | C45: Accesorios | G45: REFLO ALMACEN | H45: NetSuite | I45: =IF(OR($G45="",$H45="Rack físico"),"",COUNTIFS('Stock por Ubicación'!$A:$A,IF($H45="NetSuite",$G45,$G45&" ›*"),'Stock por Ubicación'!$G:$G,"<>0")) | J45: =IF(OR($G45="",$H45="Rack físico"),"",SUMIFS('Stock por Ubicación'!$G:$G,'Stock por Ubicación'!$A:$A,IF($H45="NetSuite",$G45,$G45&" ›*"))) | AC45: =IFERROR(__xludf.DUMMYFUNCTION("""COMPUTED_VALUE"""),"29 x 32") | AD45: =IFERROR(__xludf.DUMMYFUNCTION("""COMPUTED_VALUE"""),"29W / 32L")
A46: Cobija | B46: Cobijas | C46: Accesorios | G46: STETSON AMERICAS | H46: NetSuite | I46: =IF(OR($G46="",$H46="Rack físico"),"",COUNTIFS('Stock por Ubicación'!$A:$A,IF($H46="NetSuite",$G46,$G46&" ›*"),'Stock por Ubicación'!$G:$G,"<>0")) | J46: =IF(OR($G46="",$H46="Rack físico"),"",SUMIFS('Stock por Ubicación'!$G:$G,'Stock por Ubicación'!$A:$A,IF($H46="NetSuite",$G46,$G46&" ›*"))) | AC46: =IFERROR(__xludf.DUMMYFUNCTION("""COMPUTED_VALUE"""),"30 x 32") | AD46: =IFERROR(__xludf.DUMMYFUNCTION("""COMPUTED_VALUE"""),"30W / 32L")
A47: Cuchillo | B47: Cuchillos | C47: Accesorios | G47: The Hat Club | H47: NetSuite | I47: =IF(OR($G47="",$H47="Rack físico"),"",COUNTIFS('Stock por Ubicación'!$A:$A,IF($H47="NetSuite",$G47,$G47&" ›*"),'Stock por Ubicación'!$G:$G,"<>0")) | J47: =IF(OR($G47="",$H47="Rack físico"),"",SUMIFS('Stock por Ubicación'!$G:$G,'Stock por Ubicación'!$A:$A,IF($H47="NetSuite",$G47,$G47&" ›*"))) | AC47: =IFERROR(__xludf.DUMMYFUNCTION("""COMPUTED_VALUE"""),"31 x 32") | AD47: =IFERROR(__xludf.DUMMYFUNCTION("""COMPUTED_VALUE"""),"31W / 32L")
A48: Equipaje | B48: Equipaje | C48: Accesorios | G48: VENTAS CAMPAÑA | H48: NetSuite | I48: =IF(OR($G48="",$H48="Rack físico"),"",COUNTIFS('Stock por Ubicación'!$A:$A,IF($H48="NetSuite",$G48,$G48&" ›*"),'Stock por Ubicación'!$G:$G,"<>0")) | J48: =IF(OR($G48="",$H48="Rack físico"),"",SUMIFS('Stock por Ubicación'!$G:$G,'Stock por Ubicación'!$A:$A,IF($H48="NetSuite",$G48,$G48&" ›*"))) | AC48: =IFERROR(__xludf.DUMMYFUNCTION("""COMPUTED_VALUE"""),"32 x 32") | AD48: =IFERROR(__xludf.DUMMYFUNCTION("""COMPUTED_VALUE"""),"32W / 32L")
A49: Estuche | B49: Estuches | C49: Accesorios | G49: WB FORUM TLAQUEPAQUE | H49: NetSuite | I49: =IF(OR($G49="",$H49="Rack físico"),"",COUNTIFS('Stock por Ubicación'!$A:$A,IF($H49="NetSuite",$G49,$G49&" ›*"),'Stock por Ubicación'!$G:$G,"<>0")) | J49: =IF(OR($G49="",$H49="Rack físico"),"",SUMIFS('Stock por Ubicación'!$G:$G,'Stock por Ubicación'!$A:$A,IF($H49="NetSuite",$G49,$G49&" ›*"))) | AC49: =IFERROR(__xludf.DUMMYFUNCTION("""COMPUTED_VALUE"""),"33 x 32") | AD49: =IFERROR(__xludf.DUMMYFUNCTION("""COMPUTED_VALUE"""),"33W / 32L")
A50: Fragancia | B50: Fragancias | C50: Accesorios | G50: WB OUTLET LERMA | H50: NetSuite | I50: =IF(OR($G50="",$H50="Rack físico"),"",COUNTIFS('Stock por Ubicación'!$A:$A,IF($H50="NetSuite",$G50,$G50&" ›*"),'Stock por Ubicación'!$G:$G,"<>0")) | J50: =IF(OR($G50="",$H50="Rack físico"),"",SUMIFS('Stock por Ubicación'!$G:$G,'Stock por Ubicación'!$A:$A,IF($H50="NetSuite",$G50,$G50&" ›*"))) | AC50: =IFERROR(__xludf.DUMMYFUNCTION("""COMPUTED_VALUE"""),"34 x 32") | AD50: =IFERROR(__xludf.DUMMYFUNCTION("""COMPUTED_VALUE"""),"34W / 32L")
A51: Hebilla | B51: Hebillas | C51: Accesorios | G51: Web | H51: NetSuite | I51: =IF(OR($G51="",$H51="Rack físico"),"",COUNTIFS('Stock por Ubicación'!$A:$A,IF($H51="NetSuite",$G51,$G51&" ›*"),'Stock por Ubicación'!$G:$G,"<>0")) | J51: =IF(OR($G51="",$H51="Rack físico"),"",SUMIFS('Stock por Ubicación'!$G:$G,'Stock por Ubicación'!$A:$A,IF($H51="NetSuite",$G51,$G51&" ›*"))) | AC51: =IFERROR(__xludf.DUMMYFUNCTION("""COMPUTED_VALUE"""),"35 x 32") | AD51: =IFERROR(__xludf.DUMMYFUNCTION("""COMPUTED_VALUE"""),"35W / 32L")
A52: Joyería | B52: Joyeria | C52: Accesorios | G52: WEB | H52: NetSuite | I52: =IF(OR($G52="",$H52="Rack físico"),"",COUNTIFS('Stock por Ubicación'!$A:$A,IF($H52="NetSuite",$G52,$G52&" ›*"),'Stock por Ubicación'!$G:$G,"<>0")) | J52: =IF(OR($G52="",$H52="Rack físico"),"",SUMIFS('Stock por Ubicación'!$G:$G,'Stock por Ubicación'!$A:$A,IF($H52="NetSuite",$G52,$G52&" ›*"))) | AC52: =IFERROR(__xludf.DUMMYFUNCTION("""COMPUTED_VALUE"""),"36 x 32") | AD52: =IFERROR(__xludf.DUMMYFUNCTION("""COMPUTED_VALUE"""),"36W / 32L")
A53: Llavero | B53: Llaveros | C53: Accesorios | G53: ZONA NORTE | H53: NetSuite | I53: =IF(OR($G53="",$H53="Rack físico"),"",COUNTIFS('Stock por Ubicación'!$A:$A,IF($H53="NetSuite",$G53,$G53&" ›*"),'Stock por Ubicación'!$G:$G,"<>0")) | J53: =IF(OR($G53="",$H53="Rack físico"),"",SUMIFS('Stock por Ubicación'!$G:$G,'Stock por Ubicación'!$A:$A,IF($H53="NetSuite",$G53,$G53&" ›*"))) | AC53: =IFERROR(__xludf.DUMMYFUNCTION("""COMPUTED_VALUE"""),"38 x 32") | AD53: =IFERROR(__xludf.DUMMYFUNCTION("""COMPUTED_VALUE"""),"38W / 32L")
A54: Libro | B54: Libros | C54: Accesorios | G54: ZONA POS | H54: NetSuite | I54: =IF(OR($G54="",$H54="Rack físico"),"",COUNTIFS('Stock por Ubicación'!$A:$A,IF($H54="NetSuite",$G54,$G54&" ›*"),'Stock por Ubicación'!$G:$G,"<>0")) | J54: =IF(OR($G54="",$H54="Rack físico"),"",SUMIFS('Stock por Ubicación'!$G:$G,'Stock por Ubicación'!$A:$A,IF($H54="NetSuite",$G54,$G54&" ›*"))) | AC54: =IFERROR(__xludf.DUMMYFUNCTION("""COMPUTED_VALUE"""),"40 x 32") | AD54: =IFERROR(__xludf.DUMMYFUNCTION("""COMPUTED_VALUE"""),"40W / 32L")
A55: Mochila | B55: Mochilas | C55: Accesorios | G55: ZONA SUR | H55: NetSuite | I55: =IF(OR($G55="",$H55="Rack físico"),"",COUNTIFS('Stock por Ubicación'!$A:$A,IF($H55="NetSuite",$G55,$G55&" ›*"),'Stock por Ubicación'!$G:$G,"<>0")) | J55: =IF(OR($G55="",$H55="Rack físico"),"",SUMIFS('Stock por Ubicación'!$G:$G,'Stock por Ubicación'!$A:$A,IF($H55="NetSuite",$G55,$G55&" ›*"))) | AC55: =IFERROR(__xludf.DUMMYFUNCTION("""COMPUTED_VALUE"""),"42 x 32") | AD55: =IFERROR(__xludf.DUMMYFUNCTION("""COMPUTED_VALUE"""),"42W / 32L")
A56: Mascota | B56: Mascotas | C56: Accesorios | G56: Shopify Stetson México | H56: Shopify | I56: =IF(OR($G56="",$H56="Rack físico"),"",COUNTIFS('Stock por Ubicación'!$A:$A,IF($H56="NetSuite",$G56,$G56&" ›*"),'Stock por Ubicación'!$G:$G,"<>0")) | J56: =IF(OR($G56="",$H56="Rack físico"),"",SUMIFS('Stock por Ubicación'!$G:$G,'Stock por Ubicación'!$A:$A,IF($H56="NetSuite",$G56,$G56&" ›*"))) | AC56: =IFERROR(__xludf.DUMMYFUNCTION("""COMPUTED_VALUE"""),"44 x 32") | AD56: =IFERROR(__xludf.DUMMYFUNCTION("""COMPUTED_VALUE"""),"44W / 32L")
A57: Jean | B57: Jeans | C57: Denim | G57: Shopify Western Brothers | H57: Shopify | I57: =IF(OR($G57="",$H57="Rack físico"),"",COUNTIFS('Stock por Ubicación'!$A:$A,IF($H57="NetSuite",$G57,$G57&" ›*"),'Stock por Ubicación'!$G:$G,"<>0")) | J57: =IF(OR($G57="",$H57="Rack físico"),"",SUMIFS('Stock por Ubicación'!$G:$G,'Stock por Ubicación'!$A:$A,IF($H57="NetSuite",$G57,$G57&" ›*"))) | AC57: =IFERROR(__xludf.DUMMYFUNCTION("""COMPUTED_VALUE"""),"46 x 32") | AD57: =IFERROR(__xludf.DUMMYFUNCTION("""COMPUTED_VALUE"""),"46W / 32L")
A58: Bota | B58: Botas | C58: Calzado | G58: Odoo Universal Unique Brands | H58: Odoo | I58: =IF(OR($G58="",$H58="Rack físico"),"",COUNTIFS('Stock por Ubicación'!$A:$A,IF($H58="NetSuite",$G58,$G58&" ›*"),'Stock por Ubicación'!$G:$G,"<>0")) | J58: =IF(OR($G58="",$H58="Rack físico"),"",SUMIFS('Stock por Ubicación'!$G:$G,'Stock por Ubicación'!$A:$A,IF($H58="NetSuite",$G58,$G58&" ›*"))) | AC58: =IFERROR(__xludf.DUMMYFUNCTION("""COMPUTED_VALUE"""),"48 x 32") | AD58: =IFERROR(__xludf.DUMMYFUNCTION("""COMPUTED_VALUE"""),"48W / 32L")
A59: Zapato | B59: Zapatos | C59: Calzado | G59: J1-L1-02 | H59: Rack físico | K59: Bodega 25 | AC59: =IFERROR(__xludf.DUMMYFUNCTION("""COMPUTED_VALUE"""),"50 x 32") | AD59: =IFERROR(__xludf.DUMMYFUNCTION("""COMPUTED_VALUE"""),"50W / 32L")
A60: Tenis | B60: Tenis | C60: Calzado | G60: I1-L1-01 | H60: Rack físico | K60: Bodega 25 | AC60: =IFERROR(__xludf.DUMMYFUNCTION("""COMPUTED_VALUE"""),"28 x 34") | AD60: =IFERROR(__xludf.DUMMYFUNCTION("""COMPUTED_VALUE"""),"28W / 34L")
A61: Pantufla | B61: Pantuflas | C61: Calzado | G61: I1-L1-02 | H61: Rack físico | K61: Bodega 25 | AC61: =IFERROR(__xludf.DUMMYFUNCTION("""COMPUTED_VALUE"""),"29 x 34") | AD61: =IFERROR(__xludf.DUMMYFUNCTION("""COMPUTED_VALUE"""),"29W / 34L")
A62: Calcet | B62: Calcetines | C62: Ropa | G62: I1-L2-01 | H62: Rack físico | K62: Bodega 25 | AC62: =IFERROR(__xludf.DUMMYFUNCTION("""COMPUTED_VALUE"""),"30 x 34") | AD62: =IFERROR(__xludf.DUMMYFUNCTION("""COMPUTED_VALUE"""),"30W / 34L")
A63: Camisa | B63: Camisas | C63: Ropa | G63: I1-L2-02 | H63: Rack físico | K63: Bodega 25 | AC63: =IFERROR(__xludf.DUMMYFUNCTION("""COMPUTED_VALUE"""),"31 x 34") | AD63: =IFERROR(__xludf.DUMMYFUNCTION("""COMPUTED_VALUE"""),"31W / 34L")
A64: Sobrecamisa | B64: Camisas | C64: Ropa | G64: J1-L2-01 | H64: Rack físico | K64: Bodega 25 | AC64: =IFERROR(__xludf.DUMMYFUNCTION("""COMPUTED_VALUE"""),"32 x 34") | AD64: =IFERROR(__xludf.DUMMYFUNCTION("""COMPUTED_VALUE"""),"32W / 34L")
A65: Chaleco | B65: Chalecos | C65: Ropa | G65: J1-L2-02 | H65: Rack físico | K65: Bodega 25 | AC65: =IFERROR(__xludf.DUMMYFUNCTION("""COMPUTED_VALUE"""),"33 x 34") | AD65: =IFERROR(__xludf.DUMMYFUNCTION("""COMPUTED_VALUE"""),"33W / 34L")
A66: Chamarra | B66: Chamarras | C66: Ropa | AC66: =IFERROR(__xludf.DUMMYFUNCTION("""COMPUTED_VALUE"""),"34 x 34") | AD66: =IFERROR(__xludf.DUMMYFUNCTION("""COMPUTED_VALUE"""),"34W / 34L")
A67: Falda | B67: Faldas | C67: Ropa | AC67: =IFERROR(__xludf.DUMMYFUNCTION("""COMPUTED_VALUE"""),"35 x 34") | AD67: =IFERROR(__xludf.DUMMYFUNCTION("""COMPUTED_VALUE"""),"35W / 34L")
A68: Jumpsuit | B68: Jumpsuits | C68: Ropa | AC68: =IFERROR(__xludf.DUMMYFUNCTION("""COMPUTED_VALUE"""),"36 x 34") | AD68: =IFERROR(__xludf.DUMMYFUNCTION("""COMPUTED_VALUE"""),"36W / 34L")
A69: Pantalón | B69: Pantalones | C69: Ropa | AC69: =IFERROR(__xludf.DUMMYFUNCTION("""COMPUTED_VALUE"""),"38 x 34") | AD69: =IFERROR(__xludf.DUMMYFUNCTION("""COMPUTED_VALUE"""),"38W / 34L")
A70: Pijama | B70: Pijamas | C70: Ropa | AC70: =IFERROR(__xludf.DUMMYFUNCTION("""COMPUTED_VALUE"""),"40 x 34") | AD70: =IFERROR(__xludf.DUMMYFUNCTION("""COMPUTED_VALUE"""),"40W / 34L")
A71: Playera | B71: Playeras | C71: Ropa | AC71: =IFERROR(__xludf.DUMMYFUNCTION("""COMPUTED_VALUE"""),"42 x 34") | AD71: =IFERROR(__xludf.DUMMYFUNCTION("""COMPUTED_VALUE"""),"42W / 34L")
A72: Short | B72: Shorts | C72: Ropa | AC72: =IFERROR(__xludf.DUMMYFUNCTION("""COMPUTED_VALUE"""),"44 x 34") | AD72: =IFERROR(__xludf.DUMMYFUNCTION("""COMPUTED_VALUE"""),"44W / 34L")
A73: Sudadera | B73: Sudaderas | C73: Ropa | AC73: =IFERROR(__xludf.DUMMYFUNCTION("""COMPUTED_VALUE"""),"46 x 34") | AD73: =IFERROR(__xludf.DUMMYFUNCTION("""COMPUTED_VALUE"""),"46W / 34L")
A74: Suéter | B74: Sueteres | C74: Ropa | AC74: =IFERROR(__xludf.DUMMYFUNCTION("""COMPUTED_VALUE"""),"48 x 34") | AD74: =IFERROR(__xludf.DUMMYFUNCTION("""COMPUTED_VALUE"""),"48W / 34L")
A75: Sueter | B75: Sueteres | C75: Ropa | AC75: =IFERROR(__xludf.DUMMYFUNCTION("""COMPUTED_VALUE"""),"50 x 34") | AD75: =IFERROR(__xludf.DUMMYFUNCTION("""COMPUTED_VALUE"""),"50W / 34L")
A76: Vestido | B76: Vestidos | C76: Ropa | AC76: =IFERROR(__xludf.DUMMYFUNCTION("""COMPUTED_VALUE"""),"29 x 36") | AD76: =IFERROR(__xludf.DUMMYFUNCTION("""COMPUTED_VALUE"""),"29W / 36L")
AC77: =IFERROR(__xludf.DUMMYFUNCTION("""COMPUTED_VALUE"""),"30 x 36") | AD77: =IFERROR(__xludf.DUMMYFUNCTION("""COMPUTED_VALUE"""),"30W / 36L")
A78: 3. CATEGORÍAS — DIVISIÓN Y FAMILIA DE TALLA | E78: ↑ Volver al índice | AC78: =IFERROR(__xludf.DUMMYFUNCTION("""COMPUTED_VALUE"""),"31 x 36") | AD78: =IFERROR(__xludf.DUMMYFUNCTION("""COMPUTED_VALUE"""),"31W / 36L")
A79: Cualquier artículo de Niño/Niña usa la familia Talla Niño, sin importar la categoría. Esta lista alimenta el desplegable WB Categoría. | AC79: =IFERROR(__xludf.DUMMYFUNCTION("""COMPUTED_VALUE"""),"32 x 36") | AD79: =IFERROR(__xludf.DUMMYFUNCTION("""COMPUTED_VALUE"""),"32W / 36L")
A80: Categoría | B80: División | C80: Familia de talla (ver sección 8) | AC80: =IFERROR(__xludf.DUMMYFUNCTION("""COMPUTED_VALUE"""),"33 x 36") | AD80: =IFERROR(__xludf.DUMMYFUNCTION("""COMPUTED_VALUE"""),"33W / 36L")
A81: Bandanas | B81: Accesorios | C81: Talla única | AC81: =IFERROR(__xludf.DUMMYFUNCTION("""COMPUTED_VALUE"""),"34 x 36") | AD81: =IFERROR(__xludf.DUMMYFUNCTION("""COMPUTED_VALUE"""),"34W / 36L")
A82: Bolsos | B82: Accesorios | C82: Talla única | AC82: =IFERROR(__xludf.DUMMYFUNCTION("""COMPUTED_VALUE"""),"35 x 36") | AD82: =IFERROR(__xludf.DUMMYFUNCTION("""COMPUTED_VALUE"""),"35W / 36L")
A83: Botas | B83: Calzado | C83: Talla Calzado MX | AC83: =IFERROR(__xludf.DUMMYFUNCTION("""COMPUTED_VALUE"""),"36 x 36") | AD83: =IFERROR(__xludf.DUMMYFUNCTION("""COMPUTED_VALUE"""),"36W / 36L")
A84: Bufandas | B84: Accesorios | C84: Talla única | AC84: =IFERROR(__xludf.DUMMYFUNCTION("""COMPUTED_VALUE"""),"38 x 36") | AD84: =IFERROR(__xludf.DUMMYFUNCTION("""COMPUTED_VALUE"""),"38W / 36L")
A85: Calcetines | B85: Ropa | C85: Talla Calcetín | AC85: =IFERROR(__xludf.DUMMYFUNCTION("""COMPUTED_VALUE"""),"40 x 36") | AD85: =IFERROR(__xludf.DUMMYFUNCTION("""COMPUTED_VALUE"""),"40W / 36L")
A86: Camisas | B86: Ropa | C86: Talla Ropa | AC86: =IFERROR(__xludf.DUMMYFUNCTION("""COMPUTED_VALUE"""),"42 x 36") | AD86: =IFERROR(__xludf.DUMMYFUNCTION("""COMPUTED_VALUE"""),"42W / 36L")
A87: Carteras | B87: Accesorios | C87: Talla única | AC87: =IFERROR(__xludf.DUMMYFUNCTION("""COMPUTED_VALUE"""),"44 x 36") | AD87: =IFERROR(__xludf.DUMMYFUNCTION("""COMPUTED_VALUE"""),"44W / 36L")
A88: Chalecos | B88: Ropa | C88: Talla Ropa | AC88: =IFERROR(__xludf.DUMMYFUNCTION("""COMPUTED_VALUE"""),"30 x 38") | AD88: =IFERROR(__xludf.DUMMYFUNCTION("""COMPUTED_VALUE"""),"30W / 38L")
A89: Chamarras | B89: Ropa | C89: Talla Ropa | AC89: =IFERROR(__xludf.DUMMYFUNCTION("""COMPUTED_VALUE"""),"31 x 38") | AD89: =IFERROR(__xludf.DUMMYFUNCTION("""COMPUTED_VALUE"""),"31W / 38L")
A90: Cinturones | B90: Accesorios | C90: Talla Cinturón | AC90: =IFERROR(__xludf.DUMMYFUNCTION("""COMPUTED_VALUE"""),"32 x 38") | AD90: =IFERROR(__xludf.DUMMYFUNCTION("""COMPUTED_VALUE"""),"32W / 38L")
A91: Cobijas | B91: Accesorios | C91: Talla única | AC91: =IFERROR(__xludf.DUMMYFUNCTION("""COMPUTED_VALUE"""),"33 x 38") | AD91: =IFERROR(__xludf.DUMMYFUNCTION("""COMPUTED_VALUE"""),"33W / 38L")
A92: Cuchillos | B92: Accesorios | C92: Talla única | AC92: =IFERROR(__xludf.DUMMYFUNCTION("""COMPUTED_VALUE"""),"34 x 38") | AD92: =IFERROR(__xludf.DUMMYFUNCTION("""COMPUTED_VALUE"""),"34W / 38L")
A93: Cuidado de Botas | B93: Accesorios | C93: Contenido / Talla única | AC93: =IFERROR(__xludf.DUMMYFUNCTION("""COMPUTED_VALUE"""),"35 x 38") | AD93: =IFERROR(__xludf.DUMMYFUNCTION("""COMPUTED_VALUE"""),"35W / 38L")
A94: Cuidado de Sombreros | B94: Accesorios | C94: Contenido / Talla Ropa / Talla única | AC94: =IFERROR(__xludf.DUMMYFUNCTION("""COMPUTED_VALUE"""),"36 x 38") | AD94: =IFERROR(__xludf.DUMMYFUNCTION("""COMPUTED_VALUE"""),"36W / 38L")
A95: Equipaje | B95: Accesorios | C95: Talla única | AC95: =IFERROR(__xludf.DUMMYFUNCTION("""COMPUTED_VALUE"""),"38 x 38") | AD95: =IFERROR(__xludf.DUMMYFUNCTION("""COMPUTED_VALUE"""),"38W / 38L")
A96: Estuches | B96: Accesorios | C96: Talla única | AC96: =IFERROR(__xludf.DUMMYFUNCTION("""COMPUTED_VALUE"""),"40 x 38") | AD96: =IFERROR(__xludf.DUMMYFUNCTION("""COMPUTED_VALUE"""),"40W / 38L")
A97: Faldas | B97: Ropa | C97: Talla Ropa | AC97: =IFERROR(__xludf.DUMMYFUNCTION("""COMPUTED_VALUE"""),"42 x 38") | AD97: =IFERROR(__xludf.DUMMYFUNCTION("""COMPUTED_VALUE"""),"42W / 38L")
A98: Fragancias | B98: Accesorios | C98: Contenido | AC98: =IFERROR(__xludf.DUMMYFUNCTION("""COMPUTED_VALUE"""),"44 x 38") | AD98: =IFERROR(__xludf.DUMMYFUNCTION("""COMPUTED_VALUE"""),"44W / 38L")
A99: Gorras | B99: Accesorios | C99: Talla única | AC99: =IFERROR(__xludf.DUMMYFUNCTION("""COMPUTED_VALUE"""),3.0) | AD99: =IFERROR(__xludf.DUMMYFUNCTION("""COMPUTED_VALUE"""),"0 Long")
A100: Hebillas | B100: Accesorios | C100: Talla única | AC100: =IFERROR(__xludf.DUMMYFUNCTION("""COMPUTED_VALUE"""),5.0) | AD100: =IFERROR(__xludf.DUMMYFUNCTION("""COMPUTED_VALUE"""),"2 Long")
...

Sheet Revisión Duplicados
A1: Grupo | B1: Fuente | C1: Motivo | D1: Código de barras | E1: Identificador interno | F1: Marca principal | G1: WB N.º de estilo | H1: WB SKU | I1: WB Talla | J1: WB Talla de EE. UU. | K1: WB Marca | L1: WB Descripcion | M1: WB División | N1: WB Categoría | O1: WB Género | P1: WB Licencia | Q1: WB Temporada | R1: WB Ciclo de vida | S1: WB Color | T1: WB Fit | U1: WB Silueta | V1: WB Composición | W1: WB Descripción larga | X1: WB País de origen | Y1: Unidad | Z1: SAT Clave de producto | AA1: Enlace de imagen | AB1: Precio de compra | AC1: Precio de venta | AD1: Estatus de Validación | AE1: Detalle de Discrepancias | AF1: 🔍 Panel de Duplicados | AG1: Stock Sistema NetSuite | AH1: Ubicaciones con stock (NetSuite) | AI1: Disponible NetSuite | AJ1: Origen del registro | AK1: Notas de enriquecimiento / revisión | AL1: ¿Alguna ubicación en negativo? | AM1: Ubicaciones con existencia negativa | AN1: Fuentes de consulta | AO1: Precio compra vigente | AP1: Precio venta vigente | AQ1: 📍 Ubicación en plataformas (Plataforma + Marca) | AR1: Stock Shopify Stetson México | AS1: Stock Shopify Western Brothers | AT1: Stock Odoo Universal Unique Brands | AU1: Ubicaciones con stock (plataformas)

Sheet Stock por Ubicación
A1: Ubicación (NetSuite / Plataforma) | B1: Código de barras | C1: WB SKU | D1: Identificador interno | E1: WB Marca | F1: WB Descripción | G1: Stock en ubicación (Físico) | H1: Origen en Productos | I1: Fila en Productos | J1: Sistema
A2: B25 CEDIS | B2: =IF($I2="","",INDEX(Productos!$A:$A,$I2)) | C2: YW11 | D2: =IF($I2="","",INDEX(Productos!$B:$B,$I2)) | E2: =IF($I2="","",INDEX(Productos!$H:$H,$I2)) | F2: =IF($I2="","",INDEX(Productos!$I:$I,$I2)) | G2: 19 | H2: =IF($I2="","",INDEX(Productos!$AG:$AG,$I2)) | I2: =LET(_xlpm.r,Productos!$E$2:$E$12,_xlpm.m,IFERROR(_xlfn.XMATCH(C2,_xlpm.r),IFERROR(_xlfn.XMATCH(VALUE(C2),_xlpm.r),0)),IF(_xlpm.m=0,"",_xlpm.m+1)) | J2: NetSuite
A3: B25 CEDIS | B3: =IF($I2="","",INDEX(Productos!$A:$A,$I2)) | C3: YW32 | D3: =IF($I2="","",INDEX(Productos!$B:$B,$I2)) | E3: =IF($I2="","",INDEX(Productos!$H:$H,$I2)) | F3: =IF($I2="","",INDEX(Productos!$I:$I,$I2)) | G3: 33 | H3: =IF($I2="","",INDEX(Productos!$AG:$AG,$I2)) | I3: =LET(_xlpm.r,Productos!$E$2:$E$12,_xlpm.m,IFERROR(_xlfn.XMATCH(C3,_xlpm.r),IFERROR(_xlfn.XMATCH(VALUE(C3),_xlpm.r),0)),IF(_xlpm.m=0,"",_xlpm.m+1)) | J3: NetSuite
A4: B25 CEDIS | B4: =IF($I2="","",INDEX(Productos!$A:$A,$I2)) | C4: YW37 | D4: =IF($I2="","",INDEX(Productos!$B:$B,$I2)) | E4: =IF($I2="","",INDEX(Productos!$H:$H,$I2)) | F4: =IF($I2="","",INDEX(Productos!$I:$I,$I2)) | G4: 19 | H4: =IF($I2="","",INDEX(Productos!$AG:$AG,$I2)) | I4: =LET(_xlpm.r,Productos!$E$2:$E$12,_xlpm.m,IFERROR(_xlfn.XMATCH(C4,_xlpm.r),IFERROR(_xlfn.XMATCH(VALUE(C4),_xlpm.r),0)),IF(_xlpm.m=0,"",_xlpm.m+1)) | J4: NetSuite
A5: B25 CEDIS | B5: =IF($I2="","",INDEX(Productos!$A:$A,$I2)) | C5: YW44 | D5: =IF($I2="","",INDEX(Productos!$B:$B,$I2)) | E5: =IF($I2="","",INDEX(Productos!$H:$H,$I2)) | F5: =IF($I2="","",INDEX(Productos!$I:$I,$I2)) | G5: 31 | H5: =IF($I2="","",INDEX(Productos!$AG:$AG,$I2)) | I5: =LET(_xlpm.r,Productos!$E$2:$E$12,_xlpm.m,IFERROR(_xlfn.XMATCH(C5,_xlpm.r),IFERROR(_xlfn.XMATCH(VALUE(C5),_xlpm.r),0)),IF(_xlpm.m=0,"",_xlpm.m+1)) | J5: NetSuite
A6: B25 CEDIS | B6: =IF($I2="","",INDEX(Productos!$A:$A,$I2)) | C6: YW45 | D6: =IF($I2="","",INDEX(Productos!$B:$B,$I2)) | E6: =IF($I2="","",INDEX(Productos!$H:$H,$I2)) | F6: =IF($I2="","",INDEX(Productos!$I:$I,$I2)) | G6: 30 | H6: =IF($I2="","",INDEX(Productos!$AG:$AG,$I2)) | I6: =LET(_xlpm.r,Productos!$E$2:$E$12,_xlpm.m,IFERROR(_xlfn.XMATCH(C6,_xlpm.r),IFERROR(_xlfn.XMATCH(VALUE(C6),_xlpm.r),0)),IF(_xlpm.m=0,"",_xlpm.m+1)) | J6: NetSuite
A7: B25 CEDIS | B7: =IF($I2="","",INDEX(Productos!$A:$A,$I2)) | C7: YW46 | D7: =IF($I2="","",INDEX(Productos!$B:$B,$I2)) | E7: =IF($I2="","",INDEX(Productos!$H:$H,$I2)) | F7: =IF($I2="","",INDEX(Productos!$I:$I,$I2)) | G7: 4 | H7: =IF($I2="","",INDEX(Productos!$AG:$AG,$I2)) | I7: =LET(_xlpm.r,Productos!$E$2:$E$12,_xlpm.m,IFERROR(_xlfn.XMATCH(C7,_xlpm.r),IFERROR(_xlfn.XMATCH(VALUE(C7),_xlpm.r),0)),IF(_xlpm.m=0,"",_xlpm.m+1)) | J7: NetSuite
A8: B25 CEDIS | B8: =IF($I2="","",INDEX(Productos!$A:$A,$I2)) | C8: YW47 | D8: =IF($I2="","",INDEX(Productos!$B:$B,$I2)) | E8: =IF($I2="","",INDEX(Productos!$H:$H,$I2)) | F8: =IF($I2="","",INDEX(Productos!$I:$I,$I2)) | G8: 4 | H8: =IF($I2="","",INDEX(Productos!$AG:$AG,$I2)) | I8: =LET(_xlpm.r,Productos!$E$2:$E$12,_xlpm.m,IFERROR(_xlfn.XMATCH(C8,_xlpm.r),IFERROR(_xlfn.XMATCH(VALUE(C8),_xlpm.r),0)),IF(_xlpm.m=0,"",_xlpm.m+1)) | J8: NetSuite
A9: WB OUTLET LERMA | B9: =IF($I2="","",INDEX(Productos!$A:$A,$I2)) | C9: YW11 | D9: =IF($I2="","",INDEX(Productos!$B:$B,$I2)) | E9: =IF($I2="","",INDEX(Productos!$H:$H,$I2)) | F9: =IF($I2="","",INDEX(Productos!$I:$I,$I2)) | G9: 6 | H9: =IF($I2="","",INDEX(Productos!$AG:$AG,$I2)) | I9: =LET(_xlpm.r,Productos!$E$2:$E$12,_xlpm.m,IFERROR(_xlfn.XMATCH(C9,_xlpm.r),IFERROR(_xlfn.XMATCH(VALUE(C9),_xlpm.r),0)),IF(_xlpm.m=0,"",_xlpm.m+1)) | J9: NetSuite
A10: WB OUTLET LERMA | B10: =IF($I2="","",INDEX(Productos!$A:$A,$I2)) | C10: YW32 | D10: =IF($I2="","",INDEX(Productos!$B:$B,$I2)) | E10: =IF($I2="","",INDEX(Productos!$H:$H,$I2)) | F10: =IF($I2="","",INDEX(Productos!$I:$I,$I2)) | G10: 8 | H10: =IF($I2="","",INDEX(Productos!$AG:$AG,$I2)) | I10: =LET(_xlpm.r,Productos!$E$2:$E$12,_xlpm.m,IFERROR(_xlfn.XMATCH(C10,_xlpm.r),IFERROR(_xlfn.XMATCH(VALUE(C10),_xlpm.r),0)),IF(_xlpm.m=0,"",_xlpm.m+1)) | J10: NetSuite
A11: WB OUTLET LERMA | B11: =IF($I2="","",INDEX(Productos!$A:$A,$I2)) | C11: YW37 | D11: =IF($I2="","",INDEX(Productos!$B:$B,$I2)) | E11: =IF($I2="","",INDEX(Productos!$H:$H,$I2)) | F11: =IF($I2="","",INDEX(Productos!$I:$I,$I2)) | G11: 6 | H11: =IF($I2="","",INDEX(Productos!$AG:$AG,$I2)) | I11: =LET(_xlpm.r,Productos!$E$2:$E$12,_xlpm.m,IFERROR(_xlfn.XMATCH(C11,_xlpm.r),IFERROR(_xlfn.XMATCH(VALUE(C11),_xlpm.r),0)),IF(_xlpm.m=0,"",_xlpm.m+1)) | J11: NetSuite
A12: WB OUTLET LERMA | B12: =IF($I2="","",INDEX(Productos!$A:$A,$I2)) | C12: YW44 | D12: =IF($I2="","",INDEX(Productos!$B:$B,$I2)) | E12: =IF($I2="","",INDEX(Productos!$H:$H,$I2)) | F12: =IF($I2="","",INDEX(Productos!$I:$I,$I2)) | G12: 8 | H12: =IF($I2="","",INDEX(Productos!$AG:$AG,$I2)) | I12: =LET(_xlpm.r,Productos!$E$2:$E$12,_xlpm.m,IFERROR(_xlfn.XMATCH(C12,_xlpm.r),IFERROR(_xlfn.XMATCH(VALUE(C12),_xlpm.r),0)),IF(_xlpm.m=0,"",_xlpm.m+1)) | J12: NetSuite
A13: WB OUTLET LERMA | B13: =IF($I2="","",INDEX(Productos!$A:$A,$I2)) | C13: YW45 | D13: =IF($I2="","",INDEX(Productos!$B:$B,$I2)) | E13: =IF($I2="","",INDEX(Productos!$H:$H,$I2)) | F13: =IF($I2="","",INDEX(Productos!$I:$I,$I2)) | G13: 8 | H13: =IF($I2="","",INDEX(Productos!$AG:$AG,$I2)) | I13: =LET(_xlpm.r,Productos!$E$2:$E$12,_xlpm.m,IFERROR(_xlfn.XMATCH(C13,_xlpm.r),IFERROR(_xlfn.XMATCH(VALUE(C13),_xlpm.r),0)),IF(_xlpm.m=0,"",_xlpm.m+1)) | J13: NetSuite
A14: WB OUTLET LERMA | B14: =IF($I2="","",INDEX(Productos!$A:$A,$I2)) | C14: YW46 | D14: =IF($I2="","",INDEX(Productos!$B:$B,$I2)) | E14: =IF($I2="","",INDEX(Productos!$H:$H,$I2)) | F14: =IF($I2="","",INDEX(Productos!$I:$I,$I2)) | G14: 3 | H14: =IF($I2="","",INDEX(Productos!$AG:$AG,$I2)) | I14: =LET(_xlpm.r,Productos!$E$2:$E$12,_xlpm.m,IFERROR(_xlfn.XMATCH(C14,_xlpm.r),IFERROR(_xlfn.XMATCH(VALUE(C14),_xlpm.r),0)),IF(_xlpm.m=0,"",_xlpm.m+1)) | J14: NetSuite
A15: WB OUTLET LERMA | B15: =IF($I2="","",INDEX(Productos!$A:$A,$I2)) | C15: YW47 | D15: =IF($I2="","",INDEX(Productos!$B:$B,$I2)) | E15: =IF($I2="","",INDEX(Productos!$H:$H,$I2)) | F15: =IF($I2="","",INDEX(Productos!$I:$I,$I2)) | G15: 3 | H15: =IF($I2="","",INDEX(Productos!$AG:$AG,$I2)) | I15: =LET(_xlpm.r,Productos!$E$2:$E$12,_xlpm.m,IFERROR(_xlfn.XMATCH(C15,_xlpm.r),IFERROR(_xlfn.XMATCH(VALUE(C15),_xlpm.r),0)),IF(_xlpm.m=0,"",_xlpm.m+1)) | J15: NetSuite
A16: Odoo Universal Unique Brands › Bodega 25 › Bodega 25/General | B16: =IF($I2="","",INDEX(Productos!$A:$A,$I2)) | C16: 96234 | D16: =IF($I2="","",INDEX(Productos!$B:$B,$I2)) | E16: =IF($I2="","",INDEX(Productos!$H:$H,$I2)) | F16: =IF($I2="","",INDEX(Productos!$I:$I,$I2)) | G16: 1 | H16: =IF($I2="","",INDEX(Productos!$AG:$AG,$I2)) | I16: =LET(_xlpm.r,Productos!$E$2:$E$12,_xlpm.m,IFERROR(_xlfn.XMATCH(C16,_xlpm.r),IFERROR(_xlfn.XMATCH(VALUE(C16),_xlpm.r),0)),IF(_xlpm.m=0,"",_xlpm.m+1)) | J16: Odoo
A17: Odoo Universal Unique Brands › Bodega 25 › Bodega 25/General | B17: =IF($I2="","",INDEX(Productos!$A:$A,$I2)) | C17: 96235 | D17: =IF($I2="","",INDEX(Productos!$B:$B,$I2)) | E17: =IF($I2="","",INDEX(Productos!$H:$H,$I2)) | F17: =IF($I2="","",INDEX(Productos!$I:$I,$I2)) | G17: 1 | H17: =IF($I2="","",INDEX(Productos!$AG:$AG,$I2)) | I17: =LET(_xlpm.r,Productos!$E$2:$E$12,_xlpm.m,IFERROR(_xlfn.XMATCH(C17,_xlpm.r),IFERROR(_xlfn.XMATCH(VALUE(C17),_xlpm.r),0)),IF(_xlpm.m=0,"",_xlpm.m+1)) | J17: Odoo
A18: Odoo Universal Unique Brands › Bodega 25 › Bodega 25/General | B18: =IF($I2="","",INDEX(Productos!$A:$A,$I2)) | C18: 96645 | D18: =IF($I2="","",INDEX(Productos!$B:$B,$I2)) | E18: =IF($I2="","",INDEX(Productos!$H:$H,$I2)) | F18: =IF($I2="","",INDEX(Productos!$I:$I,$I2)) | G18: 1 | H18: =IF($I2="","",INDEX(Productos!$AG:$AG,$I2)) | I18: =LET(_xlpm.r,Productos!$E$2:$E$12,_xlpm.m,IFERROR(_xlfn.XMATCH(C18,_xlpm.r),IFERROR(_xlfn.XMATCH(VALUE(C18),_xlpm.r),0)),IF(_xlpm.m=0,"",_xlpm.m+1)) | J18: Odoo
A19: Odoo Universal Unique Brands › Bodega 25 › Bodega 25/Output | B19: =IF($I2="","",INDEX(Productos!$A:$A,$I2)) | C19: 95597 | D19: =IF($I2="","",INDEX(Productos!$B:$B,$I2)) | E19: =IF($I2="","",INDEX(Productos!$H:$H,$I2)) | F19: =IF($I2="","",INDEX(Productos!$I:$I,$I2)) | G19: 2 | H19: =IF($I2="","",INDEX(Productos!$AG:$AG,$I2)) | I19: =LET(_xlpm.r,Productos!$E$2:$E$12,_xlpm.m,IFERROR(_xlfn.XMATCH(C19,_xlpm.r),IFERROR(_xlfn.XMATCH(VALUE(C19),_xlpm.r),0)),IF(_xlpm.m=0,"",_xlpm.m+1)) | J19: Odoo
A20: Odoo Universal Unique Brands › Bodega 25 › Bodega 25/Output | B20: =IF($I2="","",INDEX(Productos!$A:$A,$I2)) | C20: 96234 | D20: =IF($I2="","",INDEX(Productos!$B:$B,$I2)) | E20: =IF($I2="","",INDEX(Productos!$H:$H,$I2)) | F20: =IF($I2="","",INDEX(Productos!$I:$I,$I2)) | G20: 2 | H20: =IF($I2="","",INDEX(Productos!$AG:$AG,$I2)) | I20: =LET(_xlpm.r,Productos!$E$2:$E$12,_xlpm.m,IFERROR(_xlfn.XMATCH(C20,_xlpm.r),IFERROR(_xlfn.XMATCH(VALUE(C20),_xlpm.r),0)),IF(_xlpm.m=0,"",_xlpm.m+1)) | J20: Odoo
A21: Odoo Universal Unique Brands › Bodega 25 › Bodega 25/Output | B21: =IF($I2="","",INDEX(Productos!$A:$A,$I2)) | C21: 96235 | D21: =IF($I2="","",INDEX(Productos!$B:$B,$I2)) | E21: =IF($I2="","",INDEX(Productos!$H:$H,$I2)) | F21: =IF($I2="","",INDEX(Productos!$I:$I,$I2)) | G21: 2 | H21: =IF($I2="","",INDEX(Productos!$AG:$AG,$I2)) | I21: =LET(_xlpm.r,Productos!$E$2:$E$12,_xlpm.m,IFERROR(_xlfn.XMATCH(C21,_xlpm.r),IFERROR(_xlfn.XMATCH(VALUE(C21),_xlpm.r),0)),IF(_xlpm.m=0,"",_xlpm.m+1)) | J21: Odoo
A22: Odoo Universal Unique Brands › Bodega 25 › Bodega 25/Output | B22: =IF($I2="","",INDEX(Productos!$A:$A,$I2)) | C22: 96645 | D22: =IF($I2="","",INDEX(Productos!$B:$B,$I2)) | E22: =IF($I2="","",INDEX(Productos!$H:$H,$I2)) | F22: =IF($I2="","",INDEX(Productos!$I:$I,$I2)) | G22: 1 | H22: =IF($I2="","",INDEX(Productos!$AG:$AG,$I2)) | I22: =LET(_xlpm.r,Productos!$E$2:$E$12,_xlpm.m,IFERROR(_xlfn.XMATCH(C22,_xlpm.r),IFERROR(_xlfn.XMATCH(VALUE(C22),_xlpm.r),0)),IF(_xlpm.m=0,"",_xlpm.m+1)) | J22: Odoo

Sheet Bodega 25
A1: Bodega 25 — Existencias en almacén
A2: Racks físicos y ubicaciones asignadas a Bodega 25 en Criterios › 9 (columna K), más cualquier ubicación con «B25» o «Bodega 25» en el nombre (NetSuite y Odoo). Racks físicos = piezas contadas en Escaneos. Solo piezas > 0.
A3: Bodega: | B3: Bodega 25 | D3: Piezas totales: | E3: =IF(ISNUMBER(I6),SUM(I6:I528),0) | F3: Renglones: | G3: =IF(ISNUMBER(I6),COUNT(I6:I528),0)
A5: Ubicación | B5: Sistema / Tipo | C5: UPC | D5: SKU | E5: Id_Interno | F5: Marca | G5: Descripción | H5: Talla | I5: Piezas en almacén
A6: =IFERROR(__xludf.DUMMYFUNCTION("ARRAYFORMULA(LET(bod,$B$3,cu,Criterios!$G$6:$G$200,ct,Criterios!$H$6:$H$200,cb,Criterios!$K$6:$K$200,asig,LAMBDA(u,LET(x,XLOOKUP(u,cu,cb,"""")&"""",IF(x<>"""",x,IF((ISNUMBER(SEARCH(""Bodega 25"",u))+ISNUMBER(SEARCH(""B25 "",u&"" "")))>0,""Bodega 25"",IF(I"&"SNUMBER(SEARCH(""G1522"",u)),""Bodega 43"",""""))))),pE,Productos!$E$2:$E$12,pA,Productos!$A$2:$A$12&"""",s,'Stock por Ubicación'!$A$2:$J$22,su,INDEX(s,0,1),sq,INDEX(s,0,7),sp,INDEX(s,0,9),selSis,(su<>"""")*ISNUMBER(sq)*(sq>0)*(asig(su)=bod)*ISNUMB"&"ER(sp)*(sp>=2)*(sp<=ROWS(pE)+1)*(INDEX(s,0,5)<>"""")>0,a,IFERROR(FILTER(CHOOSECOLS(s,1,10,2,3,4,5,6,7),selSis),""""),tu,Table_2[Ubicación / Rack],ts,Table_2[SKU]&"""",tupc,Table_2[UPC CODE]&"""",tp,Table_2[Piezas Contadas],canon_sku,IF(ISNUMBER(SEARCH(""-"&"2XL"",ts)),SUBSTITUTE(ts,""-2XL"",""-XXL""),IF(ISNUMBER(SEARCH(""-3XL"",ts)),SUBSTITUTE(ts,""-3XL"",""-XXXL""),IF(ts="""",XLOOKUP(tupc,pA,pE,""""),ts))),selRack,(tu<>"""")*(canon_sku<>"""")*((XLOOKUP(tu,cu,ct,"""")&"""")=""Rack físico"")*(asig(tu)=bod)*IS"&"NUMBER(XMATCH(canon_sku,pE))>0,pr,IFERROR(UNIQUE(FILTER(HSTACK(tu,canon_sku),selRack)),""""),b,IF(INDEX(pr,1,1)="""","""",LET(ru,INDEX(pr,0,1),sk,INDEX(pr,0,2),pz,MAP(ru,sk,LAMBDA(r_u,s_k,LET(sk_alt,SUBSTITUTE(s_k,""-XXL"",""-2XL""),sk_upc,XLOOKUP(s_k,pE,"&"pA,""""),SUMIFS(tp,tu,r_u,ts,s_k)+IF(sk_alt<>s_k,SUMIFS(tp,tu,r_u,ts,sk_alt),0)+IF(sk_upc<>"""",SUMIFS(tp,tu,r_u,tupc,sk_upc,ts,""""),0)))),rw,HSTACK(ru,IF(pz=pz,""Rack físico (escaneo)""),XLOOKUP(sk,pE,Productos!$A$2:$A$12,""""),sk,XLOOKUP(sk,pE,Produc"&"tos!$B$2:$B$2502,""""),XLOOKUP(sk,pE,Productos!$H$2:$H$12,""""),XLOOKUP(sk,pE,Productos!$I$2:$I$12,""""),pz),IFERROR(FILTER(rw,pz>0),""""))),todo,IF(INDEX(a,1,1)="""",b,IF(INDEX(b,1,1)="""",a,VSTACK(a,b))),IF(INDEX(todo,1,1)="""",""Sin existencias en "&"esta bodega"",LET(tl,XLOOKUP(INDEX(todo,0,4),pE,Productos!$F$2:$F$12,"""")&"""",o,HSTACK(CHOOSECOLS(todo,1,2,3,4,5,6,7),tl,CHOOSECOLS(todo,8)),x,SORT(o,1,TRUE,4,TRUE),IF(x="""","""",x)))))"),"B25 CEDIS")

Sheet Bodega 43
A1: Bodega 43 — Existencias en almacén
A2: Ubicaciones asignadas a Bodega 43 en Criterios › 9 (columna K), más cualquier ubicación con «G1522» en el nombre. Los racks físicos asignados a Bodega 43 aparecen aquí con sus piezas contadas en Escaneos. Solo piezas > 0.
A3: Bodega: | B3: Bodega 43 | D3: Piezas totales: | E3: =IF(ISNUMBER(I6),SUM(I6:I528),0) | F3: Renglones: | G3: =IF(ISNUMBER(I6),COUNT(I6:I528),0)
A5: Ubicación | B5: Sistema / Tipo | C5: UPC | D5: SKU | E5: Id_Interno | F5: Marca | G5: Descripción | H5: Talla | I5: Piezas en almacén
A6: =IFERROR(__xludf.DUMMYFUNCTION("ARRAYFORMULA(LET(bod,$B$3,cu,Criterios!$G$6:$G$200,ct,Criterios!$H$6:$H$200,cb,Criterios!$K$6:$K$200,asig,LAMBDA(u,LET(x,XLOOKUP(u,cu,cb,"""")&"""",IF(x<>"""",x,IF((ISNUMBER(SEARCH(""Bodega 25"",u))+ISNUMBER(SEARCH(""B25 "",u&"" "")))>0,""Bodega 25"",IF(I"&"SNUMBER(SEARCH(""G1522"",u)),""Bodega 43"",""""))))),pE,Productos!$E$2:$E$12,s,'Stock por Ubicación'!$A$2:$J$22,su,INDEX(s,0,1),sq,INDEX(s,0,7),selSis,(su<>"""")*ISNUMBER(sq)*(sq>0)*(asig(su)=bod)>0,a,IFERROR(FILTER(CHOOSECOLS(s,1,10,2,3,4,5,6,7),sel"&"Sis),""""),tu,Table_2[Ubicación / Rack],ts,Table_2[SKU],tp,Table_2[Piezas Contadas],selRack,(tu<>"""")*(ts<>"""")*((XLOOKUP(tu,cu,ct,"""")&"""")=""Rack físico"")*(asig(tu)=bod)*ISNUMBER(XMATCH(ts,pE))>0,pr,IFERROR(UNIQUE(FILTER(HSTACK(tu,ts),selRack)),"""&"""),b,IF(INDEX(pr,1,1)="""","""",LET(ru,INDEX(pr,0,1),sk,INDEX(pr,0,2),pz,MAP(ru,sk,LAMBDA(r_u,s_k,SUMIFS(tp,tu,r_u,ts,s_k))),rw,HSTACK(ru,IF(pz=pz,""Rack físico (escaneo)""),XLOOKUP(sk,pE,Productos!$A$2:$A$12,""""),sk,XLOOKUP(sk,pE,Productos!$B$2:$B$12"&"02,""""),XLOOKUP(sk,pE,Productos!$H$2:$H$12,""""),XLOOKUP(sk,pE,Productos!$I$2:$I$12,""""),pz),IFERROR(FILTER(rw,pz>0),""""))),todo,IF(INDEX(a,1,1)="""",b,IF(INDEX(b,1,1)="""",a,VSTACK(a,b))),IF(INDEX(todo,1,1)="""",""Sin existencias en esta bodega"","&"LET(sku_col,INDEX(todo,0,4)&"""",marca_col,INDEX(todo,0,6)&"""",marca_final,IF(marca_col<>"""",marca_col,IF(OR(LEFT(sku_col,3)=""100"",LEFT(sku_col,2)=""AR"",LEFT(sku_col,1)=""A""),""Ariat"",IF(OR(LEFT(sku_col,2)=""CL"",LEFT(sku_col,3)=""CAP""),""CAPSLAB"&""",IF(LEFT(sku_col,2)=""HS"",""Happy Socks"",IF(OR(LEFT(sku_col,3)=""11-"",LEFT(sku_col,3)=""12-"",LEFT(sku_col,3)=""ST-"",LEFT(sku_col,3)=""SF-""),""Stetson"",IF(OR(LEFT(sku_col,2)=""MW"",LEFT(sku_col,2)=""WG""),""Western Brothers"",IF(LEFT(sku_col,3)="""&"C47"",""Wrangler"",""Ariat""))))))),p_talla,XLOOKUP(sku_col,pE,Productos!$F$2:$F$12,"""")&"""",raw_talla,IFERROR(REGEXEXTRACT(sku_col,""[^-]+$""),""""),talla_final,IF(p_talla<>"""",p_talla,IF(raw_talla=""MEDR"",""M"",IF(raw_talla=""LGR"",""L"",IF(raw_ta"&"lla=""SMLR"",""S"",IF(raw_talla=""XLR"",""XL"",IF(raw_talla=""XSR"",""XS"",IF(raw_talla=""XXLR"",""XXL"",IF(raw_talla=""2XL"",""XXL"",IF(raw_talla=""3XL"",""XXXL"",IF(raw_talla=""SMLN"",""S"",raw_talla)))))))))),out_grid,HSTACK(CHOOSECOLS(todo,1,2,3,4,5),"&"marca_final,CHOOSECOLS(todo,7),talla_final,CHOOSECOLS(todo,8)),sorted_grid,SORT(out_grid,1,TRUE,4,TRUE),IF(sorted_grid="""","""",sorted_grid)))))"),"Almacenes G1522")

Sheet Resumen Integración
A1: Integración de plataformas → Productos (Catálogo Estándar)
A2: Generado 01/10/2026. Fuente: Catalogo_Estandar_Stetson_WB_Odoo_2026-10-01_v2.xlsx (Shopify Stetson México, Shopify Western Brothers, Odoo Universal Unique Brands). Destino: hoja Productos de HojaProductos_Prelimpieza.xlsx, con la estructura y listas de su hoja Criterios.
A4: Resultado por plataforma (variantes del archivo de plataformas)
A5: Plataforma | B5: Variantes en la fuente | C5: Coincidieron y complementaron un artículo existente | D5: Alta como artículo nuevo | E5: A hoja Duplicados (artículo distinto) | F5: No integradas (servicios / conceptos)
A6: Shopify Stetson México | B6: =SUM(C6:F6) | C6: 2412 | D6: 47 | E6: 4 | F6: 6
A7: Shopify Western Brothers | B7: =SUM(C7:F7) | C7: 2493 | D7: 18 | E7: 2 | F7: 1
A8: Odoo Universal Unique Brands | B8: =SUM(C8:F8) | C8: 1396 | D8: 360 | E8: 0 | F8: 15
A9: Total | B9: =SUM(B6:B8) | C9: =SUM(C6:C8) | D9: =SUM(D6:D8) | E9: =SUM(E6:E8) | F9: =SUM(F6:F8)
A11: Estado de la hoja Productos (se recalcula sola)
A12: Concepto | B12: Filas
A13: Filas en Productos | B13: =COUNTIF(Productos!AA:AA,"?*")
A14: Artículos con ubicación en alguna plataforma | B14: =COUNTA(Productos!AN:AN)-1
A15: … en Shopify Stetson México | B15: =COUNTIF(Productos!AN:AN,"*Shopify Stetson México*")
A16: … en Shopify Western Brothers | B16: =COUNTIF(Productos!AN:AN,"*Shopify Western Brothers*")
A17: … en Odoo Universal Unique Brands | B17: =COUNTIF(Productos!AN:AN,"*Odoo Universal Unique Brands*")
A18: Filas existentes complementadas con datos de plataformas | B18: =COUNTIF(Productos!AH:AH,"*complementado desde*")
A19: Filas nuevas dadas de alta desde plataformas | B19: =COUNTIF(Productos!AG:AG,"Nuevo – Shopify*")+COUNTIF(Productos!AG:AG,"Nuevo – Odoo*")
A20: Filas en la hoja Duplicados (Productos + plataforma) | B20: =COUNTA('Revisión Duplicados'!A:A)-1
A21: Artículos con código de barras mal asignado en la plataforma (corregir allá) | B21: =COUNTIF(Productos!AH:AH,"*corregir el código en*")
A23: Campos complementados en filas existentes (celdas vacías o con valor fuera de Criterios)
A24: Campo | B24: Shopify Stetson México | C24: Shopify Western Brothers | D24: Odoo Universal Unique Brands | E24: Total
A25: WB Silueta | B25: 1428 | C25: 1559 | D25: 18 | E25: =SUM(B25:D25)
A26: WB Fit | B26: 1652 | C26: 939 | D26: 25 | E26: =SUM(B26:D26)
A27: Enlace de imagen | B27: 234 | C27: 31 | D27: 231 | E27: =SUM(B27:D27)
A28: WB Talla de EE. UU. | B28: 0 | C28: 7 | D28: 321 | E28: =SUM(B28:D28)
A29: WB Talla | B29: 0 | C29: 0 | D29: 229 | E29: =SUM(B29:D29)
A30: WB Color | B30: 120 | C30: 29 | D30: 20 | E30: =SUM(B30:D30)
A31: WB Descripción larga | B31: 60 | C31: 7 | D31: 85 | E31: =SUM(B31:D31)
A32: WB Género | B32: 0 | C32: 0 | D32: 150 | E32: =SUM(B32:D32)
A33: WB Temporada | B33: 40 | C33: 0 | D33: 29 | E33: =SUM(B33:D33)
A34: WB Licencia | B34: 0 | C34: 0 | D34: 38 | E34: =SUM(B34:D34)
A35: WB N.º de estilo | B35: 0 | C35: 0 | D35: 35 | E35: =SUM(B35:D35)
A36: WB Ciclo de vida | B36: 0 | C36: 0 | D36: 25 | E36: =SUM(B36:D36)
... A42: Código de barras | B42: 0 | C42: 0 | D42: 1 | E42: =SUM(B42:D42)
A44: Reglas aplicadas
A45: • Búsqueda: primero por código de barras (ignorando ceros a la izquierda); si no coincide, por SKU. Si el nombre del artículo en la plataforma es un código (p. ej. «WG218-W068BK») y no trae SKU, se usa como SKU.
A46: • Si el código de barras de la plataforma apunta a otro artículo pero el SKU apunta al correcto, se usa el SKU y se anota en «Notas de enriquecimiento / revisión» que el código está mal en la plataforma (camisas Reflection Geo en Shopify Stetson, ya corregidas en Productos el 30/09).
A47: • Duplicados: sólo cuando el mismo código de barras o SKU corresponde a artículos completamente distintos (otra división, otra marca y categoría, u otro estilo con descripción sin relación). Se sacaron ambas filas —la de Productos y la de la plataforma— a la hoja Duplicados, agrupadas, para decidir cuál se queda.
A48: • Complemento: se llenan celdas vacías de Productos y se reemplazan valores fuera de Criterios (p. ej. Silueta «Manga larga» → «No Aplica»). Un valor válido de Productos nunca se sobrescribe; si la plataforma trae otro valor, se anota en «Notas de enriquecimiento / revisión».
A49: • Descripción y descripción larga: sólo se reemplazan si la de Productos es un marcador (p. ej. «WG BAG») o una línea corta y la plataforma trae una versión mucho más completa.
A50: • Tallas: «WB Talla de EE. UU.» sólo se completa si la «WB Talla» de Productos coincide con la de la plataforma, para no mezclar pares de tallas.
A51: • Precio de venta (sólo celdas vacías y filas nuevas): Shopify Stetson México ÷ 1.16, porque sus precios incluyen IVA (en 2,041 de 2,395 artículos comparables la relación con NetSuite es exactamente 1.16). Western Brothers y Odoo sin ajuste (relación 1.00 dominante).
A52: • Precio de compra: no se tomó de plataformas para artículos existentes (los costos de Odoo no son comparables con NetSuite: 188 de 708 difieren ~25×). En filas nuevas se conserva el costo que trae la plataforma.
A53: • Filas nuevas: valores validados contra Criterios (listas, catálogo de tallas, División según Categoría, Unidad PRS para calzado). Lo que no cuadra se deja vacío y se anota, como pide la Ruta de llenado (paso 10).
A54: • Ubicación: «Plataforma + Marca/tienda» en la columna AN; existencias por plataforma en AO–AQ y detalle por almacén en AR. Las tres ubicaciones se agregaron a Criterios › 9. Ubicaciones (tipo Shopify / Odoo, sin validación de stock NetSuite).
A55: • Estatus de Validación y Detalle de Discrepancias: misma fórmula de antes, ahora apuntando a la hoja Criterios de este archivo (antes apuntaba a Ciclico_1522_investigado.xlsx). «Precio compra/venta vigente» quedó como valor fijo (ver nota en AL1).
A57: Variantes no integradas (servicios / conceptos no inventariables)
A58: Plataforma | B58: Código de barras | C58: SKU | D58: Descripción | E58: Motivo
A59: Shopify Stetson México | B59: 100001 | C59: 100001 | D59: Servicio Hat Doctor | E59: Servicio / concepto no inventariable
A60: Shopify Stetson México | B60: 100001 | C60: 100001 | D60: Servicio Hat Doctor | E60: Servicio / concepto no inventariable
A61: Shopify Stetson México | B61: 100001 | C61: 100001 | D61: Servicio Hat Doctor | E61: Servicio / concepto no inventariable
A62: Shopify Stetson México | B62: 100001 | C62: 100001 | D62: Servicio Hat Doctor | E62: Servicio / concepto no inventariable
A63: Shopify Stetson México | B63: 999999 | C63: ENVIO | D63: Servicio de envio asegurado | E63: Servicio / concepto no inventariable
A64: Shopify Stetson México | B64: 999999 | C64: ENVIO | D64: Servicio de envio asegurado | E64: Servicio / concepto no inventariable
A65: Shopify Western Brothers | B65: 100001 | C65: 100001 | D65: Servicio Hat Doctor | E65: Servicio / concepto no inventariable
A66: Odoo Universal Unique Brands | D66: Tarifas de reservación | E66: Servicio / concepto no inventariable
A67: Odoo Universal Unique Brands | D67: Envío | E67: Servicio / concepto no inventariable
A68: Odoo Universal Unique Brands | D68: Descuento | E68: Servicio / concepto no inventariable
A69: Odoo Universal Unique Brands | D69: Embalaje | E69: Servicio / concepto no inventariable
A70: Odoo Universal Unique Brands | D70: Envío ecommerce | E70: Servicio / concepto no inventariable
A71: Odoo Universal Unique Brands | D71: Envío Pagado x Nosotros | E71: Servicio / concepto no inventariable
A72: Odoo Universal Unique Brands | D72: Envío Pagado x Cliente | E72: Servicio / concepto no inventariable
A73: Odoo Universal Unique Brands | D73: Envía | E73: Servicio / concepto no inventariable
A74: Odoo Universal Unique Brands | C74: TIPS | D74: Propinas | E74: Servicio / concepto no inventariable
A75: Odoo Universal Unique Brands | D75: Anticipo (PdV) | E75: Servicio / concepto no inventariable
A76: Odoo Universal Unique Brands | D76: Pagar el adeudo | E76: Servicio / concepto no inventariable
A77: Odoo Universal Unique Brands | D77: Depósito | E77: Servicio / concepto no inventariable
A78: Odoo Universal Unique Brands | D78: Liquidar factura | E78: Servicio / concepto no inventariable
A79: Odoo Universal Unique Brands | D79: GESTION DE EVENTOS | E79: Servicio / concepto no inventariable
A80: Odoo Universal Unique Brands | D80: DEVOLUCIONES Y DESCUENTOS | E80: Servicio / concepto no inventariable

Sheet Inventario
A1: Código de barras | B1: Identificador interno | C1: WB SKU | D1: WB N.º de estilo | E1: WB Marca | F1: WB Descripcion | G1: WB Talla | H1: WB Color | I1: WB División | J1: WB Categoría | K1: WB Género | L1: Unidad | M1: Precio de compra | N1: Precio de venta | O1: En mano NetSuite | P1: Disponible NetSuite | Q1: Comprometido NetSuite | R1: En pedido NetSuite | S1: En tránsito NetSuite | T1: Pendiente por surtir NetSuite | U1: En mano en ubicaciones inactivas | V1: Ubicaciones en negativo | W1: En mano NetSuite 28/09/2026 | X1: Variación neta | Y1: Odoo Universal Unique Brands | Z1: Piezas contadas (Escaneos) | AA1: Fecha del último conteo | AB1: Valor en mano a costo | AC1: Valor en mano a precio de venta | AD1: Estado del inventario | AE1: NS · B25 CEDIS | AF1: NS · WB OUTLET LERMA
A2: 087327013586 | C2: 95597 | E2: Yellowstone | F2: TESTER YELLOWSTONE 3.4 OZ COLOGNE SPRAY | G2: 100 ml | I2: Accesorios | J2: Fragancias | K2: Unisex | L2: PZS | N2: 679 | O2: 0 | X2: =O2-W2 | Y2: 2 | AB2: =IFERROR(O2*M2,0) | AC2: =IFERROR(O2*N2,0) | AD2: Solo en plataformas
C3: 96234 | E3: Yellowstone | F3: TESTER YELLOWSTONE RIDE 3.4 OZ COLOGNE SPRAY | G3: 100 ml | I3: Accesorios | J3: Fragancias | K3: Unisex | L3: PZS | N3: 679 | O3: 0 | X3: =O3-W3 | Y3: 3 | AB3: =IFERROR(O3*M3,0) | AC3: =IFERROR(O3*N3,0) | AD3: Solo en plataformas
A4: 087327030415 | C4: 96645 | E4: Yellowstone | F4: TESTER Yellowstone - Ride Reserve 3.4oz EDC | G4: 100 ml | I4: Accesorios | J4: Fragancias | K4: Unisex | L4: PZS | N4: 759 | O4: 0 | X4: =O4-W4 | Y4: 2 | AB4: =IFERROR(O4*M4,0) | AC4: =IFERROR(O4*N4,0) | AD4: Solo en plataformas
A5: 087327025572 | C5: 96235 | E5: Yellowstone | F5: TESTER Yellowstone - 1.7oz EDP - Tornado | G5: 50 ml | I5: Accesorios | J5: Fragancias | K5: Unisex | L5: PZS | N5: 639 | O5: 0 | X5: =O5-W5 | Y5: 3 | AB5: =IFERROR(O5*M5,0) | AC5: =IFERROR(O5*N5,0) | AD5: Solo en plataformas
A6: 7506552406541 | B6: 118246 | C6: YW11 | D6: YW11 | E6: Yellowstone | F6: Gorra Yellowstone 11 | G6: Talla única | H6: Negro | I6: Accesorios | J6: Gorras | K6: Hombre | L6: PZS | M6: 307.31 | N6: 645.68966 | O6: 25 | P6: 6 | Q6: 19 | R6: 19 | X6: =O6-W6 | AB6: =IFERROR(O6*M6,0) | AC6: =IFERROR(O6*N6,0) | AD6: Con existencia | AE6: 19 | AF6: 6
A7: 7506552411002 | B7: 118230 | C7: YW32 | D7: YW32 | E7: Yellowstone | F7: Gorra Yellowstone 32 | G7: Talla única | H7: Blanco | I7: Accesorios | J7: Gorras | K7: Hombre | L7: PZS | M7: 307.31 | N7: 645.68966 | O7: 41 | P7: 8 | Q7: 33 | R7: 33 | X7: =O7-W7 | AB7: =IFERROR(O7*M7,0) | AC7: =IFERROR(O7*N7,0) | AD7: Con existencia | AE7: 33 | AF7: 8
A8: 7506552411057 | B8: 118247 | C8: YW37 | D8: YW37 | E8: Yellowstone | F8: Gorra Yellowstone 37 | G8: Talla única | H8: Negro | I8: Accesorios | J8: Gorras | K8: Hombre | L8: PZS | M8: 307.31 | N8: 645.68966 | O8: 25 | P8: 6 | Q8: 19 | R8: 19 | X8: =O8-W8 | AB8: =IFERROR(O8*M8,0) | AC8: =IFERROR(O8*N8,0) | AD8: Con existencia | AE8: 19 | AF8: 6
A9: 7506552414997 | B9: 118231 | C9: YW44 | D9: YW44 | E9: Yellowstone | F9: Gorra Yellowstone 44 | G9: Talla única | H9: Cafe | I9: Accesorios | J9: Gorras | K9: Hombre | L9: PZS | M9: 307.31 | N9: 645.68966 | O9: 39 | P9: 8 | Q9: 31 | R9: 31 | X9: =O9-W9 | AB9: =IFERROR(O9*M9,0) | AC9: =IFERROR(O9*N9,0) | AD9: Con existencia | AE9: 31 | AF9: 8
A10: 7506552415000 | B10: 118232 | C10: YW45 | D10: YW45 | E10: Yellowstone | F10: Gorra Yellowstone 45 | G10: Talla única | H10: Cafe | I10: Accesorios | J10: Gorras | K10: Hombre | L10: PZS | M10: 307.31 | N10: 645.68966 | O10: 38 | P10: 8 | Q10: 30 | R10: 30 | X10: =O10-W10 | AB10: =IFERROR(O10*M10,0) | AC10: =IFERROR(O10*N10,0) | AD10: Con existencia | AE10: 30 | AF10: 8
A11: 7506552415017 | B11: 118248 | C11: YW46 | D11: YW46 | E11: Yellowstone | F11: Gorra Yellowstone 46 | G11: Talla única | H11: Cafe | I11: Accesorios | J11: Gorras | K11: Hombre | L11: PZS | M11: 307.31 | N11: 645.68966 | O11: 7 | P11: 3 | Q11: 4 | R11: 4 | X11: =O11-W11 | AB11: =IFERROR(O11*M11,0) | AC11: =IFERROR(O11*N11,0) | AD11: Con existencia | AE11: 4 | AF11: 3
A12: 7506552415024 | B12: 118249 | C12: YW47 | D12: YW47 | E12: Yellowstone | F12: Gorra Yellowstone 47 | G12: Talla única | H12: Negro | I12: Accesorios | J12: Gorras | K12: Hombre | L12: PZS | M12: 307.31 | N12: 645.68966 | O12: 7 | P12: 3 | Q12: 4 | R12: 4 | X12: =O12-W12 | AB12: =IFERROR(O12*M12,0) | AC12: =IFERROR(O12*N12,0) | AD12: Con existencia | AE12: 4 | AF12: 3

Sheet KPIs Inventario
A1: Indicadores de inventario · Yellowstone
A2: NetSuite al 06/10/2026 · corte anterior NetSuite 28/09/2026 · Shopify Ariat 05/10/2026 · Shopify Stetson, Western Brothers y Odoo 01/10/2026
A4: Existencia actual (NetSuite)
A5: Indicador | B5: Valor | C5: Nota
A6: Artículos con existencia | B6: =COUNTIF(Inventario!$O$2:$O$12,">0")
A7: Unidades en mano | B7: =SUM(Inventario!$O$2:$O$12) | C7: Existencia del sistema
A8: Unidades disponibles | B8: =SUM(Inventario!$P$2:$P$12)
A9: Unidades comprometidas | B9: =SUM(Inventario!$Q$2:$Q$12) | C9: Pedidos por surtir
A10: Unidades en tránsito | B10: =SUM(Inventario!$S$2:$S$12)
A11: Unidades en pedido | B11: 140 | C11: Órdenes de compra abiertas de 7 artículos; 0 de ellos aún no tienen existencia y no aparecen en la hoja Inventario
A12: Unidades pendientes por surtir | B12: =SUM(Inventario!$T$2:$T$12)
A13: Unidades en ubicaciones inactivas | B13: =SUM(Inventario!$U$2:$U$12) | C13: Ubicaciones dadas de baja en NetSuite que aún tienen existencia
A14: Artículos con existencia negativa | B14: =COUNTIF(Inventario!$O$2:$O$12,"<0") | C14: Revisar en conteo
A15: Unidades en negativo | B15: =SUMIF(Inventario!$O$2:$O$12,"<0")
A16: Valor en mano a costo | B16: =SUM(Inventario!$AB$2:$AB$12) | C16: Precio de compra de NetSuite; hay costos que parecen estar en dólares (ver Notas)
A17: Valor en mano a precio de venta | B17: =SUM(Inventario!$AC$2:$AC$12) | C17: Precio de venta sin IVA
A19: Movimiento neto 28/09/2026 → 06/10/2026
A20: Indicador | B20: Valor | C20: Nota
A21: Unidades en mano al 28/09/2026 | B21: =SUM(Inventario!$W$2:$W$12)
A22: Variación neta de unidades | B22: =SUM(Inventario!$X$2:$X$12) | C22: En mano actual − en mano anterior
A23: Unidades que salieron (neto) | B23: =SUMIF(Inventario!$X$2:$X$12,"<0") | C23: Ventas, traspasos o ajustes
A24: Unidades que entraron (neto) | B24: =SUMIF(Inventario!$X$2:$X$12,">0") | C24: Recepciones, traspasos o ajustes
A25: Artículos que bajaron | B25: =COUNTIF(Inventario!$X$2:$X$12,"<0")
A26: Artículos que subieron | B26: =COUNTIF(Inventario!$X$2:$X$12,">0")
A27: Artículos que se agotaron | B27: =COUNTIFS(Inventario!$O$2:$O$12,0,Inventario!$W$2:$W$12,">0")
A29: Existencia en plataformas
A30: Plataforma | B30: Unidades | C30: Artículos con existencia | D30: Corte
A31: Odoo Universal Unique Brands | B31: =SUM(Inventario!$Y$2:$Y$12) | C31: =COUNTIF(Inventario!$Y$2:$Y$12,">0") | D31: 01/10/2026
A33: Conteo cíclico
A34: Indicador | B34: Valor
A35: Piezas contadas en rack (Escaneos) | B35: =SUM(Inventario!$Z$2:$Z$12)
A36: Artículos contados | B36: =COUNTIF(Inventario!$Z$2:$Z$12,">0")
A38: Por ubicación NetSuite
A39: Ubicación | B39: Bodega / tipo | C39: Activa | D39: En mano | E39: % del total | F39: Artículos con existencia | G39: Artículos en negativo | H39: En mano 28/09/2026 | I39: Entradas netas | J39: Salidas netas | K39: Variación
A40: B25 CEDIS | B40: Bodega 25 | C40: Sí | D40: =SUM(Inventario!$AE$2:$AE$12) | E40: =IFERROR(D40/SUM($D$40:$D$41),0) | F40: =COUNTIF(Inventario!$AE$2:$AE$12,">0") | G40: =COUNTIF(Inventario!$AE$2:$AE$12,"<0") | H40: 0 | I40: 140 | J40: 0 | K40: =D40-H40
A41: WB OUTLET LERMA | B41: Tienda | C41: Sí | D41: =SUM(Inventario!$AF$2:$AF$12) | E41: =IFERROR(D41/SUM($D$40:$D$41),0) | F41: =COUNTIF(Inventario!$AF$2:$AF$12,">0") | G41: =COUNTIF(Inventario!$AF$2:$AF$12,"<0") | H41: 0 | I41: 42 | J41: 0 | K41: =D41-H41
A42: B25 WB MERCADO LIBRE | C42: Sí | D42: 0 | H42: 0 | I42: 0 | J42: 0 | K42: =D42-H42
A43: B25 WESTERN BROTHERS.MX | C43: Sí | D43: 0 | H43: 0 | I43: 0 | J43: 0 | K43: =D43-H43
A45: Por división
A46: División | B46: En mano | C46: Artículos con existencia | D46: Valor a costo | E46: Valor a precio de venta | F46: Variación neta
A47: Accesorios | B47: =SUMIFS(Inventario!$O$2:$O$12,Inventario!$I$2:$I$12,"Accesorios") | C47: =COUNTIFS(Inventario!$I$2:$I$12,"Accesorios",Inventario!$O$2:$O$12,">0") | D47: =SUMIFS(Inventario!$AB$2:$AB$12,Inventario!$I$2:$I$12,"Accesorios") | E47: =SUMIFS(Inventario!$AC$2:$AC$12,Inventario!$I$2:$I$12,"Accesorios") | F47: =SUMIFS(Inventario!$X$2:$X$12,Inventario!$I$2:$I$12,"Accesorios")
A49: Por categoría
A50: Categoría | B50: En mano | C50: Artículos con existencia | D50: Valor a costo | E50: Valor a precio de venta | F50: Variación neta
A51: Fragancias | B51: =SUMIFS(Inventario!$O$2:$O$12,Inventario!$J$2:$J$12,"Fragancias") | C51: =COUNTIFS(Inventario!$J$2:$J$12,"Fragancias",Inventario!$O$2:$O$12,">0") | D51: =SUMIFS(Inventario!$AB$2:$AB$12,Inventario!$J$2:$J$12,"Fragancias") | E51: =SUMIFS(Inventario!$AC$2:$AC$12,Inventario!$J$2:$J$12,"Fragancias") | F51: =SUMIFS(Inventario!$X$2:$X$12,Inventario!$J$2:$J$12,"Fragancias")
A52: Gorras | B52: =SUMIFS(Inventario!$O$2:$O$12,Inventario!$J$2:$J$12,"Gorras") | C52: =COUNTIFS(Inventario!$J$2:$J$12,"Gorras",Inventario!$O$2:$O$12,">0") | D52: =SUMIFS(Inventario!$AB$2:$AB$12,Inventario!$J$2:$J$12,"Gorras") | E52: =SUMIFS(Inventario!$AC$2:$AC$12,Inventario!$J$2:$J$12,"Gorras") | F52: =SUMIFS(Inventario!$X$2:$X$12,Inventario!$J$2:$J$12,"Gorras")
A54: 15 artículos con más unidades en mano
A55: Código de barras | B55: WB SKU | C55: WB Descripcion | D55: WB Talla | E55: En mano | F55: Variación
A56: 7506552411002 | B56: YW32 | C56: Gorra Yellowstone 32 | D56: Talla única | E56: 41 | F56: 41
A57: 7506552414997 | B57: YW44 | C57: Gorra Yellowstone 44 | D57: Talla única | E57: 39 | F57: 39
A58: 7506552415000 | B58: YW45 | C58: Gorra Yellowstone 45 | D58: Talla única | E58: 38 | F58: 38
A59: 7506552406541 | B59: YW11 | C59: Gorra Yellowstone 11 | D59: Talla única | E59: 25 | F59: 25
A60: 7506552411057 | B60: YW37 | C60: Gorra Yellowstone 37 | D60: Talla única | E60: 25 | F60: 25
A61: 7506552415017 | B61: YW46 | C61: Gorra Yellowstone 46 | D61: Talla única | E61: 7 | F61: 7
A62: 7506552415024 | B62: YW47 | C62: Gorra Yellowstone 47 | D62: Talla única | E62: 7 | F62: 7
A63: 087327013586 | B63: 95597 | C63: TESTER YELLOWSTONE 3.4 OZ COLOGNE SPRAY | D63: 100 ml | E63: 0 | F63: 0
B64: 96234 | C64: TESTER YELLOWSTONE RIDE 3.4 OZ COLOGNE SPRAY | D64: 100 ml | E64: 0 | F64: 0
A65: 087327030415 | B65: 96645 | C65: TESTER Yellowstone - Ride Reserve 3.4oz EDC | D65: 100 ml | E65: 0 | F65: 0
A66: 087327025572 | B66: 96235 | C66: TESTER Yellowstone - 1.7oz EDP - Tornado | D66: 50 ml | E66: 0 | F66: 0
A68: 15 artículos con más salida neta desde 28/09/2026
A69: Código de barras | B69: WB SKU | C69: WB Descripcion | D69: WB Talla | E69: En mano | F69: Variación
