Workbook

Sheet Escaneo Diario
A1: GRUPO QUINCE 22 | CONTROL DE INVENTARIOS Y CONTEO CÍCLICO DIARIO
A2: 📅 FECHA ACTUAL | C2: 📦 TOTAL ESCANEOS | E2: 🏷️ PRODUCTOS ÚNICOS | H2: 📊 TOTAL DE PIEZAS | J2: 🚀 ACCIÓN OPERATIVA
A3: =TODAY() | C3: =COUNTIF(C7:C1000, "<>") | E3: =IFERROR(__xludf.DUMMYFUNCTION("IFERROR(ROWS(UNIQUE(FILTER(D7:D1000, D7:D1000<>""""))), 0)"),0.0) | H3: =COUNTIF(C7:C1000, "<>") | J3: FINALIZAR ESCANEO
A4: Jornada en curso | C4: Registros capturados | E4: SKUs distintos | H4: Unidades contadas | J4: Asignar Folios y Archivar
A6: Fecha/Hora | B6: Ubicación/Rack | C6: UPC CODE | D6: SKU | E6: Marca | F6: Descripción | G6: División | H6: Categoría | I6: Talla / Size | J6: Alertas y Duplicados
D7: {=IF($C7="","",IFNA(_xlfn.XLOOKUP($C7,Productos!$A:$A,Productos!$E:$E,IFNA(_xlfn.XLOOKUP(TEXT($C7,"0"),Productos!$A:$A,Productos!$E:$E,IFNA(_xlfn.XLOOKUP(IFERROR(VALUE($C7),""),Productos!$A:$A,Productos!$E:$E,_xlfn.XLOOKUP($C7,Productos!$E:$E,Productos!$E:$E,"NO ENCONTRADO")),"NO ENCONTRADO")),"NO ENCONTRADO")),"NO ENCONTRADO"))} | E7: {=IF(OR($D7="",$D7="NO ENCONTRADO"),"",_xlfn.XLOOKUP($D7,Productos!$E:$E,Productos!$H:$H,""))} | F7: {=IF(OR($D7="",$D7="NO ENCONTRADO"),"",_xlfn.XLOOKUP($D7,Productos!$E:$E,Productos!$I:$I,""))} | G7: {=IF(OR($D7="",$D7="NO ENCONTRADO"),"",_xlfn.XLOOKUP($D7,Productos!$E:$E,Productos!$J:$J,""))} | H7: {=IF(OR($D7="",$D7="NO ENCONTRADO"),"",_xlfn.XLOOKUP($D7,Productos!$E:$E,Productos!$K:$K,""))} | I7: {=IF(OR($D7="",$D7="NO ENCONTRADO"),"",_xlfn.XLOOKUP($D7,Productos!$E:$E,Productos!$F:$F,""))} | J7: =IF($C7="","",IF($D7="NO ENCONTRADO",IF(COUNTIF($C$7:$C$1000,$C7)>1,"⚠️ No encontrado | Duplicado","⚠️ No encontrado"),IF(COUNTIF($C$7:$C$1000,$C7)>1,"⚠️ Duplicado","Verificado")))
D8: {=IF($C8="","",IFNA(_xlfn.XLOOKUP($C8,Productos!$A:$A,Productos!$E:$E,IFNA(_xlfn.XLOOKUP(TEXT($C8,"0"),Productos!$A:$A,Productos!$E:$E,IFNA(_xlfn.XLOOKUP(IFERROR(VALUE($C8),""),Productos!$A:$A,Productos!$E:$E,_xlfn.XLOOKUP($C8,Productos!$E:$E,Productos!$E:$E,"NO ENCONTRADO")),"NO ENCONTRADO")),"NO ENCONTRADO")),"NO ENCONTRADO"))} | E8: {=IF(OR($D8="",$D8="NO ENCONTRADO"),"",_xlfn.XLOOKUP($D8,Productos!$E:$E,Productos!$H:$H,""))} | F8: {=IF(OR($D8="",$D8="NO ENCONTRADO"),"",_xlfn.XLOOKUP($D8,Productos!$E:$E,Productos!$I:$I,""))} | G8: {=IF(OR($D8="",$D8="NO ENCONTRADO"),"",_xlfn.XLOOKUP($D8,Productos!$E:$E,Productos!$J:$J,""))} | H8: {=IF(OR($D8="",$D8="NO ENCONTRADO"),"",_xlfn.XLOOKUP($D8,Productos!$E:$E,Productos!$K:$K,""))} | I8: {=IF(OR($D8="",$D8="NO ENCONTRADO"),"",_xlfn.XLOOKUP($D8,Productos!$E:$E,Productos!$F:$F,""))} | J8: =IF($C8="","",IF($D8="NO ENCONTRADO",IF(COUNTIF($C$7:$C$1000,$C8)>1,"⚠️ No encontrado | Duplicado","⚠️ No encontrado"),IF(COUNTIF($C$7:$C$1000,$C8)>1,"⚠️ Duplicado","Verificado")))
D9: {=IF($C9="","",IFNA(_xlfn.XLOOKUP($C9,Productos!$A:$A,Productos!$E:$E,IFNA(_xlfn.XLOOKUP(TEXT($C9,"0"),Productos!$A:$A,Productos!$E:$E,IFNA(_xlfn.XLOOKUP(IFERROR(VALUE($C9),""),Productos!$A:$A,Productos!$E:$E,_xlfn.XLOOKUP($C9,Productos!$E:$E,Productos!$E:$E,"NO ENCONTRADO")),"NO ENCONTRADO")),"NO ENCONTRADO")),"NO ENCONTRADO"))} | E9: {=IF(OR($D9="",$D9="NO ENCONTRADO"),"",_xlfn.XLOOKUP($D9,Productos!$E:$E,Productos!$H:$H,""))} | F9: {=IF(OR($D9="",$D9="NO ENCONTRADO"),"",_xlfn.XLOOKUP($D9,Productos!$E:$E,Productos!$I:$I,""))} | G9: {=IF(OR($D9="",$D9="NO ENCONTRADO"),"",_xlfn.XLOOKUP($D9,Productos!$E:$E,Productos!$J:$J,""))} | H9: {=IF(OR($D9="",$D9="NO ENCONTRADO"),"",_xlfn.XLOOKUP($D9,Productos!$E:$E,Productos!$K:$K,""))} | I9: {=IF(OR($D9="",$D9="NO ENCONTRADO"),"",_xlfn.XLOOKUP($D9,Productos!$E:$E,Productos!$F:$F,""))} | J9: =IF($C9="","",IF($D9="NO ENCONTRADO",IF(COUNTIF($C$7:$C$1000,$C9)>1,"⚠️ No encontrado | Duplicado","⚠️ No encontrado"),IF(COUNTIF($C$7:$C$1000,$C9)>1,"⚠️ Duplicado","Verificado")))
D10: {=IF($C10="","",IFNA(_xlfn.XLOOKUP($C10,Productos!$A:$A,Productos!$E:$E,IFNA(_xlfn.XLOOKUP(TEXT($C10,"0"),Productos!$A:$A,Productos!$E:$E,IFNA(_xlfn.XLOOKUP(IFERROR(VALUE($C10),""),Productos!$A:$A,Productos!$E:$E,_xlfn.XLOOKUP($C10,Productos!$E:$E,Productos!$E:$E,"NO ENCONTRADO")),"NO ENCONTRADO")),"NO ENCONTRADO")),"NO ENCONTRADO"))} | E10: {=IF(OR($D10="",$D10="NO ENCONTRADO"),"",_xlfn.XLOOKUP($D10,Productos!$E:$E,Productos!$H:$H,""))} | F10: {=IF(OR($D10="",$D10="NO ENCONTRADO"),"",_xlfn.XLOOKUP($D10,Productos!$E:$E,Productos!$I:$I,""))} | G10: {=IF(OR($D10="",$D10="NO ENCONTRADO"),"",_xlfn.XLOOKUP($D10,Productos!$E:$E,Productos!$J:$J,""))} | H10: {=IF(OR($D10="",$D10="NO ENCONTRADO"),"",_xlfn.XLOOKUP($D10,Productos!$E:$E,Productos!$K:$K,""))} | I10: {=IF(OR($D10="",$D10="NO ENCONTRADO"),"",_xlfn.XLOOKUP($D10,Productos!$E:$E,Productos!$F:$F,""))} | J10: =IF($C10="","",IF($D10="NO ENCONTRADO",IF(COUNTIF($C$7:$C$1000,$C10)>1,"⚠️ No encontrado | Duplicado","⚠️ No encontrado"),IF(COUNTIF($C$7:$C$1000,$C10)>1,"⚠️ Duplicado","Verificado")))
D11: {=IF($C11="","",IFNA(_xlfn.XLOOKUP($C11,Productos!$A:$A,Productos!$E:$E,IFNA(_xlfn.XLOOKUP(TEXT($C11,"0"),Productos!$A:$A,Productos!$E:$E,IFNA(_xlfn.XLOOKUP(IFERROR(VALUE($C11),""),Productos!$A:$A,Productos!$E:$E,_xlfn.XLOOKUP($C11,Productos!$E:$E,Productos!$E:$E,"NO ENCONTRADO")),"NO ENCONTRADO")),"NO ENCONTRADO")),"NO ENCONTRADO"))} | E11: {=IF(OR($D11="",$D11="NO ENCONTRADO"),"",_xlfn.XLOOKUP($D11,Productos!$E:$E,Productos!$H:$H,""))} | F11: {=IF(OR($D11="",$D11="NO ENCONTRADO"),"",_xlfn.XLOOKUP($D11,Productos!$E:$E,Productos!$I:$I,""))} | G11: {=IF(OR($D11="",$D11="NO ENCONTRADO"),"",_xlfn.XLOOKUP($D11,Productos!$E:$E,Productos!$J:$J,""))} | H11: {=IF(OR($D11="",$D11="NO ENCONTRADO"),"",_xlfn.XLOOKUP($D11,Productos!$E:$E,Productos!$K:$K,""))} | I11: {=IF(OR($D11="",$D11="NO ENCONTRADO"),"",_xlfn.XLOOKUP($D11,Productos!$E:$E,Productos!$F:$F,""))} | J11: =IF($C11="","",IF($D11="NO ENCONTRADO",IF(COUNTIF($C$7:$C$1000,$C11)>1,"⚠️ No encontrado | Duplicado","⚠️ No encontrado"),IF(COUNTIF($C$7:$C$1000,$C11)>1,"⚠️ Duplicado","Verificado")))
D12: {=IF($C12="","",IFNA(_xlfn.XLOOKUP($C12,Productos!$A:$A,Productos!$E:$E,IFNA(_xlfn.XLOOKUP(TEXT($C12,"0"),Productos!$A:$A,Productos!$E:$E,IFNA(_xlfn.XLOOKUP(IFERROR(VALUE($C12),""),Productos!$A:$A,Productos!$E:$E,_xlfn.XLOOKUP($C12,Productos!$E:$E,Productos!$E:$E,"NO ENCONTRADO")),"NO ENCONTRADO")),"NO ENCONTRADO")),"NO ENCONTRADO"))} | E12: {=IF(OR($D12="",$D12="NO ENCONTRADO"),"",_xlfn.XLOOKUP($D12,Productos!$E:$E,Productos!$H:$H,""))} | F12: {=IF(OR($D12="",$D12="NO ENCONTRADO"),"",_xlfn.XLOOKUP($D12,Productos!$E:$E,Productos!$I:$I,""))} | G12: {=IF(OR($D12="",$D12="NO ENCONTRADO"),"",_xlfn.XLOOKUP($D12,Productos!$E:$E,Productos!$J:$J,""))} | H12: {=IF(OR($D12="",$D12="NO ENCONTRADO"),"",_xlfn.XLOOKUP($D12,Productos!$E:$E,Productos!$K:$K,""))} | I12: {=IF(OR($D12="",$D12="NO ENCONTRADO"),"",_xlfn.XLOOKUP($D12,Productos!$E:$E,Productos!$F:$F,""))} | J12: =IF($C12="","",IF($D12="NO ENCONTRADO",IF(COUNTIF($C$7:$C$1000,$C12)>1,"⚠️ No encontrado | Duplicado","⚠️ No encontrado"),IF(COUNTIF($C$7:$C$1000,$C12)>1,"⚠️ Duplicado","Verificado")))
D13: {=IF($C13="","",IFNA(_xlfn.XLOOKUP($C13,Productos!$A:$A,Productos!$E:$E,IFNA(_xlfn.XLOOKUP(TEXT($C13,"0"),Productos!$A:$A,Productos!$E:$E,IFNA(_xlfn.XLOOKUP(IFERROR(VALUE($C13),""),Productos!$A:$A,Productos!$E:$E,_xlfn.XLOOKUP($C13,Productos!$E:$E,Productos!$E:$E,"NO ENCONTRADO")),"NO ENCONTRADO")),"NO ENCONTRADO")),"NO ENCONTRADO"))} | E13: {=IF(OR($D13="",$D13="NO ENCONTRADO"),"",_xlfn.XLOOKUP($D13,Productos!$E:$E,Productos!$H:$H,""))} | F13: {=IF(OR($D13="",$D13="NO ENCONTRADO"),"",_xlfn.XLOOKUP($D13,Productos!$E:$E,Productos!$I:$I,""))} | G13: {=IF(OR($D13="",$D13="NO ENCONTRADO"),"",_xlfn.XLOOKUP($D13,Productos!$E:$E,Productos!$J:$J,""))} | H13: {=IF(OR($D13="",$D13="NO ENCONTRADO"),"",_xlfn.XLOOKUP($D13,Productos!$E:$E,Productos!$K:$K,""))} | I13: {=IF(OR($D13="",$D13="NO ENCONTRADO"),"",_xlfn.XLOOKUP($D13,Productos!$E:$E,Productos!$F:$F,""))} | J13: =IF($C13="","",IF($D13="NO ENCONTRADO",IF(COUNTIF($C$7:$C$1000,$C13)>1,"⚠️ No encontrado | Duplicado","⚠️ No encontrado"),IF(COUNTIF($C$7:$C$1000,$C13)>1,"⚠️ Duplicado","Verificado")))
D14: {=IF($C14="","",IFNA(_xlfn.XLOOKUP($C14,Productos!$A:$A,Productos!$E:$E,IFNA(_xlfn.XLOOKUP(TEXT($C14,"0"),Productos!$A:$A,Productos!$E:$E,IFNA(_xlfn.XLOOKUP(IFERROR(VALUE($C14),""),Productos!$A:$A,Productos!$E:$E,_xlfn.XLOOKUP($C14,Productos!$E:$E,Productos!$E:$E,"NO ENCONTRADO")),"NO ENCONTRADO")),"NO ENCONTRADO")),"NO ENCONTRADO"))} | E14: {=IF(OR($D14="",$D14="NO ENCONTRADO"),"",_xlfn.XLOOKUP($D14,Productos!$E:$E,Productos!$H:$H,""))} | F14: {=IF(OR($D14="",$D14="NO ENCONTRADO"),"",_xlfn.XLOOKUP($D14,Productos!$E:$E,Productos!$I:$I,""))} | G14: {=IF(OR($D14="",$D14="NO ENCONTRADO"),"",_xlfn.XLOOKUP($D14,Productos!$E:$E,Productos!$J:$J,""))} | H14: {=IF(OR($D14="",$D14="NO ENCONTRADO"),"",_xlfn.XLOOKUP($D14,Productos!$E:$E,Productos!$K:$K,""))} | I14: {=IF(OR($D14="",$D14="NO ENCONTRADO"),"",_xlfn.XLOOKUP($D14,Productos!$E:$E,Productos!$F:$F,""))} | J14: =IF($C14="","",IF($D14="NO ENCONTRADO",IF(COUNTIF($C$7:$C$1000,$C14)>1,"⚠️ No encontrado | Duplicado","⚠️ No encontrado"),IF(COUNTIF($C$7:$C$1000,$C14)>1,"⚠️ Duplicado","Verificado")))
D15: {=IF($C15="","",IFNA(_xlfn.XLOOKUP($C15,Productos!$A:$A,Productos!$E:$E,IFNA(_xlfn.XLOOKUP(TEXT($C15,"0"),Productos!$A:$A,Productos!$E:$E,IFNA(_xlfn.XLOOKUP(IFERROR(VALUE($C15),""),Productos!$A:$A,Productos!$E:$E,_xlfn.XLOOKUP($C15,Productos!$E:$E,Productos!$E:$E,"NO ENCONTRADO")),"NO ENCONTRADO")),"NO ENCONTRADO")),"NO ENCONTRADO"))} | E15: {=IF(OR($D15="",$D15="NO ENCONTRADO"),"",_xlfn.XLOOKUP($D15,Productos!$E:$E,Productos!$H:$H,""))} | F15: {=IF(OR($D15="",$D15="NO ENCONTRADO"),"",_xlfn.XLOOKUP($D15,Productos!$E:$E,Productos!$I:$I,""))} | G15: {=IF(OR($D15="",$D15="NO ENCONTRADO"),"",_xlfn.XLOOKUP($D15,Productos!$E:$E,Productos!$J:$J,""))} | H15: {=IF(OR($D15="",$D15="NO ENCONTRADO"),"",_xlfn.XLOOKUP($D15,Productos!$E:$E,Productos!$K:$K,""))} | I15: {=IF(OR($D15="",$D15="NO ENCONTRADO"),"",_xlfn.XLOOKUP($D15,Productos!$E:$E,Productos!$F:$F,""))} | J15: =IF($C15="","",IF($D15="NO ENCONTRADO",IF(COUNTIF($C$7:$C$1000,$C15)>1,"⚠️ No encontrado | Duplicado","⚠️ No encontrado"),IF(COUNTIF($C$7:$C$1000,$C15)>1,"⚠️ Duplicado","Verificado")))
D16: {=IF($C16="","",IFNA(_xlfn.XLOOKUP($C16,Productos!$A:$A,Productos!$E:$E,IFNA(_xlfn.XLOOKUP(TEXT($C16,"0"),Productos!$A:$A,Productos!$E:$E,IFNA(_xlfn.XLOOKUP(IFERROR(VALUE($C16),""),Productos!$A:$A,Productos!$E:$E,_xlfn.XLOOKUP($C16,Productos!$E:$E,Productos!$E:$E,"NO ENCONTRADO")),"NO ENCONTRADO")),"NO ENCONTRADO")),"NO ENCONTRADO"))} | E16: {=IF(OR($D16="",$D16="NO ENCONTRADO"),"",_xlfn.XLOOKUP($D16,Productos!$E:$E,Productos!$H:$H,""))} | F16: {=IF(OR($D16="",$D16="NO ENCONTRADO"),"",_xlfn.XLOOKUP($D16,Productos!$E:$E,Productos!$I:$I,""))} | G16: {=IF(OR($D16="",$D16="NO ENCONTRADO"),"",_xlfn.XLOOKUP($D16,Productos!$E:$E,Productos!$J:$J,""))} | H16: {=IF(OR($D16="",$D16="NO ENCONTRADO"),"",_xlfn.XLOOKUP($D16,Productos!$E:$E,Productos!$K:$K,""))} | I16: {=IF(OR($D16="",$D16="NO ENCONTRADO"),"",_xlfn.XLOOKUP($D16,Productos!$E:$E,Productos!$F:$F,""))} | J16: =IF($C16="","",IF($D16="NO ENCONTRADO",IF(COUNTIF($C$7:$C$1000,$C16)>1,"⚠️ No encontrado | Duplicado","⚠️ No encontrado"),IF(COUNTIF($C$7:$C$1000,$C16)>1,"⚠️ Duplicado","Verificado")))
D17: {=IF($C17="","",IFNA(_xlfn.XLOOKUP($C17,Productos!$A:$A,Productos!$E:$E,IFNA(_xlfn.XLOOKUP(TEXT($C17,"0"),Productos!$A:$A,Productos!$E:$E,IFNA(_xlfn.XLOOKUP(IFERROR(VALUE($C17),""),Productos!$A:$A,Productos!$E:$E,_xlfn.XLOOKUP($C17,Productos!$E:$E,Productos!$E:$E,"NO ENCONTRADO")),"NO ENCONTRADO")),"NO ENCONTRADO")),"NO ENCONTRADO"))} | E17: {=IF(OR($D17="",$D17="NO ENCONTRADO"),"",_xlfn.XLOOKUP($D17,Productos!$E:$E,Productos!$H:$H,""))} | F17: {=IF(OR($D17="",$D17="NO ENCONTRADO"),"",_xlfn.XLOOKUP($D17,Productos!$E:$E,Productos!$I:$I,""))} | G17: {=IF(OR($D17="",$D17="NO ENCONTRADO"),"",_xlfn.XLOOKUP($D17,Productos!$E:$E,Productos!$J:$J,""))} | H17: {=IF(OR($D17="",$D17="NO ENCONTRADO"),"",_xlfn.XLOOKUP($D17,Productos!$E:$E,Productos!$K:$K,""))} | I17: {=IF(OR($D17="",$D17="NO ENCONTRADO"),"",_xlfn.XLOOKUP($D17,Productos!$E:$E,Productos!$F:$F,""))} | J17: =IF($C17="","",IF($D17="NO ENCONTRADO",IF(COUNTIF($C$7:$C$1000,$C17)>1,"⚠️ No encontrado | Duplicado","⚠️ No encontrado"),IF(COUNTIF($C$7:$C$1000,$C17)>1,"⚠️ Duplicado","Verificado")))
D18: {=IF($C18="","",IFNA(_xlfn.XLOOKUP($C18,Productos!$A:$A,Productos!$E:$E,IFNA(_xlfn.XLOOKUP(TEXT($C18,"0"),Productos!$A:$A,Productos!$E:$E,IFNA(_xlfn.XLOOKUP(IFERROR(VALUE($C18),""),Productos!$A:$A,Productos!$E:$E,_xlfn.XLOOKUP($C18,Productos!$E:$E,Productos!$E:$E,"NO ENCONTRADO")),"NO ENCONTRADO")),"NO ENCONTRADO")),"NO ENCONTRADO"))} | E18: {=IF(OR($D18="",$D18="NO ENCONTRADO"),"",_xlfn.XLOOKUP($D18,Productos!$E:$E,Productos!$H:$H,""))} | F18: {=IF(OR($D18="",$D18="NO ENCONTRADO"),"",_xlfn.XLOOKUP($D18,Productos!$E:$E,Productos!$I:$I,""))} | G18: {=IF(OR($D18="",$D18="NO ENCONTRADO"),"",_xlfn.XLOOKUP($D18,Productos!$E:$E,Productos!$J:$J,""))} | H18: {=IF(OR($D18="",$D18="NO ENCONTRADO"),"",_xlfn.XLOOKUP($D18,Productos!$E:$E,Productos!$K:$K,""))} | I18: {=IF(OR($D18="",$D18="NO ENCONTRADO"),"",_xlfn.XLOOKUP($D18,Productos!$E:$E,Productos!$F:$F,""))} | J18: =IF($C18="","",IF($D18="NO ENCONTRADO",IF(COUNTIF($C$7:$C$1000,$C18)>1,"⚠️ No encontrado | Duplicado","⚠️ No encontrado"),IF(COUNTIF($C$7:$C$1000,$C18)>1,"⚠️ Duplicado","Verificado")))
... D1000: {=IF($C1000="","",IFNA(_xlfn.XLOOKUP($C1000,Productos!$A:$A,Productos!$E:$E,IFNA(_xlfn.XLOOKUP(TEXT($C1000,"0"),Productos!$A:$A,Productos!$E:$E,IFNA(_xlfn.XLOOKUP(IFERROR(VALUE($C1000),""),Productos!$A:$A,Productos!$E:$E,_xlfn.XLOOKUP($C1000,Productos!$E:$E,Productos!$E:$E,"NO ENCONTRADO")),"NO ENCONTRADO")),"NO ENCONTRADO")),"NO ENCONTRADO"))} | E1000: {=IF(OR($D1000="",$D1000="NO ENCONTRADO"),"",_xlfn.XLOOKUP($D1000,Productos!$E:$E,Productos!$H:$H,""))} | F1000: {=IF(OR($D1000="",$D1000="NO ENCONTRADO"),"",_xlfn.XLOOKUP($D1000,Productos!$E:$E,Productos!$I:$I,""))} | G1000: {=IF(OR($D1000="",$D1000="NO ENCONTRADO"),"",_xlfn.XLOOKUP($D1000,Productos!$E:$E,Productos!$J:$J,""))} | H1000: {=IF(OR($D1000="",$D1000="NO ENCONTRADO"),"",_xlfn.XLOOKUP($D1000,Productos!$E:$E,Productos!$K:$K,""))} | I1000: {=IF(OR($D1000="",$D1000="NO ENCONTRADO"),"",_xlfn.XLOOKUP($D1000,Productos!$E:$E,Productos!$F:$F,""))} | J1000: =IF($C1000="","",IF($D1000="NO ENCONTRADO",IF(COUNTIF($C$7:$C$1000,$C1000)>1,"⚠️ No encontrado | Duplicado","⚠️ No encontrado"),IF(COUNTIF($C$7:$C$1000,$C1000)>1,"⚠️ Duplicado","Verificado")))

Sheet Historial de Escaneos
A1: HISTORIAL Y BITÁCORA CONSOLIDADA DE CONTEOS CÍCLICOS - GRUPO QUINCE 22
A2: Registro histórico de auditorías, folios automáticos por ubicación y trazabilidad consolidada de marcas e inventario físico
A3: Fecha de Conteo | B3: Hora Registro | C3: Folio de Escaneo | D3: Ubicación / Rack | E3: Marcas Escaneadas (Todas) | F3: Total Piezas | G3: Auditor / Responsable | H3: Dictamen de Auditoría | I3: Alertas de Modificación / Incidencias

Sheet Escaneos
A1: Folio de Escaneo | B1: Fecha / Hora | C1: Ubicación / Rack | D1: UPC CODE | E1: SKU | F1: Marca | G1: Descripción | H1: Categoría | I1: Talla / Size | J1: Piezas Contadas | K1: Auditor / Responsable | L1: Estado de Conteo | M1: Detalle de Modificaciones / Alertas

Sheet Configuración
A1: CONFIGURACIÓN DEL SISTEMA Y CATÁLOGOS MAESTROS - GRUPO QUINCE 22
A2: Catálogos oficiales para validación de datos y listas desplegables del conteo cíclico diario
A3: Ubicaciones / Racks | B3: Marcas | C3: Categorías | D3: Tallas / Sizes | E3: Auditores / Operadores | F3: Estado de Conteo | H3: Ubicaciones NetSuite (Hoja a Revisar) | I3: SKUs con stock | J3: Piezas en sistema
A4: Pasillo A - Racks Principales | B4: 1522 Original | C4: Playeras | D4: XS | E4: Jesús Fregoso | F4: Verificado | H4: Almacenes G1522 | I4: {=_xlfn.XLOOKUP($H4,Criterios!$G$6:$G$200,Criterios!I$6:I$200,"")} | J4: {=_xlfn.XLOOKUP($H4,Criterios!$G$6:$G$200,Criterios!J$6:J$200,"")}
A5: Pasillo B - Estantería Media | B5: Urban Trend | C5: Pantalones | D5: S | E5: Carlos Morales | F5: Con Discrepancia | H5: AMAZON | I5: {=_xlfn.XLOOKUP($H5,Criterios!$G$6:$G$200,Criterios!I$6:I$200,"")} | J5: {=_xlfn.XLOOKUP($H5,Criterios!$G$6:$G$200,Criterios!J$6:J$200,"")}
A6: Pasillo C - Calzado y Confección | B6: Denim Co. | C6: Sudaderas | D6: M | E6: Andrea Valenzuela | F6: Pendiente | H6: ARIAT CHIHUAHUA | I6: {=_xlfn.XLOOKUP($H6,Criterios!$G$6:$G$200,Criterios!I$6:I$200,"")} | J6: {=_xlfn.XLOOKUP($H6,Criterios!$G$6:$G$200,Criterios!J$6:J$200,"")}
A7: Pasillo D - Accesorios | B7: Active Wear | C7: Chamarras | D7: L | E7: Luis Fernández | F7: Revisión Requerida | H7: ARIAT OUTLET GDL | I7: {=_xlfn.XLOOKUP($H7,Criterios!$G$6:$G$200,Criterios!I$6:I$200,"")} | J7: {=_xlfn.XLOOKUP($H7,Criterios!$G$6:$G$200,Criterios!J$6:J$200,"")}
A8: Pasillo E - Devoluciones | B8: Casual Basics | C8: Gorras | D8: XL | E8: Mariana Garza | H8: ARIAT PLAZA SAN LUIS | I8: {=_xlfn.XLOOKUP($H8,Criterios!$G$6:$G$200,Criterios!I$6:I$200,"")} | J8: {=_xlfn.XLOOKUP($H8,Criterios!$G$6:$G$200,Criterios!J$6:J$200,"")}
A9: Bodega Central - Tarimas | B9: Signature 1522 | C9: Camisas | D9: XXL | E9: Roberto Méndez | H9: ARIAT SAN NICOLAS NL | I9: {=_xlfn.XLOOKUP($H9,Criterios!$G$6:$G$200,Criterios!I$6:I$200,"")} | J9: {=_xlfn.XLOOKUP($H9,Criterios!$G$6:$G$200,Criterios!J$6:J$200,"")}
A10: Zona de Picking 1 | B10: Premium Line | C10: Calzado | D10: 28x32 | E10: Sofía Castro | H10: B25 CEDIS | I10: {=_xlfn.XLOOKUP($H10,Criterios!$G$6:$G$200,Criterios!I$6:I$200,"")} | J10: {=_xlfn.XLOOKUP($H10,Criterios!$G$6:$G$200,Criterios!J$6:J$200,"")}
A11: Zona de Recepción | B11: Vintage Republic | C11: Accesorios | D11: 30x32 | E11: Miguel Ángel Ruiz | H11: B25 STETSON.MX | I11: {=_xlfn.XLOOKUP($H11,Criterios!$G$6:$G$200,Criterios!I$6:I$200,"")} | J11: {=_xlfn.XLOOKUP($H11,Criterios!$G$6:$G$200,Criterios!J$6:J$200,"")}
A12: Almacén General - Cuarentena | B12: Essentials | C12: Ropa Deportiva | D12: 32x32 | E12: Diana Navarro | H12: B25 WB MERCADO LIBRE | I12: {=_xlfn.XLOOKUP($H12,Criterios!$G$6:$G$200,Criterios!I$6:I$200,"")} | J12: {=_xlfn.XLOOKUP($H12,Criterios!$G$6:$G$200,Criterios!J$6:J$200,"")}
A13: Mesa de Empaque | B13: Colección Especial | C13: Ropa Interior | D13: 34x32 | E13: Pedro Gómez | H13: B25 WESTERN BROTHERS.MX | I13: {=_xlfn.XLOOKUP($H13,Criterios!$G$6:$G$200,Criterios!I$6:I$200,"")} | J13: {=_xlfn.XLOOKUP($H13,Criterios!$G$6:$G$200,Criterios!J$6:J$200,"")}
A14: Área de Devoluciones | B14: Edición Limitada | C14: Calcetería | D14: UNITALLA | E14: Laura Sánchez | H14: CAPSLAB Warehouse | I14: {=_xlfn.XLOOKUP($H14,Criterios!$G$6:$G$200,Criterios!I$6:I$200,"")} | J14: {=_xlfn.XLOOKUP($H14,Criterios!$G$6:$G$200,Criterios!J$6:J$200,"")}
A15: J1-L1-01 | B15: Stetson | C15: Jeans | D15: 29 x 32 | H15: CL Muestras | I15: {=_xlfn.XLOOKUP($H15,Criterios!$G$6:$G$200,Criterios!I$6:I$200,"")} | J15: {=_xlfn.XLOOKUP($H15,Criterios!$G$6:$G$200,Criterios!J$6:J$200,"")}
A16: Almacenes G1522 | B16: Ariat | C16: Denim | D16: 30 x 32 | H16: CL POS | I16: {=_xlfn.XLOOKUP($H16,Criterios!$G$6:$G$200,Criterios!I$6:I$200,"")} | J16: {=_xlfn.XLOOKUP($H16,Criterios!$G$6:$G$200,Criterios!J$6:J$200,"")}
A17: AMAZON | B17: CAPSLAB | C17: Ropa | D17: 31 x 32 | H17: CONSIGNA REFLO | I17: {=_xlfn.XLOOKUP($H17,Criterios!$G$6:$G$200,Criterios!I$6:I$200,"")} | J17: {=_xlfn.XLOOKUP($H17,Criterios!$G$6:$G$200,Criterios!J$6:J$200,"")}
A18: ARIAT CHIHUAHUA | B18: Denver | D18: 32 x 34 | H18: CONSIGNAS | I18: {=_xlfn.XLOOKUP($H18,Criterios!$G$6:$G$200,Criterios!I$6:I$200,"")} | J18: {=_xlfn.XLOOKUP($H18,Criterios!$G$6:$G$200,Criterios!J$6:J$200,"")}
A19: ARIAT OUTLET GDL | B19: Generico | D19: 33 x 32 | H19: DEPARTAMENTAL | I19: {=_xlfn.XLOOKUP($H19,Criterios!$G$6:$G$200,Criterios!I$6:I$200,"")} | J19: {=_xlfn.XLOOKUP($H19,Criterios!$G$6:$G$200,Criterios!J$6:J$200,"")}
A20: ARIAT PLAZA SAN LUIS | B20: Happy Socks | D20: 34 x 34 | H20: ECOMMERCE | I20: {=_xlfn.XLOOKUP($H20,Criterios!$G$6:$G$200,Criterios!I$6:I$200,"")} | J20: {=_xlfn.XLOOKUP($H20,Criterios!$G$6:$G$200,Criterios!J$6:J$200,"")}
A21: ARIAT SAN NICOLAS NL | B21: Montana West | D21: 34 x 36 | H21: ENGLISH REP | I21: {=_xlfn.XLOOKUP($H21,Criterios!$G$6:$G$200,Criterios!I$6:I$200,"")} | J21: {=_xlfn.XLOOKUP($H21,Criterios!$G$6:$G$200,Criterios!J$6:J$200,"")}
A22: B25 CEDIS | B22: REFLO | D22: 36 x 32 | H22: EVENTOS (CONSIGNA) | I22: {=_xlfn.XLOOKUP($H22,Criterios!$G$6:$G$200,Criterios!I$6:I$200,"")} | J22: {=_xlfn.XLOOKUP($H22,Criterios!$G$6:$G$200,Criterios!J$6:J$200,"")}
A23: B25 STETSON.MX | B23: Ranch & Corral | D23: 36 x 34 | H23: Fixtures & MKT | I23: {=_xlfn.XLOOKUP($H23,Criterios!$G$6:$G$200,Criterios!I$6:I$200,"")} | J23: {=_xlfn.XLOOKUP($H23,Criterios!$G$6:$G$200,Criterios!J$6:J$200,"")}
A24: B25 WB MERCADO LIBRE | B24: Tru Western | D24: 38 x 32 | H24: FULL MELI | I24: {=_xlfn.XLOOKUP($H24,Criterios!$G$6:$G$200,Criterios!I$6:I$200,"")} | J24: {=_xlfn.XLOOKUP($H24,Criterios!$G$6:$G$200,Criterios!J$6:J$200,"")}
A25: B25 WESTERN BROTHERS.MX | B25: Willow Lane | D25: 32 x 32 | H25: G1522 Defectos | I25: {=_xlfn.XLOOKUP($H25,Criterios!$G$6:$G$200,Criterios!I$6:I$200,"")} | J25: {=_xlfn.XLOOKUP($H25,Criterios!$G$6:$G$200,Criterios!J$6:J$200,"")}
A26: CAPSLAB Warehouse | B26: Wrangler | D26: 34 x 32 | H26: G1522 Lost | I26: {=_xlfn.XLOOKUP($H26,Criterios!$G$6:$G$200,Criterios!I$6:I$200,"")} | J26: {=_xlfn.XLOOKUP($H26,Criterios!$G$6:$G$200,Criterios!J$6:J$200,"")}
A27: CL Muestras | H27: G1522 QA Hold | I27: {=_xlfn.XLOOKUP($H27,Criterios!$G$6:$G$200,Criterios!I$6:I$200,"")} | J27: {=_xlfn.XLOOKUP($H27,Criterios!$G$6:$G$200,Criterios!J$6:J$200,"")}
A28: CL POS | H28: GENERAL | I28: {=_xlfn.XLOOKUP($H28,Criterios!$G$6:$G$200,Criterios!I$6:I$200,"")} | J28: {=_xlfn.XLOOKUP($H28,Criterios!$G$6:$G$200,Criterios!J$6:J$200,"")}
A29: CONSIGNA REFLO | H29: HAPPY SOCKS | I29: {=_xlfn.XLOOKUP($H29,Criterios!$G$6:$G$200,Criterios!I$6:I$200,"")} | J29: {=_xlfn.XLOOKUP($H29,Criterios!$G$6:$G$200,Criterios!J$6:J$200,"")}
A30: CONSIGNAS | H30: HS MERCADO LIBRE | I30: {=_xlfn.XLOOKUP($H30,Criterios!$G$6:$G$200,Criterios!I$6:I$200,"")} | J30: {=_xlfn.XLOOKUP($H30,Criterios!$G$6:$G$200,Criterios!J$6:J$200,"")}
A31: DEPARTAMENTAL | H31: KEY ACCOUNTS | I31: {=_xlfn.XLOOKUP($H31,Criterios!$G$6:$G$200,Criterios!I$6:I$200,"")} | J31: {=_xlfn.XLOOKUP($H31,Criterios!$G$6:$G$200,Criterios!J$6:J$200,"")}
A32: ECOMMERCE | H32: LIVERPOOL MKP | I32: {=_xlfn.XLOOKUP($H32,Criterios!$G$6:$G$200,Criterios!I$6:I$200,"")} | J32: {=_xlfn.XLOOKUP($H32,Criterios!$G$6:$G$200,Criterios!J$6:J$200,"")}
A33: ENGLISH REP | H33: Mercado libre | I33: {=_xlfn.XLOOKUP($H33,Criterios!$G$6:$G$200,Criterios!I$6:I$200,"")} | J33: {=_xlfn.XLOOKUP($H33,Criterios!$G$6:$G$200,Criterios!J$6:J$200,"")}
A34: EVENTOS (CONSIGNA) | H34: MUESTRAS & EXPO | I34: {=_xlfn.XLOOKUP($H34,Criterios!$G$6:$G$200,Criterios!I$6:I$200,"")} | J34: {=_xlfn.XLOOKUP($H34,Criterios!$G$6:$G$200,Criterios!J$6:J$200,"")}
A35: Fixtures & MKT | H35: MUESTRAS REFLO | I35: {=_xlfn.XLOOKUP($H35,Criterios!$G$6:$G$200,Criterios!I$6:I$200,"")} | J35: {=_xlfn.XLOOKUP($H35,Criterios!$G$6:$G$200,Criterios!J$6:J$200,"")}
A36: FULL MELI | H36: Nogales Store | I36: {=_xlfn.XLOOKUP($H36,Criterios!$G$6:$G$200,Criterios!I$6:I$200,"")} | J36: {=_xlfn.XLOOKUP($H36,Criterios!$G$6:$G$200,Criterios!J$6:J$200,"")}
A37: G1522 Defectos | H37: Plaza del Sol Store | I37: {=_xlfn.XLOOKUP($H37,Criterios!$G$6:$G$200,Criterios!I$6:I$200,"")} | J37: {=_xlfn.XLOOKUP($H37,Criterios!$G$6:$G$200,Criterios!J$6:J$200,"")}
A38: G1522 Lost | H38: POTRILLOS | I38: {=_xlfn.XLOOKUP($H38,Criterios!$G$6:$G$200,Criterios!I$6:I$200,"")} | J38: {=_xlfn.XLOOKUP($H38,Criterios!$G$6:$G$200,Criterios!J$6:J$200,"")}
... A52: PUNTO DE VENTA | H52: ZONA SUR | I52: {=_xlfn.XLOOKUP($H52,Criterios!$G$6:$G$200,Criterios!I$6:I$200,"")} | J52: {=_xlfn.XLOOKUP($H52,Criterios!$G$6:$G$200,Criterios!J$6:J$200,"")}
A53: Punto de venta HS
A54: REFLO ALMACEN
A55: STETSON AMERICAS
A56: The Hat Club
A57: VENTAS CAMPAÑA
A58: WB FORUM TLAQUEPAQUE
A59: WB OUTLET LERMA
A60: Web
A61: WEB
A62: ZONA NORTE
A63: ZONA POS
A64: ZONA SUR

Sheet Productos
A1: Código de barras | B1: Identificador interno | C1: Marca principal | D1: WB N.º de estilo | E1: WB SKU | F1: WB Talla | G1: WB Talla de EE. UU. | H1: WB Marca | I1: WB Descripcion | J1: WB División | K1: WB Categoría | L1: WB Género | M1: WB Licencia | N1: WB Temporada | O1: WB Ciclo de vida | P1: WB Color | Q1: WB Fit | R1: WB Silueta | S1: WB Composición | T1: WB Descripción larga | U1: WB País de origen | V1: Unidad | W1: SAT Clave de producto | X1: Enlace de imagen | Y1: Precio de compra | Z1: Precio de venta | AA1: Estatus de Validación | AB1: Detalle de Discrepancias | AC1: 🔍 Panel de Duplicados | AD1: Stock Sistema NetSuite | AE1: Ubicaciones con stock (NetSuite) | AF1: Disponible NetSuite | AG1: Origen del registro | AH1: Notas de enriquecimiento / revisión | AI1: ¿Alguna ubicación en negativo? | AJ1: Ubicaciones con existencia negativa | AK1: Fuentes de consulta | AL1: Precio compra vigente | AM1: Precio venta vigente | AN1: 📍 Ubicación en plataformas (Plataforma + Marca) | AO1: Stock Shopify Stetson México | AP1: Stock Shopify Western Brothers | AQ1: Stock Odoo Universal Unique Brands | AR1: Ubicaciones con stock (plataformas)
A2: 199168087517 | C2: Roper | D2: 01-001-0016-1076 | E2: 01-001-0016-1076 BL-2XL | F2: XXL | G2: XXL | H2: Roper | I2: ROPER Shirt Black/GreyWhite /Plaid | J2: Ropa | K2: Camisas | L2: Hombre | P2: Negro | V2: PZS | W2: 53101602 | Y2: 38 | Z2: 990 | AA2: =IF(AND(A2="", B2="", E2=""), "", IF(AB2="", "Válido", IF((LEN(AB2)-LEN(SUBSTITUTE(AB2,"; ","")))/2+1>(LEN(AB2)-LEN(SUBSTITUTE(AB2,"[Aviso]","")))/7, "Con Incidencias", "Válido"))) | AB2: =IF(AND(A2="", B2="", E2=""), "", TEXTJOIN("; ", TRUE, IF(OR(TRIM(A2&"")="", ISNUMBER(SEARCH("FALTA", A2))), "UPC faltante/inválido", ""), IF(AND(A2<>"", IFERROR(_xlfn.XMATCH(A2,$A$2:$A$285,0,1)<>_xlfn.XMATCH(A2,$A$2:$A$285,0,-1),FALSE)), "Código de barras duplicado", ""), IF(AND(E2<>"", COUNTIF($E$2:$E$285, E2)>1), "SKU duplicado", ""), IF(OR(J2="", J2=""), "[Aviso] División no capturada ()", IF(ISNA(MATCH(J2, Criterios!$A$123:$A$126, 0)), "División no válida", "")), IF(OR(K2="", K2=""), "[Aviso] Categoría no capturada ()", IF(ISNA(MATCH(K2, Criterios!$A$81:$A$120, 0)), "Categoría no válida", IF(AND(J2<>"", J2<>"", J2<>VLOOKUP(K2, Criterios!$A$81:$B$120, 2, FALSE)), "División no coincide con Categoría", ""))), IF(OR(L2="", L2=""), "[Aviso] Género no capturado ()", IF(ISNA(MATCH(L2, Criterios!$B$123:$B$127, 0)), "Género no válido", "")), IF(OR(N2="", N2=""), "[Aviso] Temporada no capturada ()", IF(ISNA(MATCH(N2, Criterios!$C$123:$C$128, 0)), "Temporada no válida", "")), IF(OR(O2="", O2=""), "[Aviso] Ciclo de vida no capturado ()", IF(ISNA(MATCH(O2, Criterios!$D$123:$D$124, 0)), "Ciclo de vida no válido", "")))) | AG2: Nuevo – Odoo Universal Unique Brands 01/10/2026 | AH2: 01/10/2026: alta desde Odoo Universal Unique Brands (no existía en Productos por código de barras ni SKU) | Categoría: Palabra clave "Camisa" en tipo/categoría de la fuente (Ropa / Camisas); Género: campo de la fuente; Color detectado en el nombre (black) | Homologación G1522 06/10/2026: WB N.º de estilo: «» → «01-001-0016-1076» (Completado por regla) · Validador Shopify: WB: precio con IVA no termina en 9 | AK2: Odoo: producto 20856 / plantilla 26859 | AN2: Odoo Universal Unique Brands | AQ2: 10 | AR2: Odoo Universal Unique Brands › Bodega 25 › Bodega 25/General: 10
A3: 199168087470 | C3: Roper | D3: 01-001-0016-1076 | E3: 01-001-0016-1076 BL-L | F3: L | G3: L | H3: Roper | I3: ROPER Shirt Black/GreyWhite /Plaid | J3: Ropa | K3: Camisas | L3: Hombre | P3: Negro | V3: PZS | W3: 53101602 | Y3: 38 | Z3: 990 | AA3: =IF(AND(A3="", B3="", E3=""), "", IF(AB3="", "Válido", IF((LEN(AB3)-LEN(SUBSTITUTE(AB3,"; ","")))/2+1>(LEN(AB3)-LEN(SUBSTITUTE(AB3,"[Aviso]","")))/7, "Con Incidencias", "Válido"))) | AB3: =IF(AND(A3="", B3="", E3=""), "", TEXTJOIN("; ", TRUE, IF(OR(TRIM(A3&"")="", ISNUMBER(SEARCH("FALTA", A3))), "UPC faltante/inválido", ""), IF(AND(A3<>"", IFERROR(_xlfn.XMATCH(A3,$A$2:$A$285,0,1)<>_xlfn.XMATCH(A3,$A$2:$A$285,0,-1),FALSE)), "Código de barras duplicado", ""), IF(AND(E3<>"", COUNTIF($E$2:$E$285, E3)>1), "SKU duplicado", ""), IF(OR(J3="", J3=""), "[Aviso] División no capturada ()", IF(ISNA(MATCH(J3, Criterios!$A$123:$A$126, 0)), "División no válida", "")), IF(OR(K3="", K3=""), "[Aviso] Categoría no capturada ()", IF(ISNA(MATCH(K3, Criterios!$A$81:$A$120, 0)), "Categoría no válida", IF(AND(J3<>"", J3<>"", J3<>VLOOKUP(K3, Criterios!$A$81:$B$120, 2, FALSE)), "División no coincide con Categoría", ""))), IF(OR(L3="", L3=""), "[Aviso] Género no capturado ()", IF(ISNA(MATCH(L3, Criterios!$B$123:$B$127, 0)), "Género no válido", "")), IF(OR(N3="", N3=""), "[Aviso] Temporada no capturada ()", IF(ISNA(MATCH(N3, Criterios!$C$123:$C$128, 0)), "Temporada no válida", "")), IF(OR(O3="", O3=""), "[Aviso] Ciclo de vida no capturado ()", IF(ISNA(MATCH(O3, Criterios!$D$123:$D$124, 0)), "Ciclo de vida no válido", "")))) | AG3: Nuevo – Odoo Universal Unique Brands 01/10/2026 | AH3: 01/10/2026: alta desde Odoo Universal Unique Brands (no existía en Productos por código de barras ni SKU) | Categoría: Palabra clave "Camisa" en tipo/categoría de la fuente (Ropa / Camisas); Género: campo de la fuente; Color detectado en el nombre (black) | Homologación G1522 06/10/2026: WB N.º de estilo: «» → «01-001-0016-1076» (Completado por regla) · Validador Shopify: WB: precio con IVA no termina en 9 | AK3: Odoo: producto 20854 / plantilla 26857 | AN3: Odoo Universal Unique Brands | AQ3: 30 | AR3: Odoo Universal Unique Brands › Bodega 25 › Bodega 25/General: 30
A4: 199168087487 | C4: Roper | D4: 01-001-0016-1076 | E4: 01-001-0016-1076 BL-M | F4: M | G4: M | H4: Roper | I4: ROPER Shirt Black/GreyWhite /Plaid | J4: Ropa | K4: Camisas | L4: Hombre | P4: Negro | V4: PZS | W4: 53101602 | Y4: 38 | Z4: 990 | AA4: =IF(AND(A4="", B4="", E4=""), "", IF(AB4="", "Válido", IF((LEN(AB4)-LEN(SUBSTITUTE(AB4,"; ","")))/2+1>(LEN(AB4)-LEN(SUBSTITUTE(AB4,"[Aviso]","")))/7, "Con Incidencias", "Válido"))) | AB4: =IF(AND(A4="", B4="", E4=""), "", TEXTJOIN("; ", TRUE, IF(OR(TRIM(A4&"")="", ISNUMBER(SEARCH("FALTA", A4))), "UPC faltante/inválido", ""), IF(AND(A4<>"", IFERROR(_xlfn.XMATCH(A4,$A$2:$A$285,0,1)<>_xlfn.XMATCH(A4,$A$2:$A$285,0,-1),FALSE)), "Código de barras duplicado", ""), IF(AND(E4<>"", COUNTIF($E$2:$E$285, E4)>1), "SKU duplicado", ""), IF(OR(J4="", J4=""), "[Aviso] División no capturada ()", IF(ISNA(MATCH(J4, Criterios!$A$123:$A$126, 0)), "División no válida", "")), IF(OR(K4="", K4=""), "[Aviso] Categoría no capturada ()", IF(ISNA(MATCH(K4, Criterios!$A$81:$A$120, 0)), "Categoría no válida", IF(AND(J4<>"", J4<>"", J4<>VLOOKUP(K4, Criterios!$A$81:$B$120, 2, FALSE)), "División no coincide con Categoría", ""))), IF(OR(L4="", L4=""), "[Aviso] Género no capturado ()", IF(ISNA(MATCH(L4, Criterios!$B$123:$B$127, 0)), "Género no válido", "")), IF(OR(N4="", N4=""), "[Aviso] Temporada no capturada ()", IF(ISNA(MATCH(N4, Criterios!$C$123:$C$128, 0)), "Temporada no válida", "")), IF(OR(O4="", O4=""), "[Aviso] Ciclo de vida no capturado ()", IF(ISNA(MATCH(O4, Criterios!$D$123:$D$124, 0)), "Ciclo de vida no válido", "")))) | AG4: Nuevo – Odoo Universal Unique Brands 01/10/2026 | AH4: 01/10/2026: alta desde Odoo Universal Unique Brands (no existía en Productos por código de barras ni SKU) | Categoría: Palabra clave "Camisa" en tipo/categoría de la fuente (Ropa / Camisas); Género: campo de la fuente; Color detectado en el nombre (black) | Homologación G1522 06/10/2026: WB N.º de estilo: «» → «01-001-0016-1076» (Completado por regla) · Validador Shopify: WB: precio con IVA no termina en 9 | AK4: Odoo: producto 20853 / plantilla 26856 | AN4: Odoo Universal Unique Brands | AQ4: 30 | AR4: Odoo Universal Unique Brands › Bodega 25 › Bodega 25/General: 30
A5: 199168087494 | C5: Roper | D5: 01-001-0016-1076 | E5: 01-001-0016-1076 BL-S | F5: S | G5: S | H5: Roper | I5: ROPER Shirt Black/GreyWhite /Plaid | J5: Ropa | K5: Camisas | P5: Negro | V5: PZS | W5: 53101602 | Y5: 38 | Z5: 990 | AA5: =IF(AND(A5="", B5="", E5=""), "", IF(AB5="", "Válido", IF((LEN(AB5)-LEN(SUBSTITUTE(AB5,"; ","")))/2+1>(LEN(AB5)-LEN(SUBSTITUTE(AB5,"[Aviso]","")))/7, "Con Incidencias", "Válido"))) | AB5: =IF(AND(A5="", B5="", E5=""), "", TEXTJOIN("; ", TRUE, IF(OR(TRIM(A5&"")="", ISNUMBER(SEARCH("FALTA", A5))), "UPC faltante/inválido", ""), IF(AND(A5<>"", IFERROR(_xlfn.XMATCH(A5,$A$2:$A$285,0,1)<>_xlfn.XMATCH(A5,$A$2:$A$285,0,-1),FALSE)), "Código de barras duplicado", ""), IF(AND(E5<>"", COUNTIF($E$2:$E$285, E5)>1), "SKU duplicado", ""), IF(OR(J5="", J5=""), "[Aviso] División no capturada ()", IF(ISNA(MATCH(J5, Criterios!$A$123:$A$126, 0)), "División no válida", "")), IF(OR(K5="", K5=""), "[Aviso] Categoría no capturada ()", IF(ISNA(MATCH(K5, Criterios!$A$81:$A$120, 0)), "Categoría no válida", IF(AND(J5<>"", J5<>"", J5<>VLOOKUP(K5, Criterios!$A$81:$B$120, 2, FALSE)), "División no coincide con Categoría", ""))), IF(OR(L5="", L5=""), "[Aviso] Género no capturado ()", IF(ISNA(MATCH(L5, Criterios!$B$123:$B$127, 0)), "Género no válido", "")), IF(OR(N5="", N5=""), "[Aviso] Temporada no capturada ()", IF(ISNA(MATCH(N5, Criterios!$C$123:$C$128, 0)), "Temporada no válida", "")), IF(OR(O5="", O5=""), "[Aviso] Ciclo de vida no capturado ()", IF(ISNA(MATCH(O5, Criterios!$D$123:$D$124, 0)), "Ciclo de vida no válido", "")))) | AG5: Nuevo – Odoo Universal Unique Brands 01/10/2026 | AH5: 01/10/2026: alta desde Odoo Universal Unique Brands (no existía en Productos por código de barras ni SKU) | Talla tomada del sufijo del SKU (S); Categoría: Palabra clave "Camisa" en tipo/categoría de la fuente (Ropa / Camisas); Color detectado en el nombre (black) | Homologación G1522 06/10/2026: WB N.º de estilo: «» → «01-001-0016-1076» (Completado por regla) · Validador Shopify: WB: precio con IVA no termina en 9 | AK5: Odoo: producto 20852 / plantilla 26855 | AN5: Odoo Universal Unique Brands | AQ5: 30 | AR5: Odoo Universal Unique Brands › Bodega 25 › Bodega 25/General: 30
A6: 199168087500 | C6: Roper | D6: 01-001-0016-1076 | E6: 01-001-0016-1076 BL-XL | F6: XL | G6: XL | H6: Roper | I6: ROPER Shirt Black/GreyWhite /Plaid | J6: Ropa | K6: Camisas | L6: Hombre | P6: Negro | V6: PZS | W6: 53101602 | Y6: 38 | Z6: 990 | AA6: =IF(AND(A6="", B6="", E6=""), "", IF(AB6="", "Válido", IF((LEN(AB6)-LEN(SUBSTITUTE(AB6,"; ","")))/2+1>(LEN(AB6)-LEN(SUBSTITUTE(AB6,"[Aviso]","")))/7, "Con Incidencias", "Válido"))) | AB6: =IF(AND(A6="", B6="", E6=""), "", TEXTJOIN("; ", TRUE, IF(OR(TRIM(A6&"")="", ISNUMBER(SEARCH("FALTA", A6))), "UPC faltante/inválido", ""), IF(AND(A6<>"", IFERROR(_xlfn.XMATCH(A6,$A$2:$A$285,0,1)<>_xlfn.XMATCH(A6,$A$2:$A$285,0,-1),FALSE)), "Código de barras duplicado", ""), IF(AND(E6<>"", COUNTIF($E$2:$E$285, E6)>1), "SKU duplicado", ""), IF(OR(J6="", J6=""), "[Aviso] División no capturada ()", IF(ISNA(MATCH(J6, Criterios!$A$123:$A$126, 0)), "División no válida", "")), IF(OR(K6="", K6=""), "[Aviso] Categoría no capturada ()", IF(ISNA(MATCH(K6, Criterios!$A$81:$A$120, 0)), "Categoría no válida", IF(AND(J6<>"", J6<>"", J6<>VLOOKUP(K6, Criterios!$A$81:$B$120, 2, FALSE)), "División no coincide con Categoría", ""))), IF(OR(L6="", L6=""), "[Aviso] Género no capturado ()", IF(ISNA(MATCH(L6, Criterios!$B$123:$B$127, 0)), "Género no válido", "")), IF(OR(N6="", N6=""), "[Aviso] Temporada no capturada ()", IF(ISNA(MATCH(N6, Criterios!$C$123:$C$128, 0)), "Temporada no válida", "")), IF(OR(O6="", O6=""), "[Aviso] Ciclo de vida no capturado ()", IF(ISNA(MATCH(O6, Criterios!$D$123:$D$124, 0)), "Ciclo de vida no válido", "")))) | AG6: Nuevo – Odoo Universal Unique Brands 01/10/2026 | AH6: 01/10/2026: alta desde Odoo Universal Unique Brands (no existía en Productos por código de barras ni SKU) | Categoría: Palabra clave "Camisa" en tipo/categoría de la fuente (Ropa / Camisas); Género: campo de la fuente; Color detectado en el nombre (black) | Homologación G1522 06/10/2026: WB N.º de estilo: «» → «01-001-0016-1076» (Completado por regla) · Validador Shopify: WB: precio con IVA no termina en 9 | AK6: Odoo: producto 20855 / plantilla 26858 | AN6: Odoo Universal Unique Brands | AQ6: 20 | AR6: Odoo Universal Unique Brands › Bodega 25 › Bodega 25/General: 20
A7: 199168041441 | C7: Roper | D7: 01-001-0016-7004 | E7: 01-001-0016-7004 BL-2XL | F7: XXL | G7: XXL | H7: Roper | I7: ROPER Shirt Bl/Wh/Re Plaid | J7: Ropa | K7: Camisas | V7: PZS | W7: 53101602 | Y7: 32.09 | Z7: 859 | AA7: =IF(AND(A7="", B7="", E7=""), "", IF(AB7="", "Válido", IF((LEN(AB7)-LEN(SUBSTITUTE(AB7,"; ","")))/2+1>(LEN(AB7)-LEN(SUBSTITUTE(AB7,"[Aviso]","")))/7, "Con Incidencias", "Válido"))) | AB7: =IF(AND(A7="", B7="", E7=""), "", TEXTJOIN("; ", TRUE, IF(OR(TRIM(A7&"")="", ISNUMBER(SEARCH("FALTA", A7))), "UPC faltante/inválido", ""), IF(AND(A7<>"", IFERROR(_xlfn.XMATCH(A7,$A$2:$A$285,0,1)<>_xlfn.XMATCH(A7,$A$2:$A$285,0,-1),FALSE)), "Código de barras duplicado", ""), IF(AND(E7<>"", COUNTIF($E$2:$E$285, E7)>1), "SKU duplicado", ""), IF(OR(J7="", J7=""), "[Aviso] División no capturada ()", IF(ISNA(MATCH(J7, Criterios!$A$123:$A$126, 0)), "División no válida", "")), IF(OR(K7="", K7=""), "[Aviso] Categoría no capturada ()", IF(ISNA(MATCH(K7, Criterios!$A$81:$A$120, 0)), "Categoría no válida", IF(AND(J7<>"", J7<>"", J7<>VLOOKUP(K7, Criterios!$A$81:$B$120, 2, FALSE)), "División no coincide con Categoría", ""))), IF(OR(L7="", L7=""), "[Aviso] Género no capturado ()", IF(ISNA(MATCH(L7, Criterios!$B$123:$B$127, 0)), "Género no válido", "")), IF(OR(N7="", N7=""), "[Aviso] Temporada no capturada ()", IF(ISNA(MATCH(N7, Criterios!$C$123:$C$128, 0)), "Temporada no válida", "")), IF(OR(O7="", O7=""), "[Aviso] Ciclo de vida no capturado ()", IF(ISNA(MATCH(O7, Criterios!$D$123:$D$124, 0)), "Ciclo de vida no válido", "")))) | AG7: Nuevo – Odoo Universal Unique Brands 01/10/2026 | AH7: 01/10/2026: alta desde Odoo Universal Unique Brands (no existía en Productos por código de barras ni SKU) | Talla tomada del sufijo del SKU (2XL); Categoría: Palabra clave "Camisa" en tipo/categoría de la fuente (Ropa / Camisas); Talla: 2XL→XXL | Homologación G1522 06/10/2026: WB N.º de estilo: «» → «01-001-0016-7004» (Completado por regla) · Validador Shopify: WB: precio con IVA no termina en 9 | AK7: Odoo: producto 21093 / plantilla 27096 | AN7: Odoo Universal Unique Brands | AQ7: 2 | AR7: Odoo Universal Unique Brands › Bodega 25 › Bodega 25/General: 2
A8: 199168041458 | C8: Roper | D8: 01-001-0016-7004 | E8: 01-001-0016-7004 BL-3XL | F8: XXXL | G8: XXXL | H8: Roper | I8: ROPER Shirt Bl/Wh/Re Plaid | J8: Ropa | K8: Camisas | V8: PZS | W8: 53101602 | Y8: 32.09 | Z8: 859 | AA8: =IF(AND(A8="", B8="", E8=""), "", IF(AB8="", "Válido", IF((LEN(AB8)-LEN(SUBSTITUTE(AB8,"; ","")))/2+1>(LEN(AB8)-LEN(SUBSTITUTE(AB8,"[Aviso]","")))/7, "Con Incidencias", "Válido"))) | AB8: =IF(AND(A8="", B8="", E8=""), "", TEXTJOIN("; ", TRUE, IF(OR(TRIM(A8&"")="", ISNUMBER(SEARCH("FALTA", A8))), "UPC faltante/inválido", ""), IF(AND(A8<>"", IFERROR(_xlfn.XMATCH(A8,$A$2:$A$285,0,1)<>_xlfn.XMATCH(A8,$A$2:$A$285,0,-1),FALSE)), "Código de barras duplicado", ""), IF(AND(E8<>"", COUNTIF($E$2:$E$285, E8)>1), "SKU duplicado", ""), IF(OR(J8="", J8=""), "[Aviso] División no capturada ()", IF(ISNA(MATCH(J8, Criterios!$A$123:$A$126, 0)), "División no válida", "")), IF(OR(K8="", K8=""), "[Aviso] Categoría no capturada ()", IF(ISNA(MATCH(K8, Criterios!$A$81:$A$120, 0)), "Categoría no válida", IF(AND(J8<>"", J8<>"", J8<>VLOOKUP(K8, Criterios!$A$81:$B$120, 2, FALSE)), "División no coincide con Categoría", ""))), IF(OR(L8="", L8=""), "[Aviso] Género no capturado ()", IF(ISNA(MATCH(L8, Criterios!$B$123:$B$127, 0)), "Género no válido", "")), IF(OR(N8="", N8=""), "[Aviso] Temporada no capturada ()", IF(ISNA(MATCH(N8, Criterios!$C$123:$C$128, 0)), "Temporada no válida", "")), IF(OR(O8="", O8=""), "[Aviso] Ciclo de vida no capturado ()", IF(ISNA(MATCH(O8, Criterios!$D$123:$D$124, 0)), "Ciclo de vida no válido", "")))) | AG8: Nuevo – Odoo Universal Unique Brands 01/10/2026 | AH8: 01/10/2026: alta desde Odoo Universal Unique Brands (no existía en Productos por código de barras ni SKU) | Talla tomada del sufijo del SKU (3XL); Categoría: Palabra clave "Camisa" en tipo/categoría de la fuente (Ropa / Camisas); Talla: 3XL→XXXL | Homologación G1522 06/10/2026: WB N.º de estilo: «» → «01-001-0016-7004» (Completado por regla) · Validador Shopify: WB: precio con IVA no termina en 9 | AK8: Odoo: producto 21572 / plantilla 27583 | AN8: Odoo Universal Unique Brands | AQ8: 1 | AR8: Odoo Universal Unique Brands › Bodega 25 › Bodega 25/General: 1
A9: 199168041403 | C9: Roper | D9: 01-001-0016-7004 | E9: 01-001-0016-7004 BL-L | F9: L | G9: L | H9: Roper | I9: ROPER Shirt Bl/Wh/Re Plaid | J9: Ropa | K9: Camisas | V9: PZS | W9: 53101602 | Y9: 32.09 | Z9: 859 | AA9: =IF(AND(A9="", B9="", E9=""), "", IF(AB9="", "Válido", IF((LEN(AB9)-LEN(SUBSTITUTE(AB9,"; ","")))/2+1>(LEN(AB9)-LEN(SUBSTITUTE(AB9,"[Aviso]","")))/7, "Con Incidencias", "Válido"))) | AB9: =IF(AND(A9="", B9="", E9=""), "", TEXTJOIN("; ", TRUE, IF(OR(TRIM(A9&"")="", ISNUMBER(SEARCH("FALTA", A9))), "UPC faltante/inválido", ""), IF(AND(A9<>"", IFERROR(_xlfn.XMATCH(A9,$A$2:$A$285,0,1)<>_xlfn.XMATCH(A9,$A$2:$A$285,0,-1),FALSE)), "Código de barras duplicado", ""), IF(AND(E9<>"", COUNTIF($E$2:$E$285, E9)>1), "SKU duplicado", ""), IF(OR(J9="", J9=""), "[Aviso] División no capturada ()", IF(ISNA(MATCH(J9, Criterios!$A$123:$A$126, 0)), "División no válida", "")), IF(OR(K9="", K9=""), "[Aviso] Categoría no capturada ()", IF(ISNA(MATCH(K9, Criterios!$A$81:$A$120, 0)), "Categoría no válida", IF(AND(J9<>"", J9<>"", J9<>VLOOKUP(K9, Criterios!$A$81:$B$120, 2, FALSE)), "División no coincide con Categoría", ""))), IF(OR(L9="", L9=""), "[Aviso] Género no capturado ()", IF(ISNA(MATCH(L9, Criterios!$B$123:$B$127, 0)), "Género no válido", "")), IF(OR(N9="", N9=""), "[Aviso] Temporada no capturada ()", IF(ISNA(MATCH(N9, Criterios!$C$123:$C$128, 0)), "Temporada no válida", "")), IF(OR(O9="", O9=""), "[Aviso] Ciclo de vida no capturado ()", IF(ISNA(MATCH(O9, Criterios!$D$123:$D$124, 0)), "Ciclo de vida no válido", "")))) | AG9: Nuevo – Odoo Universal Unique Brands 01/10/2026 | AH9: 01/10/2026: alta desde Odoo Universal Unique Brands (no existía en Productos por código de barras ni SKU) | Talla tomada del sufijo del SKU (L); Categoría: Palabra clave "Camisa" en tipo/categoría de la fuente (Ropa / Camisas) | Homologación G1522 06/10/2026: WB N.º de estilo: «» → «01-001-0016-7004» (Completado por regla) · Validador Shopify: WB: precio con IVA no termina en 9 | AK9: Odoo: producto 21091 / plantilla 27094 | AN9: Odoo Universal Unique Brands | AQ9: 10 | AR9: Odoo Universal Unique Brands › Bodega 25 › Bodega 25/General: 10
A10: 199168041410 | C10: Roper | D10: 01-001-0016-7004 | E10: 01-001-0016-7004 BL-M | F10: M | G10: M | H10: Roper | I10: ROPER Shirt Bl/Wh/Re Plaid | J10: Ropa | K10: Camisas | V10: PZS | W10: 53101602 | Y10: 32.09 | Z10: 859 | AA10: =IF(AND(A10="", B10="", E10=""), "", IF(AB10="", "Válido", IF((LEN(AB10)-LEN(SUBSTITUTE(AB10,"; ","")))/2+1>(LEN(AB10)-LEN(SUBSTITUTE(AB10,"[Aviso]","")))/7, "Con Incidencias", "Válido"))) | AB10: =IF(AND(A10="", B10="", E10=""), "", TEXTJOIN("; ", TRUE, IF(OR(TRIM(A10&"")="", ISNUMBER(SEARCH("FALTA", A10))), "UPC faltante/inválido", ""), IF(AND(A10<>"", IFERROR(_xlfn.XMATCH(A10,$A$2:$A$285,0,1)<>_xlfn.XMATCH(A10,$A$2:$A$285,0,-1),FALSE)), "Código de barras duplicado", ""), IF(AND(E10<>"", COUNTIF($E$2:$E$285, E10)>1), "SKU duplicado", ""), IF(OR(J10="", J10=""), "[Aviso] División no capturada ()", IF(ISNA(MATCH(J10, Criterios!$A$123:$A$126, 0)), "División no válida", "")), IF(OR(K10="", K10=""), "[Aviso] Categoría no capturada ()", IF(ISNA(MATCH(K10, Criterios!$A$81:$A$120, 0)), "Categoría no válida", IF(AND(J10<>"", J10<>"", J10<>VLOOKUP(K10, Criterios!$A$81:$B$120, 2, FALSE)), "División no coincide con Categoría", ""))), IF(OR(L10="", L10=""), "[Aviso] Género no capturado ()", IF(ISNA(MATCH(L10, Criterios!$B$123:$B$127, 0)), "Género no válido", "")), IF(OR(N10="", N10=""), "[Aviso] Temporada no capturada ()", IF(ISNA(MATCH(N10, Criterios!$C$123:$C$128, 0)), "Temporada no válida", "")), IF(OR(O10="", O10=""), "[Aviso] Ciclo de vida no capturado ()", IF(ISNA(MATCH(O10, Criterios!$D$123:$D$124, 0)), "Ciclo de vida no válido", "")))) | AG10: Nuevo – Odoo Universal Unique Brands 01/10/2026 | AH10: 01/10/2026: alta desde Odoo Universal Unique Brands (no existía en Productos por código de barras ni SKU) | Talla tomada del sufijo del SKU (M); Categoría: Palabra clave "Camisa" en tipo/categoría de la fuente (Ropa / Camisas) | Homologación G1522 06/10/2026: WB N.º de estilo: «» → «01-001-0016-7004» (Completado por regla) · Validador Shopify: WB: precio con IVA no termina en 9 | AK10: Odoo: producto 21090 / plantilla 27093 | AN10: Odoo Universal Unique Brands | AQ10: 10 | AR10: Odoo Universal Unique Brands › Bodega 25 › Bodega 25/General: 10
A11: 199168041427 | C11: Roper | D11: 01-001-0016-7004 | E11: 01-001-0016-7004 BL-S | F11: S | G11: S | H11: Roper | I11: ROPER Shirt Bl/Wh/Re Plaid | J11: Ropa | K11: Camisas | V11: PZS | W11: 53101602 | Y11: 32.09 | Z11: 859 | AA11: =IF(AND(A11="", B11="", E11=""), "", IF(AB11="", "Válido", IF((LEN(AB11)-LEN(SUBSTITUTE(AB11,"; ","")))/2+1>(LEN(AB11)-LEN(SUBSTITUTE(AB11,"[Aviso]","")))/7, "Con Incidencias", "Válido"))) | AB11: =IF(AND(A11="", B11="", E11=""), "", TEXTJOIN("; ", TRUE, IF(OR(TRIM(A11&"")="", ISNUMBER(SEARCH("FALTA", A11))), "UPC faltante/inválido", ""), IF(AND(A11<>"", IFERROR(_xlfn.XMATCH(A11,$A$2:$A$285,0,1)<>_xlfn.XMATCH(A11,$A$2:$A$285,0,-1),FALSE)), "Código de barras duplicado", ""), IF(AND(E11<>"", COUNTIF($E$2:$E$285, E11)>1), "SKU duplicado", ""), IF(OR(J11="", J11=""), "[Aviso] División no capturada ()", IF(ISNA(MATCH(J11, Criterios!$A$123:$A$126, 0)), "División no válida", "")), IF(OR(K11="", K11=""), "[Aviso] Categoría no capturada ()", IF(ISNA(MATCH(K11, Criterios!$A$81:$A$120, 0)), "Categoría no válida", IF(AND(J11<>"", J11<>"", J11<>VLOOKUP(K11, Criterios!$A$81:$B$120, 2, FALSE)), "División no coincide con Categoría", ""))), IF(OR(L11="", L11=""), "[Aviso] Género no capturado ()", IF(ISNA(MATCH(L11, Criterios!$B$123:$B$127, 0)), "Género no válido", "")), IF(OR(N11="", N11=""), "[Aviso] Temporada no capturada ()", IF(ISNA(MATCH(N11, Criterios!$C$123:$C$128, 0)), "Temporada no válida", "")), IF(OR(O11="", O11=""), "[Aviso] Ciclo de vida no capturado ()", IF(ISNA(MATCH(O11, Criterios!$D$123:$D$124, 0)), "Ciclo de vida no válido", "")))) | AG11: Nuevo – Odoo Universal Unique Brands 01/10/2026 | AH11: 01/10/2026: alta desde Odoo Universal Unique Brands (no existía en Productos por código de barras ni SKU) | Talla tomada del sufijo del SKU (S); Categoría: Palabra clave "Camisa" en tipo/categoría de la fuente (Ropa / Camisas) | Homologación G1522 06/10/2026: WB N.º de estilo: «» → «01-001-0016-7004» (Completado por regla) · Validador Shopify: WB: precio con IVA no termina en 9 | AK11: Odoo: producto 21089 / plantilla 27092 | AN11: Odoo Universal Unique Brands | AQ11: 10 | AR11: Odoo Universal Unique Brands › Bodega 25 › Bodega 25/General: 10
A12: 199168041434 | C12: Roper | D12: 01-001-0016-7004 | E12: 01-001-0016-7004 BL-XL | F12: XL | G12: XL | H12: Roper | I12: ROPER Shirt Bl/Wh/Re Plaid | J12: Ropa | K12: Camisas | V12: PZS | W12: 53101602 | Y12: 32.09 | Z12: 859 | AA12: =IF(AND(A12="", B12="", E12=""), "", IF(AB12="", "Válido", IF((LEN(AB12)-LEN(SUBSTITUTE(AB12,"; ","")))/2+1>(LEN(AB12)-LEN(SUBSTITUTE(AB12,"[Aviso]","")))/7, "Con Incidencias", "Válido"))) | AB12: =IF(AND(A12="", B12="", E12=""), "", TEXTJOIN("; ", TRUE, IF(OR(TRIM(A12&"")="", ISNUMBER(SEARCH("FALTA", A12))), "UPC faltante/inválido", ""), IF(AND(A12<>"", IFERROR(_xlfn.XMATCH(A12,$A$2:$A$285,0,1)<>_xlfn.XMATCH(A12,$A$2:$A$285,0,-1),FALSE)), "Código de barras duplicado", ""), IF(AND(E12<>"", COUNTIF($E$2:$E$285, E12)>1), "SKU duplicado", ""), IF(OR(J12="", J12=""), "[Aviso] División no capturada ()", IF(ISNA(MATCH(J12, Criterios!$A$123:$A$126, 0)), "División no válida", "")), IF(OR(K12="", K12=""), "[Aviso] Categoría no capturada ()", IF(ISNA(MATCH(K12, Criterios!$A$81:$A$120, 0)), "Categoría no válida", IF(AND(J12<>"", J12<>"", J12<>VLOOKUP(K12, Criterios!$A$81:$B$120, 2, FALSE)), "División no coincide con Categoría", ""))), IF(OR(L12="", L12=""), "[Aviso] Género no capturado ()", IF(ISNA(MATCH(L12, Criterios!$B$123:$B$127, 0)), "Género no válido", "")), IF(OR(N12="", N12=""), "[Aviso] Temporada no capturada ()", IF(ISNA(MATCH(N12, Criterios!$C$123:$C$128, 0)), "Temporada no válida", "")), IF(OR(O12="", O12=""), "[Aviso] Ciclo de vida no capturado ()", IF(ISNA(MATCH(O12, Criterios!$D$123:$D$124, 0)), "Ciclo de vida no válido", "")))) | AG12: Nuevo – Odoo Universal Unique Brands 01/10/2026 | AH12: 01/10/2026: alta desde Odoo Universal Unique Brands (no existía en Productos por código de barras ni SKU) | Talla tomada del sufijo del SKU (XL); Categoría: Palabra clave "Camisa" en tipo/categoría de la fuente (Ropa / Camisas) | Homologación G1522 06/10/2026: WB N.º de estilo: «» → «01-001-0016-7004» (Completado por regla) · Validador Shopify: WB: precio con IVA no termina en 9 | AK12: Odoo: producto 21092 / plantilla 27095 | AN12: Odoo Universal Unique Brands | AQ12: 11 | AR12: Odoo Universal Unique Brands › Bodega 25 › Bodega 25/General: 11
A13: 199168041625 | C13: Roper | D13: 01-001-0017-7018 | E13: 01-001-0017-7018 BR-2XL | F13: XXL | G13: XXL | H13: Roper | I13: ROPER Shirt Chocolate Solid Poplin | J13: Ropa | K13: Camisas | P13: Cafe | V13: PZS | W13: 53101602 | Y13: 33.02 | Z13: 879 | AA13: =IF(AND(A13="", B13="", E13=""), "", IF(AB13="", "Válido", IF((LEN(AB13)-LEN(SUBSTITUTE(AB13,"; ","")))/2+1>(LEN(AB13)-LEN(SUBSTITUTE(AB13,"[Aviso]","")))/7, "Con Incidencias", "Válido"))) | AB13: =IF(AND(A13="", B13="", E13=""), "", TEXTJOIN("; ", TRUE, IF(OR(TRIM(A13&"")="", ISNUMBER(SEARCH("FALTA", A13))), "UPC faltante/inválido", ""), IF(AND(A13<>"", IFERROR(_xlfn.XMATCH(A13,$A$2:$A$285,0,1)<>_xlfn.XMATCH(A13,$A$2:$A$285,0,-1),FALSE)), "Código de barras duplicado", ""), IF(AND(E13<>"", COUNTIF($E$2:$E$285, E13)>1), "SKU duplicado", ""), IF(OR(J13="", J13=""), "[Aviso] División no capturada ()", IF(ISNA(MATCH(J13, Criterios!$A$123:$A$126, 0)), "División no válida", "")), IF(OR(K13="", K13=""), "[Aviso] Categoría no capturada ()", IF(ISNA(MATCH(K13, Criterios!$A$81:$A$120, 0)), "Categoría no válida", IF(AND(J13<>"", J13<>"", J13<>VLOOKUP(K13, Criterios!$A$81:$B$120, 2, FALSE)), "División no coincide con Categoría", ""))), IF(OR(L13="", L13=""), "[Aviso] Género no capturado ()", IF(ISNA(MATCH(L13, Criterios!$B$123:$B$127, 0)), "Género no válido", "")), IF(OR(N13="", N13=""), "[Aviso] Temporada no capturada ()", IF(ISNA(MATCH(N13, Criterios!$C$123:$C$128, 0)), "Temporada no válida", "")), IF(OR(O13="", O13=""), "[Aviso] Ciclo de vida no capturado ()", IF(ISNA(MATCH(O13, Criterios!$D$123:$D$124, 0)), "Ciclo de vida no válido", "")))) | AG13: Nuevo – Odoo Universal Unique Brands 01/10/2026 | AH13: 01/10/2026: alta desde Odoo Universal Unique Brands (no existía en Productos por código de barras ni SKU) | Talla tomada del sufijo del SKU (2XL); Categoría: Palabra clave "Camisa" en tipo/categoría de la fuente (Ropa / Camisas); Talla: 2XL→XXL; Color detectado en el nombre (chocolate) | Homologación G1522 06/10/2026: WB N.º de estilo: «» → «01-001-0017-7018» (Completado por regla) | AK13: Odoo: producto 21103 / plantilla 27106 | AN13: Odoo Universal Unique Brands | AQ13: 4 | AR13: Odoo Universal Unique Brands › Bodega 25 › Bodega 25/General: 4
A14: 199168041588 | C14: Roper | D14: 01-001-0017-7018 | E14: 01-001-0017-7018 BR-L | F14: L | G14: L | H14: Roper | I14: ROPER Shirt Chocolate Solid Poplin | J14: Ropa | K14: Camisas | P14: Cafe | V14: PZS | W14: 53101602 | Y14: 33.02 | Z14: 879 | AA14: =IF(AND(A14="", B14="", E14=""), "", IF(AB14="", "Válido", IF((LEN(AB14)-LEN(SUBSTITUTE(AB14,"; ","")))/2+1>(LEN(AB14)-LEN(SUBSTITUTE(AB14,"[Aviso]","")))/7, "Con Incidencias", "Válido"))) | AB14: =IF(AND(A14="", B14="", E14=""), "", TEXTJOIN("; ", TRUE, IF(OR(TRIM(A14&"")="", ISNUMBER(SEARCH("FALTA", A14))), "UPC faltante/inválido", ""), IF(AND(A14<>"", IFERROR(_xlfn.XMATCH(A14,$A$2:$A$285,0,1)<>_xlfn.XMATCH(A14,$A$2:$A$285,0,-1),FALSE)), "Código de barras duplicado", ""), IF(AND(E14<>"", COUNTIF($E$2:$E$285, E14)>1), "SKU duplicado", ""), IF(OR(J14="", J14=""), "[Aviso] División no capturada ()", IF(ISNA(MATCH(J14, Criterios!$A$123:$A$126, 0)), "División no válida", "")), IF(OR(K14="", K14=""), "[Aviso] Categoría no capturada ()", IF(ISNA(MATCH(K14, Criterios!$A$81:$A$120, 0)), "Categoría no válida", IF(AND(J14<>"", J14<>"", J14<>VLOOKUP(K14, Criterios!$A$81:$B$120, 2, FALSE)), "División no coincide con Categoría", ""))), IF(OR(L14="", L14=""), "[Aviso] Género no capturado ()", IF(ISNA(MATCH(L14, Criterios!$B$123:$B$127, 0)), "Género no válido", "")), IF(OR(N14="", N14=""), "[Aviso] Temporada no capturada ()", IF(ISNA(MATCH(N14, Criterios!$C$123:$C$128, 0)), "Temporada no válida", "")), IF(OR(O14="", O14=""), "[Aviso] Ciclo de vida no capturado ()", IF(ISNA(MATCH(O14, Criterios!$D$123:$D$124, 0)), "Ciclo de vida no válido", "")))) | AG14: Nuevo – Odoo Universal Unique Brands 01/10/2026 | AH14: 01/10/2026: alta desde Odoo Universal Unique Brands (no existía en Productos por código de barras ni SKU) | Talla tomada del sufijo del SKU (L); Categoría: Palabra clave "Camisa" en tipo/categoría de la fuente (Ropa / Camisas); Color detectado en el nombre (chocolate) | Homologación G1522 06/10/2026: WB N.º de estilo: «» → «01-001-0017-7018» (Completado por regla) | AK14: Odoo: producto 21101 / plantilla 27104 | AN14: Odoo Universal Unique Brands | AQ14: 1 | AR14: Odoo Universal Unique Brands › Bodega 25 › Bodega 25/General: 1
A15: 199168041595 | C15: Roper | D15: 01-001-0017-7018 | E15: 01-001-0017-7018 BR-M | F15: M | G15: M | H15: Roper | I15: ROPER Shirt Chocolate Solid Poplin | J15: Ropa | K15: Camisas | P15: Cafe | V15: PZS | W15: 53101602 | Y15: 33.02 | Z15: 879 | AA15: =IF(AND(A15="", B15="", E15=""), "", IF(AB15="", "Válido", IF((LEN(AB15)-LEN(SUBSTITUTE(AB15,"; ","")))/2+1>(LEN(AB15)-LEN(SUBSTITUTE(AB15,"[Aviso]","")))/7, "Con Incidencias", "Válido"))) | AB15: =IF(AND(A15="", B15="", E15=""), "", TEXTJOIN("; ", TRUE, IF(OR(TRIM(A15&"")="", ISNUMBER(SEARCH("FALTA", A15))), "UPC faltante/inválido", ""), IF(AND(A15<>"", IFERROR(_xlfn.XMATCH(A15,$A$2:$A$285,0,1)<>_xlfn.XMATCH(A15,$A$2:$A$285,0,-1),FALSE)), "Código de barras duplicado", ""), IF(AND(E15<>"", COUNTIF($E$2:$E$285, E15)>1), "SKU duplicado", ""), IF(OR(J15="", J15=""), "[Aviso] División no capturada ()", IF(ISNA(MATCH(J15, Criterios!$A$123:$A$126, 0)), "División no válida", "")), IF(OR(K15="", K15=""), "[Aviso] Categoría no capturada ()", IF(ISNA(MATCH(K15, Criterios!$A$81:$A$120, 0)), "Categoría no válida", IF(AND(J15<>"", J15<>"", J15<>VLOOKUP(K15, Criterios!$A$81:$B$120, 2, FALSE)), "División no coincide con Categoría", ""))), IF(OR(L15="", L15=""), "[Aviso] Género no capturado ()", IF(ISNA(MATCH(L15, Criterios!$B$123:$B$127, 0)), "Género no válido", "")), IF(OR(N15="", N15=""), "[Aviso] Temporada no capturada ()", IF(ISNA(MATCH(N15, Criterios!$C$123:$C$128, 0)), "Temporada no válida", "")), IF(OR(O15="", O15=""), "[Aviso] Ciclo de vida no capturado ()", IF(ISNA(MATCH(O15, Criterios!$D$123:$D$124, 0)), "Ciclo de vida no válido", "")))) | AG15: Nuevo – Odoo Universal Unique Brands 01/10/2026 | AH15: 01/10/2026: alta desde Odoo Universal Unique Brands (no existía en Productos por código de barras ni SKU) | Talla tomada del sufijo del SKU (M); Categoría: Palabra clave "Camisa" en tipo/categoría de la fuente (Ropa / Camisas); Color detectado en el nombre (chocolate) | Homologación G1522 06/10/2026: WB N.º de estilo: «» → «01-001-0017-7018» (Completado por regla) | AK15: Odoo: producto 21100 / plantilla 27103 | AN15: Odoo Universal Unique Brands | AQ15: 9 | AR15: Odoo Universal Unique Brands › Bodega 25 › Bodega 25/General: 9
A16: 199168041601 | C16: Roper | D16: 01-001-0017-7018 | E16: 01-001-0017-7018 BR-S | F16: S | G16: S | H16: Roper | I16: ROPER Shirt Chocolate Solid Poplin | J16: Ropa | K16: Camisas | P16: Cafe | V16: PZS | W16: 53101602 | Y16: 33.02 | Z16: 879 | AA16: =IF(AND(A16="", B16="", E16=""), "", IF(AB16="", "Válido", IF((LEN(AB16)-LEN(SUBSTITUTE(AB16,"; ","")))/2+1>(LEN(AB16)-LEN(SUBSTITUTE(AB16,"[Aviso]","")))/7, "Con Incidencias", "Válido"))) | AB16: =IF(AND(A16="", B16="", E16=""), "", TEXTJOIN("; ", TRUE, IF(OR(TRIM(A16&"")="", ISNUMBER(SEARCH("FALTA", A16))), "UPC faltante/inválido", ""), IF(AND(A16<>"", IFERROR(_xlfn.XMATCH(A16,$A$2:$A$285,0,1)<>_xlfn.XMATCH(A16,$A$2:$A$285,0,-1),FALSE)), "Código de barras duplicado", ""), IF(AND(E16<>"", COUNTIF($E$2:$E$285, E16)>1), "SKU duplicado", ""), IF(OR(J16="", J16=""), "[Aviso] División no capturada ()", IF(ISNA(MATCH(J16, Criterios!$A$123:$A$126, 0)), "División no válida", "")), IF(OR(K16="", K16=""), "[Aviso] Categoría no capturada ()", IF(ISNA(MATCH(K16, Criterios!$A$81:$A$120, 0)), "Categoría no válida", IF(AND(J16<>"", J16<>"", J16<>VLOOKUP(K16, Criterios!$A$81:$B$120, 2, FALSE)), "División no coincide con Categoría", ""))), IF(OR(L16="", L16=""), "[Aviso] Género no capturado ()", IF(ISNA(MATCH(L16, Criterios!$B$123:$B$127, 0)), "Género no válido", "")), IF(OR(N16="", N16=""), "[Aviso] Temporada no capturada ()", IF(ISNA(MATCH(N16, Criterios!$C$123:$C$128, 0)), "Temporada no válida", "")), IF(OR(O16="", O16=""), "[Aviso] Ciclo de vida no capturado ()", IF(ISNA(MATCH(O16, Criterios!$D$123:$D$124, 0)), "Ciclo de vida no válido", "")))) | AG16: Nuevo – Odoo Universal Unique Brands 01/10/2026 | AH16: 01/10/2026: alta desde Odoo Universal Unique Brands (no existía en Productos por código de barras ni SKU) | Talla tomada del sufijo del SKU (S); Categoría: Palabra clave "Camisa" en tipo/categoría de la fuente (Ropa / Camisas); Color detectado en el nombre (chocolate) | Homologación G1522 06/10/2026: WB N.º de estilo: «» → «01-001-0017-7018» (Completado por regla) | AK16: Odoo: producto 21099 / plantilla 27102 | AN16: Odoo Universal Unique Brands | AQ16: 7 | AR16: Odoo Universal Unique Brands › Bodega 25 › Bodega 25/General: 7
A17: 199168041618 | C17: Roper | D17: 01-001-0017-7018 | E17: 01-001-0017-7018 BR-XL | F17: XL | G17: XL | H17: Roper | I17: ROPER Shirt Chocolate Solid Poplin | J17: Ropa | K17: Camisas | P17: Cafe | V17: PZS | W17: 53101602 | Y17: 33.02 | Z17: 879 | AA17: =IF(AND(A17="", B17="", E17=""), "", IF(AB17="", "Válido", IF((LEN(AB17)-LEN(SUBSTITUTE(AB17,"; ","")))/2+1>(LEN(AB17)-LEN(SUBSTITUTE(AB17,"[Aviso]","")))/7, "Con Incidencias", "Válido"))) | AB17: =IF(AND(A17="", B17="", E17=""), "", TEXTJOIN("; ", TRUE, IF(OR(TRIM(A17&"")="", ISNUMBER(SEARCH("FALTA", A17))), "UPC faltante/inválido", ""), IF(AND(A17<>"", IFERROR(_xlfn.XMATCH(A17,$A$2:$A$285,0,1)<>_xlfn.XMATCH(A17,$A$2:$A$285,0,-1),FALSE)), "Código de barras duplicado", ""), IF(AND(E17<>"", COUNTIF($E$2:$E$285, E17)>1), "SKU duplicado", ""), IF(OR(J17="", J17=""), "[Aviso] División no capturada ()", IF(ISNA(MATCH(J17, Criterios!$A$123:$A$126, 0)), "División no válida", "")), IF(OR(K17="", K17=""), "[Aviso] Categoría no capturada ()", IF(ISNA(MATCH(K17, Criterios!$A$81:$A$120, 0)), "Categoría no válida", IF(AND(J17<>"", J17<>"", J17<>VLOOKUP(K17, Criterios!$A$81:$B$120, 2, FALSE)), "División no coincide con Categoría", ""))), IF(OR(L17="", L17=""), "[Aviso] Género no capturado ()", IF(ISNA(MATCH(L17, Criterios!$B$123:$B$127, 0)), "Género no válido", "")), IF(OR(N17="", N17=""), "[Aviso] Temporada no capturada ()", IF(ISNA(MATCH(N17, Criterios!$C$123:$C$128, 0)), "Temporada no válida", "")), IF(OR(O17="", O17=""), "[Aviso] Ciclo de vida no capturado ()", IF(ISNA(MATCH(O17, Criterios!$D$123:$D$124, 0)), "Ciclo de vida no válido", "")))) | AG17: Nuevo – Odoo Universal Unique Brands 01/10/2026 | AH17: 01/10/2026: alta desde Odoo Universal Unique Brands (no existía en Productos por código de barras ni SKU) | Talla tomada del sufijo del SKU (XL); Categoría: Palabra clave "Camisa" en tipo/categoría de la fuente (Ropa / Camisas); Color detectado en el nombre (chocolate) | Homologación G1522 06/10/2026: WB N.º de estilo: «» → «01-001-0017-7018» (Completado por regla) | AK17: Odoo: producto 21102 / plantilla 27105 | AN17: Odoo Universal Unique Brands | AQ17: 9 | AR17: Odoo Universal Unique Brands › Bodega 25 › Bodega 25/General: 9
A18: 199168041748 | C18: Roper | D18: 01-001-0019-7010 | E18: 01-001-0019-7010 GR-2XL | F18: XXL | G18: XXL | H18: Roper | I18: ROPER Shirt Olive Floral Print | J18: Ropa | K18: Camisas | P18: Verde | V18: PZS | W18: 53101602 | Y18: 22.79 | Z18: 629 | AA18: =IF(AND(A18="", B18="", E18=""), "", IF(AB18="", "Válido", IF((LEN(AB18)-LEN(SUBSTITUTE(AB18,"; ","")))/2+1>(LEN(AB18)-LEN(SUBSTITUTE(AB18,"[Aviso]","")))/7, "Con Incidencias", "Válido"))) | AB18: =IF(AND(A18="", B18="", E18=""), "", TEXTJOIN("; ", TRUE, IF(OR(TRIM(A18&"")="", ISNUMBER(SEARCH("FALTA", A18))), "UPC faltante/inválido", ""), IF(AND(A18<>"", IFERROR(_xlfn.XMATCH(A18,$A$2:$A$285,0,1)<>_xlfn.XMATCH(A18,$A$2:$A$285,0,-1),FALSE)), "Código de barras duplicado", ""), IF(AND(E18<>"", COUNTIF($E$2:$E$285, E18)>1), "SKU duplicado", ""), IF(OR(J18="", J18=""), "[Aviso] División no capturada ()", IF(ISNA(MATCH(J18, Criterios!$A$123:$A$126, 0)), "División no válida", "")), IF(OR(K18="", K18=""), "[Aviso] Categoría no capturada ()", IF(ISNA(MATCH(K18, Criterios!$A$81:$A$120, 0)), "Categoría no válida", IF(AND(J18<>"", J18<>"", J18<>VLOOKUP(K18, Criterios!$A$81:$B$120, 2, FALSE)), "División no coincide con Categoría", ""))), IF(OR(L18="", L18=""), "[Aviso] Género no capturado ()", IF(ISNA(MATCH(L18, Criterios!$B$123:$B$127, 0)), "Género no válido", "")), IF(OR(N18="", N18=""), "[Aviso] Temporada no capturada ()", IF(ISNA(MATCH(N18, Criterios!$C$123:$C$128, 0)), "Temporada no válida", "")), IF(OR(O18="", O18=""), "[Aviso] Ciclo de vida no capturado ()", IF(ISNA(MATCH(O18, Criterios!$D$123:$D$124, 0)), "Ciclo de vida no válido", "")))) | AG18: Nuevo – Odoo Universal Unique Brands 01/10/2026 | AH18: 01/10/2026: alta desde Odoo Universal Unique Brands (no existía en Productos por código de barras ni SKU) | Talla tomada del sufijo del SKU (2XL); Categoría: Palabra clave "Camisa" en tipo/categoría de la fuente (Ropa / Camisas); Talla: 2XL→XXL; Color detectado en el nombre (olive) | Homologación G1522 06/10/2026: WB N.º de estilo: «» → «01-001-0019-7010» (Completado por regla) | AK18: Odoo: producto 21080 / plantilla 27083 | AN18: Odoo Universal Unique Brands | AQ18: 3 | AR18: Odoo Universal Unique Brands › Bodega 25 › Bodega 25/General: 3
A19: 199168041700 | C19: Roper | D19: 01-001-0019-7010 | E19: 01-001-0019-7010 GR-L | F19: L | G19: L | H19: Roper | I19: ROPER Shirt Olive Floral Print | J19: Ropa | K19: Camisas | P19: Verde | V19: PZS | W19: 53101602 | Y19: 22.79 | Z19: 629 | AA19: =IF(AND(A19="", B19="", E19=""), "", IF(AB19="", "Válido", IF((LEN(AB19)-LEN(SUBSTITUTE(AB19,"; ","")))/2+1>(LEN(AB19)-LEN(SUBSTITUTE(AB19,"[Aviso]","")))/7, "Con Incidencias", "Válido"))) | AB19: =IF(AND(A19="", B19="", E19=""), "", TEXTJOIN("; ", TRUE, IF(OR(TRIM(A19&"")="", ISNUMBER(SEARCH("FALTA", A19))), "UPC faltante/inválido", ""), IF(AND(A19<>"", IFERROR(_xlfn.XMATCH(A19,$A$2:$A$285,0,1)<>_xlfn.XMATCH(A19,$A$2:$A$285,0,-1),FALSE)), "Código de barras duplicado", ""), IF(AND(E19<>"", COUNTIF($E$2:$E$285, E19)>1), "SKU duplicado", ""), IF(OR(J19="", J19=""), "[Aviso] División no capturada ()", IF(ISNA(MATCH(J19, Criterios!$A$123:$A$126, 0)), "División no válida", "")), IF(OR(K19="", K19=""), "[Aviso] Categoría no capturada ()", IF(ISNA(MATCH(K19, Criterios!$A$81:$A$120, 0)), "Categoría no válida", IF(AND(J19<>"", J19<>"", J19<>VLOOKUP(K19, Criterios!$A$81:$B$120, 2, FALSE)), "División no coincide con Categoría", ""))), IF(OR(L19="", L19=""), "[Aviso] Género no capturado ()", IF(ISNA(MATCH(L19, Criterios!$B$123:$B$127, 0)), "Género no válido", "")), IF(OR(N19="", N19=""), "[Aviso] Temporada no capturada ()", IF(ISNA(MATCH(N19, Criterios!$C$123:$C$128, 0)), "Temporada no válida", "")), IF(OR(O19="", O19=""), "[Aviso] Ciclo de vida no capturado ()", IF(ISNA(MATCH(O19, Criterios!$D$123:$D$124, 0)), "Ciclo de vida no válido", "")))) | AG19: Nuevo – Odoo Universal Unique Brands 01/10/2026 | AH19: 01/10/2026: alta desde Odoo Universal Unique Brands (no existía en Productos por código de barras ni SKU) | Talla tomada del sufijo del SKU (L); Categoría: Palabra clave "Camisa" en tipo/categoría de la fuente (Ropa / Camisas); Color detectado en el nombre (olive) | Homologación G1522 06/10/2026: WB N.º de estilo: «» → «01-001-0019-7010» (Completado por regla) | AK19: Odoo: producto 21078 / plantilla 27081 | AN19: Odoo Universal Unique Brands | AQ19: 8 | AR19: Odoo Universal Unique Brands › Bodega 25 › Bodega 25/General: 8
A20: 199168041717 | C20: Roper | D20: 01-001-0019-7010 | E20: 01-001-0019-7010 GR-M | F20: M | G20: M | H20: Roper | I20: ROPER Shirt Olive Floral Print | J20: Ropa | K20: Camisas | P20: Verde | V20: PZS | W20: 53101602 | Y20: 22.79 | Z20: 629 | AA20: =IF(AND(A20="", B20="", E20=""), "", IF(AB20="", "Válido", IF((LEN(AB20)-LEN(SUBSTITUTE(AB20,"; ","")))/2+1>(LEN(AB20)-LEN(SUBSTITUTE(AB20,"[Aviso]","")))/7, "Con Incidencias", "Válido"))) | AB20: =IF(AND(A20="", B20="", E20=""), "", TEXTJOIN("; ", TRUE, IF(OR(TRIM(A20&"")="", ISNUMBER(SEARCH("FALTA", A20))), "UPC faltante/inválido", ""), IF(AND(A20<>"", IFERROR(_xlfn.XMATCH(A20,$A$2:$A$285,0,1)<>_xlfn.XMATCH(A20,$A$2:$A$285,0,-1),FALSE)), "Código de barras duplicado", ""), IF(AND(E20<>"", COUNTIF($E$2:$E$285, E20)>1), "SKU duplicado", ""), IF(OR(J20="", J20=""), "[Aviso] División no capturada ()", IF(ISNA(MATCH(J20, Criterios!$A$123:$A$126, 0)), "División no válida", "")), IF(OR(K20="", K20=""), "[Aviso] Categoría no capturada ()", IF(ISNA(MATCH(K20, Criterios!$A$81:$A$120, 0)), "Categoría no válida", IF(AND(J20<>"", J20<>"", J20<>VLOOKUP(K20, Criterios!$A$81:$B$120, 2, FALSE)), "División no coincide con Categoría", ""))), IF(OR(L20="", L20=""), "[Aviso] Género no capturado ()", IF(ISNA(MATCH(L20, Criterios!$B$123:$B$127, 0)), "Género no válido", "")), IF(OR(N20="", N20=""), "[Aviso] Temporada no capturada ()", IF(ISNA(MATCH(N20, Criterios!$C$123:$C$128, 0)), "Temporada no válida", "")), IF(OR(O20="", O20=""), "[Aviso] Ciclo de vida no capturado ()", IF(ISNA(MATCH(O20, Criterios!$D$123:$D$124, 0)), "Ciclo de vida no válido", "")))) | AG20: Nuevo – Odoo Universal Unique Brands 01/10/2026 | AH20: 01/10/2026: alta desde Odoo Universal Unique Brands (no existía en Productos por código de barras ni SKU) | Talla tomada del sufijo del SKU (M); Categoría: Palabra clave "Camisa" en tipo/categoría de la fuente (Ropa / Camisas); Color detectado en el nombre (olive) | Homologación G1522 06/10/2026: WB N.º de estilo: «» → «01-001-0019-7010» (Completado por regla) | AK20: Odoo: producto 21077 / plantilla 27080 | AN20: Odoo Universal Unique Brands | AQ20: 8 | AR20: Odoo Universal Unique Brands › Bodega 25 › Bodega 25/General: 8
A21: 199168041724 | C21: Roper | D21: 01-001-0019-7010 | E21: 01-001-0019-7010 GR-S | F21: S | G21: S | H21: Roper | I21: ROPER Shirt Olive Floral Print | J21: Ropa | K21: Camisas | P21: Verde | V21: PZS | W21: 53101602 | Y21: 22.79 | Z21: 629 | AA21: =IF(AND(A21="", B21="", E21=""), "", IF(AB21="", "Válido", IF((LEN(AB21)-LEN(SUBSTITUTE(AB21,"; ","")))/2+1>(LEN(AB21)-LEN(SUBSTITUTE(AB21,"[Aviso]","")))/7, "Con Incidencias", "Válido"))) | AB21: =IF(AND(A21="", B21="", E21=""), "", TEXTJOIN("; ", TRUE, IF(OR(TRIM(A21&"")="", ISNUMBER(SEARCH("FALTA", A21))), "UPC faltante/inválido", ""), IF(AND(A21<>"", IFERROR(_xlfn.XMATCH(A21,$A$2:$A$285,0,1)<>_xlfn.XMATCH(A21,$A$2:$A$285,0,-1),FALSE)), "Código de barras duplicado", ""), IF(AND(E21<>"", COUNTIF($E$2:$E$285, E21)>1), "SKU duplicado", ""), IF(OR(J21="", J21=""), "[Aviso] División no capturada ()", IF(ISNA(MATCH(J21, Criterios!$A$123:$A$126, 0)), "División no válida", "")), IF(OR(K21="", K21=""), "[Aviso] Categoría no capturada ()", IF(ISNA(MATCH(K21, Criterios!$A$81:$A$120, 0)), "Categoría no válida", IF(AND(J21<>"", J21<>"", J21<>VLOOKUP(K21, Criterios!$A$81:$B$120, 2, FALSE)), "División no coincide con Categoría", ""))), IF(OR(L21="", L21=""), "[Aviso] Género no capturado ()", IF(ISNA(MATCH(L21, Criterios!$B$123:$B$127, 0)), "Género no válido", "")), IF(OR(N21="", N21=""), "[Aviso] Temporada no capturada ()", IF(ISNA(MATCH(N21, Criterios!$C$123:$C$128, 0)), "Temporada no válida", "")), IF(OR(O21="", O21=""), "[Aviso] Ciclo de vida no capturado ()", IF(ISNA(MATCH(O21, Criterios!$D$123:$D$124, 0)), "Ciclo de vida no válido", "")))) | AG21: Nuevo – Odoo Universal Unique Brands 01/10/2026 | AH21: 01/10/2026: alta desde Odoo Universal Unique Brands (no existía en Productos por código de barras ni SKU) | Talla tomada del sufijo del SKU (S); Categoría: Palabra clave "Camisa" en tipo/categoría de la fuente (Ropa / Camisas); Color detectado en el nombre (olive) | Homologación G1522 06/10/2026: WB N.º de estilo: «» → «01-001-0019-7010» (Completado por regla) | AK21: Odoo: producto 21076 / plantilla 27079 | AN21: Odoo Universal Unique Brands | AQ21: 6 | AR21: Odoo Universal Unique Brands › Bodega 25 › Bodega 25/General: 6
A22: 199168041731 | C22: Roper | D22: 01-001-0019-7010 | E22: 01-001-0019-7010 GR-XL | F22: XL | G22: XL | H22: Roper | I22: ROPER Shirt Olive Floral Print | J22: Ropa | K22: Camisas | P22: Verde | V22: PZS | W22: 53101602 | Y22: 22.79 | Z22: 629 | AA22: =IF(AND(A22="", B22="", E22=""), "", IF(AB22="", "Válido", IF((LEN(AB22)-LEN(SUBSTITUTE(AB22,"; ","")))/2+1>(LEN(AB22)-LEN(SUBSTITUTE(AB22,"[Aviso]","")))/7, "Con Incidencias", "Válido"))) | AB22: =IF(AND(A22="", B22="", E22=""), "", TEXTJOIN("; ", TRUE, IF(OR(TRIM(A22&"")="", ISNUMBER(SEARCH("FALTA", A22))), "UPC faltante/inválido", ""), IF(AND(A22<>"", IFERROR(_xlfn.XMATCH(A22,$A$2:$A$285,0,1)<>_xlfn.XMATCH(A22,$A$2:$A$285,0,-1),FALSE)), "Código de barras duplicado", ""), IF(AND(E22<>"", COUNTIF($E$2:$E$285, E22)>1), "SKU duplicado", ""), IF(OR(J22="", J22=""), "[Aviso] División no capturada ()", IF(ISNA(MATCH(J22, Criterios!$A$123:$A$126, 0)), "División no válida", "")), IF(OR(K22="", K22=""), "[Aviso] Categoría no capturada ()", IF(ISNA(MATCH(K22, Criterios!$A$81:$A$120, 0)), "Categoría no válida", IF(AND(J22<>"", J22<>"", J22<>VLOOKUP(K22, Criterios!$A$81:$B$120, 2, FALSE)), "División no coincide con Categoría", ""))), IF(OR(L22="", L22=""), "[Aviso] Género no capturado ()", IF(ISNA(MATCH(L22, Criterios!$B$123:$B$127, 0)), "Género no válido", "")), IF(OR(N22="", N22=""), "[Aviso] Temporada no capturada ()", IF(ISNA(MATCH(N22, Criterios!$C$123:$C$128, 0)), "Temporada no válida", "")), IF(OR(O22="", O22=""), "[Aviso] Ciclo de vida no capturado ()", IF(ISNA(MATCH(O22, Criterios!$D$123:$D$124, 0)), "Ciclo de vida no válido", "")))) | AG22: Nuevo – Odoo Universal Unique Brands 01/10/2026 | AH22: 01/10/2026: alta desde Odoo Universal Unique Brands (no existía en Productos por código de barras ni SKU) | Talla tomada del sufijo del SKU (XL); Categoría: Palabra clave "Camisa" en tipo/categoría de la fuente (Ropa / Camisas); Color detectado en el nombre (olive) | Homologación G1522 06/10/2026: WB N.º de estilo: «» → «01-001-0019-7010» (Completado por regla) | AK22: Odoo: producto 21079 / plantilla 27082 | AN22: Odoo Universal Unique Brands | AQ22: 8 | AR22: Odoo Universal Unique Brands › Bodega 25 › Bodega 25/General: 8
A23: 199168041762 | C23: Roper | D23: 01-001-0019-7011 | E23: 01-001-0019-7011 BL-L | F23: L | G23: L | H23: Roper | I23: ROPER Shirt Black & Grey Floral Print | J23: Ropa | K23: Camisas | P23: Negro | V23: PZS | W23: 53101602 | Y23: 22.79 | Z23: 629 | AA23: =IF(AND(A23="", B23="", E23=""), "", IF(AB23="", "Válido", IF((LEN(AB23)-LEN(SUBSTITUTE(AB23,"; ","")))/2+1>(LEN(AB23)-LEN(SUBSTITUTE(AB23,"[Aviso]","")))/7, "Con Incidencias", "Válido"))) | AB23: =IF(AND(A23="", B23="", E23=""), "", TEXTJOIN("; ", TRUE, IF(OR(TRIM(A23&"")="", ISNUMBER(SEARCH("FALTA", A23))), "UPC faltante/inválido", ""), IF(AND(A23<>"", IFERROR(_xlfn.XMATCH(A23,$A$2:$A$285,0,1)<>_xlfn.XMATCH(A23,$A$2:$A$285,0,-1),FALSE)), "Código de barras duplicado", ""), IF(AND(E23<>"", COUNTIF($E$2:$E$285, E23)>1), "SKU duplicado", ""), IF(OR(J23="", J23=""), "[Aviso] División no capturada ()", IF(ISNA(MATCH(J23, Criterios!$A$123:$A$126, 0)), "División no válida", "")), IF(OR(K23="", K23=""), "[Aviso] Categoría no capturada ()", IF(ISNA(MATCH(K23, Criterios!$A$81:$A$120, 0)), "Categoría no válida", IF(AND(J23<>"", J23<>"", J23<>VLOOKUP(K23, Criterios!$A$81:$B$120, 2, FALSE)), "División no coincide con Categoría", ""))), IF(OR(L23="", L23=""), "[Aviso] Género no capturado ()", IF(ISNA(MATCH(L23, Criterios!$B$123:$B$127, 0)), "Género no válido", "")), IF(OR(N23="", N23=""), "[Aviso] Temporada no capturada ()", IF(ISNA(MATCH(N23, Criterios!$C$123:$C$128, 0)), "Temporada no válida", "")), IF(OR(O23="", O23=""), "[Aviso] Ciclo de vida no capturado ()", IF(ISNA(MATCH(O23, Criterios!$D$123:$D$124, 0)), "Ciclo de vida no válido", "")))) | AG23: Nuevo – Odoo Universal Unique Brands 01/10/2026 | AH23: 01/10/2026: alta desde Odoo Universal Unique Brands (no existía en Productos por código de barras ni SKU) | Talla tomada del sufijo del SKU (L); Categoría: Palabra clave "Camisa" en tipo/categoría de la fuente (Ropa / Camisas); Color detectado en el nombre (black) | Homologación G1522 06/10/2026: WB N.º de estilo: «» → «01-001-0019-7011» (Completado por regla) | AK23: Odoo: producto 20926 / plantilla 26929 | AN23: Odoo Universal Unique Brands | AQ23: 14 | AR23: Odoo Universal Unique Brands › Bodega 25 › Bodega 25/General: 14
A24: 199168041779 | C24: Roper | D24: 01-001-0019-7011 | E24: 01-001-0019-7011 BL-M | F24: M | G24: M | H24: Roper | I24: ROPER Shirt Black & Grey Floral Print | J24: Ropa | K24: Camisas | P24: Negro | V24: PZS | W24: 53101602 | Y24: 22.79 | Z24: 629 | AA24: =IF(AND(A24="", B24="", E24=""), "", IF(AB24="", "Válido", IF((LEN(AB24)-LEN(SUBSTITUTE(AB24,"; ","")))/2+1>(LEN(AB24)-LEN(SUBSTITUTE(AB24,"[Aviso]","")))/7, "Con Incidencias", "Válido"))) | AB24: =IF(AND(A24="", B24="", E24=""), "", TEXTJOIN("; ", TRUE, IF(OR(TRIM(A24&"")="", ISNUMBER(SEARCH("FALTA", A24))), "UPC faltante/inválido", ""), IF(AND(A24<>"", IFERROR(_xlfn.XMATCH(A24,$A$2:$A$285,0,1)<>_xlfn.XMATCH(A24,$A$2:$A$285,0,-1),FALSE)), "Código de barras duplicado", ""), IF(AND(E24<>"", COUNTIF($E$2:$E$285, E24)>1), "SKU duplicado", ""), IF(OR(J24="", J24=""), "[Aviso] División no capturada ()", IF(ISNA(MATCH(J24, Criterios!$A$123:$A$126, 0)), "División no válida", "")), IF(OR(K24="", K24=""), "[Aviso] Categoría no capturada ()", IF(ISNA(MATCH(K24, Criterios!$A$81:$A$120, 0)), "Categoría no válida", IF(AND(J24<>"", J24<>"", J24<>VLOOKUP(K24, Criterios!$A$81:$B$120, 2, FALSE)), "División no coincide con Categoría", ""))), IF(OR(L24="", L24=""), "[Aviso] Género no capturado ()", IF(ISNA(MATCH(L24, Criterios!$B$123:$B$127, 0)), "Género no válido", "")), IF(OR(N24="", N24=""), "[Aviso] Temporada no capturada ()", IF(ISNA(MATCH(N24, Criterios!$C$123:$C$128, 0)), "Temporada no válida", "")), IF(OR(O24="", O24=""), "[Aviso] Ciclo de vida no capturado ()", IF(ISNA(MATCH(O24, Criterios!$D$123:$D$124, 0)), "Ciclo de vida no válido", "")))) | AG24: Nuevo – Odoo Universal Unique Brands 01/10/2026 | AH24: 01/10/2026: alta desde Odoo Universal Unique Brands (no existía en Productos por código de barras ni SKU) | Talla tomada del sufijo del SKU (M); Categoría: Palabra clave "Camisa" en tipo/categoría de la fuente (Ropa / Camisas); Color detectado en el nombre (black) | Homologación G1522 06/10/2026: WB N.º de estilo: «» → «01-001-0019-7011» (Completado por regla) | AK24: Odoo: producto 20925 / plantilla 26928 | AN24: Odoo Universal Unique Brands | AQ24: 15 | AR24: Odoo Universal Unique Brands › Bodega 25 › Bodega 25/General: 15
... A26: 199168041793 | C26: Roper | D26: 01-001-0019-7011 | E26: 01-001-0019-7011 BL-XL | F26: XL | G26: XL | H26: Roper | I26: ROPER Shirt Black & Grey Floral Print | J26: Ropa | K26: Camisas | P26: Negro | V26: PZS | W26: 53101602 | Y26: 22.79 | Z26: 629 | AA26: =IF(AND(A26="", B26="", E26=""), "", IF(AB26="", "Válido", IF((LEN(AB26)-LEN(SUBSTITUTE(AB26,"; ","")))/2+1>(LEN(AB26)-LEN(SUBSTITUTE(AB26,"[Aviso]","")))/7, "Con Incidencias", "Válido"))) | AB26: =IF(AND(A26="", B26="", E26=""), "", TEXTJOIN("; ", TRUE, IF(OR(TRIM(A26&"")="", ISNUMBER(SEARCH("FALTA", A26))), "UPC faltante/inválido", ""), IF(AND(A26<>"", IFERROR(_xlfn.XMATCH(A26,$A$2:$A$285,0,1)<>_xlfn.XMATCH(A26,$A$2:$A$285,0,-1),FALSE)), "Código de barras duplicado", ""), IF(AND(E26<>"", COUNTIF($E$2:$E$285, E26)>1), "SKU duplicado", ""), IF(OR(J26="", J26=""), "[Aviso] División no capturada ()", IF(ISNA(MATCH(J26, Criterios!$A$123:$A$126, 0)), "División no válida", "")), IF(OR(K26="", K26=""), "[Aviso] Categoría no capturada ()", IF(ISNA(MATCH(K26, Criterios!$A$81:$A$120, 0)), "Categoría no válida", IF(AND(J26<>"", J26<>"", J26<>VLOOKUP(K26, Criterios!$A$81:$B$120, 2, FALSE)), "División no coincide con Categoría", ""))), IF(OR(L26="", L26=""), "[Aviso] Género no capturado ()", IF(ISNA(MATCH(L26, Criterios!$B$123:$B$127, 0)), "Género no válido", "")), IF(OR(N26="", N26=""), "[Aviso] Temporada no capturada ()", IF(ISNA(MATCH(N26, Criterios!$C$123:$C$128, 0)), "Temporada no válida", "")), IF(OR(O26="", O26=""), "[Aviso] Ciclo de vida no capturado ()", IF(ISNA(MATCH(O26, Criterios!$D$123:$D$124, 0)), "Ciclo de vida no válido", "")))) | AG26: Nuevo – Odoo Universal Unique Brands 01/10/2026 | AH26: 01/10/2026: alta desde Odoo Universal Unique Brands (no existía en Productos por código de barras ni SKU) | Talla tomada del sufijo del SKU (XL); Categoría: Palabra clave "Camisa" en tipo/categoría de la fuente (Ropa / Camisas); Color detectado en el nombre (black) | Homologación G1522 06/10/2026: WB N.º de estilo: «» → «01-001-0019-7011» (Completado por regla) | AK26: Odoo: producto 20927 / plantilla 26930 | AN26: Odoo Universal Unique Brands | AQ26: 11 | AR26: Odoo Universal Unique Brands › Bodega 25 › Bodega 25/General: 11
A27: 199168041984 | C27: Roper | D27: 01-001-0024-7008 | E27: 01-001-0024-7008 BL-2XL | F27: XXL | G27: XXL | H27: Roper | I27: ROPER Shirt Bl/Gy/Br Plaid | J27: Ropa | K27: Camisas | V27: PZS | W27: 53101602 | Y27: 33.48 | Z27: 889 | AA27: =IF(AND(A27="", B27="", E27=""), "", IF(AB27="", "Válido", IF((LEN(AB27)-LEN(SUBSTITUTE(AB27,"; ","")))/2+1>(LEN(AB27)-LEN(SUBSTITUTE(AB27,"[Aviso]","")))/7, "Con Incidencias", "Válido"))) | AB27: =IF(AND(A27="", B27="", E27=""), "", TEXTJOIN("; ", TRUE, IF(OR(TRIM(A27&"")="", ISNUMBER(SEARCH("FALTA", A27))), "UPC faltante/inválido", ""), IF(AND(A27<>"", IFERROR(_xlfn.XMATCH(A27,$A$2:$A$285,0,1)<>_xlfn.XMATCH(A27,$A$2:$A$285,0,-1),FALSE)), "Código de barras duplicado", ""), IF(AND(E27<>"", COUNTIF($E$2:$E$285, E27)>1), "SKU duplicado", ""), IF(OR(J27="", J27=""), "[Aviso] División no capturada ()", IF(ISNA(MATCH(J27, Criterios!$A$123:$A$126, 0)), "División no válida", "")), IF(OR(K27="", K27=""), "[Aviso] Categoría no capturada ()", IF(ISNA(MATCH(K27, Criterios!$A$81:$A$120, 0)), "Categoría no válida", IF(AND(J27<>"", J27<>"", J27<>VLOOKUP(K27, Criterios!$A$81:$B$120, 2, FALSE)), "División no coincide con Categoría", ""))), IF(OR(L27="", L27=""), "[Aviso] Género no capturado ()", IF(ISNA(MATCH(L27, Criterios!$B$123:$B$127, 0)), "Género no válido", "")), IF(OR(N27="", N27=""), "[Aviso] Temporada no capturada ()", IF(ISNA(MATCH(N27, Criterios!$C$123:$C$128, 0)), "Temporada no válida", "")), IF(OR(O27="", O27=""), "[Aviso] Ciclo de vida no capturado ()", IF(ISNA(MATCH(O27, Criterios!$D$123:$D$124, 0)), "Ciclo de vida no válido", "")))) | AG27: Nuevo – Odoo Universal Unique Brands 01/10/2026 | AH27: 01/10/2026: alta desde Odoo Universal Unique Brands (no existía en Productos por código de barras ni SKU) | Talla tomada del sufijo del SKU (2XL); Categoría: Palabra clave "Camisa" en tipo/categoría de la fuente (Ropa / Camisas); Talla: 2XL→XXL | Homologación G1522 06/10/2026: WB N.º de estilo: «» → «01-001-0024-7008» (Completado por regla) · Validador Shopify: WB: precio con IVA no termina en 9 | AK27: Odoo: producto 21123 / plantilla 27126 | AN27: Odoo Universal Unique Brands | AQ27: 6 | AR27: Odoo Universal Unique Brands › Bodega 25 › Bodega 25/General: 6
A28: 199168041946 | C28: Roper | D28: 01-001-0024-7008 | E28: 01-001-0024-7008 BL-L | F28: L | G28: L | H28: Roper | I28: ROPER Shirt Bl/Gy/Br Plaid | J28: Ropa | K28: Camisas | V28: PZS | W28: 53101602 | Y28: 33.48 | Z28: 889 | AA28: =IF(AND(A28="", B28="", E28=""), "", IF(AB28="", "Válido", IF((LEN(AB28)-LEN(SUBSTITUTE(AB28,"; ","")))/2+1>(LEN(AB28)-LEN(SUBSTITUTE(AB28,"[Aviso]","")))/7, "Con Incidencias", "Válido"))) | AB28: =IF(AND(A28="", B28="", E28=""), "", TEXTJOIN("; ", TRUE, IF(OR(TRIM(A28&"")="", ISNUMBER(SEARCH("FALTA", A28))), "UPC faltante/inválido", ""), IF(AND(A28<>"", IFERROR(_xlfn.XMATCH(A28,$A$2:$A$285,0,1)<>_xlfn.XMATCH(A28,$A$2:$A$285,0,-1),FALSE)), "Código de barras duplicado", ""), IF(AND(E28<>"", COUNTIF($E$2:$E$285, E28)>1), "SKU duplicado", ""), IF(OR(J28="", J28=""), "[Aviso] División no capturada ()", IF(ISNA(MATCH(J28, Criterios!$A$123:$A$126, 0)), "División no válida", "")), IF(OR(K28="", K28=""), "[Aviso] Categoría no capturada ()", IF(ISNA(MATCH(K28, Criterios!$A$81:$A$120, 0)), "Categoría no válida", IF(AND(J28<>"", J28<>"", J28<>VLOOKUP(K28, Criterios!$A$81:$B$120, 2, FALSE)), "División no coincide con Categoría", ""))), IF(OR(L28="", L28=""), "[Aviso] Género no capturado ()", IF(ISNA(MATCH(L28, Criterios!$B$123:$B$127, 0)), "Género no válido", "")), IF(OR(N28="", N28=""), "[Aviso] Temporada no capturada ()", IF(ISNA(MATCH(N28, Criterios!$C$123:$C$128, 0)), "Temporada no válida", "")), IF(OR(O28="", O28=""), "[Aviso] Ciclo de vida no capturado ()", IF(ISNA(MATCH(O28, Criterios!$D$123:$D$124, 0)), "Ciclo de vida no válido", "")))) | AG28: Nuevo – Odoo Universal Unique Brands 01/10/2026 | AH28: 01/10/2026: alta desde Odoo Universal Unique Brands (no existía en Productos por código de barras ni SKU) | Talla tomada del sufijo del SKU (L); Categoría: Palabra clave "Camisa" en tipo/categoría de la fuente (Ropa / Camisas) | Homologación G1522 06/10/2026: WB N.º de estilo: «» → «01-001-0024-7008» (Completado por regla) · Validador Shopify: WB: precio con IVA no termina en 9 | AK28: Odoo: producto 21121 / plantilla 27124 | AN28: Odoo Universal Unique Brands | AQ28: 9 | AR28: Odoo Universal Unique Brands › Bodega 25 › Bodega 25/General: 9
A29: 199168041953 | C29: Roper | D29: 01-001-0024-7008 | E29: 01-001-0024-7008 BL-M | F29: M | G29: M | H29: Roper | I29: ROPER Shirt Bl/Gy/Br Plaid | J29: Ropa | K29: Camisas | V29: PZS | W29: 53101602 | Y29: 33.48 | Z29: 889 | AA29: =IF(AND(A29="", B29="", E29=""), "", IF(AB29="", "Válido", IF((LEN(AB29)-LEN(SUBSTITUTE(AB29,"; ","")))/2+1>(LEN(AB29)-LEN(SUBSTITUTE(AB29,"[Aviso]","")))/7, "Con Incidencias", "Válido"))) | AB29: =IF(AND(A29="", B29="", E29=""), "", TEXTJOIN("; ", TRUE, IF(OR(TRIM(A29&"")="", ISNUMBER(SEARCH("FALTA", A29))), "UPC faltante/inválido", ""), IF(AND(A29<>"", IFERROR(_xlfn.XMATCH(A29,$A$2:$A$285,0,1)<>_xlfn.XMATCH(A29,$A$2:$A$285,0,-1),FALSE)), "Código de barras duplicado", ""), IF(AND(E29<>"", COUNTIF($E$2:$E$285, E29)>1), "SKU duplicado", ""), IF(OR(J29="", J29=""), "[Aviso] División no capturada ()", IF(ISNA(MATCH(J29, Criterios!$A$123:$A$126, 0)), "División no válida", "")), IF(OR(K29="", K29=""), "[Aviso] Categoría no capturada ()", IF(ISNA(MATCH(K29, Criterios!$A$81:$A$120, 0)), "Categoría no válida", IF(AND(J29<>"", J29<>"", J29<>VLOOKUP(K29, Criterios!$A$81:$B$120, 2, FALSE)), "División no coincide con Categoría", ""))), IF(OR(L29="", L29=""), "[Aviso] Género no capturado ()", IF(ISNA(MATCH(L29, Criterios!$B$123:$B$127, 0)), "Género no válido", "")), IF(OR(N29="", N29=""), "[Aviso] Temporada no capturada ()", IF(ISNA(MATCH(N29, Criterios!$C$123:$C$128, 0)), "Temporada no válida", "")), IF(OR(O29="", O29=""), "[Aviso] Ciclo de vida no capturado ()", IF(ISNA(MATCH(O29, Criterios!$D$123:$D$124, 0)), "Ciclo de vida no válido", "")))) | AG29: Nuevo – Odoo Universal Unique Brands 01/10/2026 | AH29: 01/10/2026: alta desde Odoo Universal Unique Brands (no existía en Productos por código de barras ni SKU) | Talla tomada del sufijo del SKU (M); Categoría: Palabra clave "Camisa" en tipo/categoría de la fuente (Ropa / Camisas) | Homologación G1522 06/10/2026: WB N.º de estilo: «» → «01-001-0024-7008» (Completado por regla) · Validador Shopify: WB: precio con IVA no termina en 9 | AK29: Odoo: producto 21120 / plantilla 27123 | AN29: Odoo Universal Unique Brands | AQ29: 9 | AR29: Odoo Universal Unique Brands › Bodega 25 › Bodega 25/General: 9
A30: 199168041960 | C30: Roper | D30: 01-001-0024-7008 | E30: 01-001-0024-7008 BL-S | F30: S | G30: S | H30: Roper | I30: ROPER Shirt Bl/Gy/Br Plaid | J30: Ropa | K30: Camisas | V30: PZS | W30: 53101602 | Y30: 33.48 | Z30: 889 | AA30: =IF(AND(A30="", B30="", E30=""), "", IF(AB30="", "Válido", IF((LEN(AB30)-LEN(SUBSTITUTE(AB30,"; ","")))/2+1>(LEN(AB30)-LEN(SUBSTITUTE(AB30,"[Aviso]","")))/7, "Con Incidencias", "Válido"))) | AB30: =IF(AND(A30="", B30="", E30=""), "", TEXTJOIN("; ", TRUE, IF(OR(TRIM(A30&"")="", ISNUMBER(SEARCH("FALTA", A30))), "UPC faltante/inválido", ""), IF(AND(A30<>"", IFERROR(_xlfn.XMATCH(A30,$A$2:$A$285,0,1)<>_xlfn.XMATCH(A30,$A$2:$A$285,0,-1),FALSE)), "Código de barras duplicado", ""), IF(AND(E30<>"", COUNTIF($E$2:$E$285, E30)>1), "SKU duplicado", ""), IF(OR(J30="", J30=""), "[Aviso] División no capturada ()", IF(ISNA(MATCH(J30, Criterios!$A$123:$A$126, 0)), "División no válida", "")), IF(OR(K30="", K30=""), "[Aviso] Categoría no capturada ()", IF(ISNA(MATCH(K30, Criterios!$A$81:$A$120, 0)), "Categoría no válida", IF(AND(J30<>"", J30<>"", J30<>VLOOKUP(K30, Criterios!$A$81:$B$120, 2, FALSE)), "División no coincide con Categoría", ""))), IF(OR(L30="", L30=""), "[Aviso] Género no capturado ()", IF(ISNA(MATCH(L30, Criterios!$B$123:$B$127, 0)), "Género no válido", "")), IF(OR(N30="", N30=""), "[Aviso] Temporada no capturada ()", IF(ISNA(MATCH(N30, Criterios!$C$123:$C$128, 0)), "Temporada no válida", "")), IF(OR(O30="", O30=""), "[Aviso] Ciclo de vida no capturado ()", IF(ISNA(MATCH(O30, Criterios!$D$123:$D$124, 0)), "Ciclo de vida no válido", "")))) | AG30: Nuevo – Odoo Universal Unique Brands 01/10/2026 | AH30: 01/10/2026: alta desde Odoo Universal Unique Brands (no existía en Productos por código de barras ni SKU) | Talla tomada del sufijo del SKU (S); Categoría: Palabra clave "Camisa" en tipo/categoría de la fuente (Ropa / Camisas) | Homologación G1522 06/10/2026: WB N.º de estilo: «» → «01-001-0024-7008» (Completado por regla) · Validador Shopify: WB: precio con IVA no termina en 9 | AK30: Odoo: producto 21119 / plantilla 27122 | AN30: Odoo Universal Unique Brands | AQ30: 6 | AR30: Odoo Universal Unique Brands › Bodega 25 › Bodega 25/General: 6
A31: 199168041977 | C31: Roper | D31: 01-001-0024-7008 | E31: 01-001-0024-7008 BL-XL | F31: XL | G31: XL | H31: Roper | I31: ROPER Shirt Bl/Gy/Br Plaid | J31: Ropa | K31: Camisas | V31: PZS | W31: 53101602 | Y31: 33.48 | Z31: 889 | AA31: =IF(AND(A31="", B31="", E31=""), "", IF(AB31="", "Válido", IF((LEN(AB31)-LEN(SUBSTITUTE(AB31,"; ","")))/2+1>(LEN(AB31)-LEN(SUBSTITUTE(AB31,"[Aviso]","")))/7, "Con Incidencias", "Válido"))) | AB31: =IF(AND(A31="", B31="", E31=""), "", TEXTJOIN("; ", TRUE, IF(OR(TRIM(A31&"")="", ISNUMBER(SEARCH("FALTA", A31))), "UPC faltante/inválido", ""), IF(AND(A31<>"", IFERROR(_xlfn.XMATCH(A31,$A$2:$A$285,0,1)<>_xlfn.XMATCH(A31,$A$2:$A$285,0,-1),FALSE)), "Código de barras duplicado", ""), IF(AND(E31<>"", COUNTIF($E$2:$E$285, E31)>1), "SKU duplicado", ""), IF(OR(J31="", J31=""), "[Aviso] División no capturada ()", IF(ISNA(MATCH(J31, Criterios!$A$123:$A$126, 0)), "División no válida", "")), IF(OR(K31="", K31=""), "[Aviso] Categoría no capturada ()", IF(ISNA(MATCH(K31, Criterios!$A$81:$A$120, 0)), "Categoría no válida", IF(AND(J31<>"", J31<>"", J31<>VLOOKUP(K31, Criterios!$A$81:$B$120, 2, FALSE)), "División no coincide con Categoría", ""))), IF(OR(L31="", L31=""), "[Aviso] Género no capturado ()", IF(ISNA(MATCH(L31, Criterios!$B$123:$B$127, 0)), "Género no válido", "")), IF(OR(N31="", N31=""), "[Aviso] Temporada no capturada ()", IF(ISNA(MATCH(N31, Criterios!$C$123:$C$128, 0)), "Temporada no válida", "")), IF(OR(O31="", O31=""), "[Aviso] Ciclo de vida no capturado ()", IF(ISNA(MATCH(O31, Criterios!$D$123:$D$124, 0)), "Ciclo de vida no válido", "")))) | AG31: Nuevo – Odoo Universal Unique Brands 01/10/2026 | AH31: 01/10/2026: alta desde Odoo Universal Unique Brands (no existía en Productos por código de barras ni SKU) | Talla tomada del sufijo del SKU (XL); Categoría: Palabra clave "Camisa" en tipo/categoría de la fuente (Ropa / Camisas) | Homologación G1522 06/10/2026: WB N.º de estilo: «» → «01-001-0024-7008» (Completado por regla) · Validador Shopify: WB: precio con IVA no termina en 9 | AK31: Odoo: producto 21122 / plantilla 27125 | AN31: Odoo Universal Unique Brands | AQ31: 9 | AR31: Odoo Universal Unique Brands › Bodega 25 › Bodega 25/General: 9
A32: 199168087999 | C32: Roper | D32: 01-001-0044-1084 | E32: 01-001-0044-1084 BR-2XL | F32: XXL | G32: XXL | H32: Roper | I32: ROPER Shirt Brown & Blue Wide Stripe | J32: Ropa | K32: Camisas | L32: Hombre | P32: Cafe | V32: PZS | W32: 53101602 | Y32: 27 | Z32: 729 | AA32: =IF(AND(A32="", B32="", E32=""), "", IF(AB32="", "Válido", IF((LEN(AB32)-LEN(SUBSTITUTE(AB32,"; ","")))/2+1>(LEN(AB32)-LEN(SUBSTITUTE(AB32,"[Aviso]","")))/7, "Con Incidencias", "Válido"))) | AB32: =IF(AND(A32="", B32="", E32=""), "", TEXTJOIN("; ", TRUE, IF(OR(TRIM(A32&"")="", ISNUMBER(SEARCH("FALTA", A32))), "UPC faltante/inválido", ""), IF(AND(A32<>"", IFERROR(_xlfn.XMATCH(A32,$A$2:$A$285,0,1)<>_xlfn.XMATCH(A32,$A$2:$A$285,0,-1),FALSE)), "Código de barras duplicado", ""), IF(AND(E32<>"", COUNTIF($E$2:$E$285, E32)>1), "SKU duplicado", ""), IF(OR(J32="", J32=""), "[Aviso] División no capturada ()", IF(ISNA(MATCH(J32, Criterios!$A$123:$A$126, 0)), "División no válida", "")), IF(OR(K32="", K32=""), "[Aviso] Categoría no capturada ()", IF(ISNA(MATCH(K32, Criterios!$A$81:$A$120, 0)), "Categoría no válida", IF(AND(J32<>"", J32<>"", J32<>VLOOKUP(K32, Criterios!$A$81:$B$120, 2, FALSE)), "División no coincide con Categoría", ""))), IF(OR(L32="", L32=""), "[Aviso] Género no capturado ()", IF(ISNA(MATCH(L32, Criterios!$B$123:$B$127, 0)), "Género no válido", "")), IF(OR(N32="", N32=""), "[Aviso] Temporada no capturada ()", IF(ISNA(MATCH(N32, Criterios!$C$123:$C$128, 0)), "Temporada no válida", "")), IF(OR(O32="", O32=""), "[Aviso] Ciclo de vida no capturado ()", IF(ISNA(MATCH(O32, Criterios!$D$123:$D$124, 0)), "Ciclo de vida no válido", "")))) | AG32: Nuevo – Odoo Universal Unique Brands 01/10/2026 | AH32: 01/10/2026: alta desde Odoo Universal Unique Brands (no existía en Productos por código de barras ni SKU) | Categoría: Palabra clave "Camisa" en tipo/categoría de la fuente (Ropa / Camisas); Género: campo de la fuente; Color detectado en el nombre (brown) | Homologación G1522 06/10/2026: WB N.º de estilo: «» → «01-001-0044-1084» (Completado por regla) · Validador Shopify: WB: precio con IVA no termina en 9 | AK32: Odoo: producto 20851 / plantilla 26854 | AN32: Odoo Universal Unique Brands | AQ32: 10 | AR32: Odoo Universal Unique Brands › Bodega 25 › Bodega 25/General: 10
A33: 199168087951 | C33: Roper | D33: 01-001-0044-1084 | E33: 01-001-0044-1084 BR-L | F33: L | G33: L | H33: Roper | I33: ROPER Shirt Brown & Blue Wide Stripe | J33: Ropa | K33: Camisas | L33: Hombre | P33: Cafe | V33: PZS | W33: 53101602 | Y33: 27 | Z33: 729 | AA33: =IF(AND(A33="", B33="", E33=""), "", IF(AB33="", "Válido", IF((LEN(AB33)-LEN(SUBSTITUTE(AB33,"; ","")))/2+1>(LEN(AB33)-LEN(SUBSTITUTE(AB33,"[Aviso]","")))/7, "Con Incidencias", "Válido"))) | AB33: =IF(AND(A33="", B33="", E33=""), "", TEXTJOIN("; ", TRUE, IF(OR(TRIM(A33&"")="", ISNUMBER(SEARCH("FALTA", A33))), "UPC faltante/inválido", ""), IF(AND(A33<>"", IFERROR(_xlfn.XMATCH(A33,$A$2:$A$285,0,1)<>_xlfn.XMATCH(A33,$A$2:$A$285,0,-1),FALSE)), "Código de barras duplicado", ""), IF(AND(E33<>"", COUNTIF($E$2:$E$285, E33)>1), "SKU duplicado", ""), IF(OR(J33="", J33=""), "[Aviso] División no capturada ()", IF(ISNA(MATCH(J33, Criterios!$A$123:$A$126, 0)), "División no válida", "")), IF(OR(K33="", K33=""), "[Aviso] Categoría no capturada ()", IF(ISNA(MATCH(K33, Criterios!$A$81:$A$120, 0)), "Categoría no válida", IF(AND(J33<>"", J33<>"", J33<>VLOOKUP(K33, Criterios!$A$81:$B$120, 2, FALSE)), "División no coincide con Categoría", ""))), IF(OR(L33="", L33=""), "[Aviso] Género no capturado ()", IF(ISNA(MATCH(L33, Criterios!$B$123:$B$127, 0)), "Género no válido", "")), IF(OR(N33="", N33=""), "[Aviso] Temporada no capturada ()", IF(ISNA(MATCH(N33, Criterios!$C$123:$C$128, 0)), "Temporada no válida", "")), IF(OR(O33="", O33=""), "[Aviso] Ciclo de vida no capturado ()", IF(ISNA(MATCH(O33, Criterios!$D$123:$D$124, 0)), "Ciclo de vida no válido", "")))) | AG33: Nuevo – Odoo Universal Unique Brands 01/10/2026 | AH33: 01/10/2026: alta desde Odoo Universal Unique Brands (no existía en Productos por código de barras ni SKU) | Categoría: Palabra clave "Camisa" en tipo/categoría de la fuente (Ropa / Camisas); Género: campo de la fuente; Color detectado en el nombre (brown) | Homologación G1522 06/10/2026: WB N.º de estilo: «» → «01-001-0044-1084» (Completado por regla) · Validador Shopify: WB: precio con IVA no termina en 9 | AK33: Odoo: producto 20849 / plantilla 26852 | AN33: Odoo Universal Unique Brands | AQ33: 30 | AR33: Odoo Universal Unique Brands › Bodega 25 › Bodega 25/General: 30
A34: 199168087968 | C34: Roper | D34: 01-001-0044-1084 | E34: 01-001-0044-1084 BR-M | F34: M | G34: M | H34: Roper | I34: ROPER Shirt Brown & Blue Wide Stripe | J34: Ropa | K34: Camisas | L34: Hombre | P34: Cafe | V34: PZS | W34: 53101602 | Y34: 27 | Z34: 729 | AA34: =IF(AND(A34="", B34="", E34=""), "", IF(AB34="", "Válido", IF((LEN(AB34)-LEN(SUBSTITUTE(AB34,"; ","")))/2+1>(LEN(AB34)-LEN(SUBSTITUTE(AB34,"[Aviso]","")))/7, "Con Incidencias", "Válido"))) | AB34: =IF(AND(A34="", B34="", E34=""), "", TEXTJOIN("; ", TRUE, IF(OR(TRIM(A34&"")="", ISNUMBER(SEARCH("FALTA", A34))), "UPC faltante/inválido", ""), IF(AND(A34<>"", IFERROR(_xlfn.XMATCH(A34,$A$2:$A$285,0,1)<>_xlfn.XMATCH(A34,$A$2:$A$285,0,-1),FALSE)), "Código de barras duplicado", ""), IF(AND(E34<>"", COUNTIF($E$2:$E$285, E34)>1), "SKU duplicado", ""), IF(OR(J34="", J34=""), "[Aviso] División no capturada ()", IF(ISNA(MATCH(J34, Criterios!$A$123:$A$126, 0)), "División no válida", "")), IF(OR(K34="", K34=""), "[Aviso] Categoría no capturada ()", IF(ISNA(MATCH(K34, Criterios!$A$81:$A$120, 0)), "Categoría no válida", IF(AND(J34<>"", J34<>"", J34<>VLOOKUP(K34, Criterios!$A$81:$B$120, 2, FALSE)), "División no coincide con Categoría", ""))), IF(OR(L34="", L34=""), "[Aviso] Género no capturado ()", IF(ISNA(MATCH(L34, Criterios!$B$123:$B$127, 0)), "Género no válido", "")), IF(OR(N34="", N34=""), "[Aviso] Temporada no capturada ()", IF(ISNA(MATCH(N34, Criterios!$C$123:$C$128, 0)), "Temporada no válida", "")), IF(OR(O34="", O34=""), "[Aviso] Ciclo de vida no capturado ()", IF(ISNA(MATCH(O34, Criterios!$D$123:$D$124, 0)), "Ciclo de vida no válido", "")))) | AG34: Nuevo – Odoo Universal Unique Brands 01/10/2026 | AH34: 01/10/2026: alta desde Odoo Universal Unique Brands (no existía en Productos por código de barras ni SKU) | Categoría: Palabra clave "Camisa" en tipo/categoría de la fuente (Ropa / Camisas); Género: campo de la fuente; Color detectado en el nombre (brown) | Homologación G1522 06/10/2026: WB N.º de estilo: «» → «01-001-0044-1084» (Completado por regla) · Validador Shopify: WB: precio con IVA no termina en 9 | AK34: Odoo: producto 20848 / plantilla 26851 | AN34: Odoo Universal Unique Brands | AQ34: 30 | AR34: Odoo Universal Unique Brands › Bodega 25 › Bodega 25/General: 30
A35: 199168087975 | C35: Roper | D35: 01-001-0044-1084 | E35: 01-001-0044-1084 BR-S | F35: S | G35: S | H35: Roper | I35: ROPER Shirt Brown & Blue Wide Stripe | J35: Ropa | K35: Camisas | L35: Hombre | P35: Cafe | V35: PZS | W35: 53101602 | Y35: 27 | Z35: 729 | AA35: =IF(AND(A35="", B35="", E35=""), "", IF(AB35="", "Válido", IF((LEN(AB35)-LEN(SUBSTITUTE(AB35,"; ","")))/2+1>(LEN(AB35)-LEN(SUBSTITUTE(AB35,"[Aviso]","")))/7, "Con Incidencias", "Válido"))) | AB35: =IF(AND(A35="", B35="", E35=""), "", TEXTJOIN("; ", TRUE, IF(OR(TRIM(A35&"")="", ISNUMBER(SEARCH("FALTA", A35))), "UPC faltante/inválido", ""), IF(AND(A35<>"", IFERROR(_xlfn.XMATCH(A35,$A$2:$A$285,0,1)<>_xlfn.XMATCH(A35,$A$2:$A$285,0,-1),FALSE)), "Código de barras duplicado", ""), IF(AND(E35<>"", COUNTIF($E$2:$E$285, E35)>1), "SKU duplicado", ""), IF(OR(J35="", J35=""), "[Aviso] División no capturada ()", IF(ISNA(MATCH(J35, Criterios!$A$123:$A$126, 0)), "División no válida", "")), IF(OR(K35="", K35=""), "[Aviso] Categoría no capturada ()", IF(ISNA(MATCH(K35, Criterios!$A$81:$A$120, 0)), "Categoría no válida", IF(AND(J35<>"", J35<>"", J35<>VLOOKUP(K35, Criterios!$A$81:$B$120, 2, FALSE)), "División no coincide con Categoría", ""))), IF(OR(L35="", L35=""), "[Aviso] Género no capturado ()", IF(ISNA(MATCH(L35, Criterios!$B$123:$B$127, 0)), "Género no válido", "")), IF(OR(N35="", N35=""), "[Aviso] Temporada no capturada ()", IF(ISNA(MATCH(N35, Criterios!$C$123:$C$128, 0)), "Temporada no válida", "")), IF(OR(O35="", O35=""), "[Aviso] Ciclo de vida no capturado ()", IF(ISNA(MATCH(O35, Criterios!$D$123:$D$124, 0)), "Ciclo de vida no válido", "")))) | AG35: Nuevo – Odoo Universal Unique Brands 01/10/2026 | AH35: 01/10/2026: alta desde Odoo Universal Unique Brands (no existía en Productos por código de barras ni SKU) | Categoría: Palabra clave "Camisa" en tipo/categoría de la fuente (Ropa / Camisas); Género: campo de la fuente; Color detectado en el nombre (brown) | Homologación G1522 06/10/2026: WB N.º de estilo: «» → «01-001-0044-1084» (Completado por regla) · Validador Shopify: WB: precio con IVA no termina en 9 | AK35: Odoo: producto 20847 / plantilla 26850 | AN35: Odoo Universal Unique Brands | AQ35: 30 | AR35: Odoo Universal Unique Brands › Bodega 25 › Bodega 25/General: 30
A36: 199168087982 | C36: Roper | D36: 01-001-0044-1084 | E36: 01-001-0044-1084 BR-XL | F36: XL | G36: XL | H36: Roper | I36: ROPER Shirt Brown & Blue Wide Stripe | J36: Ropa | K36: Camisas | L36: Hombre | P36: Cafe | V36: PZS | W36: 53101602 | Y36: 27 | Z36: 729 | AA36: =IF(AND(A36="", B36="", E36=""), "", IF(AB36="", "Válido", IF((LEN(AB36)-LEN(SUBSTITUTE(AB36,"; ","")))/2+1>(LEN(AB36)-LEN(SUBSTITUTE(AB36,"[Aviso]","")))/7, "Con Incidencias", "Válido"))) | AB36: =IF(AND(A36="", B36="", E36=""), "", TEXTJOIN("; ", TRUE, IF(OR(TRIM(A36&"")="", ISNUMBER(SEARCH("FALTA", A36))), "UPC faltante/inválido", ""), IF(AND(A36<>"", IFERROR(_xlfn.XMATCH(A36,$A$2:$A$285,0,1)<>_xlfn.XMATCH(A36,$A$2:$A$285,0,-1),FALSE)), "Código de barras duplicado", ""), IF(AND(E36<>"", COUNTIF($E$2:$E$285, E36)>1), "SKU duplicado", ""), IF(OR(J36="", J36=""), "[Aviso] División no capturada ()", IF(ISNA(MATCH(J36, Criterios!$A$123:$A$126, 0)), "División no válida", "")), IF(OR(K36="", K36=""), "[Aviso] Categoría no capturada ()", IF(ISNA(MATCH(K36, Criterios!$A$81:$A$120, 0)), "Categoría no válida", IF(AND(J36<>"", J36<>"", J36<>VLOOKUP(K36, Criterios!$A$81:$B$120, 2, FALSE)), "División no coincide con Categoría", ""))), IF(OR(L36="", L36=""), "[Aviso] Género no capturado ()", IF(ISNA(MATCH(L36, Criterios!$B$123:$B$127, 0)), "Género no válido", "")), IF(OR(N36="", N36=""), "[Aviso] Temporada no capturada ()", IF(ISNA(MATCH(N36, Criterios!$C$123:$C$128, 0)), "Temporada no válida", "")), IF(OR(O36="", O36=""), "[Aviso] Ciclo de vida no capturado ()", IF(ISNA(MATCH(O36, Criterios!$D$123:$D$124, 0)), "Ciclo de vida no válido", "")))) | AG36: Nuevo – Odoo Universal Unique Brands 01/10/2026 | AH36: 01/10/2026: alta desde Odoo Universal Unique Brands (no existía en Productos por código de barras ni SKU) | Categoría: Palabra clave "Camisa" en tipo/categoría de la fuente (Ropa / Camisas); Género: campo de la fuente; Color detectado en el nombre (brown) | Homologación G1522 06/10/2026: WB N.º de estilo: «» → «01-001-0044-1084» (Completado por regla) · Validador Shopify: WB: precio con IVA no termina en 9 | AK36: Odoo: producto 20850 / plantilla 26853 | AN36: Odoo Universal Unique Brands | AQ36: 20 | AR36: Odoo Universal Unique Brands › Bodega 25 › Bodega 25/General: 20
A37: 199168042288 | C37: Roper | D37: 01-001-0086-7011 | E37: 01-001-0086-7011 BL-2XL | F37: XXL | G37: XXL | H37: Roper | I37: ROPER Shirt Black/Grey Floral | J37: Ropa | K37: Camisas | P37: Negro | V37: PZS | W37: 53101602 | Y37: 28.13 | Z37: 759 | AA37: =IF(AND(A37="", B37="", E37=""), "", IF(AB37="", "Válido", IF((LEN(AB37)-LEN(SUBSTITUTE(AB37,"; ","")))/2+1>(LEN(AB37)-LEN(SUBSTITUTE(AB37,"[Aviso]","")))/7, "Con Incidencias", "Válido"))) | AB37: =IF(AND(A37="", B37="", E37=""), "", TEXTJOIN("; ", TRUE, IF(OR(TRIM(A37&"")="", ISNUMBER(SEARCH("FALTA", A37))), "UPC faltante/inválido", ""), IF(AND(A37<>"", IFERROR(_xlfn.XMATCH(A37,$A$2:$A$285,0,1)<>_xlfn.XMATCH(A37,$A$2:$A$285,0,-1),FALSE)), "Código de barras duplicado", ""), IF(AND(E37<>"", COUNTIF($E$2:$E$285, E37)>1), "SKU duplicado", ""), IF(OR(J37="", J37=""), "[Aviso] División no capturada ()", IF(ISNA(MATCH(J37, Criterios!$A$123:$A$126, 0)), "División no válida", "")), IF(OR(K37="", K37=""), "[Aviso] Categoría no capturada ()", IF(ISNA(MATCH(K37, Criterios!$A$81:$A$120, 0)), "Categoría no válida", IF(AND(J37<>"", J37<>"", J37<>VLOOKUP(K37, Criterios!$A$81:$B$120, 2, FALSE)), "División no coincide con Categoría", ""))), IF(OR(L37="", L37=""), "[Aviso] Género no capturado ()", IF(ISNA(MATCH(L37, Criterios!$B$123:$B$127, 0)), "Género no válido", "")), IF(OR(N37="", N37=""), "[Aviso] Temporada no capturada ()", IF(ISNA(MATCH(N37, Criterios!$C$123:$C$128, 0)), "Temporada no válida", "")), IF(OR(O37="", O37=""), "[Aviso] Ciclo de vida no capturado ()", IF(ISNA(MATCH(O37, Criterios!$D$123:$D$124, 0)), "Ciclo de vida no válido", "")))) | AG37: Nuevo – Odoo Universal Unique Brands 01/10/2026 | AH37: 01/10/2026: alta desde Odoo Universal Unique Brands (no existía en Productos por código de barras ni SKU) | Talla tomada del sufijo del SKU (2XL); Categoría: Palabra clave "Camisa" en tipo/categoría de la fuente (Ropa / Camisas); Talla: 2XL→XXL; Color detectado en el nombre (black) | Homologación G1522 06/10/2026: WB N.º de estilo: «» → «01-001-0086-7011» (Completado por regla) · Validador Shopify: WB: precio con IVA no termina en 9 | AK37: Odoo: producto 21070 / plantilla 27073 | AN37: Odoo Universal Unique Brands | AQ37: 2 | AR37: Odoo Universal Unique Brands › Bodega 25 › Bodega 25/General: 2
A38: 199168042240 | C38: Roper | D38: 01-001-0086-7011 | E38: 01-001-0086-7011 BL-L | F38: L | G38: L | H38: Roper | I38: ROPER Shirt Black/Grey Floral | J38: Ropa | K38: Camisas | P38: Negro | V38: PZS | W38: 53101602 | Y38: 28.13 | Z38: 759 | AA38: =IF(AND(A38="", B38="", E38=""), "", IF(AB38="", "Válido", IF((LEN(AB38)-LEN(SUBSTITUTE(AB38,"; ","")))/2+1>(LEN(AB38)-LEN(SUBSTITUTE(AB38,"[Aviso]","")))/7, "Con Incidencias", "Válido"))) | AB38: =IF(AND(A38="", B38="", E38=""), "", TEXTJOIN("; ", TRUE, IF(OR(TRIM(A38&"")="", ISNUMBER(SEARCH("FALTA", A38))), "UPC faltante/inválido", ""), IF(AND(A38<>"", IFERROR(_xlfn.XMATCH(A38,$A$2:$A$285,0,1)<>_xlfn.XMATCH(A38,$A$2:$A$285,0,-1),FALSE)), "Código de barras duplicado", ""), IF(AND(E38<>"", COUNTIF($E$2:$E$285, E38)>1), "SKU duplicado", ""), IF(OR(J38="", J38=""), "[Aviso] División no capturada ()", IF(ISNA(MATCH(J38, Criterios!$A$123:$A$126, 0)), "División no válida", "")), IF(OR(K38="", K38=""), "[Aviso] Categoría no capturada ()", IF(ISNA(MATCH(K38, Criterios!$A$81:$A$120, 0)), "Categoría no válida", IF(AND(J38<>"", J38<>"", J38<>VLOOKUP(K38, Criterios!$A$81:$B$120, 2, FALSE)), "División no coincide con Categoría", ""))), IF(OR(L38="", L38=""), "[Aviso] Género no capturado ()", IF(ISNA(MATCH(L38, Criterios!$B$123:$B$127, 0)), "Género no válido", "")), IF(OR(N38="", N38=""), "[Aviso] Temporada no capturada ()", IF(ISNA(MATCH(N38, Criterios!$C$123:$C$128, 0)), "Temporada no válida", "")), IF(OR(O38="", O38=""), "[Aviso] Ciclo de vida no capturado ()", IF(ISNA(MATCH(O38, Criterios!$D$123:$D$124, 0)), "Ciclo de vida no válido", "")))) | AG38: Nuevo – Odoo Universal Unique Brands 01/10/2026 | AH38: 01/10/2026: alta desde Odoo Universal Unique Brands (no existía en Productos por código de barras ni SKU) | Talla tomada del sufijo del SKU (L); Categoría: Palabra clave "Camisa" en tipo/categoría de la fuente (Ropa / Camisas); Color detectado en el nombre (black) | Homologación G1522 06/10/2026: WB N.º de estilo: «» → «01-001-0086-7011» (Completado por regla) · Validador Shopify: WB: precio con IVA no termina en 9 | AK38: Odoo: producto 21560 / plantilla 27571 | AN38: Odoo Universal Unique Brands | AQ38: 0
A39: 199168042257 | C39: Roper | D39: 01-001-0086-7011 | E39: 01-001-0086-7011 BL-M | F39: M | G39: M | H39: Roper | I39: ROPER Shirt Black/Grey Floral | J39: Ropa | K39: Camisas | L39: Hombre | P39: Negro | V39: PZS | W39: 53101602 | Y39: 28.13 | Z39: 759 | AA39: =IF(AND(A39="", B39="", E39=""), "", IF(AB39="", "Válido", IF((LEN(AB39)-LEN(SUBSTITUTE(AB39,"; ","")))/2+1>(LEN(AB39)-LEN(SUBSTITUTE(AB39,"[Aviso]","")))/7, "Con Incidencias", "Válido"))) | AB39: =IF(AND(A39="", B39="", E39=""), "", TEXTJOIN("; ", TRUE, IF(OR(TRIM(A39&"")="", ISNUMBER(SEARCH("FALTA", A39))), "UPC faltante/inválido", ""), IF(AND(A39<>"", IFERROR(_xlfn.XMATCH(A39,$A$2:$A$285,0,1)<>_xlfn.XMATCH(A39,$A$2:$A$285,0,-1),FALSE)), "Código de barras duplicado", ""), IF(AND(E39<>"", COUNTIF($E$2:$E$285, E39)>1), "SKU duplicado", ""), IF(OR(J39="", J39=""), "[Aviso] División no capturada ()", IF(ISNA(MATCH(J39, Criterios!$A$123:$A$126, 0)), "División no válida", "")), IF(OR(K39="", K39=""), "[Aviso] Categoría no capturada ()", IF(ISNA(MATCH(K39, Criterios!$A$81:$A$120, 0)), "Categoría no válida", IF(AND(J39<>"", J39<>"", J39<>VLOOKUP(K39, Criterios!$A$81:$B$120, 2, FALSE)), "División no coincide con Categoría", ""))), IF(OR(L39="", L39=""), "[Aviso] Género no capturado ()", IF(ISNA(MATCH(L39, Criterios!$B$123:$B$127, 0)), "Género no válido", "")), IF(OR(N39="", N39=""), "[Aviso] Temporada no capturada ()", IF(ISNA(MATCH(N39, Criterios!$C$123:$C$128, 0)), "Temporada no válida", "")), IF(OR(O39="", O39=""), "[Aviso] Ciclo de vida no capturado ()", IF(ISNA(MATCH(O39, Criterios!$D$123:$D$124, 0)), "Ciclo de vida no válido", "")))) | AG39: Nuevo – Odoo Universal Unique Brands 01/10/2026 | AH39: 01/10/2026: alta desde Odoo Universal Unique Brands (no existía en Productos por código de barras ni SKU) | Categoría: Palabra clave "Camisa" en tipo/categoría de la fuente (Ropa / Camisas); Género: campo de la fuente; Color detectado en el nombre (black) | Homologación G1522 06/10/2026: WB N.º de estilo: «» → «01-001-0086-7011» (Completado por regla) · Validador Shopify: WB: precio con IVA no termina en 9 | AK39: Odoo: producto 21067 / plantilla 27070 | AN39: Odoo Universal Unique Brands | AQ39: 1 | AR39: Odoo Universal Unique Brands › Bodega 25 › Bodega 25/General: 1
A40: 199168042264 | C40: Roper | D40: 01-001-0086-7011 | E40: 01-001-0086-7011 BL-S | F40: S | G40: S | H40: Roper | I40: ROPER Shirt Black/Grey Floral | J40: Ropa | K40: Camisas | L40: Hombre | P40: Negro | V40: PZS | W40: 53101602 | Y40: 28.13 | Z40: 759 | AA40: =IF(AND(A40="", B40="", E40=""), "", IF(AB40="", "Válido", IF((LEN(AB40)-LEN(SUBSTITUTE(AB40,"; ","")))/2+1>(LEN(AB40)-LEN(SUBSTITUTE(AB40,"[Aviso]","")))/7, "Con Incidencias", "Válido"))) | AB40: =IF(AND(A40="", B40="", E40=""), "", TEXTJOIN("; ", TRUE, IF(OR(TRIM(A40&"")="", ISNUMBER(SEARCH("FALTA", A40))), "UPC faltante/inválido", ""), IF(AND(A40<>"", IFERROR(_xlfn.XMATCH(A40,$A$2:$A$285,0,1)<>_xlfn.XMATCH(A40,$A$2:$A$285,0,-1),FALSE)), "Código de barras duplicado", ""), IF(AND(E40<>"", COUNTIF($E$2:$E$285, E40)>1), "SKU duplicado", ""), IF(OR(J40="", J40=""), "[Aviso] División no capturada ()", IF(ISNA(MATCH(J40, Criterios!$A$123:$A$126, 0)), "División no válida", "")), IF(OR(K40="", K40=""), "[Aviso] Categoría no capturada ()", IF(ISNA(MATCH(K40, Criterios!$A$81:$A$120, 0)), "Categoría no válida", IF(AND(J40<>"", J40<>"", J40<>VLOOKUP(K40, Criterios!$A$81:$B$120, 2, FALSE)), "División no coincide con Categoría", ""))), IF(OR(L40="", L40=""), "[Aviso] Género no capturado ()", IF(ISNA(MATCH(L40, Criterios!$B$123:$B$127, 0)), "Género no válido", "")), IF(OR(N40="", N40=""), "[Aviso] Temporada no capturada ()", IF(ISNA(MATCH(N40, Criterios!$C$123:$C$128, 0)), "Temporada no válida", "")), IF(OR(O40="", O40=""), "[Aviso] Ciclo de vida no capturado ()", IF(ISNA(MATCH(O40, Criterios!$D$123:$D$124, 0)), "Ciclo de vida no válido", "")))) | AG40: Nuevo – Odoo Universal Unique Brands 01/10/2026 | AH40: 01/10/2026: alta desde Odoo Universal Unique Brands (no existía en Productos por código de barras ni SKU) | Categoría: Palabra clave "Camisa" en tipo/categoría de la fuente (Ropa / Camisas); Género: campo de la fuente; Color detectado en el nombre (black) | Homologación G1522 06/10/2026: WB N.º de estilo: «» → «01-001-0086-7011» (Completado por regla) · Validador Shopify: WB: precio con IVA no termina en 9 | AK40: Odoo: producto 21066 / plantilla 27069 | AN40: Odoo Universal Unique Brands | AQ40: 1 | AR40: Odoo Universal Unique Brands › Bodega 25 › Bodega 25/General: 1
A41: 199168042271 | C41: Roper | D41: 01-001-0086-7011 | E41: 01-001-0086-7011 BL-XL | F41: XL | G41: XL | H41: Roper | I41: ROPER Shirt Black/Grey Floral | J41: Ropa | K41: Camisas | L41: Hombre | P41: Negro | V41: PZS | W41: 53101602 | Y41: 28.13 | Z41: 759 | AA41: =IF(AND(A41="", B41="", E41=""), "", IF(AB41="", "Válido", IF((LEN(AB41)-LEN(SUBSTITUTE(AB41,"; ","")))/2+1>(LEN(AB41)-LEN(SUBSTITUTE(AB41,"[Aviso]","")))/7, "Con Incidencias", "Válido"))) | AB41: =IF(AND(A41="", B41="", E41=""), "", TEXTJOIN("; ", TRUE, IF(OR(TRIM(A41&"")="", ISNUMBER(SEARCH("FALTA", A41))), "UPC faltante/inválido", ""), IF(AND(A41<>"", IFERROR(_xlfn.XMATCH(A41,$A$2:$A$285,0,1)<>_xlfn.XMATCH(A41,$A$2:$A$285,0,-1),FALSE)), "Código de barras duplicado", ""), IF(AND(E41<>"", COUNTIF($E$2:$E$285, E41)>1), "SKU duplicado", ""), IF(OR(J41="", J41=""), "[Aviso] División no capturada ()", IF(ISNA(MATCH(J41, Criterios!$A$123:$A$126, 0)), "División no válida", "")), IF(OR(K41="", K41=""), "[Aviso] Categoría no capturada ()", IF(ISNA(MATCH(K41, Criterios!$A$81:$A$120, 0)), "Categoría no válida", IF(AND(J41<>"", J41<>"", J41<>VLOOKUP(K41, Criterios!$A$81:$B$120, 2, FALSE)), "División no coincide con Categoría", ""))), IF(OR(L41="", L41=""), "[Aviso] Género no capturado ()", IF(ISNA(MATCH(L41, Criterios!$B$123:$B$127, 0)), "Género no válido", "")), IF(OR(N41="", N41=""), "[Aviso] Temporada no capturada ()", IF(ISNA(MATCH(N41, Criterios!$C$123:$C$128, 0)), "Temporada no válida", "")), IF(OR(O41="", O41=""), "[Aviso] Ciclo de vida no capturado ()", IF(ISNA(MATCH(O41, Criterios!$D$123:$D$124, 0)), "Ciclo de vida no válido", "")))) | AG41: Nuevo – Odoo Universal Unique Brands 01/10/2026 | AH41: 01/10/2026: alta desde Odoo Universal Unique Brands (no existía en Productos por código de barras ni SKU) | Categoría: Palabra clave "Camisa" en tipo/categoría de la fuente (Ropa / Camisas); Género: campo de la fuente; Color detectado en el nombre (black) | Homologación G1522 06/10/2026: WB N.º de estilo: «» → «01-001-0086-7011» (Completado por regla) · Validador Shopify: WB: precio con IVA no termina en 9 | AK41: Odoo: producto 21069 / plantilla 27072 | AN41: Odoo Universal Unique Brands | AQ41: 1 | AR41: Odoo Universal Unique Brands › Bodega 25 › Bodega 25/General: 1
A42: 199168042707 | C42: Roper | D42: 01-001-0101-7003 | E42: 01-001-0101-7003 BR-2XL | F42: XXL | G42: XXL | H42: Roper | I42: ROPER Shirt Brown/Black/Tan Plaid | J42: Ropa | K42: Camisas | P42: Cafe | V42: PZS | W42: 53101602 | Y42: 22.55 | Z42: 629 | AA42: =IF(AND(A42="", B42="", E42=""), "", IF(AB42="", "Válido", IF((LEN(AB42)-LEN(SUBSTITUTE(AB42,"; ","")))/2+1>(LEN(AB42)-LEN(SUBSTITUTE(AB42,"[Aviso]","")))/7, "Con Incidencias", "Válido"))) | AB42: =IF(AND(A42="", B42="", E42=""), "", TEXTJOIN("; ", TRUE, IF(OR(TRIM(A42&"")="", ISNUMBER(SEARCH("FALTA", A42))), "UPC faltante/inválido", ""), IF(AND(A42<>"", IFERROR(_xlfn.XMATCH(A42,$A$2:$A$285,0,1)<>_xlfn.XMATCH(A42,$A$2:$A$285,0,-1),FALSE)), "Código de barras duplicado", ""), IF(AND(E42<>"", COUNTIF($E$2:$E$285, E42)>1), "SKU duplicado", ""), IF(OR(J42="", J42=""), "[Aviso] División no capturada ()", IF(ISNA(MATCH(J42, Criterios!$A$123:$A$126, 0)), "División no válida", "")), IF(OR(K42="", K42=""), "[Aviso] Categoría no capturada ()", IF(ISNA(MATCH(K42, Criterios!$A$81:$A$120, 0)), "Categoría no válida", IF(AND(J42<>"", J42<>"", J42<>VLOOKUP(K42, Criterios!$A$81:$B$120, 2, FALSE)), "División no coincide con Categoría", ""))), IF(OR(L42="", L42=""), "[Aviso] Género no capturado ()", IF(ISNA(MATCH(L42, Criterios!$B$123:$B$127, 0)), "Género no válido", "")), IF(OR(N42="", N42=""), "[Aviso] Temporada no capturada ()", IF(ISNA(MATCH(N42, Criterios!$C$123:$C$128, 0)), "Temporada no válida", "")), IF(OR(O42="", O42=""), "[Aviso] Ciclo de vida no capturado ()", IF(ISNA(MATCH(O42, Criterios!$D$123:$D$124, 0)), "Ciclo de vida no válido", "")))) | AG42: Nuevo – Odoo Universal Unique Brands 01/10/2026 | AH42: 01/10/2026: alta desde Odoo Universal Unique Brands (no existía en Productos por código de barras ni SKU) | Talla tomada del sufijo del SKU (2XL); Categoría: Palabra clave "Camisa" en tipo/categoría de la fuente (Ropa / Camisas); Talla: 2XL→XXL; Color detectado en el nombre (brown) | Homologación G1522 06/10/2026: WB N.º de estilo: «» → «01-001-0101-7003» (Completado por regla) | AK42: Odoo: producto 21118 / plantilla 27121 | AN42: Odoo Universal Unique Brands | AQ42: 2 | AR42: Odoo Universal Unique Brands › Bodega 25 › Bodega 25/General: 2
A43: 199168042660 | C43: Roper | D43: 01-001-0101-7003 | E43: 01-001-0101-7003 BR-L | F43: L | G43: L | H43: Roper | I43: ROPER Shirt Brown/Black/Tan Plaid | J43: Ropa | K43: Camisas | P43: Cafe | V43: PZS | W43: 53101602 | Y43: 22.55 | Z43: 629 | AA43: =IF(AND(A43="", B43="", E43=""), "", IF(AB43="", "Válido", IF((LEN(AB43)-LEN(SUBSTITUTE(AB43,"; ","")))/2+1>(LEN(AB43)-LEN(SUBSTITUTE(AB43,"[Aviso]","")))/7, "Con Incidencias", "Válido"))) | AB43: =IF(AND(A43="", B43="", E43=""), "", TEXTJOIN("; ", TRUE, IF(OR(TRIM(A43&"")="", ISNUMBER(SEARCH("FALTA", A43))), "UPC faltante/inválido", ""), IF(AND(A43<>"", IFERROR(_xlfn.XMATCH(A43,$A$2:$A$285,0,1)<>_xlfn.XMATCH(A43,$A$2:$A$285,0,-1),FALSE)), "Código de barras duplicado", ""), IF(AND(E43<>"", COUNTIF($E$2:$E$285, E43)>1), "SKU duplicado", ""), IF(OR(J43="", J43=""), "[Aviso] División no capturada ()", IF(ISNA(MATCH(J43, Criterios!$A$123:$A$126, 0)), "División no válida", "")), IF(OR(K43="", K43=""), "[Aviso] Categoría no capturada ()", IF(ISNA(MATCH(K43, Criterios!$A$81:$A$120, 0)), "Categoría no válida", IF(AND(J43<>"", J43<>"", J43<>VLOOKUP(K43, Criterios!$A$81:$B$120, 2, FALSE)), "División no coincide con Categoría", ""))), IF(OR(L43="", L43=""), "[Aviso] Género no capturado ()", IF(ISNA(MATCH(L43, Criterios!$B$123:$B$127, 0)), "Género no válido", "")), IF(OR(N43="", N43=""), "[Aviso] Temporada no capturada ()", IF(ISNA(MATCH(N43, Criterios!$C$123:$C$128, 0)), "Temporada no válida", "")), IF(OR(O43="", O43=""), "[Aviso] Ciclo de vida no capturado ()", IF(ISNA(MATCH(O43, Criterios!$D$123:$D$124, 0)), "Ciclo de vida no válido", "")))) | AG43: Nuevo – Odoo Universal Unique Brands 01/10/2026 | AH43: 01/10/2026: alta desde Odoo Universal Unique Brands (no existía en Productos por código de barras ni SKU) | Talla tomada del sufijo del SKU (L); Categoría: Palabra clave "Camisa" en tipo/categoría de la fuente (Ropa / Camisas); Color detectado en el nombre (brown) | Homologación G1522 06/10/2026: WB N.º de estilo: «» → «01-001-0101-7003» (Completado por regla) | AK43: Odoo: producto 21116 / plantilla 27119 | AN43: Odoo Universal Unique Brands | AQ43: 8 | AR43: Odoo Universal Unique Brands › Bodega 25 › Bodega 25/General: 8
A44: 199168042677 | C44: Roper | D44: 01-001-0101-7003 | E44: 01-001-0101-7003 BR-M | F44: M | G44: M | H44: Roper | I44: ROPER Shirt Brown/Black/Tan Plaid | J44: Ropa | K44: Camisas | P44: Cafe | V44: PZS | W44: 53101602 | Y44: 22.55 | Z44: 629 | AA44: =IF(AND(A44="", B44="", E44=""), "", IF(AB44="", "Válido", IF((LEN(AB44)-LEN(SUBSTITUTE(AB44,"; ","")))/2+1>(LEN(AB44)-LEN(SUBSTITUTE(AB44,"[Aviso]","")))/7, "Con Incidencias", "Válido"))) | AB44: =IF(AND(A44="", B44="", E44=""), "", TEXTJOIN("; ", TRUE, IF(OR(TRIM(A44&"")="", ISNUMBER(SEARCH("FALTA", A44))), "UPC faltante/inválido", ""), IF(AND(A44<>"", IFERROR(_xlfn.XMATCH(A44,$A$2:$A$285,0,1)<>_xlfn.XMATCH(A44,$A$2:$A$285,0,-1),FALSE)), "Código de barras duplicado", ""), IF(AND(E44<>"", COUNTIF($E$2:$E$285, E44)>1), "SKU duplicado", ""), IF(OR(J44="", J44=""), "[Aviso] División no capturada ()", IF(ISNA(MATCH(J44, Criterios!$A$123:$A$126, 0)), "División no válida", "")), IF(OR(K44="", K44=""), "[Aviso] Categoría no capturada ()", IF(ISNA(MATCH(K44, Criterios!$A$81:$A$120, 0)), "Categoría no válida", IF(AND(J44<>"", J44<>"", J44<>VLOOKUP(K44, Criterios!$A$81:$B$120, 2, FALSE)), "División no coincide con Categoría", ""))), IF(OR(L44="", L44=""), "[Aviso] Género no capturado ()", IF(ISNA(MATCH(L44, Criterios!$B$123:$B$127, 0)), "Género no válido", "")), IF(OR(N44="", N44=""), "[Aviso] Temporada no capturada ()", IF(ISNA(MATCH(N44, Criterios!$C$123:$C$128, 0)), "Temporada no válida", "")), IF(OR(O44="", O44=""), "[Aviso] Ciclo de vida no capturado ()", IF(ISNA(MATCH(O44, Criterios!$D$123:$D$124, 0)), "Ciclo de vida no válido", "")))) | AG44: Nuevo – Odoo Universal Unique Brands 01/10/2026 | AH44: 01/10/2026: alta desde Odoo Universal Unique Brands (no existía en Productos por código de barras ni SKU) | Talla tomada del sufijo del SKU (M); Categoría: Palabra clave "Camisa" en tipo/categoría de la fuente (Ropa / Camisas); Color detectado en el nombre (brown) | Homologación G1522 06/10/2026: WB N.º de estilo: «» → «01-001-0101-7003» (Completado por regla) | AK44: Odoo: producto 21115 / plantilla 27118 | AN44: Odoo Universal Unique Brands | AQ44: 8 | AR44: Odoo Universal Unique Brands › Bodega 25 › Bodega 25/General: 8
A45: 199168042684 | C45: Roper | D45: 01-001-0101-7003 | E45: 01-001-0101-7003 BR-S | F45: S | G45: S | H45: Roper | I45: ROPER Shirt Brown/Black/Tan Plaid | J45: Ropa | K45: Camisas | P45: Cafe | V45: PZS | W45: 53101602 | Y45: 22.55 | Z45: 629 | AA45: =IF(AND(A45="", B45="", E45=""), "", IF(AB45="", "Válido", IF((LEN(AB45)-LEN(SUBSTITUTE(AB45,"; ","")))/2+1>(LEN(AB45)-LEN(SUBSTITUTE(AB45,"[Aviso]","")))/7, "Con Incidencias", "Válido"))) | AB45: =IF(AND(A45="", B45="", E45=""), "", TEXTJOIN("; ", TRUE, IF(OR(TRIM(A45&"")="", ISNUMBER(SEARCH("FALTA", A45))), "UPC faltante/inválido", ""), IF(AND(A45<>"", IFERROR(_xlfn.XMATCH(A45,$A$2:$A$285,0,1)<>_xlfn.XMATCH(A45,$A$2:$A$285,0,-1),FALSE)), "Código de barras duplicado", ""), IF(AND(E45<>"", COUNTIF($E$2:$E$285, E45)>1), "SKU duplicado", ""), IF(OR(J45="", J45=""), "[Aviso] División no capturada ()", IF(ISNA(MATCH(J45, Criterios!$A$123:$A$126, 0)), "División no válida", "")), IF(OR(K45="", K45=""), "[Aviso] Categoría no capturada ()", IF(ISNA(MATCH(K45, Criterios!$A$81:$A$120, 0)), "Categoría no válida", IF(AND(J45<>"", J45<>"", J45<>VLOOKUP(K45, Criterios!$A$81:$B$120, 2, FALSE)), "División no coincide con Categoría", ""))), IF(OR(L45="", L45=""), "[Aviso] Género no capturado ()", IF(ISNA(MATCH(L45, Criterios!$B$123:$B$127, 0)), "Género no válido", "")), IF(OR(N45="", N45=""), "[Aviso] Temporada no capturada ()", IF(ISNA(MATCH(N45, Criterios!$C$123:$C$128, 0)), "Temporada no válida", "")), IF(OR(O45="", O45=""), "[Aviso] Ciclo de vida no capturado ()", IF(ISNA(MATCH(O45, Criterios!$D$123:$D$124, 0)), "Ciclo de vida no válido", "")))) | AG45: Nuevo – Odoo Universal Unique Brands 01/10/2026 | AH45: 01/10/2026: alta desde Odoo Universal Unique Brands (no existía en Productos por código de barras ni SKU) | Talla tomada del sufijo del SKU (S); Categoría: Palabra clave "Camisa" en tipo/categoría de la fuente (Ropa / Camisas); Color detectado en el nombre (brown) | Homologación G1522 06/10/2026: WB N.º de estilo: «» → «01-001-0101-7003» (Completado por regla) | AK45: Odoo: producto 21114 / plantilla 27117 | AN45: Odoo Universal Unique Brands | AQ45: 5 | AR45: Odoo Universal Unique Brands › Bodega 25 › Bodega 25/General: 5
A46: 199168042691 | C46: Roper | D46: 01-001-0101-7003 | E46: 01-001-0101-7003 BR-XL | F46: XL | G46: XL | H46: Roper | I46: ROPER Shirt Brown/Black/Tan Plaid | J46: Ropa | K46: Camisas | P46: Cafe | V46: PZS | W46: 53101602 | Y46: 22.55 | Z46: 629 | AA46: =IF(AND(A46="", B46="", E46=""), "", IF(AB46="", "Válido", IF((LEN(AB46)-LEN(SUBSTITUTE(AB46,"; ","")))/2+1>(LEN(AB46)-LEN(SUBSTITUTE(AB46,"[Aviso]","")))/7, "Con Incidencias", "Válido"))) | AB46: =IF(AND(A46="", B46="", E46=""), "", TEXTJOIN("; ", TRUE, IF(OR(TRIM(A46&"")="", ISNUMBER(SEARCH("FALTA", A46))), "UPC faltante/inválido", ""), IF(AND(A46<>"", IFERROR(_xlfn.XMATCH(A46,$A$2:$A$285,0,1)<>_xlfn.XMATCH(A46,$A$2:$A$285,0,-1),FALSE)), "Código de barras duplicado", ""), IF(AND(E46<>"", COUNTIF($E$2:$E$285, E46)>1), "SKU duplicado", ""), IF(OR(J46="", J46=""), "[Aviso] División no capturada ()", IF(ISNA(MATCH(J46, Criterios!$A$123:$A$126, 0)), "División no válida", "")), IF(OR(K46="", K46=""), "[Aviso] Categoría no capturada ()", IF(ISNA(MATCH(K46, Criterios!$A$81:$A$120, 0)), "Categoría no válida", IF(AND(J46<>"", J46<>"", J46<>VLOOKUP(K46, Criterios!$A$81:$B$120, 2, FALSE)), "División no coincide con Categoría", ""))), IF(OR(L46="", L46=""), "[Aviso] Género no capturado ()", IF(ISNA(MATCH(L46, Criterios!$B$123:$B$127, 0)), "Género no válido", "")), IF(OR(N46="", N46=""), "[Aviso] Temporada no capturada ()", IF(ISNA(MATCH(N46, Criterios!$C$123:$C$128, 0)), "Temporada no válida", "")), IF(OR(O46="", O46=""), "[Aviso] Ciclo de vida no capturado ()", IF(ISNA(MATCH(O46, Criterios!$D$123:$D$124, 0)), "Ciclo de vida no válido", "")))) | AG46: Nuevo – Odoo Universal Unique Brands 01/10/2026 | AH46: 01/10/2026: alta desde Odoo Universal Unique Brands (no existía en Productos por código de barras ni SKU) | Talla tomada del sufijo del SKU (XL); Categoría: Palabra clave "Camisa" en tipo/categoría de la fuente (Ropa / Camisas); Color detectado en el nombre (brown) | Homologación G1522 06/10/2026: WB N.º de estilo: «» → «01-001-0101-7003» (Completado por regla) | AK46: Odoo: producto 21117 / plantilla 27120 | AN46: Odoo Universal Unique Brands | AQ46: 8 | AR46: Odoo Universal Unique Brands › Bodega 25 › Bodega 25/General: 8
A47: 199168042943 | C47: Roper | D47: 01-001-0101-7007 | E47: 01-001-0101-7007 BU-2XL | F47: XXL | G47: XXL | H47: Roper | I47: ROPER Shirt Tq/Cobalt/Chocolate Plaid | J47: Ropa | K47: Camisas | P47: Cafe | V47: PZS | W47: 53101602 | Y47: 22.55 | Z47: 629 | AA47: =IF(AND(A47="", B47="", E47=""), "", IF(AB47="", "Válido", IF((LEN(AB47)-LEN(SUBSTITUTE(AB47,"; ","")))/2+1>(LEN(AB47)-LEN(SUBSTITUTE(AB47,"[Aviso]","")))/7, "Con Incidencias", "Válido"))) | AB47: =IF(AND(A47="", B47="", E47=""), "", TEXTJOIN("; ", TRUE, IF(OR(TRIM(A47&"")="", ISNUMBER(SEARCH("FALTA", A47))), "UPC faltante/inválido", ""), IF(AND(A47<>"", IFERROR(_xlfn.XMATCH(A47,$A$2:$A$285,0,1)<>_xlfn.XMATCH(A47,$A$2:$A$285,0,-1),FALSE)), "Código de barras duplicado", ""), IF(AND(E47<>"", COUNTIF($E$2:$E$285, E47)>1), "SKU duplicado", ""), IF(OR(J47="", J47=""), "[Aviso] División no capturada ()", IF(ISNA(MATCH(J47, Criterios!$A$123:$A$126, 0)), "División no válida", "")), IF(OR(K47="", K47=""), "[Aviso] Categoría no capturada ()", IF(ISNA(MATCH(K47, Criterios!$A$81:$A$120, 0)), "Categoría no válida", IF(AND(J47<>"", J47<>"", J47<>VLOOKUP(K47, Criterios!$A$81:$B$120, 2, FALSE)), "División no coincide con Categoría", ""))), IF(OR(L47="", L47=""), "[Aviso] Género no capturado ()", IF(ISNA(MATCH(L47, Criterios!$B$123:$B$127, 0)), "Género no válido", "")), IF(OR(N47="", N47=""), "[Aviso] Temporada no capturada ()", IF(ISNA(MATCH(N47, Criterios!$C$123:$C$128, 0)), "Temporada no válida", "")), IF(OR(O47="", O47=""), "[Aviso] Ciclo de vida no capturado ()", IF(ISNA(MATCH(O47, Criterios!$D$123:$D$124, 0)), "Ciclo de vida no válido", "")))) | AG47: Nuevo – Odoo Universal Unique Brands 01/10/2026 | AH47: 01/10/2026: alta desde Odoo Universal Unique Brands (no existía en Productos por código de barras ni SKU) | Talla tomada del sufijo del SKU (2XL); Categoría: Palabra clave "Camisa" en tipo/categoría de la fuente (Ropa / Camisas); Talla: 2XL→XXL; Color detectado en el nombre (chocolate) | Homologación G1522 06/10/2026: WB N.º de estilo: «» → «01-001-0101-7007» (Completado por regla) | AK47: Odoo: producto 20923 / plantilla 26926 | AN47: Odoo Universal Unique Brands | AQ47: 6 | AR47: Odoo Universal Unique Brands › Bodega 25 › Bodega 25/General: 6
A48: 199168042905 | C48: Roper | D48: 01-001-0101-7007 | E48: 01-001-0101-7007 BU-L | F48: L | G48: L | H48: Roper | I48: ROPER Shirt Tq/Cobalt/Chocolate Plaid | J48: Ropa | K48: Camisas | P48: Cafe | V48: PZS | W48: 53101602 | Y48: 22.55 | Z48: 629 | AA48: =IF(AND(A48="", B48="", E48=""), "", IF(AB48="", "Válido", IF((LEN(AB48)-LEN(SUBSTITUTE(AB48,"; ","")))/2+1>(LEN(AB48)-LEN(SUBSTITUTE(AB48,"[Aviso]","")))/7, "Con Incidencias", "Válido"))) | AB48: =IF(AND(A48="", B48="", E48=""), "", TEXTJOIN("; ", TRUE, IF(OR(TRIM(A48&"")="", ISNUMBER(SEARCH("FALTA", A48))), "UPC faltante/inválido", ""), IF(AND(A48<>"", IFERROR(_xlfn.XMATCH(A48,$A$2:$A$285,0,1)<>_xlfn.XMATCH(A48,$A$2:$A$285,0,-1),FALSE)), "Código de barras duplicado", ""), IF(AND(E48<>"", COUNTIF($E$2:$E$285, E48)>1), "SKU duplicado", ""), IF(OR(J48="", J48=""), "[Aviso] División no capturada ()", IF(ISNA(MATCH(J48, Criterios!$A$123:$A$126, 0)), "División no válida", "")), IF(OR(K48="", K48=""), "[Aviso] Categoría no capturada ()", IF(ISNA(MATCH(K48, Criterios!$A$81:$A$120, 0)), "Categoría no válida", IF(AND(J48<>"", J48<>"", J48<>VLOOKUP(K48, Criterios!$A$81:$B$120, 2, FALSE)), "División no coincide con Categoría", ""))), IF(OR(L48="", L48=""), "[Aviso] Género no capturado ()", IF(ISNA(MATCH(L48, Criterios!$B$123:$B$127, 0)), "Género no válido", "")), IF(OR(N48="", N48=""), "[Aviso] Temporada no capturada ()", IF(ISNA(MATCH(N48, Criterios!$C$123:$C$128, 0)), "Temporada no válida", "")), IF(OR(O48="", O48=""), "[Aviso] Ciclo de vida no capturado ()", IF(ISNA(MATCH(O48, Criterios!$D$123:$D$124, 0)), "Ciclo de vida no válido", "")))) | AG48: Nuevo – Odoo Universal Unique Brands 01/10/2026 | AH48: 01/10/2026: alta desde Odoo Universal Unique Brands (no existía en Productos por código de barras ni SKU) | Talla tomada del sufijo del SKU (L); Categoría: Palabra clave "Camisa" en tipo/categoría de la fuente (Ropa / Camisas); Color detectado en el nombre (chocolate) | Homologación G1522 06/10/2026: WB N.º de estilo: «» → «01-001-0101-7007» (Completado por regla) | AK48: Odoo: producto 20921 / plantilla 26924 | AN48: Odoo Universal Unique Brands | AQ48: 11 | AR48: Odoo Universal Unique Brands › Bodega 25 › Bodega 25/General: 11
A49: 199168042912 | C49: Roper | D49: 01-001-0101-7007 | E49: 01-001-0101-7007 BU-M | F49: M | G49: M | H49: Roper | I49: ROPER Shirt Tq/Cobalt/Chocolate Plaid | J49: Ropa | K49: Camisas | P49: Cafe | V49: PZS | W49: 53101602 | Y49: 22.55 | Z49: 629 | AA49: =IF(AND(A49="", B49="", E49=""), "", IF(AB49="", "Válido", IF((LEN(AB49)-LEN(SUBSTITUTE(AB49,"; ","")))/2+1>(LEN(AB49)-LEN(SUBSTITUTE(AB49,"[Aviso]","")))/7, "Con Incidencias", "Válido"))) | AB49: =IF(AND(A49="", B49="", E49=""), "", TEXTJOIN("; ", TRUE, IF(OR(TRIM(A49&"")="", ISNUMBER(SEARCH("FALTA", A49))), "UPC faltante/inválido", ""), IF(AND(A49<>"", IFERROR(_xlfn.XMATCH(A49,$A$2:$A$285,0,1)<>_xlfn.XMATCH(A49,$A$2:$A$285,0,-1),FALSE)), "Código de barras duplicado", ""), IF(AND(E49<>"", COUNTIF($E$2:$E$285, E49)>1), "SKU duplicado", ""), IF(OR(J49="", J49=""), "[Aviso] División no capturada ()", IF(ISNA(MATCH(J49, Criterios!$A$123:$A$126, 0)), "División no válida", "")), IF(OR(K49="", K49=""), "[Aviso] Categoría no capturada ()", IF(ISNA(MATCH(K49, Criterios!$A$81:$A$120, 0)), "Categoría no válida", IF(AND(J49<>"", J49<>"", J49<>VLOOKUP(K49, Criterios!$A$81:$B$120, 2, FALSE)), "División no coincide con Categoría", ""))), IF(OR(L49="", L49=""), "[Aviso] Género no capturado ()", IF(ISNA(MATCH(L49, Criterios!$B$123:$B$127, 0)), "Género no válido", "")), IF(OR(N49="", N49=""), "[Aviso] Temporada no capturada ()", IF(ISNA(MATCH(N49, Criterios!$C$123:$C$128, 0)), "Temporada no válida", "")), IF(OR(O49="", O49=""), "[Aviso] Ciclo de vida no capturado ()", IF(ISNA(MATCH(O49, Criterios!$D$123:$D$124, 0)), "Ciclo de vida no válido", "")))) | AG49: Nuevo – Odoo Universal Unique Brands 01/10/2026 | AH49: 01/10/2026: alta desde Odoo Universal Unique Brands (no existía en Productos por código de barras ni SKU) | Talla tomada del sufijo del SKU (M); Categoría: Palabra clave "Camisa" en tipo/categoría de la fuente (Ropa / Camisas); Color detectado en el nombre (chocolate) | Homologación G1522 06/10/2026: WB N.º de estilo: «» → «01-001-0101-7007» (Completado por regla) | AK49: Odoo: producto 20920 / plantilla 26923 | AN49: Odoo Universal Unique Brands | AQ49: 12 | AR49: Odoo Universal Unique Brands › Bodega 25 › Bodega 25/General: 12
A50: 199168042929 | C50: Roper | D50: 01-001-0101-7007 | E50: 01-001-0101-7007 BU-S | F50: S | G50: S | H50: Roper | I50: ROPER Shirt Tq/Cobalt/Chocolate Plaid | J50: Ropa | K50: Camisas | P50: Cafe | V50: PZS | W50: 53101602 | Y50: 22.55 | Z50: 629 | AA50: =IF(AND(A50="", B50="", E50=""), "", IF(AB50="", "Válido", IF((LEN(AB50)-LEN(SUBSTITUTE(AB50,"; ","")))/2+1>(LEN(AB50)-LEN(SUBSTITUTE(AB50,"[Aviso]","")))/7, "Con Incidencias", "Válido"))) | AB50: =IF(AND(A50="", B50="", E50=""), "", TEXTJOIN("; ", TRUE, IF(OR(TRIM(A50&"")="", ISNUMBER(SEARCH("FALTA", A50))), "UPC faltante/inválido", ""), IF(AND(A50<>"", IFERROR(_xlfn.XMATCH(A50,$A$2:$A$285,0,1)<>_xlfn.XMATCH(A50,$A$2:$A$285,0,-1),FALSE)), "Código de barras duplicado", ""), IF(AND(E50<>"", COUNTIF($E$2:$E$285, E50)>1), "SKU duplicado", ""), IF(OR(J50="", J50=""), "[Aviso] División no capturada ()", IF(ISNA(MATCH(J50, Criterios!$A$123:$A$126, 0)), "División no válida", "")), IF(OR(K50="", K50=""), "[Aviso] Categoría no capturada ()", IF(ISNA(MATCH(K50, Criterios!$A$81:$A$120, 0)), "Categoría no válida", IF(AND(J50<>"", J50<>"", J50<>VLOOKUP(K50, Criterios!$A$81:$B$120, 2, FALSE)), "División no coincide con Categoría", ""))), IF(OR(L50="", L50=""), "[Aviso] Género no capturado ()", IF(ISNA(MATCH(L50, Criterios!$B$123:$B$127, 0)), "Género no válido", "")), IF(OR(N50="", N50=""), "[Aviso] Temporada no capturada ()", IF(ISNA(MATCH(N50, Criterios!$C$123:$C$128, 0)), "Temporada no válida", "")), IF(OR(O50="", O50=""), "[Aviso] Ciclo de vida no capturado ()", IF(ISNA(MATCH(O50, Criterios!$D$123:$D$124, 0)), "Ciclo de vida no válido", "")))) | AG50: Nuevo – Odoo Universal Unique Brands 01/10/2026 | AH50: 01/10/2026: alta desde Odoo Universal Unique Brands (no existía en Productos por código de barras ni SKU) | Talla tomada del sufijo del SKU (S); Categoría: Palabra clave "Camisa" en tipo/categoría de la fuente (Ropa / Camisas); Color detectado en el nombre (chocolate) | Homologación G1522 06/10/2026: WB N.º de estilo: «» → «01-001-0101-7007» (Completado por regla) | AK50: Odoo: producto 20919 / plantilla 26922 | AN50: Odoo Universal Unique Brands | AQ50: 13 | AR50: Odoo Universal Unique Brands › Bodega 25 › Bodega 25/General: 13
A51: 199168042936 | C51: Roper | D51: 01-001-0101-7007 | E51: 01-001-0101-7007 BU-XL | F51: XL | G51: XL | H51: Roper | I51: ROPER Shirt Tq/Cobalt/Chocolate Plaid | J51: Ropa | K51: Camisas | P51: Cafe | V51: PZS | W51: 53101602 | Y51: 22.55 | Z51: 629 | AA51: =IF(AND(A51="", B51="", E51=""), "", IF(AB51="", "Válido", IF((LEN(AB51)-LEN(SUBSTITUTE(AB51,"; ","")))/2+1>(LEN(AB51)-LEN(SUBSTITUTE(AB51,"[Aviso]","")))/7, "Con Incidencias", "Válido"))) | AB51: =IF(AND(A51="", B51="", E51=""), "", TEXTJOIN("; ", TRUE, IF(OR(TRIM(A51&"")="", ISNUMBER(SEARCH("FALTA", A51))), "UPC faltante/inválido", ""), IF(AND(A51<>"", IFERROR(_xlfn.XMATCH(A51,$A$2:$A$285,0,1)<>_xlfn.XMATCH(A51,$A$2:$A$285,0,-1),FALSE)), "Código de barras duplicado", ""), IF(AND(E51<>"", COUNTIF($E$2:$E$285, E51)>1), "SKU duplicado", ""), IF(OR(J51="", J51=""), "[Aviso] División no capturada ()", IF(ISNA(MATCH(J51, Criterios!$A$123:$A$126, 0)), "División no válida", "")), IF(OR(K51="", K51=""), "[Aviso] Categoría no capturada ()", IF(ISNA(MATCH(K51, Criterios!$A$81:$A$120, 0)), "Categoría no válida", IF(AND(J51<>"", J51<>"", J51<>VLOOKUP(K51, Criterios!$A$81:$B$120, 2, FALSE)), "División no coincide con Categoría", ""))), IF(OR(L51="", L51=""), "[Aviso] Género no capturado ()", IF(ISNA(MATCH(L51, Criterios!$B$123:$B$127, 0)), "Género no válido", "")), IF(OR(N51="", N51=""), "[Aviso] Temporada no capturada ()", IF(ISNA(MATCH(N51, Criterios!$C$123:$C$128, 0)), "Temporada no válida", "")), IF(OR(O51="", O51=""), "[Aviso] Ciclo de vida no capturado ()", IF(ISNA(MATCH(O51, Criterios!$D$123:$D$124, 0)), "Ciclo de vida no válido", "")))) | AG51: Nuevo – Odoo Universal Unique Brands 01/10/2026 | AH51: 01/10/2026: alta desde Odoo Universal Unique Brands (no existía en Productos por código de barras ni SKU) | Talla tomada del sufijo del SKU (XL); Categoría: Palabra clave "Camisa" en tipo/categoría de la fuente (Ropa / Camisas); Color detectado en el nombre (chocolate) | Homologación G1522 06/10/2026: WB N.º de estilo: «» → «01-001-0101-7007» (Completado por regla) | AK51: Odoo: producto 20922 / plantilla 26925 | AN51: Odoo Universal Unique Brands | AQ51: 12 | AR51: Odoo Universal Unique Brands › Bodega 25 › Bodega 25/General: 12
A52: 199168044138 | C52: Roper | D52: 01-050-0016-7004 | E52: 01-050-0016-7004 BL-L | F52: L | G52: L | H52: Roper | I52: ROPER Shirt Bl/Wh/Re Plaid | J52: Ropa | K52: Camisas | V52: PZS | W52: 53101602 | Y52: 32.09 | Z52: 859 | AA52: =IF(AND(A52="", B52="", E52=""), "", IF(AB52="", "Válido", IF((LEN(AB52)-LEN(SUBSTITUTE(AB52,"; ","")))/2+1>(LEN(AB52)-LEN(SUBSTITUTE(AB52,"[Aviso]","")))/7, "Con Incidencias", "Válido"))) | AB52: =IF(AND(A52="", B52="", E52=""), "", TEXTJOIN("; ", TRUE, IF(OR(TRIM(A52&"")="", ISNUMBER(SEARCH("FALTA", A52))), "UPC faltante/inválido", ""), IF(AND(A52<>"", IFERROR(_xlfn.XMATCH(A52,$A$2:$A$285,0,1)<>_xlfn.XMATCH(A52,$A$2:$A$285,0,-1),FALSE)), "Código de barras duplicado", ""), IF(AND(E52<>"", COUNTIF($E$2:$E$285, E52)>1), "SKU duplicado", ""), IF(OR(J52="", J52=""), "[Aviso] División no capturada ()", IF(ISNA(MATCH(J52, Criterios!$A$123:$A$126, 0)), "División no válida", "")), IF(OR(K52="", K52=""), "[Aviso] Categoría no capturada ()", IF(ISNA(MATCH(K52, Criterios!$A$81:$A$120, 0)), "Categoría no válida", IF(AND(J52<>"", J52<>"", J52<>VLOOKUP(K52, Criterios!$A$81:$B$120, 2, FALSE)), "División no coincide con Categoría", ""))), IF(OR(L52="", L52=""), "[Aviso] Género no capturado ()", IF(ISNA(MATCH(L52, Criterios!$B$123:$B$127, 0)), "Género no válido", "")), IF(OR(N52="", N52=""), "[Aviso] Temporada no capturada ()", IF(ISNA(MATCH(N52, Criterios!$C$123:$C$128, 0)), "Temporada no válida", "")), IF(OR(O52="", O52=""), "[Aviso] Ciclo de vida no capturado ()", IF(ISNA(MATCH(O52, Criterios!$D$123:$D$124, 0)), "Ciclo de vida no válido", "")))) | AG52: Nuevo – Odoo Universal Unique Brands 01/10/2026 | AH52: 01/10/2026: alta desde Odoo Universal Unique Brands (no existía en Productos por código de barras ni SKU) | Talla tomada del sufijo del SKU (L); Categoría: Palabra clave "Camisa" en tipo/categoría de la fuente (Ropa / Camisas) | Homologación G1522 06/10/2026: WB N.º de estilo: «» → «01-050-0016-7004» (Completado por regla) · Validador Shopify: WB: precio con IVA no termina en 9 | AK52: Odoo: producto 21011 / plantilla 27014 | AN52: Odoo Universal Unique Brands | AQ52: 13 | AR52: Odoo Universal Unique Brands › Bodega 25 › Bodega 25/General: 13
A53: 199168044145 | C53: Roper | D53: 01-050-0016-7004 | E53: 01-050-0016-7004 BL-M | F53: M | G53: M | H53: Roper | I53: ROPER Shirt Bl/Wh/Re Plaid | J53: Ropa | K53: Camisas | V53: PZS | W53: 53101602 | Y53: 32.09 | Z53: 859 | AA53: =IF(AND(A53="", B53="", E53=""), "", IF(AB53="", "Válido", IF((LEN(AB53)-LEN(SUBSTITUTE(AB53,"; ","")))/2+1>(LEN(AB53)-LEN(SUBSTITUTE(AB53,"[Aviso]","")))/7, "Con Incidencias", "Válido"))) | AB53: =IF(AND(A53="", B53="", E53=""), "", TEXTJOIN("; ", TRUE, IF(OR(TRIM(A53&"")="", ISNUMBER(SEARCH("FALTA", A53))), "UPC faltante/inválido", ""), IF(AND(A53<>"", IFERROR(_xlfn.XMATCH(A53,$A$2:$A$285,0,1)<>_xlfn.XMATCH(A53,$A$2:$A$285,0,-1),FALSE)), "Código de barras duplicado", ""), IF(AND(E53<>"", COUNTIF($E$2:$E$285, E53)>1), "SKU duplicado", ""), IF(OR(J53="", J53=""), "[Aviso] División no capturada ()", IF(ISNA(MATCH(J53, Criterios!$A$123:$A$126, 0)), "División no válida", "")), IF(OR(K53="", K53=""), "[Aviso] Categoría no capturada ()", IF(ISNA(MATCH(K53, Criterios!$A$81:$A$120, 0)), "Categoría no válida", IF(AND(J53<>"", J53<>"", J53<>VLOOKUP(K53, Criterios!$A$81:$B$120, 2, FALSE)), "División no coincide con Categoría", ""))), IF(OR(L53="", L53=""), "[Aviso] Género no capturado ()", IF(ISNA(MATCH(L53, Criterios!$B$123:$B$127, 0)), "Género no válido", "")), IF(OR(N53="", N53=""), "[Aviso] Temporada no capturada ()", IF(ISNA(MATCH(N53, Criterios!$C$123:$C$128, 0)), "Temporada no válida", "")), IF(OR(O53="", O53=""), "[Aviso] Ciclo de vida no capturado ()", IF(ISNA(MATCH(O53, Criterios!$D$123:$D$124, 0)), "Ciclo de vida no válido", "")))) | AG53: Nuevo – Odoo Universal Unique Brands 01/10/2026 | AH53: 01/10/2026: alta desde Odoo Universal Unique Brands (no existía en Productos por código de barras ni SKU) | Talla tomada del sufijo del SKU (M); Categoría: Palabra clave "Camisa" en tipo/categoría de la fuente (Ropa / Camisas) | Homologación G1522 06/10/2026: WB N.º de estilo: «» → «01-050-0016-7004» (Completado por regla) · Validador Shopify: WB: precio con IVA no termina en 9 | AK53: Odoo: producto 21010 / plantilla 27013 | AN53: Odoo Universal Unique Brands | AQ53: 12 | AR53: Odoo Universal Unique Brands › Bodega 25 › Bodega 25/General: 12
A54: 199168044152 | C54: Roper | D54: 01-050-0016-7004 | E54: 01-050-0016-7004 BL-S | F54: S | G54: S | H54: Roper | I54: ROPER Shirt Bl/Wh/Re Plaid | J54: Ropa | K54: Camisas | V54: PZS | W54: 53101602 | Y54: 32.09 | Z54: 859 | AA54: =IF(AND(A54="", B54="", E54=""), "", IF(AB54="", "Válido", IF((LEN(AB54)-LEN(SUBSTITUTE(AB54,"; ","")))/2+1>(LEN(AB54)-LEN(SUBSTITUTE(AB54,"[Aviso]","")))/7, "Con Incidencias", "Válido"))) | AB54: =IF(AND(A54="", B54="", E54=""), "", TEXTJOIN("; ", TRUE, IF(OR(TRIM(A54&"")="", ISNUMBER(SEARCH("FALTA", A54))), "UPC faltante/inválido", ""), IF(AND(A54<>"", IFERROR(_xlfn.XMATCH(A54,$A$2:$A$285,0,1)<>_xlfn.XMATCH(A54,$A$2:$A$285,0,-1),FALSE)), "Código de barras duplicado", ""), IF(AND(E54<>"", COUNTIF($E$2:$E$285, E54)>1), "SKU duplicado", ""), IF(OR(J54="", J54=""), "[Aviso] División no capturada ()", IF(ISNA(MATCH(J54, Criterios!$A$123:$A$126, 0)), "División no válida", "")), IF(OR(K54="", K54=""), "[Aviso] Categoría no capturada ()", IF(ISNA(MATCH(K54, Criterios!$A$81:$A$120, 0)), "Categoría no válida", IF(AND(J54<>"", J54<>"", J54<>VLOOKUP(K54, Criterios!$A$81:$B$120, 2, FALSE)), "División no coincide con Categoría", ""))), IF(OR(L54="", L54=""), "[Aviso] Género no capturado ()", IF(ISNA(MATCH(L54, Criterios!$B$123:$B$127, 0)), "Género no válido", "")), IF(OR(N54="", N54=""), "[Aviso] Temporada no capturada ()", IF(ISNA(MATCH(N54, Criterios!$C$123:$C$128, 0)), "Temporada no válida", "")), IF(OR(O54="", O54=""), "[Aviso] Ciclo de vida no capturado ()", IF(ISNA(MATCH(O54, Criterios!$D$123:$D$124, 0)), "Ciclo de vida no válido", "")))) | AG54: Nuevo – Odoo Universal Unique Brands 01/10/2026 | AH54: 01/10/2026: alta desde Odoo Universal Unique Brands (no existía en Productos por código de barras ni SKU) | Talla tomada del sufijo del SKU (S); Categoría: Palabra clave "Camisa" en tipo/categoría de la fuente (Ropa / Camisas) | Homologación G1522 06/10/2026: WB N.º de estilo: «» → «01-050-0016-7004» (Completado por regla) · Validador Shopify: WB: precio con IVA no termina en 9 | AK54: Odoo: producto 21009 / plantilla 27012 | AN54: Odoo Universal Unique Brands | AQ54: 10 | AR54: Odoo Universal Unique Brands › Bodega 25 › Bodega 25/General: 10
A55: 199168044169 | C55: Roper | D55: 01-050-0016-7004 | E55: 01-050-0016-7004 BL-XL | F55: XL | G55: XL | H55: Roper | I55: ROPER Shirt Bl/Wh/Re Plaid | J55: Ropa | K55: Camisas | V55: PZS | W55: 53101602 | Y55: 32.09 | Z55: 859 | AA55: =IF(AND(A55="", B55="", E55=""), "", IF(AB55="", "Válido", IF((LEN(AB55)-LEN(SUBSTITUTE(AB55,"; ","")))/2+1>(LEN(AB55)-LEN(SUBSTITUTE(AB55,"[Aviso]","")))/7, "Con Incidencias", "Válido"))) | AB55: =IF(AND(A55="", B55="", E55=""), "", TEXTJOIN("; ", TRUE, IF(OR(TRIM(A55&"")="", ISNUMBER(SEARCH("FALTA", A55))), "UPC faltante/inválido", ""), IF(AND(A55<>"", IFERROR(_xlfn.XMATCH(A55,$A$2:$A$285,0,1)<>_xlfn.XMATCH(A55,$A$2:$A$285,0,-1),FALSE)), "Código de barras duplicado", ""), IF(AND(E55<>"", COUNTIF($E$2:$E$285, E55)>1), "SKU duplicado", ""), IF(OR(J55="", J55=""), "[Aviso] División no capturada ()", IF(ISNA(MATCH(J55, Criterios!$A$123:$A$126, 0)), "División no válida", "")), IF(OR(K55="", K55=""), "[Aviso] Categoría no capturada ()", IF(ISNA(MATCH(K55, Criterios!$A$81:$A$120, 0)), "Categoría no válida", IF(AND(J55<>"", J55<>"", J55<>VLOOKUP(K55, Criterios!$A$81:$B$120, 2, FALSE)), "División no coincide con Categoría", ""))), IF(OR(L55="", L55=""), "[Aviso] Género no capturado ()", IF(ISNA(MATCH(L55, Criterios!$B$123:$B$127, 0)), "Género no válido", "")), IF(OR(N55="", N55=""), "[Aviso] Temporada no capturada ()", IF(ISNA(MATCH(N55, Criterios!$C$123:$C$128, 0)), "Temporada no válida", "")), IF(OR(O55="", O55=""), "[Aviso] Ciclo de vida no capturado ()", IF(ISNA(MATCH(O55, Criterios!$D$123:$D$124, 0)), "Ciclo de vida no válido", "")))) | AG55: Nuevo – Odoo Universal Unique Brands 01/10/2026 | AH55: 01/10/2026: alta desde Odoo Universal Unique Brands (no existía en Productos por código de barras ni SKU) | Talla tomada del sufijo del SKU (XL); Categoría: Palabra clave "Camisa" en tipo/categoría de la fuente (Ropa / Camisas) | Homologación G1522 06/10/2026: WB N.º de estilo: «» → «01-050-0016-7004» (Completado por regla) · Validador Shopify: WB: precio con IVA no termina en 9 | AK55: Odoo: producto 21012 / plantilla 27015 | AN55: Odoo Universal Unique Brands | AQ55: 17 | AR55: Odoo Universal Unique Brands › Bodega 25 › Bodega 25/General: 17
A56: 199168044237 | C56: Roper | D56: 01-050-0016-7005 | E56: 01-050-0016-7005 BR-1XL | H56: Roper | I56: ROPER Shirt BrGy//Peri Plaid | J56: Ropa | K56: Camisas | V56: PZS | W56: 53101604 | Y56: 32.09 | Z56: 859 | AA56: =IF(AND(A56="", B56="", E56=""), "", IF(AB56="", "Válido", IF((LEN(AB56)-LEN(SUBSTITUTE(AB56,"; ","")))/2+1>(LEN(AB56)-LEN(SUBSTITUTE(AB56,"[Aviso]","")))/7, "Con Incidencias", "Válido"))) | AB56: =IF(AND(A56="", B56="", E56=""), "", TEXTJOIN("; ", TRUE, IF(OR(TRIM(A56&"")="", ISNUMBER(SEARCH("FALTA", A56))), "UPC faltante/inválido", ""), IF(AND(A56<>"", IFERROR(_xlfn.XMATCH(A56,$A$2:$A$285,0,1)<>_xlfn.XMATCH(A56,$A$2:$A$285,0,-1),FALSE)), "Código de barras duplicado", ""), IF(AND(E56<>"", COUNTIF($E$2:$E$285, E56)>1), "SKU duplicado", ""), IF(OR(J56="", J56=""), "[Aviso] División no capturada ()", IF(ISNA(MATCH(J56, Criterios!$A$123:$A$126, 0)), "División no válida", "")), IF(OR(K56="", K56=""), "[Aviso] Categoría no capturada ()", IF(ISNA(MATCH(K56, Criterios!$A$81:$A$120, 0)), "Categoría no válida", IF(AND(J56<>"", J56<>"", J56<>VLOOKUP(K56, Criterios!$A$81:$B$120, 2, FALSE)), "División no coincide con Categoría", ""))), IF(OR(L56="", L56=""), "[Aviso] Género no capturado ()", IF(ISNA(MATCH(L56, Criterios!$B$123:$B$127, 0)), "Género no válido", "")), IF(OR(N56="", N56=""), "[Aviso] Temporada no capturada ()", IF(ISNA(MATCH(N56, Criterios!$C$123:$C$128, 0)), "Temporada no válida", "")), IF(OR(O56="", O56=""), "[Aviso] Ciclo de vida no capturado ()", IF(ISNA(MATCH(O56, Criterios!$D$123:$D$124, 0)), "Ciclo de vida no válido", "")))) | AG56: Nuevo – Odoo Universal Unique Brands 01/10/2026 | AH56: 01/10/2026: alta desde Odoo Universal Unique Brands (no existía en Productos por código de barras ni SKU) | Categoría: Palabra clave "Camisa" en tipo/categoría de la fuente (Ropa / Camisas) | Homologación G1522 06/10/2026: WB N.º de estilo: «» → «01-050-0016-7005» (Completado por regla) · Validador NetSuite / Odoo: N2: talla cero o vacía · Validador Shopify: WB: precio con IVA no termina en 9 | AK56: Odoo: producto 20999 / plantilla 27002 | AN56: Odoo Universal Unique Brands | AQ56: 2 | AR56: Odoo Universal Unique Brands › Bodega 25 › Bodega 25/General: 2
C57: Roper | D57: 01-050-0016-7005 | E57: 01-050-0016-7005 BR-2XL | F57: XXL | G57: XXL | H57: Roper | I57: ROPER Shirt BrGy//Peri Plaid | J57: Ropa | K57: Camisas | V57: PZS | W57: 53101602 | Y57: 32.09 | Z57: 859 | AA57: =IF(AND(A57="", B57="", E57=""), "", IF(AB57="", "Válido", IF((LEN(AB57)-LEN(SUBSTITUTE(AB57,"; ","")))/2+1>(LEN(AB57)-LEN(SUBSTITUTE(AB57,"[Aviso]","")))/7, "Con Incidencias", "Válido"))) | AB57: =IF(AND(A57="", B57="", E57=""), "", TEXTJOIN("; ", TRUE, IF(OR(TRIM(A57&"")="", ISNUMBER(SEARCH("FALTA", A57))), "UPC faltante/inválido", ""), IF(AND(A57<>"", IFERROR(_xlfn.XMATCH(A57,$A$2:$A$285,0,1)<>_xlfn.XMATCH(A57,$A$2:$A$285,0,-1),FALSE)), "Código de barras duplicado", ""), IF(AND(E57<>"", COUNTIF($E$2:$E$285, E57)>1), "SKU duplicado", ""), IF(OR(J57="", J57=""), "[Aviso] División no capturada ()", IF(ISNA(MATCH(J57, Criterios!$A$123:$A$126, 0)), "División no válida", "")), IF(OR(K57="", K57=""), "[Aviso] Categoría no capturada ()", IF(ISNA(MATCH(K57, Criterios!$A$81:$A$120, 0)), "Categoría no válida", IF(AND(J57<>"", J57<>"", J57<>VLOOKUP(K57, Criterios!$A$81:$B$120, 2, FALSE)), "División no coincide con Categoría", ""))), IF(OR(L57="", L57=""), "[Aviso] Género no capturado ()", IF(ISNA(MATCH(L57, Criterios!$B$123:$B$127, 0)), "Género no válido", "")), IF(OR(N57="", N57=""), "[Aviso] Temporada no capturada ()", IF(ISNA(MATCH(N57, Criterios!$C$123:$C$128, 0)), "Temporada no válida", "")), IF(OR(O57="", O57=""), "[Aviso] Ciclo de vida no capturado ()", IF(ISNA(MATCH(O57, Criterios!$D$123:$D$124, 0)), "Ciclo de vida no válido", "")))) | AG57: Nuevo – Odoo Universal Unique Brands 01/10/2026 | AH57: 01/10/2026: alta desde Odoo Universal Unique Brands (no existía en Productos por código de barras ni SKU) | Talla tomada del sufijo del SKU (2XL); Categoría: Palabra clave "Camisa" en tipo/categoría de la fuente (Ropa / Camisas); Talla: 2XL→XXL | Homologación G1522 06/10/2026: WB N.º de estilo: «» → «01-050-0016-7005» (Completado por regla) · Validación G1522: Código de barras faltante · Validador NetSuite / Odoo: V1: falta código de barras · Validador Shopify: V1: falta código de barras; WB: precio con IVA no termina en 9 | AK57: Odoo: producto 21564 / plantilla 27575 | AN57: Odoo Universal Unique Brands | AQ57: 1 | AR57: Odoo Universal Unique Brands › Bodega 25 › Bodega 25/General: 1
A58: 199168044183 | C58: Roper | D58: 01-050-0016-7005 | E58: 01-050-0016-7005 BR-L | F58: L | G58: L | H58: Roper | I58: ROPER Shirt BrGy//Peri Plaid | J58: Ropa | K58: Camisas | V58: PZS | W58: 53101604 | Y58: 32.09 | Z58: 859 | AA58: =IF(AND(A58="", B58="", E58=""), "", IF(AB58="", "Válido", IF((LEN(AB58)-LEN(SUBSTITUTE(AB58,"; ","")))/2+1>(LEN(AB58)-LEN(SUBSTITUTE(AB58,"[Aviso]","")))/7, "Con Incidencias", "Válido"))) | AB58: =IF(AND(A58="", B58="", E58=""), "", TEXTJOIN("; ", TRUE, IF(OR(TRIM(A58&"")="", ISNUMBER(SEARCH("FALTA", A58))), "UPC faltante/inválido", ""), IF(AND(A58<>"", IFERROR(_xlfn.XMATCH(A58,$A$2:$A$285,0,1)<>_xlfn.XMATCH(A58,$A$2:$A$285,0,-1),FALSE)), "Código de barras duplicado", ""), IF(AND(E58<>"", COUNTIF($E$2:$E$285, E58)>1), "SKU duplicado", ""), IF(OR(J58="", J58=""), "[Aviso] División no capturada ()", IF(ISNA(MATCH(J58, Criterios!$A$123:$A$126, 0)), "División no válida", "")), IF(OR(K58="", K58=""), "[Aviso] Categoría no capturada ()", IF(ISNA(MATCH(K58, Criterios!$A$81:$A$120, 0)), "Categoría no válida", IF(AND(J58<>"", J58<>"", J58<>VLOOKUP(K58, Criterios!$A$81:$B$120, 2, FALSE)), "División no coincide con Categoría", ""))), IF(OR(L58="", L58=""), "[Aviso] Género no capturado ()", IF(ISNA(MATCH(L58, Criterios!$B$123:$B$127, 0)), "Género no válido", "")), IF(OR(N58="", N58=""), "[Aviso] Temporada no capturada ()", IF(ISNA(MATCH(N58, Criterios!$C$123:$C$128, 0)), "Temporada no válida", "")), IF(OR(O58="", O58=""), "[Aviso] Ciclo de vida no capturado ()", IF(ISNA(MATCH(O58, Criterios!$D$123:$D$124, 0)), "Ciclo de vida no válido", "")))) | AG58: Nuevo – Odoo Universal Unique Brands 01/10/2026 | AH58: 01/10/2026: alta desde Odoo Universal Unique Brands (no existía en Productos por código de barras ni SKU) | Talla tomada del sufijo del SKU (L); Categoría: Palabra clave "Camisa" en tipo/categoría de la fuente (Ropa / Camisas) | Homologación G1522 06/10/2026: WB N.º de estilo: «» → «01-050-0016-7005» (Completado por regla) · Validador Shopify: WB: precio con IVA no termina en 9 | AK58: Odoo: producto 20997 / plantilla 27000 | AN58: Odoo Universal Unique Brands | AQ58: 1 | AR58: Odoo Universal Unique Brands › Bodega 25 › Bodega 25/General: 1
A59: 199168044213 | C59: Roper | D59: 01-050-0016-7005 | E59: 01-050-0016-7005 BR-XL | F59: XL | G59: XL | H59: Roper | I59: ROPER Shirt BrGy//Peri Plaid | J59: Ropa | K59: Camisas | V59: PZS | W59: 53101604 | Y59: 32.09 | Z59: 740.52 | AA59: =IF(AND(A59="", B59="", E59=""), "", IF(AB59="", "Válido", IF((LEN(AB59)-LEN(SUBSTITUTE(AB59,"; ","")))/2+1>(LEN(AB59)-LEN(SUBSTITUTE(AB59,"[Aviso]","")))/7, "Con Incidencias", "Válido"))) | AB59: =IF(AND(A59="", B59="", E59=""), "", TEXTJOIN("; ", TRUE, IF(OR(TRIM(A59&"")="", ISNUMBER(SEARCH("FALTA", A59))), "UPC faltante/inválido", ""), IF(AND(A59<>"", IFERROR(_xlfn.XMATCH(A59,$A$2:$A$285,0,1)<>_xlfn.XMATCH(A59,$A$2:$A$285,0,-1),FALSE)), "Código de barras duplicado", ""), IF(AND(E59<>"", COUNTIF($E$2:$E$285, E59)>1), "SKU duplicado", ""), IF(OR(J59="", J59=""), "[Aviso] División no capturada ()", IF(ISNA(MATCH(J59, Criterios!$A$123:$A$126, 0)), "División no válida", "")), IF(OR(K59="", K59=""), "[Aviso] Categoría no capturada ()", IF(ISNA(MATCH(K59, Criterios!$A$81:$A$120, 0)), "Categoría no válida", IF(AND(J59<>"", J59<>"", J59<>VLOOKUP(K59, Criterios!$A$81:$B$120, 2, FALSE)), "División no coincide con Categoría", ""))), IF(OR(L59="", L59=""), "[Aviso] Género no capturado ()", IF(ISNA(MATCH(L59, Criterios!$B$123:$B$127, 0)), "Género no válido", "")), IF(OR(N59="", N59=""), "[Aviso] Temporada no capturada ()", IF(ISNA(MATCH(N59, Criterios!$C$123:$C$128, 0)), "Temporada no válida", "")), IF(OR(O59="", O59=""), "[Aviso] Ciclo de vida no capturado ()", IF(ISNA(MATCH(O59, Criterios!$D$123:$D$124, 0)), "Ciclo de vida no válido", "")))) | AG59: Nuevo – Odoo Universal Unique Brands 01/10/2026 | AH59: 01/10/2026: alta desde Odoo Universal Unique Brands (no existía en Productos por código de barras ni SKU) | Talla tomada del sufijo del SKU (XL); Categoría: Palabra clave "Camisa" en tipo/categoría de la fuente (Ropa / Camisas) | Homologación G1522 06/10/2026: WB N.º de estilo: «» → «01-050-0016-7005» (Completado por regla) | AK59: Odoo: producto 20998 / plantilla 27001 | AN59: Odoo Universal Unique Brands | AQ59: 0
A60: 199168044312 | C60: Roper | D60: 01-050-0017-7018 | E60: 01-050-0017-7018 BR-1XL | H60: Roper | I60: ROPER Chocolate Solid Poplin | J60: Ropa | K60: Camisas | P60: Cafe | V60: PZS | W60: 53102002 | Y60: 32.55 | Z60: 869 | AA60: =IF(AND(A60="", B60="", E60=""), "", IF(AB60="", "Válido", IF((LEN(AB60)-LEN(SUBSTITUTE(AB60,"; ","")))/2+1>(LEN(AB60)-LEN(SUBSTITUTE(AB60,"[Aviso]","")))/7, "Con Incidencias", "Válido"))) | AB60: =IF(AND(A60="", B60="", E60=""), "", TEXTJOIN("; ", TRUE, IF(OR(TRIM(A60&"")="", ISNUMBER(SEARCH("FALTA", A60))), "UPC faltante/inválido", ""), IF(AND(A60<>"", IFERROR(_xlfn.XMATCH(A60,$A$2:$A$285,0,1)<>_xlfn.XMATCH(A60,$A$2:$A$285,0,-1),FALSE)), "Código de barras duplicado", ""), IF(AND(E60<>"", COUNTIF($E$2:$E$285, E60)>1), "SKU duplicado", ""), IF(OR(J60="", J60=""), "[Aviso] División no capturada ()", IF(ISNA(MATCH(J60, Criterios!$A$123:$A$126, 0)), "División no válida", "")), IF(OR(K60="", K60=""), "[Aviso] Categoría no capturada ()", IF(ISNA(MATCH(K60, Criterios!$A$81:$A$120, 0)), "Categoría no válida", IF(AND(J60<>"", J60<>"", J60<>VLOOKUP(K60, Criterios!$A$81:$B$120, 2, FALSE)), "División no coincide con Categoría", ""))), IF(OR(L60="", L60=""), "[Aviso] Género no capturado ()", IF(ISNA(MATCH(L60, Criterios!$B$123:$B$127, 0)), "Género no válido", "")), IF(OR(N60="", N60=""), "[Aviso] Temporada no capturada ()", IF(ISNA(MATCH(N60, Criterios!$C$123:$C$128, 0)), "Temporada no válida", "")), IF(OR(O60="", O60=""), "[Aviso] Ciclo de vida no capturado ()", IF(ISNA(MATCH(O60, Criterios!$D$123:$D$124, 0)), "Ciclo de vida no válido", "")))) | AG60: Nuevo – Odoo Universal Unique Brands 01/10/2026 | AH60: 01/10/2026: alta desde Odoo Universal Unique Brands (no existía en Productos por código de barras ni SKU) | Categoría: Palabra clave "Camisa" en tipo/categoría de la fuente (Ropa / Camisas); Color detectado en el nombre (chocolate) | Homologación G1522 06/10/2026: WB N.º de estilo: «» → «01-050-0017-7018» (Completado por regla) · Validador NetSuite / Odoo: N2: talla cero o vacía · Validador Shopify: WB: precio con IVA no termina en 9 | AK60: Odoo: producto 20974 / plantilla 26977 | AN60: Odoo Universal Unique Brands | AQ60: 3 | AR60: Odoo Universal Unique Brands › Bodega 25 › Bodega 25/General: 3
A61: 199168044268 | C61: Roper | D61: 01-050-0017-7018 | E61: 01-050-0017-7018 BR-L | F61: L | G61: L | H61: Roper | I61: ROPER Shirt Chocolate Solid Poplin | J61: Ropa | K61: Camisas | P61: Cafe | V61: PZS | W61: 53101602 | Y61: 32.55 | Z61: 869 | AA61: =IF(AND(A61="", B61="", E61=""), "", IF(AB61="", "Válido", IF((LEN(AB61)-LEN(SUBSTITUTE(AB61,"; ","")))/2+1>(LEN(AB61)-LEN(SUBSTITUTE(AB61,"[Aviso]","")))/7, "Con Incidencias", "Válido"))) | AB61: =IF(AND(A61="", B61="", E61=""), "", TEXTJOIN("; ", TRUE, IF(OR(TRIM(A61&"")="", ISNUMBER(SEARCH("FALTA", A61))), "UPC faltante/inválido", ""), IF(AND(A61<>"", IFERROR(_xlfn.XMATCH(A61,$A$2:$A$285,0,1)<>_xlfn.XMATCH(A61,$A$2:$A$285,0,-1),FALSE)), "Código de barras duplicado", ""), IF(AND(E61<>"", COUNTIF($E$2:$E$285, E61)>1), "SKU duplicado", ""), IF(OR(J61="", J61=""), "[Aviso] División no capturada ()", IF(ISNA(MATCH(J61, Criterios!$A$123:$A$126, 0)), "División no válida", "")), IF(OR(K61="", K61=""), "[Aviso] Categoría no capturada ()", IF(ISNA(MATCH(K61, Criterios!$A$81:$A$120, 0)), "Categoría no válida", IF(AND(J61<>"", J61<>"", J61<>VLOOKUP(K61, Criterios!$A$81:$B$120, 2, FALSE)), "División no coincide con Categoría", ""))), IF(OR(L61="", L61=""), "[Aviso] Género no capturado ()", IF(ISNA(MATCH(L61, Criterios!$B$123:$B$127, 0)), "Género no válido", "")), IF(OR(N61="", N61=""), "[Aviso] Temporada no capturada ()", IF(ISNA(MATCH(N61, Criterios!$C$123:$C$128, 0)), "Temporada no válida", "")), IF(OR(O61="", O61=""), "[Aviso] Ciclo de vida no capturado ()", IF(ISNA(MATCH(O61, Criterios!$D$123:$D$124, 0)), "Ciclo de vida no válido", "")))) | AG61: Nuevo – Odoo Universal Unique Brands 01/10/2026 | AH61: 01/10/2026: alta desde Odoo Universal Unique Brands (no existía en Productos por código de barras ni SKU) | Talla tomada del sufijo del SKU (L); Categoría: Palabra clave "Camisa" en tipo/categoría de la fuente (Ropa / Camisas); Color detectado en el nombre (chocolate) | Homologación G1522 06/10/2026: WB N.º de estilo: «» → «01-050-0017-7018» (Completado por regla) · Validador Shopify: WB: precio con IVA no termina en 9 | AK61: Odoo: producto 20972 / plantilla 26975 | AN61: Odoo Universal Unique Brands | AQ61: 8 | AR61: Odoo Universal Unique Brands › Bodega 25 › Bodega 25/General: 8
A62: 199168044275 | C62: Roper | D62: 01-050-0017-7018 | E62: 01-050-0017-7018 BR-M | F62: M | G62: M | H62: Roper | I62: ROPER Shirt Chocolate Solid Poplin | J62: Ropa | K62: Camisas | P62: Cafe | V62: PZS | W62: 53101602 | Y62: 32.55 | Z62: 869 | AA62: =IF(AND(A62="", B62="", E62=""), "", IF(AB62="", "Válido", IF((LEN(AB62)-LEN(SUBSTITUTE(AB62,"; ","")))/2+1>(LEN(AB62)-LEN(SUBSTITUTE(AB62,"[Aviso]","")))/7, "Con Incidencias", "Válido"))) | AB62: =IF(AND(A62="", B62="", E62=""), "", TEXTJOIN("; ", TRUE, IF(OR(TRIM(A62&"")="", ISNUMBER(SEARCH("FALTA", A62))), "UPC faltante/inválido", ""), IF(AND(A62<>"", IFERROR(_xlfn.XMATCH(A62,$A$2:$A$285,0,1)<>_xlfn.XMATCH(A62,$A$2:$A$285,0,-1),FALSE)), "Código de barras duplicado", ""), IF(AND(E62<>"", COUNTIF($E$2:$E$285, E62)>1), "SKU duplicado", ""), IF(OR(J62="", J62=""), "[Aviso] División no capturada ()", IF(ISNA(MATCH(J62, Criterios!$A$123:$A$126, 0)), "División no válida", "")), IF(OR(K62="", K62=""), "[Aviso] Categoría no capturada ()", IF(ISNA(MATCH(K62, Criterios!$A$81:$A$120, 0)), "Categoría no válida", IF(AND(J62<>"", J62<>"", J62<>VLOOKUP(K62, Criterios!$A$81:$B$120, 2, FALSE)), "División no coincide con Categoría", ""))), IF(OR(L62="", L62=""), "[Aviso] Género no capturado ()", IF(ISNA(MATCH(L62, Criterios!$B$123:$B$127, 0)), "Género no válido", "")), IF(OR(N62="", N62=""), "[Aviso] Temporada no capturada ()", IF(ISNA(MATCH(N62, Criterios!$C$123:$C$128, 0)), "Temporada no válida", "")), IF(OR(O62="", O62=""), "[Aviso] Ciclo de vida no capturado ()", IF(ISNA(MATCH(O62, Criterios!$D$123:$D$124, 0)), "Ciclo de vida no válido", "")))) | AG62: Nuevo – Odoo Universal Unique Brands 01/10/2026 | AH62: 01/10/2026: alta desde Odoo Universal Unique Brands (no existía en Productos por código de barras ni SKU) | Talla tomada del sufijo del SKU (M); Categoría: Palabra clave "Camisa" en tipo/categoría de la fuente (Ropa / Camisas); Color detectado en el nombre (chocolate) | Homologación G1522 06/10/2026: WB N.º de estilo: «» → «01-050-0017-7018» (Completado por regla) · Validador Shopify: WB: precio con IVA no termina en 9 | AK62: Odoo: producto 20971 / plantilla 26974 | AN62: Odoo Universal Unique Brands | AQ62: 8 | AR62: Odoo Universal Unique Brands › Bodega 25 › Bodega 25/General: 8
A63: 199168044282 | C63: Roper | D63: 01-050-0017-7018 | E63: 01-050-0017-7018 BR-S | F63: S | G63: S | H63: Roper | I63: ROPER Shirt Chocolate Solid Poplin | J63: Ropa | K63: Camisas | P63: Cafe | V63: PZS | W63: 53101602 | Y63: 32.55 | Z63: 869 | AA63: =IF(AND(A63="", B63="", E63=""), "", IF(AB63="", "Válido", IF((LEN(AB63)-LEN(SUBSTITUTE(AB63,"; ","")))/2+1>(LEN(AB63)-LEN(SUBSTITUTE(AB63,"[Aviso]","")))/7, "Con Incidencias", "Válido"))) | AB63: =IF(AND(A63="", B63="", E63=""), "", TEXTJOIN("; ", TRUE, IF(OR(TRIM(A63&"")="", ISNUMBER(SEARCH("FALTA", A63))), "UPC faltante/inválido", ""), IF(AND(A63<>"", IFERROR(_xlfn.XMATCH(A63,$A$2:$A$285,0,1)<>_xlfn.XMATCH(A63,$A$2:$A$285,0,-1),FALSE)), "Código de barras duplicado", ""), IF(AND(E63<>"", COUNTIF($E$2:$E$285, E63)>1), "SKU duplicado", ""), IF(OR(J63="", J63=""), "[Aviso] División no capturada ()", IF(ISNA(MATCH(J63, Criterios!$A$123:$A$126, 0)), "División no válida", "")), IF(OR(K63="", K63=""), "[Aviso] Categoría no capturada ()", IF(ISNA(MATCH(K63, Criterios!$A$81:$A$120, 0)), "Categoría no válida", IF(AND(J63<>"", J63<>"", J63<>VLOOKUP(K63, Criterios!$A$81:$B$120, 2, FALSE)), "División no coincide con Categoría", ""))), IF(OR(L63="", L63=""), "[Aviso] Género no capturado ()", IF(ISNA(MATCH(L63, Criterios!$B$123:$B$127, 0)), "Género no válido", "")), IF(OR(N63="", N63=""), "[Aviso] Temporada no capturada ()", IF(ISNA(MATCH(N63, Criterios!$C$123:$C$128, 0)), "Temporada no válida", "")), IF(OR(O63="", O63=""), "[Aviso] Ciclo de vida no capturado ()", IF(ISNA(MATCH(O63, Criterios!$D$123:$D$124, 0)), "Ciclo de vida no válido", "")))) | AG63: Nuevo – Odoo Universal Unique Brands 01/10/2026 | AH63: 01/10/2026: alta desde Odoo Universal Unique Brands (no existía en Productos por código de barras ni SKU) | Talla tomada del sufijo del SKU (S); Categoría: Palabra clave "Camisa" en tipo/categoría de la fuente (Ropa / Camisas); Color detectado en el nombre (chocolate) | Homologación G1522 06/10/2026: WB N.º de estilo: «» → «01-050-0017-7018» (Completado por regla) · Validador Shopify: WB: precio con IVA no termina en 9 | AK63: Odoo: producto 20970 / plantilla 26973 | AN63: Odoo Universal Unique Brands | AQ63: 6 | AR63: Odoo Universal Unique Brands › Bodega 25 › Bodega 25/General: 6
A64: 199168044299 | C64: Roper | D64: 01-050-0017-7018 | E64: 01-050-0017-7018 BR-XL | F64: XL | G64: XL | H64: Roper | I64: ROPER Shirt Chocolate Solid Poplin | J64: Ropa | K64: Camisas | P64: Cafe | V64: PZS | W64: 53101602 | Y64: 32.55 | Z64: 869 | AA64: =IF(AND(A64="", B64="", E64=""), "", IF(AB64="", "Válido", IF((LEN(AB64)-LEN(SUBSTITUTE(AB64,"; ","")))/2+1>(LEN(AB64)-LEN(SUBSTITUTE(AB64,"[Aviso]","")))/7, "Con Incidencias", "Válido"))) | AB64: =IF(AND(A64="", B64="", E64=""), "", TEXTJOIN("; ", TRUE, IF(OR(TRIM(A64&"")="", ISNUMBER(SEARCH("FALTA", A64))), "UPC faltante/inválido", ""), IF(AND(A64<>"", IFERROR(_xlfn.XMATCH(A64,$A$2:$A$285,0,1)<>_xlfn.XMATCH(A64,$A$2:$A$285,0,-1),FALSE)), "Código de barras duplicado", ""), IF(AND(E64<>"", COUNTIF($E$2:$E$285, E64)>1), "SKU duplicado", ""), IF(OR(J64="", J64=""), "[Aviso] División no capturada ()", IF(ISNA(MATCH(J64, Criterios!$A$123:$A$126, 0)), "División no válida", "")), IF(OR(K64="", K64=""), "[Aviso] Categoría no capturada ()", IF(ISNA(MATCH(K64, Criterios!$A$81:$A$120, 0)), "Categoría no válida", IF(AND(J64<>"", J64<>"", J64<>VLOOKUP(K64, Criterios!$A$81:$B$120, 2, FALSE)), "División no coincide con Categoría", ""))), IF(OR(L64="", L64=""), "[Aviso] Género no capturado ()", IF(ISNA(MATCH(L64, Criterios!$B$123:$B$127, 0)), "Género no válido", "")), IF(OR(N64="", N64=""), "[Aviso] Temporada no capturada ()", IF(ISNA(MATCH(N64, Criterios!$C$123:$C$128, 0)), "Temporada no válida", "")), IF(OR(O64="", O64=""), "[Aviso] Ciclo de vida no capturado ()", IF(ISNA(MATCH(O64, Criterios!$D$123:$D$124, 0)), "Ciclo de vida no válido", "")))) | AG64: Nuevo – Odoo Universal Unique Brands 01/10/2026 | AH64: 01/10/2026: alta desde Odoo Universal Unique Brands (no existía en Productos por código de barras ni SKU) | Talla tomada del sufijo del SKU (XL); Categoría: Palabra clave "Camisa" en tipo/categoría de la fuente (Ropa / Camisas); Color detectado en el nombre (chocolate) | Homologación G1522 06/10/2026: WB N.º de estilo: «» → «01-050-0017-7018» (Completado por regla) · Validador Shopify: WB: precio con IVA no termina en 9 | AK64: Odoo: producto 20973 / plantilla 26976 | AN64: Odoo Universal Unique Brands | AQ64: 8 | AR64: Odoo Universal Unique Brands › Bodega 25 › Bodega 25/General: 8
A65: 199168044473 | C65: Roper | D65: 01-050-0019-7011 | E65: 01-050-0019-7011 BL-L | F65: L | G65: L | H65: Roper | I65: ROPER Shirt Black & Grey Floral | J65: Ropa | K65: Camisas | P65: Negro | V65: PZS | W65: 53101602 | Y65: 22.55 | Z65: 629 | AA65: =IF(AND(A65="", B65="", E65=""), "", IF(AB65="", "Válido", IF((LEN(AB65)-LEN(SUBSTITUTE(AB65,"; ","")))/2+1>(LEN(AB65)-LEN(SUBSTITUTE(AB65,"[Aviso]","")))/7, "Con Incidencias", "Válido"))) | AB65: =IF(AND(A65="", B65="", E65=""), "", TEXTJOIN("; ", TRUE, IF(OR(TRIM(A65&"")="", ISNUMBER(SEARCH("FALTA", A65))), "UPC faltante/inválido", ""), IF(AND(A65<>"", IFERROR(_xlfn.XMATCH(A65,$A$2:$A$285,0,1)<>_xlfn.XMATCH(A65,$A$2:$A$285,0,-1),FALSE)), "Código de barras duplicado", ""), IF(AND(E65<>"", COUNTIF($E$2:$E$285, E65)>1), "SKU duplicado", ""), IF(OR(J65="", J65=""), "[Aviso] División no capturada ()", IF(ISNA(MATCH(J65, Criterios!$A$123:$A$126, 0)), "División no válida", "")), IF(OR(K65="", K65=""), "[Aviso] Categoría no capturada ()", IF(ISNA(MATCH(K65, Criterios!$A$81:$A$120, 0)), "Categoría no válida", IF(AND(J65<>"", J65<>"", J65<>VLOOKUP(K65, Criterios!$A$81:$B$120, 2, FALSE)), "División no coincide con Categoría", ""))), IF(OR(L65="", L65=""), "[Aviso] Género no capturado ()", IF(ISNA(MATCH(L65, Criterios!$B$123:$B$127, 0)), "Género no válido", "")), IF(OR(N65="", N65=""), "[Aviso] Temporada no capturada ()", IF(ISNA(MATCH(N65, Criterios!$C$123:$C$128, 0)), "Temporada no válida", "")), IF(OR(O65="", O65=""), "[Aviso] Ciclo de vida no capturado ()", IF(ISNA(MATCH(O65, Criterios!$D$123:$D$124, 0)), "Ciclo de vida no válido", "")))) | AG65: Nuevo – Odoo Universal Unique Brands 01/10/2026 | AH65: 01/10/2026: alta desde Odoo Universal Unique Brands (no existía en Productos por código de barras ni SKU) | Talla tomada del sufijo del SKU (L); Categoría: Palabra clave "Camisa" en tipo/categoría de la fuente (Ropa / Camisas); Color detectado en el nombre (black) | Homologación G1522 06/10/2026: WB N.º de estilo: «» → «01-050-0019-7011» (Completado por regla) | AK65: Odoo: producto 21019 / plantilla 27022 | AN65: Odoo Universal Unique Brands | AQ65: 7 | AR65: Odoo Universal Unique Brands › Bodega 25 › Bodega 25/General: 7
A66: 199168044480 | C66: Roper | D66: 01-050-0019-7011 | E66: 01-050-0019-7011 BL-M | F66: M | G66: M | H66: Roper | I66: ROPER Shirt Black & Grey Floral | J66: Ropa | K66: Camisas | P66: Negro | V66: PZS | W66: 53101602 | Y66: 22.55 | Z66: 629 | AA66: =IF(AND(A66="", B66="", E66=""), "", IF(AB66="", "Válido", IF((LEN(AB66)-LEN(SUBSTITUTE(AB66,"; ","")))/2+1>(LEN(AB66)-LEN(SUBSTITUTE(AB66,"[Aviso]","")))/7, "Con Incidencias", "Válido"))) | AB66: =IF(AND(A66="", B66="", E66=""), "", TEXTJOIN("; ", TRUE, IF(OR(TRIM(A66&"")="", ISNUMBER(SEARCH("FALTA", A66))), "UPC faltante/inválido", ""), IF(AND(A66<>"", IFERROR(_xlfn.XMATCH(A66,$A$2:$A$285,0,1)<>_xlfn.XMATCH(A66,$A$2:$A$285,0,-1),FALSE)), "Código de barras duplicado", ""), IF(AND(E66<>"", COUNTIF($E$2:$E$285, E66)>1), "SKU duplicado", ""), IF(OR(J66="", J66=""), "[Aviso] División no capturada ()", IF(ISNA(MATCH(J66, Criterios!$A$123:$A$126, 0)), "División no válida", "")), IF(OR(K66="", K66=""), "[Aviso] Categoría no capturada ()", IF(ISNA(MATCH(K66, Criterios!$A$81:$A$120, 0)), "Categoría no válida", IF(AND(J66<>"", J66<>"", J66<>VLOOKUP(K66, Criterios!$A$81:$B$120, 2, FALSE)), "División no coincide con Categoría", ""))), IF(OR(L66="", L66=""), "[Aviso] Género no capturado ()", IF(ISNA(MATCH(L66, Criterios!$B$123:$B$127, 0)), "Género no válido", "")), IF(OR(N66="", N66=""), "[Aviso] Temporada no capturada ()", IF(ISNA(MATCH(N66, Criterios!$C$123:$C$128, 0)), "Temporada no válida", "")), IF(OR(O66="", O66=""), "[Aviso] Ciclo de vida no capturado ()", IF(ISNA(MATCH(O66, Criterios!$D$123:$D$124, 0)), "Ciclo de vida no válido", "")))) | AG66: Nuevo – Odoo Universal Unique Brands 01/10/2026 | AH66: 01/10/2026: alta desde Odoo Universal Unique Brands (no existía en Productos por código de barras ni SKU) | Talla tomada del sufijo del SKU (M); Categoría: Palabra clave "Camisa" en tipo/categoría de la fuente (Ropa / Camisas); Color detectado en el nombre (black) | Homologación G1522 06/10/2026: WB N.º de estilo: «» → «01-050-0019-7011» (Completado por regla) | AK66: Odoo: producto 21018 / plantilla 27021 | AN66: Odoo Universal Unique Brands | AQ66: 7 | AR66: Odoo Universal Unique Brands › Bodega 25 › Bodega 25/General: 7
A67: 199168044497 | C67: Roper | D67: 01-050-0019-7011 | E67: 01-050-0019-7011 BL-S | F67: S | G67: S | H67: Roper | I67: ROPER Shirt Black & Grey Floral | J67: Ropa | K67: Camisas | P67: Negro | V67: PZS | W67: 53101602 | Y67: 22.55 | Z67: 629 | AA67: =IF(AND(A67="", B67="", E67=""), "", IF(AB67="", "Válido", IF((LEN(AB67)-LEN(SUBSTITUTE(AB67,"; ","")))/2+1>(LEN(AB67)-LEN(SUBSTITUTE(AB67,"[Aviso]","")))/7, "Con Incidencias", "Válido"))) | AB67: =IF(AND(A67="", B67="", E67=""), "", TEXTJOIN("; ", TRUE, IF(OR(TRIM(A67&"")="", ISNUMBER(SEARCH("FALTA", A67))), "UPC faltante/inválido", ""), IF(AND(A67<>"", IFERROR(_xlfn.XMATCH(A67,$A$2:$A$285,0,1)<>_xlfn.XMATCH(A67,$A$2:$A$285,0,-1),FALSE)), "Código de barras duplicado", ""), IF(AND(E67<>"", COUNTIF($E$2:$E$285, E67)>1), "SKU duplicado", ""), IF(OR(J67="", J67=""), "[Aviso] División no capturada ()", IF(ISNA(MATCH(J67, Criterios!$A$123:$A$126, 0)), "División no válida", "")), IF(OR(K67="", K67=""), "[Aviso] Categoría no capturada ()", IF(ISNA(MATCH(K67, Criterios!$A$81:$A$120, 0)), "Categoría no válida", IF(AND(J67<>"", J67<>"", J67<>VLOOKUP(K67, Criterios!$A$81:$B$120, 2, FALSE)), "División no coincide con Categoría", ""))), IF(OR(L67="", L67=""), "[Aviso] Género no capturado ()", IF(ISNA(MATCH(L67, Criterios!$B$123:$B$127, 0)), "Género no válido", "")), IF(OR(N67="", N67=""), "[Aviso] Temporada no capturada ()", IF(ISNA(MATCH(N67, Criterios!$C$123:$C$128, 0)), "Temporada no válida", "")), IF(OR(O67="", O67=""), "[Aviso] Ciclo de vida no capturado ()", IF(ISNA(MATCH(O67, Criterios!$D$123:$D$124, 0)), "Ciclo de vida no válido", "")))) | AG67: Nuevo – Odoo Universal Unique Brands 01/10/2026 | AH67: 01/10/2026: alta desde Odoo Universal Unique Brands (no existía en Productos por código de barras ni SKU) | Talla tomada del sufijo del SKU (S); Categoría: Palabra clave "Camisa" en tipo/categoría de la fuente (Ropa / Camisas); Color detectado en el nombre (black) | Homologación G1522 06/10/2026: WB N.º de estilo: «» → «01-050-0019-7011» (Completado por regla) | AK67: Odoo: producto 21017 / plantilla 27020 | AN67: Odoo Universal Unique Brands | AQ67: 6 | AR67: Odoo Universal Unique Brands › Bodega 25 › Bodega 25/General: 6
A68: 199168044503 | C68: Roper | D68: 01-050-0019-7011 | E68: 01-050-0019-7011 BL-XL | F68: XL | G68: XL | H68: Roper | I68: ROPER Shirt Black & Grey Floral | J68: Ropa | K68: Camisas | P68: Negro | V68: PZS | W68: 53101602 | Y68: 22.55 | Z68: 629 | AA68: =IF(AND(A68="", B68="", E68=""), "", IF(AB68="", "Válido", IF((LEN(AB68)-LEN(SUBSTITUTE(AB68,"; ","")))/2+1>(LEN(AB68)-LEN(SUBSTITUTE(AB68,"[Aviso]","")))/7, "Con Incidencias", "Válido"))) | AB68: =IF(AND(A68="", B68="", E68=""), "", TEXTJOIN("; ", TRUE, IF(OR(TRIM(A68&"")="", ISNUMBER(SEARCH("FALTA", A68))), "UPC faltante/inválido", ""), IF(AND(A68<>"", IFERROR(_xlfn.XMATCH(A68,$A$2:$A$285,0,1)<>_xlfn.XMATCH(A68,$A$2:$A$285,0,-1),FALSE)), "Código de barras duplicado", ""), IF(AND(E68<>"", COUNTIF($E$2:$E$285, E68)>1), "SKU duplicado", ""), IF(OR(J68="", J68=""), "[Aviso] División no capturada ()", IF(ISNA(MATCH(J68, Criterios!$A$123:$A$126, 0)), "División no válida", "")), IF(OR(K68="", K68=""), "[Aviso] Categoría no capturada ()", IF(ISNA(MATCH(K68, Criterios!$A$81:$A$120, 0)), "Categoría no válida", IF(AND(J68<>"", J68<>"", J68<>VLOOKUP(K68, Criterios!$A$81:$B$120, 2, FALSE)), "División no coincide con Categoría", ""))), IF(OR(L68="", L68=""), "[Aviso] Género no capturado ()", IF(ISNA(MATCH(L68, Criterios!$B$123:$B$127, 0)), "Género no válido", "")), IF(OR(N68="", N68=""), "[Aviso] Temporada no capturada ()", IF(ISNA(MATCH(N68, Criterios!$C$123:$C$128, 0)), "Temporada no válida", "")), IF(OR(O68="", O68=""), "[Aviso] Ciclo de vida no capturado ()", IF(ISNA(MATCH(O68, Criterios!$D$123:$D$124, 0)), "Ciclo de vida no válido", "")))) | AG68: Nuevo – Odoo Universal Unique Brands 01/10/2026 | AH68: 01/10/2026: alta desde Odoo Universal Unique Brands (no existía en Productos por código de barras ni SKU) | Talla tomada del sufijo del SKU (XL); Categoría: Palabra clave "Camisa" en tipo/categoría de la fuente (Ropa / Camisas); Color detectado en el nombre (black) | Homologación G1522 06/10/2026: WB N.º de estilo: «» → «01-050-0019-7011» (Completado por regla) | AK68: Odoo: producto 21020 / plantilla 27023 | AN68: Odoo Universal Unique Brands | AQ68: 7 | AR68: Odoo Universal Unique Brands › Bodega 25 › Bodega 25/General: 7
A69: 199168044572 | C69: Roper | D69: 01-050-0024-7008 | E69: 01-050-0024-7008 BL-L | F69: L | G69: L | H69: Roper | I69: ROPER Shirt Bl/Gy/Br Plaid | J69: Ropa | K69: Camisas | V69: PZS | W69: 53101604 | Y69: 33.48 | Z69: 889 | AA69: =IF(AND(A69="", B69="", E69=""), "", IF(AB69="", "Válido", IF((LEN(AB69)-LEN(SUBSTITUTE(AB69,"; ","")))/2+1>(LEN(AB69)-LEN(SUBSTITUTE(AB69,"[Aviso]","")))/7, "Con Incidencias", "Válido"))) | AB69: =IF(AND(A69="", B69="", E69=""), "", TEXTJOIN("; ", TRUE, IF(OR(TRIM(A69&"")="", ISNUMBER(SEARCH("FALTA", A69))), "UPC faltante/inválido", ""), IF(AND(A69<>"", IFERROR(_xlfn.XMATCH(A69,$A$2:$A$285,0,1)<>_xlfn.XMATCH(A69,$A$2:$A$285,0,-1),FALSE)), "Código de barras duplicado", ""), IF(AND(E69<>"", COUNTIF($E$2:$E$285, E69)>1), "SKU duplicado", ""), IF(OR(J69="", J69=""), "[Aviso] División no capturada ()", IF(ISNA(MATCH(J69, Criterios!$A$123:$A$126, 0)), "División no válida", "")), IF(OR(K69="", K69=""), "[Aviso] Categoría no capturada ()", IF(ISNA(MATCH(K69, Criterios!$A$81:$A$120, 0)), "Categoría no válida", IF(AND(J69<>"", J69<>"", J69<>VLOOKUP(K69, Criterios!$A$81:$B$120, 2, FALSE)), "División no coincide con Categoría", ""))), IF(OR(L69="", L69=""), "[Aviso] Género no capturado ()", IF(ISNA(MATCH(L69, Criterios!$B$123:$B$127, 0)), "Género no válido", "")), IF(OR(N69="", N69=""), "[Aviso] Temporada no capturada ()", IF(ISNA(MATCH(N69, Criterios!$C$123:$C$128, 0)), "Temporada no válida", "")), IF(OR(O69="", O69=""), "[Aviso] Ciclo de vida no capturado ()", IF(ISNA(MATCH(O69, Criterios!$D$123:$D$124, 0)), "Ciclo de vida no válido", "")))) | AG69: Nuevo – Odoo Universal Unique Brands 01/10/2026 | AH69: 01/10/2026: alta desde Odoo Universal Unique Brands (no existía en Productos por código de barras ni SKU) | Talla tomada del sufijo del SKU (L); Categoría: Palabra clave "Camisa" en tipo/categoría de la fuente (Ropa / Camisas) | Homologación G1522 06/10/2026: WB N.º de estilo: «» → «01-050-0024-7008» (Completado por regla) · Validador Shopify: WB: precio con IVA no termina en 9 | AK69: Odoo: producto 20977 / plantilla 26980 | AN69: Odoo Universal Unique Brands | AQ69: 5 | AR69: Odoo Universal Unique Brands › Bodega 25 › Bodega 25/General: 5
A70: 199168044589 | C70: Roper | D70: 01-050-0024-7008 | E70: 01-050-0024-7008 BL-M | F70: M | G70: M | H70: Roper | I70: ROPER Shirt Bl/Gy/Br Plaid | J70: Ropa | K70: Camisas | V70: PZS | W70: 53101604 | Y70: 33.48 | Z70: 889 | AA70: =IF(AND(A70="", B70="", E70=""), "", IF(AB70="", "Válido", IF((LEN(AB70)-LEN(SUBSTITUTE(AB70,"; ","")))/2+1>(LEN(AB70)-LEN(SUBSTITUTE(AB70,"[Aviso]","")))/7, "Con Incidencias", "Válido"))) | AB70: =IF(AND(A70="", B70="", E70=""), "", TEXTJOIN("; ", TRUE, IF(OR(TRIM(A70&"")="", ISNUMBER(SEARCH("FALTA", A70))), "UPC faltante/inválido", ""), IF(AND(A70<>"", IFERROR(_xlfn.XMATCH(A70,$A$2:$A$285,0,1)<>_xlfn.XMATCH(A70,$A$2:$A$285,0,-1),FALSE)), "Código de barras duplicado", ""), IF(AND(E70<>"", COUNTIF($E$2:$E$285, E70)>1), "SKU duplicado", ""), IF(OR(J70="", J70=""), "[Aviso] División no capturada ()", IF(ISNA(MATCH(J70, Criterios!$A$123:$A$126, 0)), "División no válida", "")), IF(OR(K70="", K70=""), "[Aviso] Categoría no capturada ()", IF(ISNA(MATCH(K70, Criterios!$A$81:$A$120, 0)), "Categoría no válida", IF(AND(J70<>"", J70<>"", J70<>VLOOKUP(K70, Criterios!$A$81:$B$120, 2, FALSE)), "División no coincide con Categoría", ""))), IF(OR(L70="", L70=""), "[Aviso] Género no capturado ()", IF(ISNA(MATCH(L70, Criterios!$B$123:$B$127, 0)), "Género no válido", "")), IF(OR(N70="", N70=""), "[Aviso] Temporada no capturada ()", IF(ISNA(MATCH(N70, Criterios!$C$123:$C$128, 0)), "Temporada no válida", "")), IF(OR(O70="", O70=""), "[Aviso] Ciclo de vida no capturado ()", IF(ISNA(MATCH(O70, Criterios!$D$123:$D$124, 0)), "Ciclo de vida no válido", "")))) | AG70: Nuevo – Odoo Universal Unique Brands 01/10/2026 | AH70: 01/10/2026: alta desde Odoo Universal Unique Brands (no existía en Productos por código de barras ni SKU) | Talla tomada del sufijo del SKU (M); Categoría: Palabra clave "Camisa" en tipo/categoría de la fuente (Ropa / Camisas) | Homologación G1522 06/10/2026: WB N.º de estilo: «» → «01-050-0024-7008» (Completado por regla) · Validador Shopify: WB: precio con IVA no termina en 9 | AK70: Odoo: producto 20976 / plantilla 26979 | AN70: Odoo Universal Unique Brands | AQ70: 5 | AR70: Odoo Universal Unique Brands › Bodega 25 › Bodega 25/General: 5
A71: 199168044596 | C71: Roper | D71: 01-050-0024-7008 | E71: 01-050-0024-7008 BL-S | F71: S | G71: S | H71: Roper | I71: ROPER Shirt Bl/Gy/Br Plaid | J71: Ropa | K71: Camisas | V71: PZS | W71: 53101604 | Y71: 33.48 | Z71: 889 | AA71: =IF(AND(A71="", B71="", E71=""), "", IF(AB71="", "Válido", IF((LEN(AB71)-LEN(SUBSTITUTE(AB71,"; ","")))/2+1>(LEN(AB71)-LEN(SUBSTITUTE(AB71,"[Aviso]","")))/7, "Con Incidencias", "Válido"))) | AB71: =IF(AND(A71="", B71="", E71=""), "", TEXTJOIN("; ", TRUE, IF(OR(TRIM(A71&"")="", ISNUMBER(SEARCH("FALTA", A71))), "UPC faltante/inválido", ""), IF(AND(A71<>"", IFERROR(_xlfn.XMATCH(A71,$A$2:$A$285,0,1)<>_xlfn.XMATCH(A71,$A$2:$A$285,0,-1),FALSE)), "Código de barras duplicado", ""), IF(AND(E71<>"", COUNTIF($E$2:$E$285, E71)>1), "SKU duplicado", ""), IF(OR(J71="", J71=""), "[Aviso] División no capturada ()", IF(ISNA(MATCH(J71, Criterios!$A$123:$A$126, 0)), "División no válida", "")), IF(OR(K71="", K71=""), "[Aviso] Categoría no capturada ()", IF(ISNA(MATCH(K71, Criterios!$A$81:$A$120, 0)), "Categoría no válida", IF(AND(J71<>"", J71<>"", J71<>VLOOKUP(K71, Criterios!$A$81:$B$120, 2, FALSE)), "División no coincide con Categoría", ""))), IF(OR(L71="", L71=""), "[Aviso] Género no capturado ()", IF(ISNA(MATCH(L71, Criterios!$B$123:$B$127, 0)), "Género no válido", "")), IF(OR(N71="", N71=""), "[Aviso] Temporada no capturada ()", IF(ISNA(MATCH(N71, Criterios!$C$123:$C$128, 0)), "Temporada no válida", "")), IF(OR(O71="", O71=""), "[Aviso] Ciclo de vida no capturado ()", IF(ISNA(MATCH(O71, Criterios!$D$123:$D$124, 0)), "Ciclo de vida no válido", "")))) | AG71: Nuevo – Odoo Universal Unique Brands 01/10/2026 | AH71: 01/10/2026: alta desde Odoo Universal Unique Brands (no existía en Productos por código de barras ni SKU) | Talla tomada del sufijo del SKU (S); Categoría: Palabra clave "Camisa" en tipo/categoría de la fuente (Ropa / Camisas) | Homologación G1522 06/10/2026: WB N.º de estilo: «» → «01-050-0024-7008» (Completado por regla) · Validador Shopify: WB: precio con IVA no termina en 9 | AK71: Odoo: producto 20975 / plantilla 26978 | AN71: Odoo Universal Unique Brands | AQ71: 5 | AR71: Odoo Universal Unique Brands › Bodega 25 › Bodega 25/General: 5
A72: 199168044602 | C72: Roper | D72: 01-050-0024-7008 | E72: 01-050-0024-7008 BL-XL | F72: XL | G72: XL | H72: Roper | I72: ROPER Shirt Bl/Gy/Br Plaid | J72: Ropa | K72: Camisas | V72: PZS | W72: 53101604 | Y72: 33.48 | Z72: 889 | AA72: =IF(AND(A72="", B72="", E72=""), "", IF(AB72="", "Válido", IF((LEN(AB72)-LEN(SUBSTITUTE(AB72,"; ","")))/2+1>(LEN(AB72)-LEN(SUBSTITUTE(AB72,"[Aviso]","")))/7, "Con Incidencias", "Válido"))) | AB72: =IF(AND(A72="", B72="", E72=""), "", TEXTJOIN("; ", TRUE, IF(OR(TRIM(A72&"")="", ISNUMBER(SEARCH("FALTA", A72))), "UPC faltante/inválido", ""), IF(AND(A72<>"", IFERROR(_xlfn.XMATCH(A72,$A$2:$A$285,0,1)<>_xlfn.XMATCH(A72,$A$2:$A$285,0,-1),FALSE)), "Código de barras duplicado", ""), IF(AND(E72<>"", COUNTIF($E$2:$E$285, E72)>1), "SKU duplicado", ""), IF(OR(J72="", J72=""), "[Aviso] División no capturada ()", IF(ISNA(MATCH(J72, Criterios!$A$123:$A$126, 0)), "División no válida", "")), IF(OR(K72="", K72=""), "[Aviso] Categoría no capturada ()", IF(ISNA(MATCH(K72, Criterios!$A$81:$A$120, 0)), "Categoría no válida", IF(AND(J72<>"", J72<>"", J72<>VLOOKUP(K72, Criterios!$A$81:$B$120, 2, FALSE)), "División no coincide con Categoría", ""))), IF(OR(L72="", L72=""), "[Aviso] Género no capturado ()", IF(ISNA(MATCH(L72, Criterios!$B$123:$B$127, 0)), "Género no válido", "")), IF(OR(N72="", N72=""), "[Aviso] Temporada no capturada ()", IF(ISNA(MATCH(N72, Criterios!$C$123:$C$128, 0)), "Temporada no válida", "")), IF(OR(O72="", O72=""), "[Aviso] Ciclo de vida no capturado ()", IF(ISNA(MATCH(O72, Criterios!$D$123:$D$124, 0)), "Ciclo de vida no válido", "")))) | AG72: Nuevo – Odoo Universal Unique Brands 01/10/2026 | AH72: 01/10/2026: alta desde Odoo Universal Unique Brands (no existía en Productos por código de barras ni SKU) | Talla tomada del sufijo del SKU (XL); Categoría: Palabra clave "Camisa" en tipo/categoría de la fuente (Ropa / Camisas) | Homologación G1522 06/10/2026: WB N.º de estilo: «» → «01-050-0024-7008» (Completado por regla) · Validador Shopify: WB: precio con IVA no termina en 9 | AK72: Odoo: producto 20978 / plantilla 26981 | AN72: Odoo Universal Unique Brands | AQ72: 6 | AR72: Odoo Universal Unique Brands › Bodega 25 › Bodega 25/General: 6
A73: 199168044800 | C73: Roper | D73: 01-050-0087-7007 | E73: 01-050-0087-7007 BU-1XL | H73: Roper | I73: ROPER Shirt Tq/Cobalt/Choc Plaid | J73: Ropa | K73: Camisas | V73: PZS | W73: 53101602 | Y73: 28.13 | Z73: 759 | AA73: =IF(AND(A73="", B73="", E73=""), "", IF(AB73="", "Válido", IF((LEN(AB73)-LEN(SUBSTITUTE(AB73,"; ","")))/2+1>(LEN(AB73)-LEN(SUBSTITUTE(AB73,"[Aviso]","")))/7, "Con Incidencias", "Válido"))) | AB73: =IF(AND(A73="", B73="", E73=""), "", TEXTJOIN("; ", TRUE, IF(OR(TRIM(A73&"")="", ISNUMBER(SEARCH("FALTA", A73))), "UPC faltante/inválido", ""), IF(AND(A73<>"", IFERROR(_xlfn.XMATCH(A73,$A$2:$A$285,0,1)<>_xlfn.XMATCH(A73,$A$2:$A$285,0,-1),FALSE)), "Código de barras duplicado", ""), IF(AND(E73<>"", COUNTIF($E$2:$E$285, E73)>1), "SKU duplicado", ""), IF(OR(J73="", J73=""), "[Aviso] División no capturada ()", IF(ISNA(MATCH(J73, Criterios!$A$123:$A$126, 0)), "División no válida", "")), IF(OR(K73="", K73=""), "[Aviso] Categoría no capturada ()", IF(ISNA(MATCH(K73, Criterios!$A$81:$A$120, 0)), "Categoría no válida", IF(AND(J73<>"", J73<>"", J73<>VLOOKUP(K73, Criterios!$A$81:$B$120, 2, FALSE)), "División no coincide con Categoría", ""))), IF(OR(L73="", L73=""), "[Aviso] Género no capturado ()", IF(ISNA(MATCH(L73, Criterios!$B$123:$B$127, 0)), "Género no válido", "")), IF(OR(N73="", N73=""), "[Aviso] Temporada no capturada ()", IF(ISNA(MATCH(N73, Criterios!$C$123:$C$128, 0)), "Temporada no válida", "")), IF(OR(O73="", O73=""), "[Aviso] Ciclo de vida no capturado ()", IF(ISNA(MATCH(O73, Criterios!$D$123:$D$124, 0)), "Ciclo de vida no válido", "")))) | AG73: Nuevo – Odoo Universal Unique Brands 01/10/2026 | AH73: 01/10/2026: alta desde Odoo Universal Unique Brands (no existía en Productos por código de barras ni SKU) | Categoría: Palabra clave "Camisa" en tipo/categoría de la fuente (Ropa / Camisas) | Homologación G1522 06/10/2026: WB N.º de estilo: «» → «01-050-0087-7007» (Completado por regla) · Validador NetSuite / Odoo: N2: talla cero o vacía · Validador Shopify: WB: precio con IVA no termina en 9 | AK73: Odoo: producto 21008 / plantilla 27011 | AN73: Odoo Universal Unique Brands | AQ73: 6 | AR73: Odoo Universal Unique Brands › Bodega 25 › Bodega 25/General: 6
A74: 199168044756 | C74: Roper | D74: 01-050-0087-7007 | E74: 01-050-0087-7007 BU-L | F74: L | G74: L | H74: Roper | I74: ROPER Shirt Tq/Cobalt/Choc Plaid | J74: Ropa | K74: Camisas | V74: PZS | W74: 53101602 | Y74: 28.13 | Z74: 759 | AA74: =IF(AND(A74="", B74="", E74=""), "", IF(AB74="", "Válido", IF((LEN(AB74)-LEN(SUBSTITUTE(AB74,"; ","")))/2+1>(LEN(AB74)-LEN(SUBSTITUTE(AB74,"[Aviso]","")))/7, "Con Incidencias", "Válido"))) | AB74: =IF(AND(A74="", B74="", E74=""), "", TEXTJOIN("; ", TRUE, IF(OR(TRIM(A74&"")="", ISNUMBER(SEARCH("FALTA", A74))), "UPC faltante/inválido", ""), IF(AND(A74<>"", IFERROR(_xlfn.XMATCH(A74,$A$2:$A$285,0,1)<>_xlfn.XMATCH(A74,$A$2:$A$285,0,-1),FALSE)), "Código de barras duplicado", ""), IF(AND(E74<>"", COUNTIF($E$2:$E$285, E74)>1), "SKU duplicado", ""), IF(OR(J74="", J74=""), "[Aviso] División no capturada ()", IF(ISNA(MATCH(J74, Criterios!$A$123:$A$126, 0)), "División no válida", "")), IF(OR(K74="", K74=""), "[Aviso] Categoría no capturada ()", IF(ISNA(MATCH(K74, Criterios!$A$81:$A$120, 0)), "Categoría no válida", IF(AND(J74<>"", J74<>"", J74<>VLOOKUP(K74, Criterios!$A$81:$B$120, 2, FALSE)), "División no coincide con Categoría", ""))), IF(OR(L74="", L74=""), "[Aviso] Género no capturado ()", IF(ISNA(MATCH(L74, Criterios!$B$123:$B$127, 0)), "Género no válido", "")), IF(OR(N74="", N74=""), "[Aviso] Temporada no capturada ()", IF(ISNA(MATCH(N74, Criterios!$C$123:$C$128, 0)), "Temporada no válida", "")), IF(OR(O74="", O74=""), "[Aviso] Ciclo de vida no capturado ()", IF(ISNA(MATCH(O74, Criterios!$D$123:$D$124, 0)), "Ciclo de vida no válido", "")))) | AG74: Nuevo – Odoo Universal Unique Brands 01/10/2026 | AH74: 01/10/2026: alta desde Odoo Universal Unique Brands (no existía en Productos por código de barras ni SKU) | Talla tomada del sufijo del SKU (L); Categoría: Palabra clave "Camisa" en tipo/categoría de la fuente (Ropa / Camisas) | Homologación G1522 06/10/2026: WB N.º de estilo: «» → «01-050-0087-7007» (Completado por regla) · Validador Shopify: WB: precio con IVA no termina en 9 | AK74: Odoo: producto 21006 / plantilla 27009 | AN74: Odoo Universal Unique Brands | AQ74: 7 | AR74: Odoo Universal Unique Brands › Bodega 25 › Bodega 25/General: 7
A75: 199168044763 | C75: Roper | D75: 01-050-0087-7007 | E75: 01-050-0087-7007 BU-M | F75: M | G75: M | H75: Roper | I75: ROPER Shirt Tq/Cobalt/Choc Plaid | J75: Ropa | K75: Camisas | V75: PZS | W75: 53101602 | Y75: 28.13 | Z75: 759 | AA75: =IF(AND(A75="", B75="", E75=""), "", IF(AB75="", "Válido", IF((LEN(AB75)-LEN(SUBSTITUTE(AB75,"; ","")))/2+1>(LEN(AB75)-LEN(SUBSTITUTE(AB75,"[Aviso]","")))/7, "Con Incidencias", "Válido"))) | AB75: =IF(AND(A75="", B75="", E75=""), "", TEXTJOIN("; ", TRUE, IF(OR(TRIM(A75&"")="", ISNUMBER(SEARCH("FALTA", A75))), "UPC faltante/inválido", ""), IF(AND(A75<>"", IFERROR(_xlfn.XMATCH(A75,$A$2:$A$285,0,1)<>_xlfn.XMATCH(A75,$A$2:$A$285,0,-1),FALSE)), "Código de barras duplicado", ""), IF(AND(E75<>"", COUNTIF($E$2:$E$285, E75)>1), "SKU duplicado", ""), IF(OR(J75="", J75=""), "[Aviso] División no capturada ()", IF(ISNA(MATCH(J75, Criterios!$A$123:$A$126, 0)), "División no válida", "")), IF(OR(K75="", K75=""), "[Aviso] Categoría no capturada ()", IF(ISNA(MATCH(K75, Criterios!$A$81:$A$120, 0)), "Categoría no válida", IF(AND(J75<>"", J75<>"", J75<>VLOOKUP(K75, Criterios!$A$81:$B$120, 2, FALSE)), "División no coincide con Categoría", ""))), IF(OR(L75="", L75=""), "[Aviso] Género no capturado ()", IF(ISNA(MATCH(L75, Criterios!$B$123:$B$127, 0)), "Género no válido", "")), IF(OR(N75="", N75=""), "[Aviso] Temporada no capturada ()", IF(ISNA(MATCH(N75, Criterios!$C$123:$C$128, 0)), "Temporada no válida", "")), IF(OR(O75="", O75=""), "[Aviso] Ciclo de vida no capturado ()", IF(ISNA(MATCH(O75, Criterios!$D$123:$D$124, 0)), "Ciclo de vida no válido", "")))) | AG75: Nuevo – Odoo Universal Unique Brands 01/10/2026 | AH75: 01/10/2026: alta desde Odoo Universal Unique Brands (no existía en Productos por código de barras ni SKU) | Talla tomada del sufijo del SKU (M); Categoría: Palabra clave "Camisa" en tipo/categoría de la fuente (Ropa / Camisas) | Homologación G1522 06/10/2026: WB N.º de estilo: «» → «01-050-0087-7007» (Completado por regla) · Validador Shopify: WB: precio con IVA no termina en 9 | AK75: Odoo: producto 21005 / plantilla 27008 | AN75: Odoo Universal Unique Brands | AQ75: 7 | AR75: Odoo Universal Unique Brands › Bodega 25 › Bodega 25/General: 7
A76: 199168044770 | C76: Roper | D76: 01-050-0087-7007 | E76: 01-050-0087-7007 BU-S | F76: S | G76: S | H76: Roper | I76: ROPER Shirt Tq/Cobalt/Choc Plaid | J76: Ropa | K76: Camisas | V76: PZS | W76: 53101602 | Y76: 28.13 | Z76: 759 | AA76: =IF(AND(A76="", B76="", E76=""), "", IF(AB76="", "Válido", IF((LEN(AB76)-LEN(SUBSTITUTE(AB76,"; ","")))/2+1>(LEN(AB76)-LEN(SUBSTITUTE(AB76,"[Aviso]","")))/7, "Con Incidencias", "Válido"))) | AB76: =IF(AND(A76="", B76="", E76=""), "", TEXTJOIN("; ", TRUE, IF(OR(TRIM(A76&"")="", ISNUMBER(SEARCH("FALTA", A76))), "UPC faltante/inválido", ""), IF(AND(A76<>"", IFERROR(_xlfn.XMATCH(A76,$A$2:$A$285,0,1)<>_xlfn.XMATCH(A76,$A$2:$A$285,0,-1),FALSE)), "Código de barras duplicado", ""), IF(AND(E76<>"", COUNTIF($E$2:$E$285, E76)>1), "SKU duplicado", ""), IF(OR(J76="", J76=""), "[Aviso] División no capturada ()", IF(ISNA(MATCH(J76, Criterios!$A$123:$A$126, 0)), "División no válida", "")), IF(OR(K76="", K76=""), "[Aviso] Categoría no capturada ()", IF(ISNA(MATCH(K76, Criterios!$A$81:$A$120, 0)), "Categoría no válida", IF(AND(J76<>"", J76<>"", J76<>VLOOKUP(K76, Criterios!$A$81:$B$120, 2, FALSE)), "División no coincide con Categoría", ""))), IF(OR(L76="", L76=""), "[Aviso] Género no capturado ()", IF(ISNA(MATCH(L76, Criterios!$B$123:$B$127, 0)), "Género no válido", "")), IF(OR(N76="", N76=""), "[Aviso] Temporada no capturada ()", IF(ISNA(MATCH(N76, Criterios!$C$123:$C$128, 0)), "Temporada no válida", "")), IF(OR(O76="", O76=""), "[Aviso] Ciclo de vida no capturado ()", IF(ISNA(MATCH(O76, Criterios!$D$123:$D$124, 0)), "Ciclo de vida no válido", "")))) | AG76: Nuevo – Odoo Universal Unique Brands 01/10/2026 | AH76: 01/10/2026: alta desde Odoo Universal Unique Brands (no existía en Productos por código de barras ni SKU) | Talla tomada del sufijo del SKU (S); Categoría: Palabra clave "Camisa" en tipo/categoría de la fuente (Ropa / Camisas) | Homologación G1522 06/10/2026: WB N.º de estilo: «» → «01-050-0087-7007» (Completado por regla) · Validador Shopify: WB: precio con IVA no termina en 9 | AK76: Odoo: producto 21004 / plantilla 27007 | AN76: Odoo Universal Unique Brands | AQ76: 6 | AR76: Odoo Universal Unique Brands › Bodega 25 › Bodega 25/General: 6
A77: 199168044787 | C77: Roper | D77: 01-050-0087-7007 | E77: 01-050-0087-7007 BU-XL | F77: XL | G77: XL | H77: Roper | I77: ROPER Shirt Tq/Cobalt/Choc Plaid | J77: Ropa | K77: Camisas | V77: PZS | W77: 53101602 | Y77: 28.13 | Z77: 759 | AA77: =IF(AND(A77="", B77="", E77=""), "", IF(AB77="", "Válido", IF((LEN(AB77)-LEN(SUBSTITUTE(AB77,"; ","")))/2+1>(LEN(AB77)-LEN(SUBSTITUTE(AB77,"[Aviso]","")))/7, "Con Incidencias", "Válido"))) | AB77: =IF(AND(A77="", B77="", E77=""), "", TEXTJOIN("; ", TRUE, IF(OR(TRIM(A77&"")="", ISNUMBER(SEARCH("FALTA", A77))), "UPC faltante/inválido", ""), IF(AND(A77<>"", IFERROR(_xlfn.XMATCH(A77,$A$2:$A$285,0,1)<>_xlfn.XMATCH(A77,$A$2:$A$285,0,-1),FALSE)), "Código de barras duplicado", ""), IF(AND(E77<>"", COUNTIF($E$2:$E$285, E77)>1), "SKU duplicado", ""), IF(OR(J77="", J77=""), "[Aviso] División no capturada ()", IF(ISNA(MATCH(J77, Criterios!$A$123:$A$126, 0)), "División no válida", "")), IF(OR(K77="", K77=""), "[Aviso] Categoría no capturada ()", IF(ISNA(MATCH(K77, Criterios!$A$81:$A$120, 0)), "Categoría no válida", IF(AND(J77<>"", J77<>"", J77<>VLOOKUP(K77, Criterios!$A$81:$B$120, 2, FALSE)), "División no coincide con Categoría", ""))), IF(OR(L77="", L77=""), "[Aviso] Género no capturado ()", IF(ISNA(MATCH(L77, Criterios!$B$123:$B$127, 0)), "Género no válido", "")), IF(OR(N77="", N77=""), "[Aviso] Temporada no capturada ()", IF(ISNA(MATCH(N77, Criterios!$C$123:$C$128, 0)), "Temporada no válida", "")), IF(OR(O77="", O77=""), "[Aviso] Ciclo de vida no capturado ()", IF(ISNA(MATCH(O77, Criterios!$D$123:$D$124, 0)), "Ciclo de vida no válido", "")))) | AG77: Nuevo – Odoo Universal Unique Brands 01/10/2026 | AH77: 01/10/2026: alta desde Odoo Universal Unique Brands (no existía en Productos por código de barras ni SKU) | Talla tomada del sufijo del SKU (XL); Categoría: Palabra clave "Camisa" en tipo/categoría de la fuente (Ropa / Camisas) | Homologación G1522 06/10/2026: WB N.º de estilo: «» → «01-050-0087-7007» (Completado por regla) · Validador Shopify: WB: precio con IVA no termina en 9 | AK77: Odoo: producto 21007 / plantilla 27010 | AN77: Odoo Universal Unique Brands | AQ77: 7 | AR77: Odoo Universal Unique Brands › Bodega 25 › Bodega 25/General: 7
A78: 199168044831 | C78: Roper | D78: 01-050-0101-7000 | E78: 01-050-0101-7000 BU-L | F78: L | G78: L | H78: Roper | I78: ROPER Shirt Multi Blue Paid W/Lurex | J78: Ropa | K78: Camisas | P78: Varios | V78: PZS | W78: 53101602 | Y78: 22.55 | Z78: 629 | AA78: =IF(AND(A78="", B78="", E78=""), "", IF(AB78="", "Válido", IF((LEN(AB78)-LEN(SUBSTITUTE(AB78,"; ","")))/2+1>(LEN(AB78)-LEN(SUBSTITUTE(AB78,"[Aviso]","")))/7, "Con Incidencias", "Válido"))) | AB78: =IF(AND(A78="", B78="", E78=""), "", TEXTJOIN("; ", TRUE, IF(OR(TRIM(A78&"")="", ISNUMBER(SEARCH("FALTA", A78))), "UPC faltante/inválido", ""), IF(AND(A78<>"", IFERROR(_xlfn.XMATCH(A78,$A$2:$A$285,0,1)<>_xlfn.XMATCH(A78,$A$2:$A$285,0,-1),FALSE)), "Código de barras duplicado", ""), IF(AND(E78<>"", COUNTIF($E$2:$E$285, E78)>1), "SKU duplicado", ""), IF(OR(J78="", J78=""), "[Aviso] División no capturada ()", IF(ISNA(MATCH(J78, Criterios!$A$123:$A$126, 0)), "División no válida", "")), IF(OR(K78="", K78=""), "[Aviso] Categoría no capturada ()", IF(ISNA(MATCH(K78, Criterios!$A$81:$A$120, 0)), "Categoría no válida", IF(AND(J78<>"", J78<>"", J78<>VLOOKUP(K78, Criterios!$A$81:$B$120, 2, FALSE)), "División no coincide con Categoría", ""))), IF(OR(L78="", L78=""), "[Aviso] Género no capturado ()", IF(ISNA(MATCH(L78, Criterios!$B$123:$B$127, 0)), "Género no válido", "")), IF(OR(N78="", N78=""), "[Aviso] Temporada no capturada ()", IF(ISNA(MATCH(N78, Criterios!$C$123:$C$128, 0)), "Temporada no válida", "")), IF(OR(O78="", O78=""), "[Aviso] Ciclo de vida no capturado ()", IF(ISNA(MATCH(O78, Criterios!$D$123:$D$124, 0)), "Ciclo de vida no válido", "")))) | AG78: Nuevo – Odoo Universal Unique Brands 01/10/2026 | AH78: 01/10/2026: alta desde Odoo Universal Unique Brands (no existía en Productos por código de barras ni SKU) | Talla tomada del sufijo del SKU (L); Categoría: Palabra clave "Camisa" en tipo/categoría de la fuente (Ropa / Camisas); Color detectado en el nombre (multi) | Homologación G1522 06/10/2026: WB N.º de estilo: «» → «01-050-0101-7000» (Completado por regla) | AK78: Odoo: producto 20981 / plantilla 26984 | AN78: Odoo Universal Unique Brands | AQ78: 2 | AR78: Odoo Universal Unique Brands › Bodega 25 › Bodega 25/General: 2
A79: 199168044848 | C79: Roper | D79: 01-050-0101-7000 | E79: 01-050-0101-7000 BU-M | F79: M | G79: M | H79: Roper | I79: ROPER Shirt Multi Blue Paid W/Lurex | J79: Ropa | K79: Camisas | P79: Varios | V79: PZS | W79: 53101602 | Y79: 22.55 | Z79: 629 | AA79: =IF(AND(A79="", B79="", E79=""), "", IF(AB79="", "Válido", IF((LEN(AB79)-LEN(SUBSTITUTE(AB79,"; ","")))/2+1>(LEN(AB79)-LEN(SUBSTITUTE(AB79,"[Aviso]","")))/7, "Con Incidencias", "Válido"))) | AB79: =IF(AND(A79="", B79="", E79=""), "", TEXTJOIN("; ", TRUE, IF(OR(TRIM(A79&"")="", ISNUMBER(SEARCH("FALTA", A79))), "UPC faltante/inválido", ""), IF(AND(A79<>"", IFERROR(_xlfn.XMATCH(A79,$A$2:$A$285,0,1)<>_xlfn.XMATCH(A79,$A$2:$A$285,0,-1),FALSE)), "Código de barras duplicado", ""), IF(AND(E79<>"", COUNTIF($E$2:$E$285, E79)>1), "SKU duplicado", ""), IF(OR(J79="", J79=""), "[Aviso] División no capturada ()", IF(ISNA(MATCH(J79, Criterios!$A$123:$A$126, 0)), "División no válida", "")), IF(OR(K79="", K79=""), "[Aviso] Categoría no capturada ()", IF(ISNA(MATCH(K79, Criterios!$A$81:$A$120, 0)), "Categoría no válida", IF(AND(J79<>"", J79<>"", J79<>VLOOKUP(K79, Criterios!$A$81:$B$120, 2, FALSE)), "División no coincide con Categoría", ""))), IF(OR(L79="", L79=""), "[Aviso] Género no capturado ()", IF(ISNA(MATCH(L79, Criterios!$B$123:$B$127, 0)), "Género no válido", "")), IF(OR(N79="", N79=""), "[Aviso] Temporada no capturada ()", IF(ISNA(MATCH(N79, Criterios!$C$123:$C$128, 0)), "Temporada no válida", "")), IF(OR(O79="", O79=""), "[Aviso] Ciclo de vida no capturado ()", IF(ISNA(MATCH(O79, Criterios!$D$123:$D$124, 0)), "Ciclo de vida no válido", "")))) | AG79: Nuevo – Odoo Universal Unique Brands 01/10/2026 | AH79: 01/10/2026: alta desde Odoo Universal Unique Brands (no existía en Productos por código de barras ni SKU) | Talla tomada del sufijo del SKU (M); Categoría: Palabra clave "Camisa" en tipo/categoría de la fuente (Ropa / Camisas); Color detectado en el nombre (multi) | Homologación G1522 06/10/2026: WB N.º de estilo: «» → «01-050-0101-7000» (Completado por regla) | AK79: Odoo: producto 20980 / plantilla 26983 | AN79: Odoo Universal Unique Brands | AQ79: 2 | AR79: Odoo Universal Unique Brands › Bodega 25 › Bodega 25/General: 2
A80: 199168044855 | C80: Roper | D80: 01-050-0101-7000 | E80: 01-050-0101-7000 BU-S | F80: S | G80: S | H80: Roper | I80: ROPER Shirt Multi Blue Paid W/Lurex | J80: Ropa | K80: Camisas | P80: Varios | V80: PZS | W80: 53101602 | Y80: 22.55 | Z80: 629 | AA80: =IF(AND(A80="", B80="", E80=""), "", IF(AB80="", "Válido", IF((LEN(AB80)-LEN(SUBSTITUTE(AB80,"; ","")))/2+1>(LEN(AB80)-LEN(SUBSTITUTE(AB80,"[Aviso]","")))/7, "Con Incidencias", "Válido"))) | AB80: =IF(AND(A80="", B80="", E80=""), "", TEXTJOIN("; ", TRUE, IF(OR(TRIM(A80&"")="", ISNUMBER(SEARCH("FALTA", A80))), "UPC faltante/inválido", ""), IF(AND(A80<>"", IFERROR(_xlfn.XMATCH(A80,$A$2:$A$285,0,1)<>_xlfn.XMATCH(A80,$A$2:$A$285,0,-1),FALSE)), "Código de barras duplicado", ""), IF(AND(E80<>"", COUNTIF($E$2:$E$285, E80)>1), "SKU duplicado", ""), IF(OR(J80="", J80=""), "[Aviso] División no capturada ()", IF(ISNA(MATCH(J80, Criterios!$A$123:$A$126, 0)), "División no válida", "")), IF(OR(K80="", K80=""), "[Aviso] Categoría no capturada ()", IF(ISNA(MATCH(K80, Criterios!$A$81:$A$120, 0)), "Categoría no válida", IF(AND(J80<>"", J80<>"", J80<>VLOOKUP(K80, Criterios!$A$81:$B$120, 2, FALSE)), "División no coincide con Categoría", ""))), IF(OR(L80="", L80=""), "[Aviso] Género no capturado ()", IF(ISNA(MATCH(L80, Criterios!$B$123:$B$127, 0)), "Género no válido", "")), IF(OR(N80="", N80=""), "[Aviso] Temporada no capturada ()", IF(ISNA(MATCH(N80, Criterios!$C$123:$C$128, 0)), "Temporada no válida", "")), IF(OR(O80="", O80=""), "[Aviso] Ciclo de vida no capturado ()", IF(ISNA(MATCH(O80, Criterios!$D$123:$D$124, 0)), "Ciclo de vida no válido", "")))) | AG80: Nuevo – Odoo Universal Unique Brands 01/10/2026 | AH80: 01/10/2026: alta desde Odoo Universal Unique Brands (no existía en Productos por código de barras ni SKU) | Talla tomada del sufijo del SKU (S); Categoría: Palabra clave "Camisa" en tipo/categoría de la fuente (Ropa / Camisas); Color detectado en el nombre (multi) | Homologación G1522 06/10/2026: WB N.º de estilo: «» → «01-050-0101-7000» (Completado por regla) | AK80: Odoo: producto 20979 / plantilla 26982 | AN80: Odoo Universal Unique Brands | AQ80: 1 | AR80: Odoo Universal Unique Brands › Bodega 25 › Bodega 25/General: 1
