Workbook

Sheet Escaneo Diario
A1: GRUPO QUINCE 22 | CONTROL DE INVENTARIOS Y CONTEO CÍCLICO DIARIO
A2: 📅 FECHA ACTUAL | C2: 📦 TOTAL ESCANEOS | E2: 🏷️ PRODUCTOS ÚNICOS | H2: 📊 TOTAL DE PIEZAS | J2: 🚀 ACCIÓN OPERATIVA
A3: =TODAY() | C3: =COUNTIF(C7:C1000, "<>") | E3: =IFERROR(__xludf.DUMMYFUNCTION("IFERROR(ROWS(UNIQUE(FILTER(D7:D1000, D7:D1000<>""""))), 0)"),0.0) | H3: =COUNTIF(C7:C1000, "<>") | J3: FINALIZAR ESCANEO
A4: Jornada en curso | C4: Registros capturados | E4: SKUs distintos | H4: Unidades contadas | J4: Asignar Folios y Archivar
A6: Fecha/Hora | B6: Ubicación/Rack | C6: UPC CODE | D6: SKU | E6: Marca | F6: Descripción | G6: División | H6: Categoría | I6: Talla / Size | J6: Alertas y Duplicados
D7: {=IF($C7="","",IFNA(_xlfn.XLOOKUP($C7,Productos!$A:$A,Productos!$E:$E,IFNA(_xlfn.XLOOKUP(TEXT($C7,"0"),Productos!$A:$A,Productos!$E:$E,IFNA(_xlfn.XLOOKUP(IFERROR(VALUE($C7),""),Productos!$A:$A,Productos!$E:$E,_xlfn.XLOOKUP($C7,Productos!$E:$E,Productos!$E:$E,"NO ENCONTRADO")),"NO ENCONTRADO")),"NO ENCONTRADO")),"NO ENCONTRADO"))} | E7: {=IF(OR($D7="",$D7="NO ENCONTRADO"),"",_xlfn.XLOOKUP($D7,Productos!$E:$E,Productos!$H:$H,""))} | F7: {=IF(OR($D7="",$D7="NO ENCONTRADO"),"",_xlfn.XLOOKUP($D7,Productos!$E:$E,Productos!$I:$I,""))} | G7: {=IF(OR($D7="",$D7="NO ENCONTRADO"),"",_xlfn.XLOOKUP($D7,Productos!$E:$E,Productos!$J:$J,""))} | H7: {=IF(OR($D7="",$D7="NO ENCONTRADO"),"",_xlfn.XLOOKUP($D7,Productos!$E:$E,Productos!$K:$K,""))} | I7: {=IF(OR($D7="",$D7="NO ENCONTRADO"),"",_xlfn.XLOOKUP($D7,Productos!$E:$E,Productos!$F:$F,""))} | J7: =IF($C7="","",IF($D7="NO ENCONTRADO",IF(COUNTIF($C$7:$C$1000,$C7)>1,"⚠️ No encontrado | Duplicado","⚠️ No encontrado"),IF(COUNTIF($C$7:$C$1000,$C7)>1,"⚠️ Duplicado","Verificado")))
D8: {=IF($C8="","",IFNA(_xlfn.XLOOKUP($C8,Productos!$A:$A,Productos!$E:$E,IFNA(_xlfn.XLOOKUP(TEXT($C8,"0"),Productos!$A:$A,Productos!$E:$E,IFNA(_xlfn.XLOOKUP(IFERROR(VALUE($C8),""),Productos!$A:$A,Productos!$E:$E,_xlfn.XLOOKUP($C8,Productos!$E:$E,Productos!$E:$E,"NO ENCONTRADO")),"NO ENCONTRADO")),"NO ENCONTRADO")),"NO ENCONTRADO"))} | E8: {=IF(OR($D8="",$D8="NO ENCONTRADO"),"",_xlfn.XLOOKUP($D8,Productos!$E:$E,Productos!$H:$H,""))} | F8: {=IF(OR($D8="",$D8="NO ENCONTRADO"),"",_xlfn.XLOOKUP($D8,Productos!$E:$E,Productos!$I:$I,""))} | G8: {=IF(OR($D8="",$D8="NO ENCONTRADO"),"",_xlfn.XLOOKUP($D8,Productos!$E:$E,Productos!$J:$J,""))} | H8: {=IF(OR($D8="",$D8="NO ENCONTRADO"),"",_xlfn.XLOOKUP($D8,Productos!$E:$E,Productos!$K:$K,""))} | I8: {=IF(OR($D8="",$D8="NO ENCONTRADO"),"",_xlfn.XLOOKUP($D8,Productos!$E:$E,Productos!$F:$F,""))} | J8: =IF($C8="","",IF($D8="NO ENCONTRADO",IF(COUNTIF($C$7:$C$1000,$C8)>1,"⚠️ No encontrado | Duplicado","⚠️ No encontrado"),IF(COUNTIF($C$7:$C$1000,$C8)>1,"⚠️ Duplicado","Verificado")))
D9: {=IF($C9="","",IFNA(_xlfn.XLOOKUP($C9,Productos!$A:$A,Productos!$E:$E,IFNA(_xlfn.XLOOKUP(TEXT($C9,"0"),Productos!$A:$A,Productos!$E:$E,IFNA(_xlfn.XLOOKUP(IFERROR(VALUE($C9),""),Productos!$A:$A,Productos!$E:$E,_xlfn.XLOOKUP($C9,Productos!$E:$E,Productos!$E:$E,"NO ENCONTRADO")),"NO ENCONTRADO")),"NO ENCONTRADO")),"NO ENCONTRADO"))} | E9: {=IF(OR($D9="",$D9="NO ENCONTRADO"),"",_xlfn.XLOOKUP($D9,Productos!$E:$E,Productos!$H:$H,""))} | F9: {=IF(OR($D9="",$D9="NO ENCONTRADO"),"",_xlfn.XLOOKUP($D9,Productos!$E:$E,Productos!$I:$I,""))} | G9: {=IF(OR($D9="",$D9="NO ENCONTRADO"),"",_xlfn.XLOOKUP($D9,Productos!$E:$E,Productos!$J:$J,""))} | H9: {=IF(OR($D9="",$D9="NO ENCONTRADO"),"",_xlfn.XLOOKUP($D9,Productos!$E:$E,Productos!$K:$K,""))} | I9: {=IF(OR($D9="",$D9="NO ENCONTRADO"),"",_xlfn.XLOOKUP($D9,Productos!$E:$E,Productos!$F:$F,""))} | J9: =IF($C9="","",IF($D9="NO ENCONTRADO",IF(COUNTIF($C$7:$C$1000,$C9)>1,"⚠️ No encontrado | Duplicado","⚠️ No encontrado"),IF(COUNTIF($C$7:$C$1000,$C9)>1,"⚠️ Duplicado","Verificado")))
D10: {=IF($C10="","",IFNA(_xlfn.XLOOKUP($C10,Productos!$A:$A,Productos!$E:$E,IFNA(_xlfn.XLOOKUP(TEXT($C10,"0"),Productos!$A:$A,Productos!$E:$E,IFNA(_xlfn.XLOOKUP(IFERROR(VALUE($C10),""),Productos!$A:$A,Productos!$E:$E,_xlfn.XLOOKUP($C10,Productos!$E:$E,Productos!$E:$E,"NO ENCONTRADO")),"NO ENCONTRADO")),"NO ENCONTRADO")),"NO ENCONTRADO"))} | E10: {=IF(OR($D10="",$D10="NO ENCONTRADO"),"",_xlfn.XLOOKUP($D10,Productos!$E:$E,Productos!$H:$H,""))} | F10: {=IF(OR($D10="",$D10="NO ENCONTRADO"),"",_xlfn.XLOOKUP($D10,Productos!$E:$E,Productos!$I:$I,""))} | G10: {=IF(OR($D10="",$D10="NO ENCONTRADO"),"",_xlfn.XLOOKUP($D10,Productos!$E:$E,Productos!$J:$J,""))} | H10: {=IF(OR($D10="",$D10="NO ENCONTRADO"),"",_xlfn.XLOOKUP($D10,Productos!$E:$E,Productos!$K:$K,""))} | I10: {=IF(OR($D10="",$D10="NO ENCONTRADO"),"",_xlfn.XLOOKUP($D10,Productos!$E:$E,Productos!$F:$F,""))} | J10: =IF($C10="","",IF($D10="NO ENCONTRADO",IF(COUNTIF($C$7:$C$1000,$C10)>1,"⚠️ No encontrado | Duplicado","⚠️ No encontrado"),IF(COUNTIF($C$7:$C$1000,$C10)>1,"⚠️ Duplicado","Verificado")))
D11: {=IF($C11="","",IFNA(_xlfn.XLOOKUP($C11,Productos!$A:$A,Productos!$E:$E,IFNA(_xlfn.XLOOKUP(TEXT($C11,"0"),Productos!$A:$A,Productos!$E:$E,IFNA(_xlfn.XLOOKUP(IFERROR(VALUE($C11),""),Productos!$A:$A,Productos!$E:$E,_xlfn.XLOOKUP($C11,Productos!$E:$E,Productos!$E:$E,"NO ENCONTRADO")),"NO ENCONTRADO")),"NO ENCONTRADO")),"NO ENCONTRADO"))} | E11: {=IF(OR($D11="",$D11="NO ENCONTRADO"),"",_xlfn.XLOOKUP($D11,Productos!$E:$E,Productos!$H:$H,""))} | F11: {=IF(OR($D11="",$D11="NO ENCONTRADO"),"",_xlfn.XLOOKUP($D11,Productos!$E:$E,Productos!$I:$I,""))} | G11: {=IF(OR($D11="",$D11="NO ENCONTRADO"),"",_xlfn.XLOOKUP($D11,Productos!$E:$E,Productos!$J:$J,""))} | H11: {=IF(OR($D11="",$D11="NO ENCONTRADO"),"",_xlfn.XLOOKUP($D11,Productos!$E:$E,Productos!$K:$K,""))} | I11: {=IF(OR($D11="",$D11="NO ENCONTRADO"),"",_xlfn.XLOOKUP($D11,Productos!$E:$E,Productos!$F:$F,""))} | J11: =IF($C11="","",IF($D11="NO ENCONTRADO",IF(COUNTIF($C$7:$C$1000,$C11)>1,"⚠️ No encontrado | Duplicado","⚠️ No encontrado"),IF(COUNTIF($C$7:$C$1000,$C11)>1,"⚠️ Duplicado","Verificado")))
D12: {=IF($C12="","",IFNA(_xlfn.XLOOKUP($C12,Productos!$A:$A,Productos!$E:$E,IFNA(_xlfn.XLOOKUP(TEXT($C12,"0"),Productos!$A:$A,Productos!$E:$E,IFNA(_xlfn.XLOOKUP(IFERROR(VALUE($C12),""),Productos!$A:$A,Productos!$E:$E,_xlfn.XLOOKUP($C12,Productos!$E:$E,Productos!$E:$E,"NO ENCONTRADO")),"NO ENCONTRADO")),"NO ENCONTRADO")),"NO ENCONTRADO"))} | E12: {=IF(OR($D12="",$D12="NO ENCONTRADO"),"",_xlfn.XLOOKUP($D12,Productos!$E:$E,Productos!$H:$H,""))} | F12: {=IF(OR($D12="",$D12="NO ENCONTRADO"),"",_xlfn.XLOOKUP($D12,Productos!$E:$E,Productos!$I:$I,""))} | G12: {=IF(OR($D12="",$D12="NO ENCONTRADO"),"",_xlfn.XLOOKUP($D12,Productos!$E:$E,Productos!$J:$J,""))} | H12: {=IF(OR($D12="",$D12="NO ENCONTRADO"),"",_xlfn.XLOOKUP($D12,Productos!$E:$E,Productos!$K:$K,""))} | I12: {=IF(OR($D12="",$D12="NO ENCONTRADO"),"",_xlfn.XLOOKUP($D12,Productos!$E:$E,Productos!$F:$F,""))} | J12: =IF($C12="","",IF($D12="NO ENCONTRADO",IF(COUNTIF($C$7:$C$1000,$C12)>1,"⚠️ No encontrado | Duplicado","⚠️ No encontrado"),IF(COUNTIF($C$7:$C$1000,$C12)>1,"⚠️ Duplicado","Verificado")))
D13: {=IF($C13="","",IFNA(_xlfn.XLOOKUP($C13,Productos!$A:$A,Productos!$E:$E,IFNA(_xlfn.XLOOKUP(TEXT($C13,"0"),Productos!$A:$A,Productos!$E:$E,IFNA(_xlfn.XLOOKUP(IFERROR(VALUE($C13),""),Productos!$A:$A,Productos!$E:$E,_xlfn.XLOOKUP($C13,Productos!$E:$E,Productos!$E:$E,"NO ENCONTRADO")),"NO ENCONTRADO")),"NO ENCONTRADO")),"NO ENCONTRADO"))} | E13: {=IF(OR($D13="",$D13="NO ENCONTRADO"),"",_xlfn.XLOOKUP($D13,Productos!$E:$E,Productos!$H:$H,""))} | F13: {=IF(OR($D13="",$D13="NO ENCONTRADO"),"",_xlfn.XLOOKUP($D13,Productos!$E:$E,Productos!$I:$I,""))} | G13: {=IF(OR($D13="",$D13="NO ENCONTRADO"),"",_xlfn.XLOOKUP($D13,Productos!$E:$E,Productos!$J:$J,""))} | H13: {=IF(OR($D13="",$D13="NO ENCONTRADO"),"",_xlfn.XLOOKUP($D13,Productos!$E:$E,Productos!$K:$K,""))} | I13: {=IF(OR($D13="",$D13="NO ENCONTRADO"),"",_xlfn.XLOOKUP($D13,Productos!$E:$E,Productos!$F:$F,""))} | J13: =IF($C13="","",IF($D13="NO ENCONTRADO",IF(COUNTIF($C$7:$C$1000,$C13)>1,"⚠️ No encontrado | Duplicado","⚠️ No encontrado"),IF(COUNTIF($C$7:$C$1000,$C13)>1,"⚠️ Duplicado","Verificado")))
D14: {=IF($C14="","",IFNA(_xlfn.XLOOKUP($C14,Productos!$A:$A,Productos!$E:$E,IFNA(_xlfn.XLOOKUP(TEXT($C14,"0"),Productos!$A:$A,Productos!$E:$E,IFNA(_xlfn.XLOOKUP(IFERROR(VALUE($C14),""),Productos!$A:$A,Productos!$E:$E,_xlfn.XLOOKUP($C14,Productos!$E:$E,Productos!$E:$E,"NO ENCONTRADO")),"NO ENCONTRADO")),"NO ENCONTRADO")),"NO ENCONTRADO"))} | E14: {=IF(OR($D14="",$D14="NO ENCONTRADO"),"",_xlfn.XLOOKUP($D14,Productos!$E:$E,Productos!$H:$H,""))} | F14: {=IF(OR($D14="",$D14="NO ENCONTRADO"),"",_xlfn.XLOOKUP($D14,Productos!$E:$E,Productos!$I:$I,""))} | G14: {=IF(OR($D14="",$D14="NO ENCONTRADO"),"",_xlfn.XLOOKUP($D14,Productos!$E:$E,Productos!$J:$J,""))} | H14: {=IF(OR($D14="",$D14="NO ENCONTRADO"),"",_xlfn.XLOOKUP($D14,Productos!$E:$E,Productos!$K:$K,""))} | I14: {=IF(OR($D14="",$D14="NO ENCONTRADO"),"",_xlfn.XLOOKUP($D14,Productos!$E:$E,Productos!$F:$F,""))} | J14: =IF($C14="","",IF($D14="NO ENCONTRADO",IF(COUNTIF($C$7:$C$1000,$C14)>1,"⚠️ No encontrado | Duplicado","⚠️ No encontrado"),IF(COUNTIF($C$7:$C$1000,$C14)>1,"⚠️ Duplicado","Verificado")))
D15: {=IF($C15="","",IFNA(_xlfn.XLOOKUP($C15,Productos!$A:$A,Productos!$E:$E,IFNA(_xlfn.XLOOKUP(TEXT($C15,"0"),Productos!$A:$A,Productos!$E:$E,IFNA(_xlfn.XLOOKUP(IFERROR(VALUE($C15),""),Productos!$A:$A,Productos!$E:$E,_xlfn.XLOOKUP($C15,Productos!$E:$E,Productos!$E:$E,"NO ENCONTRADO")),"NO ENCONTRADO")),"NO ENCONTRADO")),"NO ENCONTRADO"))} | E15: {=IF(OR($D15="",$D15="NO ENCONTRADO"),"",_xlfn.XLOOKUP($D15,Productos!$E:$E,Productos!$H:$H,""))} | F15: {=IF(OR($D15="",$D15="NO ENCONTRADO"),"",_xlfn.XLOOKUP($D15,Productos!$E:$E,Productos!$I:$I,""))} | G15: {=IF(OR($D15="",$D15="NO ENCONTRADO"),"",_xlfn.XLOOKUP($D15,Productos!$E:$E,Productos!$J:$J,""))} | H15: {=IF(OR($D15="",$D15="NO ENCONTRADO"),"",_xlfn.XLOOKUP($D15,Productos!$E:$E,Productos!$K:$K,""))} | I15: {=IF(OR($D15="",$D15="NO ENCONTRADO"),"",_xlfn.XLOOKUP($D15,Productos!$E:$E,Productos!$F:$F,""))} | J15: =IF($C15="","",IF($D15="NO ENCONTRADO",IF(COUNTIF($C$7:$C$1000,$C15)>1,"⚠️ No encontrado | Duplicado","⚠️ No encontrado"),IF(COUNTIF($C$7:$C$1000,$C15)>1,"⚠️ Duplicado","Verificado")))
D16: {=IF($C16="","",IFNA(_xlfn.XLOOKUP($C16,Productos!$A:$A,Productos!$E:$E,IFNA(_xlfn.XLOOKUP(TEXT($C16,"0"),Productos!$A:$A,Productos!$E:$E,IFNA(_xlfn.XLOOKUP(IFERROR(VALUE($C16),""),Productos!$A:$A,Productos!$E:$E,_xlfn.XLOOKUP($C16,Productos!$E:$E,Productos!$E:$E,"NO ENCONTRADO")),"NO ENCONTRADO")),"NO ENCONTRADO")),"NO ENCONTRADO"))} | E16: {=IF(OR($D16="",$D16="NO ENCONTRADO"),"",_xlfn.XLOOKUP($D16,Productos!$E:$E,Productos!$H:$H,""))} | F16: {=IF(OR($D16="",$D16="NO ENCONTRADO"),"",_xlfn.XLOOKUP($D16,Productos!$E:$E,Productos!$I:$I,""))} | G16: {=IF(OR($D16="",$D16="NO ENCONTRADO"),"",_xlfn.XLOOKUP($D16,Productos!$E:$E,Productos!$J:$J,""))} | H16: {=IF(OR($D16="",$D16="NO ENCONTRADO"),"",_xlfn.XLOOKUP($D16,Productos!$E:$E,Productos!$K:$K,""))} | I16: {=IF(OR($D16="",$D16="NO ENCONTRADO"),"",_xlfn.XLOOKUP($D16,Productos!$E:$E,Productos!$F:$F,""))} | J16: =IF($C16="","",IF($D16="NO ENCONTRADO",IF(COUNTIF($C$7:$C$1000,$C16)>1,"⚠️ No encontrado | Duplicado","⚠️ No encontrado"),IF(COUNTIF($C$7:$C$1000,$C16)>1,"⚠️ Duplicado","Verificado")))
D17: {=IF($C17="","",IFNA(_xlfn.XLOOKUP($C17,Productos!$A:$A,Productos!$E:$E,IFNA(_xlfn.XLOOKUP(TEXT($C17,"0"),Productos!$A:$A,Productos!$E:$E,IFNA(_xlfn.XLOOKUP(IFERROR(VALUE($C17),""),Productos!$A:$A,Productos!$E:$E,_xlfn.XLOOKUP($C17,Productos!$E:$E,Productos!$E:$E,"NO ENCONTRADO")),"NO ENCONTRADO")),"NO ENCONTRADO")),"NO ENCONTRADO"))} | E17: {=IF(OR($D17="",$D17="NO ENCONTRADO"),"",_xlfn.XLOOKUP($D17,Productos!$E:$E,Productos!$H:$H,""))} | F17: {=IF(OR($D17="",$D17="NO ENCONTRADO"),"",_xlfn.XLOOKUP($D17,Productos!$E:$E,Productos!$I:$I,""))} | G17: {=IF(OR($D17="",$D17="NO ENCONTRADO"),"",_xlfn.XLOOKUP($D17,Productos!$E:$E,Productos!$J:$J,""))} | H17: {=IF(OR($D17="",$D17="NO ENCONTRADO"),"",_xlfn.XLOOKUP($D17,Productos!$E:$E,Productos!$K:$K,""))} | I17: {=IF(OR($D17="",$D17="NO ENCONTRADO"),"",_xlfn.XLOOKUP($D17,Productos!$E:$E,Productos!$F:$F,""))} | J17: =IF($C17="","",IF($D17="NO ENCONTRADO",IF(COUNTIF($C$7:$C$1000,$C17)>1,"⚠️ No encontrado | Duplicado","⚠️ No encontrado"),IF(COUNTIF($C$7:$C$1000,$C17)>1,"⚠️ Duplicado","Verificado")))
D18: {=IF($C18="","",IFNA(_xlfn.XLOOKUP($C18,Productos!$A:$A,Productos!$E:$E,IFNA(_xlfn.XLOOKUP(TEXT($C18,"0"),Productos!$A:$A,Productos!$E:$E,IFNA(_xlfn.XLOOKUP(IFERROR(VALUE($C18),""),Productos!$A:$A,Productos!$E:$E,_xlfn.XLOOKUP($C18,Productos!$E:$E,Productos!$E:$E,"NO ENCONTRADO")),"NO ENCONTRADO")),"NO ENCONTRADO")),"NO ENCONTRADO"))} | E18: {=IF(OR($D18="",$D18="NO ENCONTRADO"),"",_xlfn.XLOOKUP($D18,Productos!$E:$E,Productos!$H:$H,""))} | F18: {=IF(OR($D18="",$D18="NO ENCONTRADO"),"",_xlfn.XLOOKUP($D18,Productos!$E:$E,Productos!$I:$I,""))} | G18: {=IF(OR($D18="",$D18="NO ENCONTRADO"),"",_xlfn.XLOOKUP($D18,Productos!$E:$E,Productos!$J:$J,""))} | H18: {=IF(OR($D18="",$D18="NO ENCONTRADO"),"",_xlfn.XLOOKUP($D18,Productos!$E:$E,Productos!$K:$K,""))} | I18: {=IF(OR($D18="",$D18="NO ENCONTRADO"),"",_xlfn.XLOOKUP($D18,Productos!$E:$E,Productos!$F:$F,""))} | J18: =IF($C18="","",IF($D18="NO ENCONTRADO",IF(COUNTIF($C$7:$C$1000,$C18)>1,"⚠️ No encontrado | Duplicado","⚠️ No encontrado"),IF(COUNTIF($C$7:$C$1000,$C18)>1,"⚠️ Duplicado","Verificado")))
... D1000: {=IF($C1000="","",IFNA(_xlfn.XLOOKUP($C1000,Productos!$A:$A,Productos!$E:$E,IFNA(_xlfn.XLOOKUP(TEXT($C1000,"0"),Productos!$A:$A,Productos!$E:$E,IFNA(_xlfn.XLOOKUP(IFERROR(VALUE($C1000),""),Productos!$A:$A,Productos!$E:$E,_xlfn.XLOOKUP($C1000,Productos!$E:$E,Productos!$E:$E,"NO ENCONTRADO")),"NO ENCONTRADO")),"NO ENCONTRADO")),"NO ENCONTRADO"))} | E1000: {=IF(OR($D1000="",$D1000="NO ENCONTRADO"),"",_xlfn.XLOOKUP($D1000,Productos!$E:$E,Productos!$H:$H,""))} | F1000: {=IF(OR($D1000="",$D1000="NO ENCONTRADO"),"",_xlfn.XLOOKUP($D1000,Productos!$E:$E,Productos!$I:$I,""))} | G1000: {=IF(OR($D1000="",$D1000="NO ENCONTRADO"),"",_xlfn.XLOOKUP($D1000,Productos!$E:$E,Productos!$J:$J,""))} | H1000: {=IF(OR($D1000="",$D1000="NO ENCONTRADO"),"",_xlfn.XLOOKUP($D1000,Productos!$E:$E,Productos!$K:$K,""))} | I1000: {=IF(OR($D1000="",$D1000="NO ENCONTRADO"),"",_xlfn.XLOOKUP($D1000,Productos!$E:$E,Productos!$F:$F,""))} | J1000: =IF($C1000="","",IF($D1000="NO ENCONTRADO",IF(COUNTIF($C$7:$C$1000,$C1000)>1,"⚠️ No encontrado | Duplicado","⚠️ No encontrado"),IF(COUNTIF($C$7:$C$1000,$C1000)>1,"⚠️ Duplicado","Verificado")))

Sheet Historial de Escaneos
A1: HISTORIAL Y BITÁCORA CONSOLIDADA DE CONTEOS CÍCLICOS - GRUPO QUINCE 22
A2: Registro histórico de auditorías, folios automáticos por ubicación y trazabilidad consolidada de marcas e inventario físico
A3: Fecha de Conteo | B3: Hora Registro | C3: Folio de Escaneo | D3: Ubicación / Rack | E3: Marcas Escaneadas (Todas) | F3: Total Piezas | G3: Auditor / Responsable | H3: Dictamen de Auditoría | I3: Alertas de Modificación / Incidencias

Sheet Escaneos
A1: Folio de Escaneo | B1: Fecha / Hora | C1: Ubicación / Rack | D1: UPC CODE | E1: SKU | F1: Marca | G1: Descripción | H1: Categoría | I1: Talla / Size | J1: Piezas Contadas | K1: Auditor / Responsable | L1: Estado de Conteo | M1: Detalle de Modificaciones / Alertas

Sheet Configuración
A1: CONFIGURACIÓN DEL SISTEMA Y CATÁLOGOS MAESTROS - GRUPO QUINCE 22
A2: Catálogos oficiales para validación de datos y listas desplegables del conteo cíclico diario
A3: Ubicaciones / Racks | B3: Marcas | C3: Categorías | D3: Tallas / Sizes | E3: Auditores / Operadores | F3: Estado de Conteo | H3: Ubicaciones NetSuite (Hoja a Revisar) | I3: SKUs con stock | J3: Piezas en sistema
A4: Pasillo A - Racks Principales | B4: 1522 Original | C4: Playeras | D4: XS | E4: Jesús Fregoso | F4: Verificado | H4: Almacenes G1522 | I4: {=_xlfn.XLOOKUP($H4,Criterios!$G$6:$G$200,Criterios!I$6:I$200,"")} | J4: {=_xlfn.XLOOKUP($H4,Criterios!$G$6:$G$200,Criterios!J$6:J$200,"")}
A5: Pasillo B - Estantería Media | B5: Urban Trend | C5: Pantalones | D5: S | E5: Carlos Morales | F5: Con Discrepancia | H5: AMAZON | I5: {=_xlfn.XLOOKUP($H5,Criterios!$G$6:$G$200,Criterios!I$6:I$200,"")} | J5: {=_xlfn.XLOOKUP($H5,Criterios!$G$6:$G$200,Criterios!J$6:J$200,"")}
A6: Pasillo C - Calzado y Confección | B6: Denim Co. | C6: Sudaderas | D6: M | E6: Andrea Valenzuela | F6: Pendiente | H6: ARIAT CHIHUAHUA | I6: {=_xlfn.XLOOKUP($H6,Criterios!$G$6:$G$200,Criterios!I$6:I$200,"")} | J6: {=_xlfn.XLOOKUP($H6,Criterios!$G$6:$G$200,Criterios!J$6:J$200,"")}
A7: Pasillo D - Accesorios | B7: Active Wear | C7: Chamarras | D7: L | E7: Luis Fernández | F7: Revisión Requerida | H7: ARIAT OUTLET GDL | I7: {=_xlfn.XLOOKUP($H7,Criterios!$G$6:$G$200,Criterios!I$6:I$200,"")} | J7: {=_xlfn.XLOOKUP($H7,Criterios!$G$6:$G$200,Criterios!J$6:J$200,"")}
A8: Pasillo E - Devoluciones | B8: Casual Basics | C8: Gorras | D8: XL | E8: Mariana Garza | H8: ARIAT PLAZA SAN LUIS | I8: {=_xlfn.XLOOKUP($H8,Criterios!$G$6:$G$200,Criterios!I$6:I$200,"")} | J8: {=_xlfn.XLOOKUP($H8,Criterios!$G$6:$G$200,Criterios!J$6:J$200,"")}
A9: Bodega Central - Tarimas | B9: Signature 1522 | C9: Camisas | D9: XXL | E9: Roberto Méndez | H9: ARIAT SAN NICOLAS NL | I9: {=_xlfn.XLOOKUP($H9,Criterios!$G$6:$G$200,Criterios!I$6:I$200,"")} | J9: {=_xlfn.XLOOKUP($H9,Criterios!$G$6:$G$200,Criterios!J$6:J$200,"")}
A10: Zona de Picking 1 | B10: Premium Line | C10: Calzado | D10: 28x32 | E10: Sofía Castro | H10: B25 CEDIS | I10: {=_xlfn.XLOOKUP($H10,Criterios!$G$6:$G$200,Criterios!I$6:I$200,"")} | J10: {=_xlfn.XLOOKUP($H10,Criterios!$G$6:$G$200,Criterios!J$6:J$200,"")}
A11: Zona de Recepción | B11: Vintage Republic | C11: Accesorios | D11: 30x32 | E11: Miguel Ángel Ruiz | H11: B25 STETSON.MX | I11: {=_xlfn.XLOOKUP($H11,Criterios!$G$6:$G$200,Criterios!I$6:I$200,"")} | J11: {=_xlfn.XLOOKUP($H11,Criterios!$G$6:$G$200,Criterios!J$6:J$200,"")}
A12: Almacén General - Cuarentena | B12: Essentials | C12: Ropa Deportiva | D12: 32x32 | E12: Diana Navarro | H12: B25 WB MERCADO LIBRE | I12: {=_xlfn.XLOOKUP($H12,Criterios!$G$6:$G$200,Criterios!I$6:I$200,"")} | J12: {=_xlfn.XLOOKUP($H12,Criterios!$G$6:$G$200,Criterios!J$6:J$200,"")}
A13: Mesa de Empaque | B13: Colección Especial | C13: Ropa Interior | D13: 34x32 | E13: Pedro Gómez | H13: B25 WESTERN BROTHERS.MX | I13: {=_xlfn.XLOOKUP($H13,Criterios!$G$6:$G$200,Criterios!I$6:I$200,"")} | J13: {=_xlfn.XLOOKUP($H13,Criterios!$G$6:$G$200,Criterios!J$6:J$200,"")}
A14: Área de Devoluciones | B14: Edición Limitada | C14: Calcetería | D14: UNITALLA | E14: Laura Sánchez | H14: CAPSLAB Warehouse | I14: {=_xlfn.XLOOKUP($H14,Criterios!$G$6:$G$200,Criterios!I$6:I$200,"")} | J14: {=_xlfn.XLOOKUP($H14,Criterios!$G$6:$G$200,Criterios!J$6:J$200,"")}
A15: J1-L1-01 | B15: Stetson | C15: Jeans | D15: 29 x 32 | H15: CL Muestras | I15: {=_xlfn.XLOOKUP($H15,Criterios!$G$6:$G$200,Criterios!I$6:I$200,"")} | J15: {=_xlfn.XLOOKUP($H15,Criterios!$G$6:$G$200,Criterios!J$6:J$200,"")}
A16: Almacenes G1522 | B16: Ariat | C16: Denim | D16: 30 x 32 | H16: CL POS | I16: {=_xlfn.XLOOKUP($H16,Criterios!$G$6:$G$200,Criterios!I$6:I$200,"")} | J16: {=_xlfn.XLOOKUP($H16,Criterios!$G$6:$G$200,Criterios!J$6:J$200,"")}
A17: AMAZON | B17: CAPSLAB | C17: Ropa | D17: 31 x 32 | H17: CONSIGNA REFLO | I17: {=_xlfn.XLOOKUP($H17,Criterios!$G$6:$G$200,Criterios!I$6:I$200,"")} | J17: {=_xlfn.XLOOKUP($H17,Criterios!$G$6:$G$200,Criterios!J$6:J$200,"")}
A18: ARIAT CHIHUAHUA | B18: Denver | D18: 32 x 34 | H18: CONSIGNAS | I18: {=_xlfn.XLOOKUP($H18,Criterios!$G$6:$G$200,Criterios!I$6:I$200,"")} | J18: {=_xlfn.XLOOKUP($H18,Criterios!$G$6:$G$200,Criterios!J$6:J$200,"")}
A19: ARIAT OUTLET GDL | B19: Generico | D19: 33 x 32 | H19: DEPARTAMENTAL | I19: {=_xlfn.XLOOKUP($H19,Criterios!$G$6:$G$200,Criterios!I$6:I$200,"")} | J19: {=_xlfn.XLOOKUP($H19,Criterios!$G$6:$G$200,Criterios!J$6:J$200,"")}
A20: ARIAT PLAZA SAN LUIS | B20: Happy Socks | D20: 34 x 34 | H20: ECOMMERCE | I20: {=_xlfn.XLOOKUP($H20,Criterios!$G$6:$G$200,Criterios!I$6:I$200,"")} | J20: {=_xlfn.XLOOKUP($H20,Criterios!$G$6:$G$200,Criterios!J$6:J$200,"")}
A21: ARIAT SAN NICOLAS NL | B21: Montana West | D21: 34 x 36 | H21: ENGLISH REP | I21: {=_xlfn.XLOOKUP($H21,Criterios!$G$6:$G$200,Criterios!I$6:I$200,"")} | J21: {=_xlfn.XLOOKUP($H21,Criterios!$G$6:$G$200,Criterios!J$6:J$200,"")}
A22: B25 CEDIS | B22: REFLO | D22: 36 x 32 | H22: EVENTOS (CONSIGNA) | I22: {=_xlfn.XLOOKUP($H22,Criterios!$G$6:$G$200,Criterios!I$6:I$200,"")} | J22: {=_xlfn.XLOOKUP($H22,Criterios!$G$6:$G$200,Criterios!J$6:J$200,"")}
A23: B25 STETSON.MX | B23: Ranch & Corral | D23: 36 x 34 | H23: Fixtures & MKT | I23: {=_xlfn.XLOOKUP($H23,Criterios!$G$6:$G$200,Criterios!I$6:I$200,"")} | J23: {=_xlfn.XLOOKUP($H23,Criterios!$G$6:$G$200,Criterios!J$6:J$200,"")}
A24: B25 WB MERCADO LIBRE | B24: Tru Western | D24: 38 x 32 | H24: FULL MELI | I24: {=_xlfn.XLOOKUP($H24,Criterios!$G$6:$G$200,Criterios!I$6:I$200,"")} | J24: {=_xlfn.XLOOKUP($H24,Criterios!$G$6:$G$200,Criterios!J$6:J$200,"")}
A25: B25 WESTERN BROTHERS.MX | B25: Willow Lane | D25: 32 x 32 | H25: G1522 Defectos | I25: {=_xlfn.XLOOKUP($H25,Criterios!$G$6:$G$200,Criterios!I$6:I$200,"")} | J25: {=_xlfn.XLOOKUP($H25,Criterios!$G$6:$G$200,Criterios!J$6:J$200,"")}
A26: CAPSLAB Warehouse | B26: Wrangler | D26: 34 x 32 | H26: G1522 Lost | I26: {=_xlfn.XLOOKUP($H26,Criterios!$G$6:$G$200,Criterios!I$6:I$200,"")} | J26: {=_xlfn.XLOOKUP($H26,Criterios!$G$6:$G$200,Criterios!J$6:J$200,"")}
A27: CL Muestras | H27: G1522 QA Hold | I27: {=_xlfn.XLOOKUP($H27,Criterios!$G$6:$G$200,Criterios!I$6:I$200,"")} | J27: {=_xlfn.XLOOKUP($H27,Criterios!$G$6:$G$200,Criterios!J$6:J$200,"")}
A28: CL POS | H28: GENERAL | I28: {=_xlfn.XLOOKUP($H28,Criterios!$G$6:$G$200,Criterios!I$6:I$200,"")} | J28: {=_xlfn.XLOOKUP($H28,Criterios!$G$6:$G$200,Criterios!J$6:J$200,"")}
A29: CONSIGNA REFLO | H29: HAPPY SOCKS | I29: {=_xlfn.XLOOKUP($H29,Criterios!$G$6:$G$200,Criterios!I$6:I$200,"")} | J29: {=_xlfn.XLOOKUP($H29,Criterios!$G$6:$G$200,Criterios!J$6:J$200,"")}
A30: CONSIGNAS | H30: HS MERCADO LIBRE | I30: {=_xlfn.XLOOKUP($H30,Criterios!$G$6:$G$200,Criterios!I$6:I$200,"")} | J30: {=_xlfn.XLOOKUP($H30,Criterios!$G$6:$G$200,Criterios!J$6:J$200,"")}
A31: DEPARTAMENTAL | H31: KEY ACCOUNTS | I31: {=_xlfn.XLOOKUP($H31,Criterios!$G$6:$G$200,Criterios!I$6:I$200,"")} | J31: {=_xlfn.XLOOKUP($H31,Criterios!$G$6:$G$200,Criterios!J$6:J$200,"")}
A32: ECOMMERCE | H32: LIVERPOOL MKP | I32: {=_xlfn.XLOOKUP($H32,Criterios!$G$6:$G$200,Criterios!I$6:I$200,"")} | J32: {=_xlfn.XLOOKUP($H32,Criterios!$G$6:$G$200,Criterios!J$6:J$200,"")}
A33: ENGLISH REP | H33: Mercado libre | I33: {=_xlfn.XLOOKUP($H33,Criterios!$G$6:$G$200,Criterios!I$6:I$200,"")} | J33: {=_xlfn.XLOOKUP($H33,Criterios!$G$6:$G$200,Criterios!J$6:J$200,"")}
A34: EVENTOS (CONSIGNA) | H34: MUESTRAS & EXPO | I34: {=_xlfn.XLOOKUP($H34,Criterios!$G$6:$G$200,Criterios!I$6:I$200,"")} | J34: {=_xlfn.XLOOKUP($H34,Criterios!$G$6:$G$200,Criterios!J$6:J$200,"")}
A35: Fixtures & MKT | H35: MUESTRAS REFLO | I35: {=_xlfn.XLOOKUP($H35,Criterios!$G$6:$G$200,Criterios!I$6:I$200,"")} | J35: {=_xlfn.XLOOKUP($H35,Criterios!$G$6:$G$200,Criterios!J$6:J$200,"")}
A36: FULL MELI | H36: Nogales Store | I36: {=_xlfn.XLOOKUP($H36,Criterios!$G$6:$G$200,Criterios!I$6:I$200,"")} | J36: {=_xlfn.XLOOKUP($H36,Criterios!$G$6:$G$200,Criterios!J$6:J$200,"")}
A37: G1522 Defectos | H37: Plaza del Sol Store | I37: {=_xlfn.XLOOKUP($H37,Criterios!$G$6:$G$200,Criterios!I$6:I$200,"")} | J37: {=_xlfn.XLOOKUP($H37,Criterios!$G$6:$G$200,Criterios!J$6:J$200,"")}
A38: G1522 Lost | H38: POTRILLOS | I38: {=_xlfn.XLOOKUP($H38,Criterios!$G$6:$G$200,Criterios!I$6:I$200,"")} | J38: {=_xlfn.XLOOKUP($H38,Criterios!$G$6:$G$200,Criterios!J$6:J$200,"")}
... A52: PUNTO DE VENTA | H52: ZONA SUR | I52: {=_xlfn.XLOOKUP($H52,Criterios!$G$6:$G$200,Criterios!I$6:I$200,"")} | J52: {=_xlfn.XLOOKUP($H52,Criterios!$G$6:$G$200,Criterios!J$6:J$200,"")}
A53: Punto de venta HS
A54: REFLO ALMACEN
A55: STETSON AMERICAS
A56: The Hat Club
A57: VENTAS CAMPAÑA
A58: WB FORUM TLAQUEPAQUE
A59: WB OUTLET LERMA
A60: Web
A61: WEB
A62: ZONA NORTE
A63: ZONA POS
A64: ZONA SUR

Sheet Productos
A1: Código de barras | B1: Identificador interno | C1: Marca principal | D1: WB N.º de estilo | E1: WB SKU | F1: WB Talla | G1: WB Talla de EE. UU. | H1: WB Marca | I1: WB Descripcion | J1: WB División | K1: WB Categoría | L1: WB Género | M1: WB Licencia | N1: WB Temporada | O1: WB Ciclo de vida | P1: WB Color | Q1: WB Fit | R1: WB Silueta | S1: WB Composición | T1: WB Descripción larga | U1: WB País de origen | V1: Unidad | W1: SAT Clave de producto | X1: Enlace de imagen | Y1: Precio de compra | Z1: Precio de venta | AA1: Estatus de Validación | AB1: Detalle de Discrepancias | AC1: 🔍 Panel de Duplicados | AD1: Stock Sistema NetSuite | AE1: Ubicaciones con stock (NetSuite) | AF1: Disponible NetSuite | AG1: Origen del registro | AH1: Notas de enriquecimiento / revisión | AI1: ¿Alguna ubicación en negativo? | AJ1: Ubicaciones con existencia negativa | AK1: Fuentes de consulta | AL1: Precio compra vigente | AM1: Precio venta vigente | AN1: 📍 Ubicación en plataformas (Plataforma + Marca) | AO1: Stock Shopify Stetson México | AP1: Stock Shopify Western Brothers | AQ1: Stock Odoo Universal Unique Brands | AR1: Ubicaciones con stock (plataformas)
A2: 5060923782129 | B2: 79244 | C2: REFLO | D2: ADRIAQU | E2: ADRIAQU-M | F2: M | G2: M | H2: REFLO | I2: Playera tipo polo REFLO Adriatic Aqua/ White | J2: Ropa | K2: Playeras | M2: REFLO | P2: Blanco | S2: Poliéster reciclado | T2: Playera tipo polo de golf REFLO modelo Adriatic en color Aqua/ White, confeccionado con materiales reciclados. Estilo ADRIAQU. | V2: PZS | W2: 53101600 | X2: https://i.ibb.co/k1NTDd3/ADRIAQU.jpg | Y2: 26 | Z2: 1899 | AA2: =IF(AND(A2="", B2="", E2=""), "", IF(AB2="", "Válido", IF((LEN(AB2)-LEN(SUBSTITUTE(AB2,"; ","")))/2+1>(LEN(AB2)-LEN(SUBSTITUTE(AB2,"[Aviso]","")))/7, "Con Incidencias", "Válido"))) | AB2: =IF(AND(A2="", B2="", E2=""), "", TEXTJOIN("; ", TRUE, IF(OR(TRIM(A2&"")="", ISNUMBER(SEARCH("FALTA", A2))), "UPC faltante/inválido", ""), IF(AND(A2<>"", IFERROR(_xlfn.XMATCH(A2,$A$2:$A$653,0,1)<>_xlfn.XMATCH(A2,$A$2:$A$653,0,-1),FALSE)), "Código de barras duplicado", ""), IF(AND(E2<>"", COUNTIF($E$2:$E$653, E2)>1), "SKU duplicado", ""), IF(OR(J2="", J2=""), "[Aviso] División no capturada ()", IF(ISNA(MATCH(J2, Criterios!$A$123:$A$126, 0)), "División no válida", "")), IF(OR(K2="", K2=""), "[Aviso] Categoría no capturada ()", IF(ISNA(MATCH(K2, Criterios!$A$81:$A$120, 0)), "Categoría no válida", IF(AND(J2<>"", J2<>"", J2<>VLOOKUP(K2, Criterios!$A$81:$B$120, 2, FALSE)), "División no coincide con Categoría", ""))), IF(OR(L2="", L2=""), "[Aviso] Género no capturado ()", IF(ISNA(MATCH(L2, Criterios!$B$123:$B$127, 0)), "Género no válido", "")), IF(OR(N2="", N2=""), "[Aviso] Temporada no capturada ()", IF(ISNA(MATCH(N2, Criterios!$C$123:$C$128, 0)), "Temporada no válida", "")), IF(OR(O2="", O2=""), "[Aviso] Ciclo de vida no capturado ()", IF(ISNA(MATCH(O2, Criterios!$D$123:$D$124, 0)), "Ciclo de vida no válido", "")))) | AD2: 7 | AE2: REFLO ALMACEN (4) | AF2: 7 | AG2: Nuevo – NetSuite con existencia | AH2: Género no indicado en NetSuite; Composición: poliéster reciclado (validar % en etiqueta); Físico total NetSuite 7 ≠ suma por ubicación 4 | Revisión 29/09/2026: Marca REFLO fuera de lista Criterios; Campos sin respaldo: L, N, O, Q, U; Auditoría NetSuite 30/09/2026: llenado desde NetSuite [Z] | Homologación G1522 06/10/2026: Validador Shopify: WB: precio con IVA no termina en 9 | AI2: No | AK2: G1522ProductosTodosloscamposSandboxResults894.xlsx: fila 43897 [X,Y]; G1522_Extraccion_Articulos_NetSuite_2026-09-30.xlsx: fila 37577 [Z] | AL2: 26
A3: 5060923782136 | B3: 79245 | C3: REFLO | D3: ADRIAQU | E3: ADRIAQU-L | F3: L | G3: L | H3: REFLO | I3: Playera tipo polo REFLO Adriatic Aqua/ White | J3: Ropa | K3: Playeras | M3: REFLO | P3: Blanco | S3: Poliéster reciclado | T3: Playera tipo polo de golf REFLO modelo Adriatic en color Aqua/ White, confeccionado con materiales reciclados. Estilo ADRIAQU. | V3: PZS | W3: 53101600 | X3: https://i.ibb.co/k1NTDd3/ADRIAQU.jpg | Y3: 26 | Z3: 1899 | AA3: =IF(AND(A3="", B3="", E3=""), "", IF(AB3="", "Válido", IF((LEN(AB3)-LEN(SUBSTITUTE(AB3,"; ","")))/2+1>(LEN(AB3)-LEN(SUBSTITUTE(AB3,"[Aviso]","")))/7, "Con Incidencias", "Válido"))) | AB3: =IF(AND(A3="", B3="", E3=""), "", TEXTJOIN("; ", TRUE, IF(OR(TRIM(A3&"")="", ISNUMBER(SEARCH("FALTA", A3))), "UPC faltante/inválido", ""), IF(AND(A3<>"", IFERROR(_xlfn.XMATCH(A3,$A$2:$A$653,0,1)<>_xlfn.XMATCH(A3,$A$2:$A$653,0,-1),FALSE)), "Código de barras duplicado", ""), IF(AND(E3<>"", COUNTIF($E$2:$E$653, E3)>1), "SKU duplicado", ""), IF(OR(J3="", J3=""), "[Aviso] División no capturada ()", IF(ISNA(MATCH(J3, Criterios!$A$123:$A$126, 0)), "División no válida", "")), IF(OR(K3="", K3=""), "[Aviso] Categoría no capturada ()", IF(ISNA(MATCH(K3, Criterios!$A$81:$A$120, 0)), "Categoría no válida", IF(AND(J3<>"", J3<>"", J3<>VLOOKUP(K3, Criterios!$A$81:$B$120, 2, FALSE)), "División no coincide con Categoría", ""))), IF(OR(L3="", L3=""), "[Aviso] Género no capturado ()", IF(ISNA(MATCH(L3, Criterios!$B$123:$B$127, 0)), "Género no válido", "")), IF(OR(N3="", N3=""), "[Aviso] Temporada no capturada ()", IF(ISNA(MATCH(N3, Criterios!$C$123:$C$128, 0)), "Temporada no válida", "")), IF(OR(O3="", O3=""), "[Aviso] Ciclo de vida no capturado ()", IF(ISNA(MATCH(O3, Criterios!$D$123:$D$124, 0)), "Ciclo de vida no válido", "")))) | AD3: 10 | AE3: MUESTRAS REFLO (1); REFLO ALMACEN (5) | AF3: 9 | AG3: Nuevo – NetSuite con existencia | AH3: Género no indicado en NetSuite; Composición: poliéster reciclado (validar % en etiqueta); Físico total NetSuite 10 ≠ suma por ubicación 6 | Revisión 29/09/2026: Marca REFLO fuera de lista Criterios; Campos sin respaldo: L, N, O, Q, U; Auditoría NetSuite 30/09/2026: llenado desde NetSuite [Z] | Homologación G1522 06/10/2026: Validador Shopify: WB: precio con IVA no termina en 9 | AI3: No | AK3: G1522ProductosTodosloscamposSandboxResults894.xlsx: fila 43898 [X,Y]; G1522_Extraccion_Articulos_NetSuite_2026-09-30.xlsx: fila 37578 [Z] | AL3: 26
A4: 5060923782150 | B4: 79246 | C4: REFLO | D4: ADRIAQU | E4: ADRIAQU-XXL | F4: XXL | G4: XXL | H4: REFLO | I4: Playera tipo polo REFLO Adriatic Aqua/ White | J4: Ropa | K4: Playeras | M4: REFLO | P4: Blanco | S4: Poliéster reciclado | T4: Playera tipo polo de golf REFLO modelo Adriatic en color Aqua/ White, confeccionado con materiales reciclados. Estilo ADRIAQU. | V4: PZS | W4: 53101600 | X4: https://i.ibb.co/k1NTDd3/ADRIAQU.jpg | Y4: 26 | Z4: 1899 | AA4: =IF(AND(A4="", B4="", E4=""), "", IF(AB4="", "Válido", IF((LEN(AB4)-LEN(SUBSTITUTE(AB4,"; ","")))/2+1>(LEN(AB4)-LEN(SUBSTITUTE(AB4,"[Aviso]","")))/7, "Con Incidencias", "Válido"))) | AB4: =IF(AND(A4="", B4="", E4=""), "", TEXTJOIN("; ", TRUE, IF(OR(TRIM(A4&"")="", ISNUMBER(SEARCH("FALTA", A4))), "UPC faltante/inválido", ""), IF(AND(A4<>"", IFERROR(_xlfn.XMATCH(A4,$A$2:$A$653,0,1)<>_xlfn.XMATCH(A4,$A$2:$A$653,0,-1),FALSE)), "Código de barras duplicado", ""), IF(AND(E4<>"", COUNTIF($E$2:$E$653, E4)>1), "SKU duplicado", ""), IF(OR(J4="", J4=""), "[Aviso] División no capturada ()", IF(ISNA(MATCH(J4, Criterios!$A$123:$A$126, 0)), "División no válida", "")), IF(OR(K4="", K4=""), "[Aviso] Categoría no capturada ()", IF(ISNA(MATCH(K4, Criterios!$A$81:$A$120, 0)), "Categoría no válida", IF(AND(J4<>"", J4<>"", J4<>VLOOKUP(K4, Criterios!$A$81:$B$120, 2, FALSE)), "División no coincide con Categoría", ""))), IF(OR(L4="", L4=""), "[Aviso] Género no capturado ()", IF(ISNA(MATCH(L4, Criterios!$B$123:$B$127, 0)), "Género no válido", "")), IF(OR(N4="", N4=""), "[Aviso] Temporada no capturada ()", IF(ISNA(MATCH(N4, Criterios!$C$123:$C$128, 0)), "Temporada no válida", "")), IF(OR(O4="", O4=""), "[Aviso] Ciclo de vida no capturado ()", IF(ISNA(MATCH(O4, Criterios!$D$123:$D$124, 0)), "Ciclo de vida no válido", "")))) | AD4: 2 | AE4: REFLO ALMACEN (1) | AF4: 2 | AG4: Nuevo – NetSuite con existencia | AH4: Género no indicado en NetSuite; Composición: poliéster reciclado (validar % en etiqueta); Físico total NetSuite 2 ≠ suma por ubicación 1 | Revisión 29/09/2026: Marca REFLO fuera de lista Criterios; Campos sin respaldo: L, N, O, Q, U; Auditoría NetSuite 30/09/2026: llenado desde NetSuite [Z] | Homologación G1522 06/10/2026: Validador Shopify: WB: precio con IVA no termina en 9 | AI4: No | AK4: G1522ProductosTodosloscamposSandboxResults894.xlsx: fila 43899 [X,Y]; G1522_Extraccion_Articulos_NetSuite_2026-09-30.xlsx: fila 37579 [Z] | AL4: 26
A5: 5060923782112 | B5: 84419 | C5: REFLO | D5: ADRIAQU | E5: ADRIAQU-S | F5: S | G5: S | H5: REFLO | I5: Playera tipo polo REFLO Adriatic Aqua/White | J5: Ropa | K5: Playeras | M5: REFLO | P5: Blanco | S5: Poliéster reciclado | T5: Playera tipo polo de golf REFLO modelo Adriatic en color Aqua/White, confeccionado con materiales reciclados. Estilo ADRIAQU. | V5: PZS | W5: 53101600 | X5: https://i.ibb.co/k1NTDd3/ADRIAQU.jpg | Y5: 26 | Z5: 1899 | AA5: =IF(AND(A5="", B5="", E5=""), "", IF(AB5="", "Válido", IF((LEN(AB5)-LEN(SUBSTITUTE(AB5,"; ","")))/2+1>(LEN(AB5)-LEN(SUBSTITUTE(AB5,"[Aviso]","")))/7, "Con Incidencias", "Válido"))) | AB5: =IF(AND(A5="", B5="", E5=""), "", TEXTJOIN("; ", TRUE, IF(OR(TRIM(A5&"")="", ISNUMBER(SEARCH("FALTA", A5))), "UPC faltante/inválido", ""), IF(AND(A5<>"", IFERROR(_xlfn.XMATCH(A5,$A$2:$A$653,0,1)<>_xlfn.XMATCH(A5,$A$2:$A$653,0,-1),FALSE)), "Código de barras duplicado", ""), IF(AND(E5<>"", COUNTIF($E$2:$E$653, E5)>1), "SKU duplicado", ""), IF(OR(J5="", J5=""), "[Aviso] División no capturada ()", IF(ISNA(MATCH(J5, Criterios!$A$123:$A$126, 0)), "División no válida", "")), IF(OR(K5="", K5=""), "[Aviso] Categoría no capturada ()", IF(ISNA(MATCH(K5, Criterios!$A$81:$A$120, 0)), "Categoría no válida", IF(AND(J5<>"", J5<>"", J5<>VLOOKUP(K5, Criterios!$A$81:$B$120, 2, FALSE)), "División no coincide con Categoría", ""))), IF(OR(L5="", L5=""), "[Aviso] Género no capturado ()", IF(ISNA(MATCH(L5, Criterios!$B$123:$B$127, 0)), "Género no válido", "")), IF(OR(N5="", N5=""), "[Aviso] Temporada no capturada ()", IF(ISNA(MATCH(N5, Criterios!$C$123:$C$128, 0)), "Temporada no válida", "")), IF(OR(O5="", O5=""), "[Aviso] Ciclo de vida no capturado ()", IF(ISNA(MATCH(O5, Criterios!$D$123:$D$124, 0)), "Ciclo de vida no válido", "")))) | AD5: 8 | AE5: REFLO ALMACEN (2); CONSIGNA REFLO (2) | AF5: 8 | AG5: Nuevo – NetSuite con existencia | AH5: Género no indicado en NetSuite; Composición: poliéster reciclado (validar % en etiqueta); Físico total NetSuite 8 ≠ suma por ubicación 4 | Revisión 29/09/2026: Marca REFLO fuera de lista Criterios; Campos sin respaldo: L, N, O, Q, U; Auditoría NetSuite 30/09/2026: llenado desde NetSuite [Z] | Homologación G1522 06/10/2026: Validador Shopify: WB: precio con IVA no termina en 9 | AI5: No | AK5: G1522ProductosTodosloscamposSandboxResults894.xlsx: fila 43901 [X,Y]; G1522_Extraccion_Articulos_NetSuite_2026-09-30.xlsx: fila 39588 [Z] | AL5: 26
A6: 5060923782068 | B6: 79247 | C6: REFLO | D6: ADRICLO | E6: ADRICLO-M | F6: M | G6: M | H6: REFLO | I6: Playera tipo polo REFLO Adriatic Cloud/ Black | J6: Ropa | K6: Playeras | M6: REFLO | P6: Negro | S6: Poliéster reciclado | T6: Playera tipo polo de golf REFLO modelo Adriatic en color Cloud/ Black, confeccionado con materiales reciclados. Estilo ADRICLO. | V6: PZS | W6: 53101600 | X6: https://i.ibb.co/VSDV4Mp/ADRICLO.jpg | Y6: 26 | Z6: 1899 | AA6: =IF(AND(A6="", B6="", E6=""), "", IF(AB6="", "Válido", IF((LEN(AB6)-LEN(SUBSTITUTE(AB6,"; ","")))/2+1>(LEN(AB6)-LEN(SUBSTITUTE(AB6,"[Aviso]","")))/7, "Con Incidencias", "Válido"))) | AB6: =IF(AND(A6="", B6="", E6=""), "", TEXTJOIN("; ", TRUE, IF(OR(TRIM(A6&"")="", ISNUMBER(SEARCH("FALTA", A6))), "UPC faltante/inválido", ""), IF(AND(A6<>"", IFERROR(_xlfn.XMATCH(A6,$A$2:$A$653,0,1)<>_xlfn.XMATCH(A6,$A$2:$A$653,0,-1),FALSE)), "Código de barras duplicado", ""), IF(AND(E6<>"", COUNTIF($E$2:$E$653, E6)>1), "SKU duplicado", ""), IF(OR(J6="", J6=""), "[Aviso] División no capturada ()", IF(ISNA(MATCH(J6, Criterios!$A$123:$A$126, 0)), "División no válida", "")), IF(OR(K6="", K6=""), "[Aviso] Categoría no capturada ()", IF(ISNA(MATCH(K6, Criterios!$A$81:$A$120, 0)), "Categoría no válida", IF(AND(J6<>"", J6<>"", J6<>VLOOKUP(K6, Criterios!$A$81:$B$120, 2, FALSE)), "División no coincide con Categoría", ""))), IF(OR(L6="", L6=""), "[Aviso] Género no capturado ()", IF(ISNA(MATCH(L6, Criterios!$B$123:$B$127, 0)), "Género no válido", "")), IF(OR(N6="", N6=""), "[Aviso] Temporada no capturada ()", IF(ISNA(MATCH(N6, Criterios!$C$123:$C$128, 0)), "Temporada no válida", "")), IF(OR(O6="", O6=""), "[Aviso] Ciclo de vida no capturado ()", IF(ISNA(MATCH(O6, Criterios!$D$123:$D$124, 0)), "Ciclo de vida no válido", "")))) | AD6: 8 | AE6: REFLO ALMACEN (6) | AF6: 10 | AG6: Nuevo – NetSuite con existencia | AH6: Género no indicado en NetSuite; Composición: poliéster reciclado (validar % en etiqueta); Físico total NetSuite 8 ≠ suma por ubicación 4 | Revisión 29/09/2026: Marca REFLO fuera de lista Criterios; Campos sin respaldo: L, N, O, Q, U; Auditoría NetSuite 30/09/2026: llenado desde NetSuite [Z] | Homologación G1522 06/10/2026: Validador Shopify: WB: precio con IVA no termina en 9 | AI6: Sí | AJ6: CONSIGNA REFLO (-2) | AK6: G1522ProductosTodosloscamposSandboxResults894.xlsx: fila 43903 [X,Y]; G1522_Extraccion_Articulos_NetSuite_2026-09-30.xlsx: fila 37580 [Z] | AL6: 26
A7: 5060923782075 | B7: 79248 | C7: REFLO | D7: ADRICLO | E7: ADRICLO-L | F7: L | G7: L | H7: REFLO | I7: Playera tipo polo REFLO Adriatic Cloud/ Black | J7: Ropa | K7: Playeras | M7: REFLO | P7: Negro | S7: Poliéster reciclado | T7: Playera tipo polo de golf REFLO modelo Adriatic en color Cloud/ Black, confeccionado con materiales reciclados. Estilo ADRICLO. | V7: PZS | W7: 53101600 | X7: https://i.ibb.co/VSDV4Mp/ADRICLO.jpg | Y7: 26 | Z7: 1899 | AA7: =IF(AND(A7="", B7="", E7=""), "", IF(AB7="", "Válido", IF((LEN(AB7)-LEN(SUBSTITUTE(AB7,"; ","")))/2+1>(LEN(AB7)-LEN(SUBSTITUTE(AB7,"[Aviso]","")))/7, "Con Incidencias", "Válido"))) | AB7: =IF(AND(A7="", B7="", E7=""), "", TEXTJOIN("; ", TRUE, IF(OR(TRIM(A7&"")="", ISNUMBER(SEARCH("FALTA", A7))), "UPC faltante/inválido", ""), IF(AND(A7<>"", IFERROR(_xlfn.XMATCH(A7,$A$2:$A$653,0,1)<>_xlfn.XMATCH(A7,$A$2:$A$653,0,-1),FALSE)), "Código de barras duplicado", ""), IF(AND(E7<>"", COUNTIF($E$2:$E$653, E7)>1), "SKU duplicado", ""), IF(OR(J7="", J7=""), "[Aviso] División no capturada ()", IF(ISNA(MATCH(J7, Criterios!$A$123:$A$126, 0)), "División no válida", "")), IF(OR(K7="", K7=""), "[Aviso] Categoría no capturada ()", IF(ISNA(MATCH(K7, Criterios!$A$81:$A$120, 0)), "Categoría no válida", IF(AND(J7<>"", J7<>"", J7<>VLOOKUP(K7, Criterios!$A$81:$B$120, 2, FALSE)), "División no coincide con Categoría", ""))), IF(OR(L7="", L7=""), "[Aviso] Género no capturado ()", IF(ISNA(MATCH(L7, Criterios!$B$123:$B$127, 0)), "Género no válido", "")), IF(OR(N7="", N7=""), "[Aviso] Temporada no capturada ()", IF(ISNA(MATCH(N7, Criterios!$C$123:$C$128, 0)), "Temporada no válida", "")), IF(OR(O7="", O7=""), "[Aviso] Ciclo de vida no capturado ()", IF(ISNA(MATCH(O7, Criterios!$D$123:$D$124, 0)), "Ciclo de vida no válido", "")))) | AD7: 10 | AE7: MUESTRAS REFLO (1); REFLO ALMACEN (7) | AF7: 11 | AG7: Nuevo – NetSuite con existencia | AH7: Género no indicado en NetSuite; Composición: poliéster reciclado (validar % en etiqueta); Físico total NetSuite 10 ≠ suma por ubicación 6 | Revisión 29/09/2026: Marca REFLO fuera de lista Criterios; Campos sin respaldo: L, N, O, Q, U; Auditoría NetSuite 30/09/2026: llenado desde NetSuite [Z] | Homologación G1522 06/10/2026: Validador Shopify: WB: precio con IVA no termina en 9 | AI7: Sí | AJ7: CONSIGNA REFLO (-2) | AK7: G1522ProductosTodosloscamposSandboxResults894.xlsx: fila 43904 [X,Y]; G1522_Extraccion_Articulos_NetSuite_2026-09-30.xlsx: fila 37581 [Z] | AL7: 26
A8: 5060923782082 | B8: 79249 | C8: REFLO | D8: ADRICLO | E8: ADRICLO-XL | F8: XL | G8: XL | H8: REFLO | I8: Playera tipo polo REFLO Adriatic Cloud/ Black | J8: Ropa | K8: Playeras | M8: REFLO | P8: Negro | S8: Poliéster reciclado | T8: Playera tipo polo de golf REFLO modelo Adriatic en color Cloud/ Black, confeccionado con materiales reciclados. Estilo ADRICLO. | V8: PZS | W8: 53101600 | X8: https://i.ibb.co/VSDV4Mp/ADRICLO.jpg | Y8: 26 | Z8: 1899 | AA8: =IF(AND(A8="", B8="", E8=""), "", IF(AB8="", "Válido", IF((LEN(AB8)-LEN(SUBSTITUTE(AB8,"; ","")))/2+1>(LEN(AB8)-LEN(SUBSTITUTE(AB8,"[Aviso]","")))/7, "Con Incidencias", "Válido"))) | AB8: =IF(AND(A8="", B8="", E8=""), "", TEXTJOIN("; ", TRUE, IF(OR(TRIM(A8&"")="", ISNUMBER(SEARCH("FALTA", A8))), "UPC faltante/inválido", ""), IF(AND(A8<>"", IFERROR(_xlfn.XMATCH(A8,$A$2:$A$653,0,1)<>_xlfn.XMATCH(A8,$A$2:$A$653,0,-1),FALSE)), "Código de barras duplicado", ""), IF(AND(E8<>"", COUNTIF($E$2:$E$653, E8)>1), "SKU duplicado", ""), IF(OR(J8="", J8=""), "[Aviso] División no capturada ()", IF(ISNA(MATCH(J8, Criterios!$A$123:$A$126, 0)), "División no válida", "")), IF(OR(K8="", K8=""), "[Aviso] Categoría no capturada ()", IF(ISNA(MATCH(K8, Criterios!$A$81:$A$120, 0)), "Categoría no válida", IF(AND(J8<>"", J8<>"", J8<>VLOOKUP(K8, Criterios!$A$81:$B$120, 2, FALSE)), "División no coincide con Categoría", ""))), IF(OR(L8="", L8=""), "[Aviso] Género no capturado ()", IF(ISNA(MATCH(L8, Criterios!$B$123:$B$127, 0)), "Género no válido", "")), IF(OR(N8="", N8=""), "[Aviso] Temporada no capturada ()", IF(ISNA(MATCH(N8, Criterios!$C$123:$C$128, 0)), "Temporada no válida", "")), IF(OR(O8="", O8=""), "[Aviso] Ciclo de vida no capturado ()", IF(ISNA(MATCH(O8, Criterios!$D$123:$D$124, 0)), "Ciclo de vida no válido", "")))) | AD8: 13 | AE8: REFLO ALMACEN (8) | AF8: 14 | AG8: Nuevo – NetSuite con existencia | AH8: Género no indicado en NetSuite; Composición: poliéster reciclado (validar % en etiqueta); Físico total NetSuite 13 ≠ suma por ubicación 7 | Revisión 29/09/2026: Marca REFLO fuera de lista Criterios; Campos sin respaldo: L, N, O, Q, U; Auditoría NetSuite 30/09/2026: llenado desde NetSuite [Z] | Homologación G1522 06/10/2026: Validador Shopify: WB: precio con IVA no termina en 9 | AI8: Sí | AJ8: CONSIGNA REFLO (-1) | AK8: G1522ProductosTodosloscamposSandboxResults894.xlsx: fila 43905 [X,Y]; G1522_Extraccion_Articulos_NetSuite_2026-09-30.xlsx: fila 37582 [Z] | AL8: 26
A9: 5060923782099 | B9: 79250 | C9: REFLO | D9: ADRICLO | E9: ADRICLO-XXL | F9: XXL | G9: XXL | H9: REFLO | I9: Playera tipo polo REFLO Adriatic Cloud/ Black | J9: Ropa | K9: Playeras | M9: REFLO | P9: Negro | S9: Poliéster reciclado | T9: Playera tipo polo de golf REFLO modelo Adriatic en color Cloud/ Black, confeccionado con materiales reciclados. Estilo ADRICLO. | V9: PZS | W9: 53101600 | X9: https://i.ibb.co/VSDV4Mp/ADRICLO.jpg | Y9: 26 | Z9: 1899 | AA9: =IF(AND(A9="", B9="", E9=""), "", IF(AB9="", "Válido", IF((LEN(AB9)-LEN(SUBSTITUTE(AB9,"; ","")))/2+1>(LEN(AB9)-LEN(SUBSTITUTE(AB9,"[Aviso]","")))/7, "Con Incidencias", "Válido"))) | AB9: =IF(AND(A9="", B9="", E9=""), "", TEXTJOIN("; ", TRUE, IF(OR(TRIM(A9&"")="", ISNUMBER(SEARCH("FALTA", A9))), "UPC faltante/inválido", ""), IF(AND(A9<>"", IFERROR(_xlfn.XMATCH(A9,$A$2:$A$653,0,1)<>_xlfn.XMATCH(A9,$A$2:$A$653,0,-1),FALSE)), "Código de barras duplicado", ""), IF(AND(E9<>"", COUNTIF($E$2:$E$653, E9)>1), "SKU duplicado", ""), IF(OR(J9="", J9=""), "[Aviso] División no capturada ()", IF(ISNA(MATCH(J9, Criterios!$A$123:$A$126, 0)), "División no válida", "")), IF(OR(K9="", K9=""), "[Aviso] Categoría no capturada ()", IF(ISNA(MATCH(K9, Criterios!$A$81:$A$120, 0)), "Categoría no válida", IF(AND(J9<>"", J9<>"", J9<>VLOOKUP(K9, Criterios!$A$81:$B$120, 2, FALSE)), "División no coincide con Categoría", ""))), IF(OR(L9="", L9=""), "[Aviso] Género no capturado ()", IF(ISNA(MATCH(L9, Criterios!$B$123:$B$127, 0)), "Género no válido", "")), IF(OR(N9="", N9=""), "[Aviso] Temporada no capturada ()", IF(ISNA(MATCH(N9, Criterios!$C$123:$C$128, 0)), "Temporada no válida", "")), IF(OR(O9="", O9=""), "[Aviso] Ciclo de vida no capturado ()", IF(ISNA(MATCH(O9, Criterios!$D$123:$D$124, 0)), "Ciclo de vida no válido", "")))) | AD9: 8 | AE9: REFLO ALMACEN (5) | AF9: 9 | AG9: Nuevo – NetSuite con existencia | AH9: Género no indicado en NetSuite; Composición: poliéster reciclado (validar % en etiqueta); Físico total NetSuite 8 ≠ suma por ubicación 4 | Revisión 29/09/2026: Marca REFLO fuera de lista Criterios; Campos sin respaldo: L, N, O, Q, U; Auditoría NetSuite 30/09/2026: llenado desde NetSuite [Z] | Homologación G1522 06/10/2026: Validador Shopify: WB: precio con IVA no termina en 9 | AI9: Sí | AJ9: CONSIGNA REFLO (-1) | AK9: G1522ProductosTodosloscamposSandboxResults894.xlsx: fila 43906 [X,Y]; G1522_Extraccion_Articulos_NetSuite_2026-09-30.xlsx: fila 37583 [Z] | AL9: 26
A10: 5060923782051 | B10: 84420 | C10: REFLO | D10: ADRICLO | E10: ADRICLO-S | F10: S | G10: S | H10: REFLO | I10: Playera tipo polo REFLO Adriatic Cloud/Black | J10: Ropa | K10: Playeras | M10: REFLO | P10: Negro | S10: Poliéster reciclado | T10: Playera tipo polo de golf REFLO modelo Adriatic en color Cloud/Black, confeccionado con materiales reciclados. Estilo ADRICLO. | V10: PZS | W10: 53101600 | X10: https://i.ibb.co/VSDV4Mp/ADRICLO.jpg | Y10: 26 | Z10: 1899 | AA10: =IF(AND(A10="", B10="", E10=""), "", IF(AB10="", "Válido", IF((LEN(AB10)-LEN(SUBSTITUTE(AB10,"; ","")))/2+1>(LEN(AB10)-LEN(SUBSTITUTE(AB10,"[Aviso]","")))/7, "Con Incidencias", "Válido"))) | AB10: =IF(AND(A10="", B10="", E10=""), "", TEXTJOIN("; ", TRUE, IF(OR(TRIM(A10&"")="", ISNUMBER(SEARCH("FALTA", A10))), "UPC faltante/inválido", ""), IF(AND(A10<>"", IFERROR(_xlfn.XMATCH(A10,$A$2:$A$653,0,1)<>_xlfn.XMATCH(A10,$A$2:$A$653,0,-1),FALSE)), "Código de barras duplicado", ""), IF(AND(E10<>"", COUNTIF($E$2:$E$653, E10)>1), "SKU duplicado", ""), IF(OR(J10="", J10=""), "[Aviso] División no capturada ()", IF(ISNA(MATCH(J10, Criterios!$A$123:$A$126, 0)), "División no válida", "")), IF(OR(K10="", K10=""), "[Aviso] Categoría no capturada ()", IF(ISNA(MATCH(K10, Criterios!$A$81:$A$120, 0)), "Categoría no válida", IF(AND(J10<>"", J10<>"", J10<>VLOOKUP(K10, Criterios!$A$81:$B$120, 2, FALSE)), "División no coincide con Categoría", ""))), IF(OR(L10="", L10=""), "[Aviso] Género no capturado ()", IF(ISNA(MATCH(L10, Criterios!$B$123:$B$127, 0)), "Género no válido", "")), IF(OR(N10="", N10=""), "[Aviso] Temporada no capturada ()", IF(ISNA(MATCH(N10, Criterios!$C$123:$C$128, 0)), "Temporada no válida", "")), IF(OR(O10="", O10=""), "[Aviso] Ciclo de vida no capturado ()", IF(ISNA(MATCH(O10, Criterios!$D$123:$D$124, 0)), "Ciclo de vida no válido", "")))) | AD10: 8 | AE10: REFLO ALMACEN (4) | AF10: 8 | AG10: Nuevo – NetSuite con existencia | AH10: Género no indicado en NetSuite; Composición: poliéster reciclado (validar % en etiqueta); Físico total NetSuite 8 ≠ suma por ubicación 4 | Revisión 29/09/2026: Marca REFLO fuera de lista Criterios; Campos sin respaldo: L, N, O, Q, U; Auditoría NetSuite 30/09/2026: llenado desde NetSuite [Z] | Homologación G1522 06/10/2026: Validador Shopify: WB: precio con IVA no termina en 9 | AI10: No | AK10: G1522ProductosTodosloscamposSandboxResults894.xlsx: fila 43908 [X,Y]; G1522_Extraccion_Articulos_NetSuite_2026-09-30.xlsx: fila 39589 [Z] | AL10: 26
A11: 5060923782006 | B11: 79251 | C11: REFLO | D11: ADRIOXY | E11: ADRIOXY-M | F11: M | G11: M | H11: REFLO | I11: Playera tipo polo REFLO Adriatic Oxy/ Navy | J11: Ropa | K11: Playeras | M11: REFLO | P11: Azul | S11: Poliéster reciclado | T11: Playera tipo polo de golf REFLO modelo Adriatic en color Oxy/ Navy, confeccionado con materiales reciclados. Estilo ADRIOXY. | V11: PZS | W11: 53101600 | X11: https://i.ibb.co/NCvyXJJ/ADRIOXY.jpg | Y11: 26 | Z11: 1899 | AA11: =IF(AND(A11="", B11="", E11=""), "", IF(AB11="", "Válido", IF((LEN(AB11)-LEN(SUBSTITUTE(AB11,"; ","")))/2+1>(LEN(AB11)-LEN(SUBSTITUTE(AB11,"[Aviso]","")))/7, "Con Incidencias", "Válido"))) | AB11: =IF(AND(A11="", B11="", E11=""), "", TEXTJOIN("; ", TRUE, IF(OR(TRIM(A11&"")="", ISNUMBER(SEARCH("FALTA", A11))), "UPC faltante/inválido", ""), IF(AND(A11<>"", IFERROR(_xlfn.XMATCH(A11,$A$2:$A$653,0,1)<>_xlfn.XMATCH(A11,$A$2:$A$653,0,-1),FALSE)), "Código de barras duplicado", ""), IF(AND(E11<>"", COUNTIF($E$2:$E$653, E11)>1), "SKU duplicado", ""), IF(OR(J11="", J11=""), "[Aviso] División no capturada ()", IF(ISNA(MATCH(J11, Criterios!$A$123:$A$126, 0)), "División no válida", "")), IF(OR(K11="", K11=""), "[Aviso] Categoría no capturada ()", IF(ISNA(MATCH(K11, Criterios!$A$81:$A$120, 0)), "Categoría no válida", IF(AND(J11<>"", J11<>"", J11<>VLOOKUP(K11, Criterios!$A$81:$B$120, 2, FALSE)), "División no coincide con Categoría", ""))), IF(OR(L11="", L11=""), "[Aviso] Género no capturado ()", IF(ISNA(MATCH(L11, Criterios!$B$123:$B$127, 0)), "Género no válido", "")), IF(OR(N11="", N11=""), "[Aviso] Temporada no capturada ()", IF(ISNA(MATCH(N11, Criterios!$C$123:$C$128, 0)), "Temporada no válida", "")), IF(OR(O11="", O11=""), "[Aviso] Ciclo de vida no capturado ()", IF(ISNA(MATCH(O11, Criterios!$D$123:$D$124, 0)), "Ciclo de vida no válido", "")))) | AD11: 3 | AE11: REFLO ALMACEN (1); CONSIGNA REFLO (1) | AF11: 3 | AG11: Nuevo – NetSuite con existencia | AH11: Género no indicado en NetSuite; Composición: poliéster reciclado (validar % en etiqueta); Físico total NetSuite 3 ≠ suma por ubicación 2 | Revisión 29/09/2026: Marca REFLO fuera de lista Criterios; Campos sin respaldo: L, N, O, Q, U; Auditoría NetSuite 30/09/2026: llenado desde NetSuite [Z] | Homologación G1522 06/10/2026: Validador Shopify: WB: precio con IVA no termina en 9 | AI11: No | AK11: G1522ProductosTodosloscamposSandboxResults894.xlsx: fila 43910 [X,Y]; G1522_Extraccion_Articulos_NetSuite_2026-09-30.xlsx: fila 37584 [Z] | AL11: 26
A12: 5060923782013 | B12: 79252 | C12: REFLO | D12: ADRIOXY | E12: ADRIOXY-L | F12: L | G12: L | H12: REFLO | I12: Playera tipo polo REFLO Adriatic Oxy/ Navy | J12: Ropa | K12: Playeras | M12: REFLO | P12: Azul | S12: Poliéster reciclado | T12: Playera tipo polo de golf REFLO modelo Adriatic en color Oxy/ Navy, confeccionado con materiales reciclados. Estilo ADRIOXY. | V12: PZS | W12: 53101600 | X12: https://i.ibb.co/NCvyXJJ/ADRIOXY.jpg | Y12: 26 | Z12: 1899 | AA12: =IF(AND(A12="", B12="", E12=""), "", IF(AB12="", "Válido", IF((LEN(AB12)-LEN(SUBSTITUTE(AB12,"; ","")))/2+1>(LEN(AB12)-LEN(SUBSTITUTE(AB12,"[Aviso]","")))/7, "Con Incidencias", "Válido"))) | AB12: =IF(AND(A12="", B12="", E12=""), "", TEXTJOIN("; ", TRUE, IF(OR(TRIM(A12&"")="", ISNUMBER(SEARCH("FALTA", A12))), "UPC faltante/inválido", ""), IF(AND(A12<>"", IFERROR(_xlfn.XMATCH(A12,$A$2:$A$653,0,1)<>_xlfn.XMATCH(A12,$A$2:$A$653,0,-1),FALSE)), "Código de barras duplicado", ""), IF(AND(E12<>"", COUNTIF($E$2:$E$653, E12)>1), "SKU duplicado", ""), IF(OR(J12="", J12=""), "[Aviso] División no capturada ()", IF(ISNA(MATCH(J12, Criterios!$A$123:$A$126, 0)), "División no válida", "")), IF(OR(K12="", K12=""), "[Aviso] Categoría no capturada ()", IF(ISNA(MATCH(K12, Criterios!$A$81:$A$120, 0)), "Categoría no válida", IF(AND(J12<>"", J12<>"", J12<>VLOOKUP(K12, Criterios!$A$81:$B$120, 2, FALSE)), "División no coincide con Categoría", ""))), IF(OR(L12="", L12=""), "[Aviso] Género no capturado ()", IF(ISNA(MATCH(L12, Criterios!$B$123:$B$127, 0)), "Género no válido", "")), IF(OR(N12="", N12=""), "[Aviso] Temporada no capturada ()", IF(ISNA(MATCH(N12, Criterios!$C$123:$C$128, 0)), "Temporada no válida", "")), IF(OR(O12="", O12=""), "[Aviso] Ciclo de vida no capturado ()", IF(ISNA(MATCH(O12, Criterios!$D$123:$D$124, 0)), "Ciclo de vida no válido", "")))) | AD12: 9 | AE12: CONSIGNA REFLO (1); MUESTRAS REFLO (1); REFLO ALMACEN (3) | AF12: 8 | AG12: Nuevo – NetSuite con existencia | AH12: Género no indicado en NetSuite; Composición: poliéster reciclado (validar % en etiqueta); Físico total NetSuite 9 ≠ suma por ubicación 5 | Revisión 29/09/2026: Marca REFLO fuera de lista Criterios; Campos sin respaldo: L, N, O, Q, U; Auditoría NetSuite 30/09/2026: llenado desde NetSuite [Z] | Homologación G1522 06/10/2026: Validador Shopify: WB: precio con IVA no termina en 9 | AI12: No | AK12: G1522ProductosTodosloscamposSandboxResults894.xlsx: fila 43911 [X,Y]; G1522_Extraccion_Articulos_NetSuite_2026-09-30.xlsx: fila 37585 [Z] | AL12: 26
A13: 5060923782020 | B13: 79253 | C13: REFLO | D13: ADRIOXY | E13: ADRIOXY-XL | F13: XL | G13: XL | H13: REFLO | I13: Playera tipo polo REFLO Adriatic Oxy/ Navy | J13: Ropa | K13: Playeras | M13: REFLO | P13: Azul | S13: Poliéster reciclado | T13: Playera tipo polo de golf REFLO modelo Adriatic en color Oxy/ Navy, confeccionado con materiales reciclados. Estilo ADRIOXY. | V13: PZS | W13: 53101600 | X13: https://i.ibb.co/NCvyXJJ/ADRIOXY.jpg | Y13: 26 | Z13: 1899 | AA13: =IF(AND(A13="", B13="", E13=""), "", IF(AB13="", "Válido", IF((LEN(AB13)-LEN(SUBSTITUTE(AB13,"; ","")))/2+1>(LEN(AB13)-LEN(SUBSTITUTE(AB13,"[Aviso]","")))/7, "Con Incidencias", "Válido"))) | AB13: =IF(AND(A13="", B13="", E13=""), "", TEXTJOIN("; ", TRUE, IF(OR(TRIM(A13&"")="", ISNUMBER(SEARCH("FALTA", A13))), "UPC faltante/inválido", ""), IF(AND(A13<>"", IFERROR(_xlfn.XMATCH(A13,$A$2:$A$653,0,1)<>_xlfn.XMATCH(A13,$A$2:$A$653,0,-1),FALSE)), "Código de barras duplicado", ""), IF(AND(E13<>"", COUNTIF($E$2:$E$653, E13)>1), "SKU duplicado", ""), IF(OR(J13="", J13=""), "[Aviso] División no capturada ()", IF(ISNA(MATCH(J13, Criterios!$A$123:$A$126, 0)), "División no válida", "")), IF(OR(K13="", K13=""), "[Aviso] Categoría no capturada ()", IF(ISNA(MATCH(K13, Criterios!$A$81:$A$120, 0)), "Categoría no válida", IF(AND(J13<>"", J13<>"", J13<>VLOOKUP(K13, Criterios!$A$81:$B$120, 2, FALSE)), "División no coincide con Categoría", ""))), IF(OR(L13="", L13=""), "[Aviso] Género no capturado ()", IF(ISNA(MATCH(L13, Criterios!$B$123:$B$127, 0)), "Género no válido", "")), IF(OR(N13="", N13=""), "[Aviso] Temporada no capturada ()", IF(ISNA(MATCH(N13, Criterios!$C$123:$C$128, 0)), "Temporada no válida", "")), IF(OR(O13="", O13=""), "[Aviso] Ciclo de vida no capturado ()", IF(ISNA(MATCH(O13, Criterios!$D$123:$D$124, 0)), "Ciclo de vida no válido", "")))) | AD13: 12 | AE13: CONSIGNA REFLO (1); REFLO ALMACEN (5) | AF13: 12 | AG13: Nuevo – NetSuite con existencia | AH13: Género no indicado en NetSuite; Composición: poliéster reciclado (validar % en etiqueta); Físico total NetSuite 12 ≠ suma por ubicación 6 | Revisión 29/09/2026: Marca REFLO fuera de lista Criterios; Campos sin respaldo: L, N, O, Q, U; Auditoría NetSuite 30/09/2026: llenado desde NetSuite [Z] | Homologación G1522 06/10/2026: Validador Shopify: WB: precio con IVA no termina en 9 | AI13: No | AK13: G1522ProductosTodosloscamposSandboxResults894.xlsx: fila 43912 [X,Y]; G1522_Extraccion_Articulos_NetSuite_2026-09-30.xlsx: fila 37586 [Z] | AL13: 26
A14: 5060923782037 | B14: 79254 | C14: REFLO | D14: ADRIOXY | E14: ADRIOXY-XXL | F14: XXL | G14: XXL | H14: REFLO | I14: Playera tipo polo REFLO Adriatic Oxy/ Navy | J14: Ropa | K14: Playeras | M14: REFLO | P14: Azul | S14: Poliéster reciclado | T14: Playera tipo polo de golf REFLO modelo Adriatic en color Oxy/ Navy, confeccionado con materiales reciclados. Estilo ADRIOXY. | V14: PZS | W14: 53101600 | X14: https://i.ibb.co/NCvyXJJ/ADRIOXY.jpg | Y14: 26 | Z14: 1899 | AA14: =IF(AND(A14="", B14="", E14=""), "", IF(AB14="", "Válido", IF((LEN(AB14)-LEN(SUBSTITUTE(AB14,"; ","")))/2+1>(LEN(AB14)-LEN(SUBSTITUTE(AB14,"[Aviso]","")))/7, "Con Incidencias", "Válido"))) | AB14: =IF(AND(A14="", B14="", E14=""), "", TEXTJOIN("; ", TRUE, IF(OR(TRIM(A14&"")="", ISNUMBER(SEARCH("FALTA", A14))), "UPC faltante/inválido", ""), IF(AND(A14<>"", IFERROR(_xlfn.XMATCH(A14,$A$2:$A$653,0,1)<>_xlfn.XMATCH(A14,$A$2:$A$653,0,-1),FALSE)), "Código de barras duplicado", ""), IF(AND(E14<>"", COUNTIF($E$2:$E$653, E14)>1), "SKU duplicado", ""), IF(OR(J14="", J14=""), "[Aviso] División no capturada ()", IF(ISNA(MATCH(J14, Criterios!$A$123:$A$126, 0)), "División no válida", "")), IF(OR(K14="", K14=""), "[Aviso] Categoría no capturada ()", IF(ISNA(MATCH(K14, Criterios!$A$81:$A$120, 0)), "Categoría no válida", IF(AND(J14<>"", J14<>"", J14<>VLOOKUP(K14, Criterios!$A$81:$B$120, 2, FALSE)), "División no coincide con Categoría", ""))), IF(OR(L14="", L14=""), "[Aviso] Género no capturado ()", IF(ISNA(MATCH(L14, Criterios!$B$123:$B$127, 0)), "Género no válido", "")), IF(OR(N14="", N14=""), "[Aviso] Temporada no capturada ()", IF(ISNA(MATCH(N14, Criterios!$C$123:$C$128, 0)), "Temporada no válida", "")), IF(OR(O14="", O14=""), "[Aviso] Ciclo de vida no capturado ()", IF(ISNA(MATCH(O14, Criterios!$D$123:$D$124, 0)), "Ciclo de vida no válido", "")))) | AD14: 6 | AE14: REFLO ALMACEN (3) | AF14: 6 | AG14: Nuevo – NetSuite con existencia | AH14: Género no indicado en NetSuite; Composición: poliéster reciclado (validar % en etiqueta); Físico total NetSuite 6 ≠ suma por ubicación 3 | Revisión 29/09/2026: Marca REFLO fuera de lista Criterios; Campos sin respaldo: L, N, O, Q, U; Auditoría NetSuite 30/09/2026: llenado desde NetSuite [Z] | Homologación G1522 06/10/2026: Validador Shopify: WB: precio con IVA no termina en 9 | AI14: No | AK14: G1522ProductosTodosloscamposSandboxResults894.xlsx: fila 43913 [X,Y]; G1522_Extraccion_Articulos_NetSuite_2026-09-30.xlsx: fila 37587 [Z] | AL14: 26
A15: 5060923781993 | B15: 84421 | C15: REFLO | D15: ADRIOXY | E15: ADRIOXY-S | F15: S | G15: S | H15: REFLO | I15: Playera tipo polo REFLO Adriatic Oxy/Navy | J15: Ropa | K15: Playeras | M15: REFLO | P15: Azul | S15: Poliéster reciclado | T15: Playera tipo polo de golf REFLO modelo Adriatic en color Oxy/Navy, confeccionado con materiales reciclados. Estilo ADRIOXY. | V15: PZS | W15: 53101600 | X15: https://i.ibb.co/NCvyXJJ/ADRIOXY.jpg | Y15: 26 | Z15: 1899 | AA15: =IF(AND(A15="", B15="", E15=""), "", IF(AB15="", "Válido", IF((LEN(AB15)-LEN(SUBSTITUTE(AB15,"; ","")))/2+1>(LEN(AB15)-LEN(SUBSTITUTE(AB15,"[Aviso]","")))/7, "Con Incidencias", "Válido"))) | AB15: =IF(AND(A15="", B15="", E15=""), "", TEXTJOIN("; ", TRUE, IF(OR(TRIM(A15&"")="", ISNUMBER(SEARCH("FALTA", A15))), "UPC faltante/inválido", ""), IF(AND(A15<>"", IFERROR(_xlfn.XMATCH(A15,$A$2:$A$653,0,1)<>_xlfn.XMATCH(A15,$A$2:$A$653,0,-1),FALSE)), "Código de barras duplicado", ""), IF(AND(E15<>"", COUNTIF($E$2:$E$653, E15)>1), "SKU duplicado", ""), IF(OR(J15="", J15=""), "[Aviso] División no capturada ()", IF(ISNA(MATCH(J15, Criterios!$A$123:$A$126, 0)), "División no válida", "")), IF(OR(K15="", K15=""), "[Aviso] Categoría no capturada ()", IF(ISNA(MATCH(K15, Criterios!$A$81:$A$120, 0)), "Categoría no válida", IF(AND(J15<>"", J15<>"", J15<>VLOOKUP(K15, Criterios!$A$81:$B$120, 2, FALSE)), "División no coincide con Categoría", ""))), IF(OR(L15="", L15=""), "[Aviso] Género no capturado ()", IF(ISNA(MATCH(L15, Criterios!$B$123:$B$127, 0)), "Género no válido", "")), IF(OR(N15="", N15=""), "[Aviso] Temporada no capturada ()", IF(ISNA(MATCH(N15, Criterios!$C$123:$C$128, 0)), "Temporada no válida", "")), IF(OR(O15="", O15=""), "[Aviso] Ciclo de vida no capturado ()", IF(ISNA(MATCH(O15, Criterios!$D$123:$D$124, 0)), "Ciclo de vida no válido", "")))) | AD15: 8 | AE15: REFLO ALMACEN (2); CONSIGNA REFLO (2) | AF15: 8 | AG15: Nuevo – NetSuite con existencia | AH15: Género no indicado en NetSuite; Composición: poliéster reciclado (validar % en etiqueta); Físico total NetSuite 8 ≠ suma por ubicación 4 | Revisión 29/09/2026: Marca REFLO fuera de lista Criterios; Campos sin respaldo: L, N, O, Q, U; Auditoría NetSuite 30/09/2026: llenado desde NetSuite [Z] | Homologación G1522 06/10/2026: Validador Shopify: WB: precio con IVA no termina en 9 | AI15: No | AK15: G1522ProductosTodosloscamposSandboxResults894.xlsx: fila 43915 [X,Y]; G1522_Extraccion_Articulos_NetSuite_2026-09-30.xlsx: fila 39590 [Z] | AL15: 26
A16: 5060923780439 | B16: 79077 | C16: REFLO | D16: BISCAQU | E16: BISCAQU-S | F16: S | G16: S | H16: REFLO | I16: Short REFLO Biscay Aqua | J16: Ropa | K16: Shorts | M16: REFLO | P16: Azul | S16: Poliéster reciclado | T16: Short de golf REFLO modelo Biscay en color Aqua, confeccionado con materiales reciclados. Estilo BISCAQU. | V16: PZS | W16: 53101500 | X16: https://i.ibb.co/hsH5ZbD/BISCAQU.jpg | Y16: 19.5 | Z16: 1449 | AA16: =IF(AND(A16="", B16="", E16=""), "", IF(AB16="", "Válido", IF((LEN(AB16)-LEN(SUBSTITUTE(AB16,"; ","")))/2+1>(LEN(AB16)-LEN(SUBSTITUTE(AB16,"[Aviso]","")))/7, "Con Incidencias", "Válido"))) | AB16: =IF(AND(A16="", B16="", E16=""), "", TEXTJOIN("; ", TRUE, IF(OR(TRIM(A16&"")="", ISNUMBER(SEARCH("FALTA", A16))), "UPC faltante/inválido", ""), IF(AND(A16<>"", IFERROR(_xlfn.XMATCH(A16,$A$2:$A$653,0,1)<>_xlfn.XMATCH(A16,$A$2:$A$653,0,-1),FALSE)), "Código de barras duplicado", ""), IF(AND(E16<>"", COUNTIF($E$2:$E$653, E16)>1), "SKU duplicado", ""), IF(OR(J16="", J16=""), "[Aviso] División no capturada ()", IF(ISNA(MATCH(J16, Criterios!$A$123:$A$126, 0)), "División no válida", "")), IF(OR(K16="", K16=""), "[Aviso] Categoría no capturada ()", IF(ISNA(MATCH(K16, Criterios!$A$81:$A$120, 0)), "Categoría no válida", IF(AND(J16<>"", J16<>"", J16<>VLOOKUP(K16, Criterios!$A$81:$B$120, 2, FALSE)), "División no coincide con Categoría", ""))), IF(OR(L16="", L16=""), "[Aviso] Género no capturado ()", IF(ISNA(MATCH(L16, Criterios!$B$123:$B$127, 0)), "Género no válido", "")), IF(OR(N16="", N16=""), "[Aviso] Temporada no capturada ()", IF(ISNA(MATCH(N16, Criterios!$C$123:$C$128, 0)), "Temporada no válida", "")), IF(OR(O16="", O16=""), "[Aviso] Ciclo de vida no capturado ()", IF(ISNA(MATCH(O16, Criterios!$D$123:$D$124, 0)), "Ciclo de vida no válido", "")))) | AD16: 1 | AE16: REFLO ALMACEN (2) | AF16: 2 | AG16: Nuevo – NetSuite con existencia | AH16: Género no indicado en NetSuite; Composición: poliéster reciclado (validar % en etiqueta) | Revisión 29/09/2026: Marca REFLO fuera de lista Criterios; Campos sin respaldo: L, N, O, Q, U; Auditoría NetSuite 30/09/2026: llenado desde NetSuite [Z] | Homologación G1522 06/10/2026: Validación G1522: [Aviso] Precio de compra posiblemente en USD · Validador Shopify: WB: precio con IVA no termina en 9 | AI16: Sí | AJ16: CONSIGNA REFLO (-1) | AK16: G1522ProductosTodosloscamposSandboxResults894.xlsx: fila 45340 [X,Y]; G1522_Extraccion_Articulos_NetSuite_2026-09-30.xlsx: fila 37461 [Z] | AL16: 19.5
A17: 5060923780446 | B17: 79078 | C17: REFLO | D17: BISCAQU | E17: BISCAQU-M | F17: M | G17: M | H17: REFLO | I17: Short REFLO Biscay Aqua | J17: Ropa | K17: Shorts | M17: REFLO | P17: Azul | S17: Poliéster reciclado | T17: Short de golf REFLO modelo Biscay en color Aqua, confeccionado con materiales reciclados. Estilo BISCAQU. | V17: PZS | W17: 53101500 | X17: https://i.ibb.co/hsH5ZbD/BISCAQU.jpg | Y17: 19.5 | Z17: 1449 | AA17: =IF(AND(A17="", B17="", E17=""), "", IF(AB17="", "Válido", IF((LEN(AB17)-LEN(SUBSTITUTE(AB17,"; ","")))/2+1>(LEN(AB17)-LEN(SUBSTITUTE(AB17,"[Aviso]","")))/7, "Con Incidencias", "Válido"))) | AB17: =IF(AND(A17="", B17="", E17=""), "", TEXTJOIN("; ", TRUE, IF(OR(TRIM(A17&"")="", ISNUMBER(SEARCH("FALTA", A17))), "UPC faltante/inválido", ""), IF(AND(A17<>"", IFERROR(_xlfn.XMATCH(A17,$A$2:$A$653,0,1)<>_xlfn.XMATCH(A17,$A$2:$A$653,0,-1),FALSE)), "Código de barras duplicado", ""), IF(AND(E17<>"", COUNTIF($E$2:$E$653, E17)>1), "SKU duplicado", ""), IF(OR(J17="", J17=""), "[Aviso] División no capturada ()", IF(ISNA(MATCH(J17, Criterios!$A$123:$A$126, 0)), "División no válida", "")), IF(OR(K17="", K17=""), "[Aviso] Categoría no capturada ()", IF(ISNA(MATCH(K17, Criterios!$A$81:$A$120, 0)), "Categoría no válida", IF(AND(J17<>"", J17<>"", J17<>VLOOKUP(K17, Criterios!$A$81:$B$120, 2, FALSE)), "División no coincide con Categoría", ""))), IF(OR(L17="", L17=""), "[Aviso] Género no capturado ()", IF(ISNA(MATCH(L17, Criterios!$B$123:$B$127, 0)), "Género no válido", "")), IF(OR(N17="", N17=""), "[Aviso] Temporada no capturada ()", IF(ISNA(MATCH(N17, Criterios!$C$123:$C$128, 0)), "Temporada no válida", "")), IF(OR(O17="", O17=""), "[Aviso] Ciclo de vida no capturado ()", IF(ISNA(MATCH(O17, Criterios!$D$123:$D$124, 0)), "Ciclo de vida no válido", "")))) | AD17: 2 | AE17: REFLO ALMACEN (3) | AF17: 3 | AG17: Nuevo – NetSuite con existencia | AH17: Género no indicado en NetSuite; Composición: poliéster reciclado (validar % en etiqueta) | Revisión 29/09/2026: Marca REFLO fuera de lista Criterios; Campos sin respaldo: L, N, O, Q, U; Auditoría NetSuite 30/09/2026: llenado desde NetSuite [Z] | Homologación G1522 06/10/2026: Validación G1522: [Aviso] Precio de compra posiblemente en USD · Validador Shopify: WB: precio con IVA no termina en 9 | AI17: Sí | AJ17: CONSIGNA REFLO (-1) | AK17: G1522ProductosTodosloscamposSandboxResults894.xlsx: fila 45341 [X,Y]; G1522_Extraccion_Articulos_NetSuite_2026-09-30.xlsx: fila 37462 [Z] | AL17: 19.5
A18: 5060923780453 | B18: 79079 | C18: REFLO | D18: BISCAQU | E18: BISCAQU-L | F18: L | G18: L | H18: REFLO | I18: Short REFLO Biscay Aqua | J18: Ropa | K18: Shorts | M18: REFLO | P18: Azul | S18: Poliéster reciclado | T18: Short de golf REFLO modelo Biscay en color Aqua, confeccionado con materiales reciclados. Estilo BISCAQU. | V18: PZS | W18: 53101500 | X18: https://i.ibb.co/hsH5ZbD/BISCAQU.jpg | Y18: 19.5 | Z18: 1449 | AA18: =IF(AND(A18="", B18="", E18=""), "", IF(AB18="", "Válido", IF((LEN(AB18)-LEN(SUBSTITUTE(AB18,"; ","")))/2+1>(LEN(AB18)-LEN(SUBSTITUTE(AB18,"[Aviso]","")))/7, "Con Incidencias", "Válido"))) | AB18: =IF(AND(A18="", B18="", E18=""), "", TEXTJOIN("; ", TRUE, IF(OR(TRIM(A18&"")="", ISNUMBER(SEARCH("FALTA", A18))), "UPC faltante/inválido", ""), IF(AND(A18<>"", IFERROR(_xlfn.XMATCH(A18,$A$2:$A$653,0,1)<>_xlfn.XMATCH(A18,$A$2:$A$653,0,-1),FALSE)), "Código de barras duplicado", ""), IF(AND(E18<>"", COUNTIF($E$2:$E$653, E18)>1), "SKU duplicado", ""), IF(OR(J18="", J18=""), "[Aviso] División no capturada ()", IF(ISNA(MATCH(J18, Criterios!$A$123:$A$126, 0)), "División no válida", "")), IF(OR(K18="", K18=""), "[Aviso] Categoría no capturada ()", IF(ISNA(MATCH(K18, Criterios!$A$81:$A$120, 0)), "Categoría no válida", IF(AND(J18<>"", J18<>"", J18<>VLOOKUP(K18, Criterios!$A$81:$B$120, 2, FALSE)), "División no coincide con Categoría", ""))), IF(OR(L18="", L18=""), "[Aviso] Género no capturado ()", IF(ISNA(MATCH(L18, Criterios!$B$123:$B$127, 0)), "Género no válido", "")), IF(OR(N18="", N18=""), "[Aviso] Temporada no capturada ()", IF(ISNA(MATCH(N18, Criterios!$C$123:$C$128, 0)), "Temporada no válida", "")), IF(OR(O18="", O18=""), "[Aviso] Ciclo de vida no capturado ()", IF(ISNA(MATCH(O18, Criterios!$D$123:$D$124, 0)), "Ciclo de vida no válido", "")))) | AD18: 3 | AE18: MUESTRAS REFLO (1); REFLO ALMACEN (1) | AF18: 2 | AG18: Nuevo – NetSuite con existencia | AH18: Género no indicado en NetSuite; Composición: poliéster reciclado (validar % en etiqueta); Físico total NetSuite 3 ≠ suma por ubicación 2 | Revisión 29/09/2026: Marca REFLO fuera de lista Criterios; Campos sin respaldo: L, N, O, Q, U; Auditoría NetSuite 30/09/2026: llenado desde NetSuite [Z] | Homologación G1522 06/10/2026: Validación G1522: [Aviso] Precio de compra posiblemente en USD · Validador Shopify: WB: precio con IVA no termina en 9 | AI18: No | AK18: G1522ProductosTodosloscamposSandboxResults894.xlsx: fila 45342 [X,Y]; G1522_Extraccion_Articulos_NetSuite_2026-09-30.xlsx: fila 37463 [Z] | AL18: 19.5
A19: 5060923780460 | B19: 79080 | C19: REFLO | D19: BISCAQU | E19: BISCAQU-XL | F19: XL | G19: XL | H19: REFLO | I19: Short REFLO Biscay Aqua | J19: Ropa | K19: Shorts | M19: REFLO | P19: Azul | S19: Poliéster reciclado | T19: Short de golf REFLO modelo Biscay en color Aqua, confeccionado con materiales reciclados. Estilo BISCAQU. | V19: PZS | W19: 53101500 | X19: https://i.ibb.co/hsH5ZbD/BISCAQU.jpg | Y19: 19.5 | Z19: 1449 | AA19: =IF(AND(A19="", B19="", E19=""), "", IF(AB19="", "Válido", IF((LEN(AB19)-LEN(SUBSTITUTE(AB19,"; ","")))/2+1>(LEN(AB19)-LEN(SUBSTITUTE(AB19,"[Aviso]","")))/7, "Con Incidencias", "Válido"))) | AB19: =IF(AND(A19="", B19="", E19=""), "", TEXTJOIN("; ", TRUE, IF(OR(TRIM(A19&"")="", ISNUMBER(SEARCH("FALTA", A19))), "UPC faltante/inválido", ""), IF(AND(A19<>"", IFERROR(_xlfn.XMATCH(A19,$A$2:$A$653,0,1)<>_xlfn.XMATCH(A19,$A$2:$A$653,0,-1),FALSE)), "Código de barras duplicado", ""), IF(AND(E19<>"", COUNTIF($E$2:$E$653, E19)>1), "SKU duplicado", ""), IF(OR(J19="", J19=""), "[Aviso] División no capturada ()", IF(ISNA(MATCH(J19, Criterios!$A$123:$A$126, 0)), "División no válida", "")), IF(OR(K19="", K19=""), "[Aviso] Categoría no capturada ()", IF(ISNA(MATCH(K19, Criterios!$A$81:$A$120, 0)), "Categoría no válida", IF(AND(J19<>"", J19<>"", J19<>VLOOKUP(K19, Criterios!$A$81:$B$120, 2, FALSE)), "División no coincide con Categoría", ""))), IF(OR(L19="", L19=""), "[Aviso] Género no capturado ()", IF(ISNA(MATCH(L19, Criterios!$B$123:$B$127, 0)), "Género no válido", "")), IF(OR(N19="", N19=""), "[Aviso] Temporada no capturada ()", IF(ISNA(MATCH(N19, Criterios!$C$123:$C$128, 0)), "Temporada no válida", "")), IF(OR(O19="", O19=""), "[Aviso] Ciclo de vida no capturado ()", IF(ISNA(MATCH(O19, Criterios!$D$123:$D$124, 0)), "Ciclo de vida no válido", "")))) | AD19: 2 | AE19: REFLO ALMACEN (1) | AF19: 2 | AG19: Nuevo – NetSuite con existencia | AH19: Género no indicado en NetSuite; Composición: poliéster reciclado (validar % en etiqueta); Físico total NetSuite 2 ≠ suma por ubicación 1 | Revisión 29/09/2026: Marca REFLO fuera de lista Criterios; Campos sin respaldo: L, N, O, Q, U; Auditoría NetSuite 30/09/2026: llenado desde NetSuite [Z] | Homologación G1522 06/10/2026: Validación G1522: [Aviso] Precio de compra posiblemente en USD · Validador Shopify: WB: precio con IVA no termina en 9 | AI19: No | AK19: G1522ProductosTodosloscamposSandboxResults894.xlsx: fila 45343 [X,Y]; G1522_Extraccion_Articulos_NetSuite_2026-09-30.xlsx: fila 37464 [Z] | AL19: 19.5
A20: 5060923780323 | B20: 79081 | C20: REFLO | D20: BISCBLA | E20: BISCBLA-M | F20: M | G20: M | H20: REFLO | I20: Short REFLO Biscay Black | J20: Ropa | K20: Shorts | M20: REFLO | P20: Negro | S20: Poliéster reciclado | T20: Short de golf REFLO modelo Biscay en color Black, confeccionado con materiales reciclados. Estilo BISCBLA. | V20: PZS | W20: 53101500 | X20: https://i.ibb.co/h2mgx7X/BISCBLA.jpg | Y20: 19.5 | Z20: 1449 | AA20: =IF(AND(A20="", B20="", E20=""), "", IF(AB20="", "Válido", IF((LEN(AB20)-LEN(SUBSTITUTE(AB20,"; ","")))/2+1>(LEN(AB20)-LEN(SUBSTITUTE(AB20,"[Aviso]","")))/7, "Con Incidencias", "Válido"))) | AB20: =IF(AND(A20="", B20="", E20=""), "", TEXTJOIN("; ", TRUE, IF(OR(TRIM(A20&"")="", ISNUMBER(SEARCH("FALTA", A20))), "UPC faltante/inválido", ""), IF(AND(A20<>"", IFERROR(_xlfn.XMATCH(A20,$A$2:$A$653,0,1)<>_xlfn.XMATCH(A20,$A$2:$A$653,0,-1),FALSE)), "Código de barras duplicado", ""), IF(AND(E20<>"", COUNTIF($E$2:$E$653, E20)>1), "SKU duplicado", ""), IF(OR(J20="", J20=""), "[Aviso] División no capturada ()", IF(ISNA(MATCH(J20, Criterios!$A$123:$A$126, 0)), "División no válida", "")), IF(OR(K20="", K20=""), "[Aviso] Categoría no capturada ()", IF(ISNA(MATCH(K20, Criterios!$A$81:$A$120, 0)), "Categoría no válida", IF(AND(J20<>"", J20<>"", J20<>VLOOKUP(K20, Criterios!$A$81:$B$120, 2, FALSE)), "División no coincide con Categoría", ""))), IF(OR(L20="", L20=""), "[Aviso] Género no capturado ()", IF(ISNA(MATCH(L20, Criterios!$B$123:$B$127, 0)), "Género no válido", "")), IF(OR(N20="", N20=""), "[Aviso] Temporada no capturada ()", IF(ISNA(MATCH(N20, Criterios!$C$123:$C$128, 0)), "Temporada no válida", "")), IF(OR(O20="", O20=""), "[Aviso] Ciclo de vida no capturado ()", IF(ISNA(MATCH(O20, Criterios!$D$123:$D$124, 0)), "Ciclo de vida no válido", "")))) | AD20: 0 | AF20: 0 | AG20: Nuevo – NetSuite sin existencia | AH20: Género no indicado en NetSuite; Composición: poliéster reciclado (validar % en etiqueta) | Revisión 29/09/2026: Marca REFLO fuera de lista Criterios; Campos sin respaldo: L, N, O, Q, U; Auditoría NetSuite 30/09/2026: llenado desde NetSuite [Z] | Homologación G1522 06/10/2026: Validación G1522: [Aviso] Precio de compra posiblemente en USD · Validador Shopify: WB: precio con IVA no termina en 9 | AI20: No | AK20: G1522ProductosTodosloscamposSandboxResults894.xlsx: fila 45345 [X,Y]; G1522_Extraccion_Articulos_NetSuite_2026-09-30.xlsx: fila 37465 [Z] | AL20: 19.5
A21: 5060923780330 | B21: 79082 | C21: REFLO | D21: BISCBLA | E21: BISCBLA-L | F21: L | G21: L | H21: REFLO | I21: Short REFLO Biscay Black | J21: Ropa | K21: Shorts | M21: REFLO | P21: Negro | S21: Poliéster reciclado | T21: Short de golf REFLO modelo Biscay en color Black, confeccionado con materiales reciclados. Estilo BISCBLA. | V21: PZS | W21: 53101500 | X21: https://i.ibb.co/h2mgx7X/BISCBLA.jpg | Y21: 19.5 | Z21: 1449 | AA21: =IF(AND(A21="", B21="", E21=""), "", IF(AB21="", "Válido", IF((LEN(AB21)-LEN(SUBSTITUTE(AB21,"; ","")))/2+1>(LEN(AB21)-LEN(SUBSTITUTE(AB21,"[Aviso]","")))/7, "Con Incidencias", "Válido"))) | AB21: =IF(AND(A21="", B21="", E21=""), "", TEXTJOIN("; ", TRUE, IF(OR(TRIM(A21&"")="", ISNUMBER(SEARCH("FALTA", A21))), "UPC faltante/inválido", ""), IF(AND(A21<>"", IFERROR(_xlfn.XMATCH(A21,$A$2:$A$653,0,1)<>_xlfn.XMATCH(A21,$A$2:$A$653,0,-1),FALSE)), "Código de barras duplicado", ""), IF(AND(E21<>"", COUNTIF($E$2:$E$653, E21)>1), "SKU duplicado", ""), IF(OR(J21="", J21=""), "[Aviso] División no capturada ()", IF(ISNA(MATCH(J21, Criterios!$A$123:$A$126, 0)), "División no válida", "")), IF(OR(K21="", K21=""), "[Aviso] Categoría no capturada ()", IF(ISNA(MATCH(K21, Criterios!$A$81:$A$120, 0)), "Categoría no válida", IF(AND(J21<>"", J21<>"", J21<>VLOOKUP(K21, Criterios!$A$81:$B$120, 2, FALSE)), "División no coincide con Categoría", ""))), IF(OR(L21="", L21=""), "[Aviso] Género no capturado ()", IF(ISNA(MATCH(L21, Criterios!$B$123:$B$127, 0)), "Género no válido", "")), IF(OR(N21="", N21=""), "[Aviso] Temporada no capturada ()", IF(ISNA(MATCH(N21, Criterios!$C$123:$C$128, 0)), "Temporada no válida", "")), IF(OR(O21="", O21=""), "[Aviso] Ciclo de vida no capturado ()", IF(ISNA(MATCH(O21, Criterios!$D$123:$D$124, 0)), "Ciclo de vida no válido", "")))) | AD21: 3 | AE21: MUESTRAS REFLO (1); REFLO ALMACEN (3) | AF21: 3 | AG21: Nuevo – NetSuite con existencia | AH21: Género no indicado en NetSuite; Composición: poliéster reciclado (validar % en etiqueta) | Revisión 29/09/2026: Marca REFLO fuera de lista Criterios; Campos sin respaldo: L, N, O, Q, U; Auditoría NetSuite 30/09/2026: llenado desde NetSuite [Z] | Homologación G1522 06/10/2026: Validación G1522: [Aviso] Precio de compra posiblemente en USD · Validador Shopify: WB: precio con IVA no termina en 9 | AI21: Sí | AJ21: CONSIGNA REFLO (-1) | AK21: G1522ProductosTodosloscamposSandboxResults894.xlsx: fila 45346 [X,Y]; G1522_Extraccion_Articulos_NetSuite_2026-09-30.xlsx: fila 37466 [Z] | AL21: 19.5
A22: 5060923780347 | B22: 79083 | C22: REFLO | D22: BISCBLA | E22: BISCBLA-XL | F22: XL | G22: XL | H22: REFLO | I22: Short REFLO Biscay Black | J22: Ropa | K22: Shorts | M22: REFLO | P22: Negro | S22: Poliéster reciclado | T22: Short de golf REFLO modelo Biscay en color Black, confeccionado con materiales reciclados. Estilo BISCBLA. | V22: PZS | W22: 53101500 | X22: https://i.ibb.co/h2mgx7X/BISCBLA.jpg | Y22: 19.5 | Z22: 1449 | AA22: =IF(AND(A22="", B22="", E22=""), "", IF(AB22="", "Válido", IF((LEN(AB22)-LEN(SUBSTITUTE(AB22,"; ","")))/2+1>(LEN(AB22)-LEN(SUBSTITUTE(AB22,"[Aviso]","")))/7, "Con Incidencias", "Válido"))) | AB22: =IF(AND(A22="", B22="", E22=""), "", TEXTJOIN("; ", TRUE, IF(OR(TRIM(A22&"")="", ISNUMBER(SEARCH("FALTA", A22))), "UPC faltante/inválido", ""), IF(AND(A22<>"", IFERROR(_xlfn.XMATCH(A22,$A$2:$A$653,0,1)<>_xlfn.XMATCH(A22,$A$2:$A$653,0,-1),FALSE)), "Código de barras duplicado", ""), IF(AND(E22<>"", COUNTIF($E$2:$E$653, E22)>1), "SKU duplicado", ""), IF(OR(J22="", J22=""), "[Aviso] División no capturada ()", IF(ISNA(MATCH(J22, Criterios!$A$123:$A$126, 0)), "División no válida", "")), IF(OR(K22="", K22=""), "[Aviso] Categoría no capturada ()", IF(ISNA(MATCH(K22, Criterios!$A$81:$A$120, 0)), "Categoría no válida", IF(AND(J22<>"", J22<>"", J22<>VLOOKUP(K22, Criterios!$A$81:$B$120, 2, FALSE)), "División no coincide con Categoría", ""))), IF(OR(L22="", L22=""), "[Aviso] Género no capturado ()", IF(ISNA(MATCH(L22, Criterios!$B$123:$B$127, 0)), "Género no válido", "")), IF(OR(N22="", N22=""), "[Aviso] Temporada no capturada ()", IF(ISNA(MATCH(N22, Criterios!$C$123:$C$128, 0)), "Temporada no válida", "")), IF(OR(O22="", O22=""), "[Aviso] Ciclo de vida no capturado ()", IF(ISNA(MATCH(O22, Criterios!$D$123:$D$124, 0)), "Ciclo de vida no válido", "")))) | AD22: 4 | AE22: REFLO ALMACEN (3) | AF22: 5 | AG22: Nuevo – NetSuite con existencia | AH22: Género no indicado en NetSuite; Composición: poliéster reciclado (validar % en etiqueta); Físico total NetSuite 4 ≠ suma por ubicación 2 | Revisión 29/09/2026: Marca REFLO fuera de lista Criterios; Campos sin respaldo: L, N, O, Q, U; Auditoría NetSuite 30/09/2026: llenado desde NetSuite [Z] | Homologación G1522 06/10/2026: Validación G1522: [Aviso] Precio de compra posiblemente en USD · Validador Shopify: WB: precio con IVA no termina en 9 | AI22: Sí | AJ22: CONSIGNA REFLO (-1) | AK22: G1522ProductosTodosloscamposSandboxResults894.xlsx: fila 45347 [X,Y]; G1522_Extraccion_Articulos_NetSuite_2026-09-30.xlsx: fila 37467 [Z] | AL22: 19.5
A23: 5060923780385 | B23: 79084 | C23: REFLO | D23: BISCFRE | E23: BISCFRE-M | F23: M | G23: M | H23: REFLO | I23: Short REFLO Biscay French Navy | J23: Ropa | K23: Shorts | M23: REFLO | P23: Azul | S23: Poliéster reciclado | T23: Short de golf REFLO modelo Biscay en color French Navy, confeccionado con materiales reciclados. Estilo BISCFRE. | V23: PZS | W23: 53101500 | X23: https://i.ibb.co/hDy0Lh5/BISCFRE.jpg | Y23: 19.5 | Z23: 1449 | AA23: =IF(AND(A23="", B23="", E23=""), "", IF(AB23="", "Válido", IF((LEN(AB23)-LEN(SUBSTITUTE(AB23,"; ","")))/2+1>(LEN(AB23)-LEN(SUBSTITUTE(AB23,"[Aviso]","")))/7, "Con Incidencias", "Válido"))) | AB23: =IF(AND(A23="", B23="", E23=""), "", TEXTJOIN("; ", TRUE, IF(OR(TRIM(A23&"")="", ISNUMBER(SEARCH("FALTA", A23))), "UPC faltante/inválido", ""), IF(AND(A23<>"", IFERROR(_xlfn.XMATCH(A23,$A$2:$A$653,0,1)<>_xlfn.XMATCH(A23,$A$2:$A$653,0,-1),FALSE)), "Código de barras duplicado", ""), IF(AND(E23<>"", COUNTIF($E$2:$E$653, E23)>1), "SKU duplicado", ""), IF(OR(J23="", J23=""), "[Aviso] División no capturada ()", IF(ISNA(MATCH(J23, Criterios!$A$123:$A$126, 0)), "División no válida", "")), IF(OR(K23="", K23=""), "[Aviso] Categoría no capturada ()", IF(ISNA(MATCH(K23, Criterios!$A$81:$A$120, 0)), "Categoría no válida", IF(AND(J23<>"", J23<>"", J23<>VLOOKUP(K23, Criterios!$A$81:$B$120, 2, FALSE)), "División no coincide con Categoría", ""))), IF(OR(L23="", L23=""), "[Aviso] Género no capturado ()", IF(ISNA(MATCH(L23, Criterios!$B$123:$B$127, 0)), "Género no válido", "")), IF(OR(N23="", N23=""), "[Aviso] Temporada no capturada ()", IF(ISNA(MATCH(N23, Criterios!$C$123:$C$128, 0)), "Temporada no válida", "")), IF(OR(O23="", O23=""), "[Aviso] Ciclo de vida no capturado ()", IF(ISNA(MATCH(O23, Criterios!$D$123:$D$124, 0)), "Ciclo de vida no válido", "")))) | AD23: 7 | AE23: MUESTRAS REFLO (1); REFLO ALMACEN (3) | AF23: 6 | AG23: Nuevo – NetSuite con existencia | AH23: Género no indicado en NetSuite; Composición: poliéster reciclado (validar % en etiqueta); Físico total NetSuite 7 ≠ suma por ubicación 4 | Revisión 29/09/2026: Marca REFLO fuera de lista Criterios; Campos sin respaldo: L, N, O, Q, U; Auditoría NetSuite 30/09/2026: llenado desde NetSuite [Z] | Homologación G1522 06/10/2026: Validación G1522: [Aviso] Precio de compra posiblemente en USD · Validador Shopify: WB: precio con IVA no termina en 9 | AI23: No | AK23: G1522ProductosTodosloscamposSandboxResults894.xlsx: fila 45349 [X,Y]; G1522_Extraccion_Articulos_NetSuite_2026-09-30.xlsx: fila 37468 [Z] | AL23: 19.5
A24: 5060923780392 | B24: 79085 | C24: REFLO | D24: BISCFRE | E24: BISCFRE-L | F24: L | G24: L | H24: REFLO | I24: Short REFLO Biscay French Navy | J24: Ropa | K24: Shorts | M24: REFLO | P24: Azul | S24: Poliéster reciclado | T24: Short de golf REFLO modelo Biscay en color French Navy, confeccionado con materiales reciclados. Estilo BISCFRE. | V24: PZS | W24: 53101500 | X24: https://i.ibb.co/hDy0Lh5/BISCFRE.jpg | Y24: 19.5 | Z24: 1449 | AA24: =IF(AND(A24="", B24="", E24=""), "", IF(AB24="", "Válido", IF((LEN(AB24)-LEN(SUBSTITUTE(AB24,"; ","")))/2+1>(LEN(AB24)-LEN(SUBSTITUTE(AB24,"[Aviso]","")))/7, "Con Incidencias", "Válido"))) | AB24: =IF(AND(A24="", B24="", E24=""), "", TEXTJOIN("; ", TRUE, IF(OR(TRIM(A24&"")="", ISNUMBER(SEARCH("FALTA", A24))), "UPC faltante/inválido", ""), IF(AND(A24<>"", IFERROR(_xlfn.XMATCH(A24,$A$2:$A$653,0,1)<>_xlfn.XMATCH(A24,$A$2:$A$653,0,-1),FALSE)), "Código de barras duplicado", ""), IF(AND(E24<>"", COUNTIF($E$2:$E$653, E24)>1), "SKU duplicado", ""), IF(OR(J24="", J24=""), "[Aviso] División no capturada ()", IF(ISNA(MATCH(J24, Criterios!$A$123:$A$126, 0)), "División no válida", "")), IF(OR(K24="", K24=""), "[Aviso] Categoría no capturada ()", IF(ISNA(MATCH(K24, Criterios!$A$81:$A$120, 0)), "Categoría no válida", IF(AND(J24<>"", J24<>"", J24<>VLOOKUP(K24, Criterios!$A$81:$B$120, 2, FALSE)), "División no coincide con Categoría", ""))), IF(OR(L24="", L24=""), "[Aviso] Género no capturado ()", IF(ISNA(MATCH(L24, Criterios!$B$123:$B$127, 0)), "Género no válido", "")), IF(OR(N24="", N24=""), "[Aviso] Temporada no capturada ()", IF(ISNA(MATCH(N24, Criterios!$C$123:$C$128, 0)), "Temporada no válida", "")), IF(OR(O24="", O24=""), "[Aviso] Ciclo de vida no capturado ()", IF(ISNA(MATCH(O24, Criterios!$D$123:$D$124, 0)), "Ciclo de vida no válido", "")))) | AD24: 6 | AE24: REFLO ALMACEN (3); MUESTRAS REFLO (1) | AF24: 5 | AG24: Nuevo – NetSuite con existencia | AH24: Género no indicado en NetSuite; Composición: poliéster reciclado (validar % en etiqueta); Físico total NetSuite 6 ≠ suma por ubicación 4 | Revisión 29/09/2026: Marca REFLO fuera de lista Criterios; Campos sin respaldo: L, N, O, Q, U; Auditoría NetSuite 30/09/2026: llenado desde NetSuite [Z] | Homologación G1522 06/10/2026: Validación G1522: [Aviso] Precio de compra posiblemente en USD · Validador Shopify: WB: precio con IVA no termina en 9 | AI24: No | AK24: G1522ProductosTodosloscamposSandboxResults894.xlsx: fila 45350 [X,Y]; G1522_Extraccion_Articulos_NetSuite_2026-09-30.xlsx: fila 37469 [Z] | AL24: 19.5
A25: 5060923780408 | B25: 79086 | C25: REFLO | D25: BISCFRE | E25: BISCFRE-XL | F25: XL | G25: XL | H25: REFLO | I25: Short REFLO Biscay French Navy | J25: Ropa | K25: Shorts | M25: REFLO | P25: Azul | S25: Poliéster reciclado | T25: Short de golf REFLO modelo Biscay en color French Navy, confeccionado con materiales reciclados. Estilo BISCFRE. | V25: PZS | W25: 53101500 | X25: https://i.ibb.co/hDy0Lh5/BISCFRE.jpg | Y25: 19.5 | Z25: 1449 | AA25: =IF(AND(A25="", B25="", E25=""), "", IF(AB25="", "Válido", IF((LEN(AB25)-LEN(SUBSTITUTE(AB25,"; ","")))/2+1>(LEN(AB25)-LEN(SUBSTITUTE(AB25,"[Aviso]","")))/7, "Con Incidencias", "Válido"))) | AB25: =IF(AND(A25="", B25="", E25=""), "", TEXTJOIN("; ", TRUE, IF(OR(TRIM(A25&"")="", ISNUMBER(SEARCH("FALTA", A25))), "UPC faltante/inválido", ""), IF(AND(A25<>"", IFERROR(_xlfn.XMATCH(A25,$A$2:$A$653,0,1)<>_xlfn.XMATCH(A25,$A$2:$A$653,0,-1),FALSE)), "Código de barras duplicado", ""), IF(AND(E25<>"", COUNTIF($E$2:$E$653, E25)>1), "SKU duplicado", ""), IF(OR(J25="", J25=""), "[Aviso] División no capturada ()", IF(ISNA(MATCH(J25, Criterios!$A$123:$A$126, 0)), "División no válida", "")), IF(OR(K25="", K25=""), "[Aviso] Categoría no capturada ()", IF(ISNA(MATCH(K25, Criterios!$A$81:$A$120, 0)), "Categoría no válida", IF(AND(J25<>"", J25<>"", J25<>VLOOKUP(K25, Criterios!$A$81:$B$120, 2, FALSE)), "División no coincide con Categoría", ""))), IF(OR(L25="", L25=""), "[Aviso] Género no capturado ()", IF(ISNA(MATCH(L25, Criterios!$B$123:$B$127, 0)), "Género no válido", "")), IF(OR(N25="", N25=""), "[Aviso] Temporada no capturada ()", IF(ISNA(MATCH(N25, Criterios!$C$123:$C$128, 0)), "Temporada no válida", "")), IF(OR(O25="", O25=""), "[Aviso] Ciclo de vida no capturado ()", IF(ISNA(MATCH(O25, Criterios!$D$123:$D$124, 0)), "Ciclo de vida no válido", "")))) | AD25: 6 | AE25: REFLO ALMACEN (2); CONSIGNA REFLO (2) | AF25: 6 | AG25: Nuevo – NetSuite con existencia | AH25: Género no indicado en NetSuite; Composición: poliéster reciclado (validar % en etiqueta); Físico total NetSuite 6 ≠ suma por ubicación 4 | Revisión 29/09/2026: Marca REFLO fuera de lista Criterios; Campos sin respaldo: L, N, O, Q, U; Auditoría NetSuite 30/09/2026: llenado desde NetSuite [Z] | Homologación G1522 06/10/2026: Validación G1522: [Aviso] Precio de compra posiblemente en USD · Validador Shopify: WB: precio con IVA no termina en 9 | AI25: No | AK25: G1522ProductosTodosloscamposSandboxResults894.xlsx: fila 45351 [X,Y]; G1522_Extraccion_Articulos_NetSuite_2026-09-30.xlsx: fila 37470 [Z] | AL25: 19.5
A26: 5060923780415 | B26: 79087 | C26: REFLO | D26: BISCFRE | E26: BISCFRE-XXL | F26: XXL | G26: XXL | H26: REFLO | I26: Short REFLO Biscay French Navy | J26: Ropa | K26: Shorts | M26: REFLO | P26: Azul | S26: Poliéster reciclado | T26: Short de golf REFLO modelo Biscay en color French Navy, confeccionado con materiales reciclados. Estilo BISCFRE. | V26: PZS | W26: 53101500 | X26: https://i.ibb.co/hDy0Lh5/BISCFRE.jpg | Y26: 19.5 | Z26: 1449 | AA26: =IF(AND(A26="", B26="", E26=""), "", IF(AB26="", "Válido", IF((LEN(AB26)-LEN(SUBSTITUTE(AB26,"; ","")))/2+1>(LEN(AB26)-LEN(SUBSTITUTE(AB26,"[Aviso]","")))/7, "Con Incidencias", "Válido"))) | AB26: =IF(AND(A26="", B26="", E26=""), "", TEXTJOIN("; ", TRUE, IF(OR(TRIM(A26&"")="", ISNUMBER(SEARCH("FALTA", A26))), "UPC faltante/inválido", ""), IF(AND(A26<>"", IFERROR(_xlfn.XMATCH(A26,$A$2:$A$653,0,1)<>_xlfn.XMATCH(A26,$A$2:$A$653,0,-1),FALSE)), "Código de barras duplicado", ""), IF(AND(E26<>"", COUNTIF($E$2:$E$653, E26)>1), "SKU duplicado", ""), IF(OR(J26="", J26=""), "[Aviso] División no capturada ()", IF(ISNA(MATCH(J26, Criterios!$A$123:$A$126, 0)), "División no válida", "")), IF(OR(K26="", K26=""), "[Aviso] Categoría no capturada ()", IF(ISNA(MATCH(K26, Criterios!$A$81:$A$120, 0)), "Categoría no válida", IF(AND(J26<>"", J26<>"", J26<>VLOOKUP(K26, Criterios!$A$81:$B$120, 2, FALSE)), "División no coincide con Categoría", ""))), IF(OR(L26="", L26=""), "[Aviso] Género no capturado ()", IF(ISNA(MATCH(L26, Criterios!$B$123:$B$127, 0)), "Género no válido", "")), IF(OR(N26="", N26=""), "[Aviso] Temporada no capturada ()", IF(ISNA(MATCH(N26, Criterios!$C$123:$C$128, 0)), "Temporada no válida", "")), IF(OR(O26="", O26=""), "[Aviso] Ciclo de vida no capturado ()", IF(ISNA(MATCH(O26, Criterios!$D$123:$D$124, 0)), "Ciclo de vida no válido", "")))) | AD26: 3 | AE26: REFLO ALMACEN (1) | AF26: 3 | AG26: Nuevo – NetSuite con existencia | AH26: Género no indicado en NetSuite; Composición: poliéster reciclado (validar % en etiqueta); Físico total NetSuite 3 ≠ suma por ubicación 1 | Revisión 29/09/2026: Marca REFLO fuera de lista Criterios; Campos sin respaldo: L, N, O, Q, U; Auditoría NetSuite 30/09/2026: llenado desde NetSuite [Z] | Homologación G1522 06/10/2026: Validación G1522: [Aviso] Precio de compra posiblemente en USD · Validador Shopify: WB: precio con IVA no termina en 9 | AI26: No | AK26: G1522ProductosTodosloscamposSandboxResults894.xlsx: fila 45352 [X,Y]; G1522_Extraccion_Articulos_NetSuite_2026-09-30.xlsx: fila 37471 [Z] | AL26: 19.5
A27: 5056658700729 | B27: 79255 | C27: REFLO | D27: BOHABLA | E27: BOHABLA-M | F27: M | G27: M | H27: REFLO | I27: Playera tipo polo REFLO Bohai Black | J27: Ropa | K27: Playeras | M27: REFLO | P27: Negro | S27: 100% Poliéster reciclado | T27: Playera tipo polo de golf REFLO modelo Bohai en color Black, confeccionado con materiales reciclados. Estilo BOHABLA. | U27: China | V27: PZS | W27: 53101600 | X27: https://i.ibb.co/W5zf03J/BOHABLA.jpg | Y27: 22.75 | Z27: 1649 | AA27: =IF(AND(A27="", B27="", E27=""), "", IF(AB27="", "Válido", IF((LEN(AB27)-LEN(SUBSTITUTE(AB27,"; ","")))/2+1>(LEN(AB27)-LEN(SUBSTITUTE(AB27,"[Aviso]","")))/7, "Con Incidencias", "Válido"))) | AB27: =IF(AND(A27="", B27="", E27=""), "", TEXTJOIN("; ", TRUE, IF(OR(TRIM(A27&"")="", ISNUMBER(SEARCH("FALTA", A27))), "UPC faltante/inválido", ""), IF(AND(A27<>"", IFERROR(_xlfn.XMATCH(A27,$A$2:$A$653,0,1)<>_xlfn.XMATCH(A27,$A$2:$A$653,0,-1),FALSE)), "Código de barras duplicado", ""), IF(AND(E27<>"", COUNTIF($E$2:$E$653, E27)>1), "SKU duplicado", ""), IF(OR(J27="", J27=""), "[Aviso] División no capturada ()", IF(ISNA(MATCH(J27, Criterios!$A$123:$A$126, 0)), "División no válida", "")), IF(OR(K27="", K27=""), "[Aviso] Categoría no capturada ()", IF(ISNA(MATCH(K27, Criterios!$A$81:$A$120, 0)), "Categoría no válida", IF(AND(J27<>"", J27<>"", J27<>VLOOKUP(K27, Criterios!$A$81:$B$120, 2, FALSE)), "División no coincide con Categoría", ""))), IF(OR(L27="", L27=""), "[Aviso] Género no capturado ()", IF(ISNA(MATCH(L27, Criterios!$B$123:$B$127, 0)), "Género no válido", "")), IF(OR(N27="", N27=""), "[Aviso] Temporada no capturada ()", IF(ISNA(MATCH(N27, Criterios!$C$123:$C$128, 0)), "Temporada no válida", "")), IF(OR(O27="", O27=""), "[Aviso] Ciclo de vida no capturado ()", IF(ISNA(MATCH(O27, Criterios!$D$123:$D$124, 0)), "Ciclo de vida no válido", "")))) | AD27: 0 | AF27: 0 | AG27: Nuevo – NetSuite sin existencia | AH27: Género no indicado en NetSuite | Revisión 29/09/2026: Marca REFLO fuera de lista Criterios; Campos sin respaldo: L, N, O, Q; Auditoría NetSuite 30/09/2026: llenado desde NetSuite [Z] | Homologación G1522 06/10/2026: Validador Shopify: WB: precio con IVA no termina en 9 | AI27: No | AK27: G1522ProductosTodosloscamposSandboxResults894.xlsx: fila 45488 [X,Y]; G1522_Extraccion_Articulos_NetSuite_2026-09-30.xlsx: fila 37588 [Z] | AL27: 22.75
A28: 5056658700736 | B28: 79256 | C28: REFLO | D28: BOHABLA | E28: BOHABLA-L | F28: L | G28: L | H28: REFLO | I28: Playera tipo polo REFLO Bohai Black | J28: Ropa | K28: Playeras | M28: REFLO | P28: Negro | S28: 100% Poliéster reciclado | T28: Playera tipo polo de golf REFLO modelo Bohai en color Black, confeccionado con materiales reciclados. Estilo BOHABLA. | U28: China | V28: PZS | W28: 53101600 | X28: https://i.ibb.co/W5zf03J/BOHABLA.jpg | Y28: 22.75 | Z28: 1649 | AA28: =IF(AND(A28="", B28="", E28=""), "", IF(AB28="", "Válido", IF((LEN(AB28)-LEN(SUBSTITUTE(AB28,"; ","")))/2+1>(LEN(AB28)-LEN(SUBSTITUTE(AB28,"[Aviso]","")))/7, "Con Incidencias", "Válido"))) | AB28: =IF(AND(A28="", B28="", E28=""), "", TEXTJOIN("; ", TRUE, IF(OR(TRIM(A28&"")="", ISNUMBER(SEARCH("FALTA", A28))), "UPC faltante/inválido", ""), IF(AND(A28<>"", IFERROR(_xlfn.XMATCH(A28,$A$2:$A$653,0,1)<>_xlfn.XMATCH(A28,$A$2:$A$653,0,-1),FALSE)), "Código de barras duplicado", ""), IF(AND(E28<>"", COUNTIF($E$2:$E$653, E28)>1), "SKU duplicado", ""), IF(OR(J28="", J28=""), "[Aviso] División no capturada ()", IF(ISNA(MATCH(J28, Criterios!$A$123:$A$126, 0)), "División no válida", "")), IF(OR(K28="", K28=""), "[Aviso] Categoría no capturada ()", IF(ISNA(MATCH(K28, Criterios!$A$81:$A$120, 0)), "Categoría no válida", IF(AND(J28<>"", J28<>"", J28<>VLOOKUP(K28, Criterios!$A$81:$B$120, 2, FALSE)), "División no coincide con Categoría", ""))), IF(OR(L28="", L28=""), "[Aviso] Género no capturado ()", IF(ISNA(MATCH(L28, Criterios!$B$123:$B$127, 0)), "Género no válido", "")), IF(OR(N28="", N28=""), "[Aviso] Temporada no capturada ()", IF(ISNA(MATCH(N28, Criterios!$C$123:$C$128, 0)), "Temporada no válida", "")), IF(OR(O28="", O28=""), "[Aviso] Ciclo de vida no capturado ()", IF(ISNA(MATCH(O28, Criterios!$D$123:$D$124, 0)), "Ciclo de vida no válido", "")))) | AD28: 5 | AE28: REFLO ALMACEN (2); MUESTRAS REFLO (1) | AF28: 4 | AG28: Nuevo – NetSuite con existencia | AH28: Género no indicado en NetSuite; Físico total NetSuite 5 ≠ suma por ubicación 3 | Revisión 29/09/2026: Marca REFLO fuera de lista Criterios; Campos sin respaldo: L, N, O, Q; Auditoría NetSuite 30/09/2026: llenado desde NetSuite [Z] | Homologación G1522 06/10/2026: Validador Shopify: WB: precio con IVA no termina en 9 | AI28: No | AK28: G1522ProductosTodosloscamposSandboxResults894.xlsx: fila 45489 [X,Y]; G1522_Extraccion_Articulos_NetSuite_2026-09-30.xlsx: fila 37589 [Z] | AL28: 22.75
A29: 5056658700743 | B29: 79257 | C29: REFLO | D29: BOHABLA | E29: BOHABLA-XL | F29: XL | G29: XL | H29: REFLO | I29: Playera tipo polo REFLO Bohai Black | J29: Ropa | K29: Playeras | M29: REFLO | P29: Negro | S29: 100% Poliéster reciclado | T29: Playera tipo polo de golf REFLO modelo Bohai en color Black, confeccionado con materiales reciclados. Estilo BOHABLA. | U29: China | V29: PZS | W29: 53101600 | X29: https://i.ibb.co/W5zf03J/BOHABLA.jpg | Y29: 22.75 | Z29: 1649 | AA29: =IF(AND(A29="", B29="", E29=""), "", IF(AB29="", "Válido", IF((LEN(AB29)-LEN(SUBSTITUTE(AB29,"; ","")))/2+1>(LEN(AB29)-LEN(SUBSTITUTE(AB29,"[Aviso]","")))/7, "Con Incidencias", "Válido"))) | AB29: =IF(AND(A29="", B29="", E29=""), "", TEXTJOIN("; ", TRUE, IF(OR(TRIM(A29&"")="", ISNUMBER(SEARCH("FALTA", A29))), "UPC faltante/inválido", ""), IF(AND(A29<>"", IFERROR(_xlfn.XMATCH(A29,$A$2:$A$653,0,1)<>_xlfn.XMATCH(A29,$A$2:$A$653,0,-1),FALSE)), "Código de barras duplicado", ""), IF(AND(E29<>"", COUNTIF($E$2:$E$653, E29)>1), "SKU duplicado", ""), IF(OR(J29="", J29=""), "[Aviso] División no capturada ()", IF(ISNA(MATCH(J29, Criterios!$A$123:$A$126, 0)), "División no válida", "")), IF(OR(K29="", K29=""), "[Aviso] Categoría no capturada ()", IF(ISNA(MATCH(K29, Criterios!$A$81:$A$120, 0)), "Categoría no válida", IF(AND(J29<>"", J29<>"", J29<>VLOOKUP(K29, Criterios!$A$81:$B$120, 2, FALSE)), "División no coincide con Categoría", ""))), IF(OR(L29="", L29=""), "[Aviso] Género no capturado ()", IF(ISNA(MATCH(L29, Criterios!$B$123:$B$127, 0)), "Género no válido", "")), IF(OR(N29="", N29=""), "[Aviso] Temporada no capturada ()", IF(ISNA(MATCH(N29, Criterios!$C$123:$C$128, 0)), "Temporada no válida", "")), IF(OR(O29="", O29=""), "[Aviso] Ciclo de vida no capturado ()", IF(ISNA(MATCH(O29, Criterios!$D$123:$D$124, 0)), "Ciclo de vida no válido", "")))) | AD29: 8 | AE29: REFLO ALMACEN (5) | AF29: 8 | AG29: Nuevo – NetSuite con existencia | AH29: Género no indicado en NetSuite; Físico total NetSuite 8 ≠ suma por ubicación 5 | Revisión 29/09/2026: Marca REFLO fuera de lista Criterios; Campos sin respaldo: L, N, O, Q; Auditoría NetSuite 30/09/2026: llenado desde NetSuite [Z] | Homologación G1522 06/10/2026: Validador Shopify: WB: precio con IVA no termina en 9 | AI29: No | AK29: G1522ProductosTodosloscamposSandboxResults894.xlsx: fila 45490 [X,Y]; G1522_Extraccion_Articulos_NetSuite_2026-09-30.xlsx: fila 37590 [Z] | AL29: 22.75
A30: 5056658700750 | B30: 79258 | C30: REFLO | D30: BOHABLA | E30: BOHABLA-XXL | F30: XXL | G30: XXL | H30: REFLO | I30: Playera tipo polo REFLO Bohai Black | J30: Ropa | K30: Playeras | M30: REFLO | P30: Negro | S30: 100% Poliéster reciclado | T30: Playera tipo polo de golf REFLO modelo Bohai en color Black, confeccionado con materiales reciclados. Estilo BOHABLA. | U30: China | V30: PZS | W30: 53101600 | X30: https://i.ibb.co/W5zf03J/BOHABLA.jpg | Y30: 22.75 | Z30: 1649 | AA30: =IF(AND(A30="", B30="", E30=""), "", IF(AB30="", "Válido", IF((LEN(AB30)-LEN(SUBSTITUTE(AB30,"; ","")))/2+1>(LEN(AB30)-LEN(SUBSTITUTE(AB30,"[Aviso]","")))/7, "Con Incidencias", "Válido"))) | AB30: =IF(AND(A30="", B30="", E30=""), "", TEXTJOIN("; ", TRUE, IF(OR(TRIM(A30&"")="", ISNUMBER(SEARCH("FALTA", A30))), "UPC faltante/inválido", ""), IF(AND(A30<>"", IFERROR(_xlfn.XMATCH(A30,$A$2:$A$653,0,1)<>_xlfn.XMATCH(A30,$A$2:$A$653,0,-1),FALSE)), "Código de barras duplicado", ""), IF(AND(E30<>"", COUNTIF($E$2:$E$653, E30)>1), "SKU duplicado", ""), IF(OR(J30="", J30=""), "[Aviso] División no capturada ()", IF(ISNA(MATCH(J30, Criterios!$A$123:$A$126, 0)), "División no válida", "")), IF(OR(K30="", K30=""), "[Aviso] Categoría no capturada ()", IF(ISNA(MATCH(K30, Criterios!$A$81:$A$120, 0)), "Categoría no válida", IF(AND(J30<>"", J30<>"", J30<>VLOOKUP(K30, Criterios!$A$81:$B$120, 2, FALSE)), "División no coincide con Categoría", ""))), IF(OR(L30="", L30=""), "[Aviso] Género no capturado ()", IF(ISNA(MATCH(L30, Criterios!$B$123:$B$127, 0)), "Género no válido", "")), IF(OR(N30="", N30=""), "[Aviso] Temporada no capturada ()", IF(ISNA(MATCH(N30, Criterios!$C$123:$C$128, 0)), "Temporada no válida", "")), IF(OR(O30="", O30=""), "[Aviso] Ciclo de vida no capturado ()", IF(ISNA(MATCH(O30, Criterios!$D$123:$D$124, 0)), "Ciclo de vida no válido", "")))) | AD30: 3 | AE30: REFLO ALMACEN (2) | AF30: 3 | AG30: Nuevo – NetSuite con existencia | AH30: Género no indicado en NetSuite; Físico total NetSuite 3 ≠ suma por ubicación 2 | Revisión 29/09/2026: Marca REFLO fuera de lista Criterios; Campos sin respaldo: L, N, O, Q; Auditoría NetSuite 30/09/2026: llenado desde NetSuite [Z] | Homologación G1522 06/10/2026: Validador Shopify: WB: precio con IVA no termina en 9 | AI30: No | AK30: G1522ProductosTodosloscamposSandboxResults894.xlsx: fila 45491 [X,Y]; G1522_Extraccion_Articulos_NetSuite_2026-09-30.xlsx: fila 37591 [Z] | AL30: 22.75
A31: 5056658700545 | B31: 79259 | C31: REFLO | D31: BOHAGRE | E31: BOHAGRE-M | F31: M | G31: M | H31: REFLO | I31: Playera tipo polo REFLO Bohai Green | J31: Ropa | K31: Playeras | M31: REFLO | P31: Verde | S31: 100% Poliéster reciclado | T31: Playera tipo polo de golf REFLO modelo Bohai en color Green, confeccionado con materiales reciclados. Estilo BOHAGRE. | U31: China | V31: PZS | W31: 53101600 | X31: https://i.ibb.co/KyVSC4J/BOHAGRE.jpg | Y31: 22.75 | Z31: 1649 | AA31: =IF(AND(A31="", B31="", E31=""), "", IF(AB31="", "Válido", IF((LEN(AB31)-LEN(SUBSTITUTE(AB31,"; ","")))/2+1>(LEN(AB31)-LEN(SUBSTITUTE(AB31,"[Aviso]","")))/7, "Con Incidencias", "Válido"))) | AB31: =IF(AND(A31="", B31="", E31=""), "", TEXTJOIN("; ", TRUE, IF(OR(TRIM(A31&"")="", ISNUMBER(SEARCH("FALTA", A31))), "UPC faltante/inválido", ""), IF(AND(A31<>"", IFERROR(_xlfn.XMATCH(A31,$A$2:$A$653,0,1)<>_xlfn.XMATCH(A31,$A$2:$A$653,0,-1),FALSE)), "Código de barras duplicado", ""), IF(AND(E31<>"", COUNTIF($E$2:$E$653, E31)>1), "SKU duplicado", ""), IF(OR(J31="", J31=""), "[Aviso] División no capturada ()", IF(ISNA(MATCH(J31, Criterios!$A$123:$A$126, 0)), "División no válida", "")), IF(OR(K31="", K31=""), "[Aviso] Categoría no capturada ()", IF(ISNA(MATCH(K31, Criterios!$A$81:$A$120, 0)), "Categoría no válida", IF(AND(J31<>"", J31<>"", J31<>VLOOKUP(K31, Criterios!$A$81:$B$120, 2, FALSE)), "División no coincide con Categoría", ""))), IF(OR(L31="", L31=""), "[Aviso] Género no capturado ()", IF(ISNA(MATCH(L31, Criterios!$B$123:$B$127, 0)), "Género no válido", "")), IF(OR(N31="", N31=""), "[Aviso] Temporada no capturada ()", IF(ISNA(MATCH(N31, Criterios!$C$123:$C$128, 0)), "Temporada no válida", "")), IF(OR(O31="", O31=""), "[Aviso] Ciclo de vida no capturado ()", IF(ISNA(MATCH(O31, Criterios!$D$123:$D$124, 0)), "Ciclo de vida no válido", "")))) | AD31: 0 | AF31: 0 | AG31: Nuevo – NetSuite sin existencia | AH31: Género no indicado en NetSuite | Revisión 29/09/2026: Marca REFLO fuera de lista Criterios; Campos sin respaldo: L, N, O, Q; Auditoría NetSuite 30/09/2026: llenado desde NetSuite [Z] | Homologación G1522 06/10/2026: Validador Shopify: WB: precio con IVA no termina en 9 | AI31: No | AK31: G1522ProductosTodosloscamposSandboxResults894.xlsx: fila 45495 [X,Y]; G1522_Extraccion_Articulos_NetSuite_2026-09-30.xlsx: fila 37592 [Z] | AL31: 22.75
A32: 5056658700552 | B32: 79260 | C32: REFLO | D32: BOHAGRE | E32: BOHAGRE-L | F32: L | G32: L | H32: REFLO | I32: Playera tipo polo REFLO Bohai Green | J32: Ropa | K32: Playeras | M32: REFLO | P32: Verde | S32: 100% Poliéster reciclado | T32: Playera tipo polo de golf REFLO modelo Bohai en color Green, confeccionado con materiales reciclados. Estilo BOHAGRE. | U32: China | V32: PZS | W32: 53101600 | X32: https://i.ibb.co/KyVSC4J/BOHAGRE.jpg | Y32: 22.75 | Z32: 1649 | AA32: =IF(AND(A32="", B32="", E32=""), "", IF(AB32="", "Válido", IF((LEN(AB32)-LEN(SUBSTITUTE(AB32,"; ","")))/2+1>(LEN(AB32)-LEN(SUBSTITUTE(AB32,"[Aviso]","")))/7, "Con Incidencias", "Válido"))) | AB32: =IF(AND(A32="", B32="", E32=""), "", TEXTJOIN("; ", TRUE, IF(OR(TRIM(A32&"")="", ISNUMBER(SEARCH("FALTA", A32))), "UPC faltante/inválido", ""), IF(AND(A32<>"", IFERROR(_xlfn.XMATCH(A32,$A$2:$A$653,0,1)<>_xlfn.XMATCH(A32,$A$2:$A$653,0,-1),FALSE)), "Código de barras duplicado", ""), IF(AND(E32<>"", COUNTIF($E$2:$E$653, E32)>1), "SKU duplicado", ""), IF(OR(J32="", J32=""), "[Aviso] División no capturada ()", IF(ISNA(MATCH(J32, Criterios!$A$123:$A$126, 0)), "División no válida", "")), IF(OR(K32="", K32=""), "[Aviso] Categoría no capturada ()", IF(ISNA(MATCH(K32, Criterios!$A$81:$A$120, 0)), "Categoría no válida", IF(AND(J32<>"", J32<>"", J32<>VLOOKUP(K32, Criterios!$A$81:$B$120, 2, FALSE)), "División no coincide con Categoría", ""))), IF(OR(L32="", L32=""), "[Aviso] Género no capturado ()", IF(ISNA(MATCH(L32, Criterios!$B$123:$B$127, 0)), "Género no válido", "")), IF(OR(N32="", N32=""), "[Aviso] Temporada no capturada ()", IF(ISNA(MATCH(N32, Criterios!$C$123:$C$128, 0)), "Temporada no válida", "")), IF(OR(O32="", O32=""), "[Aviso] Ciclo de vida no capturado ()", IF(ISNA(MATCH(O32, Criterios!$D$123:$D$124, 0)), "Ciclo de vida no válido", "")))) | AD32: 1 | AE32: REFLO ALMACEN (1) | AF32: 1 | AG32: Nuevo – NetSuite con existencia | AH32: Género no indicado en NetSuite | Revisión 29/09/2026: Marca REFLO fuera de lista Criterios; Campos sin respaldo: L, N, O, Q; Auditoría NetSuite 30/09/2026: llenado desde NetSuite [Z] | Homologación G1522 06/10/2026: Validador Shopify: WB: precio con IVA no termina en 9 | AI32: No | AK32: G1522ProductosTodosloscamposSandboxResults894.xlsx: fila 45496 [X,Y]; G1522_Extraccion_Articulos_NetSuite_2026-09-30.xlsx: fila 37593 [Z] | AL32: 22.75
A33: 5056658700569 | B33: 79261 | C33: REFLO | D33: BOHAGRE | E33: BOHAGRE-XL | F33: XL | G33: XL | H33: REFLO | I33: Playera tipo polo REFLO Bohai Green | J33: Ropa | K33: Playeras | M33: REFLO | P33: Verde | S33: 100% Poliéster reciclado | T33: Playera tipo polo de golf REFLO modelo Bohai en color Green, confeccionado con materiales reciclados. Estilo BOHAGRE. | U33: China | V33: PZS | W33: 53101600 | X33: https://i.ibb.co/KyVSC4J/BOHAGRE.jpg | Y33: 22.75 | Z33: 1649 | AA33: =IF(AND(A33="", B33="", E33=""), "", IF(AB33="", "Válido", IF((LEN(AB33)-LEN(SUBSTITUTE(AB33,"; ","")))/2+1>(LEN(AB33)-LEN(SUBSTITUTE(AB33,"[Aviso]","")))/7, "Con Incidencias", "Válido"))) | AB33: =IF(AND(A33="", B33="", E33=""), "", TEXTJOIN("; ", TRUE, IF(OR(TRIM(A33&"")="", ISNUMBER(SEARCH("FALTA", A33))), "UPC faltante/inválido", ""), IF(AND(A33<>"", IFERROR(_xlfn.XMATCH(A33,$A$2:$A$653,0,1)<>_xlfn.XMATCH(A33,$A$2:$A$653,0,-1),FALSE)), "Código de barras duplicado", ""), IF(AND(E33<>"", COUNTIF($E$2:$E$653, E33)>1), "SKU duplicado", ""), IF(OR(J33="", J33=""), "[Aviso] División no capturada ()", IF(ISNA(MATCH(J33, Criterios!$A$123:$A$126, 0)), "División no válida", "")), IF(OR(K33="", K33=""), "[Aviso] Categoría no capturada ()", IF(ISNA(MATCH(K33, Criterios!$A$81:$A$120, 0)), "Categoría no válida", IF(AND(J33<>"", J33<>"", J33<>VLOOKUP(K33, Criterios!$A$81:$B$120, 2, FALSE)), "División no coincide con Categoría", ""))), IF(OR(L33="", L33=""), "[Aviso] Género no capturado ()", IF(ISNA(MATCH(L33, Criterios!$B$123:$B$127, 0)), "Género no válido", "")), IF(OR(N33="", N33=""), "[Aviso] Temporada no capturada ()", IF(ISNA(MATCH(N33, Criterios!$C$123:$C$128, 0)), "Temporada no válida", "")), IF(OR(O33="", O33=""), "[Aviso] Ciclo de vida no capturado ()", IF(ISNA(MATCH(O33, Criterios!$D$123:$D$124, 0)), "Ciclo de vida no válido", "")))) | AD33: 9 | AE33: MUESTRAS REFLO (1); REFLO ALMACEN (6) | AF33: 8 | AG33: Nuevo – NetSuite con existencia | AH33: Género no indicado en NetSuite; Físico total NetSuite 9 ≠ suma por ubicación 7 | Revisión 29/09/2026: Marca REFLO fuera de lista Criterios; Campos sin respaldo: L, N, O, Q; Auditoría NetSuite 30/09/2026: llenado desde NetSuite [Z] | Homologación G1522 06/10/2026: Validador Shopify: WB: precio con IVA no termina en 9 | AI33: No | AK33: G1522ProductosTodosloscamposSandboxResults894.xlsx: fila 45497 [X,Y]; G1522_Extraccion_Articulos_NetSuite_2026-09-30.xlsx: fila 37594 [Z] | AL33: 22.75
A34: 5056658700576 | B34: 79262 | C34: REFLO | D34: BOHAGRE | E34: BOHAGRE-XXL | F34: XXL | G34: XXL | H34: REFLO | I34: Playera tipo polo REFLO Bohai Green | J34: Ropa | K34: Playeras | M34: REFLO | P34: Verde | S34: 100% Poliéster reciclado | T34: Playera tipo polo de golf REFLO modelo Bohai en color Green, confeccionado con materiales reciclados. Estilo BOHAGRE. | U34: China | V34: PZS | W34: 53101600 | X34: https://i.ibb.co/KyVSC4J/BOHAGRE.jpg | Y34: 22.75 | Z34: 1649 | AA34: =IF(AND(A34="", B34="", E34=""), "", IF(AB34="", "Válido", IF((LEN(AB34)-LEN(SUBSTITUTE(AB34,"; ","")))/2+1>(LEN(AB34)-LEN(SUBSTITUTE(AB34,"[Aviso]","")))/7, "Con Incidencias", "Válido"))) | AB34: =IF(AND(A34="", B34="", E34=""), "", TEXTJOIN("; ", TRUE, IF(OR(TRIM(A34&"")="", ISNUMBER(SEARCH("FALTA", A34))), "UPC faltante/inválido", ""), IF(AND(A34<>"", IFERROR(_xlfn.XMATCH(A34,$A$2:$A$653,0,1)<>_xlfn.XMATCH(A34,$A$2:$A$653,0,-1),FALSE)), "Código de barras duplicado", ""), IF(AND(E34<>"", COUNTIF($E$2:$E$653, E34)>1), "SKU duplicado", ""), IF(OR(J34="", J34=""), "[Aviso] División no capturada ()", IF(ISNA(MATCH(J34, Criterios!$A$123:$A$126, 0)), "División no válida", "")), IF(OR(K34="", K34=""), "[Aviso] Categoría no capturada ()", IF(ISNA(MATCH(K34, Criterios!$A$81:$A$120, 0)), "Categoría no válida", IF(AND(J34<>"", J34<>"", J34<>VLOOKUP(K34, Criterios!$A$81:$B$120, 2, FALSE)), "División no coincide con Categoría", ""))), IF(OR(L34="", L34=""), "[Aviso] Género no capturado ()", IF(ISNA(MATCH(L34, Criterios!$B$123:$B$127, 0)), "Género no válido", "")), IF(OR(N34="", N34=""), "[Aviso] Temporada no capturada ()", IF(ISNA(MATCH(N34, Criterios!$C$123:$C$128, 0)), "Temporada no válida", "")), IF(OR(O34="", O34=""), "[Aviso] Ciclo de vida no capturado ()", IF(ISNA(MATCH(O34, Criterios!$D$123:$D$124, 0)), "Ciclo de vida no válido", "")))) | AD34: 4 | AE34: REFLO ALMACEN (4) | AF34: 5 | AG34: Nuevo – NetSuite con existencia | AH34: Género no indicado en NetSuite; Físico total NetSuite 4 ≠ suma por ubicación 3 | Revisión 29/09/2026: Marca REFLO fuera de lista Criterios; Campos sin respaldo: L, N, O, Q; Auditoría NetSuite 30/09/2026: llenado desde NetSuite [Z] | Homologación G1522 06/10/2026: Validador Shopify: WB: precio con IVA no termina en 9 | AI34: Sí | AJ34: CONSIGNA REFLO (-1) | AK34: G1522ProductosTodosloscamposSandboxResults894.xlsx: fila 45498 [X,Y]; G1522_Extraccion_Articulos_NetSuite_2026-09-30.xlsx: fila 37595 [Z] | AL34: 22.75
A35: 5056658700675 | B35: 79263 | C35: REFLO | D35: BOHAWHI | E35: BOHAWHI-L | F35: L | G35: L | H35: REFLO | I35: Playera tipo polo REFLO Bohai White | J35: Ropa | K35: Playeras | M35: REFLO | P35: Blanco | S35: 100% Poliéster reciclado | T35: Playera tipo polo de golf REFLO modelo Bohai en color White, confeccionado con materiales reciclados. Estilo BOHAWHI. | U35: China | V35: PZS | W35: 53101600 | X35: https://i.ibb.co/9H5D20G/BOHAWHI.jpg | Y35: 22.75 | Z35: 1649 | AA35: =IF(AND(A35="", B35="", E35=""), "", IF(AB35="", "Válido", IF((LEN(AB35)-LEN(SUBSTITUTE(AB35,"; ","")))/2+1>(LEN(AB35)-LEN(SUBSTITUTE(AB35,"[Aviso]","")))/7, "Con Incidencias", "Válido"))) | AB35: =IF(AND(A35="", B35="", E35=""), "", TEXTJOIN("; ", TRUE, IF(OR(TRIM(A35&"")="", ISNUMBER(SEARCH("FALTA", A35))), "UPC faltante/inválido", ""), IF(AND(A35<>"", IFERROR(_xlfn.XMATCH(A35,$A$2:$A$653,0,1)<>_xlfn.XMATCH(A35,$A$2:$A$653,0,-1),FALSE)), "Código de barras duplicado", ""), IF(AND(E35<>"", COUNTIF($E$2:$E$653, E35)>1), "SKU duplicado", ""), IF(OR(J35="", J35=""), "[Aviso] División no capturada ()", IF(ISNA(MATCH(J35, Criterios!$A$123:$A$126, 0)), "División no válida", "")), IF(OR(K35="", K35=""), "[Aviso] Categoría no capturada ()", IF(ISNA(MATCH(K35, Criterios!$A$81:$A$120, 0)), "Categoría no válida", IF(AND(J35<>"", J35<>"", J35<>VLOOKUP(K35, Criterios!$A$81:$B$120, 2, FALSE)), "División no coincide con Categoría", ""))), IF(OR(L35="", L35=""), "[Aviso] Género no capturado ()", IF(ISNA(MATCH(L35, Criterios!$B$123:$B$127, 0)), "Género no válido", "")), IF(OR(N35="", N35=""), "[Aviso] Temporada no capturada ()", IF(ISNA(MATCH(N35, Criterios!$C$123:$C$128, 0)), "Temporada no válida", "")), IF(OR(O35="", O35=""), "[Aviso] Ciclo de vida no capturado ()", IF(ISNA(MATCH(O35, Criterios!$D$123:$D$124, 0)), "Ciclo de vida no válido", "")))) | AD35: 3 | AE35: REFLO ALMACEN (1); MUESTRAS REFLO (1) | AF35: 2 | AG35: Nuevo – NetSuite con existencia | AH35: Género no indicado en NetSuite; Físico total NetSuite 3 ≠ suma por ubicación 2 | Revisión 29/09/2026: Marca REFLO fuera de lista Criterios; Campos sin respaldo: L, N, O, Q; Auditoría NetSuite 30/09/2026: llenado desde NetSuite [Z] | Homologación G1522 06/10/2026: Validador Shopify: WB: precio con IVA no termina en 9 | AI35: No | AK35: G1522ProductosTodosloscamposSandboxResults894.xlsx: fila 45504 [X,Y]; G1522_Extraccion_Articulos_NetSuite_2026-09-30.xlsx: fila 37596 [Z] | AL35: 22.75
A36: 5056658700682 | B36: 79264 | C36: REFLO | D36: BOHAWHI | E36: BOHAWHI-XL | F36: XL | G36: XL | H36: REFLO | I36: Playera tipo polo REFLO Bohai White | J36: Ropa | K36: Playeras | M36: REFLO | P36: Blanco | S36: 100% Poliéster reciclado | T36: Playera tipo polo de golf REFLO modelo Bohai en color White, confeccionado con materiales reciclados. Estilo BOHAWHI. | U36: China | V36: PZS | W36: 53101600 | X36: https://i.ibb.co/9H5D20G/BOHAWHI.jpg | Y36: 22.75 | Z36: 1649 | AA36: =IF(AND(A36="", B36="", E36=""), "", IF(AB36="", "Válido", IF((LEN(AB36)-LEN(SUBSTITUTE(AB36,"; ","")))/2+1>(LEN(AB36)-LEN(SUBSTITUTE(AB36,"[Aviso]","")))/7, "Con Incidencias", "Válido"))) | AB36: =IF(AND(A36="", B36="", E36=""), "", TEXTJOIN("; ", TRUE, IF(OR(TRIM(A36&"")="", ISNUMBER(SEARCH("FALTA", A36))), "UPC faltante/inválido", ""), IF(AND(A36<>"", IFERROR(_xlfn.XMATCH(A36,$A$2:$A$653,0,1)<>_xlfn.XMATCH(A36,$A$2:$A$653,0,-1),FALSE)), "Código de barras duplicado", ""), IF(AND(E36<>"", COUNTIF($E$2:$E$653, E36)>1), "SKU duplicado", ""), IF(OR(J36="", J36=""), "[Aviso] División no capturada ()", IF(ISNA(MATCH(J36, Criterios!$A$123:$A$126, 0)), "División no válida", "")), IF(OR(K36="", K36=""), "[Aviso] Categoría no capturada ()", IF(ISNA(MATCH(K36, Criterios!$A$81:$A$120, 0)), "Categoría no válida", IF(AND(J36<>"", J36<>"", J36<>VLOOKUP(K36, Criterios!$A$81:$B$120, 2, FALSE)), "División no coincide con Categoría", ""))), IF(OR(L36="", L36=""), "[Aviso] Género no capturado ()", IF(ISNA(MATCH(L36, Criterios!$B$123:$B$127, 0)), "Género no válido", "")), IF(OR(N36="", N36=""), "[Aviso] Temporada no capturada ()", IF(ISNA(MATCH(N36, Criterios!$C$123:$C$128, 0)), "Temporada no válida", "")), IF(OR(O36="", O36=""), "[Aviso] Ciclo de vida no capturado ()", IF(ISNA(MATCH(O36, Criterios!$D$123:$D$124, 0)), "Ciclo de vida no válido", "")))) | AD36: 2 | AE36: REFLO ALMACEN (3) | AF36: 3 | AG36: Nuevo – NetSuite con existencia | AH36: Género no indicado en NetSuite | Revisión 29/09/2026: Marca REFLO fuera de lista Criterios; Campos sin respaldo: L, N, O, Q; Auditoría NetSuite 30/09/2026: llenado desde NetSuite [Z] | Homologación G1522 06/10/2026: Validador Shopify: WB: precio con IVA no termina en 9 | AI36: Sí | AJ36: CONSIGNA REFLO (-1) | AK36: G1522ProductosTodosloscamposSandboxResults894.xlsx: fila 45505 [X,Y]; G1522_Extraccion_Articulos_NetSuite_2026-09-30.xlsx: fila 37597 [Z] | AL36: 22.75
A37: 5056658700606 | B37: 79265 | C37: REFLO | D37: BOHAYEL | E37: BOHAYEL-M | F37: M | G37: M | H37: REFLO | I37: Playera tipo polo REFLO Bohai Yellow | J37: Ropa | K37: Playeras | M37: REFLO | P37: Amarillo | S37: 100% Poliéster reciclado | T37: Playera tipo polo de golf REFLO modelo Bohai en color Yellow, confeccionado con materiales reciclados. Estilo BOHAYEL. | U37: China | V37: PZS | W37: 53101600 | X37: https://i.ibb.co/r4swMFx/BOHAYEL.jpg | Y37: 22.75 | Z37: 1649 | AA37: =IF(AND(A37="", B37="", E37=""), "", IF(AB37="", "Válido", IF((LEN(AB37)-LEN(SUBSTITUTE(AB37,"; ","")))/2+1>(LEN(AB37)-LEN(SUBSTITUTE(AB37,"[Aviso]","")))/7, "Con Incidencias", "Válido"))) | AB37: =IF(AND(A37="", B37="", E37=""), "", TEXTJOIN("; ", TRUE, IF(OR(TRIM(A37&"")="", ISNUMBER(SEARCH("FALTA", A37))), "UPC faltante/inválido", ""), IF(AND(A37<>"", IFERROR(_xlfn.XMATCH(A37,$A$2:$A$653,0,1)<>_xlfn.XMATCH(A37,$A$2:$A$653,0,-1),FALSE)), "Código de barras duplicado", ""), IF(AND(E37<>"", COUNTIF($E$2:$E$653, E37)>1), "SKU duplicado", ""), IF(OR(J37="", J37=""), "[Aviso] División no capturada ()", IF(ISNA(MATCH(J37, Criterios!$A$123:$A$126, 0)), "División no válida", "")), IF(OR(K37="", K37=""), "[Aviso] Categoría no capturada ()", IF(ISNA(MATCH(K37, Criterios!$A$81:$A$120, 0)), "Categoría no válida", IF(AND(J37<>"", J37<>"", J37<>VLOOKUP(K37, Criterios!$A$81:$B$120, 2, FALSE)), "División no coincide con Categoría", ""))), IF(OR(L37="", L37=""), "[Aviso] Género no capturado ()", IF(ISNA(MATCH(L37, Criterios!$B$123:$B$127, 0)), "Género no válido", "")), IF(OR(N37="", N37=""), "[Aviso] Temporada no capturada ()", IF(ISNA(MATCH(N37, Criterios!$C$123:$C$128, 0)), "Temporada no válida", "")), IF(OR(O37="", O37=""), "[Aviso] Ciclo de vida no capturado ()", IF(ISNA(MATCH(O37, Criterios!$D$123:$D$124, 0)), "Ciclo de vida no válido", "")))) | AD37: 4 | AE37: REFLO ALMACEN (3); CONSIGNA REFLO (1) | AF37: 4 | AG37: Nuevo – NetSuite con existencia | AH37: Género no indicado en NetSuite | Revisión 29/09/2026: Marca REFLO fuera de lista Criterios; Campos sin respaldo: L, N, O, Q; Auditoría NetSuite 30/09/2026: llenado desde NetSuite [Z] | Homologación G1522 06/10/2026: Validador Shopify: WB: precio con IVA no termina en 9 | AI37: No | AK37: G1522ProductosTodosloscamposSandboxResults894.xlsx: fila 45507 [X,Y]; G1522_Extraccion_Articulos_NetSuite_2026-09-30.xlsx: fila 37598 [Z] | AL37: 22.75
A38: 5056658700613 | B38: 79266 | C38: REFLO | D38: BOHAYEL | E38: BOHAYEL-L | F38: L | G38: L | H38: REFLO | I38: Playera tipo polo REFLO Bohai Yellow | J38: Ropa | K38: Playeras | M38: REFLO | P38: Amarillo | S38: 100% Poliéster reciclado | T38: Playera tipo polo de golf REFLO modelo Bohai en color Yellow, confeccionado con materiales reciclados. Estilo BOHAYEL. | U38: China | V38: PZS | W38: 53101600 | X38: https://i.ibb.co/r4swMFx/BOHAYEL.jpg | Y38: 22.75 | Z38: 1649 | AA38: =IF(AND(A38="", B38="", E38=""), "", IF(AB38="", "Válido", IF((LEN(AB38)-LEN(SUBSTITUTE(AB38,"; ","")))/2+1>(LEN(AB38)-LEN(SUBSTITUTE(AB38,"[Aviso]","")))/7, "Con Incidencias", "Válido"))) | AB38: =IF(AND(A38="", B38="", E38=""), "", TEXTJOIN("; ", TRUE, IF(OR(TRIM(A38&"")="", ISNUMBER(SEARCH("FALTA", A38))), "UPC faltante/inválido", ""), IF(AND(A38<>"", IFERROR(_xlfn.XMATCH(A38,$A$2:$A$653,0,1)<>_xlfn.XMATCH(A38,$A$2:$A$653,0,-1),FALSE)), "Código de barras duplicado", ""), IF(AND(E38<>"", COUNTIF($E$2:$E$653, E38)>1), "SKU duplicado", ""), IF(OR(J38="", J38=""), "[Aviso] División no capturada ()", IF(ISNA(MATCH(J38, Criterios!$A$123:$A$126, 0)), "División no válida", "")), IF(OR(K38="", K38=""), "[Aviso] Categoría no capturada ()", IF(ISNA(MATCH(K38, Criterios!$A$81:$A$120, 0)), "Categoría no válida", IF(AND(J38<>"", J38<>"", J38<>VLOOKUP(K38, Criterios!$A$81:$B$120, 2, FALSE)), "División no coincide con Categoría", ""))), IF(OR(L38="", L38=""), "[Aviso] Género no capturado ()", IF(ISNA(MATCH(L38, Criterios!$B$123:$B$127, 0)), "Género no válido", "")), IF(OR(N38="", N38=""), "[Aviso] Temporada no capturada ()", IF(ISNA(MATCH(N38, Criterios!$C$123:$C$128, 0)), "Temporada no válida", "")), IF(OR(O38="", O38=""), "[Aviso] Ciclo de vida no capturado ()", IF(ISNA(MATCH(O38, Criterios!$D$123:$D$124, 0)), "Ciclo de vida no válido", "")))) | AD38: 9 | AE38: CONSIGNA REFLO (1); MUESTRAS REFLO (1); REFLO ALMACEN (4) | AF38: 8 | AG38: Nuevo – NetSuite con existencia | AH38: Género no indicado en NetSuite; Físico total NetSuite 9 ≠ suma por ubicación 6 | Revisión 29/09/2026: Marca REFLO fuera de lista Criterios; Campos sin respaldo: L, N, O, Q; Auditoría NetSuite 30/09/2026: llenado desde NetSuite [Z] | Homologación G1522 06/10/2026: Validador Shopify: WB: precio con IVA no termina en 9 | AI38: No | AK38: G1522ProductosTodosloscamposSandboxResults894.xlsx: fila 45508 [X,Y]; G1522_Extraccion_Articulos_NetSuite_2026-09-30.xlsx: fila 37599 [Z] | AL38: 22.75
A39: 5056658700620 | B39: 79267 | C39: REFLO | D39: BOHAYEL | E39: BOHAYEL-XL | F39: XL | G39: XL | H39: REFLO | I39: Playera tipo polo REFLO Bohai Yellow | J39: Ropa | K39: Playeras | M39: REFLO | P39: Amarillo | S39: 100% Poliéster reciclado | T39: Playera tipo polo de golf REFLO modelo Bohai en color Yellow, confeccionado con materiales reciclados. Estilo BOHAYEL. | U39: China | V39: PZS | W39: 53101600 | X39: https://i.ibb.co/r4swMFx/BOHAYEL.jpg | Y39: 22.75 | Z39: 1649 | AA39: =IF(AND(A39="", B39="", E39=""), "", IF(AB39="", "Válido", IF((LEN(AB39)-LEN(SUBSTITUTE(AB39,"; ","")))/2+1>(LEN(AB39)-LEN(SUBSTITUTE(AB39,"[Aviso]","")))/7, "Con Incidencias", "Válido"))) | AB39: =IF(AND(A39="", B39="", E39=""), "", TEXTJOIN("; ", TRUE, IF(OR(TRIM(A39&"")="", ISNUMBER(SEARCH("FALTA", A39))), "UPC faltante/inválido", ""), IF(AND(A39<>"", IFERROR(_xlfn.XMATCH(A39,$A$2:$A$653,0,1)<>_xlfn.XMATCH(A39,$A$2:$A$653,0,-1),FALSE)), "Código de barras duplicado", ""), IF(AND(E39<>"", COUNTIF($E$2:$E$653, E39)>1), "SKU duplicado", ""), IF(OR(J39="", J39=""), "[Aviso] División no capturada ()", IF(ISNA(MATCH(J39, Criterios!$A$123:$A$126, 0)), "División no válida", "")), IF(OR(K39="", K39=""), "[Aviso] Categoría no capturada ()", IF(ISNA(MATCH(K39, Criterios!$A$81:$A$120, 0)), "Categoría no válida", IF(AND(J39<>"", J39<>"", J39<>VLOOKUP(K39, Criterios!$A$81:$B$120, 2, FALSE)), "División no coincide con Categoría", ""))), IF(OR(L39="", L39=""), "[Aviso] Género no capturado ()", IF(ISNA(MATCH(L39, Criterios!$B$123:$B$127, 0)), "Género no válido", "")), IF(OR(N39="", N39=""), "[Aviso] Temporada no capturada ()", IF(ISNA(MATCH(N39, Criterios!$C$123:$C$128, 0)), "Temporada no válida", "")), IF(OR(O39="", O39=""), "[Aviso] Ciclo de vida no capturado ()", IF(ISNA(MATCH(O39, Criterios!$D$123:$D$124, 0)), "Ciclo de vida no válido", "")))) | AD39: 10 | AE39: REFLO ALMACEN (6) | AF39: 10 | AG39: Nuevo – NetSuite con existencia | AH39: Género no indicado en NetSuite; Físico total NetSuite 10 ≠ suma por ubicación 6 | Revisión 29/09/2026: Marca REFLO fuera de lista Criterios; Campos sin respaldo: L, N, O, Q; Auditoría NetSuite 30/09/2026: llenado desde NetSuite [Z] | Homologación G1522 06/10/2026: Validador Shopify: WB: precio con IVA no termina en 9 | AI39: No | AK39: G1522ProductosTodosloscamposSandboxResults894.xlsx: fila 45509 [X,Y]; G1522_Extraccion_Articulos_NetSuite_2026-09-30.xlsx: fila 37600 [Z] | AL39: 22.75
A40: 5056658700637 | B40: 79268 | C40: REFLO | D40: BOHAYEL | E40: BOHAYEL-XXL | F40: XXL | G40: XXL | H40: REFLO | I40: Playera tipo polo REFLO Bohai Yellow | J40: Ropa | K40: Playeras | M40: REFLO | P40: Amarillo | S40: 100% Poliéster reciclado | T40: Playera tipo polo de golf REFLO modelo Bohai en color Yellow, confeccionado con materiales reciclados. Estilo BOHAYEL. | U40: China | V40: PZS | W40: 53101600 | X40: https://i.ibb.co/r4swMFx/BOHAYEL.jpg | Y40: 22.75 | Z40: 1649 | AA40: =IF(AND(A40="", B40="", E40=""), "", IF(AB40="", "Válido", IF((LEN(AB40)-LEN(SUBSTITUTE(AB40,"; ","")))/2+1>(LEN(AB40)-LEN(SUBSTITUTE(AB40,"[Aviso]","")))/7, "Con Incidencias", "Válido"))) | AB40: =IF(AND(A40="", B40="", E40=""), "", TEXTJOIN("; ", TRUE, IF(OR(TRIM(A40&"")="", ISNUMBER(SEARCH("FALTA", A40))), "UPC faltante/inválido", ""), IF(AND(A40<>"", IFERROR(_xlfn.XMATCH(A40,$A$2:$A$653,0,1)<>_xlfn.XMATCH(A40,$A$2:$A$653,0,-1),FALSE)), "Código de barras duplicado", ""), IF(AND(E40<>"", COUNTIF($E$2:$E$653, E40)>1), "SKU duplicado", ""), IF(OR(J40="", J40=""), "[Aviso] División no capturada ()", IF(ISNA(MATCH(J40, Criterios!$A$123:$A$126, 0)), "División no válida", "")), IF(OR(K40="", K40=""), "[Aviso] Categoría no capturada ()", IF(ISNA(MATCH(K40, Criterios!$A$81:$A$120, 0)), "Categoría no válida", IF(AND(J40<>"", J40<>"", J40<>VLOOKUP(K40, Criterios!$A$81:$B$120, 2, FALSE)), "División no coincide con Categoría", ""))), IF(OR(L40="", L40=""), "[Aviso] Género no capturado ()", IF(ISNA(MATCH(L40, Criterios!$B$123:$B$127, 0)), "Género no válido", "")), IF(OR(N40="", N40=""), "[Aviso] Temporada no capturada ()", IF(ISNA(MATCH(N40, Criterios!$C$123:$C$128, 0)), "Temporada no válida", "")), IF(OR(O40="", O40=""), "[Aviso] Ciclo de vida no capturado ()", IF(ISNA(MATCH(O40, Criterios!$D$123:$D$124, 0)), "Ciclo de vida no válido", "")))) | AD40: 5 | AE40: REFLO ALMACEN (3) | AF40: 5 | AG40: Nuevo – NetSuite con existencia | AH40: Género no indicado en NetSuite; Físico total NetSuite 5 ≠ suma por ubicación 3 | Revisión 29/09/2026: Marca REFLO fuera de lista Criterios; Campos sin respaldo: L, N, O, Q; Auditoría NetSuite 30/09/2026: llenado desde NetSuite [Z] | Homologación G1522 06/10/2026: Validador Shopify: WB: precio con IVA no termina en 9 | AI40: No | AK40: G1522ProductosTodosloscamposSandboxResults894.xlsx: fila 45510 [X,Y]; G1522_Extraccion_Articulos_NetSuite_2026-09-30.xlsx: fila 37601 [Z] | AL40: 22.75
A41: 5056658702310 | B41: 79269 | C41: REFLO | D41: BOHCOR | E41: BOHCOR-M | F41: M | G41: M | H41: REFLO | I41: Playera tipo polo REFLO Bohai 2.0 Coronet Blue | J41: Ropa | K41: Playeras | M41: REFLO | P41: Azul | S41: 100% Poliéster reciclado | T41: Playera tipo polo de golf REFLO modelo Bohai 2.0 en color Coronet Blue, confeccionado con materiales reciclados. Estilo BOHCOR. | U41: China | V41: PZS | W41: 53101600 | X41: https://i.ibb.co/ctWjPwY/BOHCOR.jpg | Y41: 22.75 | Z41: 1649 | AA41: =IF(AND(A41="", B41="", E41=""), "", IF(AB41="", "Válido", IF((LEN(AB41)-LEN(SUBSTITUTE(AB41,"; ","")))/2+1>(LEN(AB41)-LEN(SUBSTITUTE(AB41,"[Aviso]","")))/7, "Con Incidencias", "Válido"))) | AB41: =IF(AND(A41="", B41="", E41=""), "", TEXTJOIN("; ", TRUE, IF(OR(TRIM(A41&"")="", ISNUMBER(SEARCH("FALTA", A41))), "UPC faltante/inválido", ""), IF(AND(A41<>"", IFERROR(_xlfn.XMATCH(A41,$A$2:$A$653,0,1)<>_xlfn.XMATCH(A41,$A$2:$A$653,0,-1),FALSE)), "Código de barras duplicado", ""), IF(AND(E41<>"", COUNTIF($E$2:$E$653, E41)>1), "SKU duplicado", ""), IF(OR(J41="", J41=""), "[Aviso] División no capturada ()", IF(ISNA(MATCH(J41, Criterios!$A$123:$A$126, 0)), "División no válida", "")), IF(OR(K41="", K41=""), "[Aviso] Categoría no capturada ()", IF(ISNA(MATCH(K41, Criterios!$A$81:$A$120, 0)), "Categoría no válida", IF(AND(J41<>"", J41<>"", J41<>VLOOKUP(K41, Criterios!$A$81:$B$120, 2, FALSE)), "División no coincide con Categoría", ""))), IF(OR(L41="", L41=""), "[Aviso] Género no capturado ()", IF(ISNA(MATCH(L41, Criterios!$B$123:$B$127, 0)), "Género no válido", "")), IF(OR(N41="", N41=""), "[Aviso] Temporada no capturada ()", IF(ISNA(MATCH(N41, Criterios!$C$123:$C$128, 0)), "Temporada no válida", "")), IF(OR(O41="", O41=""), "[Aviso] Ciclo de vida no capturado ()", IF(ISNA(MATCH(O41, Criterios!$D$123:$D$124, 0)), "Ciclo de vida no válido", "")))) | AD41: 4 | AE41: REFLO ALMACEN (3) | AF41: 4 | AG41: Nuevo – NetSuite con existencia | AH41: Género no indicado en NetSuite; Físico total NetSuite 4 ≠ suma por ubicación 3 | Revisión 29/09/2026: Marca REFLO fuera de lista Criterios; Campos sin respaldo: L, N, O, Q; Auditoría NetSuite 30/09/2026: llenado desde NetSuite [Z] | Homologación G1522 06/10/2026: Validador Shopify: WB: precio con IVA no termina en 9 | AI41: No | AK41: G1522ProductosTodosloscamposSandboxResults894.xlsx: fila 45463 [X,Y]; G1522_Extraccion_Articulos_NetSuite_2026-09-30.xlsx: fila 37602 [Z] | AL41: 22.75
A42: 5056658702327 | B42: 79270 | C42: REFLO | D42: BOHCOR | E42: BOHCOR-L | F42: L | G42: L | H42: REFLO | I42: Playera tipo polo REFLO Bohai 2.0 Coronet Blue | J42: Ropa | K42: Playeras | M42: REFLO | P42: Azul | S42: 100% Poliéster reciclado | T42: Playera tipo polo de golf REFLO modelo Bohai 2.0 en color Coronet Blue, confeccionado con materiales reciclados. Estilo BOHCOR. | U42: China | V42: PZS | W42: 53101600 | X42: https://i.ibb.co/ctWjPwY/BOHCOR.jpg | Y42: 22.75 | Z42: 1649 | AA42: =IF(AND(A42="", B42="", E42=""), "", IF(AB42="", "Válido", IF((LEN(AB42)-LEN(SUBSTITUTE(AB42,"; ","")))/2+1>(LEN(AB42)-LEN(SUBSTITUTE(AB42,"[Aviso]","")))/7, "Con Incidencias", "Válido"))) | AB42: =IF(AND(A42="", B42="", E42=""), "", TEXTJOIN("; ", TRUE, IF(OR(TRIM(A42&"")="", ISNUMBER(SEARCH("FALTA", A42))), "UPC faltante/inválido", ""), IF(AND(A42<>"", IFERROR(_xlfn.XMATCH(A42,$A$2:$A$653,0,1)<>_xlfn.XMATCH(A42,$A$2:$A$653,0,-1),FALSE)), "Código de barras duplicado", ""), IF(AND(E42<>"", COUNTIF($E$2:$E$653, E42)>1), "SKU duplicado", ""), IF(OR(J42="", J42=""), "[Aviso] División no capturada ()", IF(ISNA(MATCH(J42, Criterios!$A$123:$A$126, 0)), "División no válida", "")), IF(OR(K42="", K42=""), "[Aviso] Categoría no capturada ()", IF(ISNA(MATCH(K42, Criterios!$A$81:$A$120, 0)), "Categoría no válida", IF(AND(J42<>"", J42<>"", J42<>VLOOKUP(K42, Criterios!$A$81:$B$120, 2, FALSE)), "División no coincide con Categoría", ""))), IF(OR(L42="", L42=""), "[Aviso] Género no capturado ()", IF(ISNA(MATCH(L42, Criterios!$B$123:$B$127, 0)), "Género no válido", "")), IF(OR(N42="", N42=""), "[Aviso] Temporada no capturada ()", IF(ISNA(MATCH(N42, Criterios!$C$123:$C$128, 0)), "Temporada no válida", "")), IF(OR(O42="", O42=""), "[Aviso] Ciclo de vida no capturado ()", IF(ISNA(MATCH(O42, Criterios!$D$123:$D$124, 0)), "Ciclo de vida no válido", "")))) | AD42: 5 | AE42: REFLO ALMACEN (2); CONSIGNA REFLO (1); MUESTRAS REFLO (1) | AF42: 4 | AG42: Nuevo – NetSuite con existencia | AH42: Género no indicado en NetSuite; Físico total NetSuite 5 ≠ suma por ubicación 4 | Revisión 29/09/2026: Marca REFLO fuera de lista Criterios; Campos sin respaldo: L, N, O, Q; Auditoría NetSuite 30/09/2026: llenado desde NetSuite [Z] | Homologación G1522 06/10/2026: Validador Shopify: WB: precio con IVA no termina en 9 | AI42: No | AK42: G1522ProductosTodosloscamposSandboxResults894.xlsx: fila 45464 [X,Y]; G1522_Extraccion_Articulos_NetSuite_2026-09-30.xlsx: fila 37603 [Z] | AL42: 22.75
A43: 5056658702334 | B43: 79271 | C43: REFLO | D43: BOHCOR | E43: BOHCOR-XL | F43: XL | G43: XL | H43: REFLO | I43: Playera tipo polo REFLO Bohai 2.0 Coronet Blue | J43: Ropa | K43: Playeras | M43: REFLO | P43: Azul | S43: 100% Poliéster reciclado | T43: Playera tipo polo de golf REFLO modelo Bohai 2.0 en color Coronet Blue, confeccionado con materiales reciclados. Estilo BOHCOR. | U43: China | V43: PZS | W43: 53101600 | X43: https://i.ibb.co/ctWjPwY/BOHCOR.jpg | Y43: 22.75 | Z43: 1649 | AA43: =IF(AND(A43="", B43="", E43=""), "", IF(AB43="", "Válido", IF((LEN(AB43)-LEN(SUBSTITUTE(AB43,"; ","")))/2+1>(LEN(AB43)-LEN(SUBSTITUTE(AB43,"[Aviso]","")))/7, "Con Incidencias", "Válido"))) | AB43: =IF(AND(A43="", B43="", E43=""), "", TEXTJOIN("; ", TRUE, IF(OR(TRIM(A43&"")="", ISNUMBER(SEARCH("FALTA", A43))), "UPC faltante/inválido", ""), IF(AND(A43<>"", IFERROR(_xlfn.XMATCH(A43,$A$2:$A$653,0,1)<>_xlfn.XMATCH(A43,$A$2:$A$653,0,-1),FALSE)), "Código de barras duplicado", ""), IF(AND(E43<>"", COUNTIF($E$2:$E$653, E43)>1), "SKU duplicado", ""), IF(OR(J43="", J43=""), "[Aviso] División no capturada ()", IF(ISNA(MATCH(J43, Criterios!$A$123:$A$126, 0)), "División no válida", "")), IF(OR(K43="", K43=""), "[Aviso] Categoría no capturada ()", IF(ISNA(MATCH(K43, Criterios!$A$81:$A$120, 0)), "Categoría no válida", IF(AND(J43<>"", J43<>"", J43<>VLOOKUP(K43, Criterios!$A$81:$B$120, 2, FALSE)), "División no coincide con Categoría", ""))), IF(OR(L43="", L43=""), "[Aviso] Género no capturado ()", IF(ISNA(MATCH(L43, Criterios!$B$123:$B$127, 0)), "Género no válido", "")), IF(OR(N43="", N43=""), "[Aviso] Temporada no capturada ()", IF(ISNA(MATCH(N43, Criterios!$C$123:$C$128, 0)), "Temporada no válida", "")), IF(OR(O43="", O43=""), "[Aviso] Ciclo de vida no capturado ()", IF(ISNA(MATCH(O43, Criterios!$D$123:$D$124, 0)), "Ciclo de vida no válido", "")))) | AD43: 6 | AE43: REFLO ALMACEN (5) | AF43: 6 | AG43: Nuevo – NetSuite con existencia | AH43: Género no indicado en NetSuite; Físico total NetSuite 6 ≠ suma por ubicación 5 | Revisión 29/09/2026: Marca REFLO fuera de lista Criterios; Campos sin respaldo: L, N, O, Q; Auditoría NetSuite 30/09/2026: llenado desde NetSuite [Z] | Homologación G1522 06/10/2026: Validador Shopify: WB: precio con IVA no termina en 9 | AI43: No | AK43: G1522ProductosTodosloscamposSandboxResults894.xlsx: fila 45465 [X,Y]; G1522_Extraccion_Articulos_NetSuite_2026-09-30.xlsx: fila 37604 [Z] | AL43: 22.75
A44: 5056658702341 | B44: 79272 | C44: REFLO | D44: BOHCOR | E44: BOHCOR-2XL | F44: XXL | G44: XXL | H44: REFLO | I44: Playera tipo polo REFLO Bohai 2.0 Coronet Blue | J44: Ropa | K44: Playeras | M44: REFLO | P44: Azul | S44: 100% Poliéster reciclado | T44: Playera tipo polo de golf REFLO modelo Bohai 2.0 en color Coronet Blue, confeccionado con materiales reciclados. Estilo BOHCOR. | U44: China | V44: PZS | W44: 53101600 | X44: https://i.ibb.co/ctWjPwY/BOHCOR.jpg | Y44: 22.75 | Z44: 1649 | AA44: =IF(AND(A44="", B44="", E44=""), "", IF(AB44="", "Válido", IF((LEN(AB44)-LEN(SUBSTITUTE(AB44,"; ","")))/2+1>(LEN(AB44)-LEN(SUBSTITUTE(AB44,"[Aviso]","")))/7, "Con Incidencias", "Válido"))) | AB44: =IF(AND(A44="", B44="", E44=""), "", TEXTJOIN("; ", TRUE, IF(OR(TRIM(A44&"")="", ISNUMBER(SEARCH("FALTA", A44))), "UPC faltante/inválido", ""), IF(AND(A44<>"", IFERROR(_xlfn.XMATCH(A44,$A$2:$A$653,0,1)<>_xlfn.XMATCH(A44,$A$2:$A$653,0,-1),FALSE)), "Código de barras duplicado", ""), IF(AND(E44<>"", COUNTIF($E$2:$E$653, E44)>1), "SKU duplicado", ""), IF(OR(J44="", J44=""), "[Aviso] División no capturada ()", IF(ISNA(MATCH(J44, Criterios!$A$123:$A$126, 0)), "División no válida", "")), IF(OR(K44="", K44=""), "[Aviso] Categoría no capturada ()", IF(ISNA(MATCH(K44, Criterios!$A$81:$A$120, 0)), "Categoría no válida", IF(AND(J44<>"", J44<>"", J44<>VLOOKUP(K44, Criterios!$A$81:$B$120, 2, FALSE)), "División no coincide con Categoría", ""))), IF(OR(L44="", L44=""), "[Aviso] Género no capturado ()", IF(ISNA(MATCH(L44, Criterios!$B$123:$B$127, 0)), "Género no válido", "")), IF(OR(N44="", N44=""), "[Aviso] Temporada no capturada ()", IF(ISNA(MATCH(N44, Criterios!$C$123:$C$128, 0)), "Temporada no válida", "")), IF(OR(O44="", O44=""), "[Aviso] Ciclo de vida no capturado ()", IF(ISNA(MATCH(O44, Criterios!$D$123:$D$124, 0)), "Ciclo de vida no válido", "")))) | AD44: 2 | AE44: REFLO ALMACEN (1) | AF44: 2 | AG44: Nuevo – NetSuite con existencia | AH44: Género no indicado en NetSuite; Físico total NetSuite 2 ≠ suma por ubicación 1 | Revisión 29/09/2026: Marca REFLO fuera de lista Criterios; Campos sin respaldo: L, N, O, Q; Auditoría NetSuite 30/09/2026: llenado desde NetSuite [Z] | Homologación G1522 06/10/2026: Validador Shopify: WB: precio con IVA no termina en 9 | AI44: No | AK44: G1522ProductosTodosloscamposSandboxResults894.xlsx: fila 45466 [X,Y]; G1522_Extraccion_Articulos_NetSuite_2026-09-30.xlsx: fila 37605 [Z] | AL44: 22.75
A45: 5056658702303 | B45: 84422 | C45: REFLO | D45: BOHCOR | E45: BOHCOR-S | F45: S | G45: S | H45: REFLO | I45: Playera tipo polo REFLO Bohai Coronet Blue | J45: Ropa | K45: Playeras | M45: REFLO | P45: Azul | S45: 100% Poliéster reciclado | T45: Playera tipo polo de golf REFLO modelo Bohai en color Coronet Blue, confeccionado con materiales reciclados. Estilo BOHCOR. | U45: China | V45: PZS | W45: 53101600 | X45: https://i.ibb.co/ctWjPwY/BOHCOR.jpg | Y45: 22.75 | Z45: 1649 | AA45: =IF(AND(A45="", B45="", E45=""), "", IF(AB45="", "Válido", IF((LEN(AB45)-LEN(SUBSTITUTE(AB45,"; ","")))/2+1>(LEN(AB45)-LEN(SUBSTITUTE(AB45,"[Aviso]","")))/7, "Con Incidencias", "Válido"))) | AB45: =IF(AND(A45="", B45="", E45=""), "", TEXTJOIN("; ", TRUE, IF(OR(TRIM(A45&"")="", ISNUMBER(SEARCH("FALTA", A45))), "UPC faltante/inválido", ""), IF(AND(A45<>"", IFERROR(_xlfn.XMATCH(A45,$A$2:$A$653,0,1)<>_xlfn.XMATCH(A45,$A$2:$A$653,0,-1),FALSE)), "Código de barras duplicado", ""), IF(AND(E45<>"", COUNTIF($E$2:$E$653, E45)>1), "SKU duplicado", ""), IF(OR(J45="", J45=""), "[Aviso] División no capturada ()", IF(ISNA(MATCH(J45, Criterios!$A$123:$A$126, 0)), "División no válida", "")), IF(OR(K45="", K45=""), "[Aviso] Categoría no capturada ()", IF(ISNA(MATCH(K45, Criterios!$A$81:$A$120, 0)), "Categoría no válida", IF(AND(J45<>"", J45<>"", J45<>VLOOKUP(K45, Criterios!$A$81:$B$120, 2, FALSE)), "División no coincide con Categoría", ""))), IF(OR(L45="", L45=""), "[Aviso] Género no capturado ()", IF(ISNA(MATCH(L45, Criterios!$B$123:$B$127, 0)), "Género no válido", "")), IF(OR(N45="", N45=""), "[Aviso] Temporada no capturada ()", IF(ISNA(MATCH(N45, Criterios!$C$123:$C$128, 0)), "Temporada no válida", "")), IF(OR(O45="", O45=""), "[Aviso] Ciclo de vida no capturado ()", IF(ISNA(MATCH(O45, Criterios!$D$123:$D$124, 0)), "Ciclo de vida no válido", "")))) | AD45: 2 | AE45: CONSIGNA REFLO (1) | AF45: 2 | AG45: Nuevo – NetSuite con existencia | AH45: Género no indicado en NetSuite; Físico total NetSuite 2 ≠ suma por ubicación 1 | Revisión 29/09/2026: Marca REFLO fuera de lista Criterios; Campos sin respaldo: L, N, O, Q; Auditoría NetSuite 30/09/2026: llenado desde NetSuite [Z] | Homologación G1522 06/10/2026: Validador Shopify: WB: precio con IVA no termina en 9 | AI45: No | AK45: G1522ProductosTodosloscamposSandboxResults894.xlsx: fila 45493 [X,Y]; G1522_Extraccion_Articulos_NetSuite_2026-09-30.xlsx: fila 39591 [Z] | AL45: 22.75
A46: 5056658702372 | B46: 79273 | C46: REFLO | D46: BOHDAR | E46: BOHDAR-M | F46: M | G46: M | H46: REFLO | I46: Playera tipo polo REFLO Bohai 2.0 Dark Forest | J46: Ropa | K46: Playeras | M46: REFLO | P46: Verde | S46: 100% Poliéster reciclado | T46: Playera tipo polo de golf REFLO modelo Bohai 2.0 en color Dark Forest, confeccionado con materiales reciclados. Estilo BOHDAR. | U46: China | V46: PZS | W46: 53101600 | X46: https://i.ibb.co/BZxsv6W/BOHDAR.jpg | Y46: 22.75 | Z46: 1649 | AA46: =IF(AND(A46="", B46="", E46=""), "", IF(AB46="", "Válido", IF((LEN(AB46)-LEN(SUBSTITUTE(AB46,"; ","")))/2+1>(LEN(AB46)-LEN(SUBSTITUTE(AB46,"[Aviso]","")))/7, "Con Incidencias", "Válido"))) | AB46: =IF(AND(A46="", B46="", E46=""), "", TEXTJOIN("; ", TRUE, IF(OR(TRIM(A46&"")="", ISNUMBER(SEARCH("FALTA", A46))), "UPC faltante/inválido", ""), IF(AND(A46<>"", IFERROR(_xlfn.XMATCH(A46,$A$2:$A$653,0,1)<>_xlfn.XMATCH(A46,$A$2:$A$653,0,-1),FALSE)), "Código de barras duplicado", ""), IF(AND(E46<>"", COUNTIF($E$2:$E$653, E46)>1), "SKU duplicado", ""), IF(OR(J46="", J46=""), "[Aviso] División no capturada ()", IF(ISNA(MATCH(J46, Criterios!$A$123:$A$126, 0)), "División no válida", "")), IF(OR(K46="", K46=""), "[Aviso] Categoría no capturada ()", IF(ISNA(MATCH(K46, Criterios!$A$81:$A$120, 0)), "Categoría no válida", IF(AND(J46<>"", J46<>"", J46<>VLOOKUP(K46, Criterios!$A$81:$B$120, 2, FALSE)), "División no coincide con Categoría", ""))), IF(OR(L46="", L46=""), "[Aviso] Género no capturado ()", IF(ISNA(MATCH(L46, Criterios!$B$123:$B$127, 0)), "Género no válido", "")), IF(OR(N46="", N46=""), "[Aviso] Temporada no capturada ()", IF(ISNA(MATCH(N46, Criterios!$C$123:$C$128, 0)), "Temporada no válida", "")), IF(OR(O46="", O46=""), "[Aviso] Ciclo de vida no capturado ()", IF(ISNA(MATCH(O46, Criterios!$D$123:$D$124, 0)), "Ciclo de vida no válido", "")))) | AD46: 8 | AE46: CONSIGNA REFLO (1); REFLO ALMACEN (3) | AF46: 8 | AG46: Nuevo – NetSuite con existencia | AH46: Género no indicado en NetSuite; Físico total NetSuite 8 ≠ suma por ubicación 4 | Revisión 29/09/2026: Marca REFLO fuera de lista Criterios; Campos sin respaldo: L, N, O, Q; Auditoría NetSuite 30/09/2026: llenado desde NetSuite [Z] | Homologación G1522 06/10/2026: Validador Shopify: WB: precio con IVA no termina en 9 | AI46: No | AK46: G1522ProductosTodosloscamposSandboxResults894.xlsx: fila 45468 [X,Y]; G1522_Extraccion_Articulos_NetSuite_2026-09-30.xlsx: fila 37606 [Z] | AL46: 22.75
A47: 5056658702389 | B47: 79274 | C47: REFLO | D47: BOHDAR | E47: BOHDAR-L | F47: L | G47: L | H47: REFLO | I47: Playera tipo polo REFLO Bohai 2.0 Dark Forest | J47: Ropa | K47: Playeras | M47: REFLO | P47: Verde | S47: 100% Poliéster reciclado | T47: Playera tipo polo de golf REFLO modelo Bohai 2.0 en color Dark Forest, confeccionado con materiales reciclados. Estilo BOHDAR. | U47: China | V47: PZS | W47: 53101600 | X47: https://i.ibb.co/BZxsv6W/BOHDAR.jpg | Y47: 22.75 | Z47: 1649 | AA47: =IF(AND(A47="", B47="", E47=""), "", IF(AB47="", "Válido", IF((LEN(AB47)-LEN(SUBSTITUTE(AB47,"; ","")))/2+1>(LEN(AB47)-LEN(SUBSTITUTE(AB47,"[Aviso]","")))/7, "Con Incidencias", "Válido"))) | AB47: =IF(AND(A47="", B47="", E47=""), "", TEXTJOIN("; ", TRUE, IF(OR(TRIM(A47&"")="", ISNUMBER(SEARCH("FALTA", A47))), "UPC faltante/inválido", ""), IF(AND(A47<>"", IFERROR(_xlfn.XMATCH(A47,$A$2:$A$653,0,1)<>_xlfn.XMATCH(A47,$A$2:$A$653,0,-1),FALSE)), "Código de barras duplicado", ""), IF(AND(E47<>"", COUNTIF($E$2:$E$653, E47)>1), "SKU duplicado", ""), IF(OR(J47="", J47=""), "[Aviso] División no capturada ()", IF(ISNA(MATCH(J47, Criterios!$A$123:$A$126, 0)), "División no válida", "")), IF(OR(K47="", K47=""), "[Aviso] Categoría no capturada ()", IF(ISNA(MATCH(K47, Criterios!$A$81:$A$120, 0)), "Categoría no válida", IF(AND(J47<>"", J47<>"", J47<>VLOOKUP(K47, Criterios!$A$81:$B$120, 2, FALSE)), "División no coincide con Categoría", ""))), IF(OR(L47="", L47=""), "[Aviso] Género no capturado ()", IF(ISNA(MATCH(L47, Criterios!$B$123:$B$127, 0)), "Género no válido", "")), IF(OR(N47="", N47=""), "[Aviso] Temporada no capturada ()", IF(ISNA(MATCH(N47, Criterios!$C$123:$C$128, 0)), "Temporada no válida", "")), IF(OR(O47="", O47=""), "[Aviso] Ciclo de vida no capturado ()", IF(ISNA(MATCH(O47, Criterios!$D$123:$D$124, 0)), "Ciclo de vida no válido", "")))) | AD47: 6 | AE47: CONSIGNA REFLO (2); REFLO ALMACEN (1); MUESTRAS REFLO (1) | AF47: 5 | AG47: Nuevo – NetSuite con existencia | AH47: Género no indicado en NetSuite; Físico total NetSuite 6 ≠ suma por ubicación 4 | Revisión 29/09/2026: Marca REFLO fuera de lista Criterios; Campos sin respaldo: L, N, O, Q; Auditoría NetSuite 30/09/2026: llenado desde NetSuite [Z] | Homologación G1522 06/10/2026: Validador Shopify: WB: precio con IVA no termina en 9 | AI47: No | AK47: G1522ProductosTodosloscamposSandboxResults894.xlsx: fila 45469 [X,Y]; G1522_Extraccion_Articulos_NetSuite_2026-09-30.xlsx: fila 37607 [Z] | AL47: 22.75
A48: 5056658702396 | B48: 79275 | C48: REFLO | D48: BOHDAR | E48: BOHDAR-XL | F48: XL | G48: XL | H48: REFLO | I48: Playera tipo polo REFLO Bohai 2.0 Dark Forest | J48: Ropa | K48: Playeras | M48: REFLO | P48: Verde | S48: 100% Poliéster reciclado | T48: Playera tipo polo de golf REFLO modelo Bohai 2.0 en color Dark Forest, confeccionado con materiales reciclados. Estilo BOHDAR. | U48: China | V48: PZS | W48: 53101600 | X48: https://i.ibb.co/BZxsv6W/BOHDAR.jpg | Y48: 22.75 | Z48: 1649 | AA48: =IF(AND(A48="", B48="", E48=""), "", IF(AB48="", "Válido", IF((LEN(AB48)-LEN(SUBSTITUTE(AB48,"; ","")))/2+1>(LEN(AB48)-LEN(SUBSTITUTE(AB48,"[Aviso]","")))/7, "Con Incidencias", "Válido"))) | AB48: =IF(AND(A48="", B48="", E48=""), "", TEXTJOIN("; ", TRUE, IF(OR(TRIM(A48&"")="", ISNUMBER(SEARCH("FALTA", A48))), "UPC faltante/inválido", ""), IF(AND(A48<>"", IFERROR(_xlfn.XMATCH(A48,$A$2:$A$653,0,1)<>_xlfn.XMATCH(A48,$A$2:$A$653,0,-1),FALSE)), "Código de barras duplicado", ""), IF(AND(E48<>"", COUNTIF($E$2:$E$653, E48)>1), "SKU duplicado", ""), IF(OR(J48="", J48=""), "[Aviso] División no capturada ()", IF(ISNA(MATCH(J48, Criterios!$A$123:$A$126, 0)), "División no válida", "")), IF(OR(K48="", K48=""), "[Aviso] Categoría no capturada ()", IF(ISNA(MATCH(K48, Criterios!$A$81:$A$120, 0)), "Categoría no válida", IF(AND(J48<>"", J48<>"", J48<>VLOOKUP(K48, Criterios!$A$81:$B$120, 2, FALSE)), "División no coincide con Categoría", ""))), IF(OR(L48="", L48=""), "[Aviso] Género no capturado ()", IF(ISNA(MATCH(L48, Criterios!$B$123:$B$127, 0)), "Género no válido", "")), IF(OR(N48="", N48=""), "[Aviso] Temporada no capturada ()", IF(ISNA(MATCH(N48, Criterios!$C$123:$C$128, 0)), "Temporada no válida", "")), IF(OR(O48="", O48=""), "[Aviso] Ciclo de vida no capturado ()", IF(ISNA(MATCH(O48, Criterios!$D$123:$D$124, 0)), "Ciclo de vida no válido", "")))) | AD48: 12 | AE48: CONSIGNA REFLO (1); REFLO ALMACEN (5) | AF48: 12 | AG48: Nuevo – NetSuite con existencia | AH48: Género no indicado en NetSuite; Físico total NetSuite 12 ≠ suma por ubicación 6 | Revisión 29/09/2026: Marca REFLO fuera de lista Criterios; Campos sin respaldo: L, N, O, Q; Auditoría NetSuite 30/09/2026: llenado desde NetSuite [Z] | Homologación G1522 06/10/2026: Validador Shopify: WB: precio con IVA no termina en 9 | AI48: No | AK48: G1522ProductosTodosloscamposSandboxResults894.xlsx: fila 45470 [X,Y]; G1522_Extraccion_Articulos_NetSuite_2026-09-30.xlsx: fila 37608 [Z] | AL48: 22.75
... A63: 5056658702488 | B63: 84424 | C63: REFLO | D63: BOHTAN | E63: BOHTAN-S | F63: S | G63: S | H63: REFLO | I63: Playera tipo polo REFLO Bohai Tangerine | J63: Ropa | K63: Playeras | M63: REFLO | P63: Naranja | S63: 100% Poliéster reciclado | T63: Playera tipo polo de golf REFLO modelo Bohai en color Tangerine, confeccionado con materiales reciclados. Estilo BOHTAN. | U63: China | V63: PZS | W63: 53101600 | X63: https://i.ibb.co/zXBdrqT/BOHTAN.jpg | Y63: 22.75 | Z63: 1649 | AA63: =IF(AND(A63="", B63="", E63=""), "", IF(AB63="", "Válido", IF((LEN(AB63)-LEN(SUBSTITUTE(AB63,"; ","")))/2+1>(LEN(AB63)-LEN(SUBSTITUTE(AB63,"[Aviso]","")))/7, "Con Incidencias", "Válido"))) | AB63: =IF(AND(A63="", B63="", E63=""), "", TEXTJOIN("; ", TRUE, IF(OR(TRIM(A63&"")="", ISNUMBER(SEARCH("FALTA", A63))), "UPC faltante/inválido", ""), IF(AND(A63<>"", IFERROR(_xlfn.XMATCH(A63,$A$2:$A$653,0,1)<>_xlfn.XMATCH(A63,$A$2:$A$653,0,-1),FALSE)), "Código de barras duplicado", ""), IF(AND(E63<>"", COUNTIF($E$2:$E$653, E63)>1), "SKU duplicado", ""), IF(OR(J63="", J63=""), "[Aviso] División no capturada ()", IF(ISNA(MATCH(J63, Criterios!$A$123:$A$126, 0)), "División no válida", "")), IF(OR(K63="", K63=""), "[Aviso] Categoría no capturada ()", IF(ISNA(MATCH(K63, Criterios!$A$81:$A$120, 0)), "Categoría no válida", IF(AND(J63<>"", J63<>"", J63<>VLOOKUP(K63, Criterios!$A$81:$B$120, 2, FALSE)), "División no coincide con Categoría", ""))), IF(OR(L63="", L63=""), "[Aviso] Género no capturado ()", IF(ISNA(MATCH(L63, Criterios!$B$123:$B$127, 0)), "Género no válido", "")), IF(OR(N63="", N63=""), "[Aviso] Temporada no capturada ()", IF(ISNA(MATCH(N63, Criterios!$C$123:$C$128, 0)), "Temporada no válida", "")), IF(OR(O63="", O63=""), "[Aviso] Ciclo de vida no capturado ()", IF(ISNA(MATCH(O63, Criterios!$D$123:$D$124, 0)), "Ciclo de vida no válido", "")))) | AD63: 8 | AE63: CONSIGNA REFLO (2); REFLO ALMACEN (2) | AF63: 8 | AG63: Nuevo – NetSuite con existencia | AH63: Género no indicado en NetSuite; Físico total NetSuite 8 ≠ suma por ubicación 4 | Revisión 29/09/2026: Marca REFLO fuera de lista Criterios; Campos sin respaldo: L, N, O, Q; Auditoría NetSuite 30/09/2026: llenado desde NetSuite [Z] | Homologación G1522 06/10/2026: Validador Shopify: WB: precio con IVA no termina en 9 | AI63: No | AK63: G1522ProductosTodosloscamposSandboxResults894.xlsx: fila 45502 [X,Y]; G1522_Extraccion_Articulos_NetSuite_2026-09-30.xlsx: fila 39593 [Z] | AL63: 22.75
A64: 5056658700187 | B64: 79289 | C64: REFLO | D64: CONGQGRE | E64: CONGQGRE-M | F64: M | G64: M | H64: REFLO | I64: Playera tipo polo REFLO Congo Green | J64: Ropa | K64: Playeras | M64: REFLO | P64: Verde | S64: Poliéster reciclado | T64: Playera tipo polo de golf REFLO modelo Congo en color Green, confeccionado con materiales reciclados. Estilo CONGQGRE. | V64: PZS | W64: 53101600 | X64: https://i.ibb.co/q5LPMPZ/CONGQGRE.jpg | Y64: 26 | Z64: 1899 | AA64: =IF(AND(A64="", B64="", E64=""), "", IF(AB64="", "Válido", IF((LEN(AB64)-LEN(SUBSTITUTE(AB64,"; ","")))/2+1>(LEN(AB64)-LEN(SUBSTITUTE(AB64,"[Aviso]","")))/7, "Con Incidencias", "Válido"))) | AB64: =IF(AND(A64="", B64="", E64=""), "", TEXTJOIN("; ", TRUE, IF(OR(TRIM(A64&"")="", ISNUMBER(SEARCH("FALTA", A64))), "UPC faltante/inválido", ""), IF(AND(A64<>"", IFERROR(_xlfn.XMATCH(A64,$A$2:$A$653,0,1)<>_xlfn.XMATCH(A64,$A$2:$A$653,0,-1),FALSE)), "Código de barras duplicado", ""), IF(AND(E64<>"", COUNTIF($E$2:$E$653, E64)>1), "SKU duplicado", ""), IF(OR(J64="", J64=""), "[Aviso] División no capturada ()", IF(ISNA(MATCH(J64, Criterios!$A$123:$A$126, 0)), "División no válida", "")), IF(OR(K64="", K64=""), "[Aviso] Categoría no capturada ()", IF(ISNA(MATCH(K64, Criterios!$A$81:$A$120, 0)), "Categoría no válida", IF(AND(J64<>"", J64<>"", J64<>VLOOKUP(K64, Criterios!$A$81:$B$120, 2, FALSE)), "División no coincide con Categoría", ""))), IF(OR(L64="", L64=""), "[Aviso] Género no capturado ()", IF(ISNA(MATCH(L64, Criterios!$B$123:$B$127, 0)), "Género no válido", "")), IF(OR(N64="", N64=""), "[Aviso] Temporada no capturada ()", IF(ISNA(MATCH(N64, Criterios!$C$123:$C$128, 0)), "Temporada no válida", "")), IF(OR(O64="", O64=""), "[Aviso] Ciclo de vida no capturado ()", IF(ISNA(MATCH(O64, Criterios!$D$123:$D$124, 0)), "Ciclo de vida no válido", "")))) | AD64: 4 | AE64: REFLO ALMACEN (2); CONSIGNA REFLO (1) | AF64: 4 | AG64: Nuevo – NetSuite con existencia | AH64: Género no indicado en NetSuite; Composición: poliéster reciclado (validar % en etiqueta); Físico total NetSuite 4 ≠ suma por ubicación 3 | Revisión 29/09/2026: Marca REFLO fuera de lista Criterios; Campos sin respaldo: L, N, O, Q, U; Auditoría NetSuite 30/09/2026: llenado desde NetSuite [Z] | Homologación G1522 06/10/2026: Validador Shopify: WB: precio con IVA no termina en 9 | AI64: No | AK64: G1522ProductosTodosloscamposSandboxResults894.xlsx: fila 48440 [X,Y]; G1522_Extraccion_Articulos_NetSuite_2026-09-30.xlsx: fila 37622 [Z] | AL64: 26
A65: 5056658700194 | B65: 79290 | C65: REFLO | D65: CONGQGRE | E65: CONGQGRE-L | F65: L | G65: L | H65: REFLO | I65: Playera tipo polo REFLO Congo Green | J65: Ropa | K65: Playeras | M65: REFLO | P65: Verde | S65: Poliéster reciclado | T65: Playera tipo polo de golf REFLO modelo Congo en color Green, confeccionado con materiales reciclados. Estilo CONGQGRE. | V65: PZS | W65: 53101600 | X65: https://i.ibb.co/q5LPMPZ/CONGQGRE.jpg | Y65: 26 | Z65: 1899 | AA65: =IF(AND(A65="", B65="", E65=""), "", IF(AB65="", "Válido", IF((LEN(AB65)-LEN(SUBSTITUTE(AB65,"; ","")))/2+1>(LEN(AB65)-LEN(SUBSTITUTE(AB65,"[Aviso]","")))/7, "Con Incidencias", "Válido"))) | AB65: =IF(AND(A65="", B65="", E65=""), "", TEXTJOIN("; ", TRUE, IF(OR(TRIM(A65&"")="", ISNUMBER(SEARCH("FALTA", A65))), "UPC faltante/inválido", ""), IF(AND(A65<>"", IFERROR(_xlfn.XMATCH(A65,$A$2:$A$653,0,1)<>_xlfn.XMATCH(A65,$A$2:$A$653,0,-1),FALSE)), "Código de barras duplicado", ""), IF(AND(E65<>"", COUNTIF($E$2:$E$653, E65)>1), "SKU duplicado", ""), IF(OR(J65="", J65=""), "[Aviso] División no capturada ()", IF(ISNA(MATCH(J65, Criterios!$A$123:$A$126, 0)), "División no válida", "")), IF(OR(K65="", K65=""), "[Aviso] Categoría no capturada ()", IF(ISNA(MATCH(K65, Criterios!$A$81:$A$120, 0)), "Categoría no válida", IF(AND(J65<>"", J65<>"", J65<>VLOOKUP(K65, Criterios!$A$81:$B$120, 2, FALSE)), "División no coincide con Categoría", ""))), IF(OR(L65="", L65=""), "[Aviso] Género no capturado ()", IF(ISNA(MATCH(L65, Criterios!$B$123:$B$127, 0)), "Género no válido", "")), IF(OR(N65="", N65=""), "[Aviso] Temporada no capturada ()", IF(ISNA(MATCH(N65, Criterios!$C$123:$C$128, 0)), "Temporada no válida", "")), IF(OR(O65="", O65=""), "[Aviso] Ciclo de vida no capturado ()", IF(ISNA(MATCH(O65, Criterios!$D$123:$D$124, 0)), "Ciclo de vida no válido", "")))) | AD65: 4 | AE65: CONSIGNA REFLO (1); REFLO ALMACEN (2); MUESTRAS REFLO (1) | AF65: 3 | AG65: Nuevo – NetSuite con existencia | AH65: Género no indicado en NetSuite; Composición: poliéster reciclado (validar % en etiqueta) | Revisión 29/09/2026: Marca REFLO fuera de lista Criterios; Campos sin respaldo: L, N, O, Q, U; Auditoría NetSuite 30/09/2026: llenado desde NetSuite [Z] | Homologación G1522 06/10/2026: Validador Shopify: WB: precio con IVA no termina en 9 | AI65: No | AK65: G1522ProductosTodosloscamposSandboxResults894.xlsx: fila 48441 [X,Y]; G1522_Extraccion_Articulos_NetSuite_2026-09-30.xlsx: fila 37623 [Z] | AL65: 26
A66: 5056658700200 | B66: 79291 | C66: REFLO | D66: CONGQGRE | E66: CONGQGRE-XL | F66: XL | G66: XL | H66: REFLO | I66: Playera tipo polo REFLO Congo Green | J66: Ropa | K66: Playeras | M66: REFLO | P66: Verde | S66: Poliéster reciclado | T66: Playera tipo polo de golf REFLO modelo Congo en color Green, confeccionado con materiales reciclados. Estilo CONGQGRE. | V66: PZS | W66: 53101600 | X66: https://i.ibb.co/q5LPMPZ/CONGQGRE.jpg | Y66: 26 | Z66: 1899 | AA66: =IF(AND(A66="", B66="", E66=""), "", IF(AB66="", "Válido", IF((LEN(AB66)-LEN(SUBSTITUTE(AB66,"; ","")))/2+1>(LEN(AB66)-LEN(SUBSTITUTE(AB66,"[Aviso]","")))/7, "Con Incidencias", "Válido"))) | AB66: =IF(AND(A66="", B66="", E66=""), "", TEXTJOIN("; ", TRUE, IF(OR(TRIM(A66&"")="", ISNUMBER(SEARCH("FALTA", A66))), "UPC faltante/inválido", ""), IF(AND(A66<>"", IFERROR(_xlfn.XMATCH(A66,$A$2:$A$653,0,1)<>_xlfn.XMATCH(A66,$A$2:$A$653,0,-1),FALSE)), "Código de barras duplicado", ""), IF(AND(E66<>"", COUNTIF($E$2:$E$653, E66)>1), "SKU duplicado", ""), IF(OR(J66="", J66=""), "[Aviso] División no capturada ()", IF(ISNA(MATCH(J66, Criterios!$A$123:$A$126, 0)), "División no válida", "")), IF(OR(K66="", K66=""), "[Aviso] Categoría no capturada ()", IF(ISNA(MATCH(K66, Criterios!$A$81:$A$120, 0)), "Categoría no válida", IF(AND(J66<>"", J66<>"", J66<>VLOOKUP(K66, Criterios!$A$81:$B$120, 2, FALSE)), "División no coincide con Categoría", ""))), IF(OR(L66="", L66=""), "[Aviso] Género no capturado ()", IF(ISNA(MATCH(L66, Criterios!$B$123:$B$127, 0)), "Género no válido", "")), IF(OR(N66="", N66=""), "[Aviso] Temporada no capturada ()", IF(ISNA(MATCH(N66, Criterios!$C$123:$C$128, 0)), "Temporada no válida", "")), IF(OR(O66="", O66=""), "[Aviso] Ciclo de vida no capturado ()", IF(ISNA(MATCH(O66, Criterios!$D$123:$D$124, 0)), "Ciclo de vida no válido", "")))) | AD66: 9 | AE66: REFLO ALMACEN (6) | AF66: 9 | AG66: Nuevo – NetSuite con existencia | AH66: Género no indicado en NetSuite; Composición: poliéster reciclado (validar % en etiqueta); Físico total NetSuite 9 ≠ suma por ubicación 6 | Revisión 29/09/2026: Marca REFLO fuera de lista Criterios; Campos sin respaldo: L, N, O, Q, U; Auditoría NetSuite 30/09/2026: llenado desde NetSuite [Z] | Homologación G1522 06/10/2026: Validador Shopify: WB: precio con IVA no termina en 9 | AI66: No | AK66: G1522ProductosTodosloscamposSandboxResults894.xlsx: fila 48442 [X,Y]; G1522_Extraccion_Articulos_NetSuite_2026-09-30.xlsx: fila 37624 [Z] | AL66: 26
A67: 5056658700217 | B67: 79292 | C67: REFLO | D67: CONGQGRE | E67: CONGQGRE-2XL | F67: XXL | G67: XXL | H67: REFLO | I67: Playera tipo polo REFLO Congo Green | J67: Ropa | K67: Playeras | M67: REFLO | P67: Verde | S67: Poliéster reciclado | T67: Playera tipo polo de golf REFLO modelo Congo en color Green, confeccionado con materiales reciclados. Estilo CONGQGRE. | V67: PZS | W67: 53101600 | X67: https://i.ibb.co/q5LPMPZ/CONGQGRE.jpg | Y67: 26 | Z67: 1899 | AA67: =IF(AND(A67="", B67="", E67=""), "", IF(AB67="", "Válido", IF((LEN(AB67)-LEN(SUBSTITUTE(AB67,"; ","")))/2+1>(LEN(AB67)-LEN(SUBSTITUTE(AB67,"[Aviso]","")))/7, "Con Incidencias", "Válido"))) | AB67: =IF(AND(A67="", B67="", E67=""), "", TEXTJOIN("; ", TRUE, IF(OR(TRIM(A67&"")="", ISNUMBER(SEARCH("FALTA", A67))), "UPC faltante/inválido", ""), IF(AND(A67<>"", IFERROR(_xlfn.XMATCH(A67,$A$2:$A$653,0,1)<>_xlfn.XMATCH(A67,$A$2:$A$653,0,-1),FALSE)), "Código de barras duplicado", ""), IF(AND(E67<>"", COUNTIF($E$2:$E$653, E67)>1), "SKU duplicado", ""), IF(OR(J67="", J67=""), "[Aviso] División no capturada ()", IF(ISNA(MATCH(J67, Criterios!$A$123:$A$126, 0)), "División no válida", "")), IF(OR(K67="", K67=""), "[Aviso] Categoría no capturada ()", IF(ISNA(MATCH(K67, Criterios!$A$81:$A$120, 0)), "Categoría no válida", IF(AND(J67<>"", J67<>"", J67<>VLOOKUP(K67, Criterios!$A$81:$B$120, 2, FALSE)), "División no coincide con Categoría", ""))), IF(OR(L67="", L67=""), "[Aviso] Género no capturado ()", IF(ISNA(MATCH(L67, Criterios!$B$123:$B$127, 0)), "Género no válido", "")), IF(OR(N67="", N67=""), "[Aviso] Temporada no capturada ()", IF(ISNA(MATCH(N67, Criterios!$C$123:$C$128, 0)), "Temporada no válida", "")), IF(OR(O67="", O67=""), "[Aviso] Ciclo de vida no capturado ()", IF(ISNA(MATCH(O67, Criterios!$D$123:$D$124, 0)), "Ciclo de vida no válido", "")))) | AD67: 3 | AE67: REFLO ALMACEN (2) | AF67: 3 | AG67: Nuevo – NetSuite con existencia | AH67: Género no indicado en NetSuite; Composición: poliéster reciclado (validar % en etiqueta); Físico total NetSuite 3 ≠ suma por ubicación 2 | Revisión 29/09/2026: Marca REFLO fuera de lista Criterios; Campos sin respaldo: L, N, O, Q, U; Auditoría NetSuite 30/09/2026: llenado desde NetSuite [Z] | Homologación G1522 06/10/2026: Validador Shopify: WB: precio con IVA no termina en 9 | AI67: No | AK67: G1522ProductosTodosloscamposSandboxResults894.xlsx: fila 48443 [X,Y]; G1522_Extraccion_Articulos_NetSuite_2026-09-30.xlsx: fila 37625 [Z] | AL67: 26
A68: 5056658700170 | B68: 84425 | C68: REFLO | D68: CONGQGRE | E68: CONGQGRE-S | F68: S | G68: S | H68: REFLO | I68: Playera tipo polo REFLO Congo Green | J68: Ropa | K68: Playeras | M68: REFLO | P68: Verde | S68: Poliéster reciclado | T68: Playera tipo polo de golf REFLO modelo Congo en color Green, confeccionado con materiales reciclados. Estilo CONGQGRE. | V68: PZS | W68: 53101600 | X68: https://i.ibb.co/q5LPMPZ/CONGQGRE.jpg | Y68: 26 | Z68: 1899 | AA68: =IF(AND(A68="", B68="", E68=""), "", IF(AB68="", "Válido", IF((LEN(AB68)-LEN(SUBSTITUTE(AB68,"; ","")))/2+1>(LEN(AB68)-LEN(SUBSTITUTE(AB68,"[Aviso]","")))/7, "Con Incidencias", "Válido"))) | AB68: =IF(AND(A68="", B68="", E68=""), "", TEXTJOIN("; ", TRUE, IF(OR(TRIM(A68&"")="", ISNUMBER(SEARCH("FALTA", A68))), "UPC faltante/inválido", ""), IF(AND(A68<>"", IFERROR(_xlfn.XMATCH(A68,$A$2:$A$653,0,1)<>_xlfn.XMATCH(A68,$A$2:$A$653,0,-1),FALSE)), "Código de barras duplicado", ""), IF(AND(E68<>"", COUNTIF($E$2:$E$653, E68)>1), "SKU duplicado", ""), IF(OR(J68="", J68=""), "[Aviso] División no capturada ()", IF(ISNA(MATCH(J68, Criterios!$A$123:$A$126, 0)), "División no válida", "")), IF(OR(K68="", K68=""), "[Aviso] Categoría no capturada ()", IF(ISNA(MATCH(K68, Criterios!$A$81:$A$120, 0)), "Categoría no válida", IF(AND(J68<>"", J68<>"", J68<>VLOOKUP(K68, Criterios!$A$81:$B$120, 2, FALSE)), "División no coincide con Categoría", ""))), IF(OR(L68="", L68=""), "[Aviso] Género no capturado ()", IF(ISNA(MATCH(L68, Criterios!$B$123:$B$127, 0)), "Género no válido", "")), IF(OR(N68="", N68=""), "[Aviso] Temporada no capturada ()", IF(ISNA(MATCH(N68, Criterios!$C$123:$C$128, 0)), "Temporada no válida", "")), IF(OR(O68="", O68=""), "[Aviso] Ciclo de vida no capturado ()", IF(ISNA(MATCH(O68, Criterios!$D$123:$D$124, 0)), "Ciclo de vida no válido", "")))) | AD68: 6 | AE68: CONSIGNA REFLO (2); REFLO ALMACEN (2) | AF68: 6 | AG68: Nuevo – NetSuite con existencia | AH68: Género no indicado en NetSuite; Composición: poliéster reciclado (validar % en etiqueta); Físico total NetSuite 6 ≠ suma por ubicación 4 | Revisión 29/09/2026: Marca REFLO fuera de lista Criterios; Campos sin respaldo: L, N, O, Q, U; Auditoría NetSuite 30/09/2026: llenado desde NetSuite [Z] | Homologación G1522 06/10/2026: Validador Shopify: WB: precio con IVA no termina en 9 | AI68: No | AK68: G1522ProductosTodosloscamposSandboxResults894.xlsx: fila 48439 [X,Y]; G1522_Extraccion_Articulos_NetSuite_2026-09-30.xlsx: fila 39594 [Z] | AL68: 26
A69: 5056658703126 | B69: 79191 | C69: REFLO | D69: DESCAV | E69: DESCAV-M | F69: M | G69: M | H69: REFLO | I69: Short 2 en 1 REFLO Desna Caviar | J69: Ropa | K69: Shorts | M69: REFLO | P69: Negro | S69: Poliéster reciclado | T69: Short 2 en 1 de golf REFLO modelo Desna en color Caviar, confeccionado con materiales reciclados. Estilo DESCAV. | V69: PZS | W69: 53101500 | X69: https://i.ibb.co/Kh6xX7Y/DESCAV.jpg | Y69: 22.75 | Z69: 1649 | AA69: =IF(AND(A69="", B69="", E69=""), "", IF(AB69="", "Válido", IF((LEN(AB69)-LEN(SUBSTITUTE(AB69,"; ","")))/2+1>(LEN(AB69)-LEN(SUBSTITUTE(AB69,"[Aviso]","")))/7, "Con Incidencias", "Válido"))) | AB69: =IF(AND(A69="", B69="", E69=""), "", TEXTJOIN("; ", TRUE, IF(OR(TRIM(A69&"")="", ISNUMBER(SEARCH("FALTA", A69))), "UPC faltante/inválido", ""), IF(AND(A69<>"", IFERROR(_xlfn.XMATCH(A69,$A$2:$A$653,0,1)<>_xlfn.XMATCH(A69,$A$2:$A$653,0,-1),FALSE)), "Código de barras duplicado", ""), IF(AND(E69<>"", COUNTIF($E$2:$E$653, E69)>1), "SKU duplicado", ""), IF(OR(J69="", J69=""), "[Aviso] División no capturada ()", IF(ISNA(MATCH(J69, Criterios!$A$123:$A$126, 0)), "División no válida", "")), IF(OR(K69="", K69=""), "[Aviso] Categoría no capturada ()", IF(ISNA(MATCH(K69, Criterios!$A$81:$A$120, 0)), "Categoría no válida", IF(AND(J69<>"", J69<>"", J69<>VLOOKUP(K69, Criterios!$A$81:$B$120, 2, FALSE)), "División no coincide con Categoría", ""))), IF(OR(L69="", L69=""), "[Aviso] Género no capturado ()", IF(ISNA(MATCH(L69, Criterios!$B$123:$B$127, 0)), "Género no válido", "")), IF(OR(N69="", N69=""), "[Aviso] Temporada no capturada ()", IF(ISNA(MATCH(N69, Criterios!$C$123:$C$128, 0)), "Temporada no válida", "")), IF(OR(O69="", O69=""), "[Aviso] Ciclo de vida no capturado ()", IF(ISNA(MATCH(O69, Criterios!$D$123:$D$124, 0)), "Ciclo de vida no válido", "")))) | AD69: 3 | AE69: REFLO ALMACEN (3) | AF69: 4 | AG69: Nuevo – NetSuite con existencia | AH69: Género no indicado en NetSuite; Composición: poliéster reciclado (validar % en etiqueta); Físico total NetSuite 3 ≠ suma por ubicación 2 | Revisión 29/09/2026: Marca REFLO fuera de lista Criterios; Campos sin respaldo: L, N, O, Q, U; Auditoría NetSuite 30/09/2026: llenado desde NetSuite [Z] | Homologación G1522 06/10/2026: Validador Shopify: WB: precio con IVA no termina en 9 | AI69: Sí | AJ69: CONSIGNA REFLO (-1) | AK69: G1522ProductosTodosloscamposSandboxResults894.xlsx: fila 48560 [X,Y]; G1522_Extraccion_Articulos_NetSuite_2026-09-30.xlsx: fila 37524 [Z] | AL69: 22.75
A70: 5056658703133 | B70: 79192 | C70: REFLO | D70: DESCAV | E70: DESCAV-L | F70: L | G70: L | H70: REFLO | I70: Short 2 en 1 REFLO Desna Caviar | J70: Ropa | K70: Shorts | M70: REFLO | P70: Negro | S70: Poliéster reciclado | T70: Short 2 en 1 de golf REFLO modelo Desna en color Caviar, confeccionado con materiales reciclados. Estilo DESCAV. | V70: PZS | W70: 53101500 | X70: https://i.ibb.co/Kh6xX7Y/DESCAV.jpg | Y70: 22.75 | Z70: 1649 | AA70: =IF(AND(A70="", B70="", E70=""), "", IF(AB70="", "Válido", IF((LEN(AB70)-LEN(SUBSTITUTE(AB70,"; ","")))/2+1>(LEN(AB70)-LEN(SUBSTITUTE(AB70,"[Aviso]","")))/7, "Con Incidencias", "Válido"))) | AB70: =IF(AND(A70="", B70="", E70=""), "", TEXTJOIN("; ", TRUE, IF(OR(TRIM(A70&"")="", ISNUMBER(SEARCH("FALTA", A70))), "UPC faltante/inválido", ""), IF(AND(A70<>"", IFERROR(_xlfn.XMATCH(A70,$A$2:$A$653,0,1)<>_xlfn.XMATCH(A70,$A$2:$A$653,0,-1),FALSE)), "Código de barras duplicado", ""), IF(AND(E70<>"", COUNTIF($E$2:$E$653, E70)>1), "SKU duplicado", ""), IF(OR(J70="", J70=""), "[Aviso] División no capturada ()", IF(ISNA(MATCH(J70, Criterios!$A$123:$A$126, 0)), "División no válida", "")), IF(OR(K70="", K70=""), "[Aviso] Categoría no capturada ()", IF(ISNA(MATCH(K70, Criterios!$A$81:$A$120, 0)), "Categoría no válida", IF(AND(J70<>"", J70<>"", J70<>VLOOKUP(K70, Criterios!$A$81:$B$120, 2, FALSE)), "División no coincide con Categoría", ""))), IF(OR(L70="", L70=""), "[Aviso] Género no capturado ()", IF(ISNA(MATCH(L70, Criterios!$B$123:$B$127, 0)), "Género no válido", "")), IF(OR(N70="", N70=""), "[Aviso] Temporada no capturada ()", IF(ISNA(MATCH(N70, Criterios!$C$123:$C$128, 0)), "Temporada no válida", "")), IF(OR(O70="", O70=""), "[Aviso] Ciclo de vida no capturado ()", IF(ISNA(MATCH(O70, Criterios!$D$123:$D$124, 0)), "Ciclo de vida no válido", "")))) | AD70: 5 | AE70: MUESTRAS REFLO (1); REFLO ALMACEN (4) | AF70: 5 | AG70: Nuevo – NetSuite con existencia | AH70: Género no indicado en NetSuite; Composición: poliéster reciclado (validar % en etiqueta); Físico total NetSuite 5 ≠ suma por ubicación 4 | Revisión 29/09/2026: Marca REFLO fuera de lista Criterios; Campos sin respaldo: L, N, O, Q, U; Auditoría NetSuite 30/09/2026: llenado desde NetSuite [Z] | Homologación G1522 06/10/2026: Validador Shopify: WB: precio con IVA no termina en 9 | AI70: Sí | AJ70: CONSIGNA REFLO (-1) | AK70: G1522ProductosTodosloscamposSandboxResults894.xlsx: fila 48561 [X,Y]; G1522_Extraccion_Articulos_NetSuite_2026-09-30.xlsx: fila 37525 [Z] | AL70: 22.75
A71: 5056658703140 | B71: 79193 | C71: REFLO | D71: DESCAV | E71: DESCAV-XL | F71: XL | G71: XL | H71: REFLO | I71: Short 2 en 1 REFLO Desna Caviar | J71: Ropa | K71: Shorts | M71: REFLO | P71: Negro | S71: Poliéster reciclado | T71: Short 2 en 1 de golf REFLO modelo Desna en color Caviar, confeccionado con materiales reciclados. Estilo DESCAV. | V71: PZS | W71: 53101500 | X71: https://i.ibb.co/Kh6xX7Y/DESCAV.jpg | Y71: 22.75 | Z71: 1649 | AA71: =IF(AND(A71="", B71="", E71=""), "", IF(AB71="", "Válido", IF((LEN(AB71)-LEN(SUBSTITUTE(AB71,"; ","")))/2+1>(LEN(AB71)-LEN(SUBSTITUTE(AB71,"[Aviso]","")))/7, "Con Incidencias", "Válido"))) | AB71: =IF(AND(A71="", B71="", E71=""), "", TEXTJOIN("; ", TRUE, IF(OR(TRIM(A71&"")="", ISNUMBER(SEARCH("FALTA", A71))), "UPC faltante/inválido", ""), IF(AND(A71<>"", IFERROR(_xlfn.XMATCH(A71,$A$2:$A$653,0,1)<>_xlfn.XMATCH(A71,$A$2:$A$653,0,-1),FALSE)), "Código de barras duplicado", ""), IF(AND(E71<>"", COUNTIF($E$2:$E$653, E71)>1), "SKU duplicado", ""), IF(OR(J71="", J71=""), "[Aviso] División no capturada ()", IF(ISNA(MATCH(J71, Criterios!$A$123:$A$126, 0)), "División no válida", "")), IF(OR(K71="", K71=""), "[Aviso] Categoría no capturada ()", IF(ISNA(MATCH(K71, Criterios!$A$81:$A$120, 0)), "Categoría no válida", IF(AND(J71<>"", J71<>"", J71<>VLOOKUP(K71, Criterios!$A$81:$B$120, 2, FALSE)), "División no coincide con Categoría", ""))), IF(OR(L71="", L71=""), "[Aviso] Género no capturado ()", IF(ISNA(MATCH(L71, Criterios!$B$123:$B$127, 0)), "Género no válido", "")), IF(OR(N71="", N71=""), "[Aviso] Temporada no capturada ()", IF(ISNA(MATCH(N71, Criterios!$C$123:$C$128, 0)), "Temporada no válida", "")), IF(OR(O71="", O71=""), "[Aviso] Ciclo de vida no capturado ()", IF(ISNA(MATCH(O71, Criterios!$D$123:$D$124, 0)), "Ciclo de vida no válido", "")))) | AD71: 7 | AE71: REFLO ALMACEN (5) | AF71: 8 | AG71: Nuevo – NetSuite con existencia | AH71: Género no indicado en NetSuite; Composición: poliéster reciclado (validar % en etiqueta); Físico total NetSuite 7 ≠ suma por ubicación 4 | Revisión 29/09/2026: Marca REFLO fuera de lista Criterios; Campos sin respaldo: L, N, O, Q, U; Auditoría NetSuite 30/09/2026: llenado desde NetSuite [Z] | Homologación G1522 06/10/2026: Validador Shopify: WB: precio con IVA no termina en 9 | AI71: Sí | AJ71: CONSIGNA REFLO (-1) | AK71: G1522ProductosTodosloscamposSandboxResults894.xlsx: fila 48562 [X,Y]; G1522_Extraccion_Articulos_NetSuite_2026-09-30.xlsx: fila 37526 [Z] | AL71: 22.75
A72: 5056658703157 | B72: 79194 | C72: REFLO | D72: DESCAV | E72: DESCAV-2XL | F72: XXL | G72: XXL | H72: REFLO | I72: Short 2 en 1 REFLO Desna Caviar | J72: Ropa | K72: Shorts | M72: REFLO | P72: Negro | S72: Poliéster reciclado | T72: Short 2 en 1 de golf REFLO modelo Desna en color Caviar, confeccionado con materiales reciclados. Estilo DESCAV. | V72: PZS | W72: 53101500 | X72: https://i.ibb.co/Kh6xX7Y/DESCAV.jpg | Y72: 22.75 | Z72: 1649 | AA72: =IF(AND(A72="", B72="", E72=""), "", IF(AB72="", "Válido", IF((LEN(AB72)-LEN(SUBSTITUTE(AB72,"; ","")))/2+1>(LEN(AB72)-LEN(SUBSTITUTE(AB72,"[Aviso]","")))/7, "Con Incidencias", "Válido"))) | AB72: =IF(AND(A72="", B72="", E72=""), "", TEXTJOIN("; ", TRUE, IF(OR(TRIM(A72&"")="", ISNUMBER(SEARCH("FALTA", A72))), "UPC faltante/inválido", ""), IF(AND(A72<>"", IFERROR(_xlfn.XMATCH(A72,$A$2:$A$653,0,1)<>_xlfn.XMATCH(A72,$A$2:$A$653,0,-1),FALSE)), "Código de barras duplicado", ""), IF(AND(E72<>"", COUNTIF($E$2:$E$653, E72)>1), "SKU duplicado", ""), IF(OR(J72="", J72=""), "[Aviso] División no capturada ()", IF(ISNA(MATCH(J72, Criterios!$A$123:$A$126, 0)), "División no válida", "")), IF(OR(K72="", K72=""), "[Aviso] Categoría no capturada ()", IF(ISNA(MATCH(K72, Criterios!$A$81:$A$120, 0)), "Categoría no válida", IF(AND(J72<>"", J72<>"", J72<>VLOOKUP(K72, Criterios!$A$81:$B$120, 2, FALSE)), "División no coincide con Categoría", ""))), IF(OR(L72="", L72=""), "[Aviso] Género no capturado ()", IF(ISNA(MATCH(L72, Criterios!$B$123:$B$127, 0)), "Género no válido", "")), IF(OR(N72="", N72=""), "[Aviso] Temporada no capturada ()", IF(ISNA(MATCH(N72, Criterios!$C$123:$C$128, 0)), "Temporada no válida", "")), IF(OR(O72="", O72=""), "[Aviso] Ciclo de vida no capturado ()", IF(ISNA(MATCH(O72, Criterios!$D$123:$D$124, 0)), "Ciclo de vida no válido", "")))) | AD72: 4 | AE72: REFLO ALMACEN (3) | AF72: 5 | AG72: Nuevo – NetSuite con existencia | AH72: Género no indicado en NetSuite; Composición: poliéster reciclado (validar % en etiqueta); Físico total NetSuite 4 ≠ suma por ubicación 2 | Revisión 29/09/2026: Marca REFLO fuera de lista Criterios; Campos sin respaldo: L, N, O, Q, U; Auditoría NetSuite 30/09/2026: llenado desde NetSuite [Z] | Homologación G1522 06/10/2026: Validador Shopify: WB: precio con IVA no termina en 9 | AI72: Sí | AJ72: CONSIGNA REFLO (-1) | AK72: G1522ProductosTodosloscamposSandboxResults894.xlsx: fila 48563 [X,Y]; G1522_Extraccion_Articulos_NetSuite_2026-09-30.xlsx: fila 37527 [Z] | AL72: 22.75
A73: 5056658703270 | B73: 79195 | C73: REFLO | D73: DESDAR | E73: DESDAR-M | F73: M | G73: M | H73: REFLO | I73: Short 2 en 1 REFLO Desna Dark Forest | J73: Ropa | K73: Shorts | M73: REFLO | P73: Verde | S73: Poliéster reciclado | T73: Short 2 en 1 de golf REFLO modelo Desna en color Dark Forest, confeccionado con materiales reciclados. Estilo DESDAR. | V73: PZS | W73: 53101500 | X73: https://i.ibb.co/n6WVqBk/DESDAR.jpg | Y73: 22.75 | Z73: 1649 | AA73: =IF(AND(A73="", B73="", E73=""), "", IF(AB73="", "Válido", IF((LEN(AB73)-LEN(SUBSTITUTE(AB73,"; ","")))/2+1>(LEN(AB73)-LEN(SUBSTITUTE(AB73,"[Aviso]","")))/7, "Con Incidencias", "Válido"))) | AB73: =IF(AND(A73="", B73="", E73=""), "", TEXTJOIN("; ", TRUE, IF(OR(TRIM(A73&"")="", ISNUMBER(SEARCH("FALTA", A73))), "UPC faltante/inválido", ""), IF(AND(A73<>"", IFERROR(_xlfn.XMATCH(A73,$A$2:$A$653,0,1)<>_xlfn.XMATCH(A73,$A$2:$A$653,0,-1),FALSE)), "Código de barras duplicado", ""), IF(AND(E73<>"", COUNTIF($E$2:$E$653, E73)>1), "SKU duplicado", ""), IF(OR(J73="", J73=""), "[Aviso] División no capturada ()", IF(ISNA(MATCH(J73, Criterios!$A$123:$A$126, 0)), "División no válida", "")), IF(OR(K73="", K73=""), "[Aviso] Categoría no capturada ()", IF(ISNA(MATCH(K73, Criterios!$A$81:$A$120, 0)), "Categoría no válida", IF(AND(J73<>"", J73<>"", J73<>VLOOKUP(K73, Criterios!$A$81:$B$120, 2, FALSE)), "División no coincide con Categoría", ""))), IF(OR(L73="", L73=""), "[Aviso] Género no capturado ()", IF(ISNA(MATCH(L73, Criterios!$B$123:$B$127, 0)), "Género no válido", "")), IF(OR(N73="", N73=""), "[Aviso] Temporada no capturada ()", IF(ISNA(MATCH(N73, Criterios!$C$123:$C$128, 0)), "Temporada no válida", "")), IF(OR(O73="", O73=""), "[Aviso] Ciclo de vida no capturado ()", IF(ISNA(MATCH(O73, Criterios!$D$123:$D$124, 0)), "Ciclo de vida no válido", "")))) | AD73: 1 | AE73: REFLO ALMACEN (1) | AF73: 1 | AG73: Nuevo – NetSuite con existencia | AH73: Género no indicado en NetSuite; Composición: poliéster reciclado (validar % en etiqueta) | Revisión 29/09/2026: Marca REFLO fuera de lista Criterios; Campos sin respaldo: L, N, O, Q, U; Auditoría NetSuite 30/09/2026: llenado desde NetSuite [Z] | Homologación G1522 06/10/2026: Validador Shopify: WB: precio con IVA no termina en 9 | AI73: No | AK73: G1522ProductosTodosloscamposSandboxResults894.xlsx: fila 48565 [X,Y]; G1522_Extraccion_Articulos_NetSuite_2026-09-30.xlsx: fila 37528 [Z] | AL73: 22.75
A74: 5056658703287 | B74: 79196 | C74: REFLO | D74: DESDAR | E74: DESDAR-L | F74: L | G74: L | H74: REFLO | I74: Short 2 en 1 REFLO Desna Dark Forest | J74: Ropa | K74: Shorts | M74: REFLO | P74: Verde | S74: Poliéster reciclado | T74: Short 2 en 1 de golf REFLO modelo Desna en color Dark Forest, confeccionado con materiales reciclados. Estilo DESDAR. | V74: PZS | W74: 53101500 | X74: https://i.ibb.co/n6WVqBk/DESDAR.jpg | Y74: 22.75 | Z74: 1649 | AA74: =IF(AND(A74="", B74="", E74=""), "", IF(AB74="", "Válido", IF((LEN(AB74)-LEN(SUBSTITUTE(AB74,"; ","")))/2+1>(LEN(AB74)-LEN(SUBSTITUTE(AB74,"[Aviso]","")))/7, "Con Incidencias", "Válido"))) | AB74: =IF(AND(A74="", B74="", E74=""), "", TEXTJOIN("; ", TRUE, IF(OR(TRIM(A74&"")="", ISNUMBER(SEARCH("FALTA", A74))), "UPC faltante/inválido", ""), IF(AND(A74<>"", IFERROR(_xlfn.XMATCH(A74,$A$2:$A$653,0,1)<>_xlfn.XMATCH(A74,$A$2:$A$653,0,-1),FALSE)), "Código de barras duplicado", ""), IF(AND(E74<>"", COUNTIF($E$2:$E$653, E74)>1), "SKU duplicado", ""), IF(OR(J74="", J74=""), "[Aviso] División no capturada ()", IF(ISNA(MATCH(J74, Criterios!$A$123:$A$126, 0)), "División no válida", "")), IF(OR(K74="", K74=""), "[Aviso] Categoría no capturada ()", IF(ISNA(MATCH(K74, Criterios!$A$81:$A$120, 0)), "Categoría no válida", IF(AND(J74<>"", J74<>"", J74<>VLOOKUP(K74, Criterios!$A$81:$B$120, 2, FALSE)), "División no coincide con Categoría", ""))), IF(OR(L74="", L74=""), "[Aviso] Género no capturado ()", IF(ISNA(MATCH(L74, Criterios!$B$123:$B$127, 0)), "Género no válido", "")), IF(OR(N74="", N74=""), "[Aviso] Temporada no capturada ()", IF(ISNA(MATCH(N74, Criterios!$C$123:$C$128, 0)), "Temporada no válida", "")), IF(OR(O74="", O74=""), "[Aviso] Ciclo de vida no capturado ()", IF(ISNA(MATCH(O74, Criterios!$D$123:$D$124, 0)), "Ciclo de vida no válido", "")))) | AD74: 5 | AE74: MUESTRAS REFLO (1); REFLO ALMACEN (3) | AF74: 4 | AG74: Nuevo – NetSuite con existencia | AH74: Género no indicado en NetSuite; Composición: poliéster reciclado (validar % en etiqueta); Físico total NetSuite 5 ≠ suma por ubicación 4 | Revisión 29/09/2026: Marca REFLO fuera de lista Criterios; Campos sin respaldo: L, N, O, Q, U; Auditoría NetSuite 30/09/2026: llenado desde NetSuite [Z] | Homologación G1522 06/10/2026: Validador Shopify: WB: precio con IVA no termina en 9 | AI74: No | AK74: G1522ProductosTodosloscamposSandboxResults894.xlsx: fila 48566 [X,Y]; G1522_Extraccion_Articulos_NetSuite_2026-09-30.xlsx: fila 37529 [Z] | AL74: 22.75
A75: 5056658703294 | B75: 79197 | C75: REFLO | D75: DESDAR | E75: DESDAR-XL | F75: XL | G75: XL | H75: REFLO | I75: Short 2 en 1 REFLO Desna Dark Forest | J75: Ropa | K75: Shorts | M75: REFLO | P75: Verde | S75: Poliéster reciclado | T75: Short 2 en 1 de golf REFLO modelo Desna en color Dark Forest, confeccionado con materiales reciclados. Estilo DESDAR. | V75: PZS | W75: 53101500 | X75: https://i.ibb.co/n6WVqBk/DESDAR.jpg | Y75: 22.75 | Z75: 1649 | AA75: =IF(AND(A75="", B75="", E75=""), "", IF(AB75="", "Válido", IF((LEN(AB75)-LEN(SUBSTITUTE(AB75,"; ","")))/2+1>(LEN(AB75)-LEN(SUBSTITUTE(AB75,"[Aviso]","")))/7, "Con Incidencias", "Válido"))) | AB75: =IF(AND(A75="", B75="", E75=""), "", TEXTJOIN("; ", TRUE, IF(OR(TRIM(A75&"")="", ISNUMBER(SEARCH("FALTA", A75))), "UPC faltante/inválido", ""), IF(AND(A75<>"", IFERROR(_xlfn.XMATCH(A75,$A$2:$A$653,0,1)<>_xlfn.XMATCH(A75,$A$2:$A$653,0,-1),FALSE)), "Código de barras duplicado", ""), IF(AND(E75<>"", COUNTIF($E$2:$E$653, E75)>1), "SKU duplicado", ""), IF(OR(J75="", J75=""), "[Aviso] División no capturada ()", IF(ISNA(MATCH(J75, Criterios!$A$123:$A$126, 0)), "División no válida", "")), IF(OR(K75="", K75=""), "[Aviso] Categoría no capturada ()", IF(ISNA(MATCH(K75, Criterios!$A$81:$A$120, 0)), "Categoría no válida", IF(AND(J75<>"", J75<>"", J75<>VLOOKUP(K75, Criterios!$A$81:$B$120, 2, FALSE)), "División no coincide con Categoría", ""))), IF(OR(L75="", L75=""), "[Aviso] Género no capturado ()", IF(ISNA(MATCH(L75, Criterios!$B$123:$B$127, 0)), "Género no válido", "")), IF(OR(N75="", N75=""), "[Aviso] Temporada no capturada ()", IF(ISNA(MATCH(N75, Criterios!$C$123:$C$128, 0)), "Temporada no válida", "")), IF(OR(O75="", O75=""), "[Aviso] Ciclo de vida no capturado ()", IF(ISNA(MATCH(O75, Criterios!$D$123:$D$124, 0)), "Ciclo de vida no válido", "")))) | AD75: 5 | AE75: REFLO ALMACEN (3) | AF75: 5 | AG75: Nuevo – NetSuite con existencia | AH75: Género no indicado en NetSuite; Composición: poliéster reciclado (validar % en etiqueta); Físico total NetSuite 5 ≠ suma por ubicación 3 | Revisión 29/09/2026: Marca REFLO fuera de lista Criterios; Campos sin respaldo: L, N, O, Q, U; Auditoría NetSuite 30/09/2026: llenado desde NetSuite [Z] | Homologación G1522 06/10/2026: Validador Shopify: WB: precio con IVA no termina en 9 | AI75: No | AK75: G1522ProductosTodosloscamposSandboxResults894.xlsx: fila 48567 [X,Y]; G1522_Extraccion_Articulos_NetSuite_2026-09-30.xlsx: fila 37530 [Z] | AL75: 22.75
A76: 5056658703300 | B76: 79198 | C76: REFLO | D76: DESDAR | E76: DESDAR-2XL | F76: XXL | G76: XXL | H76: REFLO | I76: Short 2 en 1 REFLO Desna Dark Forest | J76: Ropa | K76: Shorts | M76: REFLO | P76: Verde | S76: Poliéster reciclado | T76: Short 2 en 1 de golf REFLO modelo Desna en color Dark Forest, confeccionado con materiales reciclados. Estilo DESDAR. | V76: PZS | W76: 53101500 | X76: https://i.ibb.co/n6WVqBk/DESDAR.jpg | Y76: 22.75 | Z76: 1649 | AA76: =IF(AND(A76="", B76="", E76=""), "", IF(AB76="", "Válido", IF((LEN(AB76)-LEN(SUBSTITUTE(AB76,"; ","")))/2+1>(LEN(AB76)-LEN(SUBSTITUTE(AB76,"[Aviso]","")))/7, "Con Incidencias", "Válido"))) | AB76: =IF(AND(A76="", B76="", E76=""), "", TEXTJOIN("; ", TRUE, IF(OR(TRIM(A76&"")="", ISNUMBER(SEARCH("FALTA", A76))), "UPC faltante/inválido", ""), IF(AND(A76<>"", IFERROR(_xlfn.XMATCH(A76,$A$2:$A$653,0,1)<>_xlfn.XMATCH(A76,$A$2:$A$653,0,-1),FALSE)), "Código de barras duplicado", ""), IF(AND(E76<>"", COUNTIF($E$2:$E$653, E76)>1), "SKU duplicado", ""), IF(OR(J76="", J76=""), "[Aviso] División no capturada ()", IF(ISNA(MATCH(J76, Criterios!$A$123:$A$126, 0)), "División no válida", "")), IF(OR(K76="", K76=""), "[Aviso] Categoría no capturada ()", IF(ISNA(MATCH(K76, Criterios!$A$81:$A$120, 0)), "Categoría no válida", IF(AND(J76<>"", J76<>"", J76<>VLOOKUP(K76, Criterios!$A$81:$B$120, 2, FALSE)), "División no coincide con Categoría", ""))), IF(OR(L76="", L76=""), "[Aviso] Género no capturado ()", IF(ISNA(MATCH(L76, Criterios!$B$123:$B$127, 0)), "Género no válido", "")), IF(OR(N76="", N76=""), "[Aviso] Temporada no capturada ()", IF(ISNA(MATCH(N76, Criterios!$C$123:$C$128, 0)), "Temporada no válida", "")), IF(OR(O76="", O76=""), "[Aviso] Ciclo de vida no capturado ()", IF(ISNA(MATCH(O76, Criterios!$D$123:$D$124, 0)), "Ciclo de vida no válido", "")))) | AD76: 3 | AE76: REFLO ALMACEN (2) | AF76: 3 | AG76: Nuevo – NetSuite con existencia | AH76: Género no indicado en NetSuite; Composición: poliéster reciclado (validar % en etiqueta); Físico total NetSuite 3 ≠ suma por ubicación 2 | Revisión 29/09/2026: Marca REFLO fuera de lista Criterios; Campos sin respaldo: L, N, O, Q, U; Auditoría NetSuite 30/09/2026: llenado desde NetSuite [Z] | Homologación G1522 06/10/2026: Validador Shopify: WB: precio con IVA no termina en 9 | AI76: No | AK76: G1522ProductosTodosloscamposSandboxResults894.xlsx: fila 48568 [X,Y]; G1522_Extraccion_Articulos_NetSuite_2026-09-30.xlsx: fila 37531 [Z] | AL76: 22.75
A77: 5056658703171 | B77: 79199 | C77: REFLO | D77: DESMED | E77: DESMED-M | F77: M | G77: M | H77: REFLO | I77: Short 2 en 1 REFLO Desna Medieval Blue | J77: Ropa | K77: Shorts | M77: REFLO | P77: Azul | S77: Poliéster reciclado | T77: Short 2 en 1 de golf REFLO modelo Desna en color Medieval Blue, confeccionado con materiales reciclados. Estilo DESMED. | V77: PZS | W77: 53101500 | X77: https://i.ibb.co/1Xj3ztp/DESMED.jpg | Y77: 22.75 | Z77: 1649 | AA77: =IF(AND(A77="", B77="", E77=""), "", IF(AB77="", "Válido", IF((LEN(AB77)-LEN(SUBSTITUTE(AB77,"; ","")))/2+1>(LEN(AB77)-LEN(SUBSTITUTE(AB77,"[Aviso]","")))/7, "Con Incidencias", "Válido"))) | AB77: =IF(AND(A77="", B77="", E77=""), "", TEXTJOIN("; ", TRUE, IF(OR(TRIM(A77&"")="", ISNUMBER(SEARCH("FALTA", A77))), "UPC faltante/inválido", ""), IF(AND(A77<>"", IFERROR(_xlfn.XMATCH(A77,$A$2:$A$653,0,1)<>_xlfn.XMATCH(A77,$A$2:$A$653,0,-1),FALSE)), "Código de barras duplicado", ""), IF(AND(E77<>"", COUNTIF($E$2:$E$653, E77)>1), "SKU duplicado", ""), IF(OR(J77="", J77=""), "[Aviso] División no capturada ()", IF(ISNA(MATCH(J77, Criterios!$A$123:$A$126, 0)), "División no válida", "")), IF(OR(K77="", K77=""), "[Aviso] Categoría no capturada ()", IF(ISNA(MATCH(K77, Criterios!$A$81:$A$120, 0)), "Categoría no válida", IF(AND(J77<>"", J77<>"", J77<>VLOOKUP(K77, Criterios!$A$81:$B$120, 2, FALSE)), "División no coincide con Categoría", ""))), IF(OR(L77="", L77=""), "[Aviso] Género no capturado ()", IF(ISNA(MATCH(L77, Criterios!$B$123:$B$127, 0)), "Género no válido", "")), IF(OR(N77="", N77=""), "[Aviso] Temporada no capturada ()", IF(ISNA(MATCH(N77, Criterios!$C$123:$C$128, 0)), "Temporada no válida", "")), IF(OR(O77="", O77=""), "[Aviso] Ciclo de vida no capturado ()", IF(ISNA(MATCH(O77, Criterios!$D$123:$D$124, 0)), "Ciclo de vida no válido", "")))) | AD77: 4 | AE77: REFLO ALMACEN (3) | AF77: 5 | AG77: Nuevo – NetSuite con existencia | AH77: Género no indicado en NetSuite; Composición: poliéster reciclado (validar % en etiqueta); Físico total NetSuite 4 ≠ suma por ubicación 2 | Revisión 29/09/2026: Marca REFLO fuera de lista Criterios; Campos sin respaldo: L, N, O, Q, U; Auditoría NetSuite 30/09/2026: llenado desde NetSuite [Z] | Homologación G1522 06/10/2026: Validador Shopify: WB: precio con IVA no termina en 9 | AI77: Sí | AJ77: CONSIGNA REFLO (-1) | AK77: G1522ProductosTodosloscamposSandboxResults894.xlsx: fila 48570 [X,Y]; G1522_Extraccion_Articulos_NetSuite_2026-09-30.xlsx: fila 37532 [Z] | AL77: 22.75
A78: 5056658703188 | B78: 79200 | C78: REFLO | D78: DESMED | E78: DESMED-L | F78: L | G78: L | H78: REFLO | I78: Short 2 en 1 REFLO Desna Medieval Blue | J78: Ropa | K78: Shorts | M78: REFLO | P78: Azul | S78: Poliéster reciclado | T78: Short 2 en 1 de golf REFLO modelo Desna en color Medieval Blue, confeccionado con materiales reciclados. Estilo DESMED. | V78: PZS | W78: 53101500 | X78: https://i.ibb.co/1Xj3ztp/DESMED.jpg | Y78: 22.75 | Z78: 1649 | AA78: =IF(AND(A78="", B78="", E78=""), "", IF(AB78="", "Válido", IF((LEN(AB78)-LEN(SUBSTITUTE(AB78,"; ","")))/2+1>(LEN(AB78)-LEN(SUBSTITUTE(AB78,"[Aviso]","")))/7, "Con Incidencias", "Válido"))) | AB78: =IF(AND(A78="", B78="", E78=""), "", TEXTJOIN("; ", TRUE, IF(OR(TRIM(A78&"")="", ISNUMBER(SEARCH("FALTA", A78))), "UPC faltante/inválido", ""), IF(AND(A78<>"", IFERROR(_xlfn.XMATCH(A78,$A$2:$A$653,0,1)<>_xlfn.XMATCH(A78,$A$2:$A$653,0,-1),FALSE)), "Código de barras duplicado", ""), IF(AND(E78<>"", COUNTIF($E$2:$E$653, E78)>1), "SKU duplicado", ""), IF(OR(J78="", J78=""), "[Aviso] División no capturada ()", IF(ISNA(MATCH(J78, Criterios!$A$123:$A$126, 0)), "División no válida", "")), IF(OR(K78="", K78=""), "[Aviso] Categoría no capturada ()", IF(ISNA(MATCH(K78, Criterios!$A$81:$A$120, 0)), "Categoría no válida", IF(AND(J78<>"", J78<>"", J78<>VLOOKUP(K78, Criterios!$A$81:$B$120, 2, FALSE)), "División no coincide con Categoría", ""))), IF(OR(L78="", L78=""), "[Aviso] Género no capturado ()", IF(ISNA(MATCH(L78, Criterios!$B$123:$B$127, 0)), "Género no válido", "")), IF(OR(N78="", N78=""), "[Aviso] Temporada no capturada ()", IF(ISNA(MATCH(N78, Criterios!$C$123:$C$128, 0)), "Temporada no válida", "")), IF(OR(O78="", O78=""), "[Aviso] Ciclo de vida no capturado ()", IF(ISNA(MATCH(O78, Criterios!$D$123:$D$124, 0)), "Ciclo de vida no válido", "")))) | AD78: 7 | AE78: MUESTRAS REFLO (1); REFLO ALMACEN (4) | AF78: 7 | AG78: Nuevo – NetSuite con existencia | AH78: Género no indicado en NetSuite; Composición: poliéster reciclado (validar % en etiqueta); Físico total NetSuite 7 ≠ suma por ubicación 4 | Revisión 29/09/2026: Marca REFLO fuera de lista Criterios; Campos sin respaldo: L, N, O, Q, U; Auditoría NetSuite 30/09/2026: llenado desde NetSuite [Z] | Homologación G1522 06/10/2026: Validador Shopify: WB: precio con IVA no termina en 9 | AI78: Sí | AJ78: CONSIGNA REFLO (-1) | AK78: G1522ProductosTodosloscamposSandboxResults894.xlsx: fila 48571 [X,Y]; G1522_Extraccion_Articulos_NetSuite_2026-09-30.xlsx: fila 37533 [Z] | AL78: 22.75
A79: 5056658703195 | B79: 79201 | C79: REFLO | D79: DESMED | E79: DESMED-XL | F79: XL | G79: XL | H79: REFLO | I79: Short 2 en 1 REFLO Desna Medieval Blue | J79: Ropa | K79: Shorts | M79: REFLO | P79: Azul | S79: Poliéster reciclado | T79: Short 2 en 1 de golf REFLO modelo Desna en color Medieval Blue, confeccionado con materiales reciclados. Estilo DESMED. | V79: PZS | W79: 53101500 | X79: https://i.ibb.co/1Xj3ztp/DESMED.jpg | Y79: 22.75 | Z79: 1649 | AA79: =IF(AND(A79="", B79="", E79=""), "", IF(AB79="", "Válido", IF((LEN(AB79)-LEN(SUBSTITUTE(AB79,"; ","")))/2+1>(LEN(AB79)-LEN(SUBSTITUTE(AB79,"[Aviso]","")))/7, "Con Incidencias", "Válido"))) | AB79: =IF(AND(A79="", B79="", E79=""), "", TEXTJOIN("; ", TRUE, IF(OR(TRIM(A79&"")="", ISNUMBER(SEARCH("FALTA", A79))), "UPC faltante/inválido", ""), IF(AND(A79<>"", IFERROR(_xlfn.XMATCH(A79,$A$2:$A$653,0,1)<>_xlfn.XMATCH(A79,$A$2:$A$653,0,-1),FALSE)), "Código de barras duplicado", ""), IF(AND(E79<>"", COUNTIF($E$2:$E$653, E79)>1), "SKU duplicado", ""), IF(OR(J79="", J79=""), "[Aviso] División no capturada ()", IF(ISNA(MATCH(J79, Criterios!$A$123:$A$126, 0)), "División no válida", "")), IF(OR(K79="", K79=""), "[Aviso] Categoría no capturada ()", IF(ISNA(MATCH(K79, Criterios!$A$81:$A$120, 0)), "Categoría no válida", IF(AND(J79<>"", J79<>"", J79<>VLOOKUP(K79, Criterios!$A$81:$B$120, 2, FALSE)), "División no coincide con Categoría", ""))), IF(OR(L79="", L79=""), "[Aviso] Género no capturado ()", IF(ISNA(MATCH(L79, Criterios!$B$123:$B$127, 0)), "Género no válido", "")), IF(OR(N79="", N79=""), "[Aviso] Temporada no capturada ()", IF(ISNA(MATCH(N79, Criterios!$C$123:$C$128, 0)), "Temporada no válida", "")), IF(OR(O79="", O79=""), "[Aviso] Ciclo de vida no capturado ()", IF(ISNA(MATCH(O79, Criterios!$D$123:$D$124, 0)), "Ciclo de vida no válido", "")))) | AD79: 7 | AE79: REFLO ALMACEN (5) | AF79: 8 | AG79: Nuevo – NetSuite con existencia | AH79: Género no indicado en NetSuite; Composición: poliéster reciclado (validar % en etiqueta); Físico total NetSuite 7 ≠ suma por ubicación 4 | Revisión 29/09/2026: Marca REFLO fuera de lista Criterios; Campos sin respaldo: L, N, O, Q, U; Auditoría NetSuite 30/09/2026: llenado desde NetSuite [Z] | Homologación G1522 06/10/2026: Validador Shopify: WB: precio con IVA no termina en 9 | AI79: Sí | AJ79: CONSIGNA REFLO (-1) | AK79: G1522ProductosTodosloscamposSandboxResults894.xlsx: fila 48572 [X,Y]; G1522_Extraccion_Articulos_NetSuite_2026-09-30.xlsx: fila 37534 [Z] | AL79: 22.75
A80: 5056658703201 | B80: 79202 | C80: REFLO | D80: DESMED | E80: DESMED-2XL | F80: XXL | G80: XXL | H80: REFLO | I80: Short 2 en 1 REFLO Desna Medieval Blue | J80: Ropa | K80: Shorts | M80: REFLO | P80: Azul | S80: Poliéster reciclado | T80: Short 2 en 1 de golf REFLO modelo Desna en color Medieval Blue, confeccionado con materiales reciclados. Estilo DESMED. | V80: PZS | W80: 53101500 | X80: https://i.ibb.co/1Xj3ztp/DESMED.jpg | Y80: 22.75 | Z80: 1649 | AA80: =IF(AND(A80="", B80="", E80=""), "", IF(AB80="", "Válido", IF((LEN(AB80)-LEN(SUBSTITUTE(AB80,"; ","")))/2+1>(LEN(AB80)-LEN(SUBSTITUTE(AB80,"[Aviso]","")))/7, "Con Incidencias", "Válido"))) | AB80: =IF(AND(A80="", B80="", E80=""), "", TEXTJOIN("; ", TRUE, IF(OR(TRIM(A80&"")="", ISNUMBER(SEARCH("FALTA", A80))), "UPC faltante/inválido", ""), IF(AND(A80<>"", IFERROR(_xlfn.XMATCH(A80,$A$2:$A$653,0,1)<>_xlfn.XMATCH(A80,$A$2:$A$653,0,-1),FALSE)), "Código de barras duplicado", ""), IF(AND(E80<>"", COUNTIF($E$2:$E$653, E80)>1), "SKU duplicado", ""), IF(OR(J80="", J80=""), "[Aviso] División no capturada ()", IF(ISNA(MATCH(J80, Criterios!$A$123:$A$126, 0)), "División no válida", "")), IF(OR(K80="", K80=""), "[Aviso] Categoría no capturada ()", IF(ISNA(MATCH(K80, Criterios!$A$81:$A$120, 0)), "Categoría no válida", IF(AND(J80<>"", J80<>"", J80<>VLOOKUP(K80, Criterios!$A$81:$B$120, 2, FALSE)), "División no coincide con Categoría", ""))), IF(OR(L80="", L80=""), "[Aviso] Género no capturado ()", IF(ISNA(MATCH(L80, Criterios!$B$123:$B$127, 0)), "Género no válido", "")), IF(OR(N80="", N80=""), "[Aviso] Temporada no capturada ()", IF(ISNA(MATCH(N80, Criterios!$C$123:$C$128, 0)), "Temporada no válida", "")), IF(OR(O80="", O80=""), "[Aviso] Ciclo de vida no capturado ()", IF(ISNA(MATCH(O80, Criterios!$D$123:$D$124, 0)), "Ciclo de vida no válido", "")))) | AD80: 3 | AE80: REFLO ALMACEN (3) | AF80: 4 | AG80: Nuevo – NetSuite con existencia | AH80: Género no indicado en NetSuite; Composición: poliéster reciclado (validar % en etiqueta); Físico total NetSuite 3 ≠ suma por ubicación 2 | Revisión 29/09/2026: Marca REFLO fuera de lista Criterios; Campos sin respaldo: L, N, O, Q, U; Auditoría NetSuite 30/09/2026: llenado desde NetSuite [Z] | Homologación G1522 06/10/2026: Validador Shopify: WB: precio con IVA no termina en 9 | AI80: Sí | AJ80: CONSIGNA REFLO (-1) | AK80: G1522ProductosTodosloscamposSandboxResults894.xlsx: fila 48573 [X,Y]; G1522_Extraccion_Articulos_NetSuite_2026-09-30.xlsx: fila 37535 [Z] | AL80: 22.75
A81: 5056658703225 | B81: 79203 | C81: REFLO | D81: DESQUA | E81: DESQUA-M | F81: M | G81: M | H81: REFLO | I81: Short 2 en 1 REFLO Desna Quarry | J81: Ropa | K81: Shorts | M81: REFLO | P81: Gris | S81: Poliéster reciclado | T81: Short 2 en 1 de golf REFLO modelo Desna en color Quarry, confeccionado con materiales reciclados. Estilo DESQUA. | V81: PZS | W81: 53101500 | X81: https://i.ibb.co/8PGzYhY/DESQUA.jpg | Y81: 22.75 | Z81: 1649 | AA81: =IF(AND(A81="", B81="", E81=""), "", IF(AB81="", "Válido", IF((LEN(AB81)-LEN(SUBSTITUTE(AB81,"; ","")))/2+1>(LEN(AB81)-LEN(SUBSTITUTE(AB81,"[Aviso]","")))/7, "Con Incidencias", "Válido"))) | AB81: =IF(AND(A81="", B81="", E81=""), "", TEXTJOIN("; ", TRUE, IF(OR(TRIM(A81&"")="", ISNUMBER(SEARCH("FALTA", A81))), "UPC faltante/inválido", ""), IF(AND(A81<>"", IFERROR(_xlfn.XMATCH(A81,$A$2:$A$653,0,1)<>_xlfn.XMATCH(A81,$A$2:$A$653,0,-1),FALSE)), "Código de barras duplicado", ""), IF(AND(E81<>"", COUNTIF($E$2:$E$653, E81)>1), "SKU duplicado", ""), IF(OR(J81="", J81=""), "[Aviso] División no capturada ()", IF(ISNA(MATCH(J81, Criterios!$A$123:$A$126, 0)), "División no válida", "")), IF(OR(K81="", K81=""), "[Aviso] Categoría no capturada ()", IF(ISNA(MATCH(K81, Criterios!$A$81:$A$120, 0)), "Categoría no válida", IF(AND(J81<>"", J81<>"", J81<>VLOOKUP(K81, Criterios!$A$81:$B$120, 2, FALSE)), "División no coincide con Categoría", ""))), IF(OR(L81="", L81=""), "[Aviso] Género no capturado ()", IF(ISNA(MATCH(L81, Criterios!$B$123:$B$127, 0)), "Género no válido", "")), IF(OR(N81="", N81=""), "[Aviso] Temporada no capturada ()", IF(ISNA(MATCH(N81, Criterios!$C$123:$C$128, 0)), "Temporada no válida", "")), IF(OR(O81="", O81=""), "[Aviso] Ciclo de vida no capturado ()", IF(ISNA(MATCH(O81, Criterios!$D$123:$D$124, 0)), "Ciclo de vida no válido", "")))) | AD81: 8 | AE81: CONSIGNA REFLO (1); REFLO ALMACEN (3) | AF81: 8 | AG81: Nuevo – NetSuite con existencia | AH81: Género no indicado en NetSuite; Composición: poliéster reciclado (validar % en etiqueta); Físico total NetSuite 8 ≠ suma por ubicación 4 | Revisión 29/09/2026: Marca REFLO fuera de lista Criterios; Campos sin respaldo: L, N, O, Q, U; Auditoría NetSuite 30/09/2026: llenado desde NetSuite [Z] | Homologación G1522 06/10/2026: Validador Shopify: WB: precio con IVA no termina en 9 | AI81: No | AK81: G1522ProductosTodosloscamposSandboxResults894.xlsx: fila 48575 [X,Y]; G1522_Extraccion_Articulos_NetSuite_2026-09-30.xlsx: fila 37536 [Z] | AL81: 22.75
A82: 5056658703232 | B82: 79204 | C82: REFLO | D82: DESQUA | E82: DESQUA-L | F82: L | G82: L | H82: REFLO | I82: Short 2 en 1 REFLO Desna Quarry | J82: Ropa | K82: Shorts | M82: REFLO | P82: Gris | S82: Poliéster reciclado | T82: Short 2 en 1 de golf REFLO modelo Desna en color Quarry, confeccionado con materiales reciclados. Estilo DESQUA. | V82: PZS | W82: 53101500 | X82: https://i.ibb.co/8PGzYhY/DESQUA.jpg | Y82: 22.75 | Z82: 1649 | AA82: =IF(AND(A82="", B82="", E82=""), "", IF(AB82="", "Válido", IF((LEN(AB82)-LEN(SUBSTITUTE(AB82,"; ","")))/2+1>(LEN(AB82)-LEN(SUBSTITUTE(AB82,"[Aviso]","")))/7, "Con Incidencias", "Válido"))) | AB82: =IF(AND(A82="", B82="", E82=""), "", TEXTJOIN("; ", TRUE, IF(OR(TRIM(A82&"")="", ISNUMBER(SEARCH("FALTA", A82))), "UPC faltante/inválido", ""), IF(AND(A82<>"", IFERROR(_xlfn.XMATCH(A82,$A$2:$A$653,0,1)<>_xlfn.XMATCH(A82,$A$2:$A$653,0,-1),FALSE)), "Código de barras duplicado", ""), IF(AND(E82<>"", COUNTIF($E$2:$E$653, E82)>1), "SKU duplicado", ""), IF(OR(J82="", J82=""), "[Aviso] División no capturada ()", IF(ISNA(MATCH(J82, Criterios!$A$123:$A$126, 0)), "División no válida", "")), IF(OR(K82="", K82=""), "[Aviso] Categoría no capturada ()", IF(ISNA(MATCH(K82, Criterios!$A$81:$A$120, 0)), "Categoría no válida", IF(AND(J82<>"", J82<>"", J82<>VLOOKUP(K82, Criterios!$A$81:$B$120, 2, FALSE)), "División no coincide con Categoría", ""))), IF(OR(L82="", L82=""), "[Aviso] Género no capturado ()", IF(ISNA(MATCH(L82, Criterios!$B$123:$B$127, 0)), "Género no válido", "")), IF(OR(N82="", N82=""), "[Aviso] Temporada no capturada ()", IF(ISNA(MATCH(N82, Criterios!$C$123:$C$128, 0)), "Temporada no válida", "")), IF(OR(O82="", O82=""), "[Aviso] Ciclo de vida no capturado ()", IF(ISNA(MATCH(O82, Criterios!$D$123:$D$124, 0)), "Ciclo de vida no válido", "")))) | AD82: 7 | AE82: REFLO ALMACEN (3); MUESTRAS REFLO (1) | AF82: 6 | AG82: Nuevo – NetSuite con existencia | AH82: Género no indicado en NetSuite; Composición: poliéster reciclado (validar % en etiqueta); Físico total NetSuite 7 ≠ suma por ubicación 4 | Revisión 29/09/2026: Marca REFLO fuera de lista Criterios; Campos sin respaldo: L, N, O, Q, U; Auditoría NetSuite 30/09/2026: llenado desde NetSuite [Z] | Homologación G1522 06/10/2026: Validador Shopify: WB: precio con IVA no termina en 9 | AI82: No | AK82: G1522ProductosTodosloscamposSandboxResults894.xlsx: fila 48576 [X,Y]; G1522_Extraccion_Articulos_NetSuite_2026-09-30.xlsx: fila 37537 [Z] | AL82: 22.75
A83: 5056658703249 | B83: 79205 | C83: REFLO | D83: DESQUA | E83: DESQUA-XL | F83: XL | G83: XL | H83: REFLO | I83: Short 2 en 1 REFLO Desna Quarry | J83: Ropa | K83: Shorts | M83: REFLO | P83: Gris | S83: Poliéster reciclado | T83: Short 2 en 1 de golf REFLO modelo Desna en color Quarry, confeccionado con materiales reciclados. Estilo DESQUA. | V83: PZS | W83: 53101500 | X83: https://i.ibb.co/8PGzYhY/DESQUA.jpg | Y83: 22.75 | Z83: 1649 | AA83: =IF(AND(A83="", B83="", E83=""), "", IF(AB83="", "Válido", IF((LEN(AB83)-LEN(SUBSTITUTE(AB83,"; ","")))/2+1>(LEN(AB83)-LEN(SUBSTITUTE(AB83,"[Aviso]","")))/7, "Con Incidencias", "Válido"))) | AB83: =IF(AND(A83="", B83="", E83=""), "", TEXTJOIN("; ", TRUE, IF(OR(TRIM(A83&"")="", ISNUMBER(SEARCH("FALTA", A83))), "UPC faltante/inválido", ""), IF(AND(A83<>"", IFERROR(_xlfn.XMATCH(A83,$A$2:$A$653,0,1)<>_xlfn.XMATCH(A83,$A$2:$A$653,0,-1),FALSE)), "Código de barras duplicado", ""), IF(AND(E83<>"", COUNTIF($E$2:$E$653, E83)>1), "SKU duplicado", ""), IF(OR(J83="", J83=""), "[Aviso] División no capturada ()", IF(ISNA(MATCH(J83, Criterios!$A$123:$A$126, 0)), "División no válida", "")), IF(OR(K83="", K83=""), "[Aviso] Categoría no capturada ()", IF(ISNA(MATCH(K83, Criterios!$A$81:$A$120, 0)), "Categoría no válida", IF(AND(J83<>"", J83<>"", J83<>VLOOKUP(K83, Criterios!$A$81:$B$120, 2, FALSE)), "División no coincide con Categoría", ""))), IF(OR(L83="", L83=""), "[Aviso] Género no capturado ()", IF(ISNA(MATCH(L83, Criterios!$B$123:$B$127, 0)), "Género no válido", "")), IF(OR(N83="", N83=""), "[Aviso] Temporada no capturada ()", IF(ISNA(MATCH(N83, Criterios!$C$123:$C$128, 0)), "Temporada no válida", "")), IF(OR(O83="", O83=""), "[Aviso] Ciclo de vida no capturado ()", IF(ISNA(MATCH(O83, Criterios!$D$123:$D$124, 0)), "Ciclo de vida no válido", "")))) | AD83: 8 | AE83: CONSIGNA REFLO (1); REFLO ALMACEN (3) | AF83: 8 | AG83: Nuevo – NetSuite con existencia | AH83: Género no indicado en NetSuite; Composición: poliéster reciclado (validar % en etiqueta); Físico total NetSuite 8 ≠ suma por ubicación 4 | Revisión 29/09/2026: Marca REFLO fuera de lista Criterios; Campos sin respaldo: L, N, O, Q, U; Auditoría NetSuite 30/09/2026: llenado desde NetSuite [Z] | Homologación G1522 06/10/2026: Validador Shopify: WB: precio con IVA no termina en 9 | AI83: No | AK83: G1522ProductosTodosloscamposSandboxResults894.xlsx: fila 48577 [X,Y]; G1522_Extraccion_Articulos_NetSuite_2026-09-30.xlsx: fila 37538 [Z] | AL83: 22.75
A84: 5056658703256 | B84: 79206 | C84: REFLO | D84: DESQUA | E84: DESQUA-2XL | F84: XXL | G84: XXL | H84: REFLO | I84: Short 2 en 1 REFLO Desna Quarry | J84: Ropa | K84: Shorts | M84: REFLO | P84: Gris | S84: Poliéster reciclado | T84: Short 2 en 1 de golf REFLO modelo Desna en color Quarry, confeccionado con materiales reciclados. Estilo DESQUA. | V84: PZS | W84: 53101500 | X84: https://i.ibb.co/8PGzYhY/DESQUA.jpg | Y84: 22.75 | Z84: 1649 | AA84: =IF(AND(A84="", B84="", E84=""), "", IF(AB84="", "Válido", IF((LEN(AB84)-LEN(SUBSTITUTE(AB84,"; ","")))/2+1>(LEN(AB84)-LEN(SUBSTITUTE(AB84,"[Aviso]","")))/7, "Con Incidencias", "Válido"))) | AB84: =IF(AND(A84="", B84="", E84=""), "", TEXTJOIN("; ", TRUE, IF(OR(TRIM(A84&"")="", ISNUMBER(SEARCH("FALTA", A84))), "UPC faltante/inválido", ""), IF(AND(A84<>"", IFERROR(_xlfn.XMATCH(A84,$A$2:$A$653,0,1)<>_xlfn.XMATCH(A84,$A$2:$A$653,0,-1),FALSE)), "Código de barras duplicado", ""), IF(AND(E84<>"", COUNTIF($E$2:$E$653, E84)>1), "SKU duplicado", ""), IF(OR(J84="", J84=""), "[Aviso] División no capturada ()", IF(ISNA(MATCH(J84, Criterios!$A$123:$A$126, 0)), "División no válida", "")), IF(OR(K84="", K84=""), "[Aviso] Categoría no capturada ()", IF(ISNA(MATCH(K84, Criterios!$A$81:$A$120, 0)), "Categoría no válida", IF(AND(J84<>"", J84<>"", J84<>VLOOKUP(K84, Criterios!$A$81:$B$120, 2, FALSE)), "División no coincide con Categoría", ""))), IF(OR(L84="", L84=""), "[Aviso] Género no capturado ()", IF(ISNA(MATCH(L84, Criterios!$B$123:$B$127, 0)), "Género no válido", "")), IF(OR(N84="", N84=""), "[Aviso] Temporada no capturada ()", IF(ISNA(MATCH(N84, Criterios!$C$123:$C$128, 0)), "Temporada no válida", "")), IF(OR(O84="", O84=""), "[Aviso] Ciclo de vida no capturado ()", IF(ISNA(MATCH(O84, Criterios!$D$123:$D$124, 0)), "Ciclo de vida no válido", "")))) | AD84: 3 | AE84: REFLO ALMACEN (2) | AF84: 3 | AG84: Nuevo – NetSuite con existencia | AH84: Género no indicado en NetSuite; Composición: poliéster reciclado (validar % en etiqueta); Físico total NetSuite 3 ≠ suma por ubicación 2 | Revisión 29/09/2026: Marca REFLO fuera de lista Criterios; Campos sin respaldo: L, N, O, Q, U; Auditoría NetSuite 30/09/2026: llenado desde NetSuite [Z] | Homologación G1522 06/10/2026: Validador Shopify: WB: precio con IVA no termina en 9 | AI84: No | AK84: G1522ProductosTodosloscamposSandboxResults894.xlsx: fila 48578 [X,Y]; G1522_Extraccion_Articulos_NetSuite_2026-09-30.xlsx: fila 37539 [Z] | AL84: 22.75
A85: 5056658701719 | B85: 79088 | C85: REFLO | D85: HUDBLA | E85: HUDBLA-M | F85: M | G85: M | H85: REFLO | I85: Playera REFLO Hudson 2.0 Black | J85: Ropa | K85: Playeras | M85: REFLO | P85: Negro | S85: Poliéster reciclado | T85: Playera de golf REFLO modelo Hudson 2.0 en color Black, confeccionado con materiales reciclados. Estilo HUDBLA. | V85: PZS | W85: 53101600 | X85: https://i.ibb.co/x7G2myf/HUDBLA.jpg | Y85: 16.9 | Z85: 1249 | AA85: =IF(AND(A85="", B85="", E85=""), "", IF(AB85="", "Válido", IF((LEN(AB85)-LEN(SUBSTITUTE(AB85,"; ","")))/2+1>(LEN(AB85)-LEN(SUBSTITUTE(AB85,"[Aviso]","")))/7, "Con Incidencias", "Válido"))) | AB85: =IF(AND(A85="", B85="", E85=""), "", TEXTJOIN("; ", TRUE, IF(OR(TRIM(A85&"")="", ISNUMBER(SEARCH("FALTA", A85))), "UPC faltante/inválido", ""), IF(AND(A85<>"", IFERROR(_xlfn.XMATCH(A85,$A$2:$A$653,0,1)<>_xlfn.XMATCH(A85,$A$2:$A$653,0,-1),FALSE)), "Código de barras duplicado", ""), IF(AND(E85<>"", COUNTIF($E$2:$E$653, E85)>1), "SKU duplicado", ""), IF(OR(J85="", J85=""), "[Aviso] División no capturada ()", IF(ISNA(MATCH(J85, Criterios!$A$123:$A$126, 0)), "División no válida", "")), IF(OR(K85="", K85=""), "[Aviso] Categoría no capturada ()", IF(ISNA(MATCH(K85, Criterios!$A$81:$A$120, 0)), "Categoría no válida", IF(AND(J85<>"", J85<>"", J85<>VLOOKUP(K85, Criterios!$A$81:$B$120, 2, FALSE)), "División no coincide con Categoría", ""))), IF(OR(L85="", L85=""), "[Aviso] Género no capturado ()", IF(ISNA(MATCH(L85, Criterios!$B$123:$B$127, 0)), "Género no válido", "")), IF(OR(N85="", N85=""), "[Aviso] Temporada no capturada ()", IF(ISNA(MATCH(N85, Criterios!$C$123:$C$128, 0)), "Temporada no válida", "")), IF(OR(O85="", O85=""), "[Aviso] Ciclo de vida no capturado ()", IF(ISNA(MATCH(O85, Criterios!$D$123:$D$124, 0)), "Ciclo de vida no válido", "")))) | AD85: 3 | AE85: CONSIGNA REFLO (1); REFLO ALMACEN (1) | AF85: 3 | AG85: Nuevo – NetSuite con existencia | AH85: Género no indicado en NetSuite; Composición: poliéster reciclado (validar % en etiqueta); Físico total NetSuite 3 ≠ suma por ubicación 2 | Revisión 29/09/2026: Marca REFLO fuera de lista Criterios; Campos sin respaldo: L, N, O, Q, U; Auditoría NetSuite 30/09/2026: llenado desde NetSuite [Z] | Homologación G1522 06/10/2026: Validación G1522: [Aviso] Precio de compra posiblemente en USD · Validador Shopify: WB: precio con IVA no termina en 9 | AI85: No | AK85: G1522ProductosTodosloscamposSandboxResults894.xlsx: fila 49238 [X,Y]; G1522_Extraccion_Articulos_NetSuite_2026-09-30.xlsx: fila 37472 [Z] | AL85: 16.9
A86: 5056658701726 | B86: 79089 | C86: REFLO | D86: HUDBLA | E86: HUDBLA-L | F86: L | G86: L | H86: REFLO | I86: Playera REFLO Hudson 2.0 Black | J86: Ropa | K86: Playeras | M86: REFLO | P86: Negro | S86: Poliéster reciclado | T86: Playera de golf REFLO modelo Hudson 2.0 en color Black, confeccionado con materiales reciclados. Estilo HUDBLA. | V86: PZS | W86: 53101600 | X86: https://i.ibb.co/x7G2myf/HUDBLA.jpg | Y86: 16.9 | Z86: 1249 | AA86: =IF(AND(A86="", B86="", E86=""), "", IF(AB86="", "Válido", IF((LEN(AB86)-LEN(SUBSTITUTE(AB86,"; ","")))/2+1>(LEN(AB86)-LEN(SUBSTITUTE(AB86,"[Aviso]","")))/7, "Con Incidencias", "Válido"))) | AB86: =IF(AND(A86="", B86="", E86=""), "", TEXTJOIN("; ", TRUE, IF(OR(TRIM(A86&"")="", ISNUMBER(SEARCH("FALTA", A86))), "UPC faltante/inválido", ""), IF(AND(A86<>"", IFERROR(_xlfn.XMATCH(A86,$A$2:$A$653,0,1)<>_xlfn.XMATCH(A86,$A$2:$A$653,0,-1),FALSE)), "Código de barras duplicado", ""), IF(AND(E86<>"", COUNTIF($E$2:$E$653, E86)>1), "SKU duplicado", ""), IF(OR(J86="", J86=""), "[Aviso] División no capturada ()", IF(ISNA(MATCH(J86, Criterios!$A$123:$A$126, 0)), "División no válida", "")), IF(OR(K86="", K86=""), "[Aviso] Categoría no capturada ()", IF(ISNA(MATCH(K86, Criterios!$A$81:$A$120, 0)), "Categoría no válida", IF(AND(J86<>"", J86<>"", J86<>VLOOKUP(K86, Criterios!$A$81:$B$120, 2, FALSE)), "División no coincide con Categoría", ""))), IF(OR(L86="", L86=""), "[Aviso] Género no capturado ()", IF(ISNA(MATCH(L86, Criterios!$B$123:$B$127, 0)), "Género no válido", "")), IF(OR(N86="", N86=""), "[Aviso] Temporada no capturada ()", IF(ISNA(MATCH(N86, Criterios!$C$123:$C$128, 0)), "Temporada no válida", "")), IF(OR(O86="", O86=""), "[Aviso] Ciclo de vida no capturado ()", IF(ISNA(MATCH(O86, Criterios!$D$123:$D$124, 0)), "Ciclo de vida no válido", "")))) | AD86: 1 | AE86: MUESTRAS REFLO (1) | AF86: 0 | AG86: Nuevo – NetSuite con existencia | AH86: Género no indicado en NetSuite; Composición: poliéster reciclado (validar % en etiqueta) | Revisión 29/09/2026: Marca REFLO fuera de lista Criterios; Campos sin respaldo: L, N, O, Q, U; Auditoría NetSuite 30/09/2026: llenado desde NetSuite [Z] | Homologación G1522 06/10/2026: Validación G1522: [Aviso] Precio de compra posiblemente en USD · Validador Shopify: WB: precio con IVA no termina en 9 | AI86: No | AK86: G1522ProductosTodosloscamposSandboxResults894.xlsx: fila 49239 [X,Y]; G1522_Extraccion_Articulos_NetSuite_2026-09-30.xlsx: fila 37473 [Z] | AL86: 16.9
